package com.tencent.mm.plugin.backup.bakpcmodel;

import com.tencent.mm.plugin.backup.c.c;
import com.tencent.mm.plugin.backup.e.b;
import com.tencent.mm.plugin.backup.e.w;
import com.tencent.mm.sdk.platformtools.v;

final class g$5
  implements Runnable
{
  g$5(g paramg, int paramInt) {}
  
  /* Error */
  public final void run()
  {
    // Byte code:
    //   0: invokestatic 32	com/tencent/mm/plugin/backup/d/h:reset	()V
    //   3: invokestatic 35	com/tencent/mm/plugin/backup/d/h:Hz	()V
    //   6: new 37	com/tencent/mm/plugin/backup/e/z
    //   9: dup
    //   10: invokespecial 38	com/tencent/mm/plugin/backup/e/z:<init>	()V
    //   13: astore 4
    //   15: aload 4
    //   17: invokevirtual 41	com/tencent/mm/plugin/backup/e/z:begin	()V
    //   20: new 43	java/util/HashMap
    //   23: dup
    //   24: invokespecial 44	java/util/HashMap:<init>	()V
    //   27: astore 5
    //   29: new 46	java/util/HashSet
    //   32: dup
    //   33: invokespecial 47	java/util/HashSet:<init>	()V
    //   36: astore 6
    //   38: aload_0
    //   39: getfield 18	com/tencent/mm/plugin/backup/bakpcmodel/g$5:coO	Lcom/tencent/mm/plugin/backup/bakpcmodel/g;
    //   42: getfield 51	com/tencent/mm/plugin/backup/bakpcmodel/g:coG	Ljava/util/List;
    //   45: invokeinterface 57 1 0
    //   50: astore 7
    //   52: iconst_0
    //   53: istore_1
    //   54: aload 7
    //   56: invokeinterface 63 1 0
    //   61: ifeq +174 -> 235
    //   64: aload 7
    //   66: invokeinterface 67 1 0
    //   71: checkcast 69	com/tencent/mm/plugin/backup/b/e
    //   74: astore_3
    //   75: new 71	java/lang/StringBuilder
    //   78: dup
    //   79: invokespecial 72	java/lang/StringBuilder:<init>	()V
    //   82: invokestatic 78	com/tencent/mm/plugin/backup/e/b:HY	()Ljava/lang/String;
    //   85: invokevirtual 82	java/lang/StringBuilder:append	(Ljava/lang/String;)Ljava/lang/StringBuilder;
    //   88: ldc 84
    //   90: invokevirtual 82	java/lang/StringBuilder:append	(Ljava/lang/String;)Ljava/lang/StringBuilder;
    //   93: aload_3
    //   94: getfield 88	com/tencent/mm/plugin/backup/b/e:ID	Ljava/lang/String;
    //   97: invokestatic 94	com/tencent/mm/plugin/backup/e/g:lD	(Ljava/lang/String;)Ljava/lang/String;
    //   100: invokevirtual 82	java/lang/StringBuilder:append	(Ljava/lang/String;)Ljava/lang/StringBuilder;
    //   103: aload_3
    //   104: getfield 88	com/tencent/mm/plugin/backup/b/e:ID	Ljava/lang/String;
    //   107: invokevirtual 82	java/lang/StringBuilder:append	(Ljava/lang/String;)Ljava/lang/StringBuilder;
    //   110: invokevirtual 97	java/lang/StringBuilder:toString	()Ljava/lang/String;
    //   113: astore_3
    //   114: aload_0
    //   115: getfield 18	com/tencent/mm/plugin/backup/bakpcmodel/g$5:coO	Lcom/tencent/mm/plugin/backup/bakpcmodel/g;
    //   118: aload_3
    //   119: aload 5
    //   121: aload 4
    //   123: aload 6
    //   125: invokevirtual 101	com/tencent/mm/plugin/backup/bakpcmodel/g:a	(Ljava/lang/String;Ljava/util/HashMap;Lcom/tencent/mm/plugin/backup/e/z;Ljava/util/HashSet;)I
    //   128: istore_2
    //   129: iload_2
    //   130: ifge +16 -> 146
    //   133: aload 4
    //   135: invokevirtual 104	com/tencent/mm/plugin/backup/e/z:end	()V
    //   138: ldc 106
    //   140: ldc 108
    //   142: invokestatic 114	com/tencent/mm/sdk/platformtools/v:w	(Ljava/lang/String;Ljava/lang/String;)V
    //   145: return
    //   146: iload_2
    //   147: iload_1
    //   148: iadd
    //   149: istore_1
    //   150: aload_0
    //   151: getfield 18	com/tencent/mm/plugin/backup/bakpcmodel/g$5:coO	Lcom/tencent/mm/plugin/backup/bakpcmodel/g;
    //   154: iload_1
    //   155: aload_0
    //   156: getfield 20	com/tencent/mm/plugin/backup/bakpcmodel/g$5:coQ	I
    //   159: invokevirtual 118	com/tencent/mm/plugin/backup/bakpcmodel/g:al	(II)V
    //   162: ldc 106
    //   164: ldc 120
    //   166: iconst_1
    //   167: anewarray 4	java/lang/Object
    //   170: dup
    //   171: iconst_0
    //   172: iload_1
    //   173: invokestatic 126	java/lang/Integer:valueOf	(I)Ljava/lang/Integer;
    //   176: aastore
    //   177: invokestatic 130	com/tencent/mm/sdk/platformtools/v:i	(Ljava/lang/String;Ljava/lang/String;[Ljava/lang/Object;)V
    //   180: goto -126 -> 54
    //   183: astore_3
    //   184: ldc 106
    //   186: new 71	java/lang/StringBuilder
    //   189: dup
    //   190: ldc -124
    //   192: invokespecial 135	java/lang/StringBuilder:<init>	(Ljava/lang/String;)V
    //   195: aload_3
    //   196: invokevirtual 136	java/lang/Exception:toString	()Ljava/lang/String;
    //   199: invokevirtual 82	java/lang/StringBuilder:append	(Ljava/lang/String;)Ljava/lang/StringBuilder;
    //   202: invokevirtual 97	java/lang/StringBuilder:toString	()Ljava/lang/String;
    //   205: invokestatic 139	com/tencent/mm/sdk/platformtools/v:e	(Ljava/lang/String;Ljava/lang/String;)V
    //   208: ldc 106
    //   210: new 71	java/lang/StringBuilder
    //   213: dup
    //   214: ldc -115
    //   216: invokespecial 135	java/lang/StringBuilder:<init>	(Ljava/lang/String;)V
    //   219: aload_3
    //   220: invokevirtual 136	java/lang/Exception:toString	()Ljava/lang/String;
    //   223: invokevirtual 82	java/lang/StringBuilder:append	(Ljava/lang/String;)Ljava/lang/StringBuilder;
    //   226: invokevirtual 97	java/lang/StringBuilder:toString	()Ljava/lang/String;
    //   229: invokestatic 144	com/tencent/mm/sdk/platformtools/v:f	(Ljava/lang/String;Ljava/lang/String;)V
    //   232: goto -178 -> 54
    //   235: aload 5
    //   237: invokestatic 150	com/tencent/mm/plugin/backup/h/a:b	(Ljava/util/HashMap;)V
    //   240: aload 4
    //   242: invokevirtual 104	com/tencent/mm/plugin/backup/e/z:end	()V
    //   245: aload_0
    //   246: getfield 18	com/tencent/mm/plugin/backup/bakpcmodel/g$5:coO	Lcom/tencent/mm/plugin/backup/bakpcmodel/g;
    //   249: bipush 100
    //   251: bipush 100
    //   253: invokevirtual 118	com/tencent/mm/plugin/backup/bakpcmodel/g:al	(II)V
    //   256: ldc 106
    //   258: ldc -104
    //   260: invokestatic 154	com/tencent/mm/sdk/platformtools/v:i	(Ljava/lang/String;Ljava/lang/String;)V
    //   263: invokestatic 157	com/tencent/mm/sdk/platformtools/v:appenderFlush	()V
    //   266: new 10	com/tencent/mm/plugin/backup/bakpcmodel/g$5$1
    //   269: dup
    //   270: aload_0
    //   271: invokespecial 160	com/tencent/mm/plugin/backup/bakpcmodel/g$5$1:<init>	(Lcom/tencent/mm/plugin/backup/bakpcmodel/g$5;)V
    //   274: invokestatic 163	com/tencent/mm/plugin/backup/e/b:e	(Ljava/lang/Runnable;)V
    //   277: return
    //   278: astore_3
    //   279: goto -95 -> 184
    // Local variable table:
    //   start	length	slot	name	signature
    //   0	282	0	this	5
    //   53	120	1	i	int
    //   128	21	2	j	int
    //   74	45	3	localObject	Object
    //   183	37	3	localException1	Exception
    //   278	1	3	localException2	Exception
    //   13	228	4	localz	com.tencent.mm.plugin.backup.e.z
    //   27	209	5	localHashMap	java.util.HashMap
    //   36	88	6	localHashSet	java.util.HashSet
    //   50	15	7	localIterator	java.util.Iterator
    // Exception table:
    //   from	to	target	type
    //   114	129	183	java/lang/Exception
    //   133	145	183	java/lang/Exception
    //   150	180	278	java/lang/Exception
  }
}

/* Location:
 * Qualified Name:     com.tencent.mm.plugin.backup.bakpcmodel.g.5
 * Java Class Version: 6 (50.0)
 * JD-Core Version:    0.7.1
 */