package com.tencent.mm.compatible.loader;

public final class b
{
  /* Error */
  public static String[] ax(android.content.Context paramContext)
  {
    // Byte code:
    //   0: invokestatic 14	com/tencent/mm/loader/stub/BaseBuildInfo:rb	()Z
    //   3: ifne +12 -> 15
    //   6: ldc 16
    //   8: ldc 18
    //   10: invokestatic 24	com/tencent/mm/sdk/platformtools/u:d	(Ljava/lang/String;Ljava/lang/String;)V
    //   13: aconst_null
    //   14: areturn
    //   15: iconst_3
    //   16: anewarray 26	java/lang/String
    //   19: astore_2
    //   20: aload_2
    //   21: iconst_0
    //   22: ldc 28
    //   24: aastore
    //   25: aload_2
    //   26: iconst_1
    //   27: ldc 30
    //   29: aastore
    //   30: aload_2
    //   31: iconst_2
    //   32: ldc 32
    //   34: aastore
    //   35: new 34	java/lang/StringBuilder
    //   38: dup
    //   39: invokespecial 38	java/lang/StringBuilder:<init>	()V
    //   42: getstatic 44	com/tencent/mm/loader/stub/a:bxa	Ljava/lang/String;
    //   45: invokevirtual 48	java/lang/StringBuilder:append	(Ljava/lang/String;)Ljava/lang/StringBuilder;
    //   48: ldc 50
    //   50: invokevirtual 48	java/lang/StringBuilder:append	(Ljava/lang/String;)Ljava/lang/StringBuilder;
    //   53: invokevirtual 54	java/lang/StringBuilder:toString	()Ljava/lang/String;
    //   56: astore_1
    //   57: new 56	java/io/FileInputStream
    //   60: dup
    //   61: aload_1
    //   62: invokespecial 59	java/io/FileInputStream:<init>	(Ljava/lang/String;)V
    //   65: astore_1
    //   66: aload_2
    //   67: iconst_1
    //   68: new 26	java/lang/String
    //   71: dup
    //   72: aload_1
    //   73: invokestatic 65	com/tencent/mm/loader/stub/b:c	(Ljava/io/InputStream;)[B
    //   76: invokespecial 68	java/lang/String:<init>	([B)V
    //   79: aastore
    //   80: aload_1
    //   81: invokevirtual 71	java/io/FileInputStream:close	()V
    //   84: aload_2
    //   85: iconst_0
    //   86: new 34	java/lang/StringBuilder
    //   89: dup
    //   90: invokespecial 38	java/lang/StringBuilder:<init>	()V
    //   93: aload_2
    //   94: iconst_1
    //   95: aaload
    //   96: iconst_0
    //   97: bipush 8
    //   99: invokevirtual 75	java/lang/String:substring	(II)Ljava/lang/String;
    //   102: invokevirtual 48	java/lang/StringBuilder:append	(Ljava/lang/String;)Ljava/lang/StringBuilder;
    //   105: ldc 77
    //   107: invokevirtual 48	java/lang/StringBuilder:append	(Ljava/lang/String;)Ljava/lang/StringBuilder;
    //   110: invokevirtual 54	java/lang/StringBuilder:toString	()Ljava/lang/String;
    //   113: aastore
    //   114: new 79	java/io/File
    //   117: dup
    //   118: new 34	java/lang/StringBuilder
    //   121: dup
    //   122: invokespecial 38	java/lang/StringBuilder:<init>	()V
    //   125: aload_0
    //   126: ldc 81
    //   128: iconst_0
    //   129: invokevirtual 87	android/content/Context:getDir	(Ljava/lang/String;I)Ljava/io/File;
    //   132: invokevirtual 90	java/io/File:getAbsolutePath	()Ljava/lang/String;
    //   135: invokevirtual 48	java/lang/StringBuilder:append	(Ljava/lang/String;)Ljava/lang/StringBuilder;
    //   138: ldc 92
    //   140: invokevirtual 48	java/lang/StringBuilder:append	(Ljava/lang/String;)Ljava/lang/StringBuilder;
    //   143: aload_2
    //   144: iconst_0
    //   145: aaload
    //   146: invokevirtual 48	java/lang/StringBuilder:append	(Ljava/lang/String;)Ljava/lang/StringBuilder;
    //   149: invokevirtual 54	java/lang/StringBuilder:toString	()Ljava/lang/String;
    //   152: invokespecial 93	java/io/File:<init>	(Ljava/lang/String;)V
    //   155: astore_0
    //   156: aload_0
    //   157: invokevirtual 96	java/io/File:exists	()Z
    //   160: ifeq +10 -> 170
    //   163: aload_0
    //   164: invokevirtual 99	java/io/File:isFile	()Z
    //   167: ifne +102 -> 269
    //   170: ldc 16
    //   172: ldc 101
    //   174: iconst_1
    //   175: anewarray 4	java/lang/Object
    //   178: dup
    //   179: iconst_0
    //   180: aload_2
    //   181: iconst_0
    //   182: aaload
    //   183: aastore
    //   184: invokestatic 105	com/tencent/mm/sdk/platformtools/u:e	(Ljava/lang/String;Ljava/lang/String;[Ljava/lang/Object;)V
    //   187: aconst_null
    //   188: areturn
    //   189: astore_1
    //   190: ldc 16
    //   192: aload_1
    //   193: ldc 107
    //   195: iconst_0
    //   196: anewarray 4	java/lang/Object
    //   199: invokestatic 111	com/tencent/mm/sdk/platformtools/u:printErrStackTrace	(Ljava/lang/String;Ljava/lang/Throwable;Ljava/lang/String;[Ljava/lang/Object;)V
    //   202: goto -118 -> 84
    //   205: astore_0
    //   206: aconst_null
    //   207: astore_0
    //   208: ldc 16
    //   210: ldc 113
    //   212: invokestatic 116	com/tencent/mm/sdk/platformtools/u:i	(Ljava/lang/String;Ljava/lang/String;)V
    //   215: aload_0
    //   216: ifnull -203 -> 13
    //   219: aload_0
    //   220: invokevirtual 71	java/io/FileInputStream:close	()V
    //   223: aconst_null
    //   224: areturn
    //   225: astore_0
    //   226: ldc 16
    //   228: aload_0
    //   229: ldc 107
    //   231: iconst_0
    //   232: anewarray 4	java/lang/Object
    //   235: invokestatic 111	com/tencent/mm/sdk/platformtools/u:printErrStackTrace	(Ljava/lang/String;Ljava/lang/Throwable;Ljava/lang/String;[Ljava/lang/Object;)V
    //   238: aconst_null
    //   239: areturn
    //   240: astore_0
    //   241: aconst_null
    //   242: astore_1
    //   243: aload_1
    //   244: ifnull +7 -> 251
    //   247: aload_1
    //   248: invokevirtual 71	java/io/FileInputStream:close	()V
    //   251: aload_0
    //   252: athrow
    //   253: astore_1
    //   254: ldc 16
    //   256: aload_1
    //   257: ldc 107
    //   259: iconst_0
    //   260: anewarray 4	java/lang/Object
    //   263: invokestatic 111	com/tencent/mm/sdk/platformtools/u:printErrStackTrace	(Ljava/lang/String;Ljava/lang/Throwable;Ljava/lang/String;[Ljava/lang/Object;)V
    //   266: goto -15 -> 251
    //   269: aload_0
    //   270: invokevirtual 90	java/io/File:getAbsolutePath	()Ljava/lang/String;
    //   273: invokestatic 120	com/tencent/mm/compatible/loader/b:db	(Ljava/lang/String;)Z
    //   276: ifne +20 -> 296
    //   279: ldc 16
    //   281: ldc 122
    //   283: iconst_1
    //   284: anewarray 4	java/lang/Object
    //   287: dup
    //   288: iconst_0
    //   289: aload_0
    //   290: aastore
    //   291: invokestatic 125	com/tencent/mm/sdk/platformtools/u:w	(Ljava/lang/String;Ljava/lang/String;[Ljava/lang/Object;)V
    //   294: aconst_null
    //   295: areturn
    //   296: aload_0
    //   297: invokevirtual 90	java/io/File:getAbsolutePath	()Ljava/lang/String;
    //   300: invokestatic 128	com/tencent/mm/compatible/loader/b:dc	(Ljava/lang/String;)Z
    //   303: ifeq -290 -> 13
    //   306: aload_2
    //   307: areturn
    //   308: astore_0
    //   309: goto -66 -> 243
    //   312: astore_2
    //   313: aload_0
    //   314: astore_1
    //   315: aload_2
    //   316: astore_0
    //   317: goto -74 -> 243
    //   320: astore_0
    //   321: aload_1
    //   322: astore_0
    //   323: goto -115 -> 208
    // Local variable table:
    //   start	length	slot	name	signature
    //   0	326	0	paramContext	android.content.Context
    //   56	25	1	localObject1	Object
    //   189	4	1	localException1	Exception
    //   242	6	1	localObject2	Object
    //   253	4	1	localException2	Exception
    //   314	8	1	localContext	android.content.Context
    //   19	288	2	arrayOfString	String[]
    //   312	4	2	localObject3	Object
    // Exception table:
    //   from	to	target	type
    //   80	84	189	java/lang/Exception
    //   57	66	205	java/lang/Exception
    //   219	223	225	java/lang/Exception
    //   57	66	240	finally
    //   247	251	253	java/lang/Exception
    //   66	80	308	finally
    //   208	215	312	finally
    //   66	80	320	java/lang/Exception
  }
  
  /* Error */
  public static boolean db(String paramString)
  {
    // Byte code:
    //   0: invokestatic 137	java/lang/System:currentTimeMillis	()J
    //   3: lstore_1
    //   4: sipush 8192
    //   7: newarray <illegal type>
    //   9: astore_3
    //   10: ldc 16
    //   12: ldc -117
    //   14: iconst_2
    //   15: anewarray 4	java/lang/Object
    //   18: dup
    //   19: iconst_0
    //   20: aload_0
    //   21: aastore
    //   22: dup
    //   23: iconst_1
    //   24: ldc -115
    //   26: aastore
    //   27: invokestatic 143	com/tencent/mm/sdk/platformtools/u:d	(Ljava/lang/String;Ljava/lang/String;[Ljava/lang/Object;)V
    //   30: new 145	java/util/jar/JarFile
    //   33: dup
    //   34: aload_0
    //   35: invokespecial 146	java/util/jar/JarFile:<init>	(Ljava/lang/String;)V
    //   38: astore 4
    //   40: aload 4
    //   42: invokevirtual 150	java/util/jar/JarFile:entries	()Ljava/util/Enumeration;
    //   45: astore 5
    //   47: aload 5
    //   49: invokeinterface 155 1 0
    //   54: ifeq +190 -> 244
    //   57: aload 5
    //   59: invokeinterface 159 1 0
    //   64: checkcast 161	java/util/jar/JarEntry
    //   67: astore 6
    //   69: aload 6
    //   71: invokevirtual 164	java/util/jar/JarEntry:getName	()Ljava/lang/String;
    //   74: astore 7
    //   76: ldc 16
    //   78: ldc -90
    //   80: iconst_1
    //   81: anewarray 4	java/lang/Object
    //   84: dup
    //   85: iconst_0
    //   86: aload 7
    //   88: aastore
    //   89: invokestatic 143	com/tencent/mm/sdk/platformtools/u:d	(Ljava/lang/String;Ljava/lang/String;[Ljava/lang/Object;)V
    //   92: aload 7
    //   94: ldc -88
    //   96: invokevirtual 171	java/lang/String:startsWith	(Ljava/lang/String;)Z
    //   99: ifne -52 -> 47
    //   102: new 173	java/io/BufferedInputStream
    //   105: dup
    //   106: aload 4
    //   108: aload 6
    //   110: invokevirtual 177	java/util/jar/JarFile:getInputStream	(Ljava/util/zip/ZipEntry;)Ljava/io/InputStream;
    //   113: invokespecial 180	java/io/BufferedInputStream:<init>	(Ljava/io/InputStream;)V
    //   116: astore 8
    //   118: aload 8
    //   120: aload_3
    //   121: iconst_0
    //   122: sipush 8192
    //   125: invokevirtual 186	java/io/InputStream:read	([BII)I
    //   128: iconst_m1
    //   129: if_icmpne -11 -> 118
    //   132: aload 8
    //   134: invokevirtual 187	java/io/InputStream:close	()V
    //   137: new 189	android/content/pm/Signature
    //   140: dup
    //   141: aload 6
    //   143: invokevirtual 193	java/util/jar/JarEntry:getCertificates	()[Ljava/security/cert/Certificate;
    //   146: iconst_0
    //   147: aaload
    //   148: invokevirtual 199	java/security/cert/Certificate:getEncoded	()[B
    //   151: invokespecial 200	android/content/pm/Signature:<init>	([B)V
    //   154: invokevirtual 203	android/content/pm/Signature:toByteArray	()[B
    //   157: invokestatic 209	com/tencent/mm/a/g:m	([B)Ljava/lang/String;
    //   160: astore 8
    //   162: ldc 16
    //   164: ldc -45
    //   166: iconst_3
    //   167: anewarray 4	java/lang/Object
    //   170: dup
    //   171: iconst_0
    //   172: aload 7
    //   174: aastore
    //   175: dup
    //   176: iconst_1
    //   177: aload 6
    //   179: invokevirtual 193	java/util/jar/JarEntry:getCertificates	()[Ljava/security/cert/Certificate;
    //   182: aastore
    //   183: dup
    //   184: iconst_2
    //   185: aload 8
    //   187: aastore
    //   188: invokestatic 143	com/tencent/mm/sdk/platformtools/u:d	(Ljava/lang/String;Ljava/lang/String;[Ljava/lang/Object;)V
    //   191: aload 8
    //   193: ldc -115
    //   195: invokevirtual 215	java/lang/String:equals	(Ljava/lang/Object;)Z
    //   198: ifne -151 -> 47
    //   201: ldc 16
    //   203: ldc -39
    //   205: iconst_2
    //   206: anewarray 4	java/lang/Object
    //   209: dup
    //   210: iconst_0
    //   211: aload 7
    //   213: aastore
    //   214: dup
    //   215: iconst_1
    //   216: aload 8
    //   218: aastore
    //   219: invokestatic 105	com/tencent/mm/sdk/platformtools/u:e	(Ljava/lang/String;Ljava/lang/String;[Ljava/lang/Object;)V
    //   222: aload 4
    //   224: invokevirtual 218	java/util/jar/JarFile:close	()V
    //   227: ldc 16
    //   229: ldc -36
    //   231: iconst_1
    //   232: anewarray 4	java/lang/Object
    //   235: dup
    //   236: iconst_0
    //   237: aload_0
    //   238: aastore
    //   239: invokestatic 222	com/tencent/mm/sdk/platformtools/u:i	(Ljava/lang/String;Ljava/lang/String;[Ljava/lang/Object;)V
    //   242: iconst_0
    //   243: ireturn
    //   244: ldc 16
    //   246: ldc -32
    //   248: iconst_1
    //   249: anewarray 4	java/lang/Object
    //   252: dup
    //   253: iconst_0
    //   254: invokestatic 137	java/lang/System:currentTimeMillis	()J
    //   257: lload_1
    //   258: lsub
    //   259: invokestatic 230	java/lang/Long:valueOf	(J)Ljava/lang/Long;
    //   262: aastore
    //   263: invokestatic 222	com/tencent/mm/sdk/platformtools/u:i	(Ljava/lang/String;Ljava/lang/String;[Ljava/lang/Object;)V
    //   266: aload 4
    //   268: invokevirtual 218	java/util/jar/JarFile:close	()V
    //   271: ldc 16
    //   273: ldc -36
    //   275: iconst_1
    //   276: anewarray 4	java/lang/Object
    //   279: dup
    //   280: iconst_0
    //   281: aload_0
    //   282: aastore
    //   283: invokestatic 222	com/tencent/mm/sdk/platformtools/u:i	(Ljava/lang/String;Ljava/lang/String;[Ljava/lang/Object;)V
    //   286: iconst_1
    //   287: ireturn
    //   288: astore 4
    //   290: aconst_null
    //   291: astore_3
    //   292: ldc 16
    //   294: ldc -24
    //   296: iconst_1
    //   297: anewarray 4	java/lang/Object
    //   300: dup
    //   301: iconst_0
    //   302: aload 4
    //   304: invokevirtual 235	java/lang/Throwable:getMessage	()Ljava/lang/String;
    //   307: aastore
    //   308: invokestatic 105	com/tencent/mm/sdk/platformtools/u:e	(Ljava/lang/String;Ljava/lang/String;[Ljava/lang/Object;)V
    //   311: aload_3
    //   312: invokevirtual 218	java/util/jar/JarFile:close	()V
    //   315: ldc 16
    //   317: ldc -36
    //   319: iconst_1
    //   320: anewarray 4	java/lang/Object
    //   323: dup
    //   324: iconst_0
    //   325: aload_0
    //   326: aastore
    //   327: invokestatic 222	com/tencent/mm/sdk/platformtools/u:i	(Ljava/lang/String;Ljava/lang/String;[Ljava/lang/Object;)V
    //   330: iconst_0
    //   331: ireturn
    //   332: astore_3
    //   333: aconst_null
    //   334: astore 4
    //   336: aload 4
    //   338: invokevirtual 218	java/util/jar/JarFile:close	()V
    //   341: ldc 16
    //   343: ldc -36
    //   345: iconst_1
    //   346: anewarray 4	java/lang/Object
    //   349: dup
    //   350: iconst_0
    //   351: aload_0
    //   352: aastore
    //   353: invokestatic 222	com/tencent/mm/sdk/platformtools/u:i	(Ljava/lang/String;Ljava/lang/String;[Ljava/lang/Object;)V
    //   356: aload_3
    //   357: athrow
    //   358: astore_0
    //   359: goto -3 -> 356
    //   362: astore_3
    //   363: goto -27 -> 336
    //   366: astore 5
    //   368: aload_3
    //   369: astore 4
    //   371: aload 5
    //   373: astore_3
    //   374: goto -38 -> 336
    //   377: astore_0
    //   378: goto -48 -> 330
    //   381: astore 5
    //   383: aload 4
    //   385: astore_3
    //   386: aload 5
    //   388: astore 4
    //   390: goto -98 -> 292
    //   393: astore_0
    //   394: goto -108 -> 286
    //   397: astore_0
    //   398: goto -156 -> 242
    // Local variable table:
    //   start	length	slot	name	signature
    //   0	401	0	paramString	String
    //   3	255	1	l	long
    //   9	303	3	arrayOfByte	byte[]
    //   332	25	3	localObject1	Object
    //   362	7	3	localObject2	Object
    //   373	13	3	localObject3	Object
    //   38	229	4	localJarFile	java.util.jar.JarFile
    //   288	15	4	localThrowable1	Throwable
    //   334	55	4	localObject4	Object
    //   45	13	5	localEnumeration	java.util.Enumeration
    //   366	6	5	localObject5	Object
    //   381	6	5	localThrowable2	Throwable
    //   67	111	6	localJarEntry	java.util.jar.JarEntry
    //   74	138	7	str	String
    //   116	101	8	localObject6	Object
    // Exception table:
    //   from	to	target	type
    //   30	40	288	java/lang/Throwable
    //   30	40	332	finally
    //   336	356	358	java/lang/Throwable
    //   40	47	362	finally
    //   47	118	362	finally
    //   118	222	362	finally
    //   244	266	362	finally
    //   292	311	366	finally
    //   311	330	377	java/lang/Throwable
    //   40	47	381	java/lang/Throwable
    //   47	118	381	java/lang/Throwable
    //   118	222	381	java/lang/Throwable
    //   244	266	381	java/lang/Throwable
    //   266	286	393	java/lang/Throwable
    //   222	242	397	java/lang/Throwable
  }
  
  /* Error */
  public static boolean dc(String paramString)
  {
    // Byte code:
    //   0: aconst_null
    //   1: astore 8
    //   3: aconst_null
    //   4: astore 7
    //   6: aconst_null
    //   7: astore 5
    //   9: aconst_null
    //   10: astore 9
    //   12: aconst_null
    //   13: astore 10
    //   15: iconst_0
    //   16: istore_2
    //   17: iconst_0
    //   18: istore_1
    //   19: new 239	java/util/zip/ZipFile
    //   22: dup
    //   23: aload_0
    //   24: invokespecial 240	java/util/zip/ZipFile:<init>	(Ljava/lang/String;)V
    //   27: astore 4
    //   29: aload 8
    //   31: astore 7
    //   33: aload 9
    //   35: astore 5
    //   37: aload 4
    //   39: astore 6
    //   41: aload 4
    //   43: ldc -14
    //   45: invokevirtual 246	java/util/zip/ZipFile:getEntry	(Ljava/lang/String;)Ljava/util/zip/ZipEntry;
    //   48: astore_0
    //   49: aload_0
    //   50: ifnull +298 -> 348
    //   53: aload 8
    //   55: astore 7
    //   57: aload 9
    //   59: astore 5
    //   61: aload 4
    //   63: astore 6
    //   65: new 248	java/util/Properties
    //   68: dup
    //   69: invokespecial 249	java/util/Properties:<init>	()V
    //   72: astore 10
    //   74: aload 8
    //   76: astore 7
    //   78: aload 9
    //   80: astore 5
    //   82: aload 4
    //   84: astore 6
    //   86: aload 4
    //   88: aload_0
    //   89: invokevirtual 250	java/util/zip/ZipFile:getInputStream	(Ljava/util/zip/ZipEntry;)Ljava/io/InputStream;
    //   92: astore_0
    //   93: aload_0
    //   94: astore 7
    //   96: aload_0
    //   97: astore 5
    //   99: aload 4
    //   101: astore 6
    //   103: aload 10
    //   105: aload_0
    //   106: invokevirtual 253	java/util/Properties:load	(Ljava/io/InputStream;)V
    //   109: aload_0
    //   110: astore 7
    //   112: aload_0
    //   113: astore 5
    //   115: aload 4
    //   117: astore 6
    //   119: aload 10
    //   121: ldc -1
    //   123: invokevirtual 259	java/util/Properties:getProperty	(Ljava/lang/String;)Ljava/lang/String;
    //   126: astore 8
    //   128: aload_0
    //   129: astore 7
    //   131: aload_0
    //   132: astore 5
    //   134: aload 4
    //   136: astore 6
    //   138: aload 10
    //   140: ldc_w 261
    //   143: invokevirtual 259	java/util/Properties:getProperty	(Ljava/lang/String;)Ljava/lang/String;
    //   146: astore 9
    //   148: aload 8
    //   150: ifnull +69 -> 219
    //   153: aload_0
    //   154: astore 7
    //   156: aload_0
    //   157: astore 5
    //   159: aload 4
    //   161: astore 6
    //   163: aload 8
    //   165: getstatic 264	com/tencent/mm/loader/stub/BaseBuildInfo:bwQ	Ljava/lang/String;
    //   168: invokevirtual 215	java/lang/String:equals	(Ljava/lang/Object;)Z
    //   171: ifeq +48 -> 219
    //   174: aload 9
    //   176: ifnull +43 -> 219
    //   179: aload_0
    //   180: astore 7
    //   182: aload_0
    //   183: astore 5
    //   185: aload 4
    //   187: astore 6
    //   189: aload 9
    //   191: getstatic 267	com/tencent/mm/loader/stub/BaseBuildInfo:btx	Ljava/lang/String;
    //   194: invokevirtual 215	java/lang/String:equals	(Ljava/lang/Object;)Z
    //   197: istore_3
    //   198: iload_3
    //   199: ifeq +20 -> 219
    //   202: iconst_1
    //   203: istore_1
    //   204: aload_0
    //   205: ifnull +7 -> 212
    //   208: aload_0
    //   209: invokevirtual 187	java/io/InputStream:close	()V
    //   212: aload 4
    //   214: invokevirtual 268	java/util/zip/ZipFile:close	()V
    //   217: iload_1
    //   218: ireturn
    //   219: aload_0
    //   220: astore 7
    //   222: aload_0
    //   223: astore 5
    //   225: aload 4
    //   227: astore 6
    //   229: ldc 16
    //   231: new 34	java/lang/StringBuilder
    //   234: dup
    //   235: ldc_w 270
    //   238: invokespecial 271	java/lang/StringBuilder:<init>	(Ljava/lang/String;)V
    //   241: aload 8
    //   243: invokevirtual 48	java/lang/StringBuilder:append	(Ljava/lang/String;)Ljava/lang/StringBuilder;
    //   246: ldc_w 273
    //   249: invokevirtual 48	java/lang/StringBuilder:append	(Ljava/lang/String;)Ljava/lang/StringBuilder;
    //   252: getstatic 264	com/tencent/mm/loader/stub/BaseBuildInfo:bwQ	Ljava/lang/String;
    //   255: invokevirtual 48	java/lang/StringBuilder:append	(Ljava/lang/String;)Ljava/lang/StringBuilder;
    //   258: ldc_w 275
    //   261: invokevirtual 48	java/lang/StringBuilder:append	(Ljava/lang/String;)Ljava/lang/StringBuilder;
    //   264: aload 9
    //   266: invokevirtual 48	java/lang/StringBuilder:append	(Ljava/lang/String;)Ljava/lang/StringBuilder;
    //   269: ldc_w 273
    //   272: invokevirtual 48	java/lang/StringBuilder:append	(Ljava/lang/String;)Ljava/lang/StringBuilder;
    //   275: getstatic 267	com/tencent/mm/loader/stub/BaseBuildInfo:btx	Ljava/lang/String;
    //   278: invokevirtual 48	java/lang/StringBuilder:append	(Ljava/lang/String;)Ljava/lang/StringBuilder;
    //   281: ldc_w 277
    //   284: invokevirtual 48	java/lang/StringBuilder:append	(Ljava/lang/String;)Ljava/lang/StringBuilder;
    //   287: invokevirtual 54	java/lang/StringBuilder:toString	()Ljava/lang/String;
    //   290: invokestatic 279	com/tencent/mm/sdk/platformtools/u:e	(Ljava/lang/String;Ljava/lang/String;)V
    //   293: goto -89 -> 204
    //   296: astore_0
    //   297: aload 7
    //   299: astore 5
    //   301: aload 4
    //   303: astore 6
    //   305: ldc 16
    //   307: ldc_w 281
    //   310: invokestatic 279	com/tencent/mm/sdk/platformtools/u:e	(Ljava/lang/String;Ljava/lang/String;)V
    //   313: aload 7
    //   315: ifnull +8 -> 323
    //   318: aload 7
    //   320: invokevirtual 187	java/io/InputStream:close	()V
    //   323: iload_2
    //   324: istore_1
    //   325: aload 4
    //   327: ifnull -110 -> 217
    //   330: aload 4
    //   332: invokevirtual 268	java/util/zip/ZipFile:close	()V
    //   335: iconst_0
    //   336: ireturn
    //   337: astore_0
    //   338: ldc 16
    //   340: ldc_w 283
    //   343: invokestatic 116	com/tencent/mm/sdk/platformtools/u:i	(Ljava/lang/String;Ljava/lang/String;)V
    //   346: iconst_0
    //   347: ireturn
    //   348: aload 8
    //   350: astore 7
    //   352: aload 9
    //   354: astore 5
    //   356: aload 4
    //   358: astore 6
    //   360: ldc 16
    //   362: ldc_w 285
    //   365: invokestatic 279	com/tencent/mm/sdk/platformtools/u:e	(Ljava/lang/String;Ljava/lang/String;)V
    //   368: aload 10
    //   370: astore_0
    //   371: goto -167 -> 204
    //   374: astore 5
    //   376: aload 4
    //   378: astore_0
    //   379: aconst_null
    //   380: astore 4
    //   382: ldc 16
    //   384: aload 5
    //   386: ldc_w 287
    //   389: iconst_1
    //   390: anewarray 4	java/lang/Object
    //   393: dup
    //   394: iconst_0
    //   395: aload 5
    //   397: invokevirtual 288	java/lang/Exception:getMessage	()Ljava/lang/String;
    //   400: aastore
    //   401: invokestatic 111	com/tencent/mm/sdk/platformtools/u:printErrStackTrace	(Ljava/lang/String;Ljava/lang/Throwable;Ljava/lang/String;[Ljava/lang/Object;)V
    //   404: aload 4
    //   406: ifnull +8 -> 414
    //   409: aload 4
    //   411: invokevirtual 187	java/io/InputStream:close	()V
    //   414: iload_2
    //   415: istore_1
    //   416: aload_0
    //   417: ifnull -200 -> 217
    //   420: aload_0
    //   421: invokevirtual 268	java/util/zip/ZipFile:close	()V
    //   424: iconst_0
    //   425: ireturn
    //   426: astore_0
    //   427: ldc 16
    //   429: ldc_w 283
    //   432: invokestatic 116	com/tencent/mm/sdk/platformtools/u:i	(Ljava/lang/String;Ljava/lang/String;)V
    //   435: iconst_0
    //   436: ireturn
    //   437: astore_0
    //   438: ldc 16
    //   440: ldc_w 290
    //   443: invokestatic 116	com/tencent/mm/sdk/platformtools/u:i	(Ljava/lang/String;Ljava/lang/String;)V
    //   446: goto -234 -> 212
    //   449: astore_0
    //   450: ldc 16
    //   452: ldc_w 283
    //   455: invokestatic 116	com/tencent/mm/sdk/platformtools/u:i	(Ljava/lang/String;Ljava/lang/String;)V
    //   458: iload_1
    //   459: ireturn
    //   460: astore_0
    //   461: ldc 16
    //   463: ldc_w 290
    //   466: invokestatic 116	com/tencent/mm/sdk/platformtools/u:i	(Ljava/lang/String;Ljava/lang/String;)V
    //   469: goto -146 -> 323
    //   472: astore 4
    //   474: ldc 16
    //   476: ldc_w 290
    //   479: invokestatic 116	com/tencent/mm/sdk/platformtools/u:i	(Ljava/lang/String;Ljava/lang/String;)V
    //   482: goto -68 -> 414
    //   485: astore_0
    //   486: aconst_null
    //   487: astore 6
    //   489: aload 5
    //   491: ifnull +8 -> 499
    //   494: aload 5
    //   496: invokevirtual 187	java/io/InputStream:close	()V
    //   499: aload 6
    //   501: ifnull +8 -> 509
    //   504: aload 6
    //   506: invokevirtual 268	java/util/zip/ZipFile:close	()V
    //   509: aload_0
    //   510: athrow
    //   511: astore 4
    //   513: ldc 16
    //   515: ldc_w 290
    //   518: invokestatic 116	com/tencent/mm/sdk/platformtools/u:i	(Ljava/lang/String;Ljava/lang/String;)V
    //   521: goto -22 -> 499
    //   524: astore 4
    //   526: ldc 16
    //   528: ldc_w 283
    //   531: invokestatic 116	com/tencent/mm/sdk/platformtools/u:i	(Ljava/lang/String;Ljava/lang/String;)V
    //   534: goto -25 -> 509
    //   537: astore_0
    //   538: goto -49 -> 489
    //   541: astore 5
    //   543: aload_0
    //   544: astore 6
    //   546: aload 5
    //   548: astore_0
    //   549: aload 4
    //   551: astore 5
    //   553: goto -64 -> 489
    //   556: astore 5
    //   558: aconst_null
    //   559: astore_0
    //   560: aconst_null
    //   561: astore 4
    //   563: goto -181 -> 382
    //   566: astore 5
    //   568: aload 4
    //   570: astore 6
    //   572: aload_0
    //   573: astore 4
    //   575: aload 6
    //   577: astore_0
    //   578: goto -196 -> 382
    //   581: astore_0
    //   582: aconst_null
    //   583: astore 4
    //   585: goto -288 -> 297
    // Local variable table:
    //   start	length	slot	name	signature
    //   0	588	0	paramString	String
    //   18	441	1	bool1	boolean
    //   16	399	2	bool2	boolean
    //   197	2	3	bool3	boolean
    //   27	383	4	localZipFile	java.util.zip.ZipFile
    //   472	1	4	localException1	Exception
    //   511	1	4	localException2	Exception
    //   524	26	4	localIOException	java.io.IOException
    //   561	23	4	str1	String
    //   7	348	5	localObject1	Object
    //   374	121	5	localException3	Exception
    //   541	6	5	localObject2	Object
    //   551	1	5	localObject3	Object
    //   556	1	5	localException4	Exception
    //   566	1	5	localException5	Exception
    //   39	537	6	localObject4	Object
    //   4	347	7	str2	String
    //   1	348	8	str3	String
    //   10	343	9	str4	String
    //   13	356	10	localProperties	java.util.Properties
    // Exception table:
    //   from	to	target	type
    //   41	49	296	java/io/IOException
    //   65	74	296	java/io/IOException
    //   86	93	296	java/io/IOException
    //   103	109	296	java/io/IOException
    //   119	128	296	java/io/IOException
    //   138	148	296	java/io/IOException
    //   163	174	296	java/io/IOException
    //   189	198	296	java/io/IOException
    //   229	293	296	java/io/IOException
    //   360	368	296	java/io/IOException
    //   330	335	337	java/io/IOException
    //   41	49	374	java/lang/Exception
    //   65	74	374	java/lang/Exception
    //   86	93	374	java/lang/Exception
    //   360	368	374	java/lang/Exception
    //   420	424	426	java/io/IOException
    //   208	212	437	java/lang/Exception
    //   212	217	449	java/io/IOException
    //   318	323	460	java/lang/Exception
    //   409	414	472	java/lang/Exception
    //   19	29	485	finally
    //   494	499	511	java/lang/Exception
    //   504	509	524	java/io/IOException
    //   41	49	537	finally
    //   65	74	537	finally
    //   86	93	537	finally
    //   103	109	537	finally
    //   119	128	537	finally
    //   138	148	537	finally
    //   163	174	537	finally
    //   189	198	537	finally
    //   229	293	537	finally
    //   305	313	537	finally
    //   360	368	537	finally
    //   382	404	541	finally
    //   19	29	556	java/lang/Exception
    //   103	109	566	java/lang/Exception
    //   119	128	566	java/lang/Exception
    //   138	148	566	java/lang/Exception
    //   163	174	566	java/lang/Exception
    //   189	198	566	java/lang/Exception
    //   229	293	566	java/lang/Exception
    //   19	29	581	java/io/IOException
  }
}

/* Location:
 * Qualified Name:     com.tencent.mm.compatible.loader.b
 * Java Class Version: 6 (50.0)
 * JD-Core Version:    0.7.1
 */