package com.tencent.smtt.sdk;

import android.os.Handler;
import android.os.Looper;

final class p
  extends Handler
{
  p(Looper paramLooper)
  {
    super(paramLooper);
  }
  
  /* Error */
  public final void handleMessage(android.os.Message paramMessage)
  {
    // Byte code:
    //   0: aload_1
    //   1: getfield 23	android/os/Message:what	I
    //   4: tableswitch	default:+28->32, 100:+29->33, 101:+37->41, 102:+3021->3025
    //   32: return
    //   33: iconst_1
    //   34: getstatic 29	com/tencent/smtt/sdk/o:jKA	Lcom/tencent/smtt/sdk/k;
    //   37: invokestatic 33	com/tencent/smtt/sdk/o:a	(ZLcom/tencent/smtt/sdk/k;)V
    //   40: return
    //   41: getstatic 37	com/tencent/smtt/sdk/o:jKy	Landroid/content/Context;
    //   44: invokestatic 43	com/tencent/smtt/sdk/n:en	(Landroid/content/Context;)Lcom/tencent/smtt/sdk/n;
    //   47: astore_1
    //   48: iconst_0
    //   49: getstatic 29	com/tencent/smtt/sdk/o:jKA	Lcom/tencent/smtt/sdk/k;
    //   52: invokestatic 33	com/tencent/smtt/sdk/o:a	(ZLcom/tencent/smtt/sdk/k;)V
    //   55: aload_1
    //   56: invokevirtual 47	com/tencent/smtt/sdk/n:aUA	()Z
    //   59: ifeq +2955 -> 3014
    //   62: getstatic 29	com/tencent/smtt/sdk/o:jKA	Lcom/tencent/smtt/sdk/k;
    //   65: astore 26
    //   67: aload 26
    //   69: getfield 52	com/tencent/smtt/sdk/k:mContext	Landroid/content/Context;
    //   72: invokestatic 43	com/tencent/smtt/sdk/n:en	(Landroid/content/Context;)Lcom/tencent/smtt/sdk/n;
    //   75: invokevirtual 56	com/tencent/smtt/sdk/n:getResponseCode	()I
    //   78: istore_2
    //   79: iload_2
    //   80: iconst_1
    //   81: if_icmpeq +8 -> 89
    //   84: iload_2
    //   85: iconst_2
    //   86: if_icmpne +25 -> 111
    //   89: iconst_1
    //   90: istore_2
    //   91: iload_2
    //   92: ifeq +137 -> 229
    //   95: aload 26
    //   97: iconst_1
    //   98: invokevirtual 60	com/tencent/smtt/sdk/k:gp	(Z)Z
    //   101: ifeq +15 -> 116
    //   104: aload 26
    //   106: iconst_0
    //   107: invokevirtual 64	com/tencent/smtt/sdk/k:go	(Z)V
    //   110: return
    //   111: iconst_0
    //   112: istore_2
    //   113: goto -22 -> 91
    //   116: aload 26
    //   118: iconst_1
    //   119: invokevirtual 67	com/tencent/smtt/sdk/k:gq	(Z)V
    //   122: aload 26
    //   124: aload 26
    //   126: getfield 52	com/tencent/smtt/sdk/k:mContext	Landroid/content/Context;
    //   129: invokestatic 43	com/tencent/smtt/sdk/n:en	(Landroid/content/Context;)Lcom/tencent/smtt/sdk/n;
    //   132: invokevirtual 71	com/tencent/smtt/sdk/n:Dz	()Ljava/lang/String;
    //   135: putfield 75	com/tencent/smtt/sdk/k:mDownloadUrl	Ljava/lang/String;
    //   138: ldc 77
    //   140: new 79	java/lang/StringBuilder
    //   143: dup
    //   144: ldc 81
    //   146: invokespecial 84	java/lang/StringBuilder:<init>	(Ljava/lang/String;)V
    //   149: aload 26
    //   151: getfield 75	com/tencent/smtt/sdk/k:mDownloadUrl	Ljava/lang/String;
    //   154: invokevirtual 88	java/lang/StringBuilder:append	(Ljava/lang/String;)Ljava/lang/StringBuilder;
    //   157: ldc 90
    //   159: invokevirtual 88	java/lang/StringBuilder:append	(Ljava/lang/String;)Ljava/lang/StringBuilder;
    //   162: aload 26
    //   164: getfield 93	com/tencent/smtt/sdk/k:jJW	Ljava/lang/String;
    //   167: invokevirtual 88	java/lang/StringBuilder:append	(Ljava/lang/String;)Ljava/lang/StringBuilder;
    //   170: ldc 95
    //   172: invokevirtual 88	java/lang/StringBuilder:append	(Ljava/lang/String;)Ljava/lang/StringBuilder;
    //   175: aload 26
    //   177: getfield 99	com/tencent/smtt/sdk/k:cRW	Z
    //   180: invokevirtual 102	java/lang/StringBuilder:append	(Z)Ljava/lang/StringBuilder;
    //   183: ldc 104
    //   185: invokevirtual 88	java/lang/StringBuilder:append	(Ljava/lang/String;)Ljava/lang/StringBuilder;
    //   188: aload 26
    //   190: getfield 108	com/tencent/smtt/sdk/k:jKd	Ljava/net/HttpURLConnection;
    //   193: invokevirtual 111	java/lang/StringBuilder:append	(Ljava/lang/Object;)Ljava/lang/StringBuilder;
    //   196: invokevirtual 114	java/lang/StringBuilder:toString	()Ljava/lang/String;
    //   199: invokestatic 120	com/tencent/smtt/a/u:i	(Ljava/lang/String;Ljava/lang/String;)V
    //   202: aload 26
    //   204: getfield 75	com/tencent/smtt/sdk/k:mDownloadUrl	Ljava/lang/String;
    //   207: ifnonnull +49 -> 256
    //   210: aload 26
    //   212: getfield 93	com/tencent/smtt/sdk/k:jJW	Ljava/lang/String;
    //   215: ifnonnull +41 -> 256
    //   218: invokestatic 126	com/tencent/smtt/sdk/QbSdk:aUc	()Lcom/tencent/smtt/sdk/y;
    //   221: bipush 110
    //   223: invokeinterface 132 2 0
    //   228: return
    //   229: new 134	java/io/File
    //   232: dup
    //   233: aload 26
    //   235: getfield 138	com/tencent/smtt/sdk/k:jJX	Ljava/io/File;
    //   238: ldc -116
    //   240: invokespecial 143	java/io/File:<init>	(Ljava/io/File;Ljava/lang/String;)V
    //   243: invokevirtual 146	java/io/File:exists	()Z
    //   246: ifeq -124 -> 122
    //   249: aload 26
    //   251: iconst_0
    //   252: invokevirtual 64	com/tencent/smtt/sdk/k:go	(Z)V
    //   255: return
    //   256: aload 26
    //   258: getfield 108	com/tencent/smtt/sdk/k:jKd	Ljava/net/HttpURLConnection;
    //   261: ifnull +22 -> 283
    //   264: aload 26
    //   266: getfield 99	com/tencent/smtt/sdk/k:cRW	Z
    //   269: ifne +14 -> 283
    //   272: invokestatic 126	com/tencent/smtt/sdk/QbSdk:aUc	()Lcom/tencent/smtt/sdk/y;
    //   275: bipush 110
    //   277: invokeinterface 132 2 0
    //   282: return
    //   283: aload 26
    //   285: invokevirtual 150	com/tencent/smtt/sdk/k:aUi	()V
    //   288: ldc 77
    //   290: ldc -104
    //   292: iconst_1
    //   293: invokestatic 156	com/tencent/smtt/a/u:j	(Ljava/lang/String;Ljava/lang/String;Z)V
    //   296: aload 26
    //   298: getfield 52	com/tencent/smtt/sdk/k:mContext	Landroid/content/Context;
    //   301: invokestatic 43	com/tencent/smtt/sdk/n:en	(Landroid/content/Context;)Lcom/tencent/smtt/sdk/n;
    //   304: invokevirtual 160	com/tencent/smtt/sdk/n:aUG	()J
    //   307: lstore 15
    //   309: aload 26
    //   311: getfield 163	com/tencent/smtt/sdk/k:bUD	I
    //   314: iconst_5
    //   315: if_icmpgt +104 -> 419
    //   318: aload 26
    //   320: getfield 166	com/tencent/smtt/sdk/k:jKc	I
    //   323: bipush 8
    //   325: if_icmpgt +94 -> 419
    //   328: invokestatic 171	java/lang/System:currentTimeMillis	()J
    //   331: lstore 11
    //   333: lload 11
    //   335: aload 26
    //   337: getfield 52	com/tencent/smtt/sdk/k:mContext	Landroid/content/Context;
    //   340: invokestatic 43	com/tencent/smtt/sdk/n:en	(Landroid/content/Context;)Lcom/tencent/smtt/sdk/n;
    //   343: invokevirtual 174	com/tencent/smtt/sdk/n:aUN	()J
    //   346: lsub
    //   347: ldc2_w 175
    //   350: lcmp
    //   351: ifle +518 -> 869
    //   354: ldc 77
    //   356: ldc -78
    //   358: invokestatic 120	com/tencent/smtt/a/u:i	(Ljava/lang/String;Ljava/lang/String;)V
    //   361: aload 26
    //   363: getfield 52	com/tencent/smtt/sdk/k:mContext	Landroid/content/Context;
    //   366: invokestatic 43	com/tencent/smtt/sdk/n:en	(Landroid/content/Context;)Lcom/tencent/smtt/sdk/n;
    //   369: lload 11
    //   371: invokestatic 184	java/lang/Long:valueOf	(J)Ljava/lang/Long;
    //   374: invokevirtual 187	com/tencent/smtt/sdk/n:i	(Ljava/lang/Long;)V
    //   377: aload 26
    //   379: getfield 52	com/tencent/smtt/sdk/k:mContext	Landroid/content/Context;
    //   382: invokestatic 43	com/tencent/smtt/sdk/n:en	(Landroid/content/Context;)Lcom/tencent/smtt/sdk/n;
    //   385: lconst_0
    //   386: invokestatic 184	java/lang/Long:valueOf	(J)Ljava/lang/Long;
    //   389: invokevirtual 189	com/tencent/smtt/sdk/n:j	(Ljava/lang/Long;)V
    //   392: aload 26
    //   394: getfield 52	com/tencent/smtt/sdk/k:mContext	Landroid/content/Context;
    //   397: invokestatic 43	com/tencent/smtt/sdk/n:en	(Landroid/content/Context;)Lcom/tencent/smtt/sdk/n;
    //   400: invokevirtual 192	com/tencent/smtt/sdk/n:commit	()V
    //   403: aload 26
    //   405: invokevirtual 195	com/tencent/smtt/sdk/k:aUp	()Z
    //   408: ifne +554 -> 962
    //   411: ldc 77
    //   413: ldc -59
    //   415: iconst_1
    //   416: invokestatic 156	com/tencent/smtt/a/u:j	(Ljava/lang/String;Ljava/lang/String;Z)V
    //   419: aload 26
    //   421: getfield 99	com/tencent/smtt/sdk/k:cRW	Z
    //   424: ifne +124 -> 548
    //   427: iconst_0
    //   428: istore 19
    //   430: aload 26
    //   432: getfield 200	com/tencent/smtt/sdk/k:mFinished	Z
    //   435: ifeq +54 -> 489
    //   438: iload_2
    //   439: ifeq +2423 -> 2862
    //   442: aload 26
    //   444: iconst_0
    //   445: invokevirtual 60	com/tencent/smtt/sdk/k:gp	(Z)Z
    //   448: istore 19
    //   450: aload 26
    //   452: getfield 204	com/tencent/smtt/sdk/k:jKf	Lcom/tencent/smtt/sdk/i;
    //   455: astore_1
    //   456: iload 19
    //   458: ifeq +2473 -> 2931
    //   461: iconst_1
    //   462: istore_2
    //   463: aload_1
    //   464: iload_2
    //   465: putfield 209	com/tencent/smtt/sdk/i:jJF	I
    //   468: iload 19
    //   470: ifeq +2466 -> 2936
    //   473: aload 26
    //   475: iconst_1
    //   476: invokevirtual 64	com/tencent/smtt/sdk/k:go	(Z)V
    //   479: aload 26
    //   481: getfield 204	com/tencent/smtt/sdk/k:jKf	Lcom/tencent/smtt/sdk/i;
    //   484: ldc -45
    //   486: putfield 214	com/tencent/smtt/sdk/i:jJN	Ljava/lang/String;
    //   489: aload 26
    //   491: getfield 52	com/tencent/smtt/sdk/k:mContext	Landroid/content/Context;
    //   494: invokestatic 43	com/tencent/smtt/sdk/n:en	(Landroid/content/Context;)Lcom/tencent/smtt/sdk/n;
    //   497: astore_1
    //   498: iload 19
    //   500: ifeq +2445 -> 2945
    //   503: aload_1
    //   504: aload_1
    //   505: invokevirtual 217	com/tencent/smtt/sdk/n:aUJ	()I
    //   508: iconst_1
    //   509: iadd
    //   510: invokestatic 222	java/lang/Integer:valueOf	(I)Ljava/lang/Integer;
    //   513: invokevirtual 226	com/tencent/smtt/sdk/n:k	(Ljava/lang/Integer;)V
    //   516: aload 26
    //   518: getfield 204	com/tencent/smtt/sdk/k:jKf	Lcom/tencent/smtt/sdk/i;
    //   521: bipush 100
    //   523: invokevirtual 229	com/tencent/smtt/sdk/i:setErrorCode	(I)V
    //   526: aload_1
    //   527: invokevirtual 192	com/tencent/smtt/sdk/n:commit	()V
    //   530: aload 26
    //   532: getfield 204	com/tencent/smtt/sdk/k:jKf	Lcom/tencent/smtt/sdk/i;
    //   535: astore_1
    //   536: iload 19
    //   538: ifeq +2442 -> 2980
    //   541: iconst_1
    //   542: istore_2
    //   543: aload_1
    //   544: iload_2
    //   545: putfield 232	com/tencent/smtt/sdk/i:jJI	I
    //   548: ldc 77
    //   550: ldc -22
    //   552: invokestatic 120	com/tencent/smtt/a/u:i	(Ljava/lang/String;Ljava/lang/String;)V
    //   555: aload 26
    //   557: getfield 108	com/tencent/smtt/sdk/k:jKd	Ljava/net/HttpURLConnection;
    //   560: ifnull +93 -> 653
    //   563: aload 26
    //   565: getfield 99	com/tencent/smtt/sdk/k:cRW	Z
    //   568: ifne +22 -> 590
    //   571: aload 26
    //   573: getfield 204	com/tencent/smtt/sdk/k:jKf	Lcom/tencent/smtt/sdk/i;
    //   576: aload 26
    //   578: getfield 108	com/tencent/smtt/sdk/k:jKd	Ljava/net/HttpURLConnection;
    //   581: invokevirtual 240	java/net/HttpURLConnection:getURL	()Ljava/net/URL;
    //   584: invokestatic 243	com/tencent/smtt/sdk/k:a	(Ljava/net/URL;)Ljava/lang/String;
    //   587: putfield 246	com/tencent/smtt/sdk/i:jJB	Ljava/lang/String;
    //   590: aload 26
    //   592: getfield 108	com/tencent/smtt/sdk/k:jKd	Ljava/net/HttpURLConnection;
    //   595: invokevirtual 249	java/net/HttpURLConnection:disconnect	()V
    //   598: new 79	java/lang/StringBuilder
    //   601: dup
    //   602: invokespecial 251	java/lang/StringBuilder:<init>	()V
    //   605: aload 26
    //   607: getfield 52	com/tencent/smtt/sdk/k:mContext	Landroid/content/Context;
    //   610: invokestatic 43	com/tencent/smtt/sdk/n:en	(Landroid/content/Context;)Lcom/tencent/smtt/sdk/n;
    //   613: invokevirtual 254	com/tencent/smtt/sdk/n:aUz	()I
    //   616: invokevirtual 257	java/lang/StringBuilder:append	(I)Ljava/lang/StringBuilder;
    //   619: ldc_w 259
    //   622: invokevirtual 88	java/lang/StringBuilder:append	(Ljava/lang/String;)Ljava/lang/StringBuilder;
    //   625: invokevirtual 114	java/lang/StringBuilder:toString	()Ljava/lang/String;
    //   628: astore_1
    //   629: aload 26
    //   631: getfield 52	com/tencent/smtt/sdk/k:mContext	Landroid/content/Context;
    //   634: invokevirtual 265	android/content/Context:getContentResolver	()Landroid/content/ContentResolver;
    //   637: aload 26
    //   639: getfield 268	com/tencent/smtt/sdk/k:jKe	Ljava/lang/String;
    //   642: aload_1
    //   643: invokestatic 274	android/provider/Settings$System:putString	(Landroid/content/ContentResolver;Ljava/lang/String;Ljava/lang/String;)Z
    //   646: pop
    //   647: aload 26
    //   649: aconst_null
    //   650: putfield 108	com/tencent/smtt/sdk/k:jKd	Ljava/net/HttpURLConnection;
    //   653: aload 26
    //   655: getfield 204	com/tencent/smtt/sdk/k:jKf	Lcom/tencent/smtt/sdk/i;
    //   658: getfield 277	com/tencent/smtt/sdk/i:coy	I
    //   661: istore_3
    //   662: aload 26
    //   664: getfield 99	com/tencent/smtt/sdk/k:cRW	Z
    //   667: ifne +2342 -> 3009
    //   670: aload 26
    //   672: getfield 280	com/tencent/smtt/sdk/k:jKi	Z
    //   675: ifeq +2334 -> 3009
    //   678: aload 26
    //   680: getfield 204	com/tencent/smtt/sdk/k:jKf	Lcom/tencent/smtt/sdk/i;
    //   683: invokestatic 171	java/lang/System:currentTimeMillis	()J
    //   686: putfield 284	com/tencent/smtt/sdk/i:jJz	J
    //   689: aload 26
    //   691: getfield 52	com/tencent/smtt/sdk/k:mContext	Landroid/content/Context;
    //   694: invokestatic 290	com/tencent/smtt/a/b:eO	(Landroid/content/Context;)Ljava/lang/String;
    //   697: astore_1
    //   698: aload 26
    //   700: getfield 52	com/tencent/smtt/sdk/k:mContext	Landroid/content/Context;
    //   703: invokestatic 294	com/tencent/smtt/a/b:eP	(Landroid/content/Context;)I
    //   706: istore_2
    //   707: aload 26
    //   709: getfield 204	com/tencent/smtt/sdk/k:jKf	Lcom/tencent/smtt/sdk/i;
    //   712: aload_1
    //   713: putfield 297	com/tencent/smtt/sdk/i:jJG	Ljava/lang/String;
    //   716: aload 26
    //   718: getfield 204	com/tencent/smtt/sdk/k:jKf	Lcom/tencent/smtt/sdk/i;
    //   721: iload_2
    //   722: putfield 300	com/tencent/smtt/sdk/i:jJH	I
    //   725: iload_2
    //   726: aload 26
    //   728: getfield 303	com/tencent/smtt/sdk/k:jKh	I
    //   731: if_icmpne +15 -> 746
    //   734: aload_1
    //   735: aload 26
    //   737: getfield 306	com/tencent/smtt/sdk/k:jKg	Ljava/lang/String;
    //   740: invokevirtual 312	java/lang/String:equals	(Ljava/lang/Object;)Z
    //   743: ifne +12 -> 755
    //   746: aload 26
    //   748: getfield 204	com/tencent/smtt/sdk/k:jKf	Lcom/tencent/smtt/sdk/i;
    //   751: iconst_0
    //   752: putfield 315	com/tencent/smtt/sdk/i:jJL	I
    //   755: aload 26
    //   757: getfield 204	com/tencent/smtt/sdk/k:jKf	Lcom/tencent/smtt/sdk/i;
    //   760: getfield 277	com/tencent/smtt/sdk/i:coy	I
    //   763: ifeq +16 -> 779
    //   766: aload 26
    //   768: getfield 204	com/tencent/smtt/sdk/k:jKf	Lcom/tencent/smtt/sdk/i;
    //   771: getfield 277	com/tencent/smtt/sdk/i:coy	I
    //   774: bipush 107
    //   776: if_icmpne +66 -> 842
    //   779: aload 26
    //   781: getfield 204	com/tencent/smtt/sdk/k:jKf	Lcom/tencent/smtt/sdk/i;
    //   784: getfield 232	com/tencent/smtt/sdk/i:jJI	I
    //   787: ifne +55 -> 842
    //   790: aload 26
    //   792: getfield 52	com/tencent/smtt/sdk/k:mContext	Landroid/content/Context;
    //   795: ldc_w 317
    //   798: invokevirtual 321	android/content/Context:getSystemService	(Ljava/lang/String;)Ljava/lang/Object;
    //   801: checkcast 323	android/net/ConnectivityManager
    //   804: invokevirtual 327	android/net/ConnectivityManager:getActiveNetworkInfo	()Landroid/net/NetworkInfo;
    //   807: astore_1
    //   808: aload_1
    //   809: ifnull +2176 -> 2985
    //   812: aload_1
    //   813: invokevirtual 332	android/net/NetworkInfo:isConnected	()Z
    //   816: ifne +10 -> 826
    //   819: aload_1
    //   820: invokevirtual 335	android/net/NetworkInfo:isAvailable	()Z
    //   823: ifeq +2162 -> 2985
    //   826: iconst_1
    //   827: istore_2
    //   828: iload_2
    //   829: ifne +2161 -> 2990
    //   832: aload 26
    //   834: getfield 204	com/tencent/smtt/sdk/k:jKf	Lcom/tencent/smtt/sdk/i;
    //   837: bipush 101
    //   839: invokevirtual 229	com/tencent/smtt/sdk/i:setErrorCode	(I)V
    //   842: aload 26
    //   844: getfield 204	com/tencent/smtt/sdk/k:jKf	Lcom/tencent/smtt/sdk/i;
    //   847: getstatic 341	com/tencent/smtt/sdk/i$a:jJQ	Lcom/tencent/smtt/sdk/i$a;
    //   850: invokevirtual 344	com/tencent/smtt/sdk/i:a	(Lcom/tencent/smtt/sdk/i$a;)V
    //   853: iload_3
    //   854: bipush 100
    //   856: if_icmpeq -824 -> 32
    //   859: invokestatic 126	com/tencent/smtt/sdk/QbSdk:aUc	()Lcom/tencent/smtt/sdk/y;
    //   862: iload_3
    //   863: invokeinterface 132 2 0
    //   868: return
    //   869: aload 26
    //   871: getfield 52	com/tencent/smtt/sdk/k:mContext	Landroid/content/Context;
    //   874: invokestatic 43	com/tencent/smtt/sdk/n:en	(Landroid/content/Context;)Lcom/tencent/smtt/sdk/n;
    //   877: invokevirtual 347	com/tencent/smtt/sdk/n:aUO	()J
    //   880: lstore 5
    //   882: ldc 77
    //   884: new 79	java/lang/StringBuilder
    //   887: dup
    //   888: ldc_w 349
    //   891: invokespecial 84	java/lang/StringBuilder:<init>	(Ljava/lang/String;)V
    //   894: lload 5
    //   896: invokevirtual 352	java/lang/StringBuilder:append	(J)Ljava/lang/StringBuilder;
    //   899: invokevirtual 114	java/lang/StringBuilder:toString	()Ljava/lang/String;
    //   902: invokestatic 120	com/tencent/smtt/a/u:i	(Ljava/lang/String;Ljava/lang/String;)V
    //   905: lload 5
    //   907: lload 15
    //   909: lcmp
    //   910: iflt -507 -> 403
    //   913: ldc 77
    //   915: ldc_w 354
    //   918: iconst_1
    //   919: invokestatic 156	com/tencent/smtt/a/u:j	(Ljava/lang/String;Ljava/lang/String;Z)V
    //   922: goto -503 -> 419
    //   925: astore_1
    //   926: aload 26
    //   928: getfield 204	com/tencent/smtt/sdk/k:jKf	Lcom/tencent/smtt/sdk/i;
    //   931: aload_1
    //   932: invokevirtual 358	com/tencent/smtt/sdk/i:b	(Ljava/lang/Throwable;)V
    //   935: aload 26
    //   937: getfield 204	com/tencent/smtt/sdk/k:jKf	Lcom/tencent/smtt/sdk/i;
    //   940: bipush 107
    //   942: invokevirtual 229	com/tencent/smtt/sdk/i:setErrorCode	(I)V
    //   945: aload 26
    //   947: lconst_0
    //   948: invokevirtual 362	com/tencent/smtt/sdk/k:cZ	(J)V
    //   951: aload 26
    //   953: getfield 99	com/tencent/smtt/sdk/k:cRW	Z
    //   956: ifeq -647 -> 309
    //   959: goto -540 -> 419
    //   962: aload 26
    //   964: invokevirtual 365	com/tencent/smtt/sdk/k:aUm	()Z
    //   967: ifne -548 -> 419
    //   970: new 79	java/lang/StringBuilder
    //   973: dup
    //   974: invokespecial 251	java/lang/StringBuilder:<init>	()V
    //   977: aload 26
    //   979: getfield 52	com/tencent/smtt/sdk/k:mContext	Landroid/content/Context;
    //   982: invokestatic 43	com/tencent/smtt/sdk/n:en	(Landroid/content/Context;)Lcom/tencent/smtt/sdk/n;
    //   985: invokevirtual 254	com/tencent/smtt/sdk/n:aUz	()I
    //   988: invokevirtual 257	java/lang/StringBuilder:append	(I)Ljava/lang/StringBuilder;
    //   991: ldc_w 367
    //   994: invokevirtual 88	java/lang/StringBuilder:append	(Ljava/lang/String;)Ljava/lang/StringBuilder;
    //   997: lload 11
    //   999: invokevirtual 352	java/lang/StringBuilder:append	(J)Ljava/lang/StringBuilder;
    //   1002: invokevirtual 114	java/lang/StringBuilder:toString	()Ljava/lang/String;
    //   1005: astore_1
    //   1006: aload 26
    //   1008: getfield 52	com/tencent/smtt/sdk/k:mContext	Landroid/content/Context;
    //   1011: invokevirtual 265	android/content/Context:getContentResolver	()Landroid/content/ContentResolver;
    //   1014: aload 26
    //   1016: getfield 268	com/tencent/smtt/sdk/k:jKe	Ljava/lang/String;
    //   1019: aload_1
    //   1020: invokestatic 274	android/provider/Settings$System:putString	(Landroid/content/ContentResolver;Ljava/lang/String;Ljava/lang/String;)Z
    //   1023: pop
    //   1024: aload 26
    //   1026: iconst_1
    //   1027: putfield 280	com/tencent/smtt/sdk/k:jKi	Z
    //   1030: aload 26
    //   1032: getfield 93	com/tencent/smtt/sdk/k:jJW	Ljava/lang/String;
    //   1035: ifnull +623 -> 1658
    //   1038: aload 26
    //   1040: getfield 93	com/tencent/smtt/sdk/k:jJW	Ljava/lang/String;
    //   1043: astore_1
    //   1044: aload_1
    //   1045: aload 26
    //   1047: getfield 370	com/tencent/smtt/sdk/k:jJV	Ljava/lang/String;
    //   1050: invokevirtual 312	java/lang/String:equals	(Ljava/lang/Object;)Z
    //   1053: ifne +24 -> 1077
    //   1056: aload 26
    //   1058: getfield 204	com/tencent/smtt/sdk/k:jKf	Lcom/tencent/smtt/sdk/i;
    //   1061: astore 21
    //   1063: aload 21
    //   1065: getfield 373	com/tencent/smtt/sdk/i:jJA	Ljava/lang/String;
    //   1068: ifnonnull +599 -> 1667
    //   1071: aload 21
    //   1073: aload_1
    //   1074: putfield 373	com/tencent/smtt/sdk/i:jJA	Ljava/lang/String;
    //   1077: aload 26
    //   1079: aload_1
    //   1080: putfield 370	com/tencent/smtt/sdk/k:jJV	Ljava/lang/String;
    //   1083: aload 26
    //   1085: new 375	java/net/URL
    //   1088: dup
    //   1089: aload_1
    //   1090: invokespecial 376	java/net/URL:<init>	(Ljava/lang/String;)V
    //   1093: invokevirtual 380	java/net/URL:openConnection	()Ljava/net/URLConnection;
    //   1096: checkcast 236	java/net/HttpURLConnection
    //   1099: putfield 108	com/tencent/smtt/sdk/k:jKd	Ljava/net/HttpURLConnection;
    //   1102: aload 26
    //   1104: getfield 108	com/tencent/smtt/sdk/k:jKd	Ljava/net/HttpURLConnection;
    //   1107: ldc_w 382
    //   1110: invokestatic 385	com/tencent/smtt/sdk/o:aUQ	()Ljava/lang/String;
    //   1113: invokevirtual 388	java/net/HttpURLConnection:setRequestProperty	(Ljava/lang/String;Ljava/lang/String;)V
    //   1116: aload 26
    //   1118: getfield 108	com/tencent/smtt/sdk/k:jKd	Ljava/net/HttpURLConnection;
    //   1121: ldc_w 390
    //   1124: ldc_w 392
    //   1127: invokevirtual 388	java/net/HttpURLConnection:setRequestProperty	(Ljava/lang/String;Ljava/lang/String;)V
    //   1130: aload 26
    //   1132: getfield 108	com/tencent/smtt/sdk/k:jKd	Ljava/net/HttpURLConnection;
    //   1135: ldc_w 394
    //   1138: invokevirtual 397	java/net/HttpURLConnection:setRequestMethod	(Ljava/lang/String;)V
    //   1141: aload 26
    //   1143: getfield 108	com/tencent/smtt/sdk/k:jKd	Ljava/net/HttpURLConnection;
    //   1146: iconst_0
    //   1147: invokevirtual 400	java/net/HttpURLConnection:setInstanceFollowRedirects	(Z)V
    //   1150: aload 26
    //   1152: getfield 108	com/tencent/smtt/sdk/k:jKd	Ljava/net/HttpURLConnection;
    //   1155: aload 26
    //   1157: getfield 403	com/tencent/smtt/sdk/k:jKa	I
    //   1160: invokevirtual 406	java/net/HttpURLConnection:setConnectTimeout	(I)V
    //   1163: aload 26
    //   1165: getfield 108	com/tencent/smtt/sdk/k:jKd	Ljava/net/HttpURLConnection;
    //   1168: aload 26
    //   1170: getfield 409	com/tencent/smtt/sdk/k:jJZ	I
    //   1173: invokevirtual 412	java/net/HttpURLConnection:setReadTimeout	(I)V
    //   1176: lconst_0
    //   1177: lstore 5
    //   1179: aload 26
    //   1181: getfield 415	com/tencent/smtt/sdk/k:jKb	Z
    //   1184: ifne +2008 -> 3192
    //   1187: aload 26
    //   1189: invokevirtual 418	com/tencent/smtt/sdk/k:aUn	()J
    //   1192: lstore 5
    //   1194: ldc 77
    //   1196: new 79	java/lang/StringBuilder
    //   1199: dup
    //   1200: ldc_w 420
    //   1203: invokespecial 84	java/lang/StringBuilder:<init>	(Ljava/lang/String;)V
    //   1206: lload 5
    //   1208: invokevirtual 352	java/lang/StringBuilder:append	(J)Ljava/lang/StringBuilder;
    //   1211: invokevirtual 114	java/lang/StringBuilder:toString	()Ljava/lang/String;
    //   1214: invokestatic 120	com/tencent/smtt/a/u:i	(Ljava/lang/String;Ljava/lang/String;)V
    //   1217: aload 26
    //   1219: getfield 423	com/tencent/smtt/sdk/k:jJY	J
    //   1222: lconst_0
    //   1223: lcmp
    //   1224: ifgt +479 -> 1703
    //   1227: ldc 77
    //   1229: new 79	java/lang/StringBuilder
    //   1232: dup
    //   1233: ldc_w 425
    //   1236: invokespecial 84	java/lang/StringBuilder:<init>	(Ljava/lang/String;)V
    //   1239: lload 5
    //   1241: invokevirtual 352	java/lang/StringBuilder:append	(J)Ljava/lang/StringBuilder;
    //   1244: invokevirtual 114	java/lang/StringBuilder:toString	()Ljava/lang/String;
    //   1247: iconst_1
    //   1248: invokestatic 156	com/tencent/smtt/a/u:j	(Ljava/lang/String;Ljava/lang/String;Z)V
    //   1251: aload 26
    //   1253: getfield 108	com/tencent/smtt/sdk/k:jKd	Ljava/net/HttpURLConnection;
    //   1256: ldc_w 427
    //   1259: new 79	java/lang/StringBuilder
    //   1262: dup
    //   1263: ldc_w 429
    //   1266: invokespecial 84	java/lang/StringBuilder:<init>	(Ljava/lang/String;)V
    //   1269: lload 5
    //   1271: invokevirtual 352	java/lang/StringBuilder:append	(J)Ljava/lang/StringBuilder;
    //   1274: ldc_w 431
    //   1277: invokevirtual 88	java/lang/StringBuilder:append	(Ljava/lang/String;)Ljava/lang/StringBuilder;
    //   1280: invokevirtual 114	java/lang/StringBuilder:toString	()Ljava/lang/String;
    //   1283: invokevirtual 388	java/net/HttpURLConnection:setRequestProperty	(Ljava/lang/String;Ljava/lang/String;)V
    //   1286: aload 26
    //   1288: getfield 204	com/tencent/smtt/sdk/k:jKf	Lcom/tencent/smtt/sdk/i;
    //   1291: astore_1
    //   1292: lload 5
    //   1294: lconst_0
    //   1295: lcmp
    //   1296: ifne +1899 -> 3195
    //   1299: iconst_0
    //   1300: istore_3
    //   1301: aload_1
    //   1302: iload_3
    //   1303: putfield 434	com/tencent/smtt/sdk/i:jJE	I
    //   1306: aload 26
    //   1308: getfield 52	com/tencent/smtt/sdk/k:mContext	Landroid/content/Context;
    //   1311: invokestatic 294	com/tencent/smtt/a/b:eP	(Landroid/content/Context;)I
    //   1314: istore_3
    //   1315: aload 26
    //   1317: getfield 52	com/tencent/smtt/sdk/k:mContext	Landroid/content/Context;
    //   1320: invokestatic 290	com/tencent/smtt/a/b:eO	(Landroid/content/Context;)Ljava/lang/String;
    //   1323: astore_1
    //   1324: aload 26
    //   1326: getfield 306	com/tencent/smtt/sdk/k:jKg	Ljava/lang/String;
    //   1329: ifnonnull +458 -> 1787
    //   1332: aload 26
    //   1334: getfield 303	com/tencent/smtt/sdk/k:jKh	I
    //   1337: iconst_m1
    //   1338: if_icmpne +449 -> 1787
    //   1341: aload 26
    //   1343: aload_1
    //   1344: putfield 306	com/tencent/smtt/sdk/k:jKg	Ljava/lang/String;
    //   1347: aload 26
    //   1349: iload_3
    //   1350: putfield 303	com/tencent/smtt/sdk/k:jKh	I
    //   1353: aload 26
    //   1355: getfield 163	com/tencent/smtt/sdk/k:bUD	I
    //   1358: ifle +19 -> 1377
    //   1361: aload 26
    //   1363: getfield 108	com/tencent/smtt/sdk/k:jKd	Ljava/net/HttpURLConnection;
    //   1366: ldc_w 436
    //   1369: aload 26
    //   1371: getfield 75	com/tencent/smtt/sdk/k:mDownloadUrl	Ljava/lang/String;
    //   1374: invokevirtual 439	java/net/HttpURLConnection:addRequestProperty	(Ljava/lang/String;Ljava/lang/String;)V
    //   1377: aload 26
    //   1379: getfield 108	com/tencent/smtt/sdk/k:jKd	Ljava/net/HttpURLConnection;
    //   1382: invokevirtual 440	java/net/HttpURLConnection:getResponseCode	()I
    //   1385: istore 4
    //   1387: ldc 77
    //   1389: new 79	java/lang/StringBuilder
    //   1392: dup
    //   1393: ldc_w 442
    //   1396: invokespecial 84	java/lang/StringBuilder:<init>	(Ljava/lang/String;)V
    //   1399: iload 4
    //   1401: invokevirtual 257	java/lang/StringBuilder:append	(I)Ljava/lang/StringBuilder;
    //   1404: invokevirtual 114	java/lang/StringBuilder:toString	()Ljava/lang/String;
    //   1407: invokestatic 120	com/tencent/smtt/a/u:i	(Ljava/lang/String;Ljava/lang/String;)V
    //   1410: aload 26
    //   1412: getfield 204	com/tencent/smtt/sdk/k:jKf	Lcom/tencent/smtt/sdk/i;
    //   1415: iload 4
    //   1417: putfield 445	com/tencent/smtt/sdk/i:jJC	I
    //   1420: iload_3
    //   1421: iconst_3
    //   1422: if_icmpeq +34 -> 1456
    //   1425: aload 26
    //   1427: iconst_1
    //   1428: putfield 99	com/tencent/smtt/sdk/k:cRW	Z
    //   1431: invokestatic 126	com/tencent/smtt/sdk/QbSdk:aUc	()Lcom/tencent/smtt/sdk/y;
    //   1434: ifnull +13 -> 1447
    //   1437: invokestatic 126	com/tencent/smtt/sdk/QbSdk:aUc	()Lcom/tencent/smtt/sdk/y;
    //   1440: bipush 111
    //   1442: invokeinterface 132 2 0
    //   1447: ldc 77
    //   1449: ldc_w 447
    //   1452: iconst_0
    //   1453: invokestatic 156	com/tencent/smtt/a/u:j	(Ljava/lang/String;Ljava/lang/String;Z)V
    //   1456: aload 26
    //   1458: getfield 99	com/tencent/smtt/sdk/k:cRW	Z
    //   1461: ifne -1042 -> 419
    //   1464: iload 4
    //   1466: sipush 200
    //   1469: if_icmpeq +11 -> 1480
    //   1472: iload 4
    //   1474: sipush 206
    //   1477: if_icmpne +1111 -> 2588
    //   1480: aload 26
    //   1482: aload 26
    //   1484: getfield 108	com/tencent/smtt/sdk/k:jKd	Ljava/net/HttpURLConnection;
    //   1487: invokevirtual 450	java/net/HttpURLConnection:getContentLength	()I
    //   1490: i2l
    //   1491: lload 5
    //   1493: ladd
    //   1494: putfield 423	com/tencent/smtt/sdk/k:jJY	J
    //   1497: ldc 77
    //   1499: new 79	java/lang/StringBuilder
    //   1502: dup
    //   1503: ldc_w 452
    //   1506: invokespecial 84	java/lang/StringBuilder:<init>	(Ljava/lang/String;)V
    //   1509: aload 26
    //   1511: getfield 423	com/tencent/smtt/sdk/k:jJY	J
    //   1514: invokevirtual 352	java/lang/StringBuilder:append	(J)Ljava/lang/StringBuilder;
    //   1517: invokevirtual 114	java/lang/StringBuilder:toString	()Ljava/lang/String;
    //   1520: invokestatic 120	com/tencent/smtt/a/u:i	(Ljava/lang/String;Ljava/lang/String;)V
    //   1523: aload 26
    //   1525: getfield 204	com/tencent/smtt/sdk/k:jKf	Lcom/tencent/smtt/sdk/i;
    //   1528: aload 26
    //   1530: getfield 423	com/tencent/smtt/sdk/k:jJY	J
    //   1533: putfield 455	com/tencent/smtt/sdk/i:jJJ	J
    //   1536: aload 26
    //   1538: getfield 52	com/tencent/smtt/sdk/k:mContext	Landroid/content/Context;
    //   1541: invokestatic 43	com/tencent/smtt/sdk/n:en	(Landroid/content/Context;)Lcom/tencent/smtt/sdk/n;
    //   1544: invokevirtual 458	com/tencent/smtt/sdk/n:aUB	()J
    //   1547: lstore 7
    //   1549: lload 7
    //   1551: lconst_0
    //   1552: lcmp
    //   1553: ifeq +279 -> 1832
    //   1556: aload 26
    //   1558: getfield 423	com/tencent/smtt/sdk/k:jJY	J
    //   1561: lload 7
    //   1563: lcmp
    //   1564: ifeq +268 -> 1832
    //   1567: aload 26
    //   1569: getfield 204	com/tencent/smtt/sdk/k:jKf	Lcom/tencent/smtt/sdk/i;
    //   1572: bipush 113
    //   1574: invokevirtual 229	com/tencent/smtt/sdk/i:setErrorCode	(I)V
    //   1577: aload 26
    //   1579: getfield 204	com/tencent/smtt/sdk/k:jKf	Lcom/tencent/smtt/sdk/i;
    //   1582: new 79	java/lang/StringBuilder
    //   1585: dup
    //   1586: ldc_w 460
    //   1589: invokespecial 84	java/lang/StringBuilder:<init>	(Ljava/lang/String;)V
    //   1592: lload 7
    //   1594: invokevirtual 352	java/lang/StringBuilder:append	(J)Ljava/lang/StringBuilder;
    //   1597: ldc_w 462
    //   1600: invokevirtual 88	java/lang/StringBuilder:append	(Ljava/lang/String;)Ljava/lang/StringBuilder;
    //   1603: aload 26
    //   1605: getfield 423	com/tencent/smtt/sdk/k:jJY	J
    //   1608: invokevirtual 352	java/lang/StringBuilder:append	(J)Ljava/lang/StringBuilder;
    //   1611: invokevirtual 114	java/lang/StringBuilder:toString	()Ljava/lang/String;
    //   1614: putfield 214	com/tencent/smtt/sdk/i:jJN	Ljava/lang/String;
    //   1617: ldc 77
    //   1619: new 79	java/lang/StringBuilder
    //   1622: dup
    //   1623: ldc_w 464
    //   1626: invokespecial 84	java/lang/StringBuilder:<init>	(Ljava/lang/String;)V
    //   1629: lload 7
    //   1631: invokevirtual 352	java/lang/StringBuilder:append	(J)Ljava/lang/StringBuilder;
    //   1634: ldc_w 462
    //   1637: invokevirtual 88	java/lang/StringBuilder:append	(Ljava/lang/String;)Ljava/lang/StringBuilder;
    //   1640: aload 26
    //   1642: getfield 423	com/tencent/smtt/sdk/k:jJY	J
    //   1645: invokevirtual 352	java/lang/StringBuilder:append	(J)Ljava/lang/StringBuilder;
    //   1648: invokevirtual 114	java/lang/StringBuilder:toString	()Ljava/lang/String;
    //   1651: iconst_1
    //   1652: invokestatic 156	com/tencent/smtt/a/u:j	(Ljava/lang/String;Ljava/lang/String;Z)V
    //   1655: goto -1236 -> 419
    //   1658: aload 26
    //   1660: getfield 75	com/tencent/smtt/sdk/k:mDownloadUrl	Ljava/lang/String;
    //   1663: astore_1
    //   1664: goto -620 -> 1044
    //   1667: aload 21
    //   1669: new 79	java/lang/StringBuilder
    //   1672: dup
    //   1673: invokespecial 251	java/lang/StringBuilder:<init>	()V
    //   1676: aload 21
    //   1678: getfield 373	com/tencent/smtt/sdk/i:jJA	Ljava/lang/String;
    //   1681: invokevirtual 88	java/lang/StringBuilder:append	(Ljava/lang/String;)Ljava/lang/StringBuilder;
    //   1684: ldc_w 466
    //   1687: invokevirtual 88	java/lang/StringBuilder:append	(Ljava/lang/String;)Ljava/lang/StringBuilder;
    //   1690: aload_1
    //   1691: invokevirtual 88	java/lang/StringBuilder:append	(Ljava/lang/String;)Ljava/lang/StringBuilder;
    //   1694: invokevirtual 114	java/lang/StringBuilder:toString	()Ljava/lang/String;
    //   1697: putfield 373	com/tencent/smtt/sdk/i:jJA	Ljava/lang/String;
    //   1700: goto -623 -> 1077
    //   1703: ldc 77
    //   1705: new 79	java/lang/StringBuilder
    //   1708: dup
    //   1709: ldc_w 468
    //   1712: invokespecial 84	java/lang/StringBuilder:<init>	(Ljava/lang/String;)V
    //   1715: lload 5
    //   1717: invokevirtual 352	java/lang/StringBuilder:append	(J)Ljava/lang/StringBuilder;
    //   1720: ldc_w 470
    //   1723: invokevirtual 88	java/lang/StringBuilder:append	(Ljava/lang/String;)Ljava/lang/StringBuilder;
    //   1726: aload 26
    //   1728: getfield 423	com/tencent/smtt/sdk/k:jJY	J
    //   1731: invokevirtual 352	java/lang/StringBuilder:append	(J)Ljava/lang/StringBuilder;
    //   1734: invokevirtual 114	java/lang/StringBuilder:toString	()Ljava/lang/String;
    //   1737: iconst_1
    //   1738: invokestatic 156	com/tencent/smtt/a/u:j	(Ljava/lang/String;Ljava/lang/String;Z)V
    //   1741: aload 26
    //   1743: getfield 108	com/tencent/smtt/sdk/k:jKd	Ljava/net/HttpURLConnection;
    //   1746: ldc_w 427
    //   1749: new 79	java/lang/StringBuilder
    //   1752: dup
    //   1753: ldc_w 429
    //   1756: invokespecial 84	java/lang/StringBuilder:<init>	(Ljava/lang/String;)V
    //   1759: lload 5
    //   1761: invokevirtual 352	java/lang/StringBuilder:append	(J)Ljava/lang/StringBuilder;
    //   1764: ldc_w 431
    //   1767: invokevirtual 88	java/lang/StringBuilder:append	(Ljava/lang/String;)Ljava/lang/StringBuilder;
    //   1770: aload 26
    //   1772: getfield 423	com/tencent/smtt/sdk/k:jJY	J
    //   1775: invokevirtual 352	java/lang/StringBuilder:append	(J)Ljava/lang/StringBuilder;
    //   1778: invokevirtual 114	java/lang/StringBuilder:toString	()Ljava/lang/String;
    //   1781: invokevirtual 388	java/net/HttpURLConnection:setRequestProperty	(Ljava/lang/String;Ljava/lang/String;)V
    //   1784: goto +1408 -> 3192
    //   1787: iload_3
    //   1788: aload 26
    //   1790: getfield 303	com/tencent/smtt/sdk/k:jKh	I
    //   1793: if_icmpne +15 -> 1808
    //   1796: aload_1
    //   1797: aload 26
    //   1799: getfield 306	com/tencent/smtt/sdk/k:jKg	Ljava/lang/String;
    //   1802: invokevirtual 312	java/lang/String:equals	(Ljava/lang/Object;)Z
    //   1805: ifne -452 -> 1353
    //   1808: aload 26
    //   1810: getfield 204	com/tencent/smtt/sdk/k:jKf	Lcom/tencent/smtt/sdk/i;
    //   1813: iconst_0
    //   1814: putfield 315	com/tencent/smtt/sdk/i:jJL	I
    //   1817: aload 26
    //   1819: aload_1
    //   1820: putfield 306	com/tencent/smtt/sdk/k:jKg	Ljava/lang/String;
    //   1823: aload 26
    //   1825: iload_3
    //   1826: putfield 303	com/tencent/smtt/sdk/k:jKh	I
    //   1829: goto -476 -> 1353
    //   1832: aconst_null
    //   1833: astore 24
    //   1835: aconst_null
    //   1836: astore_1
    //   1837: aconst_null
    //   1838: astore 22
    //   1840: aload 26
    //   1842: getfield 108	com/tencent/smtt/sdk/k:jKd	Ljava/net/HttpURLConnection;
    //   1845: invokevirtual 474	java/net/HttpURLConnection:getInputStream	()Ljava/io/InputStream;
    //   1848: astore 21
    //   1850: aload 21
    //   1852: ifnull +1332 -> 3184
    //   1855: aload 26
    //   1857: getfield 108	com/tencent/smtt/sdk/k:jKd	Ljava/net/HttpURLConnection;
    //   1860: invokevirtual 477	java/net/HttpURLConnection:getContentEncoding	()Ljava/lang/String;
    //   1863: astore_1
    //   1864: aload_1
    //   1865: ifnull +98 -> 1963
    //   1868: aload_1
    //   1869: ldc_w 479
    //   1872: invokevirtual 483	java/lang/String:contains	(Ljava/lang/CharSequence;)Z
    //   1875: ifeq +88 -> 1963
    //   1878: new 485	java/util/zip/GZIPInputStream
    //   1881: dup
    //   1882: aload 21
    //   1884: invokespecial 488	java/util/zip/GZIPInputStream:<init>	(Ljava/io/InputStream;)V
    //   1887: astore_1
    //   1888: sipush 8192
    //   1891: newarray <illegal type>
    //   1893: astore 22
    //   1895: new 490	java/io/FileOutputStream
    //   1898: dup
    //   1899: new 134	java/io/File
    //   1902: dup
    //   1903: aload 26
    //   1905: getfield 138	com/tencent/smtt/sdk/k:jJX	Ljava/io/File;
    //   1908: ldc_w 492
    //   1911: invokespecial 143	java/io/File:<init>	(Ljava/io/File;Ljava/lang/String;)V
    //   1914: iconst_1
    //   1915: invokespecial 495	java/io/FileOutputStream:<init>	(Ljava/io/File;Z)V
    //   1918: astore 23
    //   1920: invokestatic 171	java/lang/System:currentTimeMillis	()J
    //   1923: lstore 7
    //   1925: lload 5
    //   1927: lstore 9
    //   1929: aload 26
    //   1931: getfield 99	com/tencent/smtt/sdk/k:cRW	Z
    //   1934: ifeq +146 -> 2080
    //   1937: ldc 77
    //   1939: ldc_w 497
    //   1942: iconst_1
    //   1943: invokestatic 156	com/tencent/smtt/a/u:j	(Ljava/lang/String;Ljava/lang/String;Z)V
    //   1946: aload 23
    //   1948: invokestatic 501	com/tencent/smtt/sdk/k:d	(Ljava/io/Closeable;)V
    //   1951: aload_1
    //   1952: invokestatic 501	com/tencent/smtt/sdk/k:d	(Ljava/io/Closeable;)V
    //   1955: aload 21
    //   1957: invokestatic 501	com/tencent/smtt/sdk/k:d	(Ljava/io/Closeable;)V
    //   1960: goto -1541 -> 419
    //   1963: aload_1
    //   1964: ifnull +110 -> 2074
    //   1967: aload_1
    //   1968: ldc_w 503
    //   1971: invokevirtual 483	java/lang/String:contains	(Ljava/lang/CharSequence;)Z
    //   1974: ifeq +100 -> 2074
    //   1977: new 505	java/util/zip/InflaterInputStream
    //   1980: dup
    //   1981: aload 21
    //   1983: new 507	java/util/zip/Inflater
    //   1986: dup
    //   1987: iconst_1
    //   1988: invokespecial 509	java/util/zip/Inflater:<init>	(Z)V
    //   1991: invokespecial 512	java/util/zip/InflaterInputStream:<init>	(Ljava/io/InputStream;Ljava/util/zip/Inflater;)V
    //   1994: astore_1
    //   1995: goto -107 -> 1888
    //   1998: astore 25
    //   2000: aload 21
    //   2002: astore_1
    //   2003: aload 24
    //   2005: astore 23
    //   2007: aload 25
    //   2009: astore 21
    //   2011: aload 21
    //   2013: instanceof 514
    //   2016: ifne +11 -> 2027
    //   2019: aload 21
    //   2021: instanceof 516
    //   2024: ifeq +466 -> 2490
    //   2027: aload 26
    //   2029: ldc_w 517
    //   2032: putfield 409	com/tencent/smtt/sdk/k:jJZ	I
    //   2035: aload 26
    //   2037: aload 26
    //   2039: getfield 163	com/tencent/smtt/sdk/k:bUD	I
    //   2042: iconst_1
    //   2043: iadd
    //   2044: putfield 163	com/tencent/smtt/sdk/k:bUD	I
    //   2047: aload 26
    //   2049: getfield 204	com/tencent/smtt/sdk/k:jKf	Lcom/tencent/smtt/sdk/i;
    //   2052: bipush 103
    //   2054: invokevirtual 229	com/tencent/smtt/sdk/i:setErrorCode	(I)V
    //   2057: aload 23
    //   2059: invokestatic 501	com/tencent/smtt/sdk/k:d	(Ljava/io/Closeable;)V
    //   2062: aload 22
    //   2064: invokestatic 501	com/tencent/smtt/sdk/k:d	(Ljava/io/Closeable;)V
    //   2067: aload_1
    //   2068: invokestatic 501	com/tencent/smtt/sdk/k:d	(Ljava/io/Closeable;)V
    //   2071: goto -1762 -> 309
    //   2074: aload 21
    //   2076: astore_1
    //   2077: goto -189 -> 1888
    //   2080: aload_1
    //   2081: aload 22
    //   2083: iconst_0
    //   2084: sipush 8192
    //   2087: invokevirtual 523	java/io/InputStream:read	([BII)I
    //   2090: istore_3
    //   2091: iload_3
    //   2092: ifgt +12 -> 2104
    //   2095: aload 26
    //   2097: iconst_1
    //   2098: putfield 200	com/tencent/smtt/sdk/k:mFinished	Z
    //   2101: goto -155 -> 1946
    //   2104: aload 23
    //   2106: aload 22
    //   2108: iconst_0
    //   2109: iload_3
    //   2110: invokevirtual 527	java/io/FileOutputStream:write	([BII)V
    //   2113: aload 23
    //   2115: invokevirtual 530	java/io/FileOutputStream:flush	()V
    //   2118: aload 26
    //   2120: getfield 52	com/tencent/smtt/sdk/k:mContext	Landroid/content/Context;
    //   2123: invokestatic 43	com/tencent/smtt/sdk/n:en	(Landroid/content/Context;)Lcom/tencent/smtt/sdk/n;
    //   2126: invokevirtual 347	com/tencent/smtt/sdk/n:aUO	()J
    //   2129: iload_3
    //   2130: i2l
    //   2131: ladd
    //   2132: lstore 13
    //   2134: aload 26
    //   2136: getfield 52	com/tencent/smtt/sdk/k:mContext	Landroid/content/Context;
    //   2139: invokestatic 43	com/tencent/smtt/sdk/n:en	(Landroid/content/Context;)Lcom/tencent/smtt/sdk/n;
    //   2142: lload 13
    //   2144: invokestatic 184	java/lang/Long:valueOf	(J)Ljava/lang/Long;
    //   2147: invokevirtual 189	com/tencent/smtt/sdk/n:j	(Ljava/lang/Long;)V
    //   2150: aload 26
    //   2152: getfield 52	com/tencent/smtt/sdk/k:mContext	Landroid/content/Context;
    //   2155: invokestatic 43	com/tencent/smtt/sdk/n:en	(Landroid/content/Context;)Lcom/tencent/smtt/sdk/n;
    //   2158: invokevirtual 192	com/tencent/smtt/sdk/n:commit	()V
    //   2161: lload 13
    //   2163: lload 15
    //   2165: lcmp
    //   2166: iflt +44 -> 2210
    //   2169: ldc 77
    //   2171: ldc_w 354
    //   2174: iconst_1
    //   2175: invokestatic 156	com/tencent/smtt/a/u:j	(Ljava/lang/String;Ljava/lang/String;Z)V
    //   2178: aload 26
    //   2180: getfield 204	com/tencent/smtt/sdk/k:jKf	Lcom/tencent/smtt/sdk/i;
    //   2183: bipush 112
    //   2185: invokevirtual 229	com/tencent/smtt/sdk/i:setErrorCode	(I)V
    //   2188: goto -242 -> 1946
    //   2191: astore 22
    //   2193: aload 23
    //   2195: invokestatic 501	com/tencent/smtt/sdk/k:d	(Ljava/io/Closeable;)V
    //   2198: aload_1
    //   2199: invokestatic 501	com/tencent/smtt/sdk/k:d	(Ljava/io/Closeable;)V
    //   2202: aload 21
    //   2204: invokestatic 501	com/tencent/smtt/sdk/k:d	(Ljava/io/Closeable;)V
    //   2207: aload 22
    //   2209: athrow
    //   2210: aload 26
    //   2212: invokevirtual 195	com/tencent/smtt/sdk/k:aUp	()Z
    //   2215: ifne +80 -> 2295
    //   2218: ldc 77
    //   2220: ldc_w 532
    //   2223: iconst_1
    //   2224: invokestatic 156	com/tencent/smtt/a/u:j	(Ljava/lang/String;Ljava/lang/String;Z)V
    //   2227: aload 26
    //   2229: getfield 204	com/tencent/smtt/sdk/k:jKf	Lcom/tencent/smtt/sdk/i;
    //   2232: new 79	java/lang/StringBuilder
    //   2235: dup
    //   2236: ldc_w 534
    //   2239: invokespecial 84	java/lang/StringBuilder:<init>	(Ljava/lang/String;)V
    //   2242: aload 26
    //   2244: getfield 138	com/tencent/smtt/sdk/k:jJX	Ljava/io/File;
    //   2247: invokevirtual 537	java/io/File:getAbsolutePath	()Ljava/lang/String;
    //   2250: invokestatic 543	com/tencent/smtt/a/e:Cm	(Ljava/lang/String;)J
    //   2253: invokevirtual 352	java/lang/StringBuilder:append	(J)Ljava/lang/StringBuilder;
    //   2256: ldc_w 545
    //   2259: invokevirtual 88	java/lang/StringBuilder:append	(Ljava/lang/String;)Ljava/lang/StringBuilder;
    //   2262: aload 26
    //   2264: getfield 52	com/tencent/smtt/sdk/k:mContext	Landroid/content/Context;
    //   2267: invokestatic 43	com/tencent/smtt/sdk/n:en	(Landroid/content/Context;)Lcom/tencent/smtt/sdk/n;
    //   2270: invokevirtual 548	com/tencent/smtt/sdk/n:aUH	()J
    //   2273: invokevirtual 352	java/lang/StringBuilder:append	(J)Ljava/lang/StringBuilder;
    //   2276: invokevirtual 114	java/lang/StringBuilder:toString	()Ljava/lang/String;
    //   2279: putfield 214	com/tencent/smtt/sdk/i:jJN	Ljava/lang/String;
    //   2282: aload 26
    //   2284: getfield 204	com/tencent/smtt/sdk/k:jKf	Lcom/tencent/smtt/sdk/i;
    //   2287: bipush 105
    //   2289: invokevirtual 229	com/tencent/smtt/sdk/i:setErrorCode	(I)V
    //   2292: goto -346 -> 1946
    //   2295: iload_3
    //   2296: i2l
    //   2297: lstore 17
    //   2299: invokestatic 171	java/lang/System:currentTimeMillis	()J
    //   2302: lstore 13
    //   2304: aload 26
    //   2306: getfield 204	com/tencent/smtt/sdk/k:jKf	Lcom/tencent/smtt/sdk/i;
    //   2309: astore 24
    //   2311: aload 24
    //   2313: lload 13
    //   2315: lload 11
    //   2317: lsub
    //   2318: aload 24
    //   2320: getfield 551	com/tencent/smtt/sdk/i:jJK	J
    //   2323: ladd
    //   2324: putfield 551	com/tencent/smtt/sdk/i:jJK	J
    //   2327: aload 26
    //   2329: getfield 204	com/tencent/smtt/sdk/k:jKf	Lcom/tencent/smtt/sdk/i;
    //   2332: astore 24
    //   2334: aload 24
    //   2336: lload 17
    //   2338: aload 24
    //   2340: getfield 554	com/tencent/smtt/sdk/i:jJO	J
    //   2343: ladd
    //   2344: putfield 554	com/tencent/smtt/sdk/i:jJO	J
    //   2347: invokestatic 171	java/lang/System:currentTimeMillis	()J
    //   2350: lstore 11
    //   2352: lload 9
    //   2354: iload_3
    //   2355: i2l
    //   2356: ladd
    //   2357: lstore 9
    //   2359: lload 11
    //   2361: lload 7
    //   2363: lsub
    //   2364: ldc2_w 555
    //   2367: lcmp
    //   2368: ifle +813 -> 3181
    //   2371: ldc 77
    //   2373: new 79	java/lang/StringBuilder
    //   2376: dup
    //   2377: ldc_w 468
    //   2380: invokespecial 84	java/lang/StringBuilder:<init>	(Ljava/lang/String;)V
    //   2383: lload 9
    //   2385: invokevirtual 352	java/lang/StringBuilder:append	(J)Ljava/lang/StringBuilder;
    //   2388: ldc_w 470
    //   2391: invokevirtual 88	java/lang/StringBuilder:append	(Ljava/lang/String;)Ljava/lang/StringBuilder;
    //   2394: aload 26
    //   2396: getfield 423	com/tencent/smtt/sdk/k:jJY	J
    //   2399: invokevirtual 352	java/lang/StringBuilder:append	(J)Ljava/lang/StringBuilder;
    //   2402: invokevirtual 114	java/lang/StringBuilder:toString	()Ljava/lang/String;
    //   2405: iconst_1
    //   2406: invokestatic 156	com/tencent/smtt/a/u:j	(Ljava/lang/String;Ljava/lang/String;Z)V
    //   2409: lload 5
    //   2411: lstore 7
    //   2413: lload 9
    //   2415: lload 5
    //   2417: lsub
    //   2418: ldc2_w 557
    //   2421: lcmp
    //   2422: ifle +53 -> 2475
    //   2425: aload 26
    //   2427: getfield 52	com/tencent/smtt/sdk/k:mContext	Landroid/content/Context;
    //   2430: invokestatic 294	com/tencent/smtt/a/b:eP	(Landroid/content/Context;)I
    //   2433: iconst_3
    //   2434: if_icmpeq +37 -> 2471
    //   2437: aload 26
    //   2439: iconst_1
    //   2440: putfield 99	com/tencent/smtt/sdk/k:cRW	Z
    //   2443: invokestatic 126	com/tencent/smtt/sdk/QbSdk:aUc	()Lcom/tencent/smtt/sdk/y;
    //   2446: ifnull +13 -> 2459
    //   2449: invokestatic 126	com/tencent/smtt/sdk/QbSdk:aUc	()Lcom/tencent/smtt/sdk/y;
    //   2452: bipush 111
    //   2454: invokeinterface 132 2 0
    //   2459: ldc 77
    //   2461: ldc_w 560
    //   2464: iconst_0
    //   2465: invokestatic 156	com/tencent/smtt/a/u:j	(Ljava/lang/String;Ljava/lang/String;Z)V
    //   2468: goto -522 -> 1946
    //   2471: lload 9
    //   2473: lstore 7
    //   2475: lload 7
    //   2477: lstore 5
    //   2479: lload 11
    //   2481: lstore 7
    //   2483: lload 13
    //   2485: lstore 11
    //   2487: goto -558 -> 1929
    //   2490: iconst_0
    //   2491: istore_3
    //   2492: new 134	java/io/File
    //   2495: dup
    //   2496: aload 26
    //   2498: getfield 138	com/tencent/smtt/sdk/k:jJX	Ljava/io/File;
    //   2501: ldc_w 492
    //   2504: invokespecial 143	java/io/File:<init>	(Ljava/io/File;Ljava/lang/String;)V
    //   2507: invokevirtual 146	java/io/File:exists	()Z
    //   2510: ifeq +5 -> 2515
    //   2513: iconst_1
    //   2514: istore_3
    //   2515: iload_3
    //   2516: ifne +36 -> 2552
    //   2519: aload 26
    //   2521: getfield 204	com/tencent/smtt/sdk/k:jKf	Lcom/tencent/smtt/sdk/i;
    //   2524: bipush 106
    //   2526: invokevirtual 229	com/tencent/smtt/sdk/i:setErrorCode	(I)V
    //   2529: aload 26
    //   2531: lconst_0
    //   2532: invokevirtual 362	com/tencent/smtt/sdk/k:cZ	(J)V
    //   2535: aload 23
    //   2537: invokestatic 501	com/tencent/smtt/sdk/k:d	(Ljava/io/Closeable;)V
    //   2540: aload 22
    //   2542: invokestatic 501	com/tencent/smtt/sdk/k:d	(Ljava/io/Closeable;)V
    //   2545: aload_1
    //   2546: invokestatic 501	com/tencent/smtt/sdk/k:d	(Ljava/io/Closeable;)V
    //   2549: goto -2240 -> 309
    //   2552: aload 26
    //   2554: getfield 204	com/tencent/smtt/sdk/k:jKf	Lcom/tencent/smtt/sdk/i;
    //   2557: bipush 104
    //   2559: invokevirtual 229	com/tencent/smtt/sdk/i:setErrorCode	(I)V
    //   2562: goto -33 -> 2529
    //   2565: astore 25
    //   2567: aload 22
    //   2569: astore 21
    //   2571: aload_1
    //   2572: astore 24
    //   2574: aload 25
    //   2576: astore 22
    //   2578: aload 21
    //   2580: astore_1
    //   2581: aload 24
    //   2583: astore 21
    //   2585: goto -392 -> 2193
    //   2588: iload 4
    //   2590: sipush 300
    //   2593: if_icmplt +51 -> 2644
    //   2596: iload 4
    //   2598: sipush 307
    //   2601: if_icmpgt +43 -> 2644
    //   2604: aload 26
    //   2606: getfield 108	com/tencent/smtt/sdk/k:jKd	Ljava/net/HttpURLConnection;
    //   2609: ldc_w 562
    //   2612: invokevirtual 566	java/net/HttpURLConnection:getHeaderField	(Ljava/lang/String;)Ljava/lang/String;
    //   2615: astore_1
    //   2616: aload_1
    //   2617: invokestatic 571	android/text/TextUtils:isEmpty	(Ljava/lang/CharSequence;)Z
    //   2620: ifne -2201 -> 419
    //   2623: aload 26
    //   2625: aload_1
    //   2626: putfield 93	com/tencent/smtt/sdk/k:jJW	Ljava/lang/String;
    //   2629: aload 26
    //   2631: aload 26
    //   2633: getfield 166	com/tencent/smtt/sdk/k:jKc	I
    //   2636: iconst_1
    //   2637: iadd
    //   2638: putfield 166	com/tencent/smtt/sdk/k:jKc	I
    //   2641: goto -2332 -> 309
    //   2644: aload 26
    //   2646: getfield 204	com/tencent/smtt/sdk/k:jKf	Lcom/tencent/smtt/sdk/i;
    //   2649: bipush 102
    //   2651: invokevirtual 229	com/tencent/smtt/sdk/i:setErrorCode	(I)V
    //   2654: iload 4
    //   2656: sipush 416
    //   2659: if_icmpne +560 -> 3219
    //   2662: iload_2
    //   2663: ifeq +30 -> 2693
    //   2666: aload 26
    //   2668: iconst_0
    //   2669: invokevirtual 60	com/tencent/smtt/sdk/k:gp	(Z)Z
    //   2672: ifeq +12 -> 2684
    //   2675: aload 26
    //   2677: iconst_0
    //   2678: invokevirtual 64	com/tencent/smtt/sdk/k:go	(Z)V
    //   2681: goto -2262 -> 419
    //   2684: aload 26
    //   2686: iconst_0
    //   2687: invokevirtual 67	com/tencent/smtt/sdk/k:gq	(Z)V
    //   2690: goto -2271 -> 419
    //   2693: aload 26
    //   2695: iconst_0
    //   2696: invokevirtual 67	com/tencent/smtt/sdk/k:gq	(Z)V
    //   2699: goto -2280 -> 419
    //   2702: aload 26
    //   2704: getfield 423	com/tencent/smtt/sdk/k:jJY	J
    //   2707: ldc2_w 572
    //   2710: lcmp
    //   2711: ifeq -2292 -> 419
    //   2714: iload 4
    //   2716: sipush 202
    //   2719: if_icmpeq -2410 -> 309
    //   2722: aload 26
    //   2724: getfield 163	com/tencent/smtt/sdk/k:bUD	I
    //   2727: iconst_5
    //   2728: if_icmpge +41 -> 2769
    //   2731: iload 4
    //   2733: sipush 503
    //   2736: if_icmpne +33 -> 2769
    //   2739: aload 26
    //   2741: aload 26
    //   2743: getfield 108	com/tencent/smtt/sdk/k:jKd	Ljava/net/HttpURLConnection;
    //   2746: ldc_w 575
    //   2749: invokevirtual 566	java/net/HttpURLConnection:getHeaderField	(Ljava/lang/String;)Ljava/lang/String;
    //   2752: invokestatic 578	java/lang/Long:parseLong	(Ljava/lang/String;)J
    //   2755: invokevirtual 362	com/tencent/smtt/sdk/k:cZ	(J)V
    //   2758: aload 26
    //   2760: getfield 99	com/tencent/smtt/sdk/k:cRW	Z
    //   2763: ifeq -2454 -> 309
    //   2766: goto -2347 -> 419
    //   2769: aload 26
    //   2771: getfield 163	com/tencent/smtt/sdk/k:bUD	I
    //   2774: iconst_5
    //   2775: if_icmpge +52 -> 2827
    //   2778: iload 4
    //   2780: sipush 408
    //   2783: if_icmpeq +27 -> 2810
    //   2786: iload 4
    //   2788: sipush 504
    //   2791: if_icmpeq +19 -> 2810
    //   2794: iload 4
    //   2796: sipush 502
    //   2799: if_icmpeq +11 -> 2810
    //   2802: iload 4
    //   2804: sipush 408
    //   2807: if_icmpne +20 -> 2827
    //   2810: aload 26
    //   2812: lconst_0
    //   2813: invokevirtual 362	com/tencent/smtt/sdk/k:cZ	(J)V
    //   2816: aload 26
    //   2818: getfield 99	com/tencent/smtt/sdk/k:cRW	Z
    //   2821: ifeq -2512 -> 309
    //   2824: goto -2405 -> 419
    //   2827: aload 26
    //   2829: invokevirtual 418	com/tencent/smtt/sdk/k:aUn	()J
    //   2832: lconst_0
    //   2833: lcmp
    //   2834: ifgt -2415 -> 419
    //   2837: aload 26
    //   2839: getfield 415	com/tencent/smtt/sdk/k:jKb	Z
    //   2842: ifne -2423 -> 419
    //   2845: iload 4
    //   2847: sipush 410
    //   2850: if_icmpeq -2431 -> 419
    //   2853: aload 26
    //   2855: iconst_1
    //   2856: putfield 415	com/tencent/smtt/sdk/k:jKb	Z
    //   2859: goto -2550 -> 309
    //   2862: new 134	java/io/File
    //   2865: dup
    //   2866: aload 26
    //   2868: getfield 138	com/tencent/smtt/sdk/k:jJX	Ljava/io/File;
    //   2871: ldc_w 492
    //   2874: invokespecial 143	java/io/File:<init>	(Ljava/io/File;Ljava/lang/String;)V
    //   2877: astore_1
    //   2878: iconst_0
    //   2879: istore 20
    //   2881: aload_1
    //   2882: new 134	java/io/File
    //   2885: dup
    //   2886: aload 26
    //   2888: getfield 138	com/tencent/smtt/sdk/k:jJX	Ljava/io/File;
    //   2891: ldc -116
    //   2893: invokespecial 143	java/io/File:<init>	(Ljava/io/File;Ljava/lang/String;)V
    //   2896: invokevirtual 582	java/io/File:renameTo	(Ljava/io/File;)Z
    //   2899: istore 19
    //   2901: iload 19
    //   2903: istore 20
    //   2905: iload 20
    //   2907: istore 19
    //   2909: iload 20
    //   2911: ifne -2461 -> 450
    //   2914: aload 26
    //   2916: getfield 204	com/tencent/smtt/sdk/k:jKf	Lcom/tencent/smtt/sdk/i;
    //   2919: bipush 109
    //   2921: invokevirtual 229	com/tencent/smtt/sdk/i:setErrorCode	(I)V
    //   2924: iload 20
    //   2926: istore 19
    //   2928: goto -2478 -> 450
    //   2931: iconst_0
    //   2932: istore_2
    //   2933: goto -2470 -> 463
    //   2936: aload 26
    //   2938: iconst_0
    //   2939: invokevirtual 67	com/tencent/smtt/sdk/k:gq	(Z)V
    //   2942: goto -2453 -> 489
    //   2945: aload_1
    //   2946: invokevirtual 585	com/tencent/smtt/sdk/n:aUL	()I
    //   2949: iconst_1
    //   2950: iadd
    //   2951: istore_2
    //   2952: aload_1
    //   2953: iload_2
    //   2954: invokestatic 222	java/lang/Integer:valueOf	(I)Ljava/lang/Integer;
    //   2957: invokevirtual 588	com/tencent/smtt/sdk/n:m	(Ljava/lang/Integer;)V
    //   2960: iload_2
    //   2961: aload_1
    //   2962: invokevirtual 591	com/tencent/smtt/sdk/n:aUK	()I
    //   2965: if_icmpne -2439 -> 526
    //   2968: aload 26
    //   2970: getfield 204	com/tencent/smtt/sdk/k:jKf	Lcom/tencent/smtt/sdk/i;
    //   2973: iconst_2
    //   2974: putfield 434	com/tencent/smtt/sdk/i:jJE	I
    //   2977: goto -2451 -> 526
    //   2980: iconst_0
    //   2981: istore_2
    //   2982: goto -2439 -> 543
    //   2985: iconst_0
    //   2986: istore_2
    //   2987: goto -2159 -> 828
    //   2990: invokestatic 594	com/tencent/smtt/sdk/k:aUo	()Z
    //   2993: ifne -2151 -> 842
    //   2996: aload 26
    //   2998: getfield 204	com/tencent/smtt/sdk/k:jKf	Lcom/tencent/smtt/sdk/i;
    //   3001: bipush 101
    //   3003: invokevirtual 229	com/tencent/smtt/sdk/i:setErrorCode	(I)V
    //   3006: goto -2164 -> 842
    //   3009: iconst_0
    //   3010: putstatic 597	com/tencent/smtt/sdk/o:jKC	Z
    //   3013: return
    //   3014: invokestatic 126	com/tencent/smtt/sdk/QbSdk:aUc	()Lcom/tencent/smtt/sdk/y;
    //   3017: bipush 110
    //   3019: invokeinterface 132 2 0
    //   3024: return
    //   3025: ldc 77
    //   3027: ldc_w 599
    //   3030: invokestatic 120	com/tencent/smtt/a/u:i	(Ljava/lang/String;Ljava/lang/String;)V
    //   3033: getstatic 29	com/tencent/smtt/sdk/o:jKA	Lcom/tencent/smtt/sdk/k;
    //   3036: astore 21
    //   3038: aload_1
    //   3039: getfield 603	android/os/Message:obj	Ljava/lang/Object;
    //   3042: checkcast 219	java/lang/Integer
    //   3045: invokevirtual 606	java/lang/Integer:intValue	()I
    //   3048: istore_2
    //   3049: new 134	java/io/File
    //   3052: dup
    //   3053: aload 21
    //   3055: getfield 138	com/tencent/smtt/sdk/k:jJX	Ljava/io/File;
    //   3058: ldc -116
    //   3060: invokespecial 143	java/io/File:<init>	(Ljava/io/File;Ljava/lang/String;)V
    //   3063: astore_1
    //   3064: aload 21
    //   3066: getfield 52	com/tencent/smtt/sdk/k:mContext	Landroid/content/Context;
    //   3069: aload_1
    //   3070: invokestatic 611	com/tencent/smtt/a/a:b	(Landroid/content/Context;Ljava/io/File;)I
    //   3073: istore_3
    //   3074: iload_2
    //   3075: ifle +13 -> 3088
    //   3078: iload_2
    //   3079: iload_3
    //   3080: if_icmpne +8 -> 3088
    //   3083: aload_1
    //   3084: invokevirtual 614	java/io/File:delete	()Z
    //   3087: pop
    //   3088: getstatic 37	com/tencent/smtt/sdk/o:jKy	Landroid/content/Context;
    //   3091: invokestatic 618	com/tencent/smtt/sdk/i:eh	(Landroid/content/Context;)Lcom/tencent/smtt/sdk/i;
    //   3094: invokevirtual 621	com/tencent/smtt/sdk/i:aUk	()V
    //   3097: return
    //   3098: astore_1
    //   3099: goto -11 -> 3088
    //   3102: astore_1
    //   3103: goto -2456 -> 647
    //   3106: astore_1
    //   3107: goto -2509 -> 598
    //   3110: astore_1
    //   3111: goto -206 -> 2905
    //   3114: astore 22
    //   3116: aconst_null
    //   3117: astore_1
    //   3118: aconst_null
    //   3119: astore 21
    //   3121: aconst_null
    //   3122: astore 23
    //   3124: goto -931 -> 2193
    //   3127: astore 22
    //   3129: aconst_null
    //   3130: astore_1
    //   3131: aconst_null
    //   3132: astore 23
    //   3134: goto -941 -> 2193
    //   3137: astore 22
    //   3139: aconst_null
    //   3140: astore 23
    //   3142: goto -949 -> 2193
    //   3145: astore 21
    //   3147: aload 24
    //   3149: astore 23
    //   3151: goto -1140 -> 2011
    //   3154: astore 22
    //   3156: aload 21
    //   3158: astore 23
    //   3160: aload 22
    //   3162: astore 21
    //   3164: aload_1
    //   3165: astore 22
    //   3167: aload 23
    //   3169: astore_1
    //   3170: aload 24
    //   3172: astore 23
    //   3174: goto -1163 -> 2011
    //   3177: astore_1
    //   3178: goto -2154 -> 1024
    //   3181: goto -698 -> 2483
    //   3184: aconst_null
    //   3185: astore_1
    //   3186: aconst_null
    //   3187: astore 23
    //   3189: goto -1243 -> 1946
    //   3192: goto -1906 -> 1286
    //   3195: iconst_1
    //   3196: istore_3
    //   3197: goto -1896 -> 1301
    //   3200: astore 22
    //   3202: aload 21
    //   3204: astore 24
    //   3206: aload 22
    //   3208: astore 21
    //   3210: aload_1
    //   3211: astore 22
    //   3213: aload 24
    //   3215: astore_1
    //   3216: goto -1205 -> 2011
    //   3219: iload 4
    //   3221: sipush 403
    //   3224: if_icmpeq -522 -> 2702
    //   3227: iload 4
    //   3229: sipush 406
    //   3232: if_icmpne -518 -> 2714
    //   3235: goto -533 -> 2702
    // Local variable table:
    //   start	length	slot	name	signature
    //   0	3238	0	this	p
    //   0	3238	1	paramMessage	android.os.Message
    //   78	3003	2	i	int
    //   661	2536	3	j	int
    //   1385	1848	4	k	int
    //   880	1598	5	l1	long
    //   1547	935	7	l2	long
    //   1927	545	9	l3	long
    //   331	2155	11	l4	long
    //   2132	352	13	l5	long
    //   307	1857	15	l6	long
    //   2297	40	17	l7	long
    //   428	2499	19	bool1	boolean
    //   2879	46	20	bool2	boolean
    //   1061	2059	21	localObject1	Object
    //   3145	12	21	localIOException1	java.io.IOException
    //   3162	47	21	localObject2	Object
    //   1838	269	22	arrayOfByte	byte[]
    //   2191	377	22	localCloseable	java.io.Closeable
    //   2576	1	22	localObject3	Object
    //   3114	1	22	localObject4	Object
    //   3127	1	22	localObject5	Object
    //   3137	1	22	localObject6	Object
    //   3154	7	22	localIOException2	java.io.IOException
    //   3165	1	22	localMessage1	android.os.Message
    //   3200	7	22	localIOException3	java.io.IOException
    //   3211	1	22	localMessage2	android.os.Message
    //   1918	1270	23	localObject7	Object
    //   1833	1381	24	localObject8	Object
    //   1998	10	25	localIOException4	java.io.IOException
    //   2565	10	25	localObject9	Object
    //   65	2932	26	localk	k
    // Exception table:
    //   from	to	target	type
    //   333	403	925	java/lang/Throwable
    //   403	419	925	java/lang/Throwable
    //   869	905	925	java/lang/Throwable
    //   913	922	925	java/lang/Throwable
    //   962	1006	925	java/lang/Throwable
    //   1006	1024	925	java/lang/Throwable
    //   1024	1044	925	java/lang/Throwable
    //   1044	1077	925	java/lang/Throwable
    //   1077	1176	925	java/lang/Throwable
    //   1179	1286	925	java/lang/Throwable
    //   1286	1292	925	java/lang/Throwable
    //   1301	1353	925	java/lang/Throwable
    //   1353	1377	925	java/lang/Throwable
    //   1377	1420	925	java/lang/Throwable
    //   1425	1447	925	java/lang/Throwable
    //   1447	1456	925	java/lang/Throwable
    //   1456	1464	925	java/lang/Throwable
    //   1480	1549	925	java/lang/Throwable
    //   1556	1655	925	java/lang/Throwable
    //   1658	1664	925	java/lang/Throwable
    //   1667	1700	925	java/lang/Throwable
    //   1703	1784	925	java/lang/Throwable
    //   1787	1808	925	java/lang/Throwable
    //   1808	1829	925	java/lang/Throwable
    //   1946	1960	925	java/lang/Throwable
    //   2057	2071	925	java/lang/Throwable
    //   2193	2210	925	java/lang/Throwable
    //   2535	2549	925	java/lang/Throwable
    //   2604	2641	925	java/lang/Throwable
    //   2644	2654	925	java/lang/Throwable
    //   2666	2681	925	java/lang/Throwable
    //   2684	2690	925	java/lang/Throwable
    //   2693	2699	925	java/lang/Throwable
    //   2702	2714	925	java/lang/Throwable
    //   2722	2731	925	java/lang/Throwable
    //   2739	2766	925	java/lang/Throwable
    //   2769	2778	925	java/lang/Throwable
    //   2810	2824	925	java/lang/Throwable
    //   2827	2845	925	java/lang/Throwable
    //   2853	2859	925	java/lang/Throwable
    //   1855	1864	1998	java/io/IOException
    //   1868	1888	1998	java/io/IOException
    //   1967	1995	1998	java/io/IOException
    //   1920	1925	2191	finally
    //   1929	1946	2191	finally
    //   2080	2091	2191	finally
    //   2095	2101	2191	finally
    //   2104	2161	2191	finally
    //   2169	2188	2191	finally
    //   2210	2292	2191	finally
    //   2299	2352	2191	finally
    //   2371	2409	2191	finally
    //   2425	2459	2191	finally
    //   2459	2468	2191	finally
    //   2011	2027	2565	finally
    //   2027	2057	2565	finally
    //   2492	2513	2565	finally
    //   2519	2529	2565	finally
    //   2529	2535	2565	finally
    //   2552	2562	2565	finally
    //   3049	3074	3098	java/lang/Exception
    //   3083	3088	3098	java/lang/Exception
    //   598	647	3102	java/lang/Exception
    //   590	598	3106	java/lang/Exception
    //   2881	2901	3110	java/lang/Exception
    //   1840	1850	3114	finally
    //   1855	1864	3127	finally
    //   1868	1888	3127	finally
    //   1967	1995	3127	finally
    //   1888	1920	3137	finally
    //   1840	1850	3145	java/io/IOException
    //   1888	1920	3154	java/io/IOException
    //   1006	1024	3177	java/lang/Exception
    //   1920	1925	3200	java/io/IOException
    //   1929	1946	3200	java/io/IOException
    //   2080	2091	3200	java/io/IOException
    //   2095	2101	3200	java/io/IOException
    //   2104	2161	3200	java/io/IOException
    //   2169	2188	3200	java/io/IOException
    //   2210	2292	3200	java/io/IOException
    //   2299	2352	3200	java/io/IOException
    //   2371	2409	3200	java/io/IOException
    //   2425	2459	3200	java/io/IOException
    //   2459	2468	3200	java/io/IOException
  }
}

/* Location:
 * Qualified Name:     com.tencent.smtt.sdk.p
 * Java Class Version: 6 (50.0)
 * JD-Core Version:    0.7.1
 */