package com.tencent.mm.sdk.platformtools;

import android.os.Process;
import java.io.File;

public final class bm
{
  private static long ibA;
  private static long ibB;
  private static long ibC;
  private static long ibD;
  private static long ibE;
  private static long ibF;
  private static long ibG;
  private static long ibH;
  private static long ibI;
  private static long ibJ;
  private static long ibK;
  private static long ibL;
  private static long ibM;
  private static long ibN;
  private static final File ibO;
  private static final File ibP;
  private static long iby;
  private static long ibz;
  
  static
  {
    Object localObject2 = null;
    Object localObject1 = new File("/proc/" + Process.myPid() + "/net/dev");
    if (((File)localObject1).isFile()) {}
    for (;;)
    {
      ibO = (File)localObject1;
      File localFile = new File("/proc/net/xt_qtaguid/stats");
      localObject1 = localObject2;
      if (localFile.isFile()) {
        localObject1 = localFile;
      }
      ibP = (File)localObject1;
      return;
      localObject1 = null;
    }
  }
  
  public static long aFr()
  {
    long l = 0L;
    if (ibI > 0L) {
      l = ibI;
    }
    return l;
  }
  
  public static long aFs()
  {
    long l = 0L;
    if (ibJ > 0L) {
      l = ibJ;
    }
    return l;
  }
  
  public static long aFt()
  {
    long l = 0L;
    if (ibG > 0L) {
      l = ibG;
    }
    return l;
  }
  
  public static long aFu()
  {
    long l = 0L;
    if (ibH > 0L) {
      l = ibH;
    }
    return l;
  }
  
  public static long aFv()
  {
    long l = 0L;
    if (ibM > 0L) {
      l = ibM;
    }
    return l;
  }
  
  public static long aFw()
  {
    long l = 0L;
    if (ibN > 0L) {
      l = ibN;
    }
    return l;
  }
  
  public static long aFx()
  {
    long l = 0L;
    if (ibK > 0L) {
      l = ibK;
    }
    return l;
  }
  
  public static long aFy()
  {
    long l = 0L;
    if (ibL > 0L) {
      l = ibL;
    }
    return l;
  }
  
  public static void reset()
  {
    iby = -1L;
    ibz = -1L;
    ibA = -1L;
    ibB = -1L;
    ibD = -1L;
    ibC = -1L;
    ibF = -1L;
    ibE = -1L;
    update();
  }
  
  /* Error */
  public static void update()
  {
    // Byte code:
    //   0: lconst_0
    //   1: lstore_3
    //   2: lconst_0
    //   3: lstore_1
    //   4: getstatic 62	com/tencent/mm/sdk/platformtools/bm:ibO	Ljava/io/File;
    //   7: ifnull +649 -> 656
    //   10: new 118	java/util/Scanner
    //   13: dup
    //   14: getstatic 62	com/tencent/mm/sdk/platformtools/bm:ibO	Ljava/io/File;
    //   17: invokespecial 121	java/util/Scanner:<init>	(Ljava/io/File;)V
    //   20: astore 14
    //   22: aload 14
    //   24: astore 13
    //   26: aload 14
    //   28: invokevirtual 124	java/util/Scanner:nextLine	()Ljava/lang/String;
    //   31: pop
    //   32: aload 14
    //   34: astore 13
    //   36: aload 14
    //   38: invokevirtual 124	java/util/Scanner:nextLine	()Ljava/lang/String;
    //   41: pop
    //   42: lconst_0
    //   43: lstore 5
    //   45: lconst_0
    //   46: lstore 7
    //   48: aload 14
    //   50: astore 13
    //   52: aload 14
    //   54: invokevirtual 127	java/util/Scanner:hasNext	()Z
    //   57: ifeq +165 -> 222
    //   60: aload 14
    //   62: astore 13
    //   64: aload 14
    //   66: invokevirtual 124	java/util/Scanner:nextLine	()Ljava/lang/String;
    //   69: ldc -127
    //   71: invokevirtual 135	java/lang/String:split	(Ljava/lang/String;)[Ljava/lang/String;
    //   74: astore 15
    //   76: aload 14
    //   78: astore 13
    //   80: aload 15
    //   82: iconst_0
    //   83: aaload
    //   84: invokevirtual 138	java/lang/String:length	()I
    //   87: ifne +1219 -> 1306
    //   90: iconst_1
    //   91: istore_0
    //   92: aload 14
    //   94: astore 13
    //   96: aload 15
    //   98: iload_0
    //   99: iconst_0
    //   100: iadd
    //   101: aaload
    //   102: ldc -116
    //   104: invokevirtual 144	java/lang/String:equals	(Ljava/lang/Object;)Z
    //   107: ifne -59 -> 48
    //   110: aload 14
    //   112: astore 13
    //   114: aload 15
    //   116: iload_0
    //   117: iconst_0
    //   118: iadd
    //   119: aaload
    //   120: ldc -110
    //   122: invokevirtual 150	java/lang/String:startsWith	(Ljava/lang/String;)Z
    //   125: ifne +21 -> 146
    //   128: aload 14
    //   130: astore 13
    //   132: aload 15
    //   134: iload_0
    //   135: iconst_0
    //   136: iadd
    //   137: aaload
    //   138: ldc -104
    //   140: invokevirtual 150	java/lang/String:startsWith	(Ljava/lang/String;)Z
    //   143: ifeq +39 -> 182
    //   146: aload 14
    //   148: astore 13
    //   150: lload_3
    //   151: aload 15
    //   153: iload_0
    //   154: bipush 9
    //   156: iadd
    //   157: aaload
    //   158: invokestatic 158	java/lang/Long:parseLong	(Ljava/lang/String;)J
    //   161: ladd
    //   162: lstore_3
    //   163: aload 14
    //   165: astore 13
    //   167: lload_1
    //   168: aload 15
    //   170: iload_0
    //   171: iconst_1
    //   172: iadd
    //   173: aaload
    //   174: invokestatic 158	java/lang/Long:parseLong	(Ljava/lang/String;)J
    //   177: ladd
    //   178: lstore_1
    //   179: goto -131 -> 48
    //   182: aload 14
    //   184: astore 13
    //   186: lload 7
    //   188: aload 15
    //   190: iload_0
    //   191: bipush 9
    //   193: iadd
    //   194: aaload
    //   195: invokestatic 158	java/lang/Long:parseLong	(Ljava/lang/String;)J
    //   198: ladd
    //   199: lstore 7
    //   201: aload 14
    //   203: astore 13
    //   205: lload 5
    //   207: aload 15
    //   209: iload_0
    //   210: iconst_1
    //   211: iadd
    //   212: aaload
    //   213: invokestatic 158	java/lang/Long:parseLong	(Ljava/lang/String;)J
    //   216: ladd
    //   217: lstore 5
    //   219: goto -171 -> 48
    //   222: aload 14
    //   224: astore 13
    //   226: aload 14
    //   228: invokevirtual 161	java/util/Scanner:close	()V
    //   231: aconst_null
    //   232: astore 14
    //   234: aload 14
    //   236: astore 13
    //   238: getstatic 97	com/tencent/mm/sdk/platformtools/bm:iby	J
    //   241: lconst_0
    //   242: lcmp
    //   243: ifge +33 -> 276
    //   246: aload 14
    //   248: astore 13
    //   250: lload_3
    //   251: putstatic 97	com/tencent/mm/sdk/platformtools/bm:iby	J
    //   254: aload 14
    //   256: astore 13
    //   258: ldc -93
    //   260: ldc -91
    //   262: iconst_1
    //   263: anewarray 4	java/lang/Object
    //   266: dup
    //   267: iconst_0
    //   268: lload_3
    //   269: invokestatic 169	java/lang/Long:valueOf	(J)Ljava/lang/Long;
    //   272: aastore
    //   273: invokestatic 175	com/tencent/mm/sdk/platformtools/t:v	(Ljava/lang/String;Ljava/lang/String;[Ljava/lang/Object;)V
    //   276: aload 14
    //   278: astore 13
    //   280: getstatic 99	com/tencent/mm/sdk/platformtools/bm:ibz	J
    //   283: lconst_0
    //   284: lcmp
    //   285: ifge +33 -> 318
    //   288: aload 14
    //   290: astore 13
    //   292: lload_1
    //   293: putstatic 99	com/tencent/mm/sdk/platformtools/bm:ibz	J
    //   296: aload 14
    //   298: astore 13
    //   300: ldc -93
    //   302: ldc -79
    //   304: iconst_1
    //   305: anewarray 4	java/lang/Object
    //   308: dup
    //   309: iconst_0
    //   310: lload_1
    //   311: invokestatic 169	java/lang/Long:valueOf	(J)Ljava/lang/Long;
    //   314: aastore
    //   315: invokestatic 175	com/tencent/mm/sdk/platformtools/t:v	(Ljava/lang/String;Ljava/lang/String;[Ljava/lang/Object;)V
    //   318: aload 14
    //   320: astore 13
    //   322: getstatic 101	com/tencent/mm/sdk/platformtools/bm:ibA	J
    //   325: lconst_0
    //   326: lcmp
    //   327: ifge +35 -> 362
    //   330: aload 14
    //   332: astore 13
    //   334: lload 7
    //   336: putstatic 101	com/tencent/mm/sdk/platformtools/bm:ibA	J
    //   339: aload 14
    //   341: astore 13
    //   343: ldc -93
    //   345: ldc -77
    //   347: iconst_1
    //   348: anewarray 4	java/lang/Object
    //   351: dup
    //   352: iconst_0
    //   353: lload 7
    //   355: invokestatic 169	java/lang/Long:valueOf	(J)Ljava/lang/Long;
    //   358: aastore
    //   359: invokestatic 175	com/tencent/mm/sdk/platformtools/t:v	(Ljava/lang/String;Ljava/lang/String;[Ljava/lang/Object;)V
    //   362: aload 14
    //   364: astore 13
    //   366: getstatic 103	com/tencent/mm/sdk/platformtools/bm:ibB	J
    //   369: lconst_0
    //   370: lcmp
    //   371: ifge +35 -> 406
    //   374: aload 14
    //   376: astore 13
    //   378: lload 5
    //   380: putstatic 103	com/tencent/mm/sdk/platformtools/bm:ibB	J
    //   383: aload 14
    //   385: astore 13
    //   387: ldc -93
    //   389: ldc -75
    //   391: iconst_1
    //   392: anewarray 4	java/lang/Object
    //   395: dup
    //   396: iconst_0
    //   397: lload 5
    //   399: invokestatic 169	java/lang/Long:valueOf	(J)Ljava/lang/Long;
    //   402: aastore
    //   403: invokestatic 175	com/tencent/mm/sdk/platformtools/t:v	(Ljava/lang/String;Ljava/lang/String;[Ljava/lang/Object;)V
    //   406: aload 14
    //   408: astore 13
    //   410: lload 5
    //   412: getstatic 103	com/tencent/mm/sdk/platformtools/bm:ibB	J
    //   415: lsub
    //   416: lconst_0
    //   417: lcmp
    //   418: ifge +30 -> 448
    //   421: aload 14
    //   423: astore 13
    //   425: ldc -93
    //   427: ldc -73
    //   429: iconst_1
    //   430: anewarray 4	java/lang/Object
    //   433: dup
    //   434: iconst_0
    //   435: lload 5
    //   437: getstatic 103	com/tencent/mm/sdk/platformtools/bm:ibB	J
    //   440: lsub
    //   441: invokestatic 169	java/lang/Long:valueOf	(J)Ljava/lang/Long;
    //   444: aastore
    //   445: invokestatic 175	com/tencent/mm/sdk/platformtools/t:v	(Ljava/lang/String;Ljava/lang/String;[Ljava/lang/Object;)V
    //   448: aload 14
    //   450: astore 13
    //   452: lload 7
    //   454: getstatic 101	com/tencent/mm/sdk/platformtools/bm:ibA	J
    //   457: lsub
    //   458: lconst_0
    //   459: lcmp
    //   460: ifge +30 -> 490
    //   463: aload 14
    //   465: astore 13
    //   467: ldc -93
    //   469: ldc -73
    //   471: iconst_1
    //   472: anewarray 4	java/lang/Object
    //   475: dup
    //   476: iconst_0
    //   477: lload 7
    //   479: getstatic 101	com/tencent/mm/sdk/platformtools/bm:ibA	J
    //   482: lsub
    //   483: invokestatic 169	java/lang/Long:valueOf	(J)Ljava/lang/Long;
    //   486: aastore
    //   487: invokestatic 175	com/tencent/mm/sdk/platformtools/t:v	(Ljava/lang/String;Ljava/lang/String;[Ljava/lang/Object;)V
    //   490: aload 14
    //   492: astore 13
    //   494: lload_3
    //   495: getstatic 97	com/tencent/mm/sdk/platformtools/bm:iby	J
    //   498: lcmp
    //   499: iflt +825 -> 1324
    //   502: aload 14
    //   504: astore 13
    //   506: lload_3
    //   507: getstatic 97	com/tencent/mm/sdk/platformtools/bm:iby	J
    //   510: lsub
    //   511: lstore 9
    //   513: aload 14
    //   515: astore 13
    //   517: lload 9
    //   519: putstatic 77	com/tencent/mm/sdk/platformtools/bm:ibG	J
    //   522: aload 14
    //   524: astore 13
    //   526: lload_1
    //   527: getstatic 99	com/tencent/mm/sdk/platformtools/bm:ibz	J
    //   530: lcmp
    //   531: iflt +799 -> 1330
    //   534: aload 14
    //   536: astore 13
    //   538: lload_1
    //   539: getstatic 99	com/tencent/mm/sdk/platformtools/bm:ibz	J
    //   542: lsub
    //   543: lstore 9
    //   545: aload 14
    //   547: astore 13
    //   549: lload 9
    //   551: putstatic 80	com/tencent/mm/sdk/platformtools/bm:ibH	J
    //   554: aload 14
    //   556: astore 13
    //   558: lload 7
    //   560: getstatic 101	com/tencent/mm/sdk/platformtools/bm:ibA	J
    //   563: lcmp
    //   564: iflt +772 -> 1336
    //   567: aload 14
    //   569: astore 13
    //   571: lload 7
    //   573: getstatic 101	com/tencent/mm/sdk/platformtools/bm:ibA	J
    //   576: lsub
    //   577: lstore 9
    //   579: aload 14
    //   581: astore 13
    //   583: lload 9
    //   585: putstatic 71	com/tencent/mm/sdk/platformtools/bm:ibI	J
    //   588: aload 14
    //   590: astore 13
    //   592: lload 5
    //   594: getstatic 103	com/tencent/mm/sdk/platformtools/bm:ibB	J
    //   597: lcmp
    //   598: iflt +745 -> 1343
    //   601: aload 14
    //   603: astore 13
    //   605: lload 5
    //   607: getstatic 103	com/tencent/mm/sdk/platformtools/bm:ibB	J
    //   610: lsub
    //   611: lstore 9
    //   613: aload 14
    //   615: astore 13
    //   617: lload 9
    //   619: putstatic 74	com/tencent/mm/sdk/platformtools/bm:ibJ	J
    //   622: aload 14
    //   624: astore 13
    //   626: lload_3
    //   627: putstatic 97	com/tencent/mm/sdk/platformtools/bm:iby	J
    //   630: aload 14
    //   632: astore 13
    //   634: lload_1
    //   635: putstatic 99	com/tencent/mm/sdk/platformtools/bm:ibz	J
    //   638: aload 14
    //   640: astore 13
    //   642: lload 7
    //   644: putstatic 101	com/tencent/mm/sdk/platformtools/bm:ibA	J
    //   647: aload 14
    //   649: astore 13
    //   651: lload 5
    //   653: putstatic 103	com/tencent/mm/sdk/platformtools/bm:ibB	J
    //   656: getstatic 66	com/tencent/mm/sdk/platformtools/bm:ibP	Ljava/io/File;
    //   659: ifnull +641 -> 1300
    //   662: invokestatic 186	android/os/Process:myUid	()I
    //   665: istore_0
    //   666: new 118	java/util/Scanner
    //   669: dup
    //   670: getstatic 66	com/tencent/mm/sdk/platformtools/bm:ibP	Ljava/io/File;
    //   673: invokespecial 121	java/util/Scanner:<init>	(Ljava/io/File;)V
    //   676: astore 14
    //   678: aload 14
    //   680: astore 13
    //   682: aload 14
    //   684: invokevirtual 124	java/util/Scanner:nextLine	()Ljava/lang/String;
    //   687: pop
    //   688: lconst_0
    //   689: lstore 7
    //   691: lconst_0
    //   692: lstore 5
    //   694: lconst_0
    //   695: lstore_3
    //   696: lconst_0
    //   697: lstore_1
    //   698: aload 14
    //   700: astore 13
    //   702: aload 14
    //   704: invokevirtual 127	java/util/Scanner:hasNext	()Z
    //   707: ifeq +129 -> 836
    //   710: aload 14
    //   712: astore 13
    //   714: aload 14
    //   716: invokevirtual 124	java/util/Scanner:nextLine	()Ljava/lang/String;
    //   719: ldc -127
    //   721: invokevirtual 135	java/lang/String:split	(Ljava/lang/String;)[Ljava/lang/String;
    //   724: astore 15
    //   726: aload 14
    //   728: astore 13
    //   730: aload 15
    //   732: iconst_3
    //   733: aaload
    //   734: invokestatic 192	java/lang/Integer:parseInt	(Ljava/lang/String;)I
    //   737: iload_0
    //   738: if_icmpne -40 -> 698
    //   741: aload 15
    //   743: iconst_1
    //   744: aaload
    //   745: astore 16
    //   747: aload 14
    //   749: astore 13
    //   751: aload 15
    //   753: iconst_5
    //   754: aaload
    //   755: invokestatic 158	java/lang/Long:parseLong	(Ljava/lang/String;)J
    //   758: lstore 11
    //   760: aload 14
    //   762: astore 13
    //   764: aload 15
    //   766: bipush 7
    //   768: aaload
    //   769: invokestatic 158	java/lang/Long:parseLong	(Ljava/lang/String;)J
    //   772: lstore 9
    //   774: aload 14
    //   776: astore 13
    //   778: aload 16
    //   780: ldc -110
    //   782: invokevirtual 150	java/lang/String:startsWith	(Ljava/lang/String;)Z
    //   785: ifne +526 -> 1311
    //   788: aload 14
    //   790: astore 13
    //   792: aload 16
    //   794: ldc -104
    //   796: invokevirtual 150	java/lang/String:startsWith	(Ljava/lang/String;)Z
    //   799: ifeq +6 -> 805
    //   802: goto +509 -> 1311
    //   805: aload 14
    //   807: astore 13
    //   809: aload 16
    //   811: ldc -116
    //   813: invokevirtual 144	java/lang/String:equals	(Ljava/lang/Object;)Z
    //   816: ifne -118 -> 698
    //   819: lload 7
    //   821: lload 11
    //   823: ladd
    //   824: lstore 7
    //   826: lload 5
    //   828: lload 9
    //   830: ladd
    //   831: lstore 5
    //   833: goto -135 -> 698
    //   836: aload 14
    //   838: astore 13
    //   840: getstatic 105	com/tencent/mm/sdk/platformtools/bm:ibD	J
    //   843: lconst_0
    //   844: lcmp
    //   845: ifge +11 -> 856
    //   848: aload 14
    //   850: astore 13
    //   852: lload_3
    //   853: putstatic 105	com/tencent/mm/sdk/platformtools/bm:ibD	J
    //   856: aload 14
    //   858: astore 13
    //   860: getstatic 107	com/tencent/mm/sdk/platformtools/bm:ibC	J
    //   863: lconst_0
    //   864: lcmp
    //   865: ifge +11 -> 876
    //   868: aload 14
    //   870: astore 13
    //   872: lload_1
    //   873: putstatic 107	com/tencent/mm/sdk/platformtools/bm:ibC	J
    //   876: aload 14
    //   878: astore 13
    //   880: getstatic 109	com/tencent/mm/sdk/platformtools/bm:ibF	J
    //   883: lconst_0
    //   884: lcmp
    //   885: ifge +12 -> 897
    //   888: aload 14
    //   890: astore 13
    //   892: lload 7
    //   894: putstatic 109	com/tencent/mm/sdk/platformtools/bm:ibF	J
    //   897: aload 14
    //   899: astore 13
    //   901: getstatic 111	com/tencent/mm/sdk/platformtools/bm:ibE	J
    //   904: lconst_0
    //   905: lcmp
    //   906: ifge +12 -> 918
    //   909: aload 14
    //   911: astore 13
    //   913: lload 5
    //   915: putstatic 111	com/tencent/mm/sdk/platformtools/bm:ibE	J
    //   918: aload 14
    //   920: astore 13
    //   922: lload_1
    //   923: getstatic 107	com/tencent/mm/sdk/platformtools/bm:ibC	J
    //   926: lcmp
    //   927: iflt +254 -> 1181
    //   930: aload 14
    //   932: astore 13
    //   934: lload_1
    //   935: getstatic 107	com/tencent/mm/sdk/platformtools/bm:ibC	J
    //   938: lsub
    //   939: lstore 9
    //   941: aload 14
    //   943: astore 13
    //   945: lload 9
    //   947: putstatic 89	com/tencent/mm/sdk/platformtools/bm:ibK	J
    //   950: aload 14
    //   952: astore 13
    //   954: lload_3
    //   955: getstatic 105	com/tencent/mm/sdk/platformtools/bm:ibD	J
    //   958: lcmp
    //   959: iflt +228 -> 1187
    //   962: aload 14
    //   964: astore 13
    //   966: lload_3
    //   967: getstatic 105	com/tencent/mm/sdk/platformtools/bm:ibD	J
    //   970: lsub
    //   971: lstore 9
    //   973: aload 14
    //   975: astore 13
    //   977: lload 9
    //   979: putstatic 92	com/tencent/mm/sdk/platformtools/bm:ibL	J
    //   982: aload 14
    //   984: astore 13
    //   986: lload 5
    //   988: getstatic 111	com/tencent/mm/sdk/platformtools/bm:ibE	J
    //   991: lcmp
    //   992: iflt +201 -> 1193
    //   995: aload 14
    //   997: astore 13
    //   999: lload 5
    //   1001: getstatic 111	com/tencent/mm/sdk/platformtools/bm:ibE	J
    //   1004: lsub
    //   1005: lstore 9
    //   1007: aload 14
    //   1009: astore 13
    //   1011: lload 9
    //   1013: putstatic 83	com/tencent/mm/sdk/platformtools/bm:ibM	J
    //   1016: aload 14
    //   1018: astore 13
    //   1020: lload 7
    //   1022: getstatic 109	com/tencent/mm/sdk/platformtools/bm:ibF	J
    //   1025: lcmp
    //   1026: iflt +174 -> 1200
    //   1029: aload 14
    //   1031: astore 13
    //   1033: lload 7
    //   1035: getstatic 109	com/tencent/mm/sdk/platformtools/bm:ibF	J
    //   1038: lsub
    //   1039: lstore 9
    //   1041: aload 14
    //   1043: astore 13
    //   1045: lload 9
    //   1047: putstatic 86	com/tencent/mm/sdk/platformtools/bm:ibN	J
    //   1050: aload 14
    //   1052: astore 13
    //   1054: lload_1
    //   1055: putstatic 107	com/tencent/mm/sdk/platformtools/bm:ibC	J
    //   1058: aload 14
    //   1060: astore 13
    //   1062: lload_3
    //   1063: putstatic 105	com/tencent/mm/sdk/platformtools/bm:ibD	J
    //   1066: aload 14
    //   1068: astore 13
    //   1070: lload 5
    //   1072: putstatic 111	com/tencent/mm/sdk/platformtools/bm:ibE	J
    //   1075: aload 14
    //   1077: astore 13
    //   1079: lload 7
    //   1081: putstatic 109	com/tencent/mm/sdk/platformtools/bm:ibF	J
    //   1084: aload 14
    //   1086: ifnull +8 -> 1094
    //   1089: aload 14
    //   1091: invokevirtual 161	java/util/Scanner:close	()V
    //   1094: ldc -93
    //   1096: ldc -62
    //   1098: bipush 8
    //   1100: anewarray 4	java/lang/Object
    //   1103: dup
    //   1104: iconst_0
    //   1105: getstatic 74	com/tencent/mm/sdk/platformtools/bm:ibJ	J
    //   1108: invokestatic 169	java/lang/Long:valueOf	(J)Ljava/lang/Long;
    //   1111: aastore
    //   1112: dup
    //   1113: iconst_1
    //   1114: getstatic 71	com/tencent/mm/sdk/platformtools/bm:ibI	J
    //   1117: invokestatic 169	java/lang/Long:valueOf	(J)Ljava/lang/Long;
    //   1120: aastore
    //   1121: dup
    //   1122: iconst_2
    //   1123: getstatic 80	com/tencent/mm/sdk/platformtools/bm:ibH	J
    //   1126: invokestatic 169	java/lang/Long:valueOf	(J)Ljava/lang/Long;
    //   1129: aastore
    //   1130: dup
    //   1131: iconst_3
    //   1132: getstatic 77	com/tencent/mm/sdk/platformtools/bm:ibG	J
    //   1135: invokestatic 169	java/lang/Long:valueOf	(J)Ljava/lang/Long;
    //   1138: aastore
    //   1139: dup
    //   1140: iconst_4
    //   1141: getstatic 86	com/tencent/mm/sdk/platformtools/bm:ibN	J
    //   1144: invokestatic 169	java/lang/Long:valueOf	(J)Ljava/lang/Long;
    //   1147: aastore
    //   1148: dup
    //   1149: iconst_5
    //   1150: getstatic 83	com/tencent/mm/sdk/platformtools/bm:ibM	J
    //   1153: invokestatic 169	java/lang/Long:valueOf	(J)Ljava/lang/Long;
    //   1156: aastore
    //   1157: dup
    //   1158: bipush 6
    //   1160: getstatic 92	com/tencent/mm/sdk/platformtools/bm:ibL	J
    //   1163: invokestatic 169	java/lang/Long:valueOf	(J)Ljava/lang/Long;
    //   1166: aastore
    //   1167: dup
    //   1168: bipush 7
    //   1170: getstatic 89	com/tencent/mm/sdk/platformtools/bm:ibK	J
    //   1173: invokestatic 169	java/lang/Long:valueOf	(J)Ljava/lang/Long;
    //   1176: aastore
    //   1177: invokestatic 197	com/tencent/mm/sdk/platformtools/t:d	(Ljava/lang/String;Ljava/lang/String;[Ljava/lang/Object;)V
    //   1180: return
    //   1181: lload_1
    //   1182: lstore 9
    //   1184: goto -243 -> 941
    //   1187: lload_3
    //   1188: lstore 9
    //   1190: goto -217 -> 973
    //   1193: lload 5
    //   1195: lstore 9
    //   1197: goto -190 -> 1007
    //   1200: lload 7
    //   1202: lstore 9
    //   1204: goto -163 -> 1041
    //   1207: aconst_null
    //   1208: astore 13
    //   1210: astore 14
    //   1212: ldc -93
    //   1214: aload 14
    //   1216: ldc -57
    //   1218: iconst_0
    //   1219: anewarray 4	java/lang/Object
    //   1222: invokestatic 203	com/tencent/mm/sdk/platformtools/t:printErrStackTrace	(Ljava/lang/String;Ljava/lang/Throwable;Ljava/lang/String;[Ljava/lang/Object;)V
    //   1225: aload 13
    //   1227: ifnull -133 -> 1094
    //   1230: aload 13
    //   1232: invokevirtual 161	java/util/Scanner:close	()V
    //   1235: goto -141 -> 1094
    //   1238: astore 14
    //   1240: aconst_null
    //   1241: astore 13
    //   1243: aload 13
    //   1245: ifnull +8 -> 1253
    //   1248: aload 13
    //   1250: invokevirtual 161	java/util/Scanner:close	()V
    //   1253: aload 14
    //   1255: athrow
    //   1256: astore 14
    //   1258: goto -15 -> 1243
    //   1261: astore 14
    //   1263: goto -20 -> 1243
    //   1266: astore 15
    //   1268: aload 14
    //   1270: astore 13
    //   1272: aload 15
    //   1274: astore 14
    //   1276: goto -64 -> 1212
    //   1279: astore 14
    //   1281: aconst_null
    //   1282: astore 13
    //   1284: goto -72 -> 1212
    //   1287: astore 15
    //   1289: aload 14
    //   1291: astore 13
    //   1293: aload 15
    //   1295: astore 14
    //   1297: goto -85 -> 1212
    //   1300: aconst_null
    //   1301: astore 14
    //   1303: goto -219 -> 1084
    //   1306: iconst_0
    //   1307: istore_0
    //   1308: goto -1216 -> 92
    //   1311: lload_3
    //   1312: lload 11
    //   1314: ladd
    //   1315: lstore_3
    //   1316: lload_1
    //   1317: lload 9
    //   1319: ladd
    //   1320: lstore_1
    //   1321: goto -623 -> 698
    //   1324: lload_3
    //   1325: lstore 9
    //   1327: goto -814 -> 513
    //   1330: lload_1
    //   1331: lstore 9
    //   1333: goto -788 -> 545
    //   1336: lload 7
    //   1338: lstore 9
    //   1340: goto -761 -> 579
    //   1343: lload 5
    //   1345: lstore 9
    //   1347: goto -734 -> 613
    // Local variable table:
    //   start	length	slot	name	signature
    //   91	1217	0	i	int
    //   3	1328	1	l1	long
    //   1	1324	3	l2	long
    //   43	1301	5	l3	long
    //   46	1291	7	l4	long
    //   511	835	9	l5	long
    //   758	555	11	l6	long
    //   24	1268	13	localObject1	Object
    //   20	1070	14	localScanner	java.util.Scanner
    //   1210	5	14	localException1	Exception
    //   1238	16	14	localObject2	Object
    //   1256	1	14	localObject3	Object
    //   1261	8	14	localObject4	Object
    //   1274	1	14	localObject5	Object
    //   1279	11	14	localException2	Exception
    //   1295	7	14	localObject6	Object
    //   74	691	15	arrayOfString	String[]
    //   1266	7	15	localException3	Exception
    //   1287	7	15	localException4	Exception
    //   745	65	16	str	String
    // Exception table:
    //   from	to	target	type
    //   4	22	1207	java/lang/Exception
    //   656	678	1207	java/lang/Exception
    //   4	22	1238	finally
    //   656	678	1238	finally
    //   26	32	1256	finally
    //   36	42	1256	finally
    //   52	60	1256	finally
    //   64	76	1256	finally
    //   80	90	1256	finally
    //   96	110	1256	finally
    //   114	128	1256	finally
    //   132	146	1256	finally
    //   150	163	1256	finally
    //   167	179	1256	finally
    //   186	201	1256	finally
    //   205	219	1256	finally
    //   226	231	1256	finally
    //   238	246	1256	finally
    //   250	254	1256	finally
    //   258	276	1256	finally
    //   280	288	1256	finally
    //   292	296	1256	finally
    //   300	318	1256	finally
    //   322	330	1256	finally
    //   334	339	1256	finally
    //   343	362	1256	finally
    //   366	374	1256	finally
    //   378	383	1256	finally
    //   387	406	1256	finally
    //   410	421	1256	finally
    //   425	448	1256	finally
    //   452	463	1256	finally
    //   467	490	1256	finally
    //   494	502	1256	finally
    //   506	513	1256	finally
    //   517	522	1256	finally
    //   526	534	1256	finally
    //   538	545	1256	finally
    //   549	554	1256	finally
    //   558	567	1256	finally
    //   571	579	1256	finally
    //   583	588	1256	finally
    //   592	601	1256	finally
    //   605	613	1256	finally
    //   617	622	1256	finally
    //   626	630	1256	finally
    //   634	638	1256	finally
    //   642	647	1256	finally
    //   651	656	1256	finally
    //   682	688	1256	finally
    //   702	710	1256	finally
    //   714	726	1256	finally
    //   730	741	1256	finally
    //   751	760	1256	finally
    //   764	774	1256	finally
    //   778	788	1256	finally
    //   792	802	1256	finally
    //   809	819	1256	finally
    //   840	848	1256	finally
    //   852	856	1256	finally
    //   860	868	1256	finally
    //   872	876	1256	finally
    //   880	888	1256	finally
    //   892	897	1256	finally
    //   901	909	1256	finally
    //   913	918	1256	finally
    //   922	930	1256	finally
    //   934	941	1256	finally
    //   945	950	1256	finally
    //   954	962	1256	finally
    //   966	973	1256	finally
    //   977	982	1256	finally
    //   986	995	1256	finally
    //   999	1007	1256	finally
    //   1011	1016	1256	finally
    //   1020	1029	1256	finally
    //   1033	1041	1256	finally
    //   1045	1050	1256	finally
    //   1054	1058	1256	finally
    //   1062	1066	1256	finally
    //   1070	1075	1256	finally
    //   1079	1084	1256	finally
    //   1212	1225	1261	finally
    //   26	32	1266	java/lang/Exception
    //   36	42	1266	java/lang/Exception
    //   52	60	1266	java/lang/Exception
    //   64	76	1266	java/lang/Exception
    //   80	90	1266	java/lang/Exception
    //   96	110	1266	java/lang/Exception
    //   114	128	1266	java/lang/Exception
    //   132	146	1266	java/lang/Exception
    //   150	163	1266	java/lang/Exception
    //   167	179	1266	java/lang/Exception
    //   186	201	1266	java/lang/Exception
    //   205	219	1266	java/lang/Exception
    //   226	231	1266	java/lang/Exception
    //   238	246	1279	java/lang/Exception
    //   250	254	1279	java/lang/Exception
    //   258	276	1279	java/lang/Exception
    //   280	288	1279	java/lang/Exception
    //   292	296	1279	java/lang/Exception
    //   300	318	1279	java/lang/Exception
    //   322	330	1279	java/lang/Exception
    //   334	339	1279	java/lang/Exception
    //   343	362	1279	java/lang/Exception
    //   366	374	1279	java/lang/Exception
    //   378	383	1279	java/lang/Exception
    //   387	406	1279	java/lang/Exception
    //   410	421	1279	java/lang/Exception
    //   425	448	1279	java/lang/Exception
    //   452	463	1279	java/lang/Exception
    //   467	490	1279	java/lang/Exception
    //   494	502	1279	java/lang/Exception
    //   506	513	1279	java/lang/Exception
    //   517	522	1279	java/lang/Exception
    //   526	534	1279	java/lang/Exception
    //   538	545	1279	java/lang/Exception
    //   549	554	1279	java/lang/Exception
    //   558	567	1279	java/lang/Exception
    //   571	579	1279	java/lang/Exception
    //   583	588	1279	java/lang/Exception
    //   592	601	1279	java/lang/Exception
    //   605	613	1279	java/lang/Exception
    //   617	622	1279	java/lang/Exception
    //   626	630	1279	java/lang/Exception
    //   634	638	1279	java/lang/Exception
    //   642	647	1279	java/lang/Exception
    //   651	656	1279	java/lang/Exception
    //   682	688	1287	java/lang/Exception
    //   702	710	1287	java/lang/Exception
    //   714	726	1287	java/lang/Exception
    //   730	741	1287	java/lang/Exception
    //   751	760	1287	java/lang/Exception
    //   764	774	1287	java/lang/Exception
    //   778	788	1287	java/lang/Exception
    //   792	802	1287	java/lang/Exception
    //   809	819	1287	java/lang/Exception
    //   840	848	1287	java/lang/Exception
    //   852	856	1287	java/lang/Exception
    //   860	868	1287	java/lang/Exception
    //   872	876	1287	java/lang/Exception
    //   880	888	1287	java/lang/Exception
    //   892	897	1287	java/lang/Exception
    //   901	909	1287	java/lang/Exception
    //   913	918	1287	java/lang/Exception
    //   922	930	1287	java/lang/Exception
    //   934	941	1287	java/lang/Exception
    //   945	950	1287	java/lang/Exception
    //   954	962	1287	java/lang/Exception
    //   966	973	1287	java/lang/Exception
    //   977	982	1287	java/lang/Exception
    //   986	995	1287	java/lang/Exception
    //   999	1007	1287	java/lang/Exception
    //   1011	1016	1287	java/lang/Exception
    //   1020	1029	1287	java/lang/Exception
    //   1033	1041	1287	java/lang/Exception
    //   1045	1050	1287	java/lang/Exception
    //   1054	1058	1287	java/lang/Exception
    //   1062	1066	1287	java/lang/Exception
    //   1070	1075	1287	java/lang/Exception
    //   1079	1084	1287	java/lang/Exception
  }
}

/* Location:
 * Qualified Name:     com.tencent.mm.sdk.platformtools.bm
 * Java Class Version: 6 (50.0)
 * JD-Core Version:    0.7.1
 */