package com.tencent.mm.an;

final class n$2
  implements Runnable
{
  n$2(n paramn, String paramString1, String paramString2, String paramString3) {}
  
  /* Error */
  public final void run()
  {
    // Byte code:
    //   0: invokestatic 37	com/tencent/mm/sdk/platformtools/ay:FS	()J
    //   3: lstore 10
    //   5: aload_0
    //   6: getfield 20	com/tencent/mm/an/n$2:cgk	Ljava/lang/String;
    //   9: invokestatic 43	com/tencent/mm/a/e:aw	(Ljava/lang/String;)I
    //   12: istore 6
    //   14: aload_0
    //   15: getfield 22	com/tencent/mm/an/n$2:cgl	Ljava/lang/String;
    //   18: invokestatic 43	com/tencent/mm/a/e:aw	(Ljava/lang/String;)I
    //   21: istore_1
    //   22: iload_1
    //   23: iload 6
    //   25: if_icmpeq +89 -> 114
    //   28: getstatic 49	com/tencent/mm/plugin/report/service/h:fUJ	Lcom/tencent/mm/plugin/report/service/h;
    //   31: sipush 12696
    //   34: iconst_5
    //   35: anewarray 4	java/lang/Object
    //   38: dup
    //   39: iconst_0
    //   40: bipush 106
    //   42: invokestatic 55	java/lang/Integer:valueOf	(I)Ljava/lang/Integer;
    //   45: aastore
    //   46: dup
    //   47: iconst_1
    //   48: aload_0
    //   49: getfield 24	com/tencent/mm/an/n$2:cgm	Ljava/lang/String;
    //   52: aastore
    //   53: dup
    //   54: iconst_2
    //   55: ldc 57
    //   57: aastore
    //   58: dup
    //   59: iconst_3
    //   60: ldc 57
    //   62: aastore
    //   63: dup
    //   64: iconst_4
    //   65: iload_1
    //   66: invokestatic 55	java/lang/Integer:valueOf	(I)Ljava/lang/Integer;
    //   69: aastore
    //   70: invokevirtual 61	com/tencent/mm/plugin/report/service/h:g	(I[Ljava/lang/Object;)V
    //   73: ldc 63
    //   75: ldc 65
    //   77: iconst_4
    //   78: anewarray 4	java/lang/Object
    //   81: dup
    //   82: iconst_0
    //   83: iload 6
    //   85: invokestatic 55	java/lang/Integer:valueOf	(I)Ljava/lang/Integer;
    //   88: aastore
    //   89: dup
    //   90: iconst_1
    //   91: iload_1
    //   92: invokestatic 55	java/lang/Integer:valueOf	(I)Ljava/lang/Integer;
    //   95: aastore
    //   96: dup
    //   97: iconst_2
    //   98: aload_0
    //   99: getfield 20	com/tencent/mm/an/n$2:cgk	Ljava/lang/String;
    //   102: aastore
    //   103: dup
    //   104: iconst_3
    //   105: aload_0
    //   106: getfield 22	com/tencent/mm/an/n$2:cgl	Ljava/lang/String;
    //   109: aastore
    //   110: invokestatic 71	com/tencent/mm/sdk/platformtools/u:e	(Ljava/lang/String;Ljava/lang/String;[Ljava/lang/Object;)V
    //   113: return
    //   114: bipush 6
    //   116: newarray <illegal type>
    //   118: astore 16
    //   120: aconst_null
    //   121: astore 15
    //   123: aconst_null
    //   124: astore 14
    //   126: new 73	java/io/FileInputStream
    //   129: dup
    //   130: aload_0
    //   131: getfield 20	com/tencent/mm/an/n$2:cgk	Ljava/lang/String;
    //   134: invokespecial 76	java/io/FileInputStream:<init>	(Ljava/lang/String;)V
    //   137: astore 12
    //   139: new 73	java/io/FileInputStream
    //   142: dup
    //   143: aload_0
    //   144: getfield 22	com/tencent/mm/an/n$2:cgl	Ljava/lang/String;
    //   147: invokespecial 76	java/io/FileInputStream:<init>	(Ljava/lang/String;)V
    //   150: astore 13
    //   152: iload 6
    //   154: sipush 4096
    //   157: idiv
    //   158: istore 7
    //   160: iload 6
    //   162: sipush 4096
    //   165: irem
    //   166: ifne +139 -> 305
    //   169: iconst_0
    //   170: istore_2
    //   171: sipush 4096
    //   174: newarray <illegal type>
    //   176: astore 14
    //   178: sipush 4096
    //   181: newarray <illegal type>
    //   183: astore 15
    //   185: iconst_0
    //   186: istore_1
    //   187: iconst_0
    //   188: istore_3
    //   189: iload_3
    //   190: iload 7
    //   192: iload_2
    //   193: iadd
    //   194: if_icmpge +190 -> 384
    //   197: iload_3
    //   198: sipush 4096
    //   201: imul
    //   202: istore 8
    //   204: aload 12
    //   206: aload 14
    //   208: iconst_0
    //   209: sipush 4096
    //   212: invokevirtual 80	java/io/FileInputStream:read	([BII)I
    //   215: istore 9
    //   217: iload 9
    //   219: aload 13
    //   221: aload 15
    //   223: iconst_0
    //   224: sipush 4096
    //   227: invokevirtual 80	java/io/FileInputStream:read	([BII)I
    //   230: if_icmpeq +80 -> 310
    //   233: ldc 63
    //   235: ldc 82
    //   237: iconst_2
    //   238: anewarray 4	java/lang/Object
    //   241: dup
    //   242: iconst_0
    //   243: iload 8
    //   245: invokestatic 55	java/lang/Integer:valueOf	(I)Ljava/lang/Integer;
    //   248: aastore
    //   249: dup
    //   250: iconst_1
    //   251: iload 9
    //   253: invokestatic 55	java/lang/Integer:valueOf	(I)Ljava/lang/Integer;
    //   256: aastore
    //   257: invokestatic 71	com/tencent/mm/sdk/platformtools/u:e	(Ljava/lang/String;Ljava/lang/String;[Ljava/lang/Object;)V
    //   260: iconst_1
    //   261: istore_2
    //   262: aload 13
    //   264: invokevirtual 85	java/io/FileInputStream:close	()V
    //   267: aload 12
    //   269: invokevirtual 85	java/io/FileInputStream:close	()V
    //   272: iload_2
    //   273: ifeq +152 -> 425
    //   276: getstatic 49	com/tencent/mm/plugin/report/service/h:fUJ	Lcom/tencent/mm/plugin/report/service/h;
    //   279: sipush 12696
    //   282: iconst_2
    //   283: anewarray 4	java/lang/Object
    //   286: dup
    //   287: iconst_0
    //   288: bipush 107
    //   290: invokestatic 55	java/lang/Integer:valueOf	(I)Ljava/lang/Integer;
    //   293: aastore
    //   294: dup
    //   295: iconst_1
    //   296: aload_0
    //   297: getfield 24	com/tencent/mm/an/n$2:cgm	Ljava/lang/String;
    //   300: aastore
    //   301: invokevirtual 61	com/tencent/mm/plugin/report/service/h:g	(I[Ljava/lang/Object;)V
    //   304: return
    //   305: iconst_1
    //   306: istore_2
    //   307: goto -136 -> 171
    //   310: iconst_0
    //   311: istore 4
    //   313: iload 4
    //   315: iload 9
    //   317: if_icmpge +60 -> 377
    //   320: iload_1
    //   321: istore 5
    //   323: aload 14
    //   325: iload 4
    //   327: baload
    //   328: aload 15
    //   330: iload 4
    //   332: baload
    //   333: if_icmpeq +32 -> 365
    //   336: iload 8
    //   338: iload 4
    //   340: iadd
    //   341: iconst_5
    //   342: imul
    //   343: iload 6
    //   345: idiv
    //   346: istore 5
    //   348: aload 16
    //   350: iload 5
    //   352: aload 16
    //   354: iload 5
    //   356: iaload
    //   357: iconst_1
    //   358: iadd
    //   359: iastore
    //   360: iload_1
    //   361: iconst_1
    //   362: iadd
    //   363: istore 5
    //   365: iload 4
    //   367: iconst_1
    //   368: iadd
    //   369: istore 4
    //   371: iload 5
    //   373: istore_1
    //   374: goto -61 -> 313
    //   377: iload_3
    //   378: iconst_1
    //   379: iadd
    //   380: istore_3
    //   381: goto -192 -> 189
    //   384: iconst_0
    //   385: istore_2
    //   386: goto -124 -> 262
    //   389: astore 13
    //   391: iconst_0
    //   392: istore_1
    //   393: aload 15
    //   395: astore 12
    //   397: ldc 63
    //   399: ldc 87
    //   401: iconst_1
    //   402: anewarray 4	java/lang/Object
    //   405: dup
    //   406: iconst_0
    //   407: aload 13
    //   409: invokestatic 91	com/tencent/mm/sdk/platformtools/ay:b	(Ljava/lang/Throwable;)Ljava/lang/String;
    //   412: aastore
    //   413: invokestatic 71	com/tencent/mm/sdk/platformtools/u:e	(Ljava/lang/String;Ljava/lang/String;[Ljava/lang/Object;)V
    //   416: iconst_1
    //   417: istore_2
    //   418: aload 14
    //   420: astore 13
    //   422: goto -160 -> 262
    //   425: new 93	java/lang/StringBuffer
    //   428: dup
    //   429: invokespecial 94	java/lang/StringBuffer:<init>	()V
    //   432: astore 12
    //   434: aload 12
    //   436: iload_1
    //   437: invokevirtual 98	java/lang/StringBuffer:append	(I)Ljava/lang/StringBuffer;
    //   440: pop
    //   441: iconst_0
    //   442: istore_1
    //   443: iload_1
    //   444: bipush 6
    //   446: if_icmpge +28 -> 474
    //   449: aload 12
    //   451: ldc 100
    //   453: invokevirtual 103	java/lang/StringBuffer:append	(Ljava/lang/String;)Ljava/lang/StringBuffer;
    //   456: pop
    //   457: aload 12
    //   459: aload 16
    //   461: iload_1
    //   462: iaload
    //   463: invokevirtual 98	java/lang/StringBuffer:append	(I)Ljava/lang/StringBuffer;
    //   466: pop
    //   467: iload_1
    //   468: iconst_1
    //   469: iadd
    //   470: istore_1
    //   471: goto -28 -> 443
    //   474: lload 10
    //   476: invokestatic 107	com/tencent/mm/sdk/platformtools/ay:an	(J)J
    //   479: lstore 10
    //   481: getstatic 49	com/tencent/mm/plugin/report/service/h:fUJ	Lcom/tencent/mm/plugin/report/service/h;
    //   484: sipush 12696
    //   487: iconst_4
    //   488: anewarray 4	java/lang/Object
    //   491: dup
    //   492: iconst_0
    //   493: sipush 400
    //   496: invokestatic 55	java/lang/Integer:valueOf	(I)Ljava/lang/Integer;
    //   499: aastore
    //   500: dup
    //   501: iconst_1
    //   502: aload_0
    //   503: getfield 24	com/tencent/mm/an/n$2:cgm	Ljava/lang/String;
    //   506: aastore
    //   507: dup
    //   508: iconst_2
    //   509: aload 12
    //   511: invokevirtual 111	java/lang/StringBuffer:toString	()Ljava/lang/String;
    //   514: aastore
    //   515: dup
    //   516: iconst_3
    //   517: lload 10
    //   519: invokestatic 116	java/lang/Long:valueOf	(J)Ljava/lang/Long;
    //   522: aastore
    //   523: invokevirtual 61	com/tencent/mm/plugin/report/service/h:g	(I[Ljava/lang/Object;)V
    //   526: ldc 63
    //   528: ldc 118
    //   530: iconst_4
    //   531: anewarray 4	java/lang/Object
    //   534: dup
    //   535: iconst_0
    //   536: lload 10
    //   538: invokestatic 116	java/lang/Long:valueOf	(J)Ljava/lang/Long;
    //   541: aastore
    //   542: dup
    //   543: iconst_1
    //   544: aload 12
    //   546: invokevirtual 111	java/lang/StringBuffer:toString	()Ljava/lang/String;
    //   549: aastore
    //   550: dup
    //   551: iconst_2
    //   552: aload_0
    //   553: getfield 20	com/tencent/mm/an/n$2:cgk	Ljava/lang/String;
    //   556: aastore
    //   557: dup
    //   558: iconst_3
    //   559: aload_0
    //   560: getfield 22	com/tencent/mm/an/n$2:cgl	Ljava/lang/String;
    //   563: aastore
    //   564: invokestatic 121	com/tencent/mm/sdk/platformtools/u:i	(Ljava/lang/String;Ljava/lang/String;[Ljava/lang/Object;)V
    //   567: return
    //   568: astore 13
    //   570: goto -303 -> 267
    //   573: astore 12
    //   575: goto -303 -> 272
    //   578: astore 13
    //   580: iconst_0
    //   581: istore_1
    //   582: goto -185 -> 397
    //   585: astore 15
    //   587: aload 13
    //   589: astore 14
    //   591: iconst_0
    //   592: istore_1
    //   593: aload 15
    //   595: astore 13
    //   597: goto -200 -> 397
    //   600: astore 15
    //   602: aload 13
    //   604: astore 14
    //   606: aload 15
    //   608: astore 13
    //   610: goto -213 -> 397
    //   613: astore 15
    //   615: aload 13
    //   617: astore 14
    //   619: aload 15
    //   621: astore 13
    //   623: goto -226 -> 397
    // Local variable table:
    //   start	length	slot	name	signature
    //   0	626	0	this	2
    //   21	572	1	i	int
    //   170	248	2	j	int
    //   188	193	3	k	int
    //   311	59	4	m	int
    //   321	51	5	n	int
    //   12	334	6	i1	int
    //   158	36	7	i2	int
    //   202	139	8	i3	int
    //   215	103	9	i4	int
    //   3	534	10	l	long
    //   137	408	12	localObject1	Object
    //   573	1	12	localException1	Exception
    //   150	113	13	localFileInputStream	java.io.FileInputStream
    //   389	19	13	localException2	Exception
    //   420	1	13	localObject2	Object
    //   568	1	13	localException3	Exception
    //   578	10	13	localException4	Exception
    //   595	27	13	localException5	Exception
    //   124	494	14	localObject3	Object
    //   121	273	15	arrayOfByte	byte[]
    //   585	9	15	localException6	Exception
    //   600	7	15	localException7	Exception
    //   613	7	15	localException8	Exception
    //   118	342	16	arrayOfInt	int[]
    // Exception table:
    //   from	to	target	type
    //   126	139	389	java/lang/Exception
    //   262	267	568	java/lang/Exception
    //   267	272	573	java/lang/Exception
    //   139	152	578	java/lang/Exception
    //   152	160	585	java/lang/Exception
    //   171	185	585	java/lang/Exception
    //   204	260	600	java/lang/Exception
    //   336	348	613	java/lang/Exception
  }
}

/* Location:
 * Qualified Name:     com.tencent.mm.an.n.2
 * Java Class Version: 6 (50.0)
 * JD-Core Version:    0.7.1
 */