package com.tencent.mm.ui.g;

final class b$4
  implements Runnable
{
  b$4(b paramb, String paramString, long paramLong) {}
  
  /* Error */
  public final void run()
  {
    // Byte code:
    //   0: aload_0
    //   1: getfield 18	com/tencent/mm/ui/g/b$4:lAu	Lcom/tencent/mm/ui/g/b;
    //   4: astore 4
    //   6: new 33	java/lang/StringBuilder
    //   9: dup
    //   10: invokespecial 34	java/lang/StringBuilder:<init>	()V
    //   13: invokestatic 38	com/tencent/mm/ui/g/b:bjf	()Ljava/lang/String;
    //   16: invokevirtual 42	java/lang/StringBuilder:append	(Ljava/lang/String;)Ljava/lang/StringBuilder;
    //   19: ldc 44
    //   21: invokevirtual 42	java/lang/StringBuilder:append	(Ljava/lang/String;)Ljava/lang/StringBuilder;
    //   24: invokevirtual 47	java/lang/StringBuilder:toString	()Ljava/lang/String;
    //   27: astore_1
    //   28: new 33	java/lang/StringBuilder
    //   31: dup
    //   32: invokespecial 34	java/lang/StringBuilder:<init>	()V
    //   35: aload_0
    //   36: getfield 20	com/tencent/mm/ui/g/b$4:lAv	Ljava/lang/String;
    //   39: invokevirtual 42	java/lang/StringBuilder:append	(Ljava/lang/String;)Ljava/lang/StringBuilder;
    //   42: ldc 49
    //   44: invokevirtual 42	java/lang/StringBuilder:append	(Ljava/lang/String;)Ljava/lang/StringBuilder;
    //   47: aload_0
    //   48: getfield 22	com/tencent/mm/ui/g/b$4:lAw	J
    //   51: invokevirtual 52	java/lang/StringBuilder:append	(J)Ljava/lang/StringBuilder;
    //   54: ldc 54
    //   56: invokevirtual 42	java/lang/StringBuilder:append	(Ljava/lang/String;)Ljava/lang/StringBuilder;
    //   59: invokevirtual 47	java/lang/StringBuilder:toString	()Ljava/lang/String;
    //   62: astore_3
    //   63: invokestatic 60	com/tencent/mm/compatible/util/e:oW	()Z
    //   66: ifne +11 -> 77
    //   69: ldc 62
    //   71: ldc 64
    //   73: invokestatic 70	com/tencent/mm/sdk/platformtools/u:i	(Ljava/lang/String;Ljava/lang/String;)V
    //   76: return
    //   77: new 72	java/io/File
    //   80: dup
    //   81: getstatic 75	com/tencent/mm/ui/g/b:lAk	Ljava/lang/String;
    //   84: invokespecial 78	java/io/File:<init>	(Ljava/lang/String;)V
    //   87: astore_2
    //   88: aload_2
    //   89: invokevirtual 81	java/io/File:exists	()Z
    //   92: ifne +8 -> 100
    //   95: aload_2
    //   96: invokevirtual 84	java/io/File:mkdirs	()Z
    //   99: pop
    //   100: aload 4
    //   102: new 72	java/io/File
    //   105: dup
    //   106: getstatic 75	com/tencent/mm/ui/g/b:lAk	Ljava/lang/String;
    //   109: ldc 44
    //   111: invokespecial 86	java/io/File:<init>	(Ljava/lang/String;Ljava/lang/String;)V
    //   114: iconst_0
    //   115: invokevirtual 90	com/tencent/mm/ui/g/b:c	(Ljava/io/File;Z)V
    //   118: new 72	java/io/File
    //   121: dup
    //   122: aload_1
    //   123: invokespecial 78	java/io/File:<init>	(Ljava/lang/String;)V
    //   126: astore_2
    //   127: aload_2
    //   128: invokevirtual 94	java/io/File:length	()J
    //   131: aload 4
    //   133: getfield 97	com/tencent/mm/ui/g/b:lAp	J
    //   136: lcmp
    //   137: ifle +17 -> 154
    //   140: ldc 62
    //   142: ldc 99
    //   144: invokestatic 102	com/tencent/mm/sdk/platformtools/u:e	(Ljava/lang/String;Ljava/lang/String;)V
    //   147: aload 4
    //   149: aload_2
    //   150: iconst_1
    //   151: invokevirtual 90	com/tencent/mm/ui/g/b:c	(Ljava/io/File;Z)V
    //   154: new 104	java/io/RandomAccessFile
    //   157: dup
    //   158: aload_1
    //   159: ldc 106
    //   161: invokespecial 107	java/io/RandomAccessFile:<init>	(Ljava/lang/String;Ljava/lang/String;)V
    //   164: astore_2
    //   165: aload_2
    //   166: astore_1
    //   167: aload_2
    //   168: aload_2
    //   169: invokevirtual 108	java/io/RandomAccessFile:length	()J
    //   172: invokevirtual 112	java/io/RandomAccessFile:seek	(J)V
    //   175: aload_2
    //   176: astore_1
    //   177: aload_2
    //   178: aload_3
    //   179: invokevirtual 118	java/lang/String:getBytes	()[B
    //   182: invokestatic 124	com/tencent/mm/ba/d:aX	([B)[B
    //   185: invokevirtual 128	java/io/RandomAccessFile:write	([B)V
    //   188: aload_2
    //   189: invokevirtual 131	java/io/RandomAccessFile:close	()V
    //   192: aload 4
    //   194: new 72	java/io/File
    //   197: dup
    //   198: new 33	java/lang/StringBuilder
    //   201: dup
    //   202: invokespecial 34	java/lang/StringBuilder:<init>	()V
    //   205: getstatic 75	com/tencent/mm/ui/g/b:lAk	Ljava/lang/String;
    //   208: invokevirtual 42	java/lang/StringBuilder:append	(Ljava/lang/String;)Ljava/lang/StringBuilder;
    //   211: ldc 44
    //   213: invokevirtual 42	java/lang/StringBuilder:append	(Ljava/lang/String;)Ljava/lang/StringBuilder;
    //   216: invokevirtual 47	java/lang/StringBuilder:toString	()Ljava/lang/String;
    //   219: invokespecial 78	java/io/File:<init>	(Ljava/lang/String;)V
    //   222: invokevirtual 135	com/tencent/mm/ui/g/b:p	(Ljava/io/File;)V
    //   225: return
    //   226: astore_2
    //   227: ldc 62
    //   229: ldc -119
    //   231: invokestatic 102	com/tencent/mm/sdk/platformtools/u:e	(Ljava/lang/String;Ljava/lang/String;)V
    //   234: goto -116 -> 118
    //   237: astore_1
    //   238: ldc 62
    //   240: aload_1
    //   241: ldc -117
    //   243: iconst_0
    //   244: anewarray 4	java/lang/Object
    //   247: invokestatic 143	com/tencent/mm/sdk/platformtools/u:printErrStackTrace	(Ljava/lang/String;Ljava/lang/Throwable;Ljava/lang/String;[Ljava/lang/Object;)V
    //   250: goto -58 -> 192
    //   253: astore_3
    //   254: aconst_null
    //   255: astore_2
    //   256: aload_2
    //   257: astore_1
    //   258: ldc 62
    //   260: aload_3
    //   261: ldc -117
    //   263: iconst_0
    //   264: anewarray 4	java/lang/Object
    //   267: invokestatic 143	com/tencent/mm/sdk/platformtools/u:printErrStackTrace	(Ljava/lang/String;Ljava/lang/Throwable;Ljava/lang/String;[Ljava/lang/Object;)V
    //   270: aload_2
    //   271: ifnull -79 -> 192
    //   274: aload_2
    //   275: invokevirtual 131	java/io/RandomAccessFile:close	()V
    //   278: goto -86 -> 192
    //   281: astore_1
    //   282: ldc 62
    //   284: aload_1
    //   285: ldc -117
    //   287: iconst_0
    //   288: anewarray 4	java/lang/Object
    //   291: invokestatic 143	com/tencent/mm/sdk/platformtools/u:printErrStackTrace	(Ljava/lang/String;Ljava/lang/Throwable;Ljava/lang/String;[Ljava/lang/Object;)V
    //   294: goto -102 -> 192
    //   297: astore_2
    //   298: aconst_null
    //   299: astore_1
    //   300: aload_1
    //   301: ifnull +7 -> 308
    //   304: aload_1
    //   305: invokevirtual 131	java/io/RandomAccessFile:close	()V
    //   308: aload_2
    //   309: athrow
    //   310: astore_1
    //   311: ldc 62
    //   313: aload_1
    //   314: ldc -117
    //   316: iconst_0
    //   317: anewarray 4	java/lang/Object
    //   320: invokestatic 143	com/tencent/mm/sdk/platformtools/u:printErrStackTrace	(Ljava/lang/String;Ljava/lang/Throwable;Ljava/lang/String;[Ljava/lang/Object;)V
    //   323: goto -15 -> 308
    //   326: astore_2
    //   327: goto -27 -> 300
    //   330: astore_3
    //   331: goto -75 -> 256
    // Local variable table:
    //   start	length	slot	name	signature
    //   0	334	0	this	4
    //   27	150	1	localObject1	Object
    //   237	4	1	localException1	Exception
    //   257	1	1	localObject2	Object
    //   281	4	1	localException2	Exception
    //   299	6	1	localObject3	Object
    //   310	4	1	localException3	Exception
    //   87	102	2	localObject4	Object
    //   226	1	2	localException4	Exception
    //   255	20	2	localObject5	Object
    //   297	12	2	localObject6	Object
    //   326	1	2	localObject7	Object
    //   62	117	3	str	String
    //   253	8	3	localIOException1	java.io.IOException
    //   330	1	3	localIOException2	java.io.IOException
    //   4	189	4	localb	b
    // Exception table:
    //   from	to	target	type
    //   77	100	226	java/lang/Exception
    //   100	118	226	java/lang/Exception
    //   188	192	237	java/lang/Exception
    //   154	165	253	java/io/IOException
    //   274	278	281	java/lang/Exception
    //   154	165	297	finally
    //   304	308	310	java/lang/Exception
    //   167	175	326	finally
    //   177	188	326	finally
    //   258	270	326	finally
    //   167	175	330	java/io/IOException
    //   177	188	330	java/io/IOException
  }
}

/* Location:
 * Qualified Name:     com.tencent.mm.ui.g.b.4
 * Java Class Version: 6 (50.0)
 * JD-Core Version:    0.7.1
 */