package com.tencent.mm.ui.h;

final class b$4
  implements Runnable
{
  b$4(b paramb, String paramString) {}
  
  /* Error */
  public final void run()
  {
    // Byte code:
    //   0: aload_0
    //   1: getfield 16	com/tencent/mm/ui/h/b$4:mbk	Lcom/tencent/mm/ui/h/b;
    //   4: astore 4
    //   6: new 29	java/lang/StringBuilder
    //   9: dup
    //   10: invokespecial 30	java/lang/StringBuilder:<init>	()V
    //   13: invokestatic 34	com/tencent/mm/ui/h/b:bpd	()Ljava/lang/String;
    //   16: invokevirtual 38	java/lang/StringBuilder:append	(Ljava/lang/String;)Ljava/lang/StringBuilder;
    //   19: ldc 40
    //   21: invokevirtual 38	java/lang/StringBuilder:append	(Ljava/lang/String;)Ljava/lang/StringBuilder;
    //   24: invokevirtual 43	java/lang/StringBuilder:toString	()Ljava/lang/String;
    //   27: astore_1
    //   28: new 29	java/lang/StringBuilder
    //   31: dup
    //   32: invokespecial 30	java/lang/StringBuilder:<init>	()V
    //   35: aload_0
    //   36: getfield 18	com/tencent/mm/ui/h/b$4:mbl	Ljava/lang/String;
    //   39: invokevirtual 38	java/lang/StringBuilder:append	(Ljava/lang/String;)Ljava/lang/StringBuilder;
    //   42: ldc 45
    //   44: invokevirtual 38	java/lang/StringBuilder:append	(Ljava/lang/String;)Ljava/lang/StringBuilder;
    //   47: invokevirtual 43	java/lang/StringBuilder:toString	()Ljava/lang/String;
    //   50: astore_3
    //   51: invokestatic 51	com/tencent/mm/compatible/util/e:no	()Z
    //   54: ifne +11 -> 65
    //   57: ldc 53
    //   59: ldc 55
    //   61: invokestatic 61	com/tencent/mm/sdk/platformtools/v:i	(Ljava/lang/String;Ljava/lang/String;)V
    //   64: return
    //   65: new 63	java/io/File
    //   68: dup
    //   69: getstatic 66	com/tencent/mm/ui/h/b:mba	Ljava/lang/String;
    //   72: invokespecial 69	java/io/File:<init>	(Ljava/lang/String;)V
    //   75: astore_2
    //   76: aload_2
    //   77: invokevirtual 72	java/io/File:exists	()Z
    //   80: ifne +8 -> 88
    //   83: aload_2
    //   84: invokevirtual 75	java/io/File:mkdirs	()Z
    //   87: pop
    //   88: aload 4
    //   90: new 63	java/io/File
    //   93: dup
    //   94: getstatic 66	com/tencent/mm/ui/h/b:mba	Ljava/lang/String;
    //   97: ldc 40
    //   99: invokespecial 77	java/io/File:<init>	(Ljava/lang/String;Ljava/lang/String;)V
    //   102: iconst_0
    //   103: invokevirtual 81	com/tencent/mm/ui/h/b:c	(Ljava/io/File;Z)V
    //   106: new 63	java/io/File
    //   109: dup
    //   110: aload_1
    //   111: invokespecial 69	java/io/File:<init>	(Ljava/lang/String;)V
    //   114: astore_2
    //   115: aload_2
    //   116: invokevirtual 85	java/io/File:length	()J
    //   119: aload 4
    //   121: getfield 89	com/tencent/mm/ui/h/b:mbf	J
    //   124: lcmp
    //   125: ifle +17 -> 142
    //   128: ldc 53
    //   130: ldc 91
    //   132: invokestatic 94	com/tencent/mm/sdk/platformtools/v:e	(Ljava/lang/String;Ljava/lang/String;)V
    //   135: aload 4
    //   137: aload_2
    //   138: iconst_1
    //   139: invokevirtual 81	com/tencent/mm/ui/h/b:c	(Ljava/io/File;Z)V
    //   142: new 96	java/io/RandomAccessFile
    //   145: dup
    //   146: aload_1
    //   147: ldc 98
    //   149: invokespecial 99	java/io/RandomAccessFile:<init>	(Ljava/lang/String;Ljava/lang/String;)V
    //   152: astore_2
    //   153: aload_2
    //   154: astore_1
    //   155: aload_2
    //   156: aload_2
    //   157: invokevirtual 100	java/io/RandomAccessFile:length	()J
    //   160: invokevirtual 104	java/io/RandomAccessFile:seek	(J)V
    //   163: aload_2
    //   164: astore_1
    //   165: aload_2
    //   166: aload_3
    //   167: invokevirtual 110	java/lang/String:getBytes	()[B
    //   170: invokestatic 116	com/tencent/mm/bd/d:be	([B)[B
    //   173: invokevirtual 120	java/io/RandomAccessFile:write	([B)V
    //   176: aload_2
    //   177: invokevirtual 123	java/io/RandomAccessFile:close	()V
    //   180: aload 4
    //   182: new 63	java/io/File
    //   185: dup
    //   186: new 29	java/lang/StringBuilder
    //   189: dup
    //   190: invokespecial 30	java/lang/StringBuilder:<init>	()V
    //   193: getstatic 66	com/tencent/mm/ui/h/b:mba	Ljava/lang/String;
    //   196: invokevirtual 38	java/lang/StringBuilder:append	(Ljava/lang/String;)Ljava/lang/StringBuilder;
    //   199: ldc 40
    //   201: invokevirtual 38	java/lang/StringBuilder:append	(Ljava/lang/String;)Ljava/lang/StringBuilder;
    //   204: invokevirtual 43	java/lang/StringBuilder:toString	()Ljava/lang/String;
    //   207: invokespecial 69	java/io/File:<init>	(Ljava/lang/String;)V
    //   210: invokevirtual 127	com/tencent/mm/ui/h/b:r	(Ljava/io/File;)V
    //   213: return
    //   214: astore_2
    //   215: ldc 53
    //   217: ldc -127
    //   219: invokestatic 94	com/tencent/mm/sdk/platformtools/v:e	(Ljava/lang/String;Ljava/lang/String;)V
    //   222: goto -116 -> 106
    //   225: astore_1
    //   226: ldc 53
    //   228: aload_1
    //   229: ldc -125
    //   231: iconst_0
    //   232: anewarray 4	java/lang/Object
    //   235: invokestatic 135	com/tencent/mm/sdk/platformtools/v:printErrStackTrace	(Ljava/lang/String;Ljava/lang/Throwable;Ljava/lang/String;[Ljava/lang/Object;)V
    //   238: goto -58 -> 180
    //   241: astore_3
    //   242: aconst_null
    //   243: astore_2
    //   244: aload_2
    //   245: astore_1
    //   246: ldc 53
    //   248: aload_3
    //   249: ldc -125
    //   251: iconst_0
    //   252: anewarray 4	java/lang/Object
    //   255: invokestatic 135	com/tencent/mm/sdk/platformtools/v:printErrStackTrace	(Ljava/lang/String;Ljava/lang/Throwable;Ljava/lang/String;[Ljava/lang/Object;)V
    //   258: aload_2
    //   259: ifnull -79 -> 180
    //   262: aload_2
    //   263: invokevirtual 123	java/io/RandomAccessFile:close	()V
    //   266: goto -86 -> 180
    //   269: astore_1
    //   270: ldc 53
    //   272: aload_1
    //   273: ldc -125
    //   275: iconst_0
    //   276: anewarray 4	java/lang/Object
    //   279: invokestatic 135	com/tencent/mm/sdk/platformtools/v:printErrStackTrace	(Ljava/lang/String;Ljava/lang/Throwable;Ljava/lang/String;[Ljava/lang/Object;)V
    //   282: goto -102 -> 180
    //   285: astore_2
    //   286: aconst_null
    //   287: astore_1
    //   288: aload_1
    //   289: ifnull +7 -> 296
    //   292: aload_1
    //   293: invokevirtual 123	java/io/RandomAccessFile:close	()V
    //   296: aload_2
    //   297: athrow
    //   298: astore_1
    //   299: ldc 53
    //   301: aload_1
    //   302: ldc -125
    //   304: iconst_0
    //   305: anewarray 4	java/lang/Object
    //   308: invokestatic 135	com/tencent/mm/sdk/platformtools/v:printErrStackTrace	(Ljava/lang/String;Ljava/lang/Throwable;Ljava/lang/String;[Ljava/lang/Object;)V
    //   311: goto -15 -> 296
    //   314: astore_2
    //   315: goto -27 -> 288
    //   318: astore_3
    //   319: goto -75 -> 244
    // Local variable table:
    //   start	length	slot	name	signature
    //   0	322	0	this	4
    //   27	138	1	localObject1	Object
    //   225	4	1	localException1	Exception
    //   245	1	1	localObject2	Object
    //   269	4	1	localException2	Exception
    //   287	6	1	localObject3	Object
    //   298	4	1	localException3	Exception
    //   75	102	2	localObject4	Object
    //   214	1	2	localException4	Exception
    //   243	20	2	localObject5	Object
    //   285	12	2	localObject6	Object
    //   314	1	2	localObject7	Object
    //   50	117	3	str	String
    //   241	8	3	localIOException1	java.io.IOException
    //   318	1	3	localIOException2	java.io.IOException
    //   4	177	4	localb	b
    // Exception table:
    //   from	to	target	type
    //   65	88	214	java/lang/Exception
    //   88	106	214	java/lang/Exception
    //   176	180	225	java/lang/Exception
    //   142	153	241	java/io/IOException
    //   262	266	269	java/lang/Exception
    //   142	153	285	finally
    //   292	296	298	java/lang/Exception
    //   155	163	314	finally
    //   165	176	314	finally
    //   246	258	314	finally
    //   155	163	318	java/io/IOException
    //   165	176	318	java/io/IOException
  }
}

/* Location:
 * Qualified Name:     com.tencent.mm.ui.h.b.4
 * Java Class Version: 6 (50.0)
 * JD-Core Version:    0.7.1
 */