package ct;

import android.os.SystemClock;
import android.text.TextUtils;
import java.net.InetAddress;
import java.net.MalformedURLException;
import java.net.URL;
import org.apache.http.impl.client.DefaultHttpClient;

public final class af
  implements aa
{
  private static DefaultHttpClient c = null;
  private Byte a;
  private a b;
  
  /* Error */
  private static DefaultHttpClient a(int paramInt1, int paramInt2)
  {
    // Byte code:
    //   0: ldc 2
    //   2: monitorenter
    //   3: getstatic 18	ct/af:c	Lorg/apache/http/impl/client/DefaultHttpClient;
    //   6: ifnonnull +139 -> 145
    //   9: ldc 27
    //   11: new 29	java/lang/StringBuilder
    //   14: dup
    //   15: ldc 31
    //   17: invokespecial 34	java/lang/StringBuilder:<init>	(Ljava/lang/String;)V
    //   20: iload_0
    //   21: invokevirtual 38	java/lang/StringBuilder:append	(I)Ljava/lang/StringBuilder;
    //   24: ldc 40
    //   26: invokevirtual 43	java/lang/StringBuilder:append	(Ljava/lang/String;)Ljava/lang/StringBuilder;
    //   29: iload_1
    //   30: invokevirtual 38	java/lang/StringBuilder:append	(I)Ljava/lang/StringBuilder;
    //   33: invokevirtual 47	java/lang/StringBuilder:toString	()Ljava/lang/String;
    //   36: invokestatic 52	ct/bc:a	(Ljava/lang/String;Ljava/lang/String;)V
    //   39: new 54	org/apache/http/params/BasicHttpParams
    //   42: dup
    //   43: invokespecial 55	org/apache/http/params/BasicHttpParams:<init>	()V
    //   46: astore_2
    //   47: aload_2
    //   48: bipush 100
    //   50: invokestatic 61	org/apache/http/conn/params/ConnManagerParams:setMaxTotalConnections	(Lorg/apache/http/params/HttpParams;I)V
    //   53: aload_2
    //   54: new 63	org/apache/http/conn/params/ConnPerRouteBean
    //   57: dup
    //   58: bipush 30
    //   60: invokespecial 66	org/apache/http/conn/params/ConnPerRouteBean:<init>	(I)V
    //   63: invokestatic 70	org/apache/http/conn/params/ConnManagerParams:setMaxConnectionsPerRoute	(Lorg/apache/http/params/HttpParams;Lorg/apache/http/conn/params/ConnPerRoute;)V
    //   66: aload_2
    //   67: ldc2_w 71
    //   70: invokestatic 76	org/apache/http/conn/params/ConnManagerParams:setTimeout	(Lorg/apache/http/params/HttpParams;J)V
    //   73: aload_2
    //   74: iconst_0
    //   75: invokestatic 82	org/apache/http/params/HttpProtocolParams:setUseExpectContinue	(Lorg/apache/http/params/HttpParams;Z)V
    //   78: aload_2
    //   79: iconst_0
    //   80: invokestatic 87	org/apache/http/client/params/HttpClientParams:setRedirecting	(Lorg/apache/http/params/HttpParams;Z)V
    //   83: aload_2
    //   84: iload_0
    //   85: invokestatic 92	org/apache/http/params/HttpConnectionParams:setConnectionTimeout	(Lorg/apache/http/params/HttpParams;I)V
    //   88: aload_2
    //   89: iload_1
    //   90: invokestatic 95	org/apache/http/params/HttpConnectionParams:setSoTimeout	(Lorg/apache/http/params/HttpParams;I)V
    //   93: aload_2
    //   94: sipush 8192
    //   97: invokestatic 98	org/apache/http/params/HttpConnectionParams:setSocketBufferSize	(Lorg/apache/http/params/HttpParams;I)V
    //   100: getstatic 18	ct/af:c	Lorg/apache/http/impl/client/DefaultHttpClient;
    //   103: new 100	ct/ag
    //   106: dup
    //   107: invokespecial 101	ct/ag:<init>	()V
    //   110: invokevirtual 107	org/apache/http/impl/client/DefaultHttpClient:setKeepAliveStrategy	(Lorg/apache/http/conn/ConnectionKeepAliveStrategy;)V
    //   113: new 103	org/apache/http/impl/client/DefaultHttpClient
    //   116: dup
    //   117: aload_2
    //   118: invokespecial 110	org/apache/http/impl/client/DefaultHttpClient:<init>	(Lorg/apache/http/params/HttpParams;)V
    //   121: astore_2
    //   122: aload_2
    //   123: putstatic 18	ct/af:c	Lorg/apache/http/impl/client/DefaultHttpClient;
    //   126: aload_2
    //   127: new 112	org/apache/http/impl/client/DefaultHttpRequestRetryHandler
    //   130: dup
    //   131: iconst_0
    //   132: iconst_0
    //   133: invokespecial 115	org/apache/http/impl/client/DefaultHttpRequestRetryHandler:<init>	(IZ)V
    //   136: invokevirtual 119	org/apache/http/impl/client/DefaultHttpClient:setHttpRequestRetryHandler	(Lorg/apache/http/client/HttpRequestRetryHandler;)V
    //   139: getstatic 18	ct/af:c	Lorg/apache/http/impl/client/DefaultHttpClient;
    //   142: invokestatic 124	ct/bb:a	(Lorg/apache/http/client/HttpClient;)V
    //   145: getstatic 18	ct/af:c	Lorg/apache/http/impl/client/DefaultHttpClient;
    //   148: astore_2
    //   149: ldc 2
    //   151: monitorexit
    //   152: aload_2
    //   153: areturn
    //   154: astore_2
    //   155: ldc 2
    //   157: monitorexit
    //   158: aload_2
    //   159: athrow
    //   160: astore_3
    //   161: goto -48 -> 113
    // Local variable table:
    //   start	length	slot	name	signature
    //   0	164	0	paramInt1	int
    //   0	164	1	paramInt2	int
    //   46	107	2	localObject1	Object
    //   154	5	2	localObject2	Object
    //   160	1	3	localThrowable	Throwable
    // Exception table:
    //   from	to	target	type
    //   3	100	154	finally
    //   100	113	154	finally
    //   113	145	154	finally
    //   145	149	154	finally
    //   100	113	160	java/lang/Throwable
  }
  
  public static void a(ae paramae)
  {
    v localv;
    String str1;
    String str2;
    if (paramae != null)
    {
      localv = v.a();
      str1 = c;
      paramae = a;
      str2 = bb.a();
      if ((TextUtils.isEmpty(str2)) || (str2.equals("unknown"))) {
        bc.c("AccessSchedulerStorageManager", "updateApnUserTime... failed with apnName:" + str2);
      }
    }
    else
    {
      return;
    }
    a.a(str2, str1, paramae.a());
    localv.a(true);
    bc.b("AccessSchedulerStorageManager", "updateApnUseTime... apnName:" + str2);
  }
  
  private static ac b(String paramString, byte[] paramArrayOfByte)
  {
    try
    {
      URL localURL = new URL(bd.c(paramString));
      int i = localURL.getPort();
      ac localac = new ac(localURL.getHost(), new int[] { i });
      if ((!TextUtils.isEmpty(paramString)) && (paramString.toLowerCase().startsWith("https://"))) {
        a = true;
      }
      g = localURL.getFile();
      k = paramArrayOfByte;
      d = paramString;
      return localac;
    }
    catch (MalformedURLException paramArrayOfByte)
    {
      throw new ah("url format error:" + paramString);
    }
  }
  
  /* Error */
  private ad b(ac paramac)
  {
    // Byte code:
    //   0: new 295	ct/ad
    //   3: dup
    //   4: invokespecial 296	ct/ad:<init>	()V
    //   7: astore 17
    //   9: invokestatic 300	ct/bb:e	()Z
    //   12: ifne +66 -> 78
    //   15: aload 17
    //   17: bipush -4
    //   19: putfield 302	ct/ad:a	I
    //   22: new 132	ct/ae
    //   25: dup
    //   26: invokespecial 303	ct/ae:<init>	()V
    //   29: astore 18
    //   31: aload 18
    //   33: aload_1
    //   34: getfield 283	ct/ac:d	Ljava/lang/String;
    //   37: putfield 304	ct/ae:d	Ljava/lang/String;
    //   40: aload 18
    //   42: ldc_w 306
    //   45: putfield 309	ct/ae:p	Ljava/lang/String;
    //   48: aload 18
    //   50: bipush -4
    //   52: putfield 195	ct/ae:i	I
    //   55: invokestatic 314	ct/p:a	()Lct/p;
    //   58: new 8	ct/af$a
    //   61: dup
    //   62: aload_0
    //   63: aload 18
    //   65: invokespecial 317	ct/af$a:<init>	(Lct/af;Lct/ae;)V
    //   68: invokevirtual 320	ct/p:a	(Ljava/lang/Runnable;)V
    //   71: aload 17
    //   73: astore 19
    //   75: aload 19
    //   77: areturn
    //   78: aload_0
    //   79: invokestatic 325	ct/i:a	()Lct/a;
    //   82: putfield 181	ct/af:b	Lct/a;
    //   85: new 327	ct/y
    //   88: dup
    //   89: aload_1
    //   90: invokespecial 330	ct/y:<init>	(Lct/ac;)V
    //   93: astore 18
    //   95: new 332	ct/z
    //   98: dup
    //   99: invokestatic 334	ct/bb:c	()I
    //   102: invokespecial 335	ct/z:<init>	(I)V
    //   105: astore 26
    //   107: aload 18
    //   109: invokevirtual 338	ct/y:c	()Ljava/util/List;
    //   112: astore 27
    //   114: aload 18
    //   116: invokevirtual 341	ct/y:a	()Lct/t;
    //   119: astore 28
    //   121: ldc 27
    //   123: new 29	java/lang/StringBuilder
    //   126: dup
    //   127: ldc_w 343
    //   130: invokespecial 34	java/lang/StringBuilder:<init>	(Ljava/lang/String;)V
    //   133: aload 27
    //   135: invokevirtual 346	java/lang/StringBuilder:append	(Ljava/lang/Object;)Ljava/lang/StringBuilder;
    //   138: ldc_w 348
    //   141: invokevirtual 43	java/lang/StringBuilder:append	(Ljava/lang/String;)Ljava/lang/StringBuilder;
    //   144: aload 28
    //   146: invokevirtual 346	java/lang/StringBuilder:append	(Ljava/lang/Object;)Ljava/lang/StringBuilder;
    //   149: invokevirtual 47	java/lang/StringBuilder:toString	()Ljava/lang/String;
    //   152: invokestatic 52	ct/bc:a	(Ljava/lang/String;Ljava/lang/String;)V
    //   155: aload 27
    //   157: invokeinterface 353 1 0
    //   162: istore 7
    //   164: aload 27
    //   166: invokeinterface 353 1 0
    //   171: istore 8
    //   173: aload 18
    //   175: invokevirtual 355	ct/y:b	()Ljava/lang/String;
    //   178: astore 29
    //   180: iconst_0
    //   181: istore 4
    //   183: iconst_0
    //   184: istore 11
    //   186: ldc_w 357
    //   189: astore 19
    //   191: iconst_0
    //   192: istore 5
    //   194: ldc_w 357
    //   197: astore 20
    //   199: iconst_0
    //   200: istore_3
    //   201: aload 17
    //   203: astore 18
    //   205: aload 20
    //   207: astore 17
    //   209: aload 18
    //   211: astore 20
    //   213: iload 4
    //   215: aload_1
    //   216: getfield 360	ct/ac:q	I
    //   219: if_icmpgt +4549 -> 4768
    //   222: iload_3
    //   223: ifne +4545 -> 4768
    //   226: invokestatic 366	android/os/SystemClock:elapsedRealtime	()J
    //   229: lstore 13
    //   231: new 295	ct/ad
    //   234: dup
    //   235: invokespecial 296	ct/ad:<init>	()V
    //   238: astore 24
    //   240: new 132	ct/ae
    //   243: dup
    //   244: invokespecial 303	ct/ae:<init>	()V
    //   247: astore 30
    //   249: aload 30
    //   251: aload 29
    //   253: putfield 369	ct/ae:w	Ljava/lang/String;
    //   256: aload 30
    //   258: aload 28
    //   260: putfield 371	ct/ae:b	Lct/t;
    //   263: iconst_0
    //   264: istore 10
    //   266: iload 4
    //   268: aload_1
    //   269: getfield 360	ct/ac:q	I
    //   272: if_icmpne +6 -> 278
    //   275: iconst_1
    //   276: istore 10
    //   278: iload 4
    //   280: iload 8
    //   282: irem
    //   283: istore_2
    //   284: iload_2
    //   285: iload 7
    //   287: iconst_1
    //   288: isub
    //   289: if_icmpge +31 -> 320
    //   292: aload 30
    //   294: iconst_1
    //   295: putfield 374	ct/ae:v	Z
    //   298: aload_1
    //   299: ldc_w 376
    //   302: aload_1
    //   303: getfield 379	ct/ac:f	Ljava/lang/String;
    //   306: invokevirtual 380	ct/ac:a	(Ljava/lang/String;Ljava/lang/String;)V
    //   309: aload_1
    //   310: ldc_w 382
    //   313: aload_1
    //   314: getfield 379	ct/ac:f	Ljava/lang/String;
    //   317: invokevirtual 380	ct/ac:a	(Ljava/lang/String;Ljava/lang/String;)V
    //   320: aload 27
    //   322: iload_2
    //   323: invokeinterface 385 2 0
    //   328: checkcast 165	ct/t
    //   331: astore 25
    //   333: aload 30
    //   335: aload 25
    //   337: putfield 138	ct/ae:a	Lct/t;
    //   340: aload 30
    //   342: aload_1
    //   343: getfield 386	ct/ac:c	Ljava/lang/String;
    //   346: putfield 135	ct/ae:c	Ljava/lang/String;
    //   349: aload 30
    //   351: aload_1
    //   352: getfield 270	ct/ac:a	Z
    //   355: putfield 389	ct/ae:B	Z
    //   358: aload 30
    //   360: aload_1
    //   361: getfield 360	ct/ac:q	I
    //   364: putfield 392	ct/ae:s	I
    //   367: invokestatic 366	android/os/SystemClock:elapsedRealtime	()J
    //   370: aload_1
    //   371: getfield 396	ct/ac:l	J
    //   374: lsub
    //   375: aload_1
    //   376: getfield 398	ct/ac:p	I
    //   379: i2l
    //   380: lcmp
    //   381: ifle +4587 -> 4968
    //   384: aload 27
    //   386: aload 27
    //   388: invokeinterface 353 1 0
    //   393: iconst_1
    //   394: isub
    //   395: invokeinterface 385 2 0
    //   400: checkcast 165	ct/t
    //   403: astore 25
    //   405: iconst_1
    //   406: istore_3
    //   407: iconst_1
    //   408: istore_2
    //   409: aload 30
    //   411: iconst_1
    //   412: putfield 401	ct/ae:y	Z
    //   415: iload_2
    //   416: istore_3
    //   417: aload 17
    //   419: invokestatic 146	android/text/TextUtils:isEmpty	(Ljava/lang/CharSequence;)Z
    //   422: ifeq +962 -> 1384
    //   425: iload_2
    //   426: istore_3
    //   427: aload_1
    //   428: getfield 270	ct/ac:a	Z
    //   431: ifne +839 -> 1270
    //   434: iload_2
    //   435: istore_3
    //   436: aload 25
    //   438: getfield 402	ct/t:b	I
    //   441: iconst_m1
    //   442: if_icmpeq +800 -> 1242
    //   445: iload_2
    //   446: istore_3
    //   447: new 29	java/lang/StringBuilder
    //   450: dup
    //   451: ldc_w 404
    //   454: invokespecial 34	java/lang/StringBuilder:<init>	(Ljava/lang/String;)V
    //   457: aload 25
    //   459: getfield 406	ct/t:a	Ljava/lang/String;
    //   462: invokevirtual 43	java/lang/StringBuilder:append	(Ljava/lang/String;)Ljava/lang/StringBuilder;
    //   465: ldc_w 408
    //   468: invokevirtual 43	java/lang/StringBuilder:append	(Ljava/lang/String;)Ljava/lang/StringBuilder;
    //   471: aload 25
    //   473: getfield 402	ct/t:b	I
    //   476: invokevirtual 38	java/lang/StringBuilder:append	(I)Ljava/lang/StringBuilder;
    //   479: invokevirtual 47	java/lang/StringBuilder:toString	()Ljava/lang/String;
    //   482: astore 18
    //   484: iload_2
    //   485: istore_3
    //   486: aload_1
    //   487: getfield 276	ct/ac:g	Ljava/lang/String;
    //   490: astore 21
    //   492: aload 18
    //   494: astore 20
    //   496: iload_2
    //   497: istore_3
    //   498: aload 21
    //   500: invokestatic 146	android/text/TextUtils:isEmpty	(Ljava/lang/CharSequence;)Z
    //   503: ifne +40 -> 543
    //   506: iload_2
    //   507: istore_3
    //   508: aload 21
    //   510: ldc_w 410
    //   513: invokevirtual 267	java/lang/String:startsWith	(Ljava/lang/String;)Z
    //   516: ifeq +835 -> 1351
    //   519: iload_2
    //   520: istore_3
    //   521: new 29	java/lang/StringBuilder
    //   524: dup
    //   525: invokespecial 411	java/lang/StringBuilder:<init>	()V
    //   528: aload 18
    //   530: invokevirtual 43	java/lang/StringBuilder:append	(Ljava/lang/String;)Ljava/lang/StringBuilder;
    //   533: aload 21
    //   535: invokevirtual 43	java/lang/StringBuilder:append	(Ljava/lang/String;)Ljava/lang/StringBuilder;
    //   538: invokevirtual 47	java/lang/StringBuilder:toString	()Ljava/lang/String;
    //   541: astore 20
    //   543: iload_2
    //   544: istore_3
    //   545: aload 30
    //   547: aload 20
    //   549: putfield 304	ct/ae:d	Ljava/lang/String;
    //   552: aload 20
    //   554: astore 18
    //   556: aload 17
    //   558: astore 20
    //   560: aload 19
    //   562: astore 22
    //   564: aload 17
    //   566: astore 21
    //   568: aload 19
    //   570: astore 23
    //   572: ldc 27
    //   574: new 29	java/lang/StringBuilder
    //   577: dup
    //   578: ldc_w 413
    //   581: invokespecial 34	java/lang/StringBuilder:<init>	(Ljava/lang/String;)V
    //   584: iload 4
    //   586: invokevirtual 38	java/lang/StringBuilder:append	(I)Ljava/lang/StringBuilder;
    //   589: ldc_w 415
    //   592: invokevirtual 43	java/lang/StringBuilder:append	(Ljava/lang/String;)Ljava/lang/StringBuilder;
    //   595: aload 18
    //   597: invokevirtual 43	java/lang/StringBuilder:append	(Ljava/lang/String;)Ljava/lang/StringBuilder;
    //   600: ldc_w 417
    //   603: invokevirtual 43	java/lang/StringBuilder:append	(Ljava/lang/String;)Ljava/lang/StringBuilder;
    //   606: iload 11
    //   608: invokevirtual 420	java/lang/StringBuilder:append	(Z)Ljava/lang/StringBuilder;
    //   611: ldc_w 422
    //   614: invokevirtual 43	java/lang/StringBuilder:append	(Ljava/lang/String;)Ljava/lang/StringBuilder;
    //   617: aload 25
    //   619: invokevirtual 346	java/lang/StringBuilder:append	(Ljava/lang/Object;)Ljava/lang/StringBuilder;
    //   622: invokevirtual 47	java/lang/StringBuilder:toString	()Ljava/lang/String;
    //   625: invokestatic 52	ct/bc:a	(Ljava/lang/String;Ljava/lang/String;)V
    //   628: aload 17
    //   630: astore 20
    //   632: aload 19
    //   634: astore 22
    //   636: aload 17
    //   638: astore 21
    //   640: aload 19
    //   642: astore 23
    //   644: new 424	org/apache/http/client/methods/HttpPost
    //   647: dup
    //   648: aload 18
    //   650: invokespecial 425	org/apache/http/client/methods/HttpPost:<init>	(Ljava/lang/String;)V
    //   653: astore 25
    //   655: aload 17
    //   657: astore 20
    //   659: aload 19
    //   661: astore 22
    //   663: aload 17
    //   665: astore 21
    //   667: aload 19
    //   669: astore 23
    //   671: new 427	java/util/HashMap
    //   674: dup
    //   675: invokespecial 428	java/util/HashMap:<init>	()V
    //   678: astore 31
    //   680: aload 17
    //   682: astore 20
    //   684: aload 19
    //   686: astore 22
    //   688: aload 17
    //   690: astore 21
    //   692: aload 19
    //   694: astore 23
    //   696: aload 31
    //   698: aload_1
    //   699: getfield 431	ct/ac:j	Ljava/util/Map;
    //   702: invokeinterface 435 2 0
    //   707: aload 17
    //   709: astore 20
    //   711: aload 19
    //   713: astore 22
    //   715: aload 17
    //   717: astore 21
    //   719: aload 19
    //   721: astore 23
    //   723: aload 31
    //   725: invokeinterface 436 1 0
    //   730: ifle +795 -> 1525
    //   733: iload 11
    //   735: ifne +790 -> 1525
    //   738: aload 17
    //   740: astore 20
    //   742: aload 19
    //   744: astore 22
    //   746: aload 17
    //   748: astore 21
    //   750: aload 19
    //   752: astore 23
    //   754: aload 31
    //   756: invokeinterface 440 1 0
    //   761: invokeinterface 446 1 0
    //   766: astore 32
    //   768: aload 17
    //   770: astore 20
    //   772: aload 19
    //   774: astore 22
    //   776: aload 17
    //   778: astore 21
    //   780: aload 19
    //   782: astore 23
    //   784: aload 32
    //   786: invokeinterface 451 1 0
    //   791: ifeq +616 -> 1407
    //   794: aload 17
    //   796: astore 20
    //   798: aload 19
    //   800: astore 22
    //   802: aload 17
    //   804: astore 21
    //   806: aload 19
    //   808: astore 23
    //   810: aload 32
    //   812: invokeinterface 455 1 0
    //   817: checkcast 150	java/lang/String
    //   820: astore 33
    //   822: aload 17
    //   824: astore 20
    //   826: aload 19
    //   828: astore 22
    //   830: aload 17
    //   832: astore 21
    //   834: aload 19
    //   836: astore 23
    //   838: aload 25
    //   840: aload 33
    //   842: aload 31
    //   844: aload 33
    //   846: invokeinterface 207 2 0
    //   851: checkcast 150	java/lang/String
    //   854: invokeinterface 460 3 0
    //   859: goto -91 -> 768
    //   862: astore 19
    //   864: aload 22
    //   866: astore 17
    //   868: iload 11
    //   870: istore 12
    //   872: aload 20
    //   874: astore 18
    //   876: iload 10
    //   878: istore 11
    //   880: iload 12
    //   882: istore 10
    //   884: iload_2
    //   885: istore_3
    //   886: ldc 27
    //   888: ldc_w 462
    //   891: aload 19
    //   893: invokestatic 465	ct/bc:a	(Ljava/lang/String;Ljava/lang/String;Ljava/lang/Throwable;)V
    //   896: aload 30
    //   898: aload 19
    //   900: invokevirtual 469	java/lang/Object:getClass	()Ljava/lang/Class;
    //   903: invokevirtual 474	java/lang/Class:getSimpleName	()Ljava/lang/String;
    //   906: putfield 477	ct/ae:o	Ljava/lang/String;
    //   909: aload 30
    //   911: aload 19
    //   913: invokestatic 480	ct/bd:a	(Ljava/lang/Exception;)Ljava/lang/String;
    //   916: putfield 309	ct/ae:p	Ljava/lang/String;
    //   919: invokestatic 300	ct/bb:e	()Z
    //   922: ifeq +3784 -> 4706
    //   925: invokestatic 484	ct/j:a	()Z
    //   928: ifeq +3772 -> 4700
    //   931: aload 19
    //   933: instanceof 486
    //   936: ifeq +3628 -> 4564
    //   939: bipush -10
    //   941: istore_2
    //   942: aload 24
    //   944: iload_2
    //   945: putfield 302	ct/ad:a	I
    //   948: aload 30
    //   950: getfield 309	ct/ae:p	Ljava/lang/String;
    //   953: ldc_w 488
    //   956: invokevirtual 491	java/lang/String:contains	(Ljava/lang/CharSequence;)Z
    //   959: ifeq +10 -> 969
    //   962: aload 24
    //   964: bipush -18
    //   966: putfield 302	ct/ad:a	I
    //   969: aload 30
    //   971: new 29	java/lang/StringBuilder
    //   974: dup
    //   975: invokespecial 411	java/lang/StringBuilder:<init>	()V
    //   978: aload_1
    //   979: getfield 493	ct/ac:s	Ljava/lang/String;
    //   982: invokevirtual 43	java/lang/StringBuilder:append	(Ljava/lang/String;)Ljava/lang/StringBuilder;
    //   985: ldc_w 495
    //   988: invokevirtual 43	java/lang/StringBuilder:append	(Ljava/lang/String;)Ljava/lang/StringBuilder;
    //   991: iload 4
    //   993: invokevirtual 38	java/lang/StringBuilder:append	(I)Ljava/lang/StringBuilder;
    //   996: invokevirtual 47	java/lang/StringBuilder:toString	()Ljava/lang/String;
    //   999: putfield 498	ct/ae:n	Ljava/lang/String;
    //   1002: aload 30
    //   1004: iload 4
    //   1006: putfield 499	ct/ae:q	I
    //   1009: aload 18
    //   1011: invokestatic 146	android/text/TextUtils:isEmpty	(Ljava/lang/CharSequence;)Z
    //   1014: ifeq +3698 -> 4712
    //   1017: iload 4
    //   1019: iconst_1
    //   1020: iadd
    //   1021: istore_2
    //   1022: iconst_0
    //   1023: istore 5
    //   1025: invokestatic 502	ct/q:b	()Ljava/lang/String;
    //   1028: invokestatic 146	android/text/TextUtils:isEmpty	(Ljava/lang/CharSequence;)Z
    //   1031: ifne +159 -> 1190
    //   1034: aload 24
    //   1036: getfield 302	ct/ad:a	I
    //   1039: bipush -21
    //   1041: if_icmpeq +149 -> 1190
    //   1044: aload 24
    //   1046: invokestatic 366	android/os/SystemClock:elapsedRealtime	()J
    //   1049: aload_1
    //   1050: getfield 396	ct/ac:l	J
    //   1053: lsub
    //   1054: l2i
    //   1055: putfield 504	ct/ad:f	I
    //   1058: aload 30
    //   1060: aload 24
    //   1062: getfield 302	ct/ad:a	I
    //   1065: putfield 195	ct/ae:i	I
    //   1068: aload 30
    //   1070: aload 17
    //   1072: putfield 507	ct/ae:A	Ljava/lang/String;
    //   1075: aload 30
    //   1077: aload 24
    //   1079: getfield 504	ct/ad:f	I
    //   1082: putfield 509	ct/ae:j	I
    //   1085: aload 30
    //   1087: invokestatic 366	android/os/SystemClock:elapsedRealtime	()J
    //   1090: lload 13
    //   1092: lsub
    //   1093: l2i
    //   1094: putfield 511	ct/ae:k	I
    //   1097: aload 30
    //   1099: aload 18
    //   1101: putfield 512	ct/ae:f	Ljava/lang/String;
    //   1104: aload_1
    //   1105: getfield 280	ct/ac:k	[B
    //   1108: ifnull +3642 -> 4750
    //   1111: aload 30
    //   1113: aload_1
    //   1114: getfield 280	ct/ac:k	[B
    //   1117: arraylength
    //   1118: i2l
    //   1119: putfield 513	ct/ae:l	J
    //   1122: aload 30
    //   1124: iload 11
    //   1126: putfield 516	ct/ae:x	Z
    //   1129: iload 11
    //   1131: ifeq +17 -> 1148
    //   1134: aload 30
    //   1136: getfield 195	ct/ae:i	I
    //   1139: ifeq +9 -> 1148
    //   1142: aload 30
    //   1144: iconst_1
    //   1145: putfield 519	ct/ae:u	I
    //   1148: aload 30
    //   1150: aload_1
    //   1151: getfield 521	ct/ac:i	Z
    //   1154: putfield 524	ct/ae:z	Z
    //   1157: aload_1
    //   1158: aload 30
    //   1160: invokevirtual 526	ct/ac:a	(Lct/ae;)V
    //   1163: invokestatic 314	ct/p:a	()Lct/p;
    //   1166: new 8	ct/af$a
    //   1169: dup
    //   1170: aload_0
    //   1171: aload 30
    //   1173: invokespecial 317	ct/af$a:<init>	(Lct/af;Lct/ae;)V
    //   1176: invokevirtual 320	ct/p:a	(Ljava/lang/Runnable;)V
    //   1179: ldc_w 528
    //   1182: aload 30
    //   1184: invokevirtual 529	ct/ae:toString	()Ljava/lang/String;
    //   1187: invokestatic 52	ct/bc:a	(Ljava/lang/String;Ljava/lang/String;)V
    //   1190: aload 24
    //   1192: astore 19
    //   1194: aload 24
    //   1196: getfield 302	ct/ad:a	I
    //   1199: bipush -17
    //   1201: if_icmpeq -1126 -> 75
    //   1204: aload 17
    //   1206: astore 19
    //   1208: aload 18
    //   1210: astore 17
    //   1212: iload 5
    //   1214: istore 4
    //   1216: aload 19
    //   1218: astore 18
    //   1220: iload 4
    //   1222: istore 5
    //   1224: aload 24
    //   1226: astore 20
    //   1228: iload 10
    //   1230: istore 11
    //   1232: iload_2
    //   1233: istore 4
    //   1235: aload 18
    //   1237: astore 19
    //   1239: goto -1026 -> 213
    //   1242: iload_2
    //   1243: istore_3
    //   1244: new 29	java/lang/StringBuilder
    //   1247: dup
    //   1248: ldc_w 404
    //   1251: invokespecial 34	java/lang/StringBuilder:<init>	(Ljava/lang/String;)V
    //   1254: aload 25
    //   1256: getfield 406	ct/t:a	Ljava/lang/String;
    //   1259: invokevirtual 43	java/lang/StringBuilder:append	(Ljava/lang/String;)Ljava/lang/StringBuilder;
    //   1262: invokevirtual 47	java/lang/StringBuilder:toString	()Ljava/lang/String;
    //   1265: astore 18
    //   1267: goto -783 -> 484
    //   1270: iload_2
    //   1271: istore_3
    //   1272: aload 25
    //   1274: getfield 402	ct/t:b	I
    //   1277: iconst_m1
    //   1278: if_icmpeq +45 -> 1323
    //   1281: iload_2
    //   1282: istore_3
    //   1283: new 29	java/lang/StringBuilder
    //   1286: dup
    //   1287: ldc_w 263
    //   1290: invokespecial 34	java/lang/StringBuilder:<init>	(Ljava/lang/String;)V
    //   1293: aload 25
    //   1295: getfield 406	ct/t:a	Ljava/lang/String;
    //   1298: invokevirtual 43	java/lang/StringBuilder:append	(Ljava/lang/String;)Ljava/lang/StringBuilder;
    //   1301: ldc_w 408
    //   1304: invokevirtual 43	java/lang/StringBuilder:append	(Ljava/lang/String;)Ljava/lang/StringBuilder;
    //   1307: aload 25
    //   1309: getfield 402	ct/t:b	I
    //   1312: invokevirtual 38	java/lang/StringBuilder:append	(I)Ljava/lang/StringBuilder;
    //   1315: invokevirtual 47	java/lang/StringBuilder:toString	()Ljava/lang/String;
    //   1318: astore 18
    //   1320: goto -836 -> 484
    //   1323: iload_2
    //   1324: istore_3
    //   1325: new 29	java/lang/StringBuilder
    //   1328: dup
    //   1329: ldc_w 263
    //   1332: invokespecial 34	java/lang/StringBuilder:<init>	(Ljava/lang/String;)V
    //   1335: aload 25
    //   1337: getfield 406	ct/t:a	Ljava/lang/String;
    //   1340: invokevirtual 43	java/lang/StringBuilder:append	(Ljava/lang/String;)Ljava/lang/StringBuilder;
    //   1343: invokevirtual 47	java/lang/StringBuilder:toString	()Ljava/lang/String;
    //   1346: astore 18
    //   1348: goto -864 -> 484
    //   1351: iload_2
    //   1352: istore_3
    //   1353: new 29	java/lang/StringBuilder
    //   1356: dup
    //   1357: invokespecial 411	java/lang/StringBuilder:<init>	()V
    //   1360: aload 18
    //   1362: invokevirtual 43	java/lang/StringBuilder:append	(Ljava/lang/String;)Ljava/lang/StringBuilder;
    //   1365: ldc_w 410
    //   1368: invokevirtual 43	java/lang/StringBuilder:append	(Ljava/lang/String;)Ljava/lang/StringBuilder;
    //   1371: aload 21
    //   1373: invokevirtual 43	java/lang/StringBuilder:append	(Ljava/lang/String;)Ljava/lang/StringBuilder;
    //   1376: invokevirtual 47	java/lang/StringBuilder:toString	()Ljava/lang/String;
    //   1379: astore 20
    //   1381: goto -838 -> 543
    //   1384: iload_2
    //   1385: istore_3
    //   1386: aload 30
    //   1388: aload 17
    //   1390: putfield 512	ct/ae:f	Ljava/lang/String;
    //   1393: aconst_null
    //   1394: astore 20
    //   1396: aload 17
    //   1398: astore 18
    //   1400: aload 20
    //   1402: astore 17
    //   1404: goto -848 -> 556
    //   1407: aload 17
    //   1409: astore 20
    //   1411: aload 19
    //   1413: astore 22
    //   1415: aload 17
    //   1417: astore 21
    //   1419: aload 19
    //   1421: astore 23
    //   1423: getstatic 531	ct/bb:c	Z
    //   1426: ifeq +33 -> 1459
    //   1429: aload 17
    //   1431: astore 20
    //   1433: aload 19
    //   1435: astore 22
    //   1437: aload 17
    //   1439: astore 21
    //   1441: aload 19
    //   1443: astore 23
    //   1445: aload 25
    //   1447: ldc_w 533
    //   1450: aload_1
    //   1451: getfield 379	ct/ac:f	Ljava/lang/String;
    //   1454: invokeinterface 460 3 0
    //   1459: aload 17
    //   1461: astore 20
    //   1463: aload 19
    //   1465: astore 22
    //   1467: aload 17
    //   1469: astore 21
    //   1471: aload 19
    //   1473: astore 23
    //   1475: aload_1
    //   1476: ldc_w 535
    //   1479: new 29	java/lang/StringBuilder
    //   1482: dup
    //   1483: ldc_w 537
    //   1486: invokespecial 34	java/lang/StringBuilder:<init>	(Ljava/lang/String;)V
    //   1489: invokestatic 539	ct/q:f	()Ljava/lang/String;
    //   1492: invokevirtual 43	java/lang/StringBuilder:append	(Ljava/lang/String;)Ljava/lang/StringBuilder;
    //   1495: ldc_w 541
    //   1498: invokevirtual 43	java/lang/StringBuilder:append	(Ljava/lang/String;)Ljava/lang/StringBuilder;
    //   1501: aload_1
    //   1502: getfield 493	ct/ac:s	Ljava/lang/String;
    //   1505: invokevirtual 43	java/lang/StringBuilder:append	(Ljava/lang/String;)Ljava/lang/StringBuilder;
    //   1508: ldc_w 495
    //   1511: invokevirtual 43	java/lang/StringBuilder:append	(Ljava/lang/String;)Ljava/lang/StringBuilder;
    //   1514: iload 4
    //   1516: invokevirtual 38	java/lang/StringBuilder:append	(I)Ljava/lang/StringBuilder;
    //   1519: invokevirtual 47	java/lang/StringBuilder:toString	()Ljava/lang/String;
    //   1522: invokevirtual 380	ct/ac:a	(Ljava/lang/String;Ljava/lang/String;)V
    //   1525: iload 11
    //   1527: ifeq +436 -> 1963
    //   1530: aload 17
    //   1532: astore 20
    //   1534: aload 19
    //   1536: astore 22
    //   1538: aload 17
    //   1540: astore 21
    //   1542: aload 19
    //   1544: astore 23
    //   1546: aload 31
    //   1548: invokeinterface 440 1 0
    //   1553: invokeinterface 446 1 0
    //   1558: astore 32
    //   1560: aload 17
    //   1562: astore 20
    //   1564: aload 19
    //   1566: astore 22
    //   1568: aload 17
    //   1570: astore 21
    //   1572: aload 19
    //   1574: astore 23
    //   1576: aload 32
    //   1578: invokeinterface 451 1 0
    //   1583: ifeq +327 -> 1910
    //   1586: aload 17
    //   1588: astore 20
    //   1590: aload 19
    //   1592: astore 22
    //   1594: aload 17
    //   1596: astore 21
    //   1598: aload 19
    //   1600: astore 23
    //   1602: aload 32
    //   1604: invokeinterface 455 1 0
    //   1609: checkcast 150	java/lang/String
    //   1612: astore 33
    //   1614: aload 17
    //   1616: astore 20
    //   1618: aload 19
    //   1620: astore 22
    //   1622: aload 17
    //   1624: astore 21
    //   1626: aload 19
    //   1628: astore 23
    //   1630: aload 25
    //   1632: aload 33
    //   1634: aload 31
    //   1636: aload 33
    //   1638: invokeinterface 207 2 0
    //   1643: checkcast 150	java/lang/String
    //   1646: invokeinterface 460 3 0
    //   1651: goto -91 -> 1560
    //   1654: astore 20
    //   1656: aload 23
    //   1658: astore 18
    //   1660: aload 21
    //   1662: astore 17
    //   1664: aload 30
    //   1666: new 29	java/lang/StringBuilder
    //   1669: dup
    //   1670: invokespecial 411	java/lang/StringBuilder:<init>	()V
    //   1673: aload_1
    //   1674: getfield 493	ct/ac:s	Ljava/lang/String;
    //   1677: invokevirtual 43	java/lang/StringBuilder:append	(Ljava/lang/String;)Ljava/lang/StringBuilder;
    //   1680: ldc_w 495
    //   1683: invokevirtual 43	java/lang/StringBuilder:append	(Ljava/lang/String;)Ljava/lang/StringBuilder;
    //   1686: iload 4
    //   1688: invokevirtual 38	java/lang/StringBuilder:append	(I)Ljava/lang/StringBuilder;
    //   1691: invokevirtual 47	java/lang/StringBuilder:toString	()Ljava/lang/String;
    //   1694: putfield 498	ct/ae:n	Ljava/lang/String;
    //   1697: aload 30
    //   1699: iload 4
    //   1701: putfield 499	ct/ae:q	I
    //   1704: aload 17
    //   1706: invokestatic 146	android/text/TextUtils:isEmpty	(Ljava/lang/CharSequence;)Z
    //   1709: ifne +19 -> 1728
    //   1712: iload 5
    //   1714: iconst_1
    //   1715: iadd
    //   1716: bipush 6
    //   1718: if_icmple +10 -> 1728
    //   1721: aload 24
    //   1723: bipush -5
    //   1725: putfield 302	ct/ad:a	I
    //   1728: invokestatic 502	ct/q:b	()Ljava/lang/String;
    //   1731: invokestatic 146	android/text/TextUtils:isEmpty	(Ljava/lang/CharSequence;)Z
    //   1734: ifne +159 -> 1893
    //   1737: aload 24
    //   1739: getfield 302	ct/ad:a	I
    //   1742: bipush -21
    //   1744: if_icmpeq +149 -> 1893
    //   1747: aload 24
    //   1749: invokestatic 366	android/os/SystemClock:elapsedRealtime	()J
    //   1752: aload_1
    //   1753: getfield 396	ct/ac:l	J
    //   1756: lsub
    //   1757: l2i
    //   1758: putfield 504	ct/ad:f	I
    //   1761: aload 30
    //   1763: aload 24
    //   1765: getfield 302	ct/ad:a	I
    //   1768: putfield 195	ct/ae:i	I
    //   1771: aload 30
    //   1773: aload 18
    //   1775: putfield 507	ct/ae:A	Ljava/lang/String;
    //   1778: aload 30
    //   1780: aload 24
    //   1782: getfield 504	ct/ad:f	I
    //   1785: putfield 509	ct/ae:j	I
    //   1788: aload 30
    //   1790: invokestatic 366	android/os/SystemClock:elapsedRealtime	()J
    //   1793: lload 13
    //   1795: lsub
    //   1796: l2i
    //   1797: putfield 511	ct/ae:k	I
    //   1800: aload 30
    //   1802: aload 17
    //   1804: putfield 512	ct/ae:f	Ljava/lang/String;
    //   1807: aload_1
    //   1808: getfield 280	ct/ac:k	[B
    //   1811: ifnull +2948 -> 4759
    //   1814: aload 30
    //   1816: aload_1
    //   1817: getfield 280	ct/ac:k	[B
    //   1820: arraylength
    //   1821: i2l
    //   1822: putfield 513	ct/ae:l	J
    //   1825: aload 30
    //   1827: iload 10
    //   1829: putfield 516	ct/ae:x	Z
    //   1832: iload 10
    //   1834: ifeq +17 -> 1851
    //   1837: aload 30
    //   1839: getfield 195	ct/ae:i	I
    //   1842: ifeq +9 -> 1851
    //   1845: aload 30
    //   1847: iconst_1
    //   1848: putfield 519	ct/ae:u	I
    //   1851: aload 30
    //   1853: aload_1
    //   1854: getfield 521	ct/ac:i	Z
    //   1857: putfield 524	ct/ae:z	Z
    //   1860: aload_1
    //   1861: aload 30
    //   1863: invokevirtual 526	ct/ac:a	(Lct/ae;)V
    //   1866: invokestatic 314	ct/p:a	()Lct/p;
    //   1869: new 8	ct/af$a
    //   1872: dup
    //   1873: aload_0
    //   1874: aload 30
    //   1876: invokespecial 317	ct/af$a:<init>	(Lct/af;Lct/ae;)V
    //   1879: invokevirtual 320	ct/p:a	(Ljava/lang/Runnable;)V
    //   1882: ldc_w 528
    //   1885: aload 30
    //   1887: invokevirtual 529	ct/ae:toString	()Ljava/lang/String;
    //   1890: invokestatic 52	ct/bc:a	(Ljava/lang/String;Ljava/lang/String;)V
    //   1893: aload 24
    //   1895: astore 19
    //   1897: aload 24
    //   1899: getfield 302	ct/ad:a	I
    //   1902: bipush -17
    //   1904: if_icmpeq -1829 -> 75
    //   1907: aload 20
    //   1909: athrow
    //   1910: aload 17
    //   1912: astore 20
    //   1914: aload 19
    //   1916: astore 22
    //   1918: aload 17
    //   1920: astore 21
    //   1922: aload 19
    //   1924: astore 23
    //   1926: getstatic 531	ct/bb:c	Z
    //   1929: ifeq +34 -> 1963
    //   1932: aload 17
    //   1934: astore 20
    //   1936: aload 19
    //   1938: astore 22
    //   1940: aload 17
    //   1942: astore 21
    //   1944: aload 19
    //   1946: astore 23
    //   1948: aload 25
    //   1950: ldc_w 533
    //   1953: aload 18
    //   1955: invokestatic 543	ct/bd:d	(Ljava/lang/String;)Ljava/lang/String;
    //   1958: invokeinterface 460 3 0
    //   1963: aload 17
    //   1965: astore 20
    //   1967: aload 19
    //   1969: astore 22
    //   1971: aload 17
    //   1973: astore 21
    //   1975: aload 19
    //   1977: astore 23
    //   1979: aload_1
    //   1980: getfield 280	ct/ac:k	[B
    //   1983: astore 18
    //   1985: aload 18
    //   1987: ifnull +58 -> 2045
    //   1990: aload 17
    //   1992: astore 20
    //   1994: aload 19
    //   1996: astore 22
    //   1998: aload 17
    //   2000: astore 21
    //   2002: aload 19
    //   2004: astore 23
    //   2006: aload 18
    //   2008: arraylength
    //   2009: ifle +36 -> 2045
    //   2012: aload 17
    //   2014: astore 20
    //   2016: aload 19
    //   2018: astore 22
    //   2020: aload 17
    //   2022: astore 21
    //   2024: aload 19
    //   2026: astore 23
    //   2028: aload 25
    //   2030: checkcast 424	org/apache/http/client/methods/HttpPost
    //   2033: new 545	org/apache/http/entity/ByteArrayEntity
    //   2036: dup
    //   2037: aload 18
    //   2039: invokespecial 548	org/apache/http/entity/ByteArrayEntity:<init>	([B)V
    //   2042: invokevirtual 552	org/apache/http/client/methods/HttpPost:setEntity	(Lorg/apache/http/HttpEntity;)V
    //   2045: aload 17
    //   2047: astore 20
    //   2049: aload 19
    //   2051: astore 22
    //   2053: aload 17
    //   2055: astore 21
    //   2057: aload 19
    //   2059: astore 23
    //   2061: ldc 27
    //   2063: new 29	java/lang/StringBuilder
    //   2066: dup
    //   2067: ldc 31
    //   2069: invokespecial 34	java/lang/StringBuilder:<init>	(Ljava/lang/String;)V
    //   2072: aload_1
    //   2073: getfield 554	ct/ac:n	I
    //   2076: invokevirtual 38	java/lang/StringBuilder:append	(I)Ljava/lang/StringBuilder;
    //   2079: ldc 40
    //   2081: invokevirtual 43	java/lang/StringBuilder:append	(Ljava/lang/String;)Ljava/lang/StringBuilder;
    //   2084: aload_1
    //   2085: getfield 556	ct/ac:o	I
    //   2088: invokevirtual 38	java/lang/StringBuilder:append	(I)Ljava/lang/StringBuilder;
    //   2091: invokevirtual 47	java/lang/StringBuilder:toString	()Ljava/lang/String;
    //   2094: invokestatic 52	ct/bc:a	(Ljava/lang/String;Ljava/lang/String;)V
    //   2097: aload 17
    //   2099: astore 20
    //   2101: aload 19
    //   2103: astore 22
    //   2105: aload 17
    //   2107: astore 21
    //   2109: aload 19
    //   2111: astore 23
    //   2113: aload_1
    //   2114: aload 26
    //   2116: getfield 557	ct/z:b	I
    //   2119: sipush 1000
    //   2122: imul
    //   2123: invokevirtual 559	ct/ac:a	(I)V
    //   2126: aload 17
    //   2128: astore 20
    //   2130: aload 19
    //   2132: astore 22
    //   2134: aload 17
    //   2136: astore 21
    //   2138: aload 19
    //   2140: astore 23
    //   2142: aload_1
    //   2143: aload 26
    //   2145: getfield 560	ct/z:a	I
    //   2148: sipush 1000
    //   2151: imul
    //   2152: invokevirtual 562	ct/ac:b	(I)V
    //   2155: aload 17
    //   2157: astore 20
    //   2159: aload 19
    //   2161: astore 22
    //   2163: aload 17
    //   2165: astore 21
    //   2167: aload 19
    //   2169: astore 23
    //   2171: aload_1
    //   2172: getfield 554	ct/ac:n	I
    //   2175: aload_1
    //   2176: getfield 556	ct/ac:o	I
    //   2179: invokestatic 564	ct/af:a	(II)Lorg/apache/http/impl/client/DefaultHttpClient;
    //   2182: astore 18
    //   2184: aload 17
    //   2186: astore 20
    //   2188: aload 19
    //   2190: astore 22
    //   2192: aload 17
    //   2194: astore 21
    //   2196: aload 19
    //   2198: astore 23
    //   2200: invokestatic 366	android/os/SystemClock:elapsedRealtime	()J
    //   2203: lstore 15
    //   2205: aload 17
    //   2207: astore 20
    //   2209: aload 19
    //   2211: astore 22
    //   2213: aload 17
    //   2215: astore 21
    //   2217: aload 19
    //   2219: astore 23
    //   2221: aload 18
    //   2223: aload 25
    //   2225: invokevirtual 568	org/apache/http/impl/client/DefaultHttpClient:execute	(Lorg/apache/http/client/methods/HttpUriRequest;)Lorg/apache/http/HttpResponse;
    //   2228: astore 25
    //   2230: aload 17
    //   2232: astore 20
    //   2234: aload 19
    //   2236: astore 22
    //   2238: aload 17
    //   2240: astore 21
    //   2242: aload 19
    //   2244: astore 23
    //   2246: aload 24
    //   2248: invokestatic 366	android/os/SystemClock:elapsedRealtime	()J
    //   2251: lload 15
    //   2253: lsub
    //   2254: l2i
    //   2255: putfield 570	ct/ad:c	I
    //   2258: aload 17
    //   2260: astore 20
    //   2262: aload 19
    //   2264: astore 22
    //   2266: aload 17
    //   2268: astore 21
    //   2270: aload 19
    //   2272: astore 23
    //   2274: ldc 27
    //   2276: new 29	java/lang/StringBuilder
    //   2279: dup
    //   2280: ldc_w 572
    //   2283: invokespecial 34	java/lang/StringBuilder:<init>	(Ljava/lang/String;)V
    //   2286: aload 24
    //   2288: getfield 570	ct/ad:c	I
    //   2291: invokevirtual 38	java/lang/StringBuilder:append	(I)Ljava/lang/StringBuilder;
    //   2294: invokevirtual 47	java/lang/StringBuilder:toString	()Ljava/lang/String;
    //   2297: invokestatic 52	ct/bc:a	(Ljava/lang/String;Ljava/lang/String;)V
    //   2300: aload 17
    //   2302: astore 20
    //   2304: aload 19
    //   2306: astore 22
    //   2308: aload 17
    //   2310: astore 21
    //   2312: aload 19
    //   2314: astore 23
    //   2316: aload 25
    //   2318: invokeinterface 578 1 0
    //   2323: invokeinterface 583 1 0
    //   2328: istore_3
    //   2329: aload 17
    //   2331: astore 20
    //   2333: aload 19
    //   2335: astore 22
    //   2337: aload 17
    //   2339: astore 21
    //   2341: aload 19
    //   2343: astore 23
    //   2345: aload 24
    //   2347: aload 25
    //   2349: putfield 586	ct/ad:e	Lorg/apache/http/HttpResponse;
    //   2352: aload 19
    //   2354: astore 18
    //   2356: aload 25
    //   2358: ifnull +69 -> 2427
    //   2361: aload 17
    //   2363: astore 20
    //   2365: aload 19
    //   2367: astore 22
    //   2369: aload 17
    //   2371: astore 21
    //   2373: aload 19
    //   2375: astore 23
    //   2377: aload 19
    //   2379: astore 18
    //   2381: aload 25
    //   2383: ldc_w 588
    //   2386: invokeinterface 592 2 0
    //   2391: ifnull +36 -> 2427
    //   2394: aload 17
    //   2396: astore 20
    //   2398: aload 19
    //   2400: astore 22
    //   2402: aload 17
    //   2404: astore 21
    //   2406: aload 19
    //   2408: astore 23
    //   2410: aload 25
    //   2412: ldc_w 588
    //   2415: invokeinterface 592 2 0
    //   2420: invokeinterface 597 1 0
    //   2425: astore 18
    //   2427: aload 17
    //   2429: astore 20
    //   2431: aload 18
    //   2433: astore 22
    //   2435: aload 17
    //   2437: astore 21
    //   2439: aload 18
    //   2441: astore 23
    //   2443: aload 30
    //   2445: aload 24
    //   2447: getfield 570	ct/ad:c	I
    //   2450: putfield 599	ct/ae:g	I
    //   2453: iload_3
    //   2454: lookupswitch	default:+2547->5001, 200:+374->2828, 204:+2035->4489, 301:+1569->4023, 302:+1569->4023, 303:+1569->4023, 307:+1569->4023, 408:+2035->4489, 502:+2035->4489, 503:+2035->4489, 504:+2035->4489
    //   2544: aload 17
    //   2546: astore 20
    //   2548: aload 18
    //   2550: astore 22
    //   2552: aload 17
    //   2554: astore 21
    //   2556: aload 18
    //   2558: astore 23
    //   2560: aload 24
    //   2562: iload_3
    //   2563: putfield 302	ct/ad:a	I
    //   2566: iload 10
    //   2568: istore 12
    //   2570: iload 11
    //   2572: istore 10
    //   2574: iload 12
    //   2576: istore 11
    //   2578: aload 30
    //   2580: new 29	java/lang/StringBuilder
    //   2583: dup
    //   2584: invokespecial 411	java/lang/StringBuilder:<init>	()V
    //   2587: aload_1
    //   2588: getfield 493	ct/ac:s	Ljava/lang/String;
    //   2591: invokevirtual 43	java/lang/StringBuilder:append	(Ljava/lang/String;)Ljava/lang/StringBuilder;
    //   2594: ldc_w 495
    //   2597: invokevirtual 43	java/lang/StringBuilder:append	(Ljava/lang/String;)Ljava/lang/StringBuilder;
    //   2600: iload 4
    //   2602: invokevirtual 38	java/lang/StringBuilder:append	(I)Ljava/lang/StringBuilder;
    //   2605: invokevirtual 47	java/lang/StringBuilder:toString	()Ljava/lang/String;
    //   2608: putfield 498	ct/ae:n	Ljava/lang/String;
    //   2611: aload 30
    //   2613: iload 4
    //   2615: putfield 499	ct/ae:q	I
    //   2618: aload 17
    //   2620: invokestatic 146	android/text/TextUtils:isEmpty	(Ljava/lang/CharSequence;)Z
    //   2623: ifeq +1903 -> 4526
    //   2626: iload 4
    //   2628: iconst_1
    //   2629: iadd
    //   2630: istore 4
    //   2632: iconst_0
    //   2633: istore_3
    //   2634: invokestatic 502	ct/q:b	()Ljava/lang/String;
    //   2637: invokestatic 146	android/text/TextUtils:isEmpty	(Ljava/lang/CharSequence;)Z
    //   2640: ifne +159 -> 2799
    //   2643: aload 24
    //   2645: getfield 302	ct/ad:a	I
    //   2648: bipush -21
    //   2650: if_icmpeq +149 -> 2799
    //   2653: aload 24
    //   2655: invokestatic 366	android/os/SystemClock:elapsedRealtime	()J
    //   2658: aload_1
    //   2659: getfield 396	ct/ac:l	J
    //   2662: lsub
    //   2663: l2i
    //   2664: putfield 504	ct/ad:f	I
    //   2667: aload 30
    //   2669: aload 24
    //   2671: getfield 302	ct/ad:a	I
    //   2674: putfield 195	ct/ae:i	I
    //   2677: aload 30
    //   2679: aload 18
    //   2681: putfield 507	ct/ae:A	Ljava/lang/String;
    //   2684: aload 30
    //   2686: aload 24
    //   2688: getfield 504	ct/ad:f	I
    //   2691: putfield 509	ct/ae:j	I
    //   2694: aload 30
    //   2696: invokestatic 366	android/os/SystemClock:elapsedRealtime	()J
    //   2699: lload 13
    //   2701: lsub
    //   2702: l2i
    //   2703: putfield 511	ct/ae:k	I
    //   2706: aload 30
    //   2708: aload 17
    //   2710: putfield 512	ct/ae:f	Ljava/lang/String;
    //   2713: aload_1
    //   2714: getfield 280	ct/ac:k	[B
    //   2717: ifnull +1838 -> 4555
    //   2720: aload 30
    //   2722: aload_1
    //   2723: getfield 280	ct/ac:k	[B
    //   2726: arraylength
    //   2727: i2l
    //   2728: putfield 513	ct/ae:l	J
    //   2731: aload 30
    //   2733: iload 11
    //   2735: putfield 516	ct/ae:x	Z
    //   2738: iload 11
    //   2740: ifeq +17 -> 2757
    //   2743: aload 30
    //   2745: getfield 195	ct/ae:i	I
    //   2748: ifeq +9 -> 2757
    //   2751: aload 30
    //   2753: iconst_1
    //   2754: putfield 519	ct/ae:u	I
    //   2757: aload 30
    //   2759: aload_1
    //   2760: getfield 521	ct/ac:i	Z
    //   2763: putfield 524	ct/ae:z	Z
    //   2766: aload_1
    //   2767: aload 30
    //   2769: invokevirtual 526	ct/ac:a	(Lct/ae;)V
    //   2772: invokestatic 314	ct/p:a	()Lct/p;
    //   2775: new 8	ct/af$a
    //   2778: dup
    //   2779: aload_0
    //   2780: aload 30
    //   2782: invokespecial 317	ct/af$a:<init>	(Lct/af;Lct/ae;)V
    //   2785: invokevirtual 320	ct/p:a	(Ljava/lang/Runnable;)V
    //   2788: ldc_w 528
    //   2791: aload 30
    //   2793: invokevirtual 529	ct/ae:toString	()Ljava/lang/String;
    //   2796: invokestatic 52	ct/bc:a	(Ljava/lang/String;Ljava/lang/String;)V
    //   2799: aload 24
    //   2801: astore 19
    //   2803: aload 24
    //   2805: getfield 302	ct/ad:a	I
    //   2808: bipush -17
    //   2810: if_icmpeq -2735 -> 75
    //   2813: iload_2
    //   2814: istore 5
    //   2816: iload 4
    //   2818: istore_2
    //   2819: iload_3
    //   2820: istore 4
    //   2822: iload 5
    //   2824: istore_3
    //   2825: goto -1605 -> 1220
    //   2828: aload 17
    //   2830: astore 20
    //   2832: aload 18
    //   2834: astore 22
    //   2836: aload 17
    //   2838: astore 21
    //   2840: aload 18
    //   2842: astore 23
    //   2844: aload 25
    //   2846: invokeinterface 603 1 0
    //   2851: invokeinterface 609 1 0
    //   2856: astore 19
    //   2858: iconst_1
    //   2859: istore 12
    //   2861: aload_1
    //   2862: getfield 612	ct/ac:h	Z
    //   2865: ifeq +1132 -> 3997
    //   2868: iconst_0
    //   2869: istore_3
    //   2870: aload_1
    //   2871: getfield 615	ct/ac:m	I
    //   2874: istore 6
    //   2876: iload 6
    //   2878: newarray <illegal type>
    //   2880: astore 20
    //   2882: invokestatic 366	android/os/SystemClock:elapsedRealtime	()J
    //   2885: lstore 15
    //   2887: iload_3
    //   2888: iload 6
    //   2890: if_icmpge +325 -> 3215
    //   2893: aload 19
    //   2895: aload 20
    //   2897: iload_3
    //   2898: iload 6
    //   2900: iload_3
    //   2901: isub
    //   2902: invokevirtual 621	java/io/InputStream:read	([BII)I
    //   2905: istore 9
    //   2907: iload 9
    //   2909: iconst_m1
    //   2910: if_icmpeq +305 -> 3215
    //   2913: iload_3
    //   2914: iload 9
    //   2916: iadd
    //   2917: istore_3
    //   2918: goto -31 -> 2887
    //   2921: astore 20
    //   2923: aload 19
    //   2925: invokevirtual 624	java/io/InputStream:close	()V
    //   2928: aload 24
    //   2930: bipush -8
    //   2932: putfield 302	ct/ad:a	I
    //   2935: aload 30
    //   2937: new 29	java/lang/StringBuilder
    //   2940: dup
    //   2941: ldc_w 626
    //   2944: invokespecial 34	java/lang/StringBuilder:<init>	(Ljava/lang/String;)V
    //   2947: iload 6
    //   2949: invokevirtual 38	java/lang/StringBuilder:append	(I)Ljava/lang/StringBuilder;
    //   2952: invokevirtual 47	java/lang/StringBuilder:toString	()Ljava/lang/String;
    //   2955: putfield 309	ct/ae:p	Ljava/lang/String;
    //   2958: aload 30
    //   2960: iload 6
    //   2962: i2l
    //   2963: putfield 628	ct/ae:m	J
    //   2966: aload 30
    //   2968: new 29	java/lang/StringBuilder
    //   2971: dup
    //   2972: invokespecial 411	java/lang/StringBuilder:<init>	()V
    //   2975: aload_1
    //   2976: getfield 493	ct/ac:s	Ljava/lang/String;
    //   2979: invokevirtual 43	java/lang/StringBuilder:append	(Ljava/lang/String;)Ljava/lang/StringBuilder;
    //   2982: ldc_w 495
    //   2985: invokevirtual 43	java/lang/StringBuilder:append	(Ljava/lang/String;)Ljava/lang/StringBuilder;
    //   2988: iload 4
    //   2990: invokevirtual 38	java/lang/StringBuilder:append	(I)Ljava/lang/StringBuilder;
    //   2993: invokevirtual 47	java/lang/StringBuilder:toString	()Ljava/lang/String;
    //   2996: putfield 498	ct/ae:n	Ljava/lang/String;
    //   2999: aload 30
    //   3001: iload 4
    //   3003: putfield 499	ct/ae:q	I
    //   3006: aload 17
    //   3008: invokestatic 146	android/text/TextUtils:isEmpty	(Ljava/lang/CharSequence;)Z
    //   3011: ifne +19 -> 3030
    //   3014: iload 5
    //   3016: iconst_1
    //   3017: iadd
    //   3018: bipush 6
    //   3020: if_icmple +10 -> 3030
    //   3023: aload 24
    //   3025: bipush -5
    //   3027: putfield 302	ct/ad:a	I
    //   3030: invokestatic 502	ct/q:b	()Ljava/lang/String;
    //   3033: invokestatic 146	android/text/TextUtils:isEmpty	(Ljava/lang/CharSequence;)Z
    //   3036: ifne +153 -> 3189
    //   3039: aload 24
    //   3041: getfield 302	ct/ad:a	I
    //   3044: bipush -21
    //   3046: if_icmpeq +143 -> 3189
    //   3049: aload 24
    //   3051: invokestatic 366	android/os/SystemClock:elapsedRealtime	()J
    //   3054: aload_1
    //   3055: getfield 396	ct/ac:l	J
    //   3058: lsub
    //   3059: l2i
    //   3060: putfield 504	ct/ad:f	I
    //   3063: aload 30
    //   3065: aload 24
    //   3067: getfield 302	ct/ad:a	I
    //   3070: putfield 195	ct/ae:i	I
    //   3073: aload 30
    //   3075: aload 18
    //   3077: putfield 507	ct/ae:A	Ljava/lang/String;
    //   3080: aload 30
    //   3082: aload 24
    //   3084: getfield 504	ct/ad:f	I
    //   3087: putfield 509	ct/ae:j	I
    //   3090: aload 30
    //   3092: invokestatic 366	android/os/SystemClock:elapsedRealtime	()J
    //   3095: lload 13
    //   3097: lsub
    //   3098: l2i
    //   3099: putfield 511	ct/ae:k	I
    //   3102: aload 30
    //   3104: aload 17
    //   3106: putfield 512	ct/ae:f	Ljava/lang/String;
    //   3109: aload_1
    //   3110: getfield 280	ct/ac:k	[B
    //   3113: ifnull +93 -> 3206
    //   3116: aload 30
    //   3118: aload_1
    //   3119: getfield 280	ct/ac:k	[B
    //   3122: arraylength
    //   3123: i2l
    //   3124: putfield 513	ct/ae:l	J
    //   3127: aload 30
    //   3129: iconst_1
    //   3130: putfield 516	ct/ae:x	Z
    //   3133: aload 30
    //   3135: getfield 195	ct/ae:i	I
    //   3138: ifeq +9 -> 3147
    //   3141: aload 30
    //   3143: iconst_1
    //   3144: putfield 519	ct/ae:u	I
    //   3147: aload 30
    //   3149: aload_1
    //   3150: getfield 521	ct/ac:i	Z
    //   3153: putfield 524	ct/ae:z	Z
    //   3156: aload_1
    //   3157: aload 30
    //   3159: invokevirtual 526	ct/ac:a	(Lct/ae;)V
    //   3162: invokestatic 314	ct/p:a	()Lct/p;
    //   3165: new 8	ct/af$a
    //   3168: dup
    //   3169: aload_0
    //   3170: aload 30
    //   3172: invokespecial 317	ct/af$a:<init>	(Lct/af;Lct/ae;)V
    //   3175: invokevirtual 320	ct/p:a	(Ljava/lang/Runnable;)V
    //   3178: ldc_w 528
    //   3181: aload 30
    //   3183: invokevirtual 529	ct/ae:toString	()Ljava/lang/String;
    //   3186: invokestatic 52	ct/bc:a	(Ljava/lang/String;Ljava/lang/String;)V
    //   3189: aload 24
    //   3191: astore 19
    //   3193: aload 24
    //   3195: getfield 302	ct/ad:a	I
    //   3198: bipush -17
    //   3200: if_icmpne -3125 -> 75
    //   3203: aload 24
    //   3205: areturn
    //   3206: aload 30
    //   3208: lconst_0
    //   3209: putfield 513	ct/ae:l	J
    //   3212: goto -85 -> 3127
    //   3215: aload 24
    //   3217: invokestatic 366	android/os/SystemClock:elapsedRealtime	()J
    //   3220: lload 15
    //   3222: lsub
    //   3223: l2i
    //   3224: putfield 630	ct/ad:d	I
    //   3227: aload 30
    //   3229: aload 24
    //   3231: getfield 630	ct/ad:d	I
    //   3234: putfield 632	ct/ae:h	I
    //   3237: aload 25
    //   3239: ifnull +394 -> 3633
    //   3242: aload 25
    //   3244: ldc_w 634
    //   3247: invokeinterface 592 2 0
    //   3252: ifnull +381 -> 3633
    //   3255: aload 25
    //   3257: ldc_w 634
    //   3260: invokeinterface 592 2 0
    //   3265: invokeinterface 597 1 0
    //   3270: astore 21
    //   3272: aload 21
    //   3274: invokestatic 146	android/text/TextUtils:isEmpty	(Ljava/lang/CharSequence;)Z
    //   3277: ifne +16 -> 3293
    //   3280: aload 30
    //   3282: aload 21
    //   3284: invokestatic 639	java/lang/Long:valueOf	(Ljava/lang/String;)Ljava/lang/Long;
    //   3287: invokevirtual 642	java/lang/Long:longValue	()J
    //   3290: putfield 628	ct/ae:m	J
    //   3293: ldc 27
    //   3295: new 29	java/lang/StringBuilder
    //   3298: dup
    //   3299: ldc_w 644
    //   3302: invokespecial 34	java/lang/StringBuilder:<init>	(Ljava/lang/String;)V
    //   3305: aload 24
    //   3307: getfield 630	ct/ad:d	I
    //   3310: invokevirtual 38	java/lang/StringBuilder:append	(I)Ljava/lang/StringBuilder;
    //   3313: ldc_w 646
    //   3316: invokevirtual 43	java/lang/StringBuilder:append	(Ljava/lang/String;)Ljava/lang/StringBuilder;
    //   3319: iload_3
    //   3320: invokevirtual 38	java/lang/StringBuilder:append	(I)Ljava/lang/StringBuilder;
    //   3323: ldc_w 648
    //   3326: invokevirtual 43	java/lang/StringBuilder:append	(Ljava/lang/String;)Ljava/lang/StringBuilder;
    //   3329: iload 6
    //   3331: invokevirtual 38	java/lang/StringBuilder:append	(I)Ljava/lang/StringBuilder;
    //   3334: invokevirtual 47	java/lang/StringBuilder:toString	()Ljava/lang/String;
    //   3337: invokestatic 52	ct/bc:a	(Ljava/lang/String;Ljava/lang/String;)V
    //   3340: iload_3
    //   3341: iload 6
    //   3343: if_icmplt +330 -> 3673
    //   3346: aload 30
    //   3348: new 29	java/lang/StringBuilder
    //   3351: dup
    //   3352: ldc_w 650
    //   3355: invokespecial 34	java/lang/StringBuilder:<init>	(Ljava/lang/String;)V
    //   3358: iload_3
    //   3359: invokevirtual 38	java/lang/StringBuilder:append	(I)Ljava/lang/StringBuilder;
    //   3362: invokevirtual 47	java/lang/StringBuilder:toString	()Ljava/lang/String;
    //   3365: putfield 309	ct/ae:p	Ljava/lang/String;
    //   3368: aload 24
    //   3370: iconst_m1
    //   3371: putfield 302	ct/ad:a	I
    //   3374: aload 19
    //   3376: invokevirtual 624	java/io/InputStream:close	()V
    //   3379: aload 24
    //   3381: getfield 302	ct/ad:a	I
    //   3384: ifne +1606 -> 4990
    //   3387: aload 30
    //   3389: iconst_0
    //   3390: putfield 519	ct/ae:u	I
    //   3393: aload 30
    //   3395: new 29	java/lang/StringBuilder
    //   3398: dup
    //   3399: invokespecial 411	java/lang/StringBuilder:<init>	()V
    //   3402: aload_1
    //   3403: getfield 493	ct/ac:s	Ljava/lang/String;
    //   3406: invokevirtual 43	java/lang/StringBuilder:append	(Ljava/lang/String;)Ljava/lang/StringBuilder;
    //   3409: ldc_w 495
    //   3412: invokevirtual 43	java/lang/StringBuilder:append	(Ljava/lang/String;)Ljava/lang/StringBuilder;
    //   3415: iload 4
    //   3417: invokevirtual 38	java/lang/StringBuilder:append	(I)Ljava/lang/StringBuilder;
    //   3420: invokevirtual 47	java/lang/StringBuilder:toString	()Ljava/lang/String;
    //   3423: putfield 498	ct/ae:n	Ljava/lang/String;
    //   3426: aload 30
    //   3428: iload 4
    //   3430: putfield 499	ct/ae:q	I
    //   3433: aload 17
    //   3435: invokestatic 146	android/text/TextUtils:isEmpty	(Ljava/lang/CharSequence;)Z
    //   3438: ifne +19 -> 3457
    //   3441: iload 5
    //   3443: iconst_1
    //   3444: iadd
    //   3445: bipush 6
    //   3447: if_icmple +10 -> 3457
    //   3450: aload 24
    //   3452: bipush -5
    //   3454: putfield 302	ct/ad:a	I
    //   3457: invokestatic 502	ct/q:b	()Ljava/lang/String;
    //   3460: invokestatic 146	android/text/TextUtils:isEmpty	(Ljava/lang/CharSequence;)Z
    //   3463: ifne +153 -> 3616
    //   3466: aload 24
    //   3468: getfield 302	ct/ad:a	I
    //   3471: bipush -21
    //   3473: if_icmpeq +143 -> 3616
    //   3476: aload 24
    //   3478: invokestatic 366	android/os/SystemClock:elapsedRealtime	()J
    //   3481: aload_1
    //   3482: getfield 396	ct/ac:l	J
    //   3485: lsub
    //   3486: l2i
    //   3487: putfield 504	ct/ad:f	I
    //   3490: aload 30
    //   3492: aload 24
    //   3494: getfield 302	ct/ad:a	I
    //   3497: putfield 195	ct/ae:i	I
    //   3500: aload 30
    //   3502: aload 18
    //   3504: putfield 507	ct/ae:A	Ljava/lang/String;
    //   3507: aload 30
    //   3509: aload 24
    //   3511: getfield 504	ct/ad:f	I
    //   3514: putfield 509	ct/ae:j	I
    //   3517: aload 30
    //   3519: invokestatic 366	android/os/SystemClock:elapsedRealtime	()J
    //   3522: lload 13
    //   3524: lsub
    //   3525: l2i
    //   3526: putfield 511	ct/ae:k	I
    //   3529: aload 30
    //   3531: aload 17
    //   3533: putfield 512	ct/ae:f	Ljava/lang/String;
    //   3536: aload_1
    //   3537: getfield 280	ct/ac:k	[B
    //   3540: ifnull +474 -> 4014
    //   3543: aload 30
    //   3545: aload_1
    //   3546: getfield 280	ct/ac:k	[B
    //   3549: arraylength
    //   3550: i2l
    //   3551: putfield 513	ct/ae:l	J
    //   3554: aload 30
    //   3556: iconst_1
    //   3557: putfield 516	ct/ae:x	Z
    //   3560: aload 30
    //   3562: getfield 195	ct/ae:i	I
    //   3565: ifeq +9 -> 3574
    //   3568: aload 30
    //   3570: iconst_1
    //   3571: putfield 519	ct/ae:u	I
    //   3574: aload 30
    //   3576: aload_1
    //   3577: getfield 521	ct/ac:i	Z
    //   3580: putfield 524	ct/ae:z	Z
    //   3583: aload_1
    //   3584: aload 30
    //   3586: invokevirtual 526	ct/ac:a	(Lct/ae;)V
    //   3589: invokestatic 314	ct/p:a	()Lct/p;
    //   3592: new 8	ct/af$a
    //   3595: dup
    //   3596: aload_0
    //   3597: aload 30
    //   3599: invokespecial 317	ct/af$a:<init>	(Lct/af;Lct/ae;)V
    //   3602: invokevirtual 320	ct/p:a	(Ljava/lang/Runnable;)V
    //   3605: ldc_w 528
    //   3608: aload 30
    //   3610: invokevirtual 529	ct/ae:toString	()Ljava/lang/String;
    //   3613: invokestatic 52	ct/bc:a	(Ljava/lang/String;Ljava/lang/String;)V
    //   3616: aload 24
    //   3618: astore 19
    //   3620: aload 24
    //   3622: getfield 302	ct/ad:a	I
    //   3625: bipush -17
    //   3627: if_icmpne -3552 -> 75
    //   3630: aload 24
    //   3632: areturn
    //   3633: iload_3
    //   3634: i2l
    //   3635: lstore 15
    //   3637: aload 30
    //   3639: lload 15
    //   3641: putfield 628	ct/ae:m	J
    //   3644: goto -351 -> 3293
    //   3647: astore 19
    //   3649: iload 11
    //   3651: istore 10
    //   3653: aload 17
    //   3655: astore 20
    //   3657: iconst_1
    //   3658: istore 11
    //   3660: iload_2
    //   3661: istore_3
    //   3662: aload 18
    //   3664: astore 17
    //   3666: aload 20
    //   3668: astore 18
    //   3670: goto -2784 -> 886
    //   3673: aload 24
    //   3675: iload_3
    //   3676: newarray <illegal type>
    //   3678: putfield 652	ct/ad:b	[B
    //   3681: aload 20
    //   3683: iconst_0
    //   3684: aload 24
    //   3686: getfield 652	ct/ad:b	[B
    //   3689: iconst_0
    //   3690: iload_3
    //   3691: invokestatic 658	java/lang/System:arraycopy	(Ljava/lang/Object;ILjava/lang/Object;II)V
    //   3694: aload 24
    //   3696: iconst_0
    //   3697: putfield 302	ct/ad:a	I
    //   3700: goto -326 -> 3374
    //   3703: astore 20
    //   3705: iconst_1
    //   3706: istore 10
    //   3708: goto -2044 -> 1664
    //   3711: astore 20
    //   3713: aload 19
    //   3715: invokevirtual 624	java/io/InputStream:close	()V
    //   3718: aload 24
    //   3720: bipush -8
    //   3722: putfield 302	ct/ad:a	I
    //   3725: aload 30
    //   3727: new 29	java/lang/StringBuilder
    //   3730: dup
    //   3731: ldc_w 626
    //   3734: invokespecial 34	java/lang/StringBuilder:<init>	(Ljava/lang/String;)V
    //   3737: iload 6
    //   3739: invokevirtual 38	java/lang/StringBuilder:append	(I)Ljava/lang/StringBuilder;
    //   3742: invokevirtual 47	java/lang/StringBuilder:toString	()Ljava/lang/String;
    //   3745: putfield 309	ct/ae:p	Ljava/lang/String;
    //   3748: aload 30
    //   3750: new 29	java/lang/StringBuilder
    //   3753: dup
    //   3754: invokespecial 411	java/lang/StringBuilder:<init>	()V
    //   3757: aload_1
    //   3758: getfield 493	ct/ac:s	Ljava/lang/String;
    //   3761: invokevirtual 43	java/lang/StringBuilder:append	(Ljava/lang/String;)Ljava/lang/StringBuilder;
    //   3764: ldc_w 495
    //   3767: invokevirtual 43	java/lang/StringBuilder:append	(Ljava/lang/String;)Ljava/lang/StringBuilder;
    //   3770: iload 4
    //   3772: invokevirtual 38	java/lang/StringBuilder:append	(I)Ljava/lang/StringBuilder;
    //   3775: invokevirtual 47	java/lang/StringBuilder:toString	()Ljava/lang/String;
    //   3778: putfield 498	ct/ae:n	Ljava/lang/String;
    //   3781: aload 30
    //   3783: iload 4
    //   3785: putfield 499	ct/ae:q	I
    //   3788: aload 17
    //   3790: invokestatic 146	android/text/TextUtils:isEmpty	(Ljava/lang/CharSequence;)Z
    //   3793: ifne +19 -> 3812
    //   3796: iload 5
    //   3798: iconst_1
    //   3799: iadd
    //   3800: bipush 6
    //   3802: if_icmple +10 -> 3812
    //   3805: aload 24
    //   3807: bipush -5
    //   3809: putfield 302	ct/ad:a	I
    //   3812: invokestatic 502	ct/q:b	()Ljava/lang/String;
    //   3815: invokestatic 146	android/text/TextUtils:isEmpty	(Ljava/lang/CharSequence;)Z
    //   3818: ifne +153 -> 3971
    //   3821: aload 24
    //   3823: getfield 302	ct/ad:a	I
    //   3826: bipush -21
    //   3828: if_icmpeq +143 -> 3971
    //   3831: aload 24
    //   3833: invokestatic 366	android/os/SystemClock:elapsedRealtime	()J
    //   3836: aload_1
    //   3837: getfield 396	ct/ac:l	J
    //   3840: lsub
    //   3841: l2i
    //   3842: putfield 504	ct/ad:f	I
    //   3845: aload 30
    //   3847: aload 24
    //   3849: getfield 302	ct/ad:a	I
    //   3852: putfield 195	ct/ae:i	I
    //   3855: aload 30
    //   3857: aload 18
    //   3859: putfield 507	ct/ae:A	Ljava/lang/String;
    //   3862: aload 30
    //   3864: aload 24
    //   3866: getfield 504	ct/ad:f	I
    //   3869: putfield 509	ct/ae:j	I
    //   3872: aload 30
    //   3874: invokestatic 366	android/os/SystemClock:elapsedRealtime	()J
    //   3877: lload 13
    //   3879: lsub
    //   3880: l2i
    //   3881: putfield 511	ct/ae:k	I
    //   3884: aload 30
    //   3886: aload 17
    //   3888: putfield 512	ct/ae:f	Ljava/lang/String;
    //   3891: aload_1
    //   3892: getfield 280	ct/ac:k	[B
    //   3895: ifnull +93 -> 3988
    //   3898: aload 30
    //   3900: aload_1
    //   3901: getfield 280	ct/ac:k	[B
    //   3904: arraylength
    //   3905: i2l
    //   3906: putfield 513	ct/ae:l	J
    //   3909: aload 30
    //   3911: iconst_1
    //   3912: putfield 516	ct/ae:x	Z
    //   3915: aload 30
    //   3917: getfield 195	ct/ae:i	I
    //   3920: ifeq +9 -> 3929
    //   3923: aload 30
    //   3925: iconst_1
    //   3926: putfield 519	ct/ae:u	I
    //   3929: aload 30
    //   3931: aload_1
    //   3932: getfield 521	ct/ac:i	Z
    //   3935: putfield 524	ct/ae:z	Z
    //   3938: aload_1
    //   3939: aload 30
    //   3941: invokevirtual 526	ct/ac:a	(Lct/ae;)V
    //   3944: invokestatic 314	ct/p:a	()Lct/p;
    //   3947: new 8	ct/af$a
    //   3950: dup
    //   3951: aload_0
    //   3952: aload 30
    //   3954: invokespecial 317	ct/af$a:<init>	(Lct/af;Lct/ae;)V
    //   3957: invokevirtual 320	ct/p:a	(Ljava/lang/Runnable;)V
    //   3960: ldc_w 528
    //   3963: aload 30
    //   3965: invokevirtual 529	ct/ae:toString	()Ljava/lang/String;
    //   3968: invokestatic 52	ct/bc:a	(Ljava/lang/String;Ljava/lang/String;)V
    //   3971: aload 24
    //   3973: astore 19
    //   3975: aload 24
    //   3977: getfield 302	ct/ad:a	I
    //   3980: bipush -17
    //   3982: if_icmpne -3907 -> 75
    //   3985: aload 24
    //   3987: areturn
    //   3988: aload 30
    //   3990: lconst_0
    //   3991: putfield 513	ct/ae:l	J
    //   3994: goto -85 -> 3909
    //   3997: ldc 27
    //   3999: ldc_w 660
    //   4002: invokestatic 178	ct/bc:b	(Ljava/lang/String;Ljava/lang/String;)V
    //   4005: aload 24
    //   4007: iconst_0
    //   4008: putfield 302	ct/ad:a	I
    //   4011: goto -632 -> 3379
    //   4014: aload 30
    //   4016: lconst_0
    //   4017: putfield 513	ct/ae:l	J
    //   4020: goto -466 -> 3554
    //   4023: aload 17
    //   4025: astore 20
    //   4027: aload 18
    //   4029: astore 22
    //   4031: aload 17
    //   4033: astore 21
    //   4035: aload 18
    //   4037: astore 23
    //   4039: aload 24
    //   4041: bipush -21
    //   4043: putfield 302	ct/ad:a	I
    //   4046: aload 17
    //   4048: astore 20
    //   4050: aload 18
    //   4052: astore 22
    //   4054: aload 17
    //   4056: astore 21
    //   4058: aload 18
    //   4060: astore 23
    //   4062: aload 25
    //   4064: ldc_w 662
    //   4067: invokeinterface 592 2 0
    //   4072: astore 19
    //   4074: aload 19
    //   4076: ifnull +109 -> 4185
    //   4079: aload 17
    //   4081: astore 20
    //   4083: aload 18
    //   4085: astore 22
    //   4087: aload 17
    //   4089: astore 21
    //   4091: aload 18
    //   4093: astore 23
    //   4095: aload 19
    //   4097: invokeinterface 597 1 0
    //   4102: astore 17
    //   4104: aload 17
    //   4106: astore 20
    //   4108: aload 18
    //   4110: astore 22
    //   4112: aload 17
    //   4114: astore 21
    //   4116: aload 18
    //   4118: astore 23
    //   4120: ldc 27
    //   4122: new 29	java/lang/StringBuilder
    //   4125: dup
    //   4126: ldc_w 664
    //   4129: invokespecial 34	java/lang/StringBuilder:<init>	(Ljava/lang/String;)V
    //   4132: aload 17
    //   4134: invokevirtual 43	java/lang/StringBuilder:append	(Ljava/lang/String;)Ljava/lang/StringBuilder;
    //   4137: invokevirtual 47	java/lang/StringBuilder:toString	()Ljava/lang/String;
    //   4140: invokestatic 178	ct/bc:b	(Ljava/lang/String;Ljava/lang/String;)V
    //   4143: aload 30
    //   4145: iconst_1
    //   4146: putfield 666	ct/ae:e	Z
    //   4149: aload 17
    //   4151: invokestatic 146	android/text/TextUtils:isEmpty	(Ljava/lang/CharSequence;)Z
    //   4154: istore 11
    //   4156: iload 11
    //   4158: ifeq +54 -> 4212
    //   4161: aload 24
    //   4163: bipush -6
    //   4165: putfield 302	ct/ad:a	I
    //   4168: aconst_null
    //   4169: astore 17
    //   4171: iconst_1
    //   4172: istore 12
    //   4174: iload 10
    //   4176: istore 11
    //   4178: iload 12
    //   4180: istore 10
    //   4182: goto -1604 -> 2578
    //   4185: aload 17
    //   4187: astore 20
    //   4189: aload 18
    //   4191: astore 22
    //   4193: aload 17
    //   4195: astore 21
    //   4197: aload 18
    //   4199: astore 23
    //   4201: ldc 27
    //   4203: ldc_w 668
    //   4206: invokestatic 160	ct/bc:c	(Ljava/lang/String;Ljava/lang/String;)V
    //   4209: goto -66 -> 4143
    //   4212: aload_1
    //   4213: getfield 670	ct/ac:r	Z
    //   4216: ifne +760 -> 4976
    //   4219: ldc 27
    //   4221: ldc_w 672
    //   4224: invokestatic 178	ct/bc:b	(Ljava/lang/String;Ljava/lang/String;)V
    //   4227: aload 24
    //   4229: bipush -7
    //   4231: putfield 302	ct/ad:a	I
    //   4234: aload 30
    //   4236: new 29	java/lang/StringBuilder
    //   4239: dup
    //   4240: invokespecial 411	java/lang/StringBuilder:<init>	()V
    //   4243: aload_1
    //   4244: getfield 493	ct/ac:s	Ljava/lang/String;
    //   4247: invokevirtual 43	java/lang/StringBuilder:append	(Ljava/lang/String;)Ljava/lang/StringBuilder;
    //   4250: ldc_w 495
    //   4253: invokevirtual 43	java/lang/StringBuilder:append	(Ljava/lang/String;)Ljava/lang/StringBuilder;
    //   4256: iload 4
    //   4258: invokevirtual 38	java/lang/StringBuilder:append	(I)Ljava/lang/StringBuilder;
    //   4261: invokevirtual 47	java/lang/StringBuilder:toString	()Ljava/lang/String;
    //   4264: putfield 498	ct/ae:n	Ljava/lang/String;
    //   4267: aload 30
    //   4269: iload 4
    //   4271: putfield 499	ct/ae:q	I
    //   4274: aload 17
    //   4276: invokestatic 146	android/text/TextUtils:isEmpty	(Ljava/lang/CharSequence;)Z
    //   4279: ifne +19 -> 4298
    //   4282: iload 5
    //   4284: iconst_1
    //   4285: iadd
    //   4286: bipush 6
    //   4288: if_icmple +10 -> 4298
    //   4291: aload 24
    //   4293: bipush -5
    //   4295: putfield 302	ct/ad:a	I
    //   4298: invokestatic 502	ct/q:b	()Ljava/lang/String;
    //   4301: invokestatic 146	android/text/TextUtils:isEmpty	(Ljava/lang/CharSequence;)Z
    //   4304: ifne +159 -> 4463
    //   4307: aload 24
    //   4309: getfield 302	ct/ad:a	I
    //   4312: bipush -21
    //   4314: if_icmpeq +149 -> 4463
    //   4317: aload 24
    //   4319: invokestatic 366	android/os/SystemClock:elapsedRealtime	()J
    //   4322: aload_1
    //   4323: getfield 396	ct/ac:l	J
    //   4326: lsub
    //   4327: l2i
    //   4328: putfield 504	ct/ad:f	I
    //   4331: aload 30
    //   4333: aload 24
    //   4335: getfield 302	ct/ad:a	I
    //   4338: putfield 195	ct/ae:i	I
    //   4341: aload 30
    //   4343: aload 18
    //   4345: putfield 507	ct/ae:A	Ljava/lang/String;
    //   4348: aload 30
    //   4350: aload 24
    //   4352: getfield 504	ct/ad:f	I
    //   4355: putfield 509	ct/ae:j	I
    //   4358: aload 30
    //   4360: invokestatic 366	android/os/SystemClock:elapsedRealtime	()J
    //   4363: lload 13
    //   4365: lsub
    //   4366: l2i
    //   4367: putfield 511	ct/ae:k	I
    //   4370: aload 30
    //   4372: aload 17
    //   4374: putfield 512	ct/ae:f	Ljava/lang/String;
    //   4377: aload_1
    //   4378: getfield 280	ct/ac:k	[B
    //   4381: ifnull +99 -> 4480
    //   4384: aload 30
    //   4386: aload_1
    //   4387: getfield 280	ct/ac:k	[B
    //   4390: arraylength
    //   4391: i2l
    //   4392: putfield 513	ct/ae:l	J
    //   4395: aload 30
    //   4397: iload 10
    //   4399: putfield 516	ct/ae:x	Z
    //   4402: iload 10
    //   4404: ifeq +17 -> 4421
    //   4407: aload 30
    //   4409: getfield 195	ct/ae:i	I
    //   4412: ifeq +9 -> 4421
    //   4415: aload 30
    //   4417: iconst_1
    //   4418: putfield 519	ct/ae:u	I
    //   4421: aload 30
    //   4423: aload_1
    //   4424: getfield 521	ct/ac:i	Z
    //   4427: putfield 524	ct/ae:z	Z
    //   4430: aload_1
    //   4431: aload 30
    //   4433: invokevirtual 526	ct/ac:a	(Lct/ae;)V
    //   4436: invokestatic 314	ct/p:a	()Lct/p;
    //   4439: new 8	ct/af$a
    //   4442: dup
    //   4443: aload_0
    //   4444: aload 30
    //   4446: invokespecial 317	ct/af$a:<init>	(Lct/af;Lct/ae;)V
    //   4449: invokevirtual 320	ct/p:a	(Ljava/lang/Runnable;)V
    //   4452: ldc_w 528
    //   4455: aload 30
    //   4457: invokevirtual 529	ct/ae:toString	()Ljava/lang/String;
    //   4460: invokestatic 52	ct/bc:a	(Ljava/lang/String;Ljava/lang/String;)V
    //   4463: aload 24
    //   4465: astore 19
    //   4467: aload 24
    //   4469: getfield 302	ct/ad:a	I
    //   4472: bipush -17
    //   4474: if_icmpne -4399 -> 75
    //   4477: aload 24
    //   4479: areturn
    //   4480: aload 30
    //   4482: lconst_0
    //   4483: putfield 513	ct/ae:l	J
    //   4486: goto -91 -> 4395
    //   4489: aload 17
    //   4491: astore 20
    //   4493: aload 18
    //   4495: astore 22
    //   4497: aload 17
    //   4499: astore 21
    //   4501: aload 18
    //   4503: astore 23
    //   4505: aload 24
    //   4507: iload_3
    //   4508: putfield 302	ct/ad:a	I
    //   4511: iload 11
    //   4513: istore 12
    //   4515: iload 10
    //   4517: istore 11
    //   4519: iload 12
    //   4521: istore 10
    //   4523: goto -1945 -> 2578
    //   4526: iload 5
    //   4528: iconst_1
    //   4529: iadd
    //   4530: istore_3
    //   4531: iload_3
    //   4532: bipush 6
    //   4534: if_icmple +439 -> 4973
    //   4537: iload 4
    //   4539: iconst_1
    //   4540: iadd
    //   4541: istore 4
    //   4543: iconst_0
    //   4544: istore_3
    //   4545: aload 24
    //   4547: bipush -5
    //   4549: putfield 302	ct/ad:a	I
    //   4552: goto -1918 -> 2634
    //   4555: aload 30
    //   4557: lconst_0
    //   4558: putfield 513	ct/ae:l	J
    //   4561: goto -1830 -> 2731
    //   4564: aload 19
    //   4566: instanceof 674
    //   4569: ifeq +9 -> 4578
    //   4572: bipush -11
    //   4574: istore_2
    //   4575: goto -3633 -> 942
    //   4578: aload 19
    //   4580: instanceof 676
    //   4583: ifeq +9 -> 4592
    //   4586: bipush -13
    //   4588: istore_2
    //   4589: goto -3647 -> 942
    //   4592: aload 19
    //   4594: instanceof 678
    //   4597: ifeq +9 -> 4606
    //   4600: bipush -14
    //   4602: istore_2
    //   4603: goto -3661 -> 942
    //   4606: aload 19
    //   4608: instanceof 680
    //   4611: ifeq +9 -> 4620
    //   4614: bipush -15
    //   4616: istore_2
    //   4617: goto -3675 -> 942
    //   4620: aload 19
    //   4622: instanceof 682
    //   4625: ifeq +9 -> 4634
    //   4628: bipush -16
    //   4630: istore_2
    //   4631: goto -3689 -> 942
    //   4634: aload 19
    //   4636: instanceof 684
    //   4639: ifeq +9 -> 4648
    //   4642: bipush -9
    //   4644: istore_2
    //   4645: goto -3703 -> 942
    //   4648: aload 19
    //   4650: instanceof 686
    //   4653: ifeq +9 -> 4662
    //   4656: bipush -22
    //   4658: istore_2
    //   4659: goto -3717 -> 942
    //   4662: aload 19
    //   4664: instanceof 688
    //   4667: ifeq +9 -> 4676
    //   4670: bipush -23
    //   4672: istore_2
    //   4673: goto -3731 -> 942
    //   4676: aload 19
    //   4678: instanceof 690
    //   4681: istore 12
    //   4683: iload 12
    //   4685: ifeq +9 -> 4694
    //   4688: bipush -12
    //   4690: istore_2
    //   4691: goto -3749 -> 942
    //   4694: bipush -3
    //   4696: istore_2
    //   4697: goto -3755 -> 942
    //   4700: bipush -17
    //   4702: istore_2
    //   4703: goto -3761 -> 942
    //   4706: bipush -4
    //   4708: istore_2
    //   4709: goto -3767 -> 942
    //   4712: iload 5
    //   4714: iconst_1
    //   4715: iadd
    //   4716: istore 6
    //   4718: iload 6
    //   4720: istore 5
    //   4722: iload 4
    //   4724: istore_2
    //   4725: iload 6
    //   4727: bipush 6
    //   4729: if_icmple -3704 -> 1025
    //   4732: iload 4
    //   4734: iconst_1
    //   4735: iadd
    //   4736: istore_2
    //   4737: iconst_0
    //   4738: istore 5
    //   4740: aload 24
    //   4742: bipush -5
    //   4744: putfield 302	ct/ad:a	I
    //   4747: goto -3722 -> 1025
    //   4750: aload 30
    //   4752: lconst_0
    //   4753: putfield 513	ct/ae:l	J
    //   4756: goto -3634 -> 1122
    //   4759: aload 30
    //   4761: lconst_0
    //   4762: putfield 513	ct/ae:l	J
    //   4765: goto -2940 -> 1825
    //   4768: aload 20
    //   4770: areturn
    //   4771: astore 19
    //   4773: goto -1845 -> 2928
    //   4776: astore 19
    //   4778: goto -1060 -> 3718
    //   4781: astore 19
    //   4783: goto -1404 -> 3379
    //   4786: astore_1
    //   4787: goto -2894 -> 1893
    //   4790: astore 20
    //   4792: goto -3128 -> 1664
    //   4795: astore 20
    //   4797: aconst_null
    //   4798: astore 17
    //   4800: goto -3136 -> 1664
    //   4803: astore 20
    //   4805: iload 11
    //   4807: istore 10
    //   4809: aload 17
    //   4811: astore 19
    //   4813: aload 18
    //   4815: astore 17
    //   4817: aload 19
    //   4819: astore 18
    //   4821: goto -3157 -> 1664
    //   4824: astore 20
    //   4826: aload 19
    //   4828: astore 18
    //   4830: goto -3166 -> 1664
    //   4833: astore 19
    //   4835: goto -3645 -> 1190
    //   4838: astore 19
    //   4840: iload 10
    //   4842: istore 11
    //   4844: aload 17
    //   4846: astore 20
    //   4848: iconst_1
    //   4849: istore 10
    //   4851: aload 18
    //   4853: astore 17
    //   4855: iload_2
    //   4856: istore_3
    //   4857: aload 20
    //   4859: astore 18
    //   4861: goto -3975 -> 886
    //   4864: astore 19
    //   4866: iload 10
    //   4868: istore 11
    //   4870: aconst_null
    //   4871: astore 20
    //   4873: iconst_1
    //   4874: istore 10
    //   4876: aload 18
    //   4878: astore 17
    //   4880: iload_2
    //   4881: istore_3
    //   4882: aload 20
    //   4884: astore 18
    //   4886: goto -4000 -> 886
    //   4889: astore 20
    //   4891: iload 10
    //   4893: istore 12
    //   4895: iload 11
    //   4897: istore 10
    //   4899: aload 17
    //   4901: astore 18
    //   4903: aload 19
    //   4905: astore 17
    //   4907: aload 20
    //   4909: astore 19
    //   4911: iload 12
    //   4913: istore 11
    //   4915: goto -4029 -> 886
    //   4918: astore 20
    //   4920: iload 10
    //   4922: istore 12
    //   4924: iload 11
    //   4926: istore 10
    //   4928: aload 17
    //   4930: astore 18
    //   4932: aload 19
    //   4934: astore 17
    //   4936: aload 20
    //   4938: astore 19
    //   4940: iload 12
    //   4942: istore 11
    //   4944: goto -4058 -> 886
    //   4947: astore 19
    //   4949: goto -2150 -> 2799
    //   4952: astore_1
    //   4953: goto -490 -> 4463
    //   4956: astore_1
    //   4957: goto -1341 -> 3616
    //   4960: astore_1
    //   4961: goto -990 -> 3971
    //   4964: astore_1
    //   4965: goto -1776 -> 3189
    //   4968: iload_3
    //   4969: istore_2
    //   4970: goto -4555 -> 415
    //   4973: goto -2339 -> 2634
    //   4976: iconst_1
    //   4977: istore 12
    //   4979: iload 10
    //   4981: istore 11
    //   4983: iload 12
    //   4985: istore 10
    //   4987: goto -2409 -> 2578
    //   4990: iload 11
    //   4992: istore 10
    //   4994: iload 12
    //   4996: istore 11
    //   4998: goto -2420 -> 2578
    //   5001: goto -2457 -> 2544
    // Local variable table:
    //   start	length	slot	name	signature
    //   0	5004	0	this	af
    //   0	5004	1	paramac	ac
    //   283	4687	2	i	int
    //   200	4769	3	j	int
    //   181	4555	4	k	int
    //   192	4547	5	m	int
    //   2874	1856	6	n	int
    //   162	127	7	i1	int
    //   171	112	8	i2	int
    //   2905	12	9	i3	int
    //   264	4729	10	bool1	boolean
    //   184	4813	11	bool2	boolean
    //   870	4125	12	bool3	boolean
    //   229	4135	13	l1	long
    //   2203	1437	15	l2	long
    //   7	4928	17	localObject1	Object
    //   29	4902	18	localObject2	Object
    //   73	762	19	localObject3	Object
    //   862	70	19	localException1	Exception
    //   1192	2427	19	localObject4	Object
    //   3647	67	19	localException2	Exception
    //   3973	704	19	localObject5	Object
    //   4771	1	19	localException3	Exception
    //   4776	1	19	localException4	Exception
    //   4781	1	19	localException5	Exception
    //   4811	16	19	localObject6	Object
    //   4833	1	19	localOutOfMemoryError1	OutOfMemoryError
    //   4838	1	19	localException6	Exception
    //   4864	40	19	localException7	Exception
    //   4909	30	19	localObject7	Object
    //   4947	1	19	localOutOfMemoryError2	OutOfMemoryError
    //   197	1420	20	localObject8	Object
    //   1654	254	20	localObject9	Object
    //   1912	984	20	localObject10	Object
    //   2921	1	20	localOutOfMemoryError3	OutOfMemoryError
    //   3655	27	20	localObject11	Object
    //   3703	1	20	localObject12	Object
    //   3711	1	20	localOutOfMemoryError4	OutOfMemoryError
    //   4025	744	20	localObject13	Object
    //   4790	1	20	localObject14	Object
    //   4795	1	20	localObject15	Object
    //   4803	1	20	localObject16	Object
    //   4824	1	20	localObject17	Object
    //   4846	37	20	localObject18	Object
    //   4889	19	20	localException8	Exception
    //   4918	19	20	localException9	Exception
    //   490	4010	21	localObject19	Object
    //   562	3934	22	localObject20	Object
    //   570	3934	23	localObject21	Object
    //   238	4503	24	localad	ad
    //   331	3732	25	localObject22	Object
    //   105	2039	26	localz	z
    //   112	275	27	localList	java.util.List
    //   119	140	28	localt	t
    //   178	74	29	str1	String
    //   247	4513	30	localae	ae
    //   678	957	31	localHashMap	java.util.HashMap
    //   766	837	32	localIterator	java.util.Iterator
    //   820	817	33	str2	String
    // Exception table:
    //   from	to	target	type
    //   572	628	862	java/lang/Exception
    //   644	655	862	java/lang/Exception
    //   671	680	862	java/lang/Exception
    //   696	707	862	java/lang/Exception
    //   723	733	862	java/lang/Exception
    //   754	768	862	java/lang/Exception
    //   784	794	862	java/lang/Exception
    //   810	822	862	java/lang/Exception
    //   838	859	862	java/lang/Exception
    //   1423	1429	862	java/lang/Exception
    //   1445	1459	862	java/lang/Exception
    //   1475	1525	862	java/lang/Exception
    //   1546	1560	862	java/lang/Exception
    //   1576	1586	862	java/lang/Exception
    //   1602	1614	862	java/lang/Exception
    //   1630	1651	862	java/lang/Exception
    //   1926	1932	862	java/lang/Exception
    //   1948	1963	862	java/lang/Exception
    //   1979	1985	862	java/lang/Exception
    //   2006	2012	862	java/lang/Exception
    //   2028	2045	862	java/lang/Exception
    //   2061	2097	862	java/lang/Exception
    //   2113	2126	862	java/lang/Exception
    //   2142	2155	862	java/lang/Exception
    //   2171	2184	862	java/lang/Exception
    //   2200	2205	862	java/lang/Exception
    //   2221	2230	862	java/lang/Exception
    //   2246	2258	862	java/lang/Exception
    //   2274	2300	862	java/lang/Exception
    //   2316	2329	862	java/lang/Exception
    //   2345	2352	862	java/lang/Exception
    //   2381	2394	862	java/lang/Exception
    //   2410	2427	862	java/lang/Exception
    //   2443	2453	862	java/lang/Exception
    //   2560	2566	862	java/lang/Exception
    //   2844	2858	862	java/lang/Exception
    //   4039	4046	862	java/lang/Exception
    //   4062	4074	862	java/lang/Exception
    //   4095	4104	862	java/lang/Exception
    //   4120	4143	862	java/lang/Exception
    //   4201	4209	862	java/lang/Exception
    //   4505	4511	862	java/lang/Exception
    //   572	628	1654	finally
    //   644	655	1654	finally
    //   671	680	1654	finally
    //   696	707	1654	finally
    //   723	733	1654	finally
    //   754	768	1654	finally
    //   784	794	1654	finally
    //   810	822	1654	finally
    //   838	859	1654	finally
    //   1423	1429	1654	finally
    //   1445	1459	1654	finally
    //   1475	1525	1654	finally
    //   1546	1560	1654	finally
    //   1576	1586	1654	finally
    //   1602	1614	1654	finally
    //   1630	1651	1654	finally
    //   1926	1932	1654	finally
    //   1948	1963	1654	finally
    //   1979	1985	1654	finally
    //   2006	2012	1654	finally
    //   2028	2045	1654	finally
    //   2061	2097	1654	finally
    //   2113	2126	1654	finally
    //   2142	2155	1654	finally
    //   2171	2184	1654	finally
    //   2200	2205	1654	finally
    //   2221	2230	1654	finally
    //   2246	2258	1654	finally
    //   2274	2300	1654	finally
    //   2316	2329	1654	finally
    //   2345	2352	1654	finally
    //   2381	2394	1654	finally
    //   2410	2427	1654	finally
    //   2443	2453	1654	finally
    //   2560	2566	1654	finally
    //   2844	2858	1654	finally
    //   4039	4046	1654	finally
    //   4062	4074	1654	finally
    //   4095	4104	1654	finally
    //   4120	4143	1654	finally
    //   4201	4209	1654	finally
    //   4505	4511	1654	finally
    //   2876	2882	2921	java/lang/OutOfMemoryError
    //   2861	2868	3647	java/lang/Exception
    //   2870	2876	3647	java/lang/Exception
    //   2876	2882	3647	java/lang/Exception
    //   2882	2887	3647	java/lang/Exception
    //   2893	2907	3647	java/lang/Exception
    //   2928	2966	3647	java/lang/Exception
    //   3215	3237	3647	java/lang/Exception
    //   3242	3293	3647	java/lang/Exception
    //   3293	3340	3647	java/lang/Exception
    //   3346	3374	3647	java/lang/Exception
    //   3379	3393	3647	java/lang/Exception
    //   3637	3644	3647	java/lang/Exception
    //   3673	3681	3647	java/lang/Exception
    //   3681	3700	3647	java/lang/Exception
    //   3718	3748	3647	java/lang/Exception
    //   3997	4011	3647	java/lang/Exception
    //   2861	2868	3703	finally
    //   2870	2876	3703	finally
    //   2876	2882	3703	finally
    //   2882	2887	3703	finally
    //   2893	2907	3703	finally
    //   2923	2928	3703	finally
    //   2928	2966	3703	finally
    //   3215	3237	3703	finally
    //   3242	3293	3703	finally
    //   3293	3340	3703	finally
    //   3346	3374	3703	finally
    //   3374	3379	3703	finally
    //   3379	3393	3703	finally
    //   3637	3644	3703	finally
    //   3673	3681	3703	finally
    //   3681	3700	3703	finally
    //   3713	3718	3703	finally
    //   3718	3748	3703	finally
    //   3997	4011	3703	finally
    //   3673	3681	3711	java/lang/OutOfMemoryError
    //   2923	2928	4771	java/lang/Exception
    //   3713	3718	4776	java/lang/Exception
    //   3374	3379	4781	java/lang/Exception
    //   1860	1893	4786	java/lang/OutOfMemoryError
    //   4143	4156	4790	finally
    //   4212	4234	4790	finally
    //   4161	4168	4795	finally
    //   886	939	4803	finally
    //   942	969	4803	finally
    //   4564	4572	4803	finally
    //   4578	4586	4803	finally
    //   4592	4600	4803	finally
    //   4606	4614	4803	finally
    //   4620	4628	4803	finally
    //   4634	4642	4803	finally
    //   4648	4656	4803	finally
    //   4662	4670	4803	finally
    //   4676	4683	4803	finally
    //   292	320	4824	finally
    //   320	405	4824	finally
    //   409	415	4824	finally
    //   417	425	4824	finally
    //   427	434	4824	finally
    //   436	445	4824	finally
    //   447	484	4824	finally
    //   486	492	4824	finally
    //   498	506	4824	finally
    //   508	519	4824	finally
    //   521	543	4824	finally
    //   545	552	4824	finally
    //   1244	1267	4824	finally
    //   1272	1281	4824	finally
    //   1283	1320	4824	finally
    //   1325	1348	4824	finally
    //   1353	1381	4824	finally
    //   1386	1393	4824	finally
    //   1157	1190	4833	java/lang/OutOfMemoryError
    //   4143	4156	4838	java/lang/Exception
    //   4212	4234	4838	java/lang/Exception
    //   4161	4168	4864	java/lang/Exception
    //   292	320	4889	java/lang/Exception
    //   320	405	4889	java/lang/Exception
    //   409	415	4918	java/lang/Exception
    //   417	425	4918	java/lang/Exception
    //   427	434	4918	java/lang/Exception
    //   436	445	4918	java/lang/Exception
    //   447	484	4918	java/lang/Exception
    //   486	492	4918	java/lang/Exception
    //   498	506	4918	java/lang/Exception
    //   508	519	4918	java/lang/Exception
    //   521	543	4918	java/lang/Exception
    //   545	552	4918	java/lang/Exception
    //   1244	1267	4918	java/lang/Exception
    //   1272	1281	4918	java/lang/Exception
    //   1283	1320	4918	java/lang/Exception
    //   1325	1348	4918	java/lang/Exception
    //   1353	1381	4918	java/lang/Exception
    //   1386	1393	4918	java/lang/Exception
    //   2766	2799	4947	java/lang/OutOfMemoryError
    //   4430	4463	4952	java/lang/OutOfMemoryError
    //   3583	3616	4956	java/lang/OutOfMemoryError
    //   3938	3971	4960	java/lang/OutOfMemoryError
    //   3156	3189	4964	java/lang/OutOfMemoryError
  }
  
  public final ac a(String paramString, byte[] paramArrayOfByte)
  {
    return b(paramString, paramArrayOfByte);
  }
  
  public final ad a(ac paramac)
  {
    bc.b("HttpAccessClientImpl", "doRequest...");
    l = SystemClock.elapsedRealtime();
    try
    {
      paramac = b(paramac);
      return paramac;
    }
    catch (Exception paramac)
    {
      paramac = new ad();
      a = -19;
    }
    return paramac;
  }
  
  final class a
    implements Runnable
  {
    private ae a;
    
    a(ae paramae)
    {
      a = paramae;
    }
    
    public final void run()
    {
      for (;;)
      {
        try
        {
          Object localObject;
          if ((a != null) && (!a.v))
          {
            localObject = InetAddress.getByName(a.c);
            a.t = ((InetAddress)localObject).getHostAddress();
            a.a = new t(a.t, 80);
          }
          if (a.i == 0)
          {
            localObject = a;
            if ((a == null) || (!a.a(b))) {
              continue;
            }
            i = 1;
            if (i == 0) {
              af.a(a);
            }
          }
        }
        catch (Exception localException2)
        {
          int i;
          continue;
        }
        try
        {
          if ((a.z) && (af.a(af.this, a))) {
            af.b(a);
          }
          return;
        }
        catch (Exception localException1)
        {
          return;
        }
        i = 0;
      }
    }
  }
}

/* Location:
 * Qualified Name:     ct.af
 * Java Class Version: 6 (50.0)
 * JD-Core Version:    0.7.1
 */