package ct;

public final class ar
{
  private static ar k = null;
  private String a = "";
  private String b = "";
  private String c = "";
  private String d = "";
  private String e = "";
  private String f = "";
  private String g = "";
  private String h = "";
  private String i = "";
  private String j = "";
  
  /* Error */
  public static void a(android.content.Context paramContext)
  {
    // Byte code:
    //   0: ldc 2
    //   2: monitorenter
    //   3: aload_0
    //   4: ifnull +233 -> 237
    //   7: getstatic 21	ct/ar:k	Lct/ar;
    //   10: ifnonnull +13 -> 23
    //   13: new 2	ct/ar
    //   16: dup
    //   17: invokespecial 49	ct/ar:<init>	()V
    //   20: putstatic 21	ct/ar:k	Lct/ar;
    //   23: getstatic 21	ct/ar:k	Lct/ar;
    //   26: astore_1
    //   27: aload_1
    //   28: monitorenter
    //   29: getstatic 21	ct/ar:k	Lct/ar;
    //   32: astore_2
    //   33: aload_0
    //   34: invokestatic 54	ct/as:a	(Landroid/content/Context;)Lct/as;
    //   37: pop
    //   38: new 56	java/lang/StringBuffer
    //   41: dup
    //   42: invokespecial 57	java/lang/StringBuffer:<init>	()V
    //   45: astore_3
    //   46: aload_3
    //   47: invokestatic 60	ct/as:a	()Ljava/lang/String;
    //   50: invokevirtual 64	java/lang/StringBuffer:append	(Ljava/lang/String;)Ljava/lang/StringBuffer;
    //   53: pop
    //   54: aload_3
    //   55: ldc 66
    //   57: invokevirtual 64	java/lang/StringBuffer:append	(Ljava/lang/String;)Ljava/lang/StringBuffer;
    //   60: pop
    //   61: aload_3
    //   62: invokestatic 68	ct/as:b	()Ljava/lang/String;
    //   65: invokevirtual 64	java/lang/StringBuffer:append	(Ljava/lang/String;)Ljava/lang/StringBuffer;
    //   68: pop
    //   69: aload_3
    //   70: ldc 70
    //   72: invokevirtual 64	java/lang/StringBuffer:append	(Ljava/lang/String;)Ljava/lang/StringBuffer;
    //   75: pop
    //   76: aload_3
    //   77: invokestatic 72	ct/as:c	()Ljava/lang/String;
    //   80: invokevirtual 64	java/lang/StringBuffer:append	(Ljava/lang/String;)Ljava/lang/StringBuffer;
    //   83: pop
    //   84: aload_2
    //   85: aload_3
    //   86: invokevirtual 75	java/lang/StringBuffer:toString	()Ljava/lang/String;
    //   89: invokespecial 78	ct/ar:a	(Ljava/lang/String;)V
    //   92: getstatic 21	ct/ar:k	Lct/ar;
    //   95: invokespecial 81	ct/ar:l	()V
    //   98: getstatic 21	ct/ar:k	Lct/ar;
    //   101: ldc 83
    //   103: invokespecial 85	ct/ar:d	(Ljava/lang/String;)V
    //   106: getstatic 21	ct/ar:k	Lct/ar;
    //   109: aload_0
    //   110: invokestatic 90	ct/aq:c	(Landroid/content/Context;)Ljava/lang/String;
    //   113: invokespecial 92	ct/ar:c	(Ljava/lang/String;)V
    //   116: getstatic 21	ct/ar:k	Lct/ar;
    //   119: astore_2
    //   120: aload_0
    //   121: invokestatic 54	ct/as:a	(Landroid/content/Context;)Lct/as;
    //   124: pop
    //   125: aload_2
    //   126: aload_0
    //   127: invokestatic 94	ct/as:b	(Landroid/content/Context;)Ljava/lang/String;
    //   130: invokespecial 96	ct/ar:e	(Ljava/lang/String;)V
    //   133: getstatic 21	ct/ar:k	Lct/ar;
    //   136: astore_2
    //   137: aload_0
    //   138: invokestatic 54	ct/as:a	(Landroid/content/Context;)Lct/as;
    //   141: pop
    //   142: aload_2
    //   143: aload_0
    //   144: invokestatic 97	ct/as:c	(Landroid/content/Context;)Ljava/lang/String;
    //   147: putfield 37	ct/ar:e	Ljava/lang/String;
    //   150: getstatic 21	ct/ar:k	Lct/ar;
    //   153: astore_2
    //   154: aload_0
    //   155: invokestatic 54	ct/as:a	(Landroid/content/Context;)Lct/as;
    //   158: pop
    //   159: aload_2
    //   160: aload_0
    //   161: invokestatic 99	ct/as:e	(Landroid/content/Context;)Ljava/lang/String;
    //   164: putfield 39	ct/ar:f	Ljava/lang/String;
    //   167: getstatic 21	ct/ar:k	Lct/ar;
    //   170: astore_2
    //   171: aload_0
    //   172: invokestatic 54	ct/as:a	(Landroid/content/Context;)Lct/as;
    //   175: pop
    //   176: aload_2
    //   177: aload_0
    //   178: invokestatic 101	ct/as:d	(Landroid/content/Context;)Ljava/lang/String;
    //   181: putfield 41	ct/ar:g	Ljava/lang/String;
    //   184: getstatic 21	ct/ar:k	Lct/ar;
    //   187: invokestatic 105	ct/q:g	()Ljava/lang/String;
    //   190: invokespecial 107	ct/ar:f	(Ljava/lang/String;)V
    //   193: getstatic 21	ct/ar:k	Lct/ar;
    //   196: aload_0
    //   197: invokestatic 109	ct/aq:a	(Landroid/content/Context;)Ljava/lang/String;
    //   200: invokespecial 111	ct/ar:b	(Ljava/lang/String;)V
    //   203: getstatic 21	ct/ar:k	Lct/ar;
    //   206: astore_2
    //   207: aload_0
    //   208: invokestatic 54	ct/as:a	(Landroid/content/Context;)Lct/as;
    //   211: pop
    //   212: aload_2
    //   213: invokestatic 113	ct/as:d	()Ljava/lang/String;
    //   216: putfield 45	ct/ar:i	Ljava/lang/String;
    //   219: getstatic 21	ct/ar:k	Lct/ar;
    //   222: astore_2
    //   223: aload_0
    //   224: invokestatic 54	ct/as:a	(Landroid/content/Context;)Lct/as;
    //   227: pop
    //   228: aload_2
    //   229: invokestatic 60	ct/as:a	()Ljava/lang/String;
    //   232: putfield 47	ct/ar:j	Ljava/lang/String;
    //   235: aload_1
    //   236: monitorexit
    //   237: ldc 2
    //   239: monitorexit
    //   240: return
    //   241: astore_0
    //   242: aload_1
    //   243: monitorexit
    //   244: aload_0
    //   245: athrow
    //   246: astore_0
    //   247: ldc 2
    //   249: monitorexit
    //   250: aload_0
    //   251: athrow
    // Local variable table:
    //   start	length	slot	name	signature
    //   0	252	0	paramContext	android.content.Context
    //   32	197	2	localar2	ar
    //   45	41	3	localStringBuffer	StringBuffer
    // Exception table:
    //   from	to	target	type
    //   29	237	241	finally
    //   7	23	246	finally
    //   23	29	246	finally
    //   242	246	246	finally
  }
  
  private void a(String paramString)
  {
    try
    {
      a = paramString;
      return;
    }
    finally
    {
      paramString = finally;
      throw paramString;
    }
  }
  
  private void b(String paramString)
  {
    try
    {
      b = paramString;
      return;
    }
    finally
    {
      paramString = finally;
      throw paramString;
    }
  }
  
  private void c(String paramString)
  {
    try
    {
      c = paramString;
      return;
    }
    finally
    {
      paramString = finally;
      throw paramString;
    }
  }
  
  private void d(String paramString) {}
  
  private void e(String paramString)
  {
    try
    {
      d = paramString;
      return;
    }
    finally
    {
      paramString = finally;
      throw paramString;
    }
  }
  
  private void f(String paramString)
  {
    try
    {
      h = paramString;
      return;
    }
    finally
    {
      paramString = finally;
      throw paramString;
    }
  }
  
  public static ar k()
  {
    try
    {
      ar localar = k;
      return localar;
    }
    finally
    {
      localObject = finally;
      throw ((Throwable)localObject);
    }
  }
  
  private void l() {}
  
  public final String a()
  {
    try
    {
      String str = a;
      return str;
    }
    finally
    {
      localObject = finally;
      throw ((Throwable)localObject);
    }
  }
  
  public final String b()
  {
    try
    {
      String str = b;
      return str;
    }
    finally
    {
      localObject = finally;
      throw ((Throwable)localObject);
    }
  }
  
  public final String c()
  {
    try
    {
      String str = c;
      return str;
    }
    finally
    {
      localObject = finally;
      throw ((Throwable)localObject);
    }
  }
  
  public final String d()
  {
    try
    {
      String str = d;
      return str;
    }
    finally
    {
      localObject = finally;
      throw ((Throwable)localObject);
    }
  }
  
  public final String e()
  {
    try
    {
      String str = h;
      return str;
    }
    finally
    {
      localObject = finally;
      throw ((Throwable)localObject);
    }
  }
  
  public final String f()
  {
    return e;
  }
  
  public final String g()
  {
    return f;
  }
  
  public final String h()
  {
    return g;
  }
  
  public final String i()
  {
    return i;
  }
  
  public final String j()
  {
    return j;
  }
}

/* Location:
 * Qualified Name:     ct.ar
 * Java Class Version: 6 (50.0)
 * JD-Core Version:    0.7.1
 */