package ct;

import java.util.concurrent.CountDownLatch;

final class ax$b
  implements Runnable
{
  private CountDownLatch a = null;
  private ax.c b = null;
  private aw c = null;
  
  public ax$b(CountDownLatch paramCountDownLatch, ax.c paramc, aw paramaw)
  {
    a = paramCountDownLatch;
    b = paramc;
    c = paramaw;
  }
  
  /* Error */
  public final void run()
  {
    // Byte code:
    //   0: aload_0
    //   1: getfield 25	ct/ax$b:c	Lct/aw;
    //   4: invokevirtual 35	ct/aw:a	()V
    //   7: aload_0
    //   8: getfield 25	ct/ax$b:c	Lct/aw;
    //   11: getfield 38	ct/aw:c	I
    //   14: putstatic 40	ct/ax:a	I
    //   17: aload_0
    //   18: getfield 25	ct/ax$b:c	Lct/aw;
    //   21: getfield 43	ct/aw:d	I
    //   24: putstatic 45	ct/ax:b	I
    //   27: aload_0
    //   28: getfield 23	ct/ax$b:b	Lct/ax$c;
    //   31: astore_1
    //   32: aload_0
    //   33: getfield 25	ct/ax$b:c	Lct/aw;
    //   36: astore_2
    //   37: aload_2
    //   38: ifnull +33 -> 71
    //   41: aload_1
    //   42: getfield 50	ct/ax$c:a	Ljava/util/concurrent/locks/Lock;
    //   45: invokeinterface 55 1 0
    //   50: aload_1
    //   51: getfield 57	ct/ax$c:b	Lct/aw;
    //   54: ifnonnull +25 -> 79
    //   57: aload_1
    //   58: aload_2
    //   59: putfield 57	ct/ax$c:b	Lct/aw;
    //   62: aload_1
    //   63: getfield 50	ct/ax$c:a	Ljava/util/concurrent/locks/Lock;
    //   66: invokeinterface 60 1 0
    //   71: aload_0
    //   72: getfield 21	ct/ax$b:a	Ljava/util/concurrent/CountDownLatch;
    //   75: invokevirtual 65	java/util/concurrent/CountDownLatch:countDown	()V
    //   78: return
    //   79: aload_2
    //   80: getfield 68	ct/aw:b	Ljava/net/Socket;
    //   83: invokevirtual 73	java/net/Socket:close	()V
    //   86: goto -24 -> 62
    //   89: astore_2
    //   90: goto -28 -> 62
    //   93: astore_2
    //   94: aload_1
    //   95: getfield 50	ct/ax$c:a	Ljava/util/concurrent/locks/Lock;
    //   98: invokeinterface 60 1 0
    //   103: aload_2
    //   104: athrow
    //   105: astore_1
    //   106: return
    // Local variable table:
    //   start	length	slot	name	signature
    //   0	107	0	this	b
    //   31	64	1	localc	ax.c
    //   105	1	1	localThrowable	Throwable
    //   36	44	2	localaw	aw
    //   89	1	2	localIOException	java.io.IOException
    //   93	11	2	localObject	Object
    // Exception table:
    //   from	to	target	type
    //   79	86	89	java/io/IOException
    //   50	62	93	finally
    //   79	86	93	finally
    //   0	37	105	java/lang/Throwable
    //   41	50	105	java/lang/Throwable
    //   62	71	105	java/lang/Throwable
    //   71	78	105	java/lang/Throwable
    //   94	105	105	java/lang/Throwable
  }
}

/* Location:
 * Qualified Name:     ct.ax.b
 * Java Class Version: 6 (50.0)
 * JD-Core Version:    0.7.1
 */