package ct;

import android.annotation.SuppressLint;
import android.content.Context;
import android.content.pm.ApplicationInfo;
import android.content.pm.PackageInfo;
import android.content.pm.PackageManager;
import android.content.pm.PackageManager.NameNotFoundException;
import android.location.LocationManager;
import android.net.wifi.WifiManager;
import android.os.Build.VERSION;
import android.os.Bundle;
import android.telephony.TelephonyManager;
import android.util.Pair;
import com.tencent.map.geolocation.internal.TencentHttpClient;
import com.tencent.map.geolocation.internal.TencentHttpClientFactory;
import java.lang.reflect.Method;
import java.util.ArrayList;
import java.util.HashMap;
import java.util.Iterator;
import java.util.List;
import java.util.concurrent.CountDownLatch;
import java.util.concurrent.ExecutorService;
import java.util.concurrent.LinkedBlockingQueue;
import java.util.concurrent.ThreadPoolExecutor;
import java.util.concurrent.TimeUnit;
import org.eclipse.jdt.annotation.Nullable;

public class bj
{
  private static volatile bj l;
  public final Context a;
  private final bk b;
  private final ExecutorService c;
  private final HashMap d;
  private final PackageManager e;
  private final TelephonyManager f;
  private final WifiManager g;
  private final LocationManager h;
  private final cd i;
  private final TencentHttpClient j;
  private final CountDownLatch k;
  private List m;
  
  @SuppressLint({"NewApi"})
  private bj(Context paramContext)
  {
    a = paramContext;
    e = paramContext.getPackageManager();
    f = ((TelephonyManager)paramContext.getSystemService("phone"));
    g = ((WifiManager)paramContext.getSystemService("wifi"));
    h = ((LocationManager)paramContext.getSystemService("location"));
    i = new cc(this);
    Object localObject = new Bundle();
    ((Bundle)localObject).putString("channelId", b.a.c(paramContext.getPackageName()));
    j = TencentHttpClientFactory.getInstance().getTencentHttpClient(paramContext, (Bundle)localObject);
    localObject = new ThreadPoolExecutor(1, 5, 60000L, TimeUnit.MILLISECONDS, new LinkedBlockingQueue());
    if (Build.VERSION.SDK_INT >= 9) {
      ((ThreadPoolExecutor)localObject).allowCoreThreadTimeOut(true);
    }
    c = ((ExecutorService)localObject);
    d = new HashMap();
    d.put("cell", new bo("cell"));
    d.put("so", new bp(paramContext, "so"));
    b = new bk(this);
    b.h = b(paramContext);
    k = new CountDownLatch(1);
    new Thread(new Runnable()
    {
      public final void run()
      {
        k();
        bj.a(bj.this).countDown();
      }
    }).start();
  }
  
  public static bj a(Context paramContext)
  {
    if (l == null) {}
    try
    {
      if (l == null) {
        l = new bj(paramContext);
      }
      return l;
    }
    finally {}
  }
  
  private static String b(Context paramContext)
  {
    try
    {
      paramContext = getPackageManagergetApplicationInfogetPackageName128metaData;
      if (paramContext != null)
      {
        if (paramContext.containsKey("TencentGeoLocationSDK")) {
          return paramContext.getString("TencentGeoLocationSDK");
        }
        if (paramContext.containsKey("TencentMapSDK"))
        {
          paramContext = paramContext.getString("TencentMapSDK");
          return paramContext;
        }
        return "";
      }
    }
    catch (PackageManager.NameNotFoundException paramContext) {}
    return "";
  }
  
  private PackageInfo l()
  {
    try
    {
      PackageInfo localPackageInfo = e.getPackageInfo(a.getPackageName(), 0);
      return localPackageInfo;
    }
    catch (PackageManager.NameNotFoundException localNameNotFoundException) {}
    return new PackageInfo();
  }
  
  @Nullable
  public final TelephonyManager a()
  {
    return f;
  }
  
  public final bn a(String paramString)
  {
    paramString = (bn)d.get(paramString);
    if (paramString != null) {
      return paramString;
    }
    return bm.a;
  }
  
  public final String a(String paramString, byte[] paramArrayOfByte)
  {
    paramString = j.postSync(paramString, paramArrayOfByte);
    paramArrayOfByte = b.a.c((byte[])first);
    if (paramArrayOfByte != null) {
      return new String(paramArrayOfByte, (String)second);
    }
    b.a.a("AppContext", "postSync: inflate failed");
    return "{}";
  }
  
  public final void a(Object paramObject)
  {
    for (;;)
    {
      Object localObject3;
      try
      {
        if (m == null) {
          m = new ArrayList();
        }
        Object localObject1 = m.iterator();
        if (!((Iterator)localObject1).hasNext()) {
          break label191;
        }
        localObject2 = nextc;
        if (paramObject != localObject2) {
          continue;
        }
        n = 1;
        if (n != 0) {
          return;
        }
        localObject1 = paramObject.getClass().getDeclaredMethods();
        int i1 = localObject1.length;
        n = 0;
        if (n >= i1) {
          continue;
        }
        localObject2 = localObject1[n];
        localObject3 = ((Method)localObject2).getName();
        if ((!((String)localObject3).startsWith("on")) || (!((String)localObject3).endsWith("Event"))) {
          break label184;
        }
        localObject3 = ((Method)localObject2).getParameterTypes();
        if (localObject3.length != 1) {
          throw new IllegalArgumentException("EventHandler methods must specify a single Object paramter.");
        }
      }
      finally {}
      Object localObject2 = new dc(localObject3[0], (Method)localObject2, paramObject);
      m.add(localObject2);
      label184:
      n += 1;
      continue;
      label191:
      int n = 0;
    }
  }
  
  @Nullable
  public final WifiManager b()
  {
    return g;
  }
  
  public final void b(Object paramObject)
  {
    List localList;
    try
    {
      localList = m;
      if (localList == null) {
        break label119;
      }
      ArrayList localArrayList = new ArrayList();
      Iterator localIterator = localList.iterator();
      while (localIterator.hasNext())
      {
        dc localdc = (dc)localIterator.next();
        Object localObject = c;
        if ((localObject == null) || (localObject == paramObject)) {
          localArrayList.add(localdc);
        }
      }
      paramObject = localArrayList.iterator();
    }
    finally {}
    while (((Iterator)paramObject).hasNext()) {
      localList.remove((dc)((Iterator)paramObject).next());
    }
    label119:
  }
  
  @Nullable
  public final LocationManager c()
  {
    return h;
  }
  
  /* Error */
  public final void c(@Nullable Object paramObject)
  {
    // Byte code:
    //   0: aload_0
    //   1: monitorenter
    //   2: aload_1
    //   3: ifnonnull +6 -> 9
    //   6: aload_0
    //   7: monitorexit
    //   8: return
    //   9: aload_0
    //   10: getfield 281	ct/bj:m	Ljava/util/List;
    //   13: astore_3
    //   14: aload_3
    //   15: ifnull -9 -> 6
    //   18: aload_3
    //   19: invokeinterface 290 1 0
    //   24: astore_3
    //   25: aload_3
    //   26: invokeinterface 296 1 0
    //   31: ifeq -25 -> 6
    //   34: aload_3
    //   35: invokeinterface 300 1 0
    //   40: checkcast 302	ct/dc
    //   43: astore 4
    //   45: aload_1
    //   46: invokevirtual 308	java/lang/Object:getClass	()Ljava/lang/Class;
    //   49: aload 4
    //   51: getfield 355	ct/dc:a	Ljava/lang/Class;
    //   54: invokevirtual 358	java/lang/Object:equals	(Ljava/lang/Object;)Z
    //   57: istore_2
    //   58: iload_2
    //   59: ifeq -34 -> 25
    //   62: aload 4
    //   64: getfield 361	ct/dc:b	Ljava/lang/reflect/Method;
    //   67: aload 4
    //   69: getfield 304	ct/dc:c	Ljava/lang/Object;
    //   72: iconst_1
    //   73: anewarray 4	java/lang/Object
    //   76: dup
    //   77: iconst_0
    //   78: aload_1
    //   79: aastore
    //   80: invokevirtual 365	java/lang/reflect/Method:invoke	(Ljava/lang/Object;[Ljava/lang/Object;)Ljava/lang/Object;
    //   83: pop
    //   84: goto -59 -> 25
    //   87: astore 4
    //   89: ldc_w 272
    //   92: ldc -34
    //   94: aload 4
    //   96: invokestatic 368	ct/b$a:a	(Ljava/lang/String;Ljava/lang/String;Ljava/lang/Throwable;)V
    //   99: goto -74 -> 25
    //   102: astore_1
    //   103: aload_0
    //   104: monitorexit
    //   105: aload_1
    //   106: athrow
    // Local variable table:
    //   start	length	slot	name	signature
    //   0	107	0	this	bj
    //   0	107	1	paramObject	Object
    //   57	2	2	bool	boolean
    //   13	22	3	localObject	Object
    //   43	25	4	localdc	dc
    //   87	8	4	localException	Exception
    // Exception table:
    //   from	to	target	type
    //   62	84	87	java/lang/Exception
    //   9	14	102	finally
    //   18	25	102	finally
    //   25	58	102	finally
    //   62	84	102	finally
    //   89	99	102	finally
  }
  
  public final boolean d()
  {
    return f != null;
  }
  
  public final boolean e()
  {
    return g != null;
  }
  
  public final boolean f()
  {
    return h != null;
  }
  
  public final cd g()
  {
    return i;
  }
  
  public final bk h()
  {
    return b;
  }
  
  public final bk i()
  {
    if (-1L > 0L) {}
    try
    {
      if (!k.await(-1L, TimeUnit.MILLISECONDS))
      {
        return null;
        k.await();
      }
      return b;
    }
    catch (InterruptedException localInterruptedException) {}
    return null;
  }
  
  public final ExecutorService j()
  {
    return c;
  }
  
  /* Error */
  final void k()
  {
    // Byte code:
    //   0: ldc_w 272
    //   3: iconst_4
    //   4: ldc_w 390
    //   7: invokestatic 393	ct/b$a:a	(Ljava/lang/String;ILjava/lang/String;)V
    //   10: aload_0
    //   11: getfield 165	ct/bj:b	Lct/bk;
    //   14: astore 7
    //   16: new 395	java/io/FileInputStream
    //   19: dup
    //   20: new 397	java/io/File
    //   23: dup
    //   24: invokestatic 403	android/os/Environment:getExternalStorageDirectory	()Ljava/io/File;
    //   27: ldc_w 405
    //   30: invokespecial 408	java/io/File:<init>	(Ljava/io/File;Ljava/lang/String;)V
    //   33: invokespecial 411	java/io/FileInputStream:<init>	(Ljava/io/File;)V
    //   36: astore 5
    //   38: aload 5
    //   40: ifnonnull +711 -> 751
    //   43: aload_0
    //   44: getfield 42	ct/bj:a	Landroid/content/Context;
    //   47: invokevirtual 415	android/content/Context:getAssets	()Landroid/content/res/AssetManager;
    //   50: ldc_w 405
    //   53: invokevirtual 421	android/content/res/AssetManager:open	(Ljava/lang/String;)Ljava/io/InputStream;
    //   56: astore 6
    //   58: aload 6
    //   60: ifnull +675 -> 735
    //   63: sipush 1024
    //   66: newarray <illegal type>
    //   68: astore 5
    //   70: new 423	org/json/JSONObject
    //   73: dup
    //   74: new 264	java/lang/String
    //   77: dup
    //   78: aload 5
    //   80: iconst_0
    //   81: aload 6
    //   83: aload 5
    //   85: invokevirtual 429	java/io/InputStream:read	([B)I
    //   88: invokespecial 432	java/lang/String:<init>	([BII)V
    //   91: invokespecial 433	org/json/JSONObject:<init>	(Ljava/lang/String;)V
    //   94: astore 5
    //   96: aload 6
    //   98: invokestatic 436	ct/b$a:a	(Ljava/io/Closeable;)V
    //   101: aload 5
    //   103: ifnull +162 -> 265
    //   106: aload 5
    //   108: ldc_w 437
    //   111: iconst_0
    //   112: invokevirtual 441	org/json/JSONObject:optBoolean	(Ljava/lang/String;Z)Z
    //   115: pop
    //   116: aload 5
    //   118: ldc_w 443
    //   121: iconst_0
    //   122: invokevirtual 441	org/json/JSONObject:optBoolean	(Ljava/lang/String;Z)Z
    //   125: pop
    //   126: aload 5
    //   128: ldc_w 445
    //   131: iconst_0
    //   132: invokevirtual 441	org/json/JSONObject:optBoolean	(Ljava/lang/String;Z)Z
    //   135: pop
    //   136: aload 5
    //   138: ldc_w 447
    //   141: iconst_0
    //   142: invokevirtual 441	org/json/JSONObject:optBoolean	(Ljava/lang/String;Z)Z
    //   145: pop
    //   146: aload 5
    //   148: ldc_w 449
    //   151: iconst_0
    //   152: invokevirtual 441	org/json/JSONObject:optBoolean	(Ljava/lang/String;Z)Z
    //   155: pop
    //   156: aload 5
    //   158: ldc_w 451
    //   161: ldc2_w 452
    //   164: invokevirtual 457	org/json/JSONObject:optLong	(Ljava/lang/String;J)J
    //   167: pop2
    //   168: aload 5
    //   170: ldc_w 459
    //   173: ldc2_w 460
    //   176: invokevirtual 457	org/json/JSONObject:optLong	(Ljava/lang/String;J)J
    //   179: pop2
    //   180: aload 7
    //   182: aload 5
    //   184: ldc_w 463
    //   187: iconst_1
    //   188: invokevirtual 441	org/json/JSONObject:optBoolean	(Ljava/lang/String;Z)Z
    //   191: putfield 467	ct/bk:r	Z
    //   194: aload 7
    //   196: aload 5
    //   198: ldc_w 469
    //   201: iconst_0
    //   202: invokevirtual 441	org/json/JSONObject:optBoolean	(Ljava/lang/String;Z)Z
    //   205: putfield 471	ct/bk:s	Z
    //   208: aload 7
    //   210: aload 5
    //   212: ldc_w 472
    //   215: iconst_1
    //   216: invokevirtual 441	org/json/JSONObject:optBoolean	(Ljava/lang/String;Z)Z
    //   219: putfield 475	ct/bk:t	Z
    //   222: aload 5
    //   224: ldc_w 477
    //   227: ldc_w 479
    //   230: invokevirtual 483	org/json/JSONObject:optString	(Ljava/lang/String;Ljava/lang/String;)Ljava/lang/String;
    //   233: astore 6
    //   235: aload 7
    //   237: aload 6
    //   239: putfield 485	ct/bk:o	Ljava/lang/String;
    //   242: aload 7
    //   244: aload 6
    //   246: putfield 488	ct/bk:q	Ljava/lang/String;
    //   249: aload 7
    //   251: aload 5
    //   253: ldc_w 490
    //   256: ldc_w 492
    //   259: invokevirtual 483	org/json/JSONObject:optString	(Ljava/lang/String;Ljava/lang/String;)Ljava/lang/String;
    //   262: putfield 495	ct/bk:p	Ljava/lang/String;
    //   265: aload_0
    //   266: invokespecial 497	ct/bj:l	()Landroid/content/pm/PackageInfo;
    //   269: astore 6
    //   271: aload 6
    //   273: getfield 500	android/content/pm/PackageInfo:versionCode	I
    //   276: istore_1
    //   277: aload 7
    //   279: aload 6
    //   281: getfield 503	android/content/pm/PackageInfo:versionName	Ljava/lang/String;
    //   284: putfield 505	ct/bk:i	Ljava/lang/String;
    //   287: aload_0
    //   288: getfield 42	ct/bj:a	Landroid/content/Context;
    //   291: invokevirtual 508	android/content/Context:getApplicationInfo	()Landroid/content/pm/ApplicationInfo;
    //   294: aload_0
    //   295: getfield 50	ct/bj:e	Landroid/content/pm/PackageManager;
    //   298: invokevirtual 512	android/content/pm/ApplicationInfo:loadLabel	(Landroid/content/pm/PackageManager;)Ljava/lang/CharSequence;
    //   301: astore 5
    //   303: aload 5
    //   305: ifnull +408 -> 713
    //   308: aload 5
    //   310: invokevirtual 515	java/lang/Object:toString	()Ljava/lang/String;
    //   313: astore 5
    //   315: aload 7
    //   317: aload 5
    //   319: putfield 517	ct/bk:j	Ljava/lang/String;
    //   322: aload_0
    //   323: getfield 60	ct/bj:f	Landroid/telephony/TelephonyManager;
    //   326: astore 5
    //   328: aload 5
    //   330: ifnull +103 -> 433
    //   333: iconst_2
    //   334: newarray <illegal type>
    //   336: astore 8
    //   338: aload 5
    //   340: aload 8
    //   342: invokestatic 522	ct/cv:a	(Landroid/telephony/TelephonyManager;[I)V
    //   345: aload 7
    //   347: aload 8
    //   349: iconst_0
    //   350: iaload
    //   351: putfield 524	ct/bk:k	I
    //   354: aload 7
    //   356: aload 8
    //   358: iconst_1
    //   359: iaload
    //   360: putfield 526	ct/bk:l	I
    //   363: aload 7
    //   365: aload 5
    //   367: invokevirtual 530	android/telephony/TelephonyManager:getPhoneType	()I
    //   370: putfield 532	ct/bk:b	I
    //   373: aload 5
    //   375: invokevirtual 535	android/telephony/TelephonyManager:getDeviceId	()Ljava/lang/String;
    //   378: getstatic 540	ct/da:a	Ljava/util/regex/Pattern;
    //   381: invokestatic 543	ct/da:a	(Ljava/lang/String;Ljava/util/regex/Pattern;)Ljava/lang/String;
    //   384: astore 8
    //   386: aload 5
    //   388: invokevirtual 546	android/telephony/TelephonyManager:getSubscriberId	()Ljava/lang/String;
    //   391: getstatic 548	ct/da:b	Ljava/util/regex/Pattern;
    //   394: invokestatic 543	ct/da:a	(Ljava/lang/String;Ljava/util/regex/Pattern;)Ljava/lang/String;
    //   397: astore 9
    //   399: aload 5
    //   401: invokevirtual 551	android/telephony/TelephonyManager:getLine1Number	()Ljava/lang/String;
    //   404: getstatic 553	ct/da:c	Ljava/util/regex/Pattern;
    //   407: invokestatic 543	ct/da:a	(Ljava/lang/String;Ljava/util/regex/Pattern;)Ljava/lang/String;
    //   410: astore 5
    //   412: aload 7
    //   414: aload 8
    //   416: putfield 555	ct/bk:c	Ljava/lang/String;
    //   419: aload 7
    //   421: aload 9
    //   423: putfield 557	ct/bk:d	Ljava/lang/String;
    //   426: aload 7
    //   428: aload 5
    //   430: putfield 559	ct/bk:e	Ljava/lang/String;
    //   433: aload 7
    //   435: aload_0
    //   436: invokestatic 564	ct/db:c	(Lct/bj;)Ljava/lang/String;
    //   439: ldc_w 566
    //   442: ldc -34
    //   444: invokevirtual 569	java/lang/String:replaceAll	(Ljava/lang/String;Ljava/lang/String;)Ljava/lang/String;
    //   447: getstatic 575	java/util/Locale:ENGLISH	Ljava/util/Locale;
    //   450: invokevirtual 579	java/lang/String:toUpperCase	(Ljava/util/Locale;)Ljava/lang/String;
    //   453: getstatic 581	ct/da:d	Ljava/util/regex/Pattern;
    //   456: invokestatic 543	ct/da:a	(Ljava/lang/String;Ljava/util/regex/Pattern;)Ljava/lang/String;
    //   459: putfield 583	ct/bk:f	Ljava/lang/String;
    //   462: aload_0
    //   463: getfield 50	ct/bj:e	Landroid/content/pm/PackageManager;
    //   466: astore 5
    //   468: aload 5
    //   470: ldc_w 585
    //   473: invokevirtual 588	android/content/pm/PackageManager:hasSystemFeature	(Ljava/lang/String;)Z
    //   476: istore_2
    //   477: aload 5
    //   479: ldc_w 590
    //   482: invokevirtual 588	android/content/pm/PackageManager:hasSystemFeature	(Ljava/lang/String;)Z
    //   485: istore_3
    //   486: aload 5
    //   488: ldc_w 592
    //   491: invokevirtual 588	android/content/pm/PackageManager:hasSystemFeature	(Ljava/lang/String;)Z
    //   494: istore 4
    //   496: ldc_w 272
    //   499: new 594	java/lang/StringBuilder
    //   502: dup
    //   503: ldc_w 596
    //   506: invokespecial 597	java/lang/StringBuilder:<init>	(Ljava/lang/String;)V
    //   509: iload_2
    //   510: invokevirtual 601	java/lang/StringBuilder:append	(Z)Ljava/lang/StringBuilder;
    //   513: ldc_w 603
    //   516: invokevirtual 606	java/lang/StringBuilder:append	(Ljava/lang/String;)Ljava/lang/StringBuilder;
    //   519: iload_3
    //   520: invokevirtual 601	java/lang/StringBuilder:append	(Z)Ljava/lang/StringBuilder;
    //   523: ldc_w 608
    //   526: invokevirtual 606	java/lang/StringBuilder:append	(Ljava/lang/String;)Ljava/lang/StringBuilder;
    //   529: iload 4
    //   531: invokevirtual 601	java/lang/StringBuilder:append	(Z)Ljava/lang/StringBuilder;
    //   534: invokevirtual 609	java/lang/StringBuilder:toString	()Ljava/lang/String;
    //   537: invokestatic 276	ct/b$a:a	(Ljava/lang/String;Ljava/lang/String;)V
    //   540: new 594	java/lang/StringBuilder
    //   543: dup
    //   544: invokespecial 610	java/lang/StringBuilder:<init>	()V
    //   547: astore 5
    //   549: aload 5
    //   551: ldc_w 612
    //   554: invokevirtual 606	java/lang/StringBuilder:append	(Ljava/lang/String;)Ljava/lang/StringBuilder;
    //   557: getstatic 617	android/os/Build:MODEL	Ljava/lang/String;
    //   560: invokevirtual 606	java/lang/StringBuilder:append	(Ljava/lang/String;)Ljava/lang/StringBuilder;
    //   563: ldc_w 619
    //   566: invokevirtual 606	java/lang/StringBuilder:append	(Ljava/lang/String;)Ljava/lang/StringBuilder;
    //   569: getstatic 622	android/os/Build$VERSION:RELEASE	Ljava/lang/String;
    //   572: invokevirtual 606	java/lang/StringBuilder:append	(Ljava/lang/String;)Ljava/lang/StringBuilder;
    //   575: ldc_w 619
    //   578: invokevirtual 606	java/lang/StringBuilder:append	(Ljava/lang/String;)Ljava/lang/StringBuilder;
    //   581: aload 7
    //   583: invokevirtual 624	ct/bk:a	()Ljava/lang/String;
    //   586: invokevirtual 606	java/lang/StringBuilder:append	(Ljava/lang/String;)Ljava/lang/StringBuilder;
    //   589: ldc_w 626
    //   592: invokevirtual 606	java/lang/StringBuilder:append	(Ljava/lang/String;)Ljava/lang/StringBuilder;
    //   595: aload 7
    //   597: getfield 524	ct/bk:k	I
    //   600: invokevirtual 629	java/lang/StringBuilder:append	(I)Ljava/lang/StringBuilder;
    //   603: ldc_w 619
    //   606: invokevirtual 606	java/lang/StringBuilder:append	(Ljava/lang/String;)Ljava/lang/StringBuilder;
    //   609: aload 7
    //   611: getfield 526	ct/bk:l	I
    //   614: invokevirtual 629	java/lang/StringBuilder:append	(I)Ljava/lang/StringBuilder;
    //   617: ldc_w 631
    //   620: invokevirtual 606	java/lang/StringBuilder:append	(Ljava/lang/String;)Ljava/lang/StringBuilder;
    //   623: aload 6
    //   625: getfield 500	android/content/pm/PackageInfo:versionCode	I
    //   628: invokevirtual 629	java/lang/StringBuilder:append	(I)Ljava/lang/StringBuilder;
    //   631: ldc_w 619
    //   634: invokevirtual 606	java/lang/StringBuilder:append	(Ljava/lang/String;)Ljava/lang/StringBuilder;
    //   637: aload 6
    //   639: getfield 503	android/content/pm/PackageInfo:versionName	Ljava/lang/String;
    //   642: invokevirtual 606	java/lang/StringBuilder:append	(Ljava/lang/String;)Ljava/lang/StringBuilder;
    //   645: ldc_w 633
    //   648: invokevirtual 606	java/lang/StringBuilder:append	(Ljava/lang/String;)Ljava/lang/StringBuilder;
    //   651: aload 7
    //   653: invokevirtual 635	ct/bk:d	()Ljava/lang/String;
    //   656: invokevirtual 606	java/lang/StringBuilder:append	(Ljava/lang/String;)Ljava/lang/StringBuilder;
    //   659: ldc_w 619
    //   662: invokevirtual 606	java/lang/StringBuilder:append	(Ljava/lang/String;)Ljava/lang/StringBuilder;
    //   665: aload 7
    //   667: invokevirtual 637	ct/bk:e	()Ljava/lang/String;
    //   670: invokevirtual 606	java/lang/StringBuilder:append	(Ljava/lang/String;)Ljava/lang/StringBuilder;
    //   673: pop
    //   674: ldc_w 272
    //   677: aload 5
    //   679: invokevirtual 609	java/lang/StringBuilder:toString	()Ljava/lang/String;
    //   682: invokestatic 276	ct/b$a:a	(Ljava/lang/String;Ljava/lang/String;)V
    //   685: ldc_w 272
    //   688: ldc_w 639
    //   691: invokestatic 276	ct/b$a:a	(Ljava/lang/String;Ljava/lang/String;)V
    //   694: return
    //   695: astore 5
    //   697: ldc_w 272
    //   700: ldc -34
    //   702: aload 5
    //   704: invokestatic 368	ct/b$a:a	(Ljava/lang/String;Ljava/lang/String;Ljava/lang/Throwable;)V
    //   707: aconst_null
    //   708: astore 5
    //   710: goto -614 -> 96
    //   713: ldc_w 641
    //   716: astore 5
    //   718: goto -403 -> 315
    //   721: astore 5
    //   723: ldc_w 272
    //   726: ldc_w 643
    //   729: aload 5
    //   731: invokestatic 368	ct/b$a:a	(Ljava/lang/String;Ljava/lang/String;Ljava/lang/Throwable;)V
    //   734: return
    //   735: aconst_null
    //   736: astore 5
    //   738: goto -637 -> 101
    //   741: astore 5
    //   743: aconst_null
    //   744: astore 5
    //   746: goto -708 -> 38
    //   749: astore 6
    //   751: aload 5
    //   753: astore 6
    //   755: goto -697 -> 58
    // Local variable table:
    //   start	length	slot	name	signature
    //   0	758	0	this	bj
    //   276	1	1	n	int
    //   476	34	2	bool1	boolean
    //   485	35	3	bool2	boolean
    //   494	36	4	bool3	boolean
    //   36	642	5	localObject1	Object
    //   695	8	5	localException	Exception
    //   708	9	5	str1	String
    //   721	9	5	localThrowable	Throwable
    //   736	1	5	localObject2	Object
    //   741	1	5	localFileNotFoundException	java.io.FileNotFoundException
    //   744	8	5	localObject3	Object
    //   56	582	6	localObject4	Object
    //   749	1	6	localIOException	java.io.IOException
    //   753	1	6	localObject5	Object
    //   14	652	7	localbk	bk
    //   336	79	8	localObject6	Object
    //   397	25	9	str2	String
    // Exception table:
    //   from	to	target	type
    //   70	96	695	java/lang/Exception
    //   0	16	721	java/lang/Throwable
    //   16	38	721	java/lang/Throwable
    //   43	58	721	java/lang/Throwable
    //   63	70	721	java/lang/Throwable
    //   70	96	721	java/lang/Throwable
    //   96	101	721	java/lang/Throwable
    //   106	265	721	java/lang/Throwable
    //   265	303	721	java/lang/Throwable
    //   308	315	721	java/lang/Throwable
    //   315	328	721	java/lang/Throwable
    //   333	433	721	java/lang/Throwable
    //   433	694	721	java/lang/Throwable
    //   697	707	721	java/lang/Throwable
    //   16	38	741	java/io/FileNotFoundException
    //   43	58	749	java/io/IOException
  }
}

/* Location:
 * Qualified Name:     ct.bj
 * Java Class Version: 6 (50.0)
 * JD-Core Version:    0.7.1
 */