package ct;

final class s$a
  implements Runnable
{
  private final ao a;
  
  s$a(ao paramao)
  {
    a = paramao;
  }
  
  /* Error */
  public final void run()
  {
    // Byte code:
    //   0: ldc2_w 26
    //   3: invokestatic 33	java/lang/Thread:sleep	(J)V
    //   6: aload_0
    //   7: getfield 17	ct/s$a:a	Lct/ao;
    //   10: invokestatic 38	ct/j:a	(Lct/ao;)Ljava/util/HashMap;
    //   13: astore_1
    //   14: invokestatic 44	ct/ar:k	()Lct/ar;
    //   17: ifnonnull +9 -> 26
    //   20: invokestatic 49	ct/q:a	()Landroid/content/Context;
    //   23: invokestatic 52	ct/ar:a	(Landroid/content/Context;)V
    //   26: ldc 54
    //   28: aload_1
    //   29: invokestatic 59	ct/au:a	(Ljava/lang/String;Ljava/util/HashMap;)V
    //   32: return
    //   33: astore_1
    //   34: return
    //   35: astore_1
    //   36: return
    //   37: astore_1
    //   38: return
    // Local variable table:
    //   start	length	slot	name	signature
    //   0	39	0	this	a
    //   13	16	1	localHashMap	java.util.HashMap
    //   33	1	1	localInterruptedException	InterruptedException
    //   35	1	1	localOutOfMemoryError	OutOfMemoryError
    //   37	1	1	localException	Exception
    // Exception table:
    //   from	to	target	type
    //   0	14	33	java/lang/InterruptedException
    //   14	26	33	java/lang/InterruptedException
    //   26	32	33	java/lang/InterruptedException
    //   14	26	35	java/lang/OutOfMemoryError
    //   26	32	35	java/lang/OutOfMemoryError
    //   14	26	37	java/lang/Exception
    //   26	32	37	java/lang/Exception
  }
}

/* Location:
 * Qualified Name:     ct.s.a
 * Java Class Version: 6 (50.0)
 * JD-Core Version:    0.7.1
 */