package ct;

import android.text.TextUtils;
import java.net.MalformedURLException;
import java.net.URL;

public final class x
{
  public static aa a(z paramz)
  {
    try
    {
      z localz = (z)paramz;
      k = System.currentTimeMillis();
      new StringBuilder("doRequest... key:").append(p);
      az.b();
      aa localaa = b(localz);
      long l1 = System.currentTimeMillis();
      long l2 = k;
      new StringBuilder("endRequest... key:").append(p).append("costTime: ").append(l1 - l2);
      az.b();
      return localaa;
    }
    catch (Throwable paramz)
    {
      paramz = new aa();
      a = -19;
    }
    return paramz;
  }
  
  public static z a(String paramString, byte[] paramArrayOfByte)
  {
    try
    {
      URL localURL = new URL(ba.c(paramString));
      int i = localURL.getPort();
      z localz = new z(localURL.getHost(), new int[] { i });
      if ((!TextUtils.isEmpty(paramString)) && (paramString.toLowerCase().startsWith("https://"))) {
        a = true;
      }
      f = localURL.getFile();
      j = paramArrayOfByte;
      return localz;
    }
    catch (MalformedURLException paramArrayOfByte)
    {
      throw new ae("url format error:" + paramString);
    }
  }
  
  private static boolean a(long paramLong)
  {
    if (ay.f()) {
      if (System.currentTimeMillis() - paramLong <= 6000L) {}
    }
    do
    {
      do
      {
        return true;
        return false;
        if (!ay.h()) {
          break;
        }
      } while (System.currentTimeMillis() - paramLong > 10000L);
      return false;
    } while (System.currentTimeMillis() - paramLong > 10000L);
    return false;
  }
  
  /* Error */
  private static aa b(z paramz)
  {
    // Byte code:
    //   0: new 56	ct/aa
    //   3: dup
    //   4: invokespecial 57	ct/aa:<init>	()V
    //   7: astore 23
    //   9: new 140	ct/ab
    //   12: dup
    //   13: aload_0
    //   14: invokespecial 143	ct/ab:<init>	(Lct/z;)V
    //   17: astore 30
    //   19: aload 30
    //   21: getfield 146	ct/ab:c	Ljava/util/List;
    //   24: astore 31
    //   26: aload 30
    //   28: getfield 148	ct/ab:b	Ljava/lang/String;
    //   31: astore 32
    //   33: aload 31
    //   35: invokeinterface 153 1 0
    //   40: istore 7
    //   42: aload 31
    //   44: invokeinterface 153 1 0
    //   49: istore 8
    //   51: iconst_0
    //   52: istore_3
    //   53: ldc -101
    //   55: astore 22
    //   57: iconst_0
    //   58: istore 13
    //   60: invokestatic 21	java/lang/System:currentTimeMillis	()J
    //   63: aload_0
    //   64: getfield 25	ct/z:k	J
    //   67: lsub
    //   68: l2i
    //   69: istore 9
    //   71: ldc -101
    //   73: astore 20
    //   75: iconst_0
    //   76: istore 4
    //   78: iconst_0
    //   79: istore_1
    //   80: iload_3
    //   81: aload_0
    //   82: getfield 158	ct/z:n	I
    //   85: if_icmpgt +4999 -> 5084
    //   88: iload_1
    //   89: ifne +4995 -> 5084
    //   92: invokestatic 21	java/lang/System:currentTimeMillis	()J
    //   95: lstore 15
    //   97: new 56	ct/aa
    //   100: dup
    //   101: invokespecial 57	ct/aa:<init>	()V
    //   104: astore 23
    //   106: new 160	ct/ac
    //   109: dup
    //   110: invokespecial 161	ct/ac:<init>	()V
    //   113: astore 29
    //   115: aload 29
    //   117: aload 32
    //   119: putfield 164	ct/ac:y	Ljava/lang/String;
    //   122: aload 29
    //   124: iload 9
    //   126: putfield 167	ct/ac:i	I
    //   129: aload 29
    //   131: aload 30
    //   133: getfield 170	ct/ab:a	Lct/s;
    //   136: putfield 172	ct/ac:b	Lct/s;
    //   139: aconst_null
    //   140: astore 26
    //   142: aconst_null
    //   143: astore 25
    //   145: iconst_0
    //   146: istore 12
    //   148: iload_3
    //   149: aload_0
    //   150: getfield 158	ct/z:n	I
    //   153: if_icmpne +6 -> 159
    //   156: iconst_1
    //   157: istore 12
    //   159: iload_3
    //   160: iload 8
    //   162: irem
    //   163: istore_2
    //   164: iload_2
    //   165: iload 7
    //   167: iconst_1
    //   168: isub
    //   169: if_icmpge +29 -> 198
    //   172: aload 29
    //   174: iconst_1
    //   175: putfield 175	ct/ac:x	Z
    //   178: aload_0
    //   179: ldc -79
    //   181: aload_0
    //   182: getfield 180	ct/z:e	Ljava/lang/String;
    //   185: invokevirtual 183	ct/z:a	(Ljava/lang/String;Ljava/lang/String;)V
    //   188: aload_0
    //   189: ldc -71
    //   191: aload_0
    //   192: getfield 180	ct/z:e	Ljava/lang/String;
    //   195: invokevirtual 183	ct/z:a	(Ljava/lang/String;Ljava/lang/String;)V
    //   198: aload 31
    //   200: iload_2
    //   201: invokeinterface 189 2 0
    //   206: checkcast 191	ct/s
    //   209: astore 24
    //   211: aload 29
    //   213: aload 24
    //   215: putfield 192	ct/ac:a	Lct/s;
    //   218: aload 29
    //   220: aload_0
    //   221: getfield 194	ct/z:c	Ljava/lang/String;
    //   224: putfield 195	ct/ac:c	Ljava/lang/String;
    //   227: aload 29
    //   229: aload_0
    //   230: getfield 103	ct/z:a	Z
    //   233: putfield 198	ct/ac:D	Z
    //   236: aload 29
    //   238: aload_0
    //   239: getfield 158	ct/z:n	I
    //   242: putfield 201	ct/ac:u	I
    //   245: invokestatic 21	java/lang/System:currentTimeMillis	()J
    //   248: aload_0
    //   249: getfield 25	ct/z:k	J
    //   252: lsub
    //   253: aload_0
    //   254: getfield 204	ct/z:m	I
    //   257: i2l
    //   258: lcmp
    //   259: ifle +5270 -> 5529
    //   262: aload 31
    //   264: aload 31
    //   266: invokeinterface 153 1 0
    //   271: iconst_1
    //   272: isub
    //   273: invokeinterface 189 2 0
    //   278: checkcast 191	ct/s
    //   281: astore 24
    //   283: iconst_1
    //   284: istore_2
    //   285: iconst_1
    //   286: istore 5
    //   288: iconst_1
    //   289: istore_1
    //   290: aload 29
    //   292: iconst_1
    //   293: putfield 207	ct/ac:A	Z
    //   296: iload_1
    //   297: istore_2
    //   298: iload_1
    //   299: istore 5
    //   301: aload 22
    //   303: invokestatic 89	android/text/TextUtils:isEmpty	(Ljava/lang/CharSequence;)Z
    //   306: ifeq +858 -> 1164
    //   309: iload_1
    //   310: istore_2
    //   311: iload_1
    //   312: istore 5
    //   314: aload_0
    //   315: getfield 103	ct/z:a	Z
    //   318: ifne +724 -> 1042
    //   321: iload_1
    //   322: istore_2
    //   323: iload_1
    //   324: istore 5
    //   326: aload 24
    //   328: getfield 209	ct/s:b	I
    //   331: iconst_m1
    //   332: if_icmpeq +680 -> 1012
    //   335: iload_1
    //   336: istore_2
    //   337: iload_1
    //   338: istore 5
    //   340: new 27	java/lang/StringBuilder
    //   343: dup
    //   344: ldc -45
    //   346: invokespecial 32	java/lang/StringBuilder:<init>	(Ljava/lang/String;)V
    //   349: aload 24
    //   351: getfield 213	ct/s:a	Ljava/lang/String;
    //   354: invokevirtual 40	java/lang/StringBuilder:append	(Ljava/lang/String;)Ljava/lang/StringBuilder;
    //   357: ldc -41
    //   359: invokevirtual 40	java/lang/StringBuilder:append	(Ljava/lang/String;)Ljava/lang/StringBuilder;
    //   362: aload 24
    //   364: getfield 209	ct/s:b	I
    //   367: invokevirtual 218	java/lang/StringBuilder:append	(I)Ljava/lang/StringBuilder;
    //   370: invokevirtual 120	java/lang/StringBuilder:toString	()Ljava/lang/String;
    //   373: astore 19
    //   375: iload_1
    //   376: istore_2
    //   377: iload_1
    //   378: istore 5
    //   380: aload_0
    //   381: getfield 109	ct/z:f	Ljava/lang/String;
    //   384: astore 27
    //   386: aload 19
    //   388: astore 21
    //   390: iload_1
    //   391: istore_2
    //   392: iload_1
    //   393: istore 5
    //   395: aload 27
    //   397: invokestatic 89	android/text/TextUtils:isEmpty	(Ljava/lang/CharSequence;)Z
    //   400: ifne +45 -> 445
    //   403: iload_1
    //   404: istore_2
    //   405: iload_1
    //   406: istore 5
    //   408: aload 27
    //   410: ldc -36
    //   412: invokevirtual 100	java/lang/String:startsWith	(Ljava/lang/String;)Z
    //   415: ifeq +714 -> 1129
    //   418: iload_1
    //   419: istore_2
    //   420: iload_1
    //   421: istore 5
    //   423: new 27	java/lang/StringBuilder
    //   426: dup
    //   427: invokespecial 221	java/lang/StringBuilder:<init>	()V
    //   430: aload 19
    //   432: invokevirtual 40	java/lang/StringBuilder:append	(Ljava/lang/String;)Ljava/lang/StringBuilder;
    //   435: aload 27
    //   437: invokevirtual 40	java/lang/StringBuilder:append	(Ljava/lang/String;)Ljava/lang/StringBuilder;
    //   440: invokevirtual 120	java/lang/StringBuilder:toString	()Ljava/lang/String;
    //   443: astore 21
    //   445: iload_1
    //   446: istore_2
    //   447: iload_1
    //   448: istore 5
    //   450: aload 29
    //   452: aload 21
    //   454: putfield 224	ct/ac:d	Ljava/lang/String;
    //   457: aload 22
    //   459: astore 19
    //   461: new 27	java/lang/StringBuilder
    //   464: dup
    //   465: ldc -30
    //   467: invokespecial 32	java/lang/StringBuilder:<init>	(Ljava/lang/String;)V
    //   470: iload_3
    //   471: invokevirtual 218	java/lang/StringBuilder:append	(I)Ljava/lang/StringBuilder;
    //   474: ldc -28
    //   476: invokevirtual 40	java/lang/StringBuilder:append	(Ljava/lang/String;)Ljava/lang/StringBuilder;
    //   479: aload 21
    //   481: invokevirtual 40	java/lang/StringBuilder:append	(Ljava/lang/String;)Ljava/lang/StringBuilder;
    //   484: ldc -26
    //   486: invokevirtual 40	java/lang/StringBuilder:append	(Ljava/lang/String;)Ljava/lang/StringBuilder;
    //   489: iload 13
    //   491: invokevirtual 233	java/lang/StringBuilder:append	(Z)Ljava/lang/StringBuilder;
    //   494: ldc -21
    //   496: invokevirtual 40	java/lang/StringBuilder:append	(Ljava/lang/String;)Ljava/lang/StringBuilder;
    //   499: aload 24
    //   501: invokevirtual 238	java/lang/StringBuilder:append	(Ljava/lang/Object;)Ljava/lang/StringBuilder;
    //   504: pop
    //   505: invokestatic 240	ct/az:a	()V
    //   508: new 242	org/apache/http/client/methods/HttpPost
    //   511: dup
    //   512: aload 21
    //   514: invokespecial 243	org/apache/http/client/methods/HttpPost:<init>	(Ljava/lang/String;)V
    //   517: astore 33
    //   519: new 245	java/util/HashMap
    //   522: dup
    //   523: invokespecial 246	java/util/HashMap:<init>	()V
    //   526: astore 22
    //   528: aload 22
    //   530: aload_0
    //   531: getfield 249	ct/z:i	Ljava/util/Map;
    //   534: invokeinterface 255 2 0
    //   539: aload 22
    //   541: invokeinterface 256 1 0
    //   546: ifle +660 -> 1206
    //   549: iload 13
    //   551: ifne +655 -> 1206
    //   554: aload 22
    //   556: invokeinterface 260 1 0
    //   561: invokeinterface 266 1 0
    //   566: astore 24
    //   568: aload 24
    //   570: invokeinterface 271 1 0
    //   575: ifeq +611 -> 1186
    //   578: aload 24
    //   580: invokeinterface 275 1 0
    //   585: checkcast 91	java/lang/String
    //   588: astore 27
    //   590: aload 33
    //   592: aload 27
    //   594: aload 22
    //   596: aload 27
    //   598: invokeinterface 278 2 0
    //   603: checkcast 91	java/lang/String
    //   606: invokeinterface 283 3 0
    //   611: goto -43 -> 568
    //   614: astore 22
    //   616: aload 20
    //   618: astore 24
    //   620: iconst_3
    //   621: istore_2
    //   622: aconst_null
    //   623: astore 20
    //   625: aload 19
    //   627: astore 21
    //   629: aload 24
    //   631: astore 19
    //   633: invokestatic 285	ct/az:d	()V
    //   636: aload 29
    //   638: aload 22
    //   640: invokevirtual 289	java/lang/Object:getClass	()Ljava/lang/Class;
    //   643: invokevirtual 294	java/lang/Class:getSimpleName	()Ljava/lang/String;
    //   646: putfield 297	ct/ac:q	Ljava/lang/String;
    //   649: aload 29
    //   651: new 27	java/lang/StringBuilder
    //   654: dup
    //   655: invokespecial 221	java/lang/StringBuilder:<init>	()V
    //   658: iload_2
    //   659: invokevirtual 218	java/lang/StringBuilder:append	(I)Ljava/lang/StringBuilder;
    //   662: ldc_w 299
    //   665: invokevirtual 40	java/lang/StringBuilder:append	(Ljava/lang/String;)Ljava/lang/StringBuilder;
    //   668: aload 22
    //   670: invokestatic 302	ct/ba:a	(Ljava/lang/Exception;)Ljava/lang/String;
    //   673: invokevirtual 40	java/lang/StringBuilder:append	(Ljava/lang/String;)Ljava/lang/StringBuilder;
    //   676: invokevirtual 120	java/lang/StringBuilder:toString	()Ljava/lang/String;
    //   679: putfield 305	ct/ac:r	Ljava/lang/String;
    //   682: invokestatic 307	ct/ay:e	()Z
    //   685: ifeq +3964 -> 4649
    //   688: aload 22
    //   690: instanceof 309
    //   693: ifeq +3848 -> 4541
    //   696: bipush -10
    //   698: istore_2
    //   699: aload 23
    //   701: iload_2
    //   702: putfield 60	ct/aa:a	I
    //   705: aload 29
    //   707: getfield 305	ct/ac:r	Ljava/lang/String;
    //   710: ldc_w 311
    //   713: invokevirtual 314	java/lang/String:contains	(Ljava/lang/CharSequence;)Z
    //   716: ifeq +10 -> 726
    //   719: aload 23
    //   721: bipush -18
    //   723: putfield 60	ct/aa:a	I
    //   726: aload 29
    //   728: new 27	java/lang/StringBuilder
    //   731: dup
    //   732: invokespecial 221	java/lang/StringBuilder:<init>	()V
    //   735: aload_0
    //   736: getfield 36	ct/z:p	Ljava/lang/String;
    //   739: invokevirtual 40	java/lang/StringBuilder:append	(Ljava/lang/String;)Ljava/lang/StringBuilder;
    //   742: ldc_w 316
    //   745: invokevirtual 40	java/lang/StringBuilder:append	(Ljava/lang/String;)Ljava/lang/StringBuilder;
    //   748: iload_3
    //   749: invokevirtual 218	java/lang/StringBuilder:append	(I)Ljava/lang/StringBuilder;
    //   752: invokevirtual 120	java/lang/StringBuilder:toString	()Ljava/lang/String;
    //   755: putfield 317	ct/ac:p	Ljava/lang/String;
    //   758: aload 29
    //   760: iload_3
    //   761: putfield 320	ct/ac:s	I
    //   764: aload 21
    //   766: invokestatic 89	android/text/TextUtils:isEmpty	(Ljava/lang/CharSequence;)Z
    //   769: ifeq +3886 -> 4655
    //   772: iload_3
    //   773: iconst_1
    //   774: iadd
    //   775: istore 4
    //   777: iconst_0
    //   778: istore_2
    //   779: invokestatic 324	ct/p:b	()Ljava/lang/String;
    //   782: invokestatic 89	android/text/TextUtils:isEmpty	(Ljava/lang/CharSequence;)Z
    //   785: ifne +162 -> 947
    //   788: aload 23
    //   790: getfield 60	ct/aa:a	I
    //   793: bipush -21
    //   795: if_icmpeq +152 -> 947
    //   798: aload 23
    //   800: invokestatic 21	java/lang/System:currentTimeMillis	()J
    //   803: aload_0
    //   804: getfield 25	ct/z:k	J
    //   807: lsub
    //   808: l2i
    //   809: putfield 326	ct/aa:f	I
    //   812: aload 29
    //   814: aload 23
    //   816: getfield 60	ct/aa:a	I
    //   819: putfield 328	ct/ac:k	I
    //   822: aload 29
    //   824: aload 19
    //   826: putfield 331	ct/ac:C	Ljava/lang/String;
    //   829: aload 29
    //   831: aload 23
    //   833: getfield 326	ct/aa:f	I
    //   836: putfield 334	ct/ac:l	I
    //   839: aload 29
    //   841: invokestatic 21	java/lang/System:currentTimeMillis	()J
    //   844: lload 15
    //   846: lsub
    //   847: l2i
    //   848: putfield 335	ct/ac:m	I
    //   851: aload 29
    //   853: aload 21
    //   855: putfield 336	ct/ac:f	Ljava/lang/String;
    //   858: aload_0
    //   859: getfield 113	ct/z:j	[B
    //   862: ifnull +3829 -> 4691
    //   865: aload 29
    //   867: aload_0
    //   868: getfield 113	ct/z:j	[B
    //   871: arraylength
    //   872: i2l
    //   873: putfield 338	ct/ac:n	J
    //   876: aload 29
    //   878: iload 12
    //   880: putfield 341	ct/ac:z	Z
    //   883: iload 12
    //   885: ifeq +17 -> 902
    //   888: aload 29
    //   890: getfield 328	ct/ac:k	I
    //   893: ifeq +9 -> 902
    //   896: aload 29
    //   898: iconst_1
    //   899: putfield 344	ct/ac:w	I
    //   902: aload 29
    //   904: aload_0
    //   905: getfield 346	ct/z:h	Z
    //   908: putfield 349	ct/ac:B	Z
    //   911: invokestatic 354	ct/o:a	()Lct/o;
    //   914: new 356	ct/ad
    //   917: dup
    //   918: aload 29
    //   920: invokespecial 359	ct/ad:<init>	(Lct/ac;)V
    //   923: invokevirtual 362	ct/o:a	(Ljava/lang/Runnable;)V
    //   926: aload_0
    //   927: aload 29
    //   929: invokevirtual 364	ct/z:a	(Lct/ac;)V
    //   932: aload 29
    //   934: invokevirtual 365	ct/ac:toString	()Ljava/lang/String;
    //   937: pop
    //   938: aload 29
    //   940: invokevirtual 365	ct/ac:toString	()Ljava/lang/String;
    //   943: pop
    //   944: invokestatic 45	ct/az:b	()V
    //   947: aload 20
    //   949: ifnull +28 -> 977
    //   952: aload_0
    //   953: getfield 368	ct/z:g	Z
    //   956: ifne +11 -> 967
    //   959: aload 23
    //   961: getfield 60	ct/aa:a	I
    //   964: ifeq +13 -> 977
    //   967: aload 20
    //   969: invokevirtual 374	org/apache/http/impl/client/DefaultHttpClient:getConnectionManager	()Lorg/apache/http/conn/ClientConnectionManager;
    //   972: invokeinterface 379 1 0
    //   977: lload 15
    //   979: invokestatic 381	ct/x:a	(J)Z
    //   982: istore 12
    //   984: aload 23
    //   986: getfield 60	ct/aa:a	I
    //   989: bipush -4
    //   991: if_icmpeq +18 -> 1009
    //   994: aload 23
    //   996: getfield 60	ct/aa:a	I
    //   999: bipush -17
    //   1001: if_icmpeq +8 -> 1009
    //   1004: iload 12
    //   1006: ifeq +3694 -> 4700
    //   1009: aload 23
    //   1011: areturn
    //   1012: iload_1
    //   1013: istore_2
    //   1014: iload_1
    //   1015: istore 5
    //   1017: new 27	java/lang/StringBuilder
    //   1020: dup
    //   1021: ldc -45
    //   1023: invokespecial 32	java/lang/StringBuilder:<init>	(Ljava/lang/String;)V
    //   1026: aload 24
    //   1028: getfield 213	ct/s:a	Ljava/lang/String;
    //   1031: invokevirtual 40	java/lang/StringBuilder:append	(Ljava/lang/String;)Ljava/lang/StringBuilder;
    //   1034: invokevirtual 120	java/lang/StringBuilder:toString	()Ljava/lang/String;
    //   1037: astore 19
    //   1039: goto -664 -> 375
    //   1042: iload_1
    //   1043: istore_2
    //   1044: iload_1
    //   1045: istore 5
    //   1047: aload 24
    //   1049: getfield 209	ct/s:b	I
    //   1052: iconst_m1
    //   1053: if_icmpeq +46 -> 1099
    //   1056: iload_1
    //   1057: istore_2
    //   1058: iload_1
    //   1059: istore 5
    //   1061: new 27	java/lang/StringBuilder
    //   1064: dup
    //   1065: ldc 96
    //   1067: invokespecial 32	java/lang/StringBuilder:<init>	(Ljava/lang/String;)V
    //   1070: aload 24
    //   1072: getfield 213	ct/s:a	Ljava/lang/String;
    //   1075: invokevirtual 40	java/lang/StringBuilder:append	(Ljava/lang/String;)Ljava/lang/StringBuilder;
    //   1078: ldc -41
    //   1080: invokevirtual 40	java/lang/StringBuilder:append	(Ljava/lang/String;)Ljava/lang/StringBuilder;
    //   1083: aload 24
    //   1085: getfield 209	ct/s:b	I
    //   1088: invokevirtual 218	java/lang/StringBuilder:append	(I)Ljava/lang/StringBuilder;
    //   1091: invokevirtual 120	java/lang/StringBuilder:toString	()Ljava/lang/String;
    //   1094: astore 19
    //   1096: goto -721 -> 375
    //   1099: iload_1
    //   1100: istore_2
    //   1101: iload_1
    //   1102: istore 5
    //   1104: new 27	java/lang/StringBuilder
    //   1107: dup
    //   1108: ldc 96
    //   1110: invokespecial 32	java/lang/StringBuilder:<init>	(Ljava/lang/String;)V
    //   1113: aload 24
    //   1115: getfield 213	ct/s:a	Ljava/lang/String;
    //   1118: invokevirtual 40	java/lang/StringBuilder:append	(Ljava/lang/String;)Ljava/lang/StringBuilder;
    //   1121: invokevirtual 120	java/lang/StringBuilder:toString	()Ljava/lang/String;
    //   1124: astore 19
    //   1126: goto -751 -> 375
    //   1129: iload_1
    //   1130: istore_2
    //   1131: iload_1
    //   1132: istore 5
    //   1134: new 27	java/lang/StringBuilder
    //   1137: dup
    //   1138: invokespecial 221	java/lang/StringBuilder:<init>	()V
    //   1141: aload 19
    //   1143: invokevirtual 40	java/lang/StringBuilder:append	(Ljava/lang/String;)Ljava/lang/StringBuilder;
    //   1146: ldc -36
    //   1148: invokevirtual 40	java/lang/StringBuilder:append	(Ljava/lang/String;)Ljava/lang/StringBuilder;
    //   1151: aload 27
    //   1153: invokevirtual 40	java/lang/StringBuilder:append	(Ljava/lang/String;)Ljava/lang/StringBuilder;
    //   1156: invokevirtual 120	java/lang/StringBuilder:toString	()Ljava/lang/String;
    //   1159: astore 21
    //   1161: goto -716 -> 445
    //   1164: iload_1
    //   1165: istore_2
    //   1166: iload_1
    //   1167: istore 5
    //   1169: aload 29
    //   1171: aload 22
    //   1173: putfield 336	ct/ac:f	Ljava/lang/String;
    //   1176: aconst_null
    //   1177: astore 19
    //   1179: aload 22
    //   1181: astore 21
    //   1183: goto -722 -> 461
    //   1186: getstatic 383	ct/ay:d	Z
    //   1189: ifeq +17 -> 1206
    //   1192: aload 33
    //   1194: ldc_w 385
    //   1197: aload_0
    //   1198: getfield 180	ct/z:e	Ljava/lang/String;
    //   1201: invokeinterface 283 3 0
    //   1206: aload 33
    //   1208: ldc_w 387
    //   1211: new 27	java/lang/StringBuilder
    //   1214: dup
    //   1215: ldc_w 389
    //   1218: invokespecial 32	java/lang/StringBuilder:<init>	(Ljava/lang/String;)V
    //   1221: invokestatic 391	ct/p:f	()Ljava/lang/String;
    //   1224: invokevirtual 40	java/lang/StringBuilder:append	(Ljava/lang/String;)Ljava/lang/StringBuilder;
    //   1227: ldc_w 393
    //   1230: invokevirtual 40	java/lang/StringBuilder:append	(Ljava/lang/String;)Ljava/lang/StringBuilder;
    //   1233: aload_0
    //   1234: getfield 36	ct/z:p	Ljava/lang/String;
    //   1237: invokevirtual 40	java/lang/StringBuilder:append	(Ljava/lang/String;)Ljava/lang/StringBuilder;
    //   1240: ldc_w 316
    //   1243: invokevirtual 40	java/lang/StringBuilder:append	(Ljava/lang/String;)Ljava/lang/StringBuilder;
    //   1246: iload_3
    //   1247: invokevirtual 218	java/lang/StringBuilder:append	(I)Ljava/lang/StringBuilder;
    //   1250: invokevirtual 120	java/lang/StringBuilder:toString	()Ljava/lang/String;
    //   1253: invokeinterface 283 3 0
    //   1258: iload 13
    //   1260: ifeq +398 -> 1658
    //   1263: aload 22
    //   1265: invokeinterface 260 1 0
    //   1270: invokeinterface 266 1 0
    //   1275: astore 24
    //   1277: aload 24
    //   1279: invokeinterface 271 1 0
    //   1284: ifeq +353 -> 1637
    //   1287: aload 24
    //   1289: invokeinterface 275 1 0
    //   1294: checkcast 91	java/lang/String
    //   1297: astore 27
    //   1299: aload 33
    //   1301: aload 27
    //   1303: aload 22
    //   1305: aload 27
    //   1307: invokeinterface 278 2 0
    //   1312: checkcast 91	java/lang/String
    //   1315: invokeinterface 283 3 0
    //   1320: goto -43 -> 1277
    //   1323: astore 21
    //   1325: aload 20
    //   1327: astore 21
    //   1329: aload 25
    //   1331: astore 20
    //   1333: aload 19
    //   1335: astore 22
    //   1337: aload 21
    //   1339: astore 19
    //   1341: aload 29
    //   1343: new 27	java/lang/StringBuilder
    //   1346: dup
    //   1347: invokespecial 221	java/lang/StringBuilder:<init>	()V
    //   1350: aload_0
    //   1351: getfield 36	ct/z:p	Ljava/lang/String;
    //   1354: invokevirtual 40	java/lang/StringBuilder:append	(Ljava/lang/String;)Ljava/lang/StringBuilder;
    //   1357: ldc_w 316
    //   1360: invokevirtual 40	java/lang/StringBuilder:append	(Ljava/lang/String;)Ljava/lang/StringBuilder;
    //   1363: iload_3
    //   1364: invokevirtual 218	java/lang/StringBuilder:append	(I)Ljava/lang/StringBuilder;
    //   1367: invokevirtual 120	java/lang/StringBuilder:toString	()Ljava/lang/String;
    //   1370: putfield 317	ct/ac:p	Ljava/lang/String;
    //   1373: aload 29
    //   1375: iload_3
    //   1376: putfield 320	ct/ac:s	I
    //   1379: aload 22
    //   1381: invokestatic 89	android/text/TextUtils:isEmpty	(Ljava/lang/CharSequence;)Z
    //   1384: ifeq +3333 -> 4717
    //   1387: iload_3
    //   1388: iconst_1
    //   1389: iadd
    //   1390: istore 4
    //   1392: iconst_0
    //   1393: istore_2
    //   1394: invokestatic 324	ct/p:b	()Ljava/lang/String;
    //   1397: invokestatic 89	android/text/TextUtils:isEmpty	(Ljava/lang/CharSequence;)Z
    //   1400: ifne +162 -> 1562
    //   1403: aload 23
    //   1405: getfield 60	ct/aa:a	I
    //   1408: bipush -21
    //   1410: if_icmpeq +152 -> 1562
    //   1413: aload 23
    //   1415: invokestatic 21	java/lang/System:currentTimeMillis	()J
    //   1418: aload_0
    //   1419: getfield 25	ct/z:k	J
    //   1422: lsub
    //   1423: l2i
    //   1424: putfield 326	ct/aa:f	I
    //   1427: aload 29
    //   1429: aload 23
    //   1431: getfield 60	ct/aa:a	I
    //   1434: putfield 328	ct/ac:k	I
    //   1437: aload 29
    //   1439: aload 19
    //   1441: putfield 331	ct/ac:C	Ljava/lang/String;
    //   1444: aload 29
    //   1446: aload 23
    //   1448: getfield 326	ct/aa:f	I
    //   1451: putfield 334	ct/ac:l	I
    //   1454: aload 29
    //   1456: invokestatic 21	java/lang/System:currentTimeMillis	()J
    //   1459: lload 15
    //   1461: lsub
    //   1462: l2i
    //   1463: putfield 335	ct/ac:m	I
    //   1466: aload 29
    //   1468: aload 22
    //   1470: putfield 336	ct/ac:f	Ljava/lang/String;
    //   1473: aload_0
    //   1474: getfield 113	ct/z:j	[B
    //   1477: ifnull +3276 -> 4753
    //   1480: aload 29
    //   1482: aload_0
    //   1483: getfield 113	ct/z:j	[B
    //   1486: arraylength
    //   1487: i2l
    //   1488: putfield 338	ct/ac:n	J
    //   1491: aload 29
    //   1493: iload 12
    //   1495: putfield 341	ct/ac:z	Z
    //   1498: iload 12
    //   1500: ifeq +17 -> 1517
    //   1503: aload 29
    //   1505: getfield 328	ct/ac:k	I
    //   1508: ifeq +9 -> 1517
    //   1511: aload 29
    //   1513: iconst_1
    //   1514: putfield 344	ct/ac:w	I
    //   1517: aload 29
    //   1519: aload_0
    //   1520: getfield 346	ct/z:h	Z
    //   1523: putfield 349	ct/ac:B	Z
    //   1526: invokestatic 354	ct/o:a	()Lct/o;
    //   1529: new 356	ct/ad
    //   1532: dup
    //   1533: aload 29
    //   1535: invokespecial 359	ct/ad:<init>	(Lct/ac;)V
    //   1538: invokevirtual 362	ct/o:a	(Ljava/lang/Runnable;)V
    //   1541: aload_0
    //   1542: aload 29
    //   1544: invokevirtual 364	ct/z:a	(Lct/ac;)V
    //   1547: aload 29
    //   1549: invokevirtual 365	ct/ac:toString	()Ljava/lang/String;
    //   1552: pop
    //   1553: aload 29
    //   1555: invokevirtual 365	ct/ac:toString	()Ljava/lang/String;
    //   1558: pop
    //   1559: invokestatic 45	ct/az:b	()V
    //   1562: aload 20
    //   1564: ifnull +28 -> 1592
    //   1567: aload_0
    //   1568: getfield 368	ct/z:g	Z
    //   1571: ifne +11 -> 1582
    //   1574: aload 23
    //   1576: getfield 60	ct/aa:a	I
    //   1579: ifeq +13 -> 1592
    //   1582: aload 20
    //   1584: invokevirtual 374	org/apache/http/impl/client/DefaultHttpClient:getConnectionManager	()Lorg/apache/http/conn/ClientConnectionManager;
    //   1587: invokeinterface 379 1 0
    //   1592: lload 15
    //   1594: invokestatic 381	ct/x:a	(J)Z
    //   1597: istore 12
    //   1599: aload 23
    //   1601: getfield 60	ct/aa:a	I
    //   1604: bipush -4
    //   1606: if_icmpeq -597 -> 1009
    //   1609: aload 23
    //   1611: getfield 60	ct/aa:a	I
    //   1614: bipush -17
    //   1616: if_icmpeq -607 -> 1009
    //   1619: iload 12
    //   1621: ifne -612 -> 1009
    //   1624: iload 4
    //   1626: istore_3
    //   1627: aload 19
    //   1629: astore 20
    //   1631: iload_2
    //   1632: istore 4
    //   1634: goto -1554 -> 80
    //   1637: getstatic 383	ct/ay:d	Z
    //   1640: ifeq +18 -> 1658
    //   1643: aload 33
    //   1645: ldc_w 385
    //   1648: aload 21
    //   1650: invokestatic 395	ct/ba:d	(Ljava/lang/String;)Ljava/lang/String;
    //   1653: invokeinterface 283 3 0
    //   1658: aload_0
    //   1659: getfield 113	ct/z:j	[B
    //   1662: astore 21
    //   1664: aload 21
    //   1666: ifnull +26 -> 1692
    //   1669: aload 21
    //   1671: arraylength
    //   1672: ifle +20 -> 1692
    //   1675: aload 33
    //   1677: checkcast 242	org/apache/http/client/methods/HttpPost
    //   1680: new 397	org/apache/http/entity/ByteArrayEntity
    //   1683: dup
    //   1684: aload 21
    //   1686: invokespecial 400	org/apache/http/entity/ByteArrayEntity:<init>	([B)V
    //   1689: invokevirtual 404	org/apache/http/client/methods/HttpPost:setEntity	(Lorg/apache/http/HttpEntity;)V
    //   1692: new 406	org/apache/http/params/BasicHttpParams
    //   1695: dup
    //   1696: invokespecial 407	org/apache/http/params/BasicHttpParams:<init>	()V
    //   1699: astore 21
    //   1701: aload 21
    //   1703: iconst_0
    //   1704: invokestatic 413	org/apache/http/client/params/HttpClientParams:setRedirecting	(Lorg/apache/http/params/HttpParams;Z)V
    //   1707: new 370	org/apache/http/impl/client/DefaultHttpClient
    //   1710: dup
    //   1711: aload 21
    //   1713: invokespecial 416	org/apache/http/impl/client/DefaultHttpClient:<init>	(Lorg/apache/http/params/HttpParams;)V
    //   1716: astore 22
    //   1718: aload 22
    //   1720: invokestatic 419	ct/ay:a	(Lorg/apache/http/client/HttpClient;)V
    //   1723: bipush 10
    //   1725: istore 5
    //   1727: bipush 20
    //   1729: istore_2
    //   1730: invokestatic 127	ct/ay:f	()Z
    //   1733: ifeq +893 -> 2626
    //   1736: iconst_5
    //   1737: istore 5
    //   1739: iconst_5
    //   1740: istore_2
    //   1741: aload 22
    //   1743: invokeinterface 425 1 0
    //   1748: ldc_w 427
    //   1751: iload 5
    //   1753: sipush 1000
    //   1756: imul
    //   1757: invokestatic 433	java/lang/Integer:valueOf	(I)Ljava/lang/Integer;
    //   1760: invokeinterface 439 3 0
    //   1765: pop
    //   1766: aload 22
    //   1768: invokeinterface 425 1 0
    //   1773: ldc_w 441
    //   1776: iload_2
    //   1777: sipush 1000
    //   1780: imul
    //   1781: invokestatic 433	java/lang/Integer:valueOf	(I)Ljava/lang/Integer;
    //   1784: invokeinterface 439 3 0
    //   1789: pop
    //   1790: aload 22
    //   1792: new 443	org/apache/http/impl/client/DefaultHttpRequestRetryHandler
    //   1795: dup
    //   1796: iconst_0
    //   1797: iconst_0
    //   1798: invokespecial 446	org/apache/http/impl/client/DefaultHttpRequestRetryHandler:<init>	(IZ)V
    //   1801: invokevirtual 450	org/apache/http/impl/client/DefaultHttpClient:setHttpRequestRetryHandler	(Lorg/apache/http/client/HttpRequestRetryHandler;)V
    //   1804: iconst_5
    //   1805: istore 5
    //   1807: aload 19
    //   1809: astore 24
    //   1811: aload 20
    //   1813: astore 25
    //   1815: aload 19
    //   1817: astore 26
    //   1819: aload 20
    //   1821: astore 27
    //   1823: iload 5
    //   1825: istore_2
    //   1826: aload 20
    //   1828: astore 28
    //   1830: aload 29
    //   1832: invokestatic 21	java/lang/System:currentTimeMillis	()J
    //   1835: lload 15
    //   1837: lsub
    //   1838: l2i
    //   1839: putfield 452	ct/ac:g	I
    //   1842: aload 19
    //   1844: astore 24
    //   1846: aload 20
    //   1848: astore 25
    //   1850: aload 19
    //   1852: astore 26
    //   1854: aload 20
    //   1856: astore 27
    //   1858: iload 5
    //   1860: istore_2
    //   1861: aload 20
    //   1863: astore 28
    //   1865: invokestatic 21	java/lang/System:currentTimeMillis	()J
    //   1868: lstore 17
    //   1870: aload 19
    //   1872: astore 24
    //   1874: aload 20
    //   1876: astore 25
    //   1878: aload 19
    //   1880: astore 26
    //   1882: aload 20
    //   1884: astore 27
    //   1886: iload 5
    //   1888: istore_2
    //   1889: aload 20
    //   1891: astore 28
    //   1893: aload 22
    //   1895: aload 33
    //   1897: invokevirtual 456	org/apache/http/impl/client/DefaultHttpClient:execute	(Lorg/apache/http/client/methods/HttpUriRequest;)Lorg/apache/http/HttpResponse;
    //   1900: astore 33
    //   1902: aload 19
    //   1904: astore 24
    //   1906: aload 20
    //   1908: astore 25
    //   1910: aload 19
    //   1912: astore 26
    //   1914: aload 20
    //   1916: astore 27
    //   1918: iload 5
    //   1920: istore_2
    //   1921: aload 20
    //   1923: astore 28
    //   1925: aload 23
    //   1927: invokestatic 21	java/lang/System:currentTimeMillis	()J
    //   1930: lload 17
    //   1932: lsub
    //   1933: l2i
    //   1934: putfield 458	ct/aa:c	I
    //   1937: bipush 6
    //   1939: istore 5
    //   1941: aload 19
    //   1943: astore 24
    //   1945: aload 20
    //   1947: astore 25
    //   1949: aload 19
    //   1951: astore 26
    //   1953: aload 20
    //   1955: astore 27
    //   1957: iload 5
    //   1959: istore_2
    //   1960: aload 20
    //   1962: astore 28
    //   1964: new 27	java/lang/StringBuilder
    //   1967: dup
    //   1968: ldc_w 460
    //   1971: invokespecial 32	java/lang/StringBuilder:<init>	(Ljava/lang/String;)V
    //   1974: aload 23
    //   1976: getfield 458	ct/aa:c	I
    //   1979: invokevirtual 218	java/lang/StringBuilder:append	(I)Ljava/lang/StringBuilder;
    //   1982: pop
    //   1983: aload 19
    //   1985: astore 24
    //   1987: aload 20
    //   1989: astore 25
    //   1991: aload 19
    //   1993: astore 26
    //   1995: aload 20
    //   1997: astore 27
    //   1999: iload 5
    //   2001: istore_2
    //   2002: aload 20
    //   2004: astore 28
    //   2006: invokestatic 240	ct/az:a	()V
    //   2009: aload 19
    //   2011: astore 24
    //   2013: aload 20
    //   2015: astore 25
    //   2017: aload 19
    //   2019: astore 26
    //   2021: aload 20
    //   2023: astore 27
    //   2025: iload 5
    //   2027: istore_2
    //   2028: aload 20
    //   2030: astore 28
    //   2032: aload 33
    //   2034: invokeinterface 466 1 0
    //   2039: invokeinterface 471 1 0
    //   2044: istore 6
    //   2046: aload 19
    //   2048: astore 24
    //   2050: aload 20
    //   2052: astore 25
    //   2054: aload 19
    //   2056: astore 26
    //   2058: aload 20
    //   2060: astore 27
    //   2062: iload 5
    //   2064: istore_2
    //   2065: aload 20
    //   2067: astore 28
    //   2069: aload 23
    //   2071: aload 33
    //   2073: putfield 474	ct/aa:e	Lorg/apache/http/HttpResponse;
    //   2076: aload 20
    //   2078: astore 21
    //   2080: aload 33
    //   2082: ifnull +83 -> 2165
    //   2085: aload 20
    //   2087: astore 21
    //   2089: aload 19
    //   2091: astore 24
    //   2093: aload 20
    //   2095: astore 25
    //   2097: aload 19
    //   2099: astore 26
    //   2101: aload 20
    //   2103: astore 27
    //   2105: iload 5
    //   2107: istore_2
    //   2108: aload 20
    //   2110: astore 28
    //   2112: aload 33
    //   2114: ldc_w 476
    //   2117: invokeinterface 480 2 0
    //   2122: ifnull +43 -> 2165
    //   2125: aload 19
    //   2127: astore 24
    //   2129: aload 20
    //   2131: astore 25
    //   2133: aload 19
    //   2135: astore 26
    //   2137: aload 20
    //   2139: astore 27
    //   2141: iload 5
    //   2143: istore_2
    //   2144: aload 20
    //   2146: astore 28
    //   2148: aload 33
    //   2150: ldc_w 476
    //   2153: invokeinterface 480 2 0
    //   2158: invokeinterface 485 1 0
    //   2163: astore 21
    //   2165: aload 19
    //   2167: astore 24
    //   2169: aload 21
    //   2171: astore 25
    //   2173: aload 19
    //   2175: astore 26
    //   2177: aload 21
    //   2179: astore 27
    //   2181: iload 5
    //   2183: istore_2
    //   2184: aload 21
    //   2186: astore 28
    //   2188: aload 29
    //   2190: aload 23
    //   2192: getfield 458	ct/aa:c	I
    //   2195: putfield 487	ct/ac:h	I
    //   2198: bipush 7
    //   2200: istore_2
    //   2201: iload 6
    //   2203: lookupswitch	default:+3360->5563, 200:+459->2662, 204:+2260->4463, 301:+1778->3981, 302:+1778->3981, 303:+1778->3981, 307:+1778->3981, 408:+2260->4463, 502:+2260->4463, 503:+2260->4463, 504:+2260->4463
    //   2292: aload 19
    //   2294: astore 24
    //   2296: aload 21
    //   2298: astore 25
    //   2300: aload 19
    //   2302: astore 26
    //   2304: aload 21
    //   2306: astore 27
    //   2308: aload 21
    //   2310: astore 28
    //   2312: aload 23
    //   2314: iload 6
    //   2316: putfield 60	ct/aa:a	I
    //   2319: iload 12
    //   2321: istore 14
    //   2323: iload 13
    //   2325: istore 12
    //   2327: iload 14
    //   2329: istore 13
    //   2331: aload 29
    //   2333: new 27	java/lang/StringBuilder
    //   2336: dup
    //   2337: invokespecial 221	java/lang/StringBuilder:<init>	()V
    //   2340: aload_0
    //   2341: getfield 36	ct/z:p	Ljava/lang/String;
    //   2344: invokevirtual 40	java/lang/StringBuilder:append	(Ljava/lang/String;)Ljava/lang/StringBuilder;
    //   2347: ldc_w 316
    //   2350: invokevirtual 40	java/lang/StringBuilder:append	(Ljava/lang/String;)Ljava/lang/StringBuilder;
    //   2353: iload_3
    //   2354: invokevirtual 218	java/lang/StringBuilder:append	(I)Ljava/lang/StringBuilder;
    //   2357: invokevirtual 120	java/lang/StringBuilder:toString	()Ljava/lang/String;
    //   2360: putfield 317	ct/ac:p	Ljava/lang/String;
    //   2363: aload 29
    //   2365: iload_3
    //   2366: putfield 320	ct/ac:s	I
    //   2369: aload 19
    //   2371: invokestatic 89	android/text/TextUtils:isEmpty	(Ljava/lang/CharSequence;)Z
    //   2374: ifeq +2131 -> 4505
    //   2377: iload_3
    //   2378: iconst_1
    //   2379: iadd
    //   2380: istore_3
    //   2381: iconst_0
    //   2382: istore_2
    //   2383: invokestatic 324	ct/p:b	()Ljava/lang/String;
    //   2386: invokestatic 89	android/text/TextUtils:isEmpty	(Ljava/lang/CharSequence;)Z
    //   2389: ifne +162 -> 2551
    //   2392: aload 23
    //   2394: getfield 60	ct/aa:a	I
    //   2397: bipush -21
    //   2399: if_icmpeq +152 -> 2551
    //   2402: aload 23
    //   2404: invokestatic 21	java/lang/System:currentTimeMillis	()J
    //   2407: aload_0
    //   2408: getfield 25	ct/z:k	J
    //   2411: lsub
    //   2412: l2i
    //   2413: putfield 326	ct/aa:f	I
    //   2416: aload 29
    //   2418: aload 23
    //   2420: getfield 60	ct/aa:a	I
    //   2423: putfield 328	ct/ac:k	I
    //   2426: aload 29
    //   2428: aload 21
    //   2430: putfield 331	ct/ac:C	Ljava/lang/String;
    //   2433: aload 29
    //   2435: aload 23
    //   2437: getfield 326	ct/aa:f	I
    //   2440: putfield 334	ct/ac:l	I
    //   2443: aload 29
    //   2445: invokestatic 21	java/lang/System:currentTimeMillis	()J
    //   2448: lload 15
    //   2450: lsub
    //   2451: l2i
    //   2452: putfield 335	ct/ac:m	I
    //   2455: aload 29
    //   2457: aload 19
    //   2459: putfield 336	ct/ac:f	Ljava/lang/String;
    //   2462: aload_0
    //   2463: getfield 113	ct/z:j	[B
    //   2466: ifnull +2066 -> 4532
    //   2469: aload 29
    //   2471: aload_0
    //   2472: getfield 113	ct/z:j	[B
    //   2475: arraylength
    //   2476: i2l
    //   2477: putfield 338	ct/ac:n	J
    //   2480: aload 29
    //   2482: iload 13
    //   2484: putfield 341	ct/ac:z	Z
    //   2487: iload 13
    //   2489: ifeq +17 -> 2506
    //   2492: aload 29
    //   2494: getfield 328	ct/ac:k	I
    //   2497: ifeq +9 -> 2506
    //   2500: aload 29
    //   2502: iconst_1
    //   2503: putfield 344	ct/ac:w	I
    //   2506: aload 29
    //   2508: aload_0
    //   2509: getfield 346	ct/z:h	Z
    //   2512: putfield 349	ct/ac:B	Z
    //   2515: invokestatic 354	ct/o:a	()Lct/o;
    //   2518: new 356	ct/ad
    //   2521: dup
    //   2522: aload 29
    //   2524: invokespecial 359	ct/ad:<init>	(Lct/ac;)V
    //   2527: invokevirtual 362	ct/o:a	(Ljava/lang/Runnable;)V
    //   2530: aload_0
    //   2531: aload 29
    //   2533: invokevirtual 364	ct/z:a	(Lct/ac;)V
    //   2536: aload 29
    //   2538: invokevirtual 365	ct/ac:toString	()Ljava/lang/String;
    //   2541: pop
    //   2542: aload 29
    //   2544: invokevirtual 365	ct/ac:toString	()Ljava/lang/String;
    //   2547: pop
    //   2548: invokestatic 45	ct/az:b	()V
    //   2551: aload_0
    //   2552: getfield 368	ct/z:g	Z
    //   2555: ifne +11 -> 2566
    //   2558: aload 23
    //   2560: getfield 60	ct/aa:a	I
    //   2563: ifeq +13 -> 2576
    //   2566: aload 22
    //   2568: invokevirtual 374	org/apache/http/impl/client/DefaultHttpClient:getConnectionManager	()Lorg/apache/http/conn/ClientConnectionManager;
    //   2571: invokeinterface 379 1 0
    //   2576: lload 15
    //   2578: invokestatic 381	ct/x:a	(J)Z
    //   2581: istore 13
    //   2583: aload 23
    //   2585: getfield 60	ct/aa:a	I
    //   2588: bipush -4
    //   2590: if_icmpeq -1581 -> 1009
    //   2593: aload 23
    //   2595: getfield 60	ct/aa:a	I
    //   2598: bipush -17
    //   2600: if_icmpeq -1591 -> 1009
    //   2603: iload 13
    //   2605: ifne -1596 -> 1009
    //   2608: aload 19
    //   2610: astore 22
    //   2612: iload 12
    //   2614: istore 13
    //   2616: aload 21
    //   2618: astore 20
    //   2620: iload_2
    //   2621: istore 4
    //   2623: goto -2543 -> 80
    //   2626: invokestatic 132	ct/ay:h	()Z
    //   2629: ifeq +13 -> 2642
    //   2632: bipush 10
    //   2634: istore 5
    //   2636: bipush 10
    //   2638: istore_2
    //   2639: goto -898 -> 1741
    //   2642: invokestatic 489	ct/ay:g	()Z
    //   2645: istore 14
    //   2647: iload 14
    //   2649: ifeq -908 -> 1741
    //   2652: bipush 15
    //   2654: istore 5
    //   2656: bipush 10
    //   2658: istore_2
    //   2659: goto -918 -> 1741
    //   2662: aload 19
    //   2664: astore 24
    //   2666: aload 21
    //   2668: astore 25
    //   2670: aload 19
    //   2672: astore 26
    //   2674: aload 21
    //   2676: astore 27
    //   2678: aload 21
    //   2680: astore 28
    //   2682: aload 33
    //   2684: invokeinterface 493 1 0
    //   2689: invokeinterface 499 1 0
    //   2694: astore 20
    //   2696: iconst_1
    //   2697: istore 14
    //   2699: bipush 8
    //   2701: istore 5
    //   2703: iload 5
    //   2705: istore_2
    //   2706: aload_0
    //   2707: getfield 368	ct/z:g	Z
    //   2710: ifeq +1224 -> 3934
    //   2713: iconst_0
    //   2714: istore 6
    //   2716: iload 5
    //   2718: istore_2
    //   2719: aload_0
    //   2720: getfield 500	ct/z:l	I
    //   2723: istore 10
    //   2725: iload 5
    //   2727: istore_2
    //   2728: iload 10
    //   2730: newarray <illegal type>
    //   2732: astore 24
    //   2734: iload 5
    //   2736: istore_2
    //   2737: invokestatic 21	java/lang/System:currentTimeMillis	()J
    //   2740: lstore 17
    //   2742: iload 6
    //   2744: iload 10
    //   2746: if_icmpge +385 -> 3131
    //   2749: iload 5
    //   2751: istore_2
    //   2752: aload 20
    //   2754: aload 24
    //   2756: iload 6
    //   2758: iload 10
    //   2760: iload 6
    //   2762: isub
    //   2763: invokevirtual 506	java/io/InputStream:read	([BII)I
    //   2766: istore 11
    //   2768: iload 11
    //   2770: iconst_m1
    //   2771: if_icmpeq +360 -> 3131
    //   2774: iload 6
    //   2776: iload 11
    //   2778: iadd
    //   2779: istore 6
    //   2781: goto -39 -> 2742
    //   2784: astore 24
    //   2786: aload 20
    //   2788: invokevirtual 509	java/io/InputStream:close	()V
    //   2791: iload 5
    //   2793: istore_2
    //   2794: aload 23
    //   2796: bipush -8
    //   2798: putfield 60	ct/aa:a	I
    //   2801: iload 5
    //   2803: istore_2
    //   2804: aload 29
    //   2806: new 27	java/lang/StringBuilder
    //   2809: dup
    //   2810: ldc_w 511
    //   2813: invokespecial 32	java/lang/StringBuilder:<init>	(Ljava/lang/String;)V
    //   2816: iload 10
    //   2818: invokevirtual 218	java/lang/StringBuilder:append	(I)Ljava/lang/StringBuilder;
    //   2821: invokevirtual 120	java/lang/StringBuilder:toString	()Ljava/lang/String;
    //   2824: putfield 305	ct/ac:r	Ljava/lang/String;
    //   2827: iload 5
    //   2829: istore_2
    //   2830: aload 29
    //   2832: iload 10
    //   2834: i2l
    //   2835: putfield 514	ct/ac:o	J
    //   2838: aload 29
    //   2840: new 27	java/lang/StringBuilder
    //   2843: dup
    //   2844: invokespecial 221	java/lang/StringBuilder:<init>	()V
    //   2847: aload_0
    //   2848: getfield 36	ct/z:p	Ljava/lang/String;
    //   2851: invokevirtual 40	java/lang/StringBuilder:append	(Ljava/lang/String;)Ljava/lang/StringBuilder;
    //   2854: ldc_w 316
    //   2857: invokevirtual 40	java/lang/StringBuilder:append	(Ljava/lang/String;)Ljava/lang/StringBuilder;
    //   2860: iload_3
    //   2861: invokevirtual 218	java/lang/StringBuilder:append	(I)Ljava/lang/StringBuilder;
    //   2864: invokevirtual 120	java/lang/StringBuilder:toString	()Ljava/lang/String;
    //   2867: putfield 317	ct/ac:p	Ljava/lang/String;
    //   2870: aload 29
    //   2872: iload_3
    //   2873: putfield 320	ct/ac:s	I
    //   2876: aload 19
    //   2878: invokestatic 89	android/text/TextUtils:isEmpty	(Ljava/lang/CharSequence;)Z
    //   2881: ifne +19 -> 2900
    //   2884: iload 4
    //   2886: iconst_1
    //   2887: iadd
    //   2888: bipush 6
    //   2890: if_icmple +10 -> 2900
    //   2893: aload 23
    //   2895: bipush -5
    //   2897: putfield 60	ct/aa:a	I
    //   2900: invokestatic 324	ct/p:b	()Ljava/lang/String;
    //   2903: invokestatic 89	android/text/TextUtils:isEmpty	(Ljava/lang/CharSequence;)Z
    //   2906: ifne +156 -> 3062
    //   2909: aload 23
    //   2911: getfield 60	ct/aa:a	I
    //   2914: bipush -21
    //   2916: if_icmpeq +146 -> 3062
    //   2919: aload 23
    //   2921: invokestatic 21	java/lang/System:currentTimeMillis	()J
    //   2924: aload_0
    //   2925: getfield 25	ct/z:k	J
    //   2928: lsub
    //   2929: l2i
    //   2930: putfield 326	ct/aa:f	I
    //   2933: aload 29
    //   2935: aload 23
    //   2937: getfield 60	ct/aa:a	I
    //   2940: putfield 328	ct/ac:k	I
    //   2943: aload 29
    //   2945: aload 21
    //   2947: putfield 331	ct/ac:C	Ljava/lang/String;
    //   2950: aload 29
    //   2952: aload 23
    //   2954: getfield 326	ct/aa:f	I
    //   2957: putfield 334	ct/ac:l	I
    //   2960: aload 29
    //   2962: invokestatic 21	java/lang/System:currentTimeMillis	()J
    //   2965: lload 15
    //   2967: lsub
    //   2968: l2i
    //   2969: putfield 335	ct/ac:m	I
    //   2972: aload 29
    //   2974: aload 19
    //   2976: putfield 336	ct/ac:f	Ljava/lang/String;
    //   2979: aload_0
    //   2980: getfield 113	ct/z:j	[B
    //   2983: ifnull +139 -> 3122
    //   2986: aload 29
    //   2988: aload_0
    //   2989: getfield 113	ct/z:j	[B
    //   2992: arraylength
    //   2993: i2l
    //   2994: putfield 338	ct/ac:n	J
    //   2997: aload 29
    //   2999: iconst_1
    //   3000: putfield 341	ct/ac:z	Z
    //   3003: aload 29
    //   3005: getfield 328	ct/ac:k	I
    //   3008: ifeq +9 -> 3017
    //   3011: aload 29
    //   3013: iconst_1
    //   3014: putfield 344	ct/ac:w	I
    //   3017: aload 29
    //   3019: aload_0
    //   3020: getfield 346	ct/z:h	Z
    //   3023: putfield 349	ct/ac:B	Z
    //   3026: invokestatic 354	ct/o:a	()Lct/o;
    //   3029: new 356	ct/ad
    //   3032: dup
    //   3033: aload 29
    //   3035: invokespecial 359	ct/ad:<init>	(Lct/ac;)V
    //   3038: invokevirtual 362	ct/o:a	(Ljava/lang/Runnable;)V
    //   3041: aload_0
    //   3042: aload 29
    //   3044: invokevirtual 364	ct/z:a	(Lct/ac;)V
    //   3047: aload 29
    //   3049: invokevirtual 365	ct/ac:toString	()Ljava/lang/String;
    //   3052: pop
    //   3053: aload 29
    //   3055: invokevirtual 365	ct/ac:toString	()Ljava/lang/String;
    //   3058: pop
    //   3059: invokestatic 45	ct/az:b	()V
    //   3062: aload_0
    //   3063: getfield 368	ct/z:g	Z
    //   3066: ifne +11 -> 3077
    //   3069: aload 23
    //   3071: getfield 60	ct/aa:a	I
    //   3074: ifeq +13 -> 3087
    //   3077: aload 22
    //   3079: invokevirtual 374	org/apache/http/impl/client/DefaultHttpClient:getConnectionManager	()Lorg/apache/http/conn/ClientConnectionManager;
    //   3082: invokeinterface 379 1 0
    //   3087: lload 15
    //   3089: invokestatic 381	ct/x:a	(J)Z
    //   3092: istore 12
    //   3094: aload 23
    //   3096: getfield 60	ct/aa:a	I
    //   3099: bipush -4
    //   3101: if_icmpeq -2092 -> 1009
    //   3104: aload 23
    //   3106: getfield 60	ct/aa:a	I
    //   3109: bipush -17
    //   3111: if_icmpeq -2102 -> 1009
    //   3114: iload 12
    //   3116: ifeq -2107 -> 1009
    //   3119: aload 23
    //   3121: areturn
    //   3122: aload 29
    //   3124: lconst_0
    //   3125: putfield 338	ct/ac:n	J
    //   3128: goto -131 -> 2997
    //   3131: bipush 9
    //   3133: istore 5
    //   3135: iload 5
    //   3137: istore_2
    //   3138: aload 23
    //   3140: invokestatic 21	java/lang/System:currentTimeMillis	()J
    //   3143: lload 17
    //   3145: lsub
    //   3146: l2i
    //   3147: putfield 516	ct/aa:d	I
    //   3150: iload 5
    //   3152: istore_2
    //   3153: aload 29
    //   3155: aload 23
    //   3157: getfield 516	ct/aa:d	I
    //   3160: putfield 518	ct/ac:j	I
    //   3163: iload 5
    //   3165: istore_2
    //   3166: aload 29
    //   3168: iload 6
    //   3170: i2l
    //   3171: putfield 514	ct/ac:o	J
    //   3174: iload 6
    //   3176: iload 10
    //   3178: if_icmplt +347 -> 3525
    //   3181: iload 5
    //   3183: istore_2
    //   3184: aload 29
    //   3186: new 27	java/lang/StringBuilder
    //   3189: dup
    //   3190: ldc_w 520
    //   3193: invokespecial 32	java/lang/StringBuilder:<init>	(Ljava/lang/String;)V
    //   3196: iload 6
    //   3198: invokevirtual 218	java/lang/StringBuilder:append	(I)Ljava/lang/StringBuilder;
    //   3201: invokevirtual 120	java/lang/StringBuilder:toString	()Ljava/lang/String;
    //   3204: putfield 305	ct/ac:r	Ljava/lang/String;
    //   3207: iload 5
    //   3209: istore_2
    //   3210: aload 23
    //   3212: iconst_m1
    //   3213: putfield 60	ct/aa:a	I
    //   3216: aload 20
    //   3218: invokevirtual 509	java/io/InputStream:close	()V
    //   3221: iload 5
    //   3223: istore_2
    //   3224: aload 23
    //   3226: getfield 60	ct/aa:a	I
    //   3229: ifne +2323 -> 5552
    //   3232: iload 5
    //   3234: istore_2
    //   3235: aload 29
    //   3237: iconst_0
    //   3238: putfield 344	ct/ac:w	I
    //   3241: aload 29
    //   3243: new 27	java/lang/StringBuilder
    //   3246: dup
    //   3247: invokespecial 221	java/lang/StringBuilder:<init>	()V
    //   3250: aload_0
    //   3251: getfield 36	ct/z:p	Ljava/lang/String;
    //   3254: invokevirtual 40	java/lang/StringBuilder:append	(Ljava/lang/String;)Ljava/lang/StringBuilder;
    //   3257: ldc_w 316
    //   3260: invokevirtual 40	java/lang/StringBuilder:append	(Ljava/lang/String;)Ljava/lang/StringBuilder;
    //   3263: iload_3
    //   3264: invokevirtual 218	java/lang/StringBuilder:append	(I)Ljava/lang/StringBuilder;
    //   3267: invokevirtual 120	java/lang/StringBuilder:toString	()Ljava/lang/String;
    //   3270: putfield 317	ct/ac:p	Ljava/lang/String;
    //   3273: aload 29
    //   3275: iload_3
    //   3276: putfield 320	ct/ac:s	I
    //   3279: aload 19
    //   3281: invokestatic 89	android/text/TextUtils:isEmpty	(Ljava/lang/CharSequence;)Z
    //   3284: ifne +19 -> 3303
    //   3287: iload 4
    //   3289: iconst_1
    //   3290: iadd
    //   3291: bipush 6
    //   3293: if_icmple +10 -> 3303
    //   3296: aload 23
    //   3298: bipush -5
    //   3300: putfield 60	ct/aa:a	I
    //   3303: invokestatic 324	ct/p:b	()Ljava/lang/String;
    //   3306: invokestatic 89	android/text/TextUtils:isEmpty	(Ljava/lang/CharSequence;)Z
    //   3309: ifne +156 -> 3465
    //   3312: aload 23
    //   3314: getfield 60	ct/aa:a	I
    //   3317: bipush -21
    //   3319: if_icmpeq +146 -> 3465
    //   3322: aload 23
    //   3324: invokestatic 21	java/lang/System:currentTimeMillis	()J
    //   3327: aload_0
    //   3328: getfield 25	ct/z:k	J
    //   3331: lsub
    //   3332: l2i
    //   3333: putfield 326	ct/aa:f	I
    //   3336: aload 29
    //   3338: aload 23
    //   3340: getfield 60	ct/aa:a	I
    //   3343: putfield 328	ct/ac:k	I
    //   3346: aload 29
    //   3348: aload 21
    //   3350: putfield 331	ct/ac:C	Ljava/lang/String;
    //   3353: aload 29
    //   3355: aload 23
    //   3357: getfield 326	ct/aa:f	I
    //   3360: putfield 334	ct/ac:l	I
    //   3363: aload 29
    //   3365: invokestatic 21	java/lang/System:currentTimeMillis	()J
    //   3368: lload 15
    //   3370: lsub
    //   3371: l2i
    //   3372: putfield 335	ct/ac:m	I
    //   3375: aload 29
    //   3377: aload 19
    //   3379: putfield 336	ct/ac:f	Ljava/lang/String;
    //   3382: aload_0
    //   3383: getfield 113	ct/z:j	[B
    //   3386: ifnull +586 -> 3972
    //   3389: aload 29
    //   3391: aload_0
    //   3392: getfield 113	ct/z:j	[B
    //   3395: arraylength
    //   3396: i2l
    //   3397: putfield 338	ct/ac:n	J
    //   3400: aload 29
    //   3402: iconst_1
    //   3403: putfield 341	ct/ac:z	Z
    //   3406: aload 29
    //   3408: getfield 328	ct/ac:k	I
    //   3411: ifeq +9 -> 3420
    //   3414: aload 29
    //   3416: iconst_1
    //   3417: putfield 344	ct/ac:w	I
    //   3420: aload 29
    //   3422: aload_0
    //   3423: getfield 346	ct/z:h	Z
    //   3426: putfield 349	ct/ac:B	Z
    //   3429: invokestatic 354	ct/o:a	()Lct/o;
    //   3432: new 356	ct/ad
    //   3435: dup
    //   3436: aload 29
    //   3438: invokespecial 359	ct/ad:<init>	(Lct/ac;)V
    //   3441: invokevirtual 362	ct/o:a	(Ljava/lang/Runnable;)V
    //   3444: aload_0
    //   3445: aload 29
    //   3447: invokevirtual 364	ct/z:a	(Lct/ac;)V
    //   3450: aload 29
    //   3452: invokevirtual 365	ct/ac:toString	()Ljava/lang/String;
    //   3455: pop
    //   3456: aload 29
    //   3458: invokevirtual 365	ct/ac:toString	()Ljava/lang/String;
    //   3461: pop
    //   3462: invokestatic 45	ct/az:b	()V
    //   3465: aload_0
    //   3466: getfield 368	ct/z:g	Z
    //   3469: ifne +11 -> 3480
    //   3472: aload 23
    //   3474: getfield 60	ct/aa:a	I
    //   3477: ifeq +13 -> 3490
    //   3480: aload 22
    //   3482: invokevirtual 374	org/apache/http/impl/client/DefaultHttpClient:getConnectionManager	()Lorg/apache/http/conn/ClientConnectionManager;
    //   3485: invokeinterface 379 1 0
    //   3490: lload 15
    //   3492: invokestatic 381	ct/x:a	(J)Z
    //   3495: istore 12
    //   3497: aload 23
    //   3499: getfield 60	ct/aa:a	I
    //   3502: bipush -4
    //   3504: if_icmpeq -2495 -> 1009
    //   3507: aload 23
    //   3509: getfield 60	ct/aa:a	I
    //   3512: bipush -17
    //   3514: if_icmpeq -2505 -> 1009
    //   3517: iload 12
    //   3519: ifeq -2510 -> 1009
    //   3522: aload 23
    //   3524: areturn
    //   3525: iload 5
    //   3527: istore_2
    //   3528: aload 23
    //   3530: iload 6
    //   3532: newarray <illegal type>
    //   3534: putfield 522	ct/aa:b	[B
    //   3537: iload 5
    //   3539: istore_2
    //   3540: aload 24
    //   3542: iconst_0
    //   3543: aload 23
    //   3545: getfield 522	ct/aa:b	[B
    //   3548: iconst_0
    //   3549: iload 6
    //   3551: invokestatic 526	java/lang/System:arraycopy	(Ljava/lang/Object;ILjava/lang/Object;II)V
    //   3554: iload 5
    //   3556: istore_2
    //   3557: aload 23
    //   3559: iconst_0
    //   3560: putfield 60	ct/aa:a	I
    //   3563: goto -347 -> 3216
    //   3566: astore 20
    //   3568: aload 19
    //   3570: astore 25
    //   3572: iconst_1
    //   3573: istore 12
    //   3575: aload 22
    //   3577: astore 24
    //   3579: aload 21
    //   3581: astore 19
    //   3583: aload 25
    //   3585: astore 21
    //   3587: aload 20
    //   3589: astore 22
    //   3591: aload 24
    //   3593: astore 20
    //   3595: goto -2962 -> 633
    //   3598: astore 24
    //   3600: aload 20
    //   3602: invokevirtual 509	java/io/InputStream:close	()V
    //   3605: iload 5
    //   3607: istore_2
    //   3608: aload 23
    //   3610: bipush -8
    //   3612: putfield 60	ct/aa:a	I
    //   3615: iload 5
    //   3617: istore_2
    //   3618: aload 29
    //   3620: new 27	java/lang/StringBuilder
    //   3623: dup
    //   3624: ldc_w 511
    //   3627: invokespecial 32	java/lang/StringBuilder:<init>	(Ljava/lang/String;)V
    //   3630: iload 10
    //   3632: invokevirtual 218	java/lang/StringBuilder:append	(I)Ljava/lang/StringBuilder;
    //   3635: invokevirtual 120	java/lang/StringBuilder:toString	()Ljava/lang/String;
    //   3638: putfield 305	ct/ac:r	Ljava/lang/String;
    //   3641: aload 29
    //   3643: new 27	java/lang/StringBuilder
    //   3646: dup
    //   3647: invokespecial 221	java/lang/StringBuilder:<init>	()V
    //   3650: aload_0
    //   3651: getfield 36	ct/z:p	Ljava/lang/String;
    //   3654: invokevirtual 40	java/lang/StringBuilder:append	(Ljava/lang/String;)Ljava/lang/StringBuilder;
    //   3657: ldc_w 316
    //   3660: invokevirtual 40	java/lang/StringBuilder:append	(Ljava/lang/String;)Ljava/lang/StringBuilder;
    //   3663: iload_3
    //   3664: invokevirtual 218	java/lang/StringBuilder:append	(I)Ljava/lang/StringBuilder;
    //   3667: invokevirtual 120	java/lang/StringBuilder:toString	()Ljava/lang/String;
    //   3670: putfield 317	ct/ac:p	Ljava/lang/String;
    //   3673: aload 29
    //   3675: iload_3
    //   3676: putfield 320	ct/ac:s	I
    //   3679: aload 19
    //   3681: invokestatic 89	android/text/TextUtils:isEmpty	(Ljava/lang/CharSequence;)Z
    //   3684: ifne +19 -> 3703
    //   3687: iload 4
    //   3689: iconst_1
    //   3690: iadd
    //   3691: bipush 6
    //   3693: if_icmple +10 -> 3703
    //   3696: aload 23
    //   3698: bipush -5
    //   3700: putfield 60	ct/aa:a	I
    //   3703: invokestatic 324	ct/p:b	()Ljava/lang/String;
    //   3706: invokestatic 89	android/text/TextUtils:isEmpty	(Ljava/lang/CharSequence;)Z
    //   3709: ifne +156 -> 3865
    //   3712: aload 23
    //   3714: getfield 60	ct/aa:a	I
    //   3717: bipush -21
    //   3719: if_icmpeq +146 -> 3865
    //   3722: aload 23
    //   3724: invokestatic 21	java/lang/System:currentTimeMillis	()J
    //   3727: aload_0
    //   3728: getfield 25	ct/z:k	J
    //   3731: lsub
    //   3732: l2i
    //   3733: putfield 326	ct/aa:f	I
    //   3736: aload 29
    //   3738: aload 23
    //   3740: getfield 60	ct/aa:a	I
    //   3743: putfield 328	ct/ac:k	I
    //   3746: aload 29
    //   3748: aload 21
    //   3750: putfield 331	ct/ac:C	Ljava/lang/String;
    //   3753: aload 29
    //   3755: aload 23
    //   3757: getfield 326	ct/aa:f	I
    //   3760: putfield 334	ct/ac:l	I
    //   3763: aload 29
    //   3765: invokestatic 21	java/lang/System:currentTimeMillis	()J
    //   3768: lload 15
    //   3770: lsub
    //   3771: l2i
    //   3772: putfield 335	ct/ac:m	I
    //   3775: aload 29
    //   3777: aload 19
    //   3779: putfield 336	ct/ac:f	Ljava/lang/String;
    //   3782: aload_0
    //   3783: getfield 113	ct/z:j	[B
    //   3786: ifnull +139 -> 3925
    //   3789: aload 29
    //   3791: aload_0
    //   3792: getfield 113	ct/z:j	[B
    //   3795: arraylength
    //   3796: i2l
    //   3797: putfield 338	ct/ac:n	J
    //   3800: aload 29
    //   3802: iconst_1
    //   3803: putfield 341	ct/ac:z	Z
    //   3806: aload 29
    //   3808: getfield 328	ct/ac:k	I
    //   3811: ifeq +9 -> 3820
    //   3814: aload 29
    //   3816: iconst_1
    //   3817: putfield 344	ct/ac:w	I
    //   3820: aload 29
    //   3822: aload_0
    //   3823: getfield 346	ct/z:h	Z
    //   3826: putfield 349	ct/ac:B	Z
    //   3829: invokestatic 354	ct/o:a	()Lct/o;
    //   3832: new 356	ct/ad
    //   3835: dup
    //   3836: aload 29
    //   3838: invokespecial 359	ct/ad:<init>	(Lct/ac;)V
    //   3841: invokevirtual 362	ct/o:a	(Ljava/lang/Runnable;)V
    //   3844: aload_0
    //   3845: aload 29
    //   3847: invokevirtual 364	ct/z:a	(Lct/ac;)V
    //   3850: aload 29
    //   3852: invokevirtual 365	ct/ac:toString	()Ljava/lang/String;
    //   3855: pop
    //   3856: aload 29
    //   3858: invokevirtual 365	ct/ac:toString	()Ljava/lang/String;
    //   3861: pop
    //   3862: invokestatic 45	ct/az:b	()V
    //   3865: aload_0
    //   3866: getfield 368	ct/z:g	Z
    //   3869: ifne +11 -> 3880
    //   3872: aload 23
    //   3874: getfield 60	ct/aa:a	I
    //   3877: ifeq +13 -> 3890
    //   3880: aload 22
    //   3882: invokevirtual 374	org/apache/http/impl/client/DefaultHttpClient:getConnectionManager	()Lorg/apache/http/conn/ClientConnectionManager;
    //   3885: invokeinterface 379 1 0
    //   3890: lload 15
    //   3892: invokestatic 381	ct/x:a	(J)Z
    //   3895: istore 12
    //   3897: aload 23
    //   3899: getfield 60	ct/aa:a	I
    //   3902: bipush -4
    //   3904: if_icmpeq -2895 -> 1009
    //   3907: aload 23
    //   3909: getfield 60	ct/aa:a	I
    //   3912: bipush -17
    //   3914: if_icmpeq -2905 -> 1009
    //   3917: iload 12
    //   3919: ifeq -2910 -> 1009
    //   3922: aload 23
    //   3924: areturn
    //   3925: aload 29
    //   3927: lconst_0
    //   3928: putfield 338	ct/ac:n	J
    //   3931: goto -131 -> 3800
    //   3934: iload 5
    //   3936: istore_2
    //   3937: invokestatic 45	ct/az:b	()V
    //   3940: iload 5
    //   3942: istore_2
    //   3943: aload 23
    //   3945: iconst_0
    //   3946: putfield 60	ct/aa:a	I
    //   3949: goto -728 -> 3221
    //   3952: astore 20
    //   3954: aload 22
    //   3956: astore 20
    //   3958: aload 19
    //   3960: astore 22
    //   3962: iconst_1
    //   3963: istore 12
    //   3965: aload 21
    //   3967: astore 19
    //   3969: goto -2628 -> 1341
    //   3972: aload 29
    //   3974: lconst_0
    //   3975: putfield 338	ct/ac:n	J
    //   3978: goto -578 -> 3400
    //   3981: aload 19
    //   3983: astore 24
    //   3985: aload 21
    //   3987: astore 25
    //   3989: aload 19
    //   3991: astore 26
    //   3993: aload 21
    //   3995: astore 27
    //   3997: aload 21
    //   3999: astore 28
    //   4001: aload 23
    //   4003: bipush -21
    //   4005: putfield 60	ct/aa:a	I
    //   4008: aload 19
    //   4010: astore 24
    //   4012: aload 21
    //   4014: astore 25
    //   4016: aload 19
    //   4018: astore 26
    //   4020: aload 21
    //   4022: astore 27
    //   4024: aload 19
    //   4026: astore 20
    //   4028: aload 33
    //   4030: ldc_w 528
    //   4033: invokeinterface 480 2 0
    //   4038: astore 28
    //   4040: aload 28
    //   4042: ifnull +1507 -> 5549
    //   4045: aload 19
    //   4047: astore 24
    //   4049: aload 21
    //   4051: astore 25
    //   4053: aload 19
    //   4055: astore 26
    //   4057: aload 21
    //   4059: astore 27
    //   4061: aload 19
    //   4063: astore 20
    //   4065: aload 28
    //   4067: invokeinterface 485 1 0
    //   4072: astore 19
    //   4074: aload 19
    //   4076: astore 28
    //   4078: aload 19
    //   4080: astore 24
    //   4082: aload 21
    //   4084: astore 25
    //   4086: aload 19
    //   4088: astore 26
    //   4090: aload 21
    //   4092: astore 27
    //   4094: aload 19
    //   4096: astore 20
    //   4098: invokestatic 45	ct/az:b	()V
    //   4101: aload 28
    //   4103: astore 19
    //   4105: aload 29
    //   4107: iconst_1
    //   4108: putfield 530	ct/ac:e	Z
    //   4111: aload 19
    //   4113: invokestatic 89	android/text/TextUtils:isEmpty	(Ljava/lang/CharSequence;)Z
    //   4116: istore 13
    //   4118: iload 13
    //   4120: ifeq +27 -> 4147
    //   4123: aload 23
    //   4125: bipush -6
    //   4127: putfield 60	ct/aa:a	I
    //   4130: aconst_null
    //   4131: astore 19
    //   4133: iconst_1
    //   4134: istore 14
    //   4136: iload 12
    //   4138: istore 13
    //   4140: iload 14
    //   4142: istore 12
    //   4144: goto -1813 -> 2331
    //   4147: aload_0
    //   4148: getfield 532	ct/z:o	Z
    //   4151: ifne +1384 -> 5535
    //   4154: invokestatic 45	ct/az:b	()V
    //   4157: aload 23
    //   4159: bipush -7
    //   4161: putfield 60	ct/aa:a	I
    //   4164: aload 29
    //   4166: new 27	java/lang/StringBuilder
    //   4169: dup
    //   4170: invokespecial 221	java/lang/StringBuilder:<init>	()V
    //   4173: aload_0
    //   4174: getfield 36	ct/z:p	Ljava/lang/String;
    //   4177: invokevirtual 40	java/lang/StringBuilder:append	(Ljava/lang/String;)Ljava/lang/StringBuilder;
    //   4180: ldc_w 316
    //   4183: invokevirtual 40	java/lang/StringBuilder:append	(Ljava/lang/String;)Ljava/lang/StringBuilder;
    //   4186: iload_3
    //   4187: invokevirtual 218	java/lang/StringBuilder:append	(I)Ljava/lang/StringBuilder;
    //   4190: invokevirtual 120	java/lang/StringBuilder:toString	()Ljava/lang/String;
    //   4193: putfield 317	ct/ac:p	Ljava/lang/String;
    //   4196: aload 29
    //   4198: iload_3
    //   4199: putfield 320	ct/ac:s	I
    //   4202: aload 19
    //   4204: invokestatic 89	android/text/TextUtils:isEmpty	(Ljava/lang/CharSequence;)Z
    //   4207: ifne +19 -> 4226
    //   4210: iload 4
    //   4212: iconst_1
    //   4213: iadd
    //   4214: bipush 6
    //   4216: if_icmple +10 -> 4226
    //   4219: aload 23
    //   4221: bipush -5
    //   4223: putfield 60	ct/aa:a	I
    //   4226: invokestatic 324	ct/p:b	()Ljava/lang/String;
    //   4229: invokestatic 89	android/text/TextUtils:isEmpty	(Ljava/lang/CharSequence;)Z
    //   4232: ifne +162 -> 4394
    //   4235: aload 23
    //   4237: getfield 60	ct/aa:a	I
    //   4240: bipush -21
    //   4242: if_icmpeq +152 -> 4394
    //   4245: aload 23
    //   4247: invokestatic 21	java/lang/System:currentTimeMillis	()J
    //   4250: aload_0
    //   4251: getfield 25	ct/z:k	J
    //   4254: lsub
    //   4255: l2i
    //   4256: putfield 326	ct/aa:f	I
    //   4259: aload 29
    //   4261: aload 23
    //   4263: getfield 60	ct/aa:a	I
    //   4266: putfield 328	ct/ac:k	I
    //   4269: aload 29
    //   4271: aload 21
    //   4273: putfield 331	ct/ac:C	Ljava/lang/String;
    //   4276: aload 29
    //   4278: aload 23
    //   4280: getfield 326	ct/aa:f	I
    //   4283: putfield 334	ct/ac:l	I
    //   4286: aload 29
    //   4288: invokestatic 21	java/lang/System:currentTimeMillis	()J
    //   4291: lload 15
    //   4293: lsub
    //   4294: l2i
    //   4295: putfield 335	ct/ac:m	I
    //   4298: aload 29
    //   4300: aload 19
    //   4302: putfield 336	ct/ac:f	Ljava/lang/String;
    //   4305: aload_0
    //   4306: getfield 113	ct/z:j	[B
    //   4309: ifnull +145 -> 4454
    //   4312: aload 29
    //   4314: aload_0
    //   4315: getfield 113	ct/z:j	[B
    //   4318: arraylength
    //   4319: i2l
    //   4320: putfield 338	ct/ac:n	J
    //   4323: aload 29
    //   4325: iload 12
    //   4327: putfield 341	ct/ac:z	Z
    //   4330: iload 12
    //   4332: ifeq +17 -> 4349
    //   4335: aload 29
    //   4337: getfield 328	ct/ac:k	I
    //   4340: ifeq +9 -> 4349
    //   4343: aload 29
    //   4345: iconst_1
    //   4346: putfield 344	ct/ac:w	I
    //   4349: aload 29
    //   4351: aload_0
    //   4352: getfield 346	ct/z:h	Z
    //   4355: putfield 349	ct/ac:B	Z
    //   4358: invokestatic 354	ct/o:a	()Lct/o;
    //   4361: new 356	ct/ad
    //   4364: dup
    //   4365: aload 29
    //   4367: invokespecial 359	ct/ad:<init>	(Lct/ac;)V
    //   4370: invokevirtual 362	ct/o:a	(Ljava/lang/Runnable;)V
    //   4373: aload_0
    //   4374: aload 29
    //   4376: invokevirtual 364	ct/z:a	(Lct/ac;)V
    //   4379: aload 29
    //   4381: invokevirtual 365	ct/ac:toString	()Ljava/lang/String;
    //   4384: pop
    //   4385: aload 29
    //   4387: invokevirtual 365	ct/ac:toString	()Ljava/lang/String;
    //   4390: pop
    //   4391: invokestatic 45	ct/az:b	()V
    //   4394: aload_0
    //   4395: getfield 368	ct/z:g	Z
    //   4398: ifne +11 -> 4409
    //   4401: aload 23
    //   4403: getfield 60	ct/aa:a	I
    //   4406: ifeq +13 -> 4419
    //   4409: aload 22
    //   4411: invokevirtual 374	org/apache/http/impl/client/DefaultHttpClient:getConnectionManager	()Lorg/apache/http/conn/ClientConnectionManager;
    //   4414: invokeinterface 379 1 0
    //   4419: lload 15
    //   4421: invokestatic 381	ct/x:a	(J)Z
    //   4424: istore 12
    //   4426: aload 23
    //   4428: getfield 60	ct/aa:a	I
    //   4431: bipush -4
    //   4433: if_icmpeq -3424 -> 1009
    //   4436: aload 23
    //   4438: getfield 60	ct/aa:a	I
    //   4441: bipush -17
    //   4443: if_icmpeq -3434 -> 1009
    //   4446: iload 12
    //   4448: ifeq -3439 -> 1009
    //   4451: aload 23
    //   4453: areturn
    //   4454: aload 29
    //   4456: lconst_0
    //   4457: putfield 338	ct/ac:n	J
    //   4460: goto -137 -> 4323
    //   4463: aload 19
    //   4465: astore 24
    //   4467: aload 21
    //   4469: astore 25
    //   4471: aload 19
    //   4473: astore 26
    //   4475: aload 21
    //   4477: astore 27
    //   4479: aload 21
    //   4481: astore 28
    //   4483: aload 23
    //   4485: iload 6
    //   4487: putfield 60	ct/aa:a	I
    //   4490: iload 13
    //   4492: istore 14
    //   4494: iload 12
    //   4496: istore 13
    //   4498: iload 14
    //   4500: istore 12
    //   4502: goto -2171 -> 2331
    //   4505: iload 4
    //   4507: iconst_1
    //   4508: iadd
    //   4509: istore_2
    //   4510: iload_2
    //   4511: bipush 6
    //   4513: if_icmple +1019 -> 5532
    //   4516: iload_3
    //   4517: iconst_1
    //   4518: iadd
    //   4519: istore_3
    //   4520: iconst_0
    //   4521: istore_2
    //   4522: aload 23
    //   4524: bipush -5
    //   4526: putfield 60	ct/aa:a	I
    //   4529: goto -2146 -> 2383
    //   4532: aload 29
    //   4534: lconst_0
    //   4535: putfield 338	ct/ac:n	J
    //   4538: goto -2058 -> 2480
    //   4541: aload 22
    //   4543: instanceof 534
    //   4546: ifeq +9 -> 4555
    //   4549: bipush -11
    //   4551: istore_2
    //   4552: goto -3853 -> 699
    //   4555: aload 22
    //   4557: instanceof 536
    //   4560: ifeq +9 -> 4569
    //   4563: bipush -13
    //   4565: istore_2
    //   4566: goto -3867 -> 699
    //   4569: aload 22
    //   4571: instanceof 538
    //   4574: ifeq +9 -> 4583
    //   4577: bipush -14
    //   4579: istore_2
    //   4580: goto -3881 -> 699
    //   4583: aload 22
    //   4585: instanceof 540
    //   4588: ifeq +9 -> 4597
    //   4591: bipush -15
    //   4593: istore_2
    //   4594: goto -3895 -> 699
    //   4597: aload 22
    //   4599: instanceof 542
    //   4602: ifeq +9 -> 4611
    //   4605: bipush -16
    //   4607: istore_2
    //   4608: goto -3909 -> 699
    //   4611: aload 22
    //   4613: instanceof 544
    //   4616: ifeq +9 -> 4625
    //   4619: bipush -22
    //   4621: istore_2
    //   4622: goto -3923 -> 699
    //   4625: aload 22
    //   4627: instanceof 546
    //   4630: istore 14
    //   4632: iload 14
    //   4634: ifeq +9 -> 4643
    //   4637: bipush -12
    //   4639: istore_2
    //   4640: goto -3941 -> 699
    //   4643: bipush -3
    //   4645: istore_2
    //   4646: goto -3947 -> 699
    //   4649: bipush -4
    //   4651: istore_2
    //   4652: goto -3953 -> 699
    //   4655: iload 4
    //   4657: iconst_1
    //   4658: iadd
    //   4659: istore 5
    //   4661: iload 5
    //   4663: istore_2
    //   4664: iload_3
    //   4665: istore 4
    //   4667: iload 5
    //   4669: bipush 6
    //   4671: if_icmple -3892 -> 779
    //   4674: iload_3
    //   4675: iconst_1
    //   4676: iadd
    //   4677: istore 4
    //   4679: iconst_0
    //   4680: istore_2
    //   4681: aload 23
    //   4683: bipush -5
    //   4685: putfield 60	ct/aa:a	I
    //   4688: goto -3909 -> 779
    //   4691: aload 29
    //   4693: lconst_0
    //   4694: putfield 338	ct/ac:n	J
    //   4697: goto -3821 -> 876
    //   4700: aload 21
    //   4702: astore 22
    //   4704: iload 4
    //   4706: istore_3
    //   4707: aload 19
    //   4709: astore 20
    //   4711: iload_2
    //   4712: istore 4
    //   4714: goto -4634 -> 80
    //   4717: iload 4
    //   4719: iconst_1
    //   4720: iadd
    //   4721: istore 5
    //   4723: iload 5
    //   4725: istore_2
    //   4726: iload_3
    //   4727: istore 4
    //   4729: iload 5
    //   4731: bipush 6
    //   4733: if_icmple -3339 -> 1394
    //   4736: iload_3
    //   4737: iconst_1
    //   4738: iadd
    //   4739: istore 4
    //   4741: iconst_0
    //   4742: istore_2
    //   4743: aload 23
    //   4745: bipush -5
    //   4747: putfield 60	ct/aa:a	I
    //   4750: goto -3356 -> 1394
    //   4753: aload 29
    //   4755: lconst_0
    //   4756: putfield 338	ct/ac:n	J
    //   4759: goto -3268 -> 1491
    //   4762: astore 26
    //   4764: aload 22
    //   4766: astore 20
    //   4768: aload 25
    //   4770: astore 21
    //   4772: aload 24
    //   4774: astore 19
    //   4776: aload 26
    //   4778: astore 22
    //   4780: aload 29
    //   4782: new 27	java/lang/StringBuilder
    //   4785: dup
    //   4786: invokespecial 221	java/lang/StringBuilder:<init>	()V
    //   4789: aload_0
    //   4790: getfield 36	ct/z:p	Ljava/lang/String;
    //   4793: invokevirtual 40	java/lang/StringBuilder:append	(Ljava/lang/String;)Ljava/lang/StringBuilder;
    //   4796: ldc_w 316
    //   4799: invokevirtual 40	java/lang/StringBuilder:append	(Ljava/lang/String;)Ljava/lang/StringBuilder;
    //   4802: iload_3
    //   4803: invokevirtual 218	java/lang/StringBuilder:append	(I)Ljava/lang/StringBuilder;
    //   4806: invokevirtual 120	java/lang/StringBuilder:toString	()Ljava/lang/String;
    //   4809: putfield 317	ct/ac:p	Ljava/lang/String;
    //   4812: aload 29
    //   4814: iload_3
    //   4815: putfield 320	ct/ac:s	I
    //   4818: aload 19
    //   4820: invokestatic 89	android/text/TextUtils:isEmpty	(Ljava/lang/CharSequence;)Z
    //   4823: ifne +19 -> 4842
    //   4826: iload 4
    //   4828: iconst_1
    //   4829: iadd
    //   4830: bipush 6
    //   4832: if_icmple +10 -> 4842
    //   4835: aload 23
    //   4837: bipush -5
    //   4839: putfield 60	ct/aa:a	I
    //   4842: invokestatic 324	ct/p:b	()Ljava/lang/String;
    //   4845: invokestatic 89	android/text/TextUtils:isEmpty	(Ljava/lang/CharSequence;)Z
    //   4848: ifne +162 -> 5010
    //   4851: aload 23
    //   4853: getfield 60	ct/aa:a	I
    //   4856: bipush -21
    //   4858: if_icmpeq +152 -> 5010
    //   4861: aload 23
    //   4863: invokestatic 21	java/lang/System:currentTimeMillis	()J
    //   4866: aload_0
    //   4867: getfield 25	ct/z:k	J
    //   4870: lsub
    //   4871: l2i
    //   4872: putfield 326	ct/aa:f	I
    //   4875: aload 29
    //   4877: aload 23
    //   4879: getfield 60	ct/aa:a	I
    //   4882: putfield 328	ct/ac:k	I
    //   4885: aload 29
    //   4887: aload 21
    //   4889: putfield 331	ct/ac:C	Ljava/lang/String;
    //   4892: aload 29
    //   4894: aload 23
    //   4896: getfield 326	ct/aa:f	I
    //   4899: putfield 334	ct/ac:l	I
    //   4902: aload 29
    //   4904: invokestatic 21	java/lang/System:currentTimeMillis	()J
    //   4907: lload 15
    //   4909: lsub
    //   4910: l2i
    //   4911: putfield 335	ct/ac:m	I
    //   4914: aload 29
    //   4916: aload 19
    //   4918: putfield 336	ct/ac:f	Ljava/lang/String;
    //   4921: aload_0
    //   4922: getfield 113	ct/z:j	[B
    //   4925: ifnull +150 -> 5075
    //   4928: aload 29
    //   4930: aload_0
    //   4931: getfield 113	ct/z:j	[B
    //   4934: arraylength
    //   4935: i2l
    //   4936: putfield 338	ct/ac:n	J
    //   4939: aload 29
    //   4941: iload 12
    //   4943: putfield 341	ct/ac:z	Z
    //   4946: iload 12
    //   4948: ifeq +17 -> 4965
    //   4951: aload 29
    //   4953: getfield 328	ct/ac:k	I
    //   4956: ifeq +9 -> 4965
    //   4959: aload 29
    //   4961: iconst_1
    //   4962: putfield 344	ct/ac:w	I
    //   4965: aload 29
    //   4967: aload_0
    //   4968: getfield 346	ct/z:h	Z
    //   4971: putfield 349	ct/ac:B	Z
    //   4974: invokestatic 354	ct/o:a	()Lct/o;
    //   4977: new 356	ct/ad
    //   4980: dup
    //   4981: aload 29
    //   4983: invokespecial 359	ct/ad:<init>	(Lct/ac;)V
    //   4986: invokevirtual 362	ct/o:a	(Ljava/lang/Runnable;)V
    //   4989: aload_0
    //   4990: aload 29
    //   4992: invokevirtual 364	ct/z:a	(Lct/ac;)V
    //   4995: aload 29
    //   4997: invokevirtual 365	ct/ac:toString	()Ljava/lang/String;
    //   5000: pop
    //   5001: aload 29
    //   5003: invokevirtual 365	ct/ac:toString	()Ljava/lang/String;
    //   5006: pop
    //   5007: invokestatic 45	ct/az:b	()V
    //   5010: aload 20
    //   5012: ifnull +28 -> 5040
    //   5015: aload_0
    //   5016: getfield 368	ct/z:g	Z
    //   5019: ifne +11 -> 5030
    //   5022: aload 23
    //   5024: getfield 60	ct/aa:a	I
    //   5027: ifeq +13 -> 5040
    //   5030: aload 20
    //   5032: invokevirtual 374	org/apache/http/impl/client/DefaultHttpClient:getConnectionManager	()Lorg/apache/http/conn/ClientConnectionManager;
    //   5035: invokeinterface 379 1 0
    //   5040: lload 15
    //   5042: invokestatic 381	ct/x:a	(J)Z
    //   5045: istore 12
    //   5047: aload 23
    //   5049: getfield 60	ct/aa:a	I
    //   5052: bipush -4
    //   5054: if_icmpeq -4045 -> 1009
    //   5057: aload 23
    //   5059: getfield 60	ct/aa:a	I
    //   5062: bipush -17
    //   5064: if_icmpeq -4055 -> 1009
    //   5067: iload 12
    //   5069: ifne -4060 -> 1009
    //   5072: aload 22
    //   5074: athrow
    //   5075: aload 29
    //   5077: lconst_0
    //   5078: putfield 338	ct/ac:n	J
    //   5081: goto -142 -> 4939
    //   5084: aload 23
    //   5086: areturn
    //   5087: astore 20
    //   5089: goto -2298 -> 2791
    //   5092: astore 20
    //   5094: goto -1489 -> 3605
    //   5097: astore 20
    //   5099: goto -1878 -> 3221
    //   5102: astore 19
    //   5104: goto -94 -> 5010
    //   5107: astore 24
    //   5109: iconst_1
    //   5110: istore 12
    //   5112: aload 22
    //   5114: astore 20
    //   5116: aload 24
    //   5118: astore 22
    //   5120: goto -340 -> 4780
    //   5123: astore 24
    //   5125: aload 22
    //   5127: astore 20
    //   5129: aload 24
    //   5131: astore 22
    //   5133: goto -353 -> 4780
    //   5136: astore 19
    //   5138: aload 22
    //   5140: astore 20
    //   5142: aconst_null
    //   5143: astore 24
    //   5145: aload 19
    //   5147: astore 22
    //   5149: aload 24
    //   5151: astore 19
    //   5153: goto -373 -> 4780
    //   5156: astore 21
    //   5158: aload 22
    //   5160: astore 19
    //   5162: aload 21
    //   5164: astore 22
    //   5166: aload 20
    //   5168: astore 21
    //   5170: aload 26
    //   5172: astore 20
    //   5174: goto -394 -> 4780
    //   5177: astore 22
    //   5179: aload 20
    //   5181: astore 21
    //   5183: aload 26
    //   5185: astore 20
    //   5187: goto -407 -> 4780
    //   5190: astore 22
    //   5192: aload 19
    //   5194: astore 24
    //   5196: aload 21
    //   5198: astore 19
    //   5200: aload 24
    //   5202: astore 21
    //   5204: goto -424 -> 4780
    //   5207: astore 21
    //   5209: goto -3647 -> 1562
    //   5212: astore 19
    //   5214: aload 22
    //   5216: astore 20
    //   5218: aload 27
    //   5220: astore 19
    //   5222: aload 26
    //   5224: astore 22
    //   5226: goto -3885 -> 1341
    //   5229: astore 20
    //   5231: aload 22
    //   5233: astore 20
    //   5235: iconst_1
    //   5236: istore 13
    //   5238: aload 19
    //   5240: astore 22
    //   5242: aload 21
    //   5244: astore 19
    //   5246: goto -3905 -> 1341
    //   5249: astore 19
    //   5251: aload 22
    //   5253: astore 20
    //   5255: iconst_1
    //   5256: istore 13
    //   5258: aconst_null
    //   5259: astore 22
    //   5261: aload 21
    //   5263: astore 19
    //   5265: goto -3924 -> 1341
    //   5268: astore 19
    //   5270: aload 20
    //   5272: astore 19
    //   5274: aload 25
    //   5276: astore 20
    //   5278: goto -3937 -> 1341
    //   5281: astore 19
    //   5283: iload_2
    //   5284: istore_1
    //   5285: aload 20
    //   5287: astore 19
    //   5289: aload 25
    //   5291: astore 20
    //   5293: goto -3952 -> 1341
    //   5296: astore 22
    //   5298: goto -4351 -> 947
    //   5301: astore 20
    //   5303: aload 19
    //   5305: astore 21
    //   5307: aload 22
    //   5309: astore 24
    //   5311: aload 28
    //   5313: astore 19
    //   5315: aload 20
    //   5317: astore 22
    //   5319: aload 24
    //   5321: astore 20
    //   5323: goto -4690 -> 633
    //   5326: astore 24
    //   5328: aload 21
    //   5330: astore 19
    //   5332: bipush 10
    //   5334: istore_2
    //   5335: aload 22
    //   5337: astore 25
    //   5339: aload 20
    //   5341: astore 21
    //   5343: aload 24
    //   5345: astore 22
    //   5347: aload 25
    //   5349: astore 20
    //   5351: goto -4718 -> 633
    //   5354: astore 20
    //   5356: iconst_1
    //   5357: istore 13
    //   5359: aload 22
    //   5361: astore 24
    //   5363: aload 19
    //   5365: astore 22
    //   5367: aload 21
    //   5369: astore 19
    //   5371: bipush 10
    //   5373: istore_2
    //   5374: aload 22
    //   5376: astore 21
    //   5378: aload 20
    //   5380: astore 22
    //   5382: aload 24
    //   5384: astore 20
    //   5386: goto -4753 -> 633
    //   5389: astore 20
    //   5391: iconst_1
    //   5392: istore 13
    //   5394: aload 22
    //   5396: astore 24
    //   5398: aconst_null
    //   5399: astore 22
    //   5401: aload 21
    //   5403: astore 19
    //   5405: bipush 10
    //   5407: istore_2
    //   5408: aload 22
    //   5410: astore 21
    //   5412: aload 20
    //   5414: astore 22
    //   5416: aload 24
    //   5418: astore 20
    //   5420: goto -4787 -> 633
    //   5423: astore 24
    //   5425: aconst_null
    //   5426: astore 25
    //   5428: aload 20
    //   5430: astore 19
    //   5432: iconst_2
    //   5433: istore_2
    //   5434: aload 22
    //   5436: astore 21
    //   5438: aload 24
    //   5440: astore 22
    //   5442: aload 25
    //   5444: astore 20
    //   5446: goto -4813 -> 633
    //   5449: astore 21
    //   5451: aload 20
    //   5453: astore 19
    //   5455: iconst_2
    //   5456: istore_2
    //   5457: aload 21
    //   5459: astore 20
    //   5461: iload 5
    //   5463: istore_1
    //   5464: aconst_null
    //   5465: astore 24
    //   5467: aload 22
    //   5469: astore 21
    //   5471: aload 20
    //   5473: astore 22
    //   5475: aload 24
    //   5477: astore 20
    //   5479: goto -4846 -> 633
    //   5482: astore 22
    //   5484: aload 19
    //   5486: astore 21
    //   5488: aconst_null
    //   5489: astore 24
    //   5491: iconst_4
    //   5492: istore_2
    //   5493: aload 20
    //   5495: astore 19
    //   5497: aload 24
    //   5499: astore 20
    //   5501: goto -4868 -> 633
    //   5504: astore 20
    //   5506: goto -2955 -> 2551
    //   5509: astore 19
    //   5511: goto -1117 -> 4394
    //   5514: astore 19
    //   5516: goto -2051 -> 3465
    //   5519: astore 19
    //   5521: goto -1656 -> 3865
    //   5524: astore 19
    //   5526: goto -2464 -> 3062
    //   5529: goto -5233 -> 296
    //   5532: goto -3149 -> 2383
    //   5535: iconst_1
    //   5536: istore 14
    //   5538: iload 12
    //   5540: istore 13
    //   5542: iload 14
    //   5544: istore 12
    //   5546: goto -3215 -> 2331
    //   5549: goto -1444 -> 4105
    //   5552: iload 13
    //   5554: istore 12
    //   5556: iload 14
    //   5558: istore 13
    //   5560: goto -3229 -> 2331
    //   5563: goto -3271 -> 2292
    // Local variable table:
    //   start	length	slot	name	signature
    //   0	5566	0	paramz	z
    //   79	5385	1	i	int
    //   163	5330	2	j	int
    //   52	4763	3	k	int
    //   76	4754	4	m	int
    //   286	5176	5	n	int
    //   2044	2442	6	i1	int
    //   40	129	7	i2	int
    //   49	114	8	i3	int
    //   69	56	9	i4	int
    //   2723	908	10	i5	int
    //   2766	13	11	i6	int
    //   146	5409	12	bool1	boolean
    //   58	5501	13	bool2	boolean
    //   2321	3236	14	bool3	boolean
    //   95	4946	15	l1	long
    //   1868	1276	17	l2	long
    //   373	4544	19	localObject1	Object
    //   5102	1	19	localThrowable1	Throwable
    //   5136	10	19	localObject2	Object
    //   5151	48	19	localObject3	Object
    //   5212	1	19	localThrowable2	Throwable
    //   5220	25	19	localObject4	Object
    //   5249	1	19	localThrowable3	Throwable
    //   5263	1	19	localObject5	Object
    //   5268	1	19	localThrowable4	Throwable
    //   5272	1	19	localObject6	Object
    //   5281	1	19	localThrowable5	Throwable
    //   5287	209	19	localObject7	Object
    //   5509	1	19	localThrowable6	Throwable
    //   5514	1	19	localThrowable7	Throwable
    //   5519	1	19	localThrowable8	Throwable
    //   5524	1	19	localThrowable9	Throwable
    //   73	3144	20	localObject8	Object
    //   3566	22	20	localException1	Exception
    //   3593	8	20	localObject9	Object
    //   3952	1	20	localThrowable10	Throwable
    //   3956	1075	20	localObject10	Object
    //   5087	1	20	localException2	Exception
    //   5092	1	20	localException3	Exception
    //   5097	1	20	localException4	Exception
    //   5114	103	20	localObject11	Object
    //   5229	1	20	localThrowable11	Throwable
    //   5233	59	20	localObject12	Object
    //   5301	15	20	localException5	Exception
    //   5321	29	20	localObject13	Object
    //   5354	25	20	localException6	Exception
    //   5384	1	20	localObject14	Object
    //   5389	24	20	localException7	Exception
    //   5418	82	20	localObject15	Object
    //   5504	1	20	localThrowable12	Throwable
    //   388	794	21	localObject16	Object
    //   1323	1	21	localThrowable13	Throwable
    //   1327	3561	21	localObject17	Object
    //   5156	7	21	localObject18	Object
    //   5168	35	21	localObject19	Object
    //   5207	55	21	localThrowable14	Throwable
    //   5305	132	21	localObject20	Object
    //   5449	9	21	localException8	Exception
    //   5469	18	21	localObject21	Object
    //   55	540	22	localObject22	Object
    //   614	690	22	localException9	Exception
    //   1335	3830	22	localObject23	Object
    //   5177	1	22	localObject24	Object
    //   5190	25	22	localObject25	Object
    //   5224	36	22	localObject26	Object
    //   5296	12	22	localThrowable15	Throwable
    //   5317	157	22	localObject27	Object
    //   5482	1	22	localException10	Exception
    //   7	5078	23	localaa	aa
    //   209	2546	24	localObject28	Object
    //   2784	757	24	localOutOfMemoryError1	OutOfMemoryError
    //   3577	15	24	localObject29	Object
    //   3598	1	24	localOutOfMemoryError2	OutOfMemoryError
    //   3983	790	24	localObject30	Object
    //   5107	10	24	localObject31	Object
    //   5123	7	24	localObject32	Object
    //   5143	177	24	localObject33	Object
    //   5326	18	24	localException11	Exception
    //   5361	56	24	localObject34	Object
    //   5423	16	24	localException12	Exception
    //   5465	33	24	localObject35	Object
    //   143	5300	25	localObject36	Object
    //   140	4334	26	localObject37	Object
    //   4762	461	26	localObject38	Object
    //   384	4835	27	localObject39	Object
    //   1828	3484	28	localObject40	Object
    //   113	4963	29	localac	ac
    //   17	115	30	localab	ab
    //   24	241	31	localList	java.util.List
    //   31	87	32	str	String
    //   517	3512	33	localObject41	Object
    // Exception table:
    //   from	to	target	type
    //   461	549	614	java/lang/Exception
    //   554	568	614	java/lang/Exception
    //   568	611	614	java/lang/Exception
    //   1186	1206	614	java/lang/Exception
    //   1206	1258	614	java/lang/Exception
    //   1263	1277	614	java/lang/Exception
    //   1277	1320	614	java/lang/Exception
    //   1637	1658	614	java/lang/Exception
    //   1658	1664	614	java/lang/Exception
    //   1669	1692	614	java/lang/Exception
    //   461	549	1323	java/lang/Throwable
    //   554	568	1323	java/lang/Throwable
    //   568	611	1323	java/lang/Throwable
    //   1186	1206	1323	java/lang/Throwable
    //   1206	1258	1323	java/lang/Throwable
    //   1263	1277	1323	java/lang/Throwable
    //   1277	1320	1323	java/lang/Throwable
    //   1637	1658	1323	java/lang/Throwable
    //   1658	1664	1323	java/lang/Throwable
    //   1669	1692	1323	java/lang/Throwable
    //   1692	1723	1323	java/lang/Throwable
    //   1730	1736	1323	java/lang/Throwable
    //   1741	1804	1323	java/lang/Throwable
    //   2626	2632	1323	java/lang/Throwable
    //   2642	2647	1323	java/lang/Throwable
    //   2728	2734	2784	java/lang/OutOfMemoryError
    //   2706	2713	3566	java/lang/Exception
    //   2719	2725	3566	java/lang/Exception
    //   2728	2734	3566	java/lang/Exception
    //   2737	2742	3566	java/lang/Exception
    //   2752	2768	3566	java/lang/Exception
    //   2794	2801	3566	java/lang/Exception
    //   2804	2827	3566	java/lang/Exception
    //   2830	2838	3566	java/lang/Exception
    //   3138	3150	3566	java/lang/Exception
    //   3153	3163	3566	java/lang/Exception
    //   3166	3174	3566	java/lang/Exception
    //   3184	3207	3566	java/lang/Exception
    //   3210	3216	3566	java/lang/Exception
    //   3224	3232	3566	java/lang/Exception
    //   3235	3241	3566	java/lang/Exception
    //   3528	3537	3566	java/lang/Exception
    //   3540	3554	3566	java/lang/Exception
    //   3557	3563	3566	java/lang/Exception
    //   3608	3615	3566	java/lang/Exception
    //   3618	3641	3566	java/lang/Exception
    //   3937	3940	3566	java/lang/Exception
    //   3943	3949	3566	java/lang/Exception
    //   3528	3537	3598	java/lang/OutOfMemoryError
    //   2706	2713	3952	java/lang/Throwable
    //   2719	2725	3952	java/lang/Throwable
    //   2728	2734	3952	java/lang/Throwable
    //   2737	2742	3952	java/lang/Throwable
    //   2752	2768	3952	java/lang/Throwable
    //   2786	2791	3952	java/lang/Throwable
    //   2794	2801	3952	java/lang/Throwable
    //   2804	2827	3952	java/lang/Throwable
    //   2830	2838	3952	java/lang/Throwable
    //   3138	3150	3952	java/lang/Throwable
    //   3153	3163	3952	java/lang/Throwable
    //   3166	3174	3952	java/lang/Throwable
    //   3184	3207	3952	java/lang/Throwable
    //   3210	3216	3952	java/lang/Throwable
    //   3216	3221	3952	java/lang/Throwable
    //   3224	3232	3952	java/lang/Throwable
    //   3235	3241	3952	java/lang/Throwable
    //   3528	3537	3952	java/lang/Throwable
    //   3540	3554	3952	java/lang/Throwable
    //   3557	3563	3952	java/lang/Throwable
    //   3600	3605	3952	java/lang/Throwable
    //   3608	3615	3952	java/lang/Throwable
    //   3618	3641	3952	java/lang/Throwable
    //   3937	3940	3952	java/lang/Throwable
    //   3943	3949	3952	java/lang/Throwable
    //   1830	1842	4762	finally
    //   1865	1870	4762	finally
    //   1893	1902	4762	finally
    //   1925	1937	4762	finally
    //   1964	1983	4762	finally
    //   2006	2009	4762	finally
    //   2032	2046	4762	finally
    //   2069	2076	4762	finally
    //   2112	2125	4762	finally
    //   2148	2165	4762	finally
    //   2188	2198	4762	finally
    //   2312	2319	4762	finally
    //   2682	2696	4762	finally
    //   4001	4008	4762	finally
    //   4028	4040	4762	finally
    //   4065	4074	4762	finally
    //   4098	4101	4762	finally
    //   4483	4490	4762	finally
    //   2786	2791	5087	java/lang/Exception
    //   3600	3605	5092	java/lang/Exception
    //   3216	3221	5097	java/lang/Exception
    //   4974	5010	5102	java/lang/Throwable
    //   2706	2713	5107	finally
    //   2719	2725	5107	finally
    //   2728	2734	5107	finally
    //   2737	2742	5107	finally
    //   2752	2768	5107	finally
    //   2786	2791	5107	finally
    //   2794	2801	5107	finally
    //   2804	2827	5107	finally
    //   2830	2838	5107	finally
    //   3138	3150	5107	finally
    //   3153	3163	5107	finally
    //   3166	3174	5107	finally
    //   3184	3207	5107	finally
    //   3210	3216	5107	finally
    //   3216	3221	5107	finally
    //   3224	3232	5107	finally
    //   3235	3241	5107	finally
    //   3528	3537	5107	finally
    //   3540	3554	5107	finally
    //   3557	3563	5107	finally
    //   3600	3605	5107	finally
    //   3608	3615	5107	finally
    //   3618	3641	5107	finally
    //   3937	3940	5107	finally
    //   3943	3949	5107	finally
    //   4105	4118	5123	finally
    //   4147	4164	5123	finally
    //   4123	4130	5136	finally
    //   172	198	5156	finally
    //   198	283	5156	finally
    //   290	296	5156	finally
    //   301	309	5156	finally
    //   314	321	5156	finally
    //   326	335	5156	finally
    //   340	375	5156	finally
    //   380	386	5156	finally
    //   395	403	5156	finally
    //   408	418	5156	finally
    //   423	445	5156	finally
    //   450	457	5156	finally
    //   1017	1039	5156	finally
    //   1047	1056	5156	finally
    //   1061	1096	5156	finally
    //   1104	1126	5156	finally
    //   1134	1161	5156	finally
    //   1169	1176	5156	finally
    //   461	549	5177	finally
    //   554	568	5177	finally
    //   568	611	5177	finally
    //   1186	1206	5177	finally
    //   1206	1258	5177	finally
    //   1263	1277	5177	finally
    //   1277	1320	5177	finally
    //   1637	1658	5177	finally
    //   1658	1664	5177	finally
    //   1669	1692	5177	finally
    //   1692	1723	5177	finally
    //   1730	1736	5177	finally
    //   1741	1804	5177	finally
    //   2626	2632	5177	finally
    //   2642	2647	5177	finally
    //   633	696	5190	finally
    //   699	726	5190	finally
    //   4541	4549	5190	finally
    //   4555	4563	5190	finally
    //   4569	4577	5190	finally
    //   4583	4591	5190	finally
    //   4597	4605	5190	finally
    //   4611	4619	5190	finally
    //   4625	4632	5190	finally
    //   1526	1562	5207	java/lang/Throwable
    //   1830	1842	5212	java/lang/Throwable
    //   1865	1870	5212	java/lang/Throwable
    //   1893	1902	5212	java/lang/Throwable
    //   1925	1937	5212	java/lang/Throwable
    //   1964	1983	5212	java/lang/Throwable
    //   2006	2009	5212	java/lang/Throwable
    //   2032	2046	5212	java/lang/Throwable
    //   2069	2076	5212	java/lang/Throwable
    //   2112	2125	5212	java/lang/Throwable
    //   2148	2165	5212	java/lang/Throwable
    //   2188	2198	5212	java/lang/Throwable
    //   2312	2319	5212	java/lang/Throwable
    //   2682	2696	5212	java/lang/Throwable
    //   4001	4008	5212	java/lang/Throwable
    //   4028	4040	5212	java/lang/Throwable
    //   4065	4074	5212	java/lang/Throwable
    //   4098	4101	5212	java/lang/Throwable
    //   4483	4490	5212	java/lang/Throwable
    //   4105	4118	5229	java/lang/Throwable
    //   4147	4164	5229	java/lang/Throwable
    //   4123	4130	5249	java/lang/Throwable
    //   172	198	5268	java/lang/Throwable
    //   198	283	5268	java/lang/Throwable
    //   290	296	5281	java/lang/Throwable
    //   301	309	5281	java/lang/Throwable
    //   314	321	5281	java/lang/Throwable
    //   326	335	5281	java/lang/Throwable
    //   340	375	5281	java/lang/Throwable
    //   380	386	5281	java/lang/Throwable
    //   395	403	5281	java/lang/Throwable
    //   408	418	5281	java/lang/Throwable
    //   423	445	5281	java/lang/Throwable
    //   450	457	5281	java/lang/Throwable
    //   1017	1039	5281	java/lang/Throwable
    //   1047	1056	5281	java/lang/Throwable
    //   1061	1096	5281	java/lang/Throwable
    //   1104	1126	5281	java/lang/Throwable
    //   1134	1161	5281	java/lang/Throwable
    //   1169	1176	5281	java/lang/Throwable
    //   911	947	5296	java/lang/Throwable
    //   1830	1842	5301	java/lang/Exception
    //   1865	1870	5301	java/lang/Exception
    //   1893	1902	5301	java/lang/Exception
    //   1925	1937	5301	java/lang/Exception
    //   1964	1983	5301	java/lang/Exception
    //   2006	2009	5301	java/lang/Exception
    //   2032	2046	5301	java/lang/Exception
    //   2069	2076	5301	java/lang/Exception
    //   2112	2125	5301	java/lang/Exception
    //   2148	2165	5301	java/lang/Exception
    //   2188	2198	5301	java/lang/Exception
    //   2312	2319	5301	java/lang/Exception
    //   2682	2696	5301	java/lang/Exception
    //   4001	4008	5301	java/lang/Exception
    //   4483	4490	5301	java/lang/Exception
    //   4028	4040	5326	java/lang/Exception
    //   4065	4074	5326	java/lang/Exception
    //   4098	4101	5326	java/lang/Exception
    //   4105	4118	5354	java/lang/Exception
    //   4147	4164	5354	java/lang/Exception
    //   4123	4130	5389	java/lang/Exception
    //   172	198	5423	java/lang/Exception
    //   198	283	5423	java/lang/Exception
    //   290	296	5449	java/lang/Exception
    //   301	309	5449	java/lang/Exception
    //   314	321	5449	java/lang/Exception
    //   326	335	5449	java/lang/Exception
    //   340	375	5449	java/lang/Exception
    //   380	386	5449	java/lang/Exception
    //   395	403	5449	java/lang/Exception
    //   408	418	5449	java/lang/Exception
    //   423	445	5449	java/lang/Exception
    //   450	457	5449	java/lang/Exception
    //   1017	1039	5449	java/lang/Exception
    //   1047	1056	5449	java/lang/Exception
    //   1061	1096	5449	java/lang/Exception
    //   1104	1126	5449	java/lang/Exception
    //   1134	1161	5449	java/lang/Exception
    //   1169	1176	5449	java/lang/Exception
    //   1692	1723	5482	java/lang/Exception
    //   1730	1736	5482	java/lang/Exception
    //   1741	1804	5482	java/lang/Exception
    //   2626	2632	5482	java/lang/Exception
    //   2642	2647	5482	java/lang/Exception
    //   2515	2551	5504	java/lang/Throwable
    //   4358	4394	5509	java/lang/Throwable
    //   3429	3465	5514	java/lang/Throwable
    //   3829	3865	5519	java/lang/Throwable
    //   3026	3062	5524	java/lang/Throwable
  }
}

/* Location:
 * Qualified Name:     ct.x
 * Java Class Version: 6 (50.0)
 * JD-Core Version:    0.7.1
 */