package com.tencent.smtt.sdk.a;

import MTT.ThirdAppInfoNew;

final class b$1
  extends Thread
{
  b$1(String paramString, ThirdAppInfoNew paramThirdAppInfoNew)
  {
    super(paramString);
  }
  
  /* Error */
  public final void run()
  {
    // Byte code:
    //   0: aconst_null
    //   1: astore_1
    //   2: getstatic 36	android/os/Build$VERSION:SDK_INT	I
    //   5: bipush 8
    //   7: if_icmpge +4 -> 11
    //   10: return
    //   11: getstatic 40	com/tencent/smtt/sdk/a/b:mwr	[B
    //   14: ifnonnull +13 -> 27
    //   17: ldc 42
    //   19: ldc 44
    //   21: invokevirtual 50	java/lang/String:getBytes	(Ljava/lang/String;)[B
    //   24: putstatic 40	com/tencent/smtt/sdk/a/b:mwr	[B
    //   27: getstatic 40	com/tencent/smtt/sdk/a/b:mwr	[B
    //   30: ifnonnull +26 -> 56
    //   33: ldc 52
    //   35: ldc 54
    //   37: invokestatic 60	com/tencent/smtt/utils/TbsLog:e	(Ljava/lang/String;Ljava/lang/String;)V
    //   40: return
    //   41: astore_2
    //   42: aconst_null
    //   43: putstatic 40	com/tencent/smtt/sdk/a/b:mwr	[B
    //   46: ldc 52
    //   48: ldc 62
    //   50: invokestatic 60	com/tencent/smtt/utils/TbsLog:e	(Ljava/lang/String;Ljava/lang/String;)V
    //   53: goto -26 -> 27
    //   56: invokestatic 68	com/tencent/smtt/utils/p:bsx	()Lcom/tencent/smtt/utils/p;
    //   59: getfield 72	com/tencent/smtt/utils/p:mxl	Ljava/lang/String;
    //   62: astore_2
    //   63: invokestatic 78	com/tencent/smtt/utils/i:bsp	()Lcom/tencent/smtt/utils/i;
    //   66: pop
    //   67: invokestatic 82	com/tencent/smtt/utils/i:bsq	()Ljava/lang/String;
    //   70: astore_3
    //   71: new 84	java/net/URL
    //   74: dup
    //   75: new 86	java/lang/StringBuilder
    //   78: dup
    //   79: invokespecial 88	java/lang/StringBuilder:<init>	()V
    //   82: aload_2
    //   83: invokevirtual 92	java/lang/StringBuilder:append	(Ljava/lang/String;)Ljava/lang/StringBuilder;
    //   86: aload_3
    //   87: invokevirtual 92	java/lang/StringBuilder:append	(Ljava/lang/String;)Ljava/lang/StringBuilder;
    //   90: invokevirtual 95	java/lang/StringBuilder:toString	()Ljava/lang/String;
    //   93: invokespecial 96	java/net/URL:<init>	(Ljava/lang/String;)V
    //   96: invokevirtual 100	java/net/URL:openConnection	()Ljava/net/URLConnection;
    //   99: checkcast 102	java/net/HttpURLConnection
    //   102: astore_3
    //   103: aload_3
    //   104: ldc 104
    //   106: invokevirtual 107	java/net/HttpURLConnection:setRequestMethod	(Ljava/lang/String;)V
    //   109: aload_3
    //   110: iconst_1
    //   111: invokevirtual 111	java/net/HttpURLConnection:setDoOutput	(Z)V
    //   114: aload_3
    //   115: iconst_1
    //   116: invokevirtual 114	java/net/HttpURLConnection:setDoInput	(Z)V
    //   119: aload_3
    //   120: iconst_0
    //   121: invokevirtual 117	java/net/HttpURLConnection:setUseCaches	(Z)V
    //   124: aload_3
    //   125: sipush 20000
    //   128: invokevirtual 121	java/net/HttpURLConnection:setConnectTimeout	(I)V
    //   131: getstatic 36	android/os/Build$VERSION:SDK_INT	I
    //   134: bipush 13
    //   136: if_icmple +11 -> 147
    //   139: aload_3
    //   140: ldc 123
    //   142: ldc 125
    //   144: invokevirtual 128	java/net/HttpURLConnection:setRequestProperty	(Ljava/lang/String;Ljava/lang/String;)V
    //   147: aload_0
    //   148: getfield 12	com/tencent/smtt/sdk/a/b$1:mws	LMTT/ThirdAppInfoNew;
    //   151: invokestatic 132	com/tencent/smtt/sdk/a/b:b	(LMTT/ThirdAppInfoNew;)Lorg/json/JSONObject;
    //   154: astore_2
    //   155: aload_2
    //   156: astore_1
    //   157: aload_1
    //   158: ifnonnull +80 -> 238
    //   161: ldc 52
    //   163: ldc -122
    //   165: invokestatic 60	com/tencent/smtt/utils/TbsLog:e	(Ljava/lang/String;Ljava/lang/String;)V
    //   168: return
    //   169: astore_1
    //   170: ldc 52
    //   172: new 86	java/lang/StringBuilder
    //   175: dup
    //   176: ldc -120
    //   178: invokespecial 137	java/lang/StringBuilder:<init>	(Ljava/lang/String;)V
    //   181: aload_1
    //   182: invokevirtual 140	java/lang/StringBuilder:append	(Ljava/lang/Object;)Ljava/lang/StringBuilder;
    //   185: invokevirtual 95	java/lang/StringBuilder:toString	()Ljava/lang/String;
    //   188: invokestatic 60	com/tencent/smtt/utils/TbsLog:e	(Ljava/lang/String;Ljava/lang/String;)V
    //   191: return
    //   192: astore_1
    //   193: ldc 52
    //   195: new 86	java/lang/StringBuilder
    //   198: dup
    //   199: ldc -114
    //   201: invokespecial 137	java/lang/StringBuilder:<init>	(Ljava/lang/String;)V
    //   204: aload_1
    //   205: invokevirtual 140	java/lang/StringBuilder:append	(Ljava/lang/Object;)Ljava/lang/StringBuilder;
    //   208: invokevirtual 95	java/lang/StringBuilder:toString	()Ljava/lang/String;
    //   211: invokestatic 60	com/tencent/smtt/utils/TbsLog:e	(Ljava/lang/String;Ljava/lang/String;)V
    //   214: return
    //   215: astore_1
    //   216: ldc 52
    //   218: new 86	java/lang/StringBuilder
    //   221: dup
    //   222: ldc -112
    //   224: invokespecial 137	java/lang/StringBuilder:<init>	(Ljava/lang/String;)V
    //   227: aload_1
    //   228: invokevirtual 140	java/lang/StringBuilder:append	(Ljava/lang/Object;)Ljava/lang/StringBuilder;
    //   231: invokevirtual 95	java/lang/StringBuilder:toString	()Ljava/lang/String;
    //   234: invokestatic 60	com/tencent/smtt/utils/TbsLog:e	(Ljava/lang/String;Ljava/lang/String;)V
    //   237: return
    //   238: aload_1
    //   239: invokevirtual 147	org/json/JSONObject:toString	()Ljava/lang/String;
    //   242: ldc 44
    //   244: invokevirtual 50	java/lang/String:getBytes	(Ljava/lang/String;)[B
    //   247: astore_1
    //   248: invokestatic 78	com/tencent/smtt/utils/i:bsp	()Lcom/tencent/smtt/utils/i;
    //   251: aload_1
    //   252: invokevirtual 151	com/tencent/smtt/utils/i:bn	([B)[B
    //   255: astore_1
    //   256: aload_3
    //   257: ldc -103
    //   259: ldc -101
    //   261: invokevirtual 128	java/net/HttpURLConnection:setRequestProperty	(Ljava/lang/String;Ljava/lang/String;)V
    //   264: aload_3
    //   265: ldc -99
    //   267: aload_1
    //   268: arraylength
    //   269: invokestatic 161	java/lang/String:valueOf	(I)Ljava/lang/String;
    //   272: invokevirtual 128	java/net/HttpURLConnection:setRequestProperty	(Ljava/lang/String;Ljava/lang/String;)V
    //   275: aload_3
    //   276: invokevirtual 165	java/net/HttpURLConnection:getOutputStream	()Ljava/io/OutputStream;
    //   279: astore_2
    //   280: aload_2
    //   281: aload_1
    //   282: invokevirtual 171	java/io/OutputStream:write	([B)V
    //   285: aload_2
    //   286: invokevirtual 174	java/io/OutputStream:flush	()V
    //   289: aload_3
    //   290: invokevirtual 178	java/net/HttpURLConnection:getResponseCode	()I
    //   293: sipush 200
    //   296: if_icmpeq -286 -> 10
    //   299: ldc 52
    //   301: ldc -76
    //   303: invokestatic 60	com/tencent/smtt/utils/TbsLog:e	(Ljava/lang/String;Ljava/lang/String;)V
    //   306: return
    //   307: astore_1
    //   308: ldc 52
    //   310: new 86	java/lang/StringBuilder
    //   313: dup
    //   314: ldc -74
    //   316: invokespecial 137	java/lang/StringBuilder:<init>	(Ljava/lang/String;)V
    //   319: aload_1
    //   320: invokevirtual 185	java/lang/Throwable:getMessage	()Ljava/lang/String;
    //   323: invokevirtual 92	java/lang/StringBuilder:append	(Ljava/lang/String;)Ljava/lang/StringBuilder;
    //   326: invokevirtual 95	java/lang/StringBuilder:toString	()Ljava/lang/String;
    //   329: invokestatic 60	com/tencent/smtt/utils/TbsLog:e	(Ljava/lang/String;Ljava/lang/String;)V
    //   332: return
    //   333: astore_1
    //   334: return
    //   335: astore_2
    //   336: goto -179 -> 157
    // Local variable table:
    //   start	length	slot	name	signature
    //   0	339	0	this	1
    //   1	157	1	localObject1	Object
    //   169	13	1	localIOException	java.io.IOException
    //   192	13	1	localAssertionError	AssertionError
    //   215	24	1	localNoClassDefFoundError	NoClassDefFoundError
    //   247	35	1	arrayOfByte	byte[]
    //   307	13	1	localThrowable1	Throwable
    //   333	1	1	localThrowable2	Throwable
    //   41	1	2	localUnsupportedEncodingException	java.io.UnsupportedEncodingException
    //   62	224	2	localObject2	Object
    //   335	1	2	localException	Exception
    //   70	220	3	localObject3	Object
    // Exception table:
    //   from	to	target	type
    //   17	27	41	java/io/UnsupportedEncodingException
    //   56	109	169	java/io/IOException
    //   56	109	192	java/lang/AssertionError
    //   56	109	215	java/lang/NoClassDefFoundError
    //   275	306	307	java/lang/Throwable
    //   238	256	333	java/lang/Throwable
    //   147	155	335	java/lang/Exception
  }
}

/* Location:
 * Qualified Name:     com.tencent.smtt.sdk.a.b.1
 * Java Class Version: 6 (50.0)
 * JD-Core Version:    0.7.1
 */