package com.tencent.mm.model;

import com.tencent.mm.r.c;
import com.tencent.mm.r.c.a;
import com.tencent.mm.sdk.platformtools.ay;
import com.tencent.mm.sdk.platformtools.u;
import com.tencent.mm.storage.ag;
import java.util.HashMap;
import java.util.Iterator;
import java.util.LinkedList;
import java.util.List;
import java.util.Map;

public final class bd
  implements c
{
  private long bCT = -1L;
  public a bCU;
  private Map bCV = new HashMap();
  private Map bCW = new HashMap();
  
  private void a(String paramString, c.a parama, boolean paramBoolean)
  {
    Map localMap;
    if (paramBoolean)
    {
      localMap = bCW;
      paramString = (List)localMap.get(paramString);
      if ((paramString != null) && (!paramString.isEmpty())) {
        break label52;
      }
      u.w("!44@/B4Tb64lLpLqQYyN0INswY/XO4icKaZhr30o48Gx2tE=", "listener list is empty, return now");
    }
    for (;;)
    {
      return;
      localMap = bCV;
      break;
      label52:
      u.i("!44@/B4Tb64lLpLqQYyN0INswY/XO4icKaZhr30o48Gx2tE=", "listener list size is %d", new Object[] { Integer.valueOf(paramString.size()) });
      paramString = paramString.iterator();
      while (paramString.hasNext()) {
        ((b)paramString.next()).a(parama);
      }
    }
  }
  
  public final void a(String paramString, b paramb, boolean paramBoolean)
  {
    if ((ay.kz(paramString)) || (paramb == null)) {
      return;
    }
    if (paramBoolean) {}
    for (Map localMap = bCW;; localMap = bCV)
    {
      List localList = (List)localMap.get(paramString);
      Object localObject = localList;
      if (localList == null)
      {
        localObject = new LinkedList();
        localMap.put(paramString, localObject);
      }
      if (((List)localObject).contains(paramb)) {
        break;
      }
      ((List)localObject).add(paramb);
      return;
    }
  }
  
  /* Error */
  public final com.tencent.mm.r.c.b b(c.a parama)
  {
    // Byte code:
    //   0: aload_1
    //   1: getfield 122	com/tencent/mm/r/c$a:bFh	Lcom/tencent/mm/protocal/b/aj;
    //   4: astore 16
    //   6: aload 16
    //   8: getfield 128	com/tencent/mm/protocal/b/aj:iXu	I
    //   11: tableswitch	default:+21->32, 10001:+45->56, 10002:+91->102
    //   32: ldc 52
    //   34: ldc -126
    //   36: iconst_1
    //   37: anewarray 4	java/lang/Object
    //   40: dup
    //   41: iconst_0
    //   42: aload 16
    //   44: getfield 128	com/tencent/mm/protocal/b/aj:iXu	I
    //   47: invokestatic 72	java/lang/Integer:valueOf	(I)Ljava/lang/Integer;
    //   50: aastore
    //   51: invokestatic 132	com/tencent/mm/sdk/platformtools/u:w	(Ljava/lang/String;Ljava/lang/String;[Ljava/lang/Object;)V
    //   54: aconst_null
    //   55: areturn
    //   56: aload 16
    //   58: getfield 136	com/tencent/mm/protocal/b/aj:iXs	Lcom/tencent/mm/protocal/b/aly;
    //   61: invokestatic 141	com/tencent/mm/platformtools/n:a	(Lcom/tencent/mm/protocal/b/aly;)Ljava/lang/String;
    //   64: astore 11
    //   66: aload 16
    //   68: getfield 144	com/tencent/mm/protocal/b/aj:iXv	Lcom/tencent/mm/protocal/b/aly;
    //   71: invokestatic 141	com/tencent/mm/platformtools/n:a	(Lcom/tencent/mm/protocal/b/aly;)Ljava/lang/String;
    //   74: pop
    //   75: aload_0
    //   76: aload 11
    //   78: aload_1
    //   79: iconst_0
    //   80: invokespecial 146	com/tencent/mm/model/bd:a	(Ljava/lang/String;Lcom/tencent/mm/r/c$a;Z)V
    //   83: getstatic 152	com/tencent/mm/plugin/report/service/h:fUJ	Lcom/tencent/mm/plugin/report/service/h;
    //   86: sipush 10395
    //   89: aload 16
    //   91: getfield 155	com/tencent/mm/protocal/b/aj:iXA	J
    //   94: invokestatic 160	java/lang/String:valueOf	(J)Ljava/lang/String;
    //   97: invokevirtual 164	com/tencent/mm/plugin/report/service/h:O	(ILjava/lang/String;)V
    //   100: aconst_null
    //   101: areturn
    //   102: aload 16
    //   104: getfield 144	com/tencent/mm/protocal/b/aj:iXv	Lcom/tencent/mm/protocal/b/aly;
    //   107: invokestatic 141	com/tencent/mm/platformtools/n:a	(Lcom/tencent/mm/protocal/b/aly;)Ljava/lang/String;
    //   110: astore 15
    //   112: aload 15
    //   114: invokestatic 99	com/tencent/mm/sdk/platformtools/ay:kz	(Ljava/lang/String;)Z
    //   117: ifeq +12 -> 129
    //   120: ldc 52
    //   122: ldc -90
    //   124: invokestatic 169	com/tencent/mm/sdk/platformtools/u:e	(Ljava/lang/String;Ljava/lang/String;)V
    //   127: aconst_null
    //   128: areturn
    //   129: aload 15
    //   131: ldc -85
    //   133: invokevirtual 174	java/lang/String:startsWith	(Ljava/lang/String;)Z
    //   136: ifeq +1135 -> 1271
    //   139: aload 15
    //   141: invokestatic 180	com/tencent/mm/sdk/platformtools/ap:CY	(Ljava/lang/String;)Ljava/util/Map;
    //   144: astore 13
    //   146: aload 13
    //   148: ifnonnull +21 -> 169
    //   151: ldc 52
    //   153: ldc -74
    //   155: iconst_1
    //   156: anewarray 4	java/lang/Object
    //   159: dup
    //   160: iconst_0
    //   161: aload 15
    //   163: aastore
    //   164: invokestatic 184	com/tencent/mm/sdk/platformtools/u:e	(Ljava/lang/String;Ljava/lang/String;[Ljava/lang/Object;)V
    //   167: aconst_null
    //   168: areturn
    //   169: ldc -70
    //   171: astore 14
    //   173: ldc 52
    //   175: ldc -68
    //   177: iconst_2
    //   178: anewarray 4	java/lang/Object
    //   181: dup
    //   182: iconst_0
    //   183: aload 15
    //   185: aastore
    //   186: dup
    //   187: iconst_1
    //   188: aload 14
    //   190: aastore
    //   191: invokestatic 191	com/tencent/mm/sdk/platformtools/u:d	(Ljava/lang/String;Ljava/lang/String;[Ljava/lang/Object;)V
    //   194: aload 14
    //   196: ifnull +11 -> 207
    //   199: aload_0
    //   200: aload 14
    //   202: aload_1
    //   203: iconst_1
    //   204: invokespecial 146	com/tencent/mm/model/bd:a	(Ljava/lang/String;Lcom/tencent/mm/r/c$a;Z)V
    //   207: aconst_null
    //   208: astore 12
    //   210: aload 12
    //   212: astore 11
    //   214: aload 14
    //   216: ifnull +54 -> 270
    //   219: aload 12
    //   221: astore 11
    //   223: aload 14
    //   225: ldc -63
    //   227: invokevirtual 196	java/lang/String:equals	(Ljava/lang/Object;)Z
    //   230: ifeq +40 -> 270
    //   233: aload 16
    //   235: aload 13
    //   237: ldc -58
    //   239: invokeinterface 44 2 0
    //   244: checkcast 157	java/lang/String
    //   247: invokestatic 202	com/tencent/mm/platformtools/n:kw	(Ljava/lang/String;)Lcom/tencent/mm/protocal/b/aly;
    //   250: putfield 144	com/tencent/mm/protocal/b/aj:iXv	Lcom/tencent/mm/protocal/b/aly;
    //   253: iconst_1
    //   254: invokestatic 72	java/lang/Integer:valueOf	(I)Ljava/lang/Integer;
    //   257: invokestatic 208	com/tencent/mm/r/c$c:X	(Ljava/lang/Object;)Lcom/tencent/mm/r/c;
    //   260: astore 11
    //   262: aload 11
    //   264: ifnonnull +1088 -> 1352
    //   267: aconst_null
    //   268: astore 11
    //   270: aload 14
    //   272: ifnull +83 -> 355
    //   275: aload 14
    //   277: ldc -46
    //   279: invokevirtual 196	java/lang/String:equals	(Ljava/lang/Object;)Z
    //   282: ifeq +73 -> 355
    //   285: invokestatic 216	com/tencent/mm/g/h:pS	()Lcom/tencent/mm/g/e;
    //   288: aload 15
    //   290: aload 13
    //   292: iconst_0
    //   293: invokevirtual 221	com/tencent/mm/g/e:a	(Ljava/lang/String;Ljava/util/Map;Z)V
    //   296: invokestatic 225	com/tencent/mm/g/h:pT	()Lcom/tencent/mm/g/c;
    //   299: pop
    //   300: invokestatic 230	com/tencent/mm/g/c:pz	()I
    //   303: iconst_2
    //   304: if_icmpne +14 -> 318
    //   307: getstatic 152	com/tencent/mm/plugin/report/service/h:fUJ	Lcom/tencent/mm/plugin/report/service/h;
    //   310: sipush 10879
    //   313: ldc -24
    //   315: invokevirtual 164	com/tencent/mm/plugin/report/service/h:O	(ILjava/lang/String;)V
    //   318: invokestatic 216	com/tencent/mm/g/h:pS	()Lcom/tencent/mm/g/e;
    //   321: ldc -22
    //   323: invokevirtual 238	com/tencent/mm/g/e:getValue	(Ljava/lang/String;)Ljava/lang/String;
    //   326: iconst_0
    //   327: invokestatic 242	com/tencent/mm/sdk/platformtools/ay:getInt	(Ljava/lang/String;I)I
    //   330: istore_2
    //   331: ldc 52
    //   333: new 244	java/lang/StringBuilder
    //   336: dup
    //   337: ldc -10
    //   339: invokespecial 249	java/lang/StringBuilder:<init>	(Ljava/lang/String;)V
    //   342: iload_2
    //   343: invokestatic 253	java/lang/Integer:toString	(I)Ljava/lang/String;
    //   346: invokevirtual 257	java/lang/StringBuilder:append	(Ljava/lang/String;)Ljava/lang/StringBuilder;
    //   349: invokevirtual 260	java/lang/StringBuilder:toString	()Ljava/lang/String;
    //   352: invokestatic 262	com/tencent/mm/sdk/platformtools/u:d	(Ljava/lang/String;Ljava/lang/String;)V
    //   355: aload 14
    //   357: ifnull +25 -> 382
    //   360: aload 14
    //   362: ldc_w 264
    //   365: invokevirtual 196	java/lang/String:equals	(Ljava/lang/Object;)Z
    //   368: ifeq +14 -> 382
    //   371: invokestatic 216	com/tencent/mm/g/h:pS	()Lcom/tencent/mm/g/e;
    //   374: aload 15
    //   376: aload 13
    //   378: iconst_1
    //   379: invokevirtual 221	com/tencent/mm/g/e:a	(Ljava/lang/String;Ljava/util/Map;Z)V
    //   382: aload 14
    //   384: ifnull +254 -> 638
    //   387: aload 14
    //   389: ldc_w 266
    //   392: invokevirtual 196	java/lang/String:equals	(Ljava/lang/Object;)Z
    //   395: ifeq +243 -> 638
    //   398: aload 13
    //   400: ldc_w 268
    //   403: invokeinterface 44 2 0
    //   408: checkcast 157	java/lang/String
    //   411: astore 12
    //   413: aload 13
    //   415: ldc_w 270
    //   418: invokeinterface 44 2 0
    //   423: checkcast 157	java/lang/String
    //   426: astore 17
    //   428: aload 13
    //   430: ldc_w 272
    //   433: invokeinterface 44 2 0
    //   438: checkcast 157	java/lang/String
    //   441: astore 18
    //   443: aload 12
    //   445: ifnull +43 -> 488
    //   448: aload 12
    //   450: invokevirtual 275	java/lang/String:length	()I
    //   453: ifle +35 -> 488
    //   456: invokestatic 281	com/tencent/mm/model/aq:ua	()Lcom/tencent/mm/model/aq;
    //   459: new 283	com/tencent/mm/model/ap
    //   462: dup
    //   463: aload 12
    //   465: invokestatic 286	java/lang/Integer:valueOf	(Ljava/lang/String;)Ljava/lang/Integer;
    //   468: invokevirtual 289	java/lang/Integer:intValue	()I
    //   471: aload 17
    //   473: invokestatic 286	java/lang/Integer:valueOf	(Ljava/lang/String;)Ljava/lang/Integer;
    //   476: invokevirtual 289	java/lang/Integer:intValue	()I
    //   479: aload 18
    //   481: invokespecial 292	com/tencent/mm/model/ap:<init>	(IILjava/lang/String;)V
    //   484: invokevirtual 295	com/tencent/mm/model/aq:a	(Lcom/tencent/mm/model/ap;)Z
    //   487: pop
    //   488: aload 13
    //   490: ldc_w 297
    //   493: invokeinterface 44 2 0
    //   498: checkcast 157	java/lang/String
    //   501: astore 12
    //   503: aload 13
    //   505: ldc_w 299
    //   508: invokeinterface 44 2 0
    //   513: checkcast 157	java/lang/String
    //   516: astore 17
    //   518: aload 12
    //   520: ifnull +21 -> 541
    //   523: aload 17
    //   525: ifnull +16 -> 541
    //   528: invokestatic 305	com/tencent/mm/model/ah:tD	()Lcom/tencent/mm/model/c;
    //   531: invokevirtual 311	com/tencent/mm/model/c:rT	()Lcom/tencent/mm/model/b/b;
    //   534: aload 17
    //   536: iconst_1
    //   537: aconst_null
    //   538: invokevirtual 316	com/tencent/mm/model/b/b:a	(Ljava/lang/String;Z[Ljava/lang/String;)V
    //   541: aload 13
    //   543: ldc_w 318
    //   546: invokeinterface 44 2 0
    //   551: checkcast 157	java/lang/String
    //   554: astore 12
    //   556: aload 13
    //   558: ldc_w 320
    //   561: invokeinterface 44 2 0
    //   566: checkcast 157	java/lang/String
    //   569: astore 17
    //   571: aload 13
    //   573: ldc_w 322
    //   576: invokeinterface 44 2 0
    //   581: checkcast 157	java/lang/String
    //   584: astore 18
    //   586: aload 12
    //   588: invokestatic 99	com/tencent/mm/sdk/platformtools/ay:kz	(Ljava/lang/String;)Z
    //   591: ifne +47 -> 638
    //   594: aload 18
    //   596: invokestatic 99	com/tencent/mm/sdk/platformtools/ay:kz	(Ljava/lang/String;)Z
    //   599: ifne +39 -> 638
    //   602: aload 18
    //   604: ldc_w 324
    //   607: invokevirtual 196	java/lang/String:equals	(Ljava/lang/Object;)Z
    //   610: ifeq +4723 -> 5333
    //   613: iconst_1
    //   614: istore 6
    //   616: invokestatic 305	com/tencent/mm/model/ah:tD	()Lcom/tencent/mm/model/c;
    //   619: invokevirtual 328	com/tencent/mm/model/c:rU	()Lcom/tencent/mm/model/b/c;
    //   622: aload 12
    //   624: iload 6
    //   626: iconst_1
    //   627: anewarray 157	java/lang/String
    //   630: dup
    //   631: iconst_0
    //   632: aload 17
    //   634: aastore
    //   635: invokevirtual 331	com/tencent/mm/model/b/c:a	(Ljava/lang/String;Z[Ljava/lang/String;)V
    //   638: aload 14
    //   640: invokestatic 99	com/tencent/mm/sdk/platformtools/ay:kz	(Ljava/lang/String;)Z
    //   643: ifne +130 -> 773
    //   646: aload 14
    //   648: ldc_w 333
    //   651: invokevirtual 196	java/lang/String:equals	(Ljava/lang/Object;)Z
    //   654: ifeq +119 -> 773
    //   657: aload 13
    //   659: ldc_w 335
    //   662: invokeinterface 44 2 0
    //   667: checkcast 157	java/lang/String
    //   670: astore 12
    //   672: aload 13
    //   674: ldc_w 337
    //   677: invokeinterface 44 2 0
    //   682: checkcast 157	java/lang/String
    //   685: astore 17
    //   687: ldc 52
    //   689: ldc_w 339
    //   692: iconst_3
    //   693: anewarray 4	java/lang/Object
    //   696: dup
    //   697: iconst_0
    //   698: aload 17
    //   700: aastore
    //   701: dup
    //   702: iconst_1
    //   703: aload 12
    //   705: aastore
    //   706: dup
    //   707: iconst_2
    //   708: aload 15
    //   710: aastore
    //   711: invokestatic 76	com/tencent/mm/sdk/platformtools/u:i	(Ljava/lang/String;Ljava/lang/String;[Ljava/lang/Object;)V
    //   714: aload 17
    //   716: iconst_0
    //   717: invokestatic 242	com/tencent/mm/sdk/platformtools/ay:getInt	(Ljava/lang/String;I)I
    //   720: istore_2
    //   721: iload_2
    //   722: i2l
    //   723: ldc2_w 340
    //   726: lcmp
    //   727: ifle +33 -> 760
    //   730: iload_2
    //   731: i2l
    //   732: ldc2_w 342
    //   735: lcmp
    //   736: ifge +24 -> 760
    //   739: invokestatic 305	com/tencent/mm/model/ah:tD	()Lcom/tencent/mm/model/c;
    //   742: invokevirtual 347	com/tencent/mm/model/c:rn	()Lcom/tencent/mm/storage/h;
    //   745: ldc_w 348
    //   748: invokestatic 352	com/tencent/mm/sdk/platformtools/ay:FR	()J
    //   751: iload_2
    //   752: i2l
    //   753: ladd
    //   754: invokestatic 357	java/lang/Long:valueOf	(J)Ljava/lang/Long;
    //   757: invokevirtual 363	com/tencent/mm/storage/h:set	(ILjava/lang/Object;)V
    //   760: aload 12
    //   762: invokestatic 99	com/tencent/mm/sdk/platformtools/ay:kz	(Ljava/lang/String;)Z
    //   765: ifne +8 -> 773
    //   768: aload 12
    //   770: invokestatic 368	com/tencent/mm/plugin/report/b/c:sI	(Ljava/lang/String;)V
    //   773: aload 14
    //   775: ifnull +894 -> 1669
    //   778: aload 14
    //   780: ldc_w 370
    //   783: invokevirtual 196	java/lang/String:equals	(Ljava/lang/Object;)Z
    //   786: ifeq +883 -> 1669
    //   789: ldc 52
    //   791: ldc_w 372
    //   794: invokestatic 374	com/tencent/mm/sdk/platformtools/u:i	(Ljava/lang/String;Ljava/lang/String;)V
    //   797: aload 13
    //   799: ldc_w 376
    //   802: invokeinterface 44 2 0
    //   807: checkcast 157	java/lang/String
    //   810: astore 12
    //   812: aload 13
    //   814: ldc_w 378
    //   817: invokeinterface 44 2 0
    //   822: checkcast 157	java/lang/String
    //   825: astore 14
    //   827: aload 13
    //   829: ldc_w 380
    //   832: invokeinterface 44 2 0
    //   837: checkcast 157	java/lang/String
    //   840: astore 11
    //   842: ldc 52
    //   844: ldc_w 382
    //   847: iconst_2
    //   848: anewarray 4	java/lang/Object
    //   851: dup
    //   852: iconst_0
    //   853: aload 14
    //   855: aastore
    //   856: dup
    //   857: iconst_1
    //   858: aload 11
    //   860: aastore
    //   861: invokestatic 76	com/tencent/mm/sdk/platformtools/u:i	(Ljava/lang/String;Ljava/lang/String;[Ljava/lang/Object;)V
    //   864: lconst_0
    //   865: lstore 7
    //   867: aload 14
    //   869: invokestatic 386	java/lang/Long:parseLong	(Ljava/lang/String;)J
    //   872: lstore 9
    //   874: lload 9
    //   876: lstore 7
    //   878: invokestatic 305	com/tencent/mm/model/ah:tD	()Lcom/tencent/mm/model/c;
    //   881: invokevirtual 390	com/tencent/mm/model/c:rs	()Lcom/tencent/mm/storage/ah;
    //   884: aload 12
    //   886: lload 9
    //   888: invokevirtual 396	com/tencent/mm/storage/ah:x	(Ljava/lang/String;J)Lcom/tencent/mm/storage/ag;
    //   891: astore 12
    //   893: lload 9
    //   895: lstore 7
    //   897: aload 12
    //   899: invokestatic 402	com/tencent/mm/storage/ag:B	(Lcom/tencent/mm/storage/ag;)Lcom/tencent/mm/storage/ag;
    //   902: astore 13
    //   904: lload 9
    //   906: lstore 7
    //   908: aload 12
    //   910: aload 11
    //   912: invokevirtual 405	com/tencent/mm/storage/ag:setContent	(Ljava/lang/String;)V
    //   915: lload 9
    //   917: lstore 7
    //   919: aload 12
    //   921: sipush 10000
    //   924: invokevirtual 409	com/tencent/mm/storage/ag:setType	(I)V
    //   927: lload 9
    //   929: lstore 7
    //   931: aload 12
    //   933: aload_1
    //   934: invokestatic 414	com/tencent/mm/model/ar:a	(Lcom/tencent/mm/storage/ag;Lcom/tencent/mm/r/c$a;)V
    //   937: lload 9
    //   939: lstore 7
    //   941: invokestatic 305	com/tencent/mm/model/ah:tD	()Lcom/tencent/mm/model/c;
    //   944: invokevirtual 390	com/tencent/mm/model/c:rs	()Lcom/tencent/mm/storage/ah;
    //   947: aload 12
    //   949: getfield 419	com/tencent/mm/d/b/bg:field_msgId	J
    //   952: aload 12
    //   954: invokevirtual 422	com/tencent/mm/storage/ah:a	(JLcom/tencent/mm/storage/ag;)V
    //   957: lload 9
    //   959: lstore 7
    //   961: invokestatic 305	com/tencent/mm/model/ah:tD	()Lcom/tencent/mm/model/c;
    //   964: invokevirtual 426	com/tencent/mm/model/c:rt	()Lcom/tencent/mm/storage/s;
    //   967: aload 12
    //   969: getfield 430	com/tencent/mm/d/b/bg:field_talker	Ljava/lang/String;
    //   972: invokevirtual 436	com/tencent/mm/storage/s:EA	(Ljava/lang/String;)Lcom/tencent/mm/storage/r;
    //   975: astore 14
    //   977: aload 14
    //   979: ifnull +82 -> 1061
    //   982: lload 9
    //   984: lstore 7
    //   986: aload 14
    //   988: getfield 441	com/tencent/mm/d/b/t:field_unReadCount	I
    //   991: ifle +70 -> 1061
    //   994: lload 9
    //   996: lstore 7
    //   998: invokestatic 305	com/tencent/mm/model/ah:tD	()Lcom/tencent/mm/model/c;
    //   1001: invokevirtual 390	com/tencent/mm/model/c:rs	()Lcom/tencent/mm/storage/ah;
    //   1004: aload 12
    //   1006: invokevirtual 445	com/tencent/mm/storage/ah:C	(Lcom/tencent/mm/storage/ag;)I
    //   1009: istore_2
    //   1010: lload 9
    //   1012: lstore 7
    //   1014: aload 14
    //   1016: getfield 441	com/tencent/mm/d/b/t:field_unReadCount	I
    //   1019: iload_2
    //   1020: if_icmplt +41 -> 1061
    //   1023: lload 9
    //   1025: lstore 7
    //   1027: aload 14
    //   1029: aload 14
    //   1031: getfield 441	com/tencent/mm/d/b/t:field_unReadCount	I
    //   1034: iconst_1
    //   1035: isub
    //   1036: invokevirtual 450	com/tencent/mm/storage/r:bi	(I)V
    //   1039: lload 9
    //   1041: lstore 7
    //   1043: invokestatic 305	com/tencent/mm/model/ah:tD	()Lcom/tencent/mm/model/c;
    //   1046: invokevirtual 426	com/tencent/mm/model/c:rt	()Lcom/tencent/mm/storage/s;
    //   1049: aload 14
    //   1051: aload 14
    //   1053: getfield 453	com/tencent/mm/d/b/t:field_username	Ljava/lang/String;
    //   1056: iconst_1
    //   1057: invokevirtual 456	com/tencent/mm/storage/s:a	(Lcom/tencent/mm/storage/r;Ljava/lang/String;Z)I
    //   1060: pop
    //   1061: aload_1
    //   1062: ifnull +424 -> 1486
    //   1065: lload 9
    //   1067: lstore 7
    //   1069: aload_1
    //   1070: getfield 460	com/tencent/mm/r/c$a:bFi	Z
    //   1073: ifeq +413 -> 1486
    //   1076: lload 9
    //   1078: lstore 7
    //   1080: new 462	com/tencent/mm/storage/ab
    //   1083: dup
    //   1084: invokespecial 463	com/tencent/mm/storage/ab:<init>	()V
    //   1087: astore 14
    //   1089: lload 9
    //   1091: lstore 7
    //   1093: aload 14
    //   1095: lload 9
    //   1097: putfield 466	com/tencent/mm/storage/ab:field_originSvrId	J
    //   1100: lload 9
    //   1102: lstore 7
    //   1104: aload 12
    //   1106: getfield 419	com/tencent/mm/d/b/bg:field_msgId	J
    //   1109: lconst_0
    //   1110: lcmp
    //   1111: ifne +315 -> 1426
    //   1114: lload 9
    //   1116: lstore 7
    //   1118: ldc 52
    //   1120: ldc_w 468
    //   1123: iconst_1
    //   1124: anewarray 4	java/lang/Object
    //   1127: dup
    //   1128: iconst_0
    //   1129: lload 9
    //   1131: invokestatic 357	java/lang/Long:valueOf	(J)Ljava/lang/Long;
    //   1134: aastore
    //   1135: invokestatic 76	com/tencent/mm/sdk/platformtools/u:i	(Ljava/lang/String;Ljava/lang/String;[Ljava/lang/Object;)V
    //   1138: lload 9
    //   1140: lstore 7
    //   1142: aload 14
    //   1144: aload 15
    //   1146: putfield 471	com/tencent/mm/storage/ab:field_content	Ljava/lang/String;
    //   1149: lload 9
    //   1151: lstore 7
    //   1153: aload 14
    //   1155: aload 16
    //   1157: getfield 474	com/tencent/mm/protocal/b/aj:fpL	I
    //   1160: i2l
    //   1161: putfield 477	com/tencent/mm/storage/ab:field_createTime	J
    //   1164: lload 9
    //   1166: lstore 7
    //   1168: aload 14
    //   1170: aload_1
    //   1171: invokestatic 481	com/tencent/mm/model/ar:c	(Lcom/tencent/mm/r/c$a;)I
    //   1174: putfield 484	com/tencent/mm/storage/ab:field_flag	I
    //   1177: lload 9
    //   1179: lstore 7
    //   1181: aload 14
    //   1183: aload 16
    //   1185: getfield 136	com/tencent/mm/protocal/b/aj:iXs	Lcom/tencent/mm/protocal/b/aly;
    //   1188: invokestatic 141	com/tencent/mm/platformtools/n:a	(Lcom/tencent/mm/protocal/b/aly;)Ljava/lang/String;
    //   1191: putfield 487	com/tencent/mm/storage/ab:field_fromUserName	Ljava/lang/String;
    //   1194: lload 9
    //   1196: lstore 7
    //   1198: aload 14
    //   1200: aload 16
    //   1202: getfield 490	com/tencent/mm/protocal/b/aj:iXt	Lcom/tencent/mm/protocal/b/aly;
    //   1205: invokestatic 141	com/tencent/mm/platformtools/n:a	(Lcom/tencent/mm/protocal/b/aly;)Ljava/lang/String;
    //   1208: putfield 493	com/tencent/mm/storage/ab:field_toUserName	Ljava/lang/String;
    //   1211: lload 9
    //   1213: lstore 7
    //   1215: aload 14
    //   1217: aload 16
    //   1219: getfield 155	com/tencent/mm/protocal/b/aj:iXA	J
    //   1222: putfield 496	com/tencent/mm/storage/ab:field_newMsgId	J
    //   1225: lload 9
    //   1227: lstore 7
    //   1229: ldc 52
    //   1231: ldc_w 498
    //   1234: iconst_2
    //   1235: anewarray 4	java/lang/Object
    //   1238: dup
    //   1239: iconst_0
    //   1240: invokestatic 305	com/tencent/mm/model/ah:tD	()Lcom/tencent/mm/model/c;
    //   1243: invokevirtual 502	com/tencent/mm/model/c:rX	()Lcom/tencent/mm/storage/ac;
    //   1246: aload 14
    //   1248: invokevirtual 507	com/tencent/mm/storage/ac:a	(Lcom/tencent/mm/sdk/h/c;)Z
    //   1251: invokestatic 512	java/lang/Boolean:valueOf	(Z)Ljava/lang/Boolean;
    //   1254: aastore
    //   1255: dup
    //   1256: iconst_1
    //   1257: aload 14
    //   1259: getfield 515	com/tencent/mm/storage/ab:jYv	J
    //   1262: invokestatic 357	java/lang/Long:valueOf	(J)Ljava/lang/Long;
    //   1265: aastore
    //   1266: invokestatic 76	com/tencent/mm/sdk/platformtools/u:i	(Ljava/lang/String;Ljava/lang/String;[Ljava/lang/Object;)V
    //   1269: aconst_null
    //   1270: areturn
    //   1271: aload 15
    //   1273: ldc_w 517
    //   1276: invokevirtual 521	java/lang/String:indexOf	(Ljava/lang/String;)I
    //   1279: istore_2
    //   1280: iload_2
    //   1281: iconst_m1
    //   1282: if_icmpne +13 -> 1295
    //   1285: ldc 52
    //   1287: ldc_w 523
    //   1290: invokestatic 169	com/tencent/mm/sdk/platformtools/u:e	(Ljava/lang/String;Ljava/lang/String;)V
    //   1293: aconst_null
    //   1294: areturn
    //   1295: aload 15
    //   1297: iload_2
    //   1298: invokevirtual 526	java/lang/String:substring	(I)Ljava/lang/String;
    //   1301: ldc_w 528
    //   1304: aconst_null
    //   1305: invokestatic 533	com/tencent/mm/sdk/platformtools/q:J	(Ljava/lang/String;Ljava/lang/String;Ljava/lang/String;)Ljava/util/Map;
    //   1308: astore 13
    //   1310: aload 13
    //   1312: ifnonnull +22 -> 1334
    //   1315: ldc 52
    //   1317: ldc_w 535
    //   1320: iconst_1
    //   1321: anewarray 4	java/lang/Object
    //   1324: dup
    //   1325: iconst_0
    //   1326: aload 15
    //   1328: aastore
    //   1329: invokestatic 184	com/tencent/mm/sdk/platformtools/u:e	(Ljava/lang/String;Ljava/lang/String;[Ljava/lang/Object;)V
    //   1332: aconst_null
    //   1333: areturn
    //   1334: aload 13
    //   1336: ldc_w 537
    //   1339: invokeinterface 44 2 0
    //   1344: checkcast 157	java/lang/String
    //   1347: astore 14
    //   1349: goto -1176 -> 173
    //   1352: aload 11
    //   1354: aload_1
    //   1355: invokeinterface 539 2 0
    //   1360: astore 11
    //   1362: goto -1092 -> 270
    //   1365: astore 12
    //   1367: ldc 52
    //   1369: aload 12
    //   1371: invokevirtual 540	java/lang/Exception:toString	()Ljava/lang/String;
    //   1374: invokestatic 169	com/tencent/mm/sdk/platformtools/u:e	(Ljava/lang/String;Ljava/lang/String;)V
    //   1377: goto -889 -> 488
    //   1380: astore 12
    //   1382: ldc 52
    //   1384: aload 12
    //   1386: invokevirtual 540	java/lang/Exception:toString	()Ljava/lang/String;
    //   1389: invokestatic 169	com/tencent/mm/sdk/platformtools/u:e	(Ljava/lang/String;Ljava/lang/String;)V
    //   1392: goto -851 -> 541
    //   1395: astore 12
    //   1397: ldc 52
    //   1399: new 244	java/lang/StringBuilder
    //   1402: dup
    //   1403: ldc_w 542
    //   1406: invokespecial 249	java/lang/StringBuilder:<init>	(Ljava/lang/String;)V
    //   1409: aload 12
    //   1411: invokevirtual 540	java/lang/Exception:toString	()Ljava/lang/String;
    //   1414: invokevirtual 257	java/lang/StringBuilder:append	(Ljava/lang/String;)Ljava/lang/StringBuilder;
    //   1417: invokevirtual 260	java/lang/StringBuilder:toString	()Ljava/lang/String;
    //   1420: invokestatic 169	com/tencent/mm/sdk/platformtools/u:e	(Ljava/lang/String;Ljava/lang/String;)V
    //   1423: goto -785 -> 638
    //   1426: lload 9
    //   1428: lstore 7
    //   1430: ldc 52
    //   1432: ldc_w 544
    //   1435: iconst_1
    //   1436: anewarray 4	java/lang/Object
    //   1439: dup
    //   1440: iconst_0
    //   1441: lload 9
    //   1443: invokestatic 357	java/lang/Long:valueOf	(J)Ljava/lang/Long;
    //   1446: aastore
    //   1447: invokestatic 76	com/tencent/mm/sdk/platformtools/u:i	(Ljava/lang/String;Ljava/lang/String;[Ljava/lang/Object;)V
    //   1450: lload 9
    //   1452: lstore 7
    //   1454: invokestatic 305	com/tencent/mm/model/ah:tD	()Lcom/tencent/mm/model/c;
    //   1457: invokevirtual 502	com/tencent/mm/model/c:rX	()Lcom/tencent/mm/storage/ac;
    //   1460: aload 14
    //   1462: iconst_1
    //   1463: iconst_0
    //   1464: anewarray 157	java/lang/String
    //   1467: invokevirtual 547	com/tencent/mm/storage/ac:a	(Lcom/tencent/mm/sdk/h/c;Z[Ljava/lang/String;)Z
    //   1470: pop
    //   1471: lload 9
    //   1473: lstore 7
    //   1475: invokestatic 305	com/tencent/mm/model/ah:tD	()Lcom/tencent/mm/model/c;
    //   1478: invokevirtual 390	com/tencent/mm/model/c:rs	()Lcom/tencent/mm/storage/ah;
    //   1481: lload 9
    //   1483: invokevirtual 551	com/tencent/mm/storage/ah:dF	(J)V
    //   1486: lload 9
    //   1488: lstore 7
    //   1490: aload 12
    //   1492: getfield 419	com/tencent/mm/d/b/bg:field_msgId	J
    //   1495: lconst_0
    //   1496: lcmp
    //   1497: ifne +59 -> 1556
    //   1500: aload_1
    //   1501: ifnull +14 -> 1515
    //   1504: lload 9
    //   1506: lstore 7
    //   1508: aload_1
    //   1509: getfield 460	com/tencent/mm/r/c$a:bFi	Z
    //   1512: ifne +44 -> 1556
    //   1515: lload 9
    //   1517: lstore 7
    //   1519: ldc 52
    //   1521: ldc_w 553
    //   1524: iconst_1
    //   1525: anewarray 4	java/lang/Object
    //   1528: dup
    //   1529: iconst_0
    //   1530: lload 9
    //   1532: invokestatic 357	java/lang/Long:valueOf	(J)Ljava/lang/Long;
    //   1535: aastore
    //   1536: invokestatic 76	com/tencent/mm/sdk/platformtools/u:i	(Ljava/lang/String;Ljava/lang/String;[Ljava/lang/Object;)V
    //   1539: lload 9
    //   1541: lstore 7
    //   1543: invokestatic 305	com/tencent/mm/model/ah:tD	()Lcom/tencent/mm/model/c;
    //   1546: invokevirtual 390	com/tencent/mm/model/c:rs	()Lcom/tencent/mm/storage/ah;
    //   1549: lload 9
    //   1551: invokevirtual 551	com/tencent/mm/storage/ah:dF	(J)V
    //   1554: aconst_null
    //   1555: areturn
    //   1556: lload 9
    //   1558: lstore 7
    //   1560: new 555	com/tencent/mm/d/a/ke
    //   1563: dup
    //   1564: invokespecial 556	com/tencent/mm/d/a/ke:<init>	()V
    //   1567: astore_1
    //   1568: lload 9
    //   1570: lstore 7
    //   1572: aload_1
    //   1573: getfield 560	com/tencent/mm/d/a/ke:aGE	Lcom/tencent/mm/d/a/ke$a;
    //   1576: aload 12
    //   1578: getfield 419	com/tencent/mm/d/b/bg:field_msgId	J
    //   1581: putfield 565	com/tencent/mm/d/a/ke$a:avg	J
    //   1584: lload 9
    //   1586: lstore 7
    //   1588: aload_1
    //   1589: getfield 560	com/tencent/mm/d/a/ke:aGE	Lcom/tencent/mm/d/a/ke$a;
    //   1592: aload 11
    //   1594: putfield 568	com/tencent/mm/d/a/ke$a:aGF	Ljava/lang/String;
    //   1597: lload 9
    //   1599: lstore 7
    //   1601: aload_1
    //   1602: getfield 560	com/tencent/mm/d/a/ke:aGE	Lcom/tencent/mm/d/a/ke$a;
    //   1605: aload 12
    //   1607: putfield 572	com/tencent/mm/d/a/ke$a:aFR	Lcom/tencent/mm/storage/ag;
    //   1610: lload 9
    //   1612: lstore 7
    //   1614: aload_1
    //   1615: getfield 560	com/tencent/mm/d/a/ke:aGE	Lcom/tencent/mm/d/a/ke$a;
    //   1618: aload 13
    //   1620: putfield 575	com/tencent/mm/d/a/ke$a:aGG	Lcom/tencent/mm/storage/ag;
    //   1623: lload 9
    //   1625: lstore 7
    //   1627: getstatic 581	com/tencent/mm/sdk/c/a:jUF	Lcom/tencent/mm/sdk/c/a;
    //   1630: aload_1
    //   1631: invokevirtual 585	com/tencent/mm/sdk/c/a:j	(Lcom/tencent/mm/sdk/c/b;)Z
    //   1634: pop
    //   1635: aconst_null
    //   1636: areturn
    //   1637: astore_1
    //   1638: ldc 52
    //   1640: aload_1
    //   1641: ldc_w 587
    //   1644: iconst_2
    //   1645: anewarray 4	java/lang/Object
    //   1648: dup
    //   1649: iconst_0
    //   1650: lload 7
    //   1652: invokestatic 357	java/lang/Long:valueOf	(J)Ljava/lang/Long;
    //   1655: aastore
    //   1656: dup
    //   1657: iconst_1
    //   1658: aload_1
    //   1659: invokevirtual 540	java/lang/Exception:toString	()Ljava/lang/String;
    //   1662: aastore
    //   1663: invokestatic 591	com/tencent/mm/sdk/platformtools/u:printErrStackTrace	(Ljava/lang/String;Ljava/lang/Throwable;Ljava/lang/String;[Ljava/lang/Object;)V
    //   1666: goto -31 -> 1635
    //   1669: aload 14
    //   1671: ifnull +561 -> 2232
    //   1674: aload 14
    //   1676: ldc_w 593
    //   1679: invokevirtual 196	java/lang/String:equals	(Ljava/lang/Object;)Z
    //   1682: ifeq +550 -> 2232
    //   1685: ldc 52
    //   1687: ldc_w 595
    //   1690: invokestatic 374	com/tencent/mm/sdk/platformtools/u:i	(Ljava/lang/String;Ljava/lang/String;)V
    //   1693: aload 13
    //   1695: ldc_w 597
    //   1698: invokeinterface 44 2 0
    //   1703: checkcast 157	java/lang/String
    //   1706: astore 14
    //   1708: aload 13
    //   1710: ldc_w 599
    //   1713: invokeinterface 44 2 0
    //   1718: checkcast 157	java/lang/String
    //   1721: astore 12
    //   1723: aload 13
    //   1725: ldc_w 601
    //   1728: invokeinterface 44 2 0
    //   1733: checkcast 157	java/lang/String
    //   1736: astore 13
    //   1738: aload 15
    //   1740: ldc_w 603
    //   1743: invokevirtual 521	java/lang/String:indexOf	(Ljava/lang/String;)I
    //   1746: istore_2
    //   1747: aload 15
    //   1749: ldc_w 605
    //   1752: invokevirtual 521	java/lang/String:indexOf	(Ljava/lang/String;)I
    //   1755: istore_3
    //   1756: iload_2
    //   1757: iconst_m1
    //   1758: if_icmpeq +8 -> 1766
    //   1761: iload_3
    //   1762: iconst_m1
    //   1763: if_icmpne +77 -> 1840
    //   1766: ldc -24
    //   1768: astore 11
    //   1770: ldc 52
    //   1772: ldc_w 607
    //   1775: iconst_4
    //   1776: anewarray 4	java/lang/Object
    //   1779: dup
    //   1780: iconst_0
    //   1781: aload 14
    //   1783: aastore
    //   1784: dup
    //   1785: iconst_1
    //   1786: aload 12
    //   1788: aastore
    //   1789: dup
    //   1790: iconst_2
    //   1791: aload 13
    //   1793: aastore
    //   1794: dup
    //   1795: iconst_3
    //   1796: aload 11
    //   1798: aastore
    //   1799: invokestatic 76	com/tencent/mm/sdk/platformtools/u:i	(Ljava/lang/String;Ljava/lang/String;[Ljava/lang/Object;)V
    //   1802: invokestatic 305	com/tencent/mm/model/ah:tD	()Lcom/tencent/mm/model/c;
    //   1805: invokevirtual 390	com/tencent/mm/model/c:rs	()Lcom/tencent/mm/storage/ah;
    //   1808: aload 13
    //   1810: aload 12
    //   1812: invokevirtual 611	com/tencent/mm/storage/ah:cp	(Ljava/lang/String;Ljava/lang/String;)Ljava/util/LinkedList;
    //   1815: astore 13
    //   1817: aload 13
    //   1819: ifnull +11 -> 1830
    //   1822: aload 13
    //   1824: invokevirtual 612	java/util/LinkedList:size	()I
    //   1827: ifgt +38 -> 1865
    //   1830: ldc 52
    //   1832: ldc_w 614
    //   1835: invokestatic 169	com/tencent/mm/sdk/platformtools/u:e	(Ljava/lang/String;Ljava/lang/String;)V
    //   1838: aconst_null
    //   1839: areturn
    //   1840: aload 15
    //   1842: iload_2
    //   1843: iload_3
    //   1844: bipush 6
    //   1846: iadd
    //   1847: invokevirtual 617	java/lang/String:substring	(II)Ljava/lang/String;
    //   1850: ldc_w 619
    //   1853: aconst_null
    //   1854: invokestatic 533	com/tencent/mm/sdk/platformtools/q:J	(Ljava/lang/String;Ljava/lang/String;Ljava/lang/String;)Ljava/util/Map;
    //   1857: invokestatic 623	com/tencent/mm/sdk/platformtools/ap:P	(Ljava/util/Map;)Ljava/lang/String;
    //   1860: astore 11
    //   1862: goto -92 -> 1770
    //   1865: aload 13
    //   1867: invokevirtual 624	java/util/LinkedList:iterator	()Ljava/util/Iterator;
    //   1870: astore 13
    //   1872: aload 13
    //   1874: invokeinterface 85 1 0
    //   1879: ifeq +57 -> 1936
    //   1882: aload 13
    //   1884: invokeinterface 89 1 0
    //   1889: checkcast 398	com/tencent/mm/storage/ag
    //   1892: astore 15
    //   1894: aload 15
    //   1896: ifnonnull +42 -> 1938
    //   1899: ldc 52
    //   1901: ldc_w 626
    //   1904: invokestatic 169	com/tencent/mm/sdk/platformtools/u:e	(Ljava/lang/String;Ljava/lang/String;)V
    //   1907: goto -35 -> 1872
    //   1910: astore_1
    //   1911: ldc 52
    //   1913: aload_1
    //   1914: ldc_w 628
    //   1917: iconst_2
    //   1918: anewarray 4	java/lang/Object
    //   1921: dup
    //   1922: iconst_0
    //   1923: aload 12
    //   1925: aastore
    //   1926: dup
    //   1927: iconst_1
    //   1928: aload_1
    //   1929: invokevirtual 540	java/lang/Exception:toString	()Ljava/lang/String;
    //   1932: aastore
    //   1933: invokestatic 591	com/tencent/mm/sdk/platformtools/u:printErrStackTrace	(Ljava/lang/String;Ljava/lang/Throwable;Ljava/lang/String;[Ljava/lang/Object;)V
    //   1936: aconst_null
    //   1937: areturn
    //   1938: aload 15
    //   1940: getfield 631	com/tencent/mm/d/b/bg:field_msgSvrId	J
    //   1943: lconst_0
    //   1944: lcmp
    //   1945: ifge +40 -> 1985
    //   1948: ldc 52
    //   1950: ldc_w 633
    //   1953: iconst_2
    //   1954: anewarray 4	java/lang/Object
    //   1957: dup
    //   1958: iconst_0
    //   1959: aload 15
    //   1961: getfield 419	com/tencent/mm/d/b/bg:field_msgId	J
    //   1964: invokestatic 357	java/lang/Long:valueOf	(J)Ljava/lang/Long;
    //   1967: aastore
    //   1968: dup
    //   1969: iconst_1
    //   1970: aload 15
    //   1972: getfield 631	com/tencent/mm/d/b/bg:field_msgSvrId	J
    //   1975: invokestatic 357	java/lang/Long:valueOf	(J)Ljava/lang/Long;
    //   1978: aastore
    //   1979: invokestatic 184	com/tencent/mm/sdk/platformtools/u:e	(Ljava/lang/String;Ljava/lang/String;[Ljava/lang/Object;)V
    //   1982: goto -110 -> 1872
    //   1985: ldc 52
    //   1987: ldc_w 635
    //   1990: iconst_2
    //   1991: anewarray 4	java/lang/Object
    //   1994: dup
    //   1995: iconst_0
    //   1996: aload 15
    //   1998: getfield 419	com/tencent/mm/d/b/bg:field_msgId	J
    //   2001: invokestatic 357	java/lang/Long:valueOf	(J)Ljava/lang/Long;
    //   2004: aastore
    //   2005: dup
    //   2006: iconst_1
    //   2007: aload 15
    //   2009: getfield 631	com/tencent/mm/d/b/bg:field_msgSvrId	J
    //   2012: invokestatic 357	java/lang/Long:valueOf	(J)Ljava/lang/Long;
    //   2015: aastore
    //   2016: invokestatic 76	com/tencent/mm/sdk/platformtools/u:i	(Ljava/lang/String;Ljava/lang/String;[Ljava/lang/Object;)V
    //   2019: aload 14
    //   2021: invokestatic 638	java/lang/Integer:parseInt	(Ljava/lang/String;)I
    //   2024: istore_2
    //   2025: iload_2
    //   2026: iconst_1
    //   2027: if_icmpne +77 -> 2104
    //   2030: invokestatic 305	com/tencent/mm/model/ah:tD	()Lcom/tencent/mm/model/c;
    //   2033: invokevirtual 390	com/tencent/mm/model/c:rs	()Lcom/tencent/mm/storage/ah;
    //   2036: aload 15
    //   2038: getfield 430	com/tencent/mm/d/b/bg:field_talker	Ljava/lang/String;
    //   2041: aload 15
    //   2043: getfield 631	com/tencent/mm/d/b/bg:field_msgSvrId	J
    //   2046: invokevirtual 642	com/tencent/mm/storage/ah:D	(Ljava/lang/String;J)I
    //   2049: pop
    //   2050: new 555	com/tencent/mm/d/a/ke
    //   2053: dup
    //   2054: invokespecial 556	com/tencent/mm/d/a/ke:<init>	()V
    //   2057: astore 16
    //   2059: aload 16
    //   2061: getfield 560	com/tencent/mm/d/a/ke:aGE	Lcom/tencent/mm/d/a/ke$a;
    //   2064: aload 15
    //   2066: getfield 419	com/tencent/mm/d/b/bg:field_msgId	J
    //   2069: putfield 565	com/tencent/mm/d/a/ke$a:avg	J
    //   2072: aload 16
    //   2074: getfield 560	com/tencent/mm/d/a/ke:aGE	Lcom/tencent/mm/d/a/ke$a;
    //   2077: aload 11
    //   2079: putfield 568	com/tencent/mm/d/a/ke$a:aGF	Ljava/lang/String;
    //   2082: aload 16
    //   2084: getfield 560	com/tencent/mm/d/a/ke:aGE	Lcom/tencent/mm/d/a/ke$a;
    //   2087: aload 15
    //   2089: putfield 572	com/tencent/mm/d/a/ke$a:aFR	Lcom/tencent/mm/storage/ag;
    //   2092: getstatic 581	com/tencent/mm/sdk/c/a:jUF	Lcom/tencent/mm/sdk/c/a;
    //   2095: aload 16
    //   2097: invokevirtual 585	com/tencent/mm/sdk/c/a:j	(Lcom/tencent/mm/sdk/c/b;)Z
    //   2100: pop
    //   2101: goto -229 -> 1872
    //   2104: iload_2
    //   2105: iconst_2
    //   2106: if_icmpne -56 -> 2050
    //   2109: aload 15
    //   2111: getfield 645	com/tencent/mm/d/b/bg:field_type	I
    //   2114: ldc_w 646
    //   2117: if_icmpne -67 -> 2050
    //   2120: aload 15
    //   2122: aload 11
    //   2124: invokevirtual 405	com/tencent/mm/storage/ag:setContent	(Ljava/lang/String;)V
    //   2127: aload 15
    //   2129: aload_1
    //   2130: invokestatic 414	com/tencent/mm/model/ar:a	(Lcom/tencent/mm/storage/ag;Lcom/tencent/mm/r/c$a;)V
    //   2133: invokestatic 305	com/tencent/mm/model/ah:tD	()Lcom/tencent/mm/model/c;
    //   2136: invokevirtual 390	com/tencent/mm/model/c:rs	()Lcom/tencent/mm/storage/ah;
    //   2139: aload 15
    //   2141: getfield 631	com/tencent/mm/d/b/bg:field_msgSvrId	J
    //   2144: aload 15
    //   2146: invokevirtual 648	com/tencent/mm/storage/ah:b	(JLcom/tencent/mm/storage/ag;)V
    //   2149: invokestatic 305	com/tencent/mm/model/ah:tD	()Lcom/tencent/mm/model/c;
    //   2152: invokevirtual 426	com/tencent/mm/model/c:rt	()Lcom/tencent/mm/storage/s;
    //   2155: aload 15
    //   2157: getfield 430	com/tencent/mm/d/b/bg:field_talker	Ljava/lang/String;
    //   2160: invokevirtual 436	com/tencent/mm/storage/s:EA	(Ljava/lang/String;)Lcom/tencent/mm/storage/r;
    //   2163: astore 16
    //   2165: aload 16
    //   2167: ifnull -117 -> 2050
    //   2170: aload 16
    //   2172: getfield 441	com/tencent/mm/d/b/t:field_unReadCount	I
    //   2175: ifle -125 -> 2050
    //   2178: invokestatic 305	com/tencent/mm/model/ah:tD	()Lcom/tencent/mm/model/c;
    //   2181: invokevirtual 390	com/tencent/mm/model/c:rs	()Lcom/tencent/mm/storage/ah;
    //   2184: aload 15
    //   2186: invokevirtual 445	com/tencent/mm/storage/ah:C	(Lcom/tencent/mm/storage/ag;)I
    //   2189: istore_2
    //   2190: aload 16
    //   2192: getfield 441	com/tencent/mm/d/b/t:field_unReadCount	I
    //   2195: iload_2
    //   2196: if_icmplt -146 -> 2050
    //   2199: aload 16
    //   2201: aload 16
    //   2203: getfield 441	com/tencent/mm/d/b/t:field_unReadCount	I
    //   2206: iconst_1
    //   2207: isub
    //   2208: invokevirtual 450	com/tencent/mm/storage/r:bi	(I)V
    //   2211: invokestatic 305	com/tencent/mm/model/ah:tD	()Lcom/tencent/mm/model/c;
    //   2214: invokevirtual 426	com/tencent/mm/model/c:rt	()Lcom/tencent/mm/storage/s;
    //   2217: aload 16
    //   2219: aload 16
    //   2221: getfield 453	com/tencent/mm/d/b/t:field_username	Ljava/lang/String;
    //   2224: iconst_1
    //   2225: invokevirtual 456	com/tencent/mm/storage/s:a	(Lcom/tencent/mm/storage/r;Ljava/lang/String;Z)I
    //   2228: pop
    //   2229: goto -179 -> 2050
    //   2232: aload 14
    //   2234: ifnull +3096 -> 5330
    //   2237: aload 14
    //   2239: ldc_w 650
    //   2242: invokevirtual 196	java/lang/String:equals	(Ljava/lang/Object;)Z
    //   2245: ifeq +3085 -> 5330
    //   2248: ldc_w 651
    //   2251: invokestatic 72	java/lang/Integer:valueOf	(I)Ljava/lang/Integer;
    //   2254: invokestatic 208	com/tencent/mm/r/c$c:X	(Ljava/lang/Object;)Lcom/tencent/mm/r/c;
    //   2257: astore 11
    //   2259: aload 11
    //   2261: ifnonnull +882 -> 3143
    //   2264: aconst_null
    //   2265: astore 11
    //   2267: aload 11
    //   2269: astore 12
    //   2271: aload 14
    //   2273: ifnull +37 -> 2310
    //   2276: aload 11
    //   2278: astore 12
    //   2280: aload 14
    //   2282: ldc_w 653
    //   2285: invokevirtual 196	java/lang/String:equals	(Ljava/lang/Object;)Z
    //   2288: ifeq +22 -> 2310
    //   2291: ldc_w 654
    //   2294: invokestatic 72	java/lang/Integer:valueOf	(I)Ljava/lang/Integer;
    //   2297: invokestatic 208	com/tencent/mm/r/c$c:X	(Ljava/lang/Object;)Lcom/tencent/mm/r/c;
    //   2300: astore 11
    //   2302: aload 11
    //   2304: ifnonnull +852 -> 3156
    //   2307: aconst_null
    //   2308: astore 12
    //   2310: aload 12
    //   2312: astore 11
    //   2314: aload 14
    //   2316: ifnull +37 -> 2353
    //   2319: aload 12
    //   2321: astore 11
    //   2323: aload 14
    //   2325: ldc_w 656
    //   2328: invokevirtual 196	java/lang/String:equals	(Ljava/lang/Object;)Z
    //   2331: ifeq +22 -> 2353
    //   2334: ldc_w 657
    //   2337: invokestatic 72	java/lang/Integer:valueOf	(I)Ljava/lang/Integer;
    //   2340: invokestatic 208	com/tencent/mm/r/c$c:X	(Ljava/lang/Object;)Lcom/tencent/mm/r/c;
    //   2343: astore 11
    //   2345: aload 11
    //   2347: ifnonnull +822 -> 3169
    //   2350: aconst_null
    //   2351: astore 11
    //   2353: aload 14
    //   2355: ifnull +136 -> 2491
    //   2358: aload 14
    //   2360: ldc_w 659
    //   2363: invokevirtual 196	java/lang/String:equals	(Ljava/lang/Object;)Z
    //   2366: ifeq +125 -> 2491
    //   2369: aload 16
    //   2371: getfield 136	com/tencent/mm/protocal/b/aj:iXs	Lcom/tencent/mm/protocal/b/aly;
    //   2374: invokestatic 141	com/tencent/mm/platformtools/n:a	(Lcom/tencent/mm/protocal/b/aly;)Ljava/lang/String;
    //   2377: astore 12
    //   2379: invokestatic 305	com/tencent/mm/model/ah:tD	()Lcom/tencent/mm/model/c;
    //   2382: invokevirtual 390	com/tencent/mm/model/c:rs	()Lcom/tencent/mm/storage/ah;
    //   2385: aload 12
    //   2387: aload 16
    //   2389: getfield 155	com/tencent/mm/protocal/b/aj:iXA	J
    //   2392: invokevirtual 396	com/tencent/mm/storage/ah:x	(Ljava/lang/String;J)Lcom/tencent/mm/storage/ag;
    //   2395: astore 17
    //   2397: iconst_0
    //   2398: istore_2
    //   2399: aload 17
    //   2401: getfield 419	com/tencent/mm/d/b/bg:field_msgId	J
    //   2404: lconst_0
    //   2405: lcmp
    //   2406: ifle +5 -> 2411
    //   2409: iconst_1
    //   2410: istore_2
    //   2411: aload 17
    //   2413: aload 16
    //   2415: getfield 155	com/tencent/mm/protocal/b/aj:iXA	J
    //   2418: invokevirtual 662	com/tencent/mm/storage/ag:u	(J)V
    //   2421: aload 17
    //   2423: aload 12
    //   2425: aload 16
    //   2427: getfield 474	com/tencent/mm/protocal/b/aj:fpL	I
    //   2430: i2l
    //   2431: invokestatic 665	com/tencent/mm/model/ar:d	(Ljava/lang/String;J)J
    //   2434: invokevirtual 668	com/tencent/mm/storage/ag:v	(J)V
    //   2437: aload 17
    //   2439: sipush 10002
    //   2442: invokevirtual 409	com/tencent/mm/storage/ag:setType	(I)V
    //   2445: aload 17
    //   2447: aload 15
    //   2449: invokevirtual 405	com/tencent/mm/storage/ag:setContent	(Ljava/lang/String;)V
    //   2452: aload 17
    //   2454: iconst_0
    //   2455: invokevirtual 671	com/tencent/mm/storage/ag:bl	(I)V
    //   2458: aload 17
    //   2460: aload 12
    //   2462: invokevirtual 674	com/tencent/mm/storage/ag:setTalker	(Ljava/lang/String;)V
    //   2465: aload 17
    //   2467: aload 16
    //   2469: getfield 677	com/tencent/mm/protocal/b/aj:iXy	Ljava/lang/String;
    //   2472: invokevirtual 680	com/tencent/mm/storage/ag:cs	(Ljava/lang/String;)V
    //   2475: aload 17
    //   2477: aload_1
    //   2478: invokestatic 414	com/tencent/mm/model/ar:a	(Lcom/tencent/mm/storage/ag;Lcom/tencent/mm/r/c$a;)V
    //   2481: iload_2
    //   2482: ifne +700 -> 3182
    //   2485: aload 17
    //   2487: invokestatic 683	com/tencent/mm/model/ar:e	(Lcom/tencent/mm/storage/ag;)J
    //   2490: pop2
    //   2491: aload 11
    //   2493: astore 12
    //   2495: aload 14
    //   2497: ifnull +405 -> 2902
    //   2500: aload 11
    //   2502: astore 12
    //   2504: aload 14
    //   2506: ldc_w 685
    //   2509: invokevirtual 196	java/lang/String:equals	(Ljava/lang/Object;)Z
    //   2512: ifeq +390 -> 2902
    //   2515: aload 11
    //   2517: astore 12
    //   2519: aload_0
    //   2520: getfield 29	com/tencent/mm/model/bd:bCT	J
    //   2523: aload 16
    //   2525: getfield 155	com/tencent/mm/protocal/b/aj:iXA	J
    //   2528: lcmp
    //   2529: ifeq +373 -> 2902
    //   2532: aload_0
    //   2533: aload 16
    //   2535: getfield 155	com/tencent/mm/protocal/b/aj:iXA	J
    //   2538: putfield 29	com/tencent/mm/model/bd:bCT	J
    //   2541: ldc 52
    //   2543: ldc_w 687
    //   2546: invokestatic 374	com/tencent/mm/sdk/platformtools/u:i	(Ljava/lang/String;Ljava/lang/String;)V
    //   2549: new 689	com/tencent/mm/model/bi
    //   2552: dup
    //   2553: aload 13
    //   2555: invokespecial 692	com/tencent/mm/model/bi:<init>	(Ljava/util/Map;)V
    //   2558: astore 12
    //   2560: aload 12
    //   2562: getfield 695	com/tencent/mm/model/bi:bDf	Ljava/util/Map;
    //   2565: ldc_w 697
    //   2568: invokeinterface 44 2 0
    //   2573: checkcast 157	java/lang/String
    //   2576: astore 15
    //   2578: aload 12
    //   2580: getfield 695	com/tencent/mm/model/bi:bDf	Ljava/util/Map;
    //   2583: ldc_w 699
    //   2586: invokeinterface 44 2 0
    //   2591: checkcast 157	java/lang/String
    //   2594: astore 17
    //   2596: aload 12
    //   2598: getfield 695	com/tencent/mm/model/bi:bDf	Ljava/util/Map;
    //   2601: ldc_w 701
    //   2604: invokeinterface 44 2 0
    //   2609: checkcast 157	java/lang/String
    //   2612: astore 11
    //   2614: aload 12
    //   2616: getfield 695	com/tencent/mm/model/bi:bDf	Ljava/util/Map;
    //   2619: ldc_w 703
    //   2622: invokeinterface 44 2 0
    //   2627: checkcast 157	java/lang/String
    //   2630: astore 18
    //   2632: ldc_w 705
    //   2635: ldc_w 707
    //   2638: iconst_3
    //   2639: anewarray 4	java/lang/Object
    //   2642: dup
    //   2643: iconst_0
    //   2644: aload 15
    //   2646: aastore
    //   2647: dup
    //   2648: iconst_1
    //   2649: aload 17
    //   2651: aastore
    //   2652: dup
    //   2653: iconst_2
    //   2654: aload 11
    //   2656: aastore
    //   2657: invokestatic 191	com/tencent/mm/sdk/platformtools/u:d	(Ljava/lang/String;Ljava/lang/String;[Ljava/lang/Object;)V
    //   2660: invokestatic 216	com/tencent/mm/g/h:pS	()Lcom/tencent/mm/g/e;
    //   2663: ldc_w 709
    //   2666: invokevirtual 238	com/tencent/mm/g/e:getValue	(Ljava/lang/String;)Ljava/lang/String;
    //   2669: astore 11
    //   2671: ldc_w 705
    //   2674: ldc_w 711
    //   2677: iconst_1
    //   2678: anewarray 4	java/lang/Object
    //   2681: dup
    //   2682: iconst_0
    //   2683: aload 11
    //   2685: aastore
    //   2686: invokestatic 191	com/tencent/mm/sdk/platformtools/u:d	(Ljava/lang/String;Ljava/lang/String;[Ljava/lang/Object;)V
    //   2689: aload 11
    //   2691: invokestatic 99	com/tencent/mm/sdk/platformtools/ay:kz	(Ljava/lang/String;)Z
    //   2694: ifne +507 -> 3201
    //   2697: aload 11
    //   2699: invokestatic 386	java/lang/Long:parseLong	(Ljava/lang/String;)J
    //   2702: lstore 7
    //   2704: aload 18
    //   2706: iconst_0
    //   2707: iconst_m1
    //   2708: invokestatic 716	com/tencent/mm/q/b:a	(Ljava/lang/String;ZI)Landroid/graphics/Bitmap;
    //   2711: astore 19
    //   2713: invokestatic 720	com/tencent/mm/model/ah:kU	()Lcom/tencent/mm/model/y;
    //   2716: astore 20
    //   2718: aload 17
    //   2720: invokestatic 99	com/tencent/mm/sdk/platformtools/ay:kz	(Ljava/lang/String;)Z
    //   2723: ifeq +484 -> 3207
    //   2726: ldc_w 705
    //   2729: ldc_w 722
    //   2732: invokestatic 169	com/tencent/mm/sdk/platformtools/u:e	(Ljava/lang/String;Ljava/lang/String;)V
    //   2735: ldc_w 724
    //   2738: astore 11
    //   2740: new 726	android/content/Intent
    //   2743: dup
    //   2744: invokespecial 727	android/content/Intent:<init>	()V
    //   2747: astore 21
    //   2749: aload 21
    //   2751: invokestatic 733	com/tencent/mm/sdk/platformtools/y:getContext	()Landroid/content/Context;
    //   2754: aload 11
    //   2756: invokevirtual 737	android/content/Intent:setClassName	(Landroid/content/Context;Ljava/lang/String;)Landroid/content/Intent;
    //   2759: pop
    //   2760: aload 21
    //   2762: ldc_w 738
    //   2765: invokevirtual 742	android/content/Intent:setFlags	(I)Landroid/content/Intent;
    //   2768: pop
    //   2769: aload 21
    //   2771: ldc_w 744
    //   2774: aload 12
    //   2776: getfield 695	com/tencent/mm/model/bi:bDf	Ljava/util/Map;
    //   2779: ldc_w 697
    //   2782: invokeinterface 44 2 0
    //   2787: checkcast 157	java/lang/String
    //   2790: invokevirtual 748	android/content/Intent:putExtra	(Ljava/lang/String;Ljava/lang/String;)Landroid/content/Intent;
    //   2793: pop
    //   2794: aload 17
    //   2796: ldc_w 750
    //   2799: invokevirtual 196	java/lang/String:equals	(Ljava/lang/Object;)Z
    //   2802: ifne +28 -> 2830
    //   2805: aload 21
    //   2807: ldc_w 752
    //   2810: aload 12
    //   2812: getfield 695	com/tencent/mm/model/bi:bDf	Ljava/util/Map;
    //   2815: ldc_w 699
    //   2818: invokeinterface 44 2 0
    //   2823: checkcast 157	java/lang/String
    //   2826: invokevirtual 748	android/content/Intent:putExtra	(Ljava/lang/String;Ljava/lang/String;)Landroid/content/Intent;
    //   2829: pop
    //   2830: aload 20
    //   2832: iconst_m1
    //   2833: invokestatic 733	com/tencent/mm/sdk/platformtools/y:getContext	()Landroid/content/Context;
    //   2836: invokestatic 758	java/util/UUID:randomUUID	()Ljava/util/UUID;
    //   2839: invokevirtual 761	java/util/UUID:hashCode	()I
    //   2842: aload 21
    //   2844: ldc_w 762
    //   2847: invokestatic 768	android/app/PendingIntent:getActivity	(Landroid/content/Context;ILandroid/content/Intent;I)Landroid/app/PendingIntent;
    //   2850: invokestatic 733	com/tencent/mm/sdk/platformtools/y:getContext	()Landroid/content/Context;
    //   2853: ldc_w 769
    //   2856: invokevirtual 774	android/content/Context:getString	(I)Ljava/lang/String;
    //   2859: aload 15
    //   2861: aload 15
    //   2863: aload 19
    //   2865: aload 18
    //   2867: invokeinterface 779 8 0
    //   2872: astore 11
    //   2874: aload 11
    //   2876: aload 11
    //   2878: getfield 784	android/app/Notification:flags	I
    //   2881: bipush 16
    //   2883: ior
    //   2884: putfield 784	android/app/Notification:flags	I
    //   2887: invokestatic 720	com/tencent/mm/model/ah:kU	()Lcom/tencent/mm/model/y;
    //   2890: aload 11
    //   2892: iconst_0
    //   2893: invokeinterface 787 3 0
    //   2898: pop
    //   2899: aconst_null
    //   2900: astore 12
    //   2902: aload 12
    //   2904: astore 11
    //   2906: aload 14
    //   2908: ifnull +561 -> 3469
    //   2911: aload 12
    //   2913: astore 11
    //   2915: aload 14
    //   2917: ldc_w 789
    //   2920: invokevirtual 196	java/lang/String:equals	(Ljava/lang/Object;)Z
    //   2923: ifeq +546 -> 3469
    //   2926: aload 13
    //   2928: ldc_w 791
    //   2931: invokeinterface 44 2 0
    //   2936: checkcast 157	java/lang/String
    //   2939: astore 17
    //   2941: aload 13
    //   2943: ldc_w 793
    //   2946: invokeinterface 44 2 0
    //   2951: checkcast 157	java/lang/String
    //   2954: astore 18
    //   2956: ldc 52
    //   2958: ldc_w 795
    //   2961: iconst_2
    //   2962: anewarray 4	java/lang/Object
    //   2965: dup
    //   2966: iconst_0
    //   2967: aload 17
    //   2969: aastore
    //   2970: dup
    //   2971: iconst_1
    //   2972: aload 18
    //   2974: aastore
    //   2975: invokestatic 76	com/tencent/mm/sdk/platformtools/u:i	(Ljava/lang/String;Ljava/lang/String;[Ljava/lang/Object;)V
    //   2978: invokestatic 733	com/tencent/mm/sdk/platformtools/y:getContext	()Landroid/content/Context;
    //   2981: ldc_w 797
    //   2984: iconst_4
    //   2985: invokevirtual 801	android/content/Context:getSharedPreferences	(Ljava/lang/String;I)Landroid/content/SharedPreferences;
    //   2988: astore 19
    //   2990: aload 19
    //   2992: ldc_w 803
    //   2995: ldc -24
    //   2997: invokeinterface 808 3 0
    //   3002: astore 15
    //   3004: aload 15
    //   3006: aload 17
    //   3008: invokevirtual 811	java/lang/String:contains	(Ljava/lang/CharSequence;)Z
    //   3011: ifne +401 -> 3412
    //   3014: aload 15
    //   3016: ldc_w 813
    //   3019: invokevirtual 817	java/lang/String:split	(Ljava/lang/String;)[Ljava/lang/String;
    //   3022: astore 20
    //   3024: aload 20
    //   3026: ifnull +297 -> 3323
    //   3029: aload 20
    //   3031: arraylength
    //   3032: bipush 10
    //   3034: if_icmple +289 -> 3323
    //   3037: aload 20
    //   3039: arraylength
    //   3040: istore_3
    //   3041: iconst_0
    //   3042: istore_2
    //   3043: ldc -24
    //   3045: astore 11
    //   3047: aload 11
    //   3049: astore 12
    //   3051: iload_2
    //   3052: iload_3
    //   3053: if_icmpge +274 -> 3327
    //   3056: aload 20
    //   3058: iload_2
    //   3059: aaload
    //   3060: ldc_w 819
    //   3063: invokevirtual 817	java/lang/String:split	(Ljava/lang/String;)[Ljava/lang/String;
    //   3066: astore 21
    //   3068: aload 11
    //   3070: astore 12
    //   3072: aload 21
    //   3074: iconst_0
    //   3075: aaload
    //   3076: invokestatic 386	java/lang/Long:parseLong	(Ljava/lang/String;)J
    //   3079: invokestatic 823	com/tencent/mm/sdk/platformtools/ay:am	(J)J
    //   3082: ldc2_w 824
    //   3085: lcmp
    //   3086: ifge +46 -> 3132
    //   3089: new 244	java/lang/StringBuilder
    //   3092: dup
    //   3093: invokespecial 826	java/lang/StringBuilder:<init>	()V
    //   3096: aload 11
    //   3098: invokevirtual 257	java/lang/StringBuilder:append	(Ljava/lang/String;)Ljava/lang/StringBuilder;
    //   3101: aload 21
    //   3103: iconst_0
    //   3104: aaload
    //   3105: invokevirtual 257	java/lang/StringBuilder:append	(Ljava/lang/String;)Ljava/lang/StringBuilder;
    //   3108: ldc_w 819
    //   3111: invokevirtual 257	java/lang/StringBuilder:append	(Ljava/lang/String;)Ljava/lang/StringBuilder;
    //   3114: aload 21
    //   3116: iconst_1
    //   3117: aaload
    //   3118: invokevirtual 257	java/lang/StringBuilder:append	(Ljava/lang/String;)Ljava/lang/StringBuilder;
    //   3121: ldc_w 813
    //   3124: invokevirtual 257	java/lang/StringBuilder:append	(Ljava/lang/String;)Ljava/lang/StringBuilder;
    //   3127: invokevirtual 260	java/lang/StringBuilder:toString	()Ljava/lang/String;
    //   3130: astore 12
    //   3132: iload_2
    //   3133: iconst_1
    //   3134: iadd
    //   3135: istore_2
    //   3136: aload 12
    //   3138: astore 11
    //   3140: goto -93 -> 3047
    //   3143: aload 11
    //   3145: aload_1
    //   3146: invokeinterface 539 2 0
    //   3151: astore 11
    //   3153: goto -886 -> 2267
    //   3156: aload 11
    //   3158: aload_1
    //   3159: invokeinterface 539 2 0
    //   3164: astore 12
    //   3166: goto -856 -> 2310
    //   3169: aload 11
    //   3171: aload_1
    //   3172: invokeinterface 539 2 0
    //   3177: astore 11
    //   3179: goto -826 -> 2353
    //   3182: invokestatic 305	com/tencent/mm/model/ah:tD	()Lcom/tencent/mm/model/c;
    //   3185: invokevirtual 390	com/tencent/mm/model/c:rs	()Lcom/tencent/mm/storage/ah;
    //   3188: aload 16
    //   3190: getfield 155	com/tencent/mm/protocal/b/aj:iXA	J
    //   3193: aload 17
    //   3195: invokevirtual 648	com/tencent/mm/storage/ah:b	(JLcom/tencent/mm/storage/ag;)V
    //   3198: goto -707 -> 2491
    //   3201: lconst_0
    //   3202: lstore 7
    //   3204: goto -500 -> 2704
    //   3207: ldc2_w 827
    //   3210: lload 7
    //   3212: land
    //   3213: ldc2_w 827
    //   3216: lcmp
    //   3217: ifne +22 -> 3239
    //   3220: aload 17
    //   3222: ldc_w 830
    //   3225: invokevirtual 174	java/lang/String:startsWith	(Ljava/lang/String;)Z
    //   3228: ifeq +11 -> 3239
    //   3231: ldc_w 832
    //   3234: astore 11
    //   3236: goto -496 -> 2740
    //   3239: lload 7
    //   3241: ldc2_w 833
    //   3244: land
    //   3245: ldc2_w 833
    //   3248: lcmp
    //   3249: ifne +22 -> 3271
    //   3252: aload 17
    //   3254: ldc_w 836
    //   3257: invokevirtual 174	java/lang/String:startsWith	(Ljava/lang/String;)Z
    //   3260: ifeq +11 -> 3271
    //   3263: ldc_w 838
    //   3266: astore 11
    //   3268: goto -528 -> 2740
    //   3271: ldc_w 705
    //   3274: ldc_w 840
    //   3277: iconst_1
    //   3278: anewarray 4	java/lang/Object
    //   3281: dup
    //   3282: iconst_0
    //   3283: aload 17
    //   3285: aastore
    //   3286: invokestatic 184	com/tencent/mm/sdk/platformtools/u:e	(Ljava/lang/String;Ljava/lang/String;[Ljava/lang/Object;)V
    //   3289: ldc_w 724
    //   3292: astore 11
    //   3294: goto -554 -> 2740
    //   3297: astore 12
    //   3299: ldc 52
    //   3301: ldc_w 842
    //   3304: iconst_1
    //   3305: anewarray 4	java/lang/Object
    //   3308: dup
    //   3309: iconst_0
    //   3310: aload 12
    //   3312: aastore
    //   3313: invokestatic 184	com/tencent/mm/sdk/platformtools/u:e	(Ljava/lang/String;Ljava/lang/String;[Ljava/lang/Object;)V
    //   3316: aload 11
    //   3318: astore 12
    //   3320: goto -188 -> 3132
    //   3323: aload 15
    //   3325: astore 12
    //   3327: new 244	java/lang/StringBuilder
    //   3330: dup
    //   3331: invokespecial 826	java/lang/StringBuilder:<init>	()V
    //   3334: aload 12
    //   3336: invokevirtual 257	java/lang/StringBuilder:append	(Ljava/lang/String;)Ljava/lang/StringBuilder;
    //   3339: invokestatic 352	com/tencent/mm/sdk/platformtools/ay:FR	()J
    //   3342: invokevirtual 845	java/lang/StringBuilder:append	(J)Ljava/lang/StringBuilder;
    //   3345: ldc_w 819
    //   3348: invokevirtual 257	java/lang/StringBuilder:append	(Ljava/lang/String;)Ljava/lang/StringBuilder;
    //   3351: aload 17
    //   3353: invokevirtual 257	java/lang/StringBuilder:append	(Ljava/lang/String;)Ljava/lang/StringBuilder;
    //   3356: ldc_w 813
    //   3359: invokevirtual 257	java/lang/StringBuilder:append	(Ljava/lang/String;)Ljava/lang/StringBuilder;
    //   3362: invokevirtual 260	java/lang/StringBuilder:toString	()Ljava/lang/String;
    //   3365: astore 11
    //   3367: ldc 52
    //   3369: ldc_w 847
    //   3372: iconst_2
    //   3373: anewarray 4	java/lang/Object
    //   3376: dup
    //   3377: iconst_0
    //   3378: aload 15
    //   3380: aastore
    //   3381: dup
    //   3382: iconst_1
    //   3383: aload 11
    //   3385: aastore
    //   3386: invokestatic 76	com/tencent/mm/sdk/platformtools/u:i	(Ljava/lang/String;Ljava/lang/String;[Ljava/lang/Object;)V
    //   3389: aload 19
    //   3391: invokeinterface 851 1 0
    //   3396: ldc_w 803
    //   3399: aload 11
    //   3401: invokeinterface 857 3 0
    //   3406: invokeinterface 860 1 0
    //   3411: pop
    //   3412: new 862	com/tencent/mm/sdk/platformtools/aa
    //   3415: dup
    //   3416: invokestatic 868	android/os/Looper:getMainLooper	()Landroid/os/Looper;
    //   3419: invokespecial 871	com/tencent/mm/sdk/platformtools/aa:<init>	(Landroid/os/Looper;)V
    //   3422: new 8	com/tencent/mm/model/bd$1
    //   3425: dup
    //   3426: aload_0
    //   3427: aload 17
    //   3429: invokespecial 874	com/tencent/mm/model/bd$1:<init>	(Lcom/tencent/mm/model/bd;Ljava/lang/String;)V
    //   3432: invokevirtual 878	com/tencent/mm/sdk/platformtools/aa:post	(Ljava/lang/Runnable;)Z
    //   3435: pop
    //   3436: aload 16
    //   3438: aload 18
    //   3440: invokestatic 202	com/tencent/mm/platformtools/n:kw	(Ljava/lang/String;)Lcom/tencent/mm/protocal/b/aly;
    //   3443: putfield 144	com/tencent/mm/protocal/b/aj:iXv	Lcom/tencent/mm/protocal/b/aly;
    //   3446: aload 16
    //   3448: iconst_1
    //   3449: putfield 128	com/tencent/mm/protocal/b/aj:iXu	I
    //   3452: iconst_1
    //   3453: invokestatic 72	java/lang/Integer:valueOf	(I)Ljava/lang/Integer;
    //   3456: invokestatic 208	com/tencent/mm/r/c$c:X	(Ljava/lang/Object;)Lcom/tencent/mm/r/c;
    //   3459: astore 11
    //   3461: aload 11
    //   3463: ifnonnull +154 -> 3617
    //   3466: aconst_null
    //   3467: astore 11
    //   3469: aload 14
    //   3471: ifnull +485 -> 3956
    //   3474: aload 14
    //   3476: ldc_w 880
    //   3479: invokevirtual 196	java/lang/String:equals	(Ljava/lang/Object;)Z
    //   3482: ifeq +474 -> 3956
    //   3485: aload 13
    //   3487: ldc_w 882
    //   3490: invokeinterface 44 2 0
    //   3495: checkcast 157	java/lang/String
    //   3498: astore_1
    //   3499: aload 13
    //   3501: ldc_w 884
    //   3504: invokeinterface 44 2 0
    //   3509: checkcast 157	java/lang/String
    //   3512: astore 13
    //   3514: aload_1
    //   3515: ifnonnull +1812 -> 5327
    //   3518: ldc -24
    //   3520: astore_1
    //   3521: ldc 52
    //   3523: ldc_w 886
    //   3526: iconst_3
    //   3527: anewarray 4	java/lang/Object
    //   3530: dup
    //   3531: iconst_0
    //   3532: aload_1
    //   3533: invokevirtual 275	java/lang/String:length	()I
    //   3536: invokestatic 72	java/lang/Integer:valueOf	(I)Ljava/lang/Integer;
    //   3539: aastore
    //   3540: dup
    //   3541: iconst_1
    //   3542: aload_1
    //   3543: aastore
    //   3544: dup
    //   3545: iconst_2
    //   3546: aload 13
    //   3548: aastore
    //   3549: invokestatic 76	com/tencent/mm/sdk/platformtools/u:i	(Ljava/lang/String;Ljava/lang/String;[Ljava/lang/Object;)V
    //   3552: invokestatic 892	com/tencent/mm/protocal/z:aTv	()Lcom/tencent/mm/protocal/z;
    //   3555: getfield 895	com/tencent/mm/protocal/z:iVr	Ljava/lang/String;
    //   3558: invokevirtual 899	java/lang/String:getBytes	()[B
    //   3561: astore 14
    //   3563: invokestatic 892	com/tencent/mm/protocal/z:aTv	()Lcom/tencent/mm/protocal/z;
    //   3566: getfield 902	com/tencent/mm/protocal/z:iVs	Ljava/lang/String;
    //   3569: invokevirtual 899	java/lang/String:getBytes	()[B
    //   3572: astore 15
    //   3574: aconst_null
    //   3575: astore 11
    //   3577: invokestatic 906	com/tencent/mm/model/ah:tE	()Lcom/tencent/mm/r/m;
    //   3580: getfield 912	com/tencent/mm/r/m:bFO	Lcom/tencent/mm/network/e;
    //   3583: invokeinterface 918 1 0
    //   3588: invokeinterface 923 1 0
    //   3593: astore 12
    //   3595: aload 12
    //   3597: astore 11
    //   3599: aload 11
    //   3601: invokestatic 926	com/tencent/mm/sdk/platformtools/ay:J	([B)Z
    //   3604: ifeq +51 -> 3655
    //   3607: ldc 52
    //   3609: ldc_w 928
    //   3612: invokestatic 169	com/tencent/mm/sdk/platformtools/u:e	(Ljava/lang/String;Ljava/lang/String;)V
    //   3615: aconst_null
    //   3616: areturn
    //   3617: aload 11
    //   3619: aload_1
    //   3620: invokeinterface 539 2 0
    //   3625: astore 11
    //   3627: goto -158 -> 3469
    //   3630: astore 12
    //   3632: ldc 52
    //   3634: ldc_w 930
    //   3637: iconst_1
    //   3638: anewarray 4	java/lang/Object
    //   3641: dup
    //   3642: iconst_0
    //   3643: aload 12
    //   3645: invokestatic 933	com/tencent/mm/sdk/platformtools/ay:b	(Ljava/lang/Throwable;)Ljava/lang/String;
    //   3648: aastore
    //   3649: invokestatic 184	com/tencent/mm/sdk/platformtools/u:e	(Ljava/lang/String;Ljava/lang/String;[Ljava/lang/Object;)V
    //   3652: goto -53 -> 3599
    //   3655: new 935	com/tencent/mm/pointers/PByteArray
    //   3658: dup
    //   3659: invokespecial 936	com/tencent/mm/pointers/PByteArray:<init>	()V
    //   3662: astore 12
    //   3664: aload_1
    //   3665: invokestatic 99	com/tencent/mm/sdk/platformtools/ay:kz	(Ljava/lang/String;)Z
    //   3668: ifne +27 -> 3695
    //   3671: aload 15
    //   3673: invokestatic 926	com/tencent/mm/sdk/platformtools/ay:J	([B)Z
    //   3676: ifne +19 -> 3695
    //   3679: aload 14
    //   3681: invokestatic 926	com/tencent/mm/sdk/platformtools/ay:J	([B)Z
    //   3684: ifne +11 -> 3695
    //   3687: aload 11
    //   3689: invokestatic 926	com/tencent/mm/sdk/platformtools/ay:J	([B)Z
    //   3692: ifeq +227 -> 3919
    //   3695: aload_1
    //   3696: ifnonnull +192 -> 3888
    //   3699: iconst_m1
    //   3700: istore_2
    //   3701: aload 15
    //   3703: ifnonnull +193 -> 3896
    //   3706: iconst_m1
    //   3707: istore_3
    //   3708: aload 14
    //   3710: ifnonnull +193 -> 3903
    //   3713: iconst_m1
    //   3714: istore 4
    //   3716: aload 11
    //   3718: ifnonnull +193 -> 3911
    //   3721: iconst_m1
    //   3722: istore 5
    //   3724: ldc 52
    //   3726: ldc_w 938
    //   3729: iconst_4
    //   3730: anewarray 4	java/lang/Object
    //   3733: dup
    //   3734: iconst_0
    //   3735: iload_2
    //   3736: invokestatic 72	java/lang/Integer:valueOf	(I)Ljava/lang/Integer;
    //   3739: aastore
    //   3740: dup
    //   3741: iconst_1
    //   3742: iload_3
    //   3743: invokestatic 72	java/lang/Integer:valueOf	(I)Ljava/lang/Integer;
    //   3746: aastore
    //   3747: dup
    //   3748: iconst_2
    //   3749: iload 4
    //   3751: invokestatic 72	java/lang/Integer:valueOf	(I)Ljava/lang/Integer;
    //   3754: aastore
    //   3755: dup
    //   3756: iconst_3
    //   3757: iload 5
    //   3759: invokestatic 72	java/lang/Integer:valueOf	(I)Ljava/lang/Integer;
    //   3762: aastore
    //   3763: invokestatic 132	com/tencent/mm/sdk/platformtools/u:w	(Ljava/lang/String;Ljava/lang/String;[Ljava/lang/Object;)V
    //   3766: aload 12
    //   3768: getfield 942	com/tencent/mm/pointers/PByteArray:value	[B
    //   3771: astore_1
    //   3772: new 944	com/tencent/mm/protocal/b/aau
    //   3775: dup
    //   3776: invokespecial 945	com/tencent/mm/protocal/b/aau:<init>	()V
    //   3779: astore 11
    //   3781: aload 12
    //   3783: getfield 942	com/tencent/mm/pointers/PByteArray:value	[B
    //   3786: ifnull +154 -> 3940
    //   3789: aload 11
    //   3791: new 157	java/lang/String
    //   3794: dup
    //   3795: aload 12
    //   3797: getfield 942	com/tencent/mm/pointers/PByteArray:value	[B
    //   3800: invokespecial 948	java/lang/String:<init>	([B)V
    //   3803: putfield 951	com/tencent/mm/protocal/b/aau:fUt	Ljava/lang/String;
    //   3806: aload_1
    //   3807: ifnonnull +143 -> 3950
    //   3810: iconst_m1
    //   3811: istore_2
    //   3812: ldc 52
    //   3814: ldc_w 953
    //   3817: iconst_3
    //   3818: anewarray 4	java/lang/Object
    //   3821: dup
    //   3822: iconst_0
    //   3823: iload_2
    //   3824: invokestatic 72	java/lang/Integer:valueOf	(I)Ljava/lang/Integer;
    //   3827: aastore
    //   3828: dup
    //   3829: iconst_1
    //   3830: aload 11
    //   3832: getfield 951	com/tencent/mm/protocal/b/aau:fUt	Ljava/lang/String;
    //   3835: invokevirtual 275	java/lang/String:length	()I
    //   3838: invokestatic 72	java/lang/Integer:valueOf	(I)Ljava/lang/Integer;
    //   3841: aastore
    //   3842: dup
    //   3843: iconst_2
    //   3844: aload 11
    //   3846: getfield 951	com/tencent/mm/protocal/b/aau:fUt	Ljava/lang/String;
    //   3849: invokevirtual 899	java/lang/String:getBytes	()[B
    //   3852: invokestatic 959	com/tencent/mm/a/g:m	([B)Ljava/lang/String;
    //   3855: aastore
    //   3856: invokestatic 76	com/tencent/mm/sdk/platformtools/u:i	(Ljava/lang/String;Ljava/lang/String;[Ljava/lang/Object;)V
    //   3859: aload 11
    //   3861: aload 13
    //   3863: putfield 962	com/tencent/mm/protocal/b/aau:jwZ	Ljava/lang/String;
    //   3866: invokestatic 305	com/tencent/mm/model/ah:tD	()Lcom/tencent/mm/model/c;
    //   3869: invokevirtual 966	com/tencent/mm/model/c:rp	()Lcom/tencent/mm/ag/c;
    //   3872: new 968	com/tencent/mm/ag/b$a
    //   3875: dup
    //   3876: bipush 59
    //   3878: aload 11
    //   3880: invokespecial 971	com/tencent/mm/ag/b$a:<init>	(ILcom/tencent/mm/at/a;)V
    //   3883: invokevirtual 976	com/tencent/mm/ag/c:b	(Lcom/tencent/mm/ag/b$q;)V
    //   3886: aconst_null
    //   3887: areturn
    //   3888: aload_1
    //   3889: invokevirtual 275	java/lang/String:length	()I
    //   3892: istore_2
    //   3893: goto -192 -> 3701
    //   3896: aload 15
    //   3898: arraylength
    //   3899: istore_3
    //   3900: goto -192 -> 3708
    //   3903: aload 14
    //   3905: arraylength
    //   3906: istore 4
    //   3908: goto -192 -> 3716
    //   3911: aload 11
    //   3913: arraylength
    //   3914: istore 5
    //   3916: goto -192 -> 3724
    //   3919: invokestatic 305	com/tencent/mm/model/ah:tD	()Lcom/tencent/mm/model/c;
    //   3922: getfield 979	com/tencent/mm/model/c:uin	I
    //   3925: aload_1
    //   3926: aload 14
    //   3928: aload 15
    //   3930: aload 11
    //   3932: aload 12
    //   3934: invokestatic 985	com/tencent/mm/protocal/MMProtocalJni:genClientCheckKVRes	(ILjava/lang/String;[B[B[BLcom/tencent/mm/pointers/PByteArray;)V
    //   3937: goto -171 -> 3766
    //   3940: aload 11
    //   3942: ldc -24
    //   3944: putfield 951	com/tencent/mm/protocal/b/aau:fUt	Ljava/lang/String;
    //   3947: goto -141 -> 3806
    //   3950: aload_1
    //   3951: arraylength
    //   3952: istore_2
    //   3953: goto -141 -> 3812
    //   3956: aload 14
    //   3958: ifnull +299 -> 4257
    //   3961: aload 14
    //   3963: ldc_w 987
    //   3966: invokevirtual 196	java/lang/String:equals	(Ljava/lang/Object;)Z
    //   3969: ifeq +288 -> 4257
    //   3972: aload 13
    //   3974: ldc_w 989
    //   3977: invokeinterface 44 2 0
    //   3982: checkcast 157	java/lang/String
    //   3985: astore 11
    //   3987: aload 13
    //   3989: ldc_w 991
    //   3992: invokeinterface 44 2 0
    //   3997: pop
    //   3998: aload 13
    //   4000: ldc_w 993
    //   4003: invokeinterface 44 2 0
    //   4008: checkcast 157	java/lang/String
    //   4011: astore_1
    //   4012: aload 11
    //   4014: invokestatic 998	com/tencent/mm/t/f:gs	(Ljava/lang/String;)J
    //   4017: lstore 7
    //   4019: lload 7
    //   4021: ldc2_w 26
    //   4024: lcmp
    //   4025: ifne +22 -> 4047
    //   4028: ldc 52
    //   4030: ldc_w 1000
    //   4033: iconst_1
    //   4034: anewarray 4	java/lang/Object
    //   4037: dup
    //   4038: iconst_0
    //   4039: aload 11
    //   4041: aastore
    //   4042: invokestatic 76	com/tencent/mm/sdk/platformtools/u:i	(Ljava/lang/String;Ljava/lang/String;[Ljava/lang/Object;)V
    //   4045: aconst_null
    //   4046: areturn
    //   4047: invokestatic 1006	com/tencent/mm/t/aj:xI	()Lcom/tencent/mm/t/c;
    //   4050: lload 7
    //   4052: invokevirtual 1012	com/tencent/mm/t/c:K	(J)Lcom/tencent/mm/t/b;
    //   4055: getfield 1017	com/tencent/mm/t/b:field_newUnReadCount	I
    //   4058: istore_2
    //   4059: invokestatic 1006	com/tencent/mm/t/aj:xI	()Lcom/tencent/mm/t/c;
    //   4062: lload 7
    //   4064: invokevirtual 1021	com/tencent/mm/t/c:M	(J)Z
    //   4067: pop
    //   4068: invokestatic 1025	com/tencent/mm/t/aj:xH	()Lcom/tencent/mm/t/e;
    //   4071: lload 7
    //   4073: invokevirtual 1031	com/tencent/mm/t/e:Q	(J)Lcom/tencent/mm/t/d;
    //   4076: astore 11
    //   4078: invokestatic 305	com/tencent/mm/model/ah:tD	()Lcom/tencent/mm/model/c;
    //   4081: invokevirtual 426	com/tencent/mm/model/c:rt	()Lcom/tencent/mm/storage/s;
    //   4084: aload_1
    //   4085: invokevirtual 436	com/tencent/mm/storage/s:EA	(Ljava/lang/String;)Lcom/tencent/mm/storage/r;
    //   4088: astore 12
    //   4090: aload 12
    //   4092: ifnonnull +21 -> 4113
    //   4095: ldc 52
    //   4097: ldc_w 1033
    //   4100: iconst_1
    //   4101: anewarray 4	java/lang/Object
    //   4104: dup
    //   4105: iconst_0
    //   4106: aload_1
    //   4107: aastore
    //   4108: invokestatic 132	com/tencent/mm/sdk/platformtools/u:w	(Ljava/lang/String;Ljava/lang/String;[Ljava/lang/Object;)V
    //   4111: aconst_null
    //   4112: areturn
    //   4113: aload 11
    //   4115: iconst_1
    //   4116: invokevirtual 1039	com/tencent/mm/t/d:cU	(I)Z
    //   4119: ifeq +72 -> 4191
    //   4122: aload 12
    //   4124: getfield 1042	com/tencent/mm/d/b/t:field_unReadMuteCount	I
    //   4127: iload_2
    //   4128: if_icmpgt +34 -> 4162
    //   4131: aload 12
    //   4133: iconst_0
    //   4134: invokevirtual 1045	com/tencent/mm/storage/r:bp	(I)V
    //   4137: invokestatic 305	com/tencent/mm/model/ah:tD	()Lcom/tencent/mm/model/c;
    //   4140: invokevirtual 426	com/tencent/mm/model/c:rt	()Lcom/tencent/mm/storage/s;
    //   4143: aload 12
    //   4145: aload_1
    //   4146: iconst_1
    //   4147: invokevirtual 456	com/tencent/mm/storage/s:a	(Lcom/tencent/mm/storage/r;Ljava/lang/String;Z)I
    //   4150: pop
    //   4151: invokestatic 720	com/tencent/mm/model/ah:kU	()Lcom/tencent/mm/model/y;
    //   4154: aload_1
    //   4155: invokeinterface 1048 2 0
    //   4160: aconst_null
    //   4161: areturn
    //   4162: aload 12
    //   4164: aload 12
    //   4166: getfield 1042	com/tencent/mm/d/b/t:field_unReadMuteCount	I
    //   4169: iload_2
    //   4170: isub
    //   4171: invokevirtual 1045	com/tencent/mm/storage/r:bp	(I)V
    //   4174: invokestatic 305	com/tencent/mm/model/ah:tD	()Lcom/tencent/mm/model/c;
    //   4177: invokevirtual 426	com/tencent/mm/model/c:rt	()Lcom/tencent/mm/storage/s;
    //   4180: aload 12
    //   4182: aload_1
    //   4183: iconst_1
    //   4184: invokevirtual 456	com/tencent/mm/storage/s:a	(Lcom/tencent/mm/storage/r;Ljava/lang/String;Z)I
    //   4187: pop
    //   4188: goto -28 -> 4160
    //   4191: aload 12
    //   4193: getfield 441	com/tencent/mm/d/b/t:field_unReadCount	I
    //   4196: iload_2
    //   4197: if_icmpgt +25 -> 4222
    //   4200: invokestatic 305	com/tencent/mm/model/ah:tD	()Lcom/tencent/mm/model/c;
    //   4203: invokevirtual 426	com/tencent/mm/model/c:rt	()Lcom/tencent/mm/storage/s;
    //   4206: aload_1
    //   4207: invokevirtual 1051	com/tencent/mm/storage/s:EC	(Ljava/lang/String;)Z
    //   4210: pop
    //   4211: invokestatic 720	com/tencent/mm/model/ah:kU	()Lcom/tencent/mm/model/y;
    //   4214: aload_1
    //   4215: invokeinterface 1048 2 0
    //   4220: aconst_null
    //   4221: areturn
    //   4222: aload 12
    //   4224: iconst_0
    //   4225: invokevirtual 1054	com/tencent/mm/storage/r:bo	(I)V
    //   4228: aload 12
    //   4230: aload 12
    //   4232: getfield 441	com/tencent/mm/d/b/t:field_unReadCount	I
    //   4235: iload_2
    //   4236: isub
    //   4237: invokevirtual 450	com/tencent/mm/storage/r:bi	(I)V
    //   4240: invokestatic 305	com/tencent/mm/model/ah:tD	()Lcom/tencent/mm/model/c;
    //   4243: invokevirtual 426	com/tencent/mm/model/c:rt	()Lcom/tencent/mm/storage/s;
    //   4246: aload 12
    //   4248: aload_1
    //   4249: iconst_1
    //   4250: invokevirtual 456	com/tencent/mm/storage/s:a	(Lcom/tencent/mm/storage/r;Ljava/lang/String;Z)I
    //   4253: pop
    //   4254: goto -34 -> 4220
    //   4257: aload 14
    //   4259: ifnull +117 -> 4376
    //   4262: aload 14
    //   4264: ldc_w 1056
    //   4267: invokevirtual 196	java/lang/String:equals	(Ljava/lang/Object;)Z
    //   4270: ifeq +106 -> 4376
    //   4273: aload 13
    //   4275: ldc_w 989
    //   4278: invokeinterface 44 2 0
    //   4283: checkcast 157	java/lang/String
    //   4286: astore_1
    //   4287: aload 13
    //   4289: ldc_w 1058
    //   4292: invokeinterface 44 2 0
    //   4297: checkcast 157	java/lang/String
    //   4300: astore 12
    //   4302: aload 13
    //   4304: ldc_w 993
    //   4307: invokeinterface 44 2 0
    //   4312: pop
    //   4313: invokestatic 1025	com/tencent/mm/t/aj:xH	()Lcom/tencent/mm/t/e;
    //   4316: aload_1
    //   4317: invokevirtual 1062	com/tencent/mm/t/e:go	(Ljava/lang/String;)Lcom/tencent/mm/t/d;
    //   4320: astore 15
    //   4322: aload 15
    //   4324: ifnonnull +21 -> 4345
    //   4327: ldc 52
    //   4329: ldc_w 1064
    //   4332: iconst_1
    //   4333: anewarray 4	java/lang/Object
    //   4336: dup
    //   4337: iconst_0
    //   4338: aload_1
    //   4339: aastore
    //   4340: invokestatic 76	com/tencent/mm/sdk/platformtools/u:i	(Ljava/lang/String;Ljava/lang/String;[Ljava/lang/Object;)V
    //   4343: aconst_null
    //   4344: areturn
    //   4345: aload 15
    //   4347: getfield 1067	com/tencent/mm/t/d:field_chatVersion	I
    //   4350: aload 12
    //   4352: ldc_w 1068
    //   4355: invokestatic 242	com/tencent/mm/sdk/platformtools/ay:getInt	(Ljava/lang/String;I)I
    //   4358: if_icmpge +18 -> 4376
    //   4361: aload 15
    //   4363: iconst_1
    //   4364: putfield 1071	com/tencent/mm/t/d:field_needToUpdate	Z
    //   4367: invokestatic 1025	com/tencent/mm/t/aj:xH	()Lcom/tencent/mm/t/e;
    //   4370: aload 15
    //   4372: invokevirtual 1074	com/tencent/mm/t/e:b	(Lcom/tencent/mm/t/d;)Z
    //   4375: pop
    //   4376: aload 14
    //   4378: ifnull +232 -> 4610
    //   4381: aload 14
    //   4383: ldc_w 1076
    //   4386: invokevirtual 196	java/lang/String:equals	(Ljava/lang/Object;)Z
    //   4389: ifeq +221 -> 4610
    //   4392: aload 13
    //   4394: ldc_w 1078
    //   4397: invokeinterface 44 2 0
    //   4402: checkcast 157	java/lang/String
    //   4405: iconst_0
    //   4406: invokestatic 242	com/tencent/mm/sdk/platformtools/ay:getInt	(Ljava/lang/String;I)I
    //   4409: istore_2
    //   4410: aload 13
    //   4412: ldc_w 1080
    //   4415: invokeinterface 44 2 0
    //   4420: checkcast 157	java/lang/String
    //   4423: invokestatic 1083	com/tencent/mm/sdk/platformtools/ay:ky	(Ljava/lang/String;)Ljava/lang/String;
    //   4426: astore 11
    //   4428: aload 13
    //   4430: ldc_w 1085
    //   4433: invokeinterface 44 2 0
    //   4438: checkcast 157	java/lang/String
    //   4441: invokestatic 1083	com/tencent/mm/sdk/platformtools/ay:ky	(Ljava/lang/String;)Ljava/lang/String;
    //   4444: astore_1
    //   4445: new 157	java/lang/String
    //   4448: dup
    //   4449: aload 11
    //   4451: invokevirtual 899	java/lang/String:getBytes	()[B
    //   4454: iconst_0
    //   4455: invokestatic 1091	android/util/Base64:decode	([BI)[B
    //   4458: invokespecial 948	java/lang/String:<init>	([B)V
    //   4461: astore 11
    //   4463: new 157	java/lang/String
    //   4466: dup
    //   4467: invokestatic 1096	com/tencent/mm/compatible/d/p:ox	()Ljava/lang/String;
    //   4470: invokevirtual 899	java/lang/String:getBytes	()[B
    //   4473: invokestatic 1102	com/tencent/mm/at/b:aH	([B)Lcom/tencent/mm/at/b;
    //   4476: bipush 16
    //   4478: invokevirtual 1106	com/tencent/mm/at/b:oQ	(I)Lcom/tencent/mm/at/b;
    //   4481: getfield 1109	com/tencent/mm/at/b:iTS	[B
    //   4484: invokespecial 948	java/lang/String:<init>	([B)V
    //   4487: astore 12
    //   4489: ldc 52
    //   4491: ldc_w 1111
    //   4494: iconst_4
    //   4495: anewarray 4	java/lang/Object
    //   4498: dup
    //   4499: iconst_0
    //   4500: iload_2
    //   4501: invokestatic 72	java/lang/Integer:valueOf	(I)Ljava/lang/Integer;
    //   4504: aastore
    //   4505: dup
    //   4506: iconst_1
    //   4507: aload 11
    //   4509: aastore
    //   4510: dup
    //   4511: iconst_2
    //   4512: aload 12
    //   4514: aastore
    //   4515: dup
    //   4516: iconst_3
    //   4517: aload_1
    //   4518: aastore
    //   4519: invokestatic 76	com/tencent/mm/sdk/platformtools/u:i	(Ljava/lang/String;Ljava/lang/String;[Ljava/lang/Object;)V
    //   4522: aload 11
    //   4524: invokestatic 99	com/tencent/mm/sdk/platformtools/ay:kz	(Ljava/lang/String;)Z
    //   4527: ifne +13 -> 4540
    //   4530: aload 11
    //   4532: aload 12
    //   4534: invokevirtual 196	java/lang/String:equals	(Ljava/lang/Object;)Z
    //   4537: ifeq +65 -> 4602
    //   4540: invokestatic 305	com/tencent/mm/model/ah:tD	()Lcom/tencent/mm/model/c;
    //   4543: invokevirtual 347	com/tencent/mm/model/c:rn	()Lcom/tencent/mm/storage/h;
    //   4546: getstatic 1117	com/tencent/mm/storage/j$a:kch	Lcom/tencent/mm/storage/j$a;
    //   4549: iconst_1
    //   4550: invokestatic 512	java/lang/Boolean:valueOf	(Z)Ljava/lang/Boolean;
    //   4553: invokevirtual 1120	com/tencent/mm/storage/h:b	(Lcom/tencent/mm/storage/j$a;Ljava/lang/Object;)V
    //   4556: invokestatic 305	com/tencent/mm/model/ah:tD	()Lcom/tencent/mm/model/c;
    //   4559: invokevirtual 347	com/tencent/mm/model/c:rn	()Lcom/tencent/mm/storage/h;
    //   4562: astore 11
    //   4564: getstatic 1123	com/tencent/mm/storage/j$a:kci	Lcom/tencent/mm/storage/j$a;
    //   4567: astore 12
    //   4569: iload_2
    //   4570: iconst_1
    //   4571: if_icmpne +33 -> 4604
    //   4574: iconst_1
    //   4575: istore 6
    //   4577: aload 11
    //   4579: aload 12
    //   4581: iload 6
    //   4583: invokestatic 512	java/lang/Boolean:valueOf	(Z)Ljava/lang/Boolean;
    //   4586: invokevirtual 1120	com/tencent/mm/storage/h:b	(Lcom/tencent/mm/storage/j$a;Ljava/lang/Object;)V
    //   4589: invokestatic 305	com/tencent/mm/model/ah:tD	()Lcom/tencent/mm/model/c;
    //   4592: invokevirtual 347	com/tencent/mm/model/c:rn	()Lcom/tencent/mm/storage/h;
    //   4595: getstatic 1126	com/tencent/mm/storage/j$a:kcj	Lcom/tencent/mm/storage/j$a;
    //   4598: aload_1
    //   4599: invokevirtual 1120	com/tencent/mm/storage/h:b	(Lcom/tencent/mm/storage/j$a;Ljava/lang/Object;)V
    //   4602: aconst_null
    //   4603: areturn
    //   4604: iconst_0
    //   4605: istore 6
    //   4607: goto -30 -> 4577
    //   4610: aload 14
    //   4612: ifnull +262 -> 4874
    //   4615: aload 14
    //   4617: ldc_w 1128
    //   4620: invokevirtual 196	java/lang/String:equals	(Ljava/lang/Object;)Z
    //   4623: ifeq +251 -> 4874
    //   4626: new 1130	com/tencent/mm/protocal/b/afo
    //   4629: dup
    //   4630: invokespecial 1131	com/tencent/mm/protocal/b/afo:<init>	()V
    //   4633: astore_1
    //   4634: aload_1
    //   4635: aload 13
    //   4637: ldc_w 1133
    //   4640: invokeinterface 44 2 0
    //   4645: checkcast 157	java/lang/String
    //   4648: putfield 1136	com/tencent/mm/protocal/b/afo:jCX	Ljava/lang/String;
    //   4651: aload_1
    //   4652: aload 13
    //   4654: ldc_w 1138
    //   4657: invokeinterface 44 2 0
    //   4662: checkcast 157	java/lang/String
    //   4665: iconst_0
    //   4666: invokestatic 242	com/tencent/mm/sdk/platformtools/ay:getInt	(Ljava/lang/String;I)I
    //   4669: putfield 1141	com/tencent/mm/protocal/b/afo:jCY	I
    //   4672: aload_1
    //   4673: aload 13
    //   4675: ldc_w 1143
    //   4678: invokeinterface 44 2 0
    //   4683: checkcast 157	java/lang/String
    //   4686: iconst_0
    //   4687: invokestatic 242	com/tencent/mm/sdk/platformtools/ay:getInt	(Ljava/lang/String;I)I
    //   4690: putfield 1146	com/tencent/mm/protocal/b/afo:jCZ	I
    //   4693: aload_1
    //   4694: aload 13
    //   4696: ldc_w 1148
    //   4699: invokeinterface 44 2 0
    //   4704: checkcast 157	java/lang/String
    //   4707: iconst_0
    //   4708: invokestatic 242	com/tencent/mm/sdk/platformtools/ay:getInt	(Ljava/lang/String;I)I
    //   4711: putfield 1151	com/tencent/mm/protocal/b/afo:jdn	I
    //   4714: aload_1
    //   4715: aload_1
    //   4716: getfield 1136	com/tencent/mm/protocal/b/afo:jCX	Ljava/lang/String;
    //   4719: aload_1
    //   4720: getfield 1141	com/tencent/mm/protocal/b/afo:jCY	I
    //   4723: i2l
    //   4724: aload_1
    //   4725: getfield 1146	com/tencent/mm/protocal/b/afo:jCZ	I
    //   4728: i2l
    //   4729: invokestatic 1156	com/tencent/mm/model/at:a	(Ljava/lang/String;JJ)Ljava/lang/String;
    //   4732: putfield 1159	com/tencent/mm/protocal/b/afo:jDa	Ljava/lang/String;
    //   4735: aload_1
    //   4736: aload_1
    //   4737: getfield 1136	com/tencent/mm/protocal/b/afo:jCX	Ljava/lang/String;
    //   4740: invokestatic 1162	com/tencent/mm/model/at:fs	(Ljava/lang/String;)J
    //   4743: l2i
    //   4744: putfield 1165	com/tencent/mm/protocal/b/afo:jhy	I
    //   4747: invokestatic 1168	com/tencent/mm/model/at:checkMsgLevel	()Z
    //   4750: ifeq +511 -> 5261
    //   4753: iconst_1
    //   4754: istore_2
    //   4755: aload_1
    //   4756: iload_2
    //   4757: putfield 1171	com/tencent/mm/protocal/b/afo:jDb	I
    //   4760: aload_1
    //   4761: invokestatic 1176	com/tencent/mm/compatible/d/u:oN	()I
    //   4764: putfield 1179	com/tencent/mm/protocal/b/afo:jgx	I
    //   4767: aload_1
    //   4768: bipush 8
    //   4770: anewarray 4	java/lang/Object
    //   4773: dup
    //   4774: iconst_0
    //   4775: aload_1
    //   4776: getfield 1136	com/tencent/mm/protocal/b/afo:jCX	Ljava/lang/String;
    //   4779: aastore
    //   4780: dup
    //   4781: iconst_1
    //   4782: aload_1
    //   4783: getfield 1141	com/tencent/mm/protocal/b/afo:jCY	I
    //   4786: invokestatic 72	java/lang/Integer:valueOf	(I)Ljava/lang/Integer;
    //   4789: aastore
    //   4790: dup
    //   4791: iconst_2
    //   4792: aload_1
    //   4793: getfield 1146	com/tencent/mm/protocal/b/afo:jCZ	I
    //   4796: invokestatic 72	java/lang/Integer:valueOf	(I)Ljava/lang/Integer;
    //   4799: aastore
    //   4800: dup
    //   4801: iconst_3
    //   4802: aload_1
    //   4803: getfield 1151	com/tencent/mm/protocal/b/afo:jdn	I
    //   4806: invokestatic 72	java/lang/Integer:valueOf	(I)Ljava/lang/Integer;
    //   4809: aastore
    //   4810: dup
    //   4811: iconst_4
    //   4812: aload_1
    //   4813: getfield 1159	com/tencent/mm/protocal/b/afo:jDa	Ljava/lang/String;
    //   4816: aastore
    //   4817: dup
    //   4818: iconst_5
    //   4819: aload_1
    //   4820: getfield 1165	com/tencent/mm/protocal/b/afo:jhy	I
    //   4823: invokestatic 72	java/lang/Integer:valueOf	(I)Ljava/lang/Integer;
    //   4826: aastore
    //   4827: dup
    //   4828: bipush 6
    //   4830: aload_1
    //   4831: getfield 1171	com/tencent/mm/protocal/b/afo:jDb	I
    //   4834: invokestatic 72	java/lang/Integer:valueOf	(I)Ljava/lang/Integer;
    //   4837: aastore
    //   4838: dup
    //   4839: bipush 7
    //   4841: aload_1
    //   4842: getfield 1179	com/tencent/mm/protocal/b/afo:jgx	I
    //   4845: invokestatic 72	java/lang/Integer:valueOf	(I)Ljava/lang/Integer;
    //   4848: aastore
    //   4849: invokestatic 1182	com/tencent/mm/model/at:c	([Ljava/lang/Object;)Ljava/lang/String;
    //   4852: putfield 1185	com/tencent/mm/protocal/b/afo:jDc	Ljava/lang/String;
    //   4855: invokestatic 305	com/tencent/mm/model/ah:tD	()Lcom/tencent/mm/model/c;
    //   4858: invokevirtual 966	com/tencent/mm/model/c:rp	()Lcom/tencent/mm/ag/c;
    //   4861: new 968	com/tencent/mm/ag/b$a
    //   4864: dup
    //   4865: bipush 61
    //   4867: aload_1
    //   4868: invokespecial 971	com/tencent/mm/ag/b$a:<init>	(ILcom/tencent/mm/at/a;)V
    //   4871: invokevirtual 976	com/tencent/mm/ag/c:b	(Lcom/tencent/mm/ag/b$q;)V
    //   4874: aload 14
    //   4876: ifnull +137 -> 5013
    //   4879: aload 14
    //   4881: ldc_w 1187
    //   4884: invokevirtual 196	java/lang/String:equals	(Ljava/lang/Object;)Z
    //   4887: ifeq +126 -> 5013
    //   4890: new 1189	com/tencent/mm/protocal/b/afq
    //   4893: dup
    //   4894: invokespecial 1190	com/tencent/mm/protocal/b/afq:<init>	()V
    //   4897: astore_1
    //   4898: aload_1
    //   4899: aload 13
    //   4901: ldc_w 1192
    //   4904: invokeinterface 44 2 0
    //   4909: checkcast 157	java/lang/String
    //   4912: iconst_0
    //   4913: invokestatic 242	com/tencent/mm/sdk/platformtools/ay:getInt	(Ljava/lang/String;I)I
    //   4916: putfield 1193	com/tencent/mm/protocal/b/afq:jdn	I
    //   4919: aload_1
    //   4920: invokestatic 1196	com/tencent/mm/model/at:uq	()Ljava/lang/String;
    //   4923: putfield 1199	com/tencent/mm/protocal/b/afq:jDe	Ljava/lang/String;
    //   4926: invokestatic 1168	com/tencent/mm/model/at:checkMsgLevel	()Z
    //   4929: ifeq +337 -> 5266
    //   4932: iconst_1
    //   4933: istore_2
    //   4934: aload_1
    //   4935: iload_2
    //   4936: putfield 1200	com/tencent/mm/protocal/b/afq:jDb	I
    //   4939: aload_1
    //   4940: invokestatic 1176	com/tencent/mm/compatible/d/u:oN	()I
    //   4943: putfield 1201	com/tencent/mm/protocal/b/afq:jgx	I
    //   4946: aload_1
    //   4947: iconst_4
    //   4948: anewarray 4	java/lang/Object
    //   4951: dup
    //   4952: iconst_0
    //   4953: aload_1
    //   4954: getfield 1193	com/tencent/mm/protocal/b/afq:jdn	I
    //   4957: invokestatic 72	java/lang/Integer:valueOf	(I)Ljava/lang/Integer;
    //   4960: aastore
    //   4961: dup
    //   4962: iconst_1
    //   4963: aload_1
    //   4964: getfield 1199	com/tencent/mm/protocal/b/afq:jDe	Ljava/lang/String;
    //   4967: aastore
    //   4968: dup
    //   4969: iconst_2
    //   4970: aload_1
    //   4971: getfield 1200	com/tencent/mm/protocal/b/afq:jDb	I
    //   4974: invokestatic 72	java/lang/Integer:valueOf	(I)Ljava/lang/Integer;
    //   4977: aastore
    //   4978: dup
    //   4979: iconst_3
    //   4980: aload_1
    //   4981: getfield 1201	com/tencent/mm/protocal/b/afq:jgx	I
    //   4984: invokestatic 72	java/lang/Integer:valueOf	(I)Ljava/lang/Integer;
    //   4987: aastore
    //   4988: invokestatic 1182	com/tencent/mm/model/at:c	([Ljava/lang/Object;)Ljava/lang/String;
    //   4991: putfield 1202	com/tencent/mm/protocal/b/afq:jDc	Ljava/lang/String;
    //   4994: invokestatic 305	com/tencent/mm/model/ah:tD	()Lcom/tencent/mm/model/c;
    //   4997: invokevirtual 966	com/tencent/mm/model/c:rp	()Lcom/tencent/mm/ag/c;
    //   5000: new 968	com/tencent/mm/ag/b$a
    //   5003: dup
    //   5004: bipush 62
    //   5006: aload_1
    //   5007: invokespecial 971	com/tencent/mm/ag/b$a:<init>	(ILcom/tencent/mm/at/a;)V
    //   5010: invokevirtual 976	com/tencent/mm/ag/c:b	(Lcom/tencent/mm/ag/b$q;)V
    //   5013: aload 14
    //   5015: ifnull +137 -> 5152
    //   5018: aload 14
    //   5020: ldc_w 1204
    //   5023: invokevirtual 196	java/lang/String:equals	(Ljava/lang/Object;)Z
    //   5026: ifeq +126 -> 5152
    //   5029: new 1206	com/tencent/mm/protocal/b/afp
    //   5032: dup
    //   5033: invokespecial 1207	com/tencent/mm/protocal/b/afp:<init>	()V
    //   5036: astore_1
    //   5037: aload_1
    //   5038: aload 13
    //   5040: ldc_w 1209
    //   5043: invokeinterface 44 2 0
    //   5048: checkcast 157	java/lang/String
    //   5051: iconst_0
    //   5052: invokestatic 242	com/tencent/mm/sdk/platformtools/ay:getInt	(Ljava/lang/String;I)I
    //   5055: putfield 1210	com/tencent/mm/protocal/b/afp:jdn	I
    //   5058: aload_1
    //   5059: invokestatic 1213	com/tencent/mm/model/at:ur	()Ljava/lang/String;
    //   5062: putfield 1216	com/tencent/mm/protocal/b/afp:jDd	Ljava/lang/String;
    //   5065: invokestatic 1168	com/tencent/mm/model/at:checkMsgLevel	()Z
    //   5068: ifeq +203 -> 5271
    //   5071: iconst_1
    //   5072: istore_2
    //   5073: aload_1
    //   5074: iload_2
    //   5075: putfield 1217	com/tencent/mm/protocal/b/afp:jDb	I
    //   5078: aload_1
    //   5079: invokestatic 1176	com/tencent/mm/compatible/d/u:oN	()I
    //   5082: putfield 1218	com/tencent/mm/protocal/b/afp:jgx	I
    //   5085: aload_1
    //   5086: iconst_4
    //   5087: anewarray 4	java/lang/Object
    //   5090: dup
    //   5091: iconst_0
    //   5092: aload_1
    //   5093: getfield 1210	com/tencent/mm/protocal/b/afp:jdn	I
    //   5096: invokestatic 72	java/lang/Integer:valueOf	(I)Ljava/lang/Integer;
    //   5099: aastore
    //   5100: dup
    //   5101: iconst_1
    //   5102: aload_1
    //   5103: getfield 1216	com/tencent/mm/protocal/b/afp:jDd	Ljava/lang/String;
    //   5106: aastore
    //   5107: dup
    //   5108: iconst_2
    //   5109: aload_1
    //   5110: getfield 1217	com/tencent/mm/protocal/b/afp:jDb	I
    //   5113: invokestatic 72	java/lang/Integer:valueOf	(I)Ljava/lang/Integer;
    //   5116: aastore
    //   5117: dup
    //   5118: iconst_3
    //   5119: aload_1
    //   5120: getfield 1218	com/tencent/mm/protocal/b/afp:jgx	I
    //   5123: invokestatic 72	java/lang/Integer:valueOf	(I)Ljava/lang/Integer;
    //   5126: aastore
    //   5127: invokestatic 1182	com/tencent/mm/model/at:c	([Ljava/lang/Object;)Ljava/lang/String;
    //   5130: putfield 1219	com/tencent/mm/protocal/b/afp:jDc	Ljava/lang/String;
    //   5133: invokestatic 305	com/tencent/mm/model/ah:tD	()Lcom/tencent/mm/model/c;
    //   5136: invokevirtual 966	com/tencent/mm/model/c:rp	()Lcom/tencent/mm/ag/c;
    //   5139: new 968	com/tencent/mm/ag/b$a
    //   5142: dup
    //   5143: bipush 63
    //   5145: aload_1
    //   5146: invokespecial 971	com/tencent/mm/ag/b$a:<init>	(ILcom/tencent/mm/at/a;)V
    //   5149: invokevirtual 976	com/tencent/mm/ag/c:b	(Lcom/tencent/mm/ag/b$q;)V
    //   5152: aload 14
    //   5154: ifnull +104 -> 5258
    //   5157: aload 14
    //   5159: ldc_w 1221
    //   5162: invokevirtual 196	java/lang/String:equals	(Ljava/lang/Object;)Z
    //   5165: ifeq +93 -> 5258
    //   5168: aload 13
    //   5170: ldc_w 1223
    //   5173: invokeinterface 44 2 0
    //   5178: checkcast 157	java/lang/String
    //   5181: iconst_0
    //   5182: invokestatic 242	com/tencent/mm/sdk/platformtools/ay:getInt	(Ljava/lang/String;I)I
    //   5185: istore_2
    //   5186: aload 13
    //   5188: ldc_w 1225
    //   5191: invokeinterface 44 2 0
    //   5196: checkcast 157	java/lang/String
    //   5199: iconst_m1
    //   5200: invokestatic 242	com/tencent/mm/sdk/platformtools/ay:getInt	(Ljava/lang/String;I)I
    //   5203: istore_3
    //   5204: ldc 52
    //   5206: ldc_w 1227
    //   5209: iconst_1
    //   5210: anewarray 4	java/lang/Object
    //   5213: dup
    //   5214: iconst_0
    //   5215: iload_2
    //   5216: invokestatic 72	java/lang/Integer:valueOf	(I)Ljava/lang/Integer;
    //   5219: aastore
    //   5220: invokestatic 76	com/tencent/mm/sdk/platformtools/u:i	(Ljava/lang/String;Ljava/lang/String;[Ljava/lang/Object;)V
    //   5223: iload_3
    //   5224: ifne +58 -> 5282
    //   5227: invokestatic 305	com/tencent/mm/model/ah:tD	()Lcom/tencent/mm/model/c;
    //   5230: invokevirtual 347	com/tencent/mm/model/c:rn	()Lcom/tencent/mm/storage/h;
    //   5233: astore_1
    //   5234: getstatic 1230	com/tencent/mm/storage/j$a:kcw	Lcom/tencent/mm/storage/j$a;
    //   5237: astore 12
    //   5239: iload_2
    //   5240: iconst_1
    //   5241: if_icmpne +35 -> 5276
    //   5244: iconst_1
    //   5245: istore 6
    //   5247: aload_1
    //   5248: aload 12
    //   5250: iload 6
    //   5252: invokestatic 512	java/lang/Boolean:valueOf	(Z)Ljava/lang/Boolean;
    //   5255: invokevirtual 1120	com/tencent/mm/storage/h:b	(Lcom/tencent/mm/storage/j$a;Ljava/lang/Object;)V
    //   5258: aload 11
    //   5260: areturn
    //   5261: iconst_0
    //   5262: istore_2
    //   5263: goto -508 -> 4755
    //   5266: iconst_0
    //   5267: istore_2
    //   5268: goto -334 -> 4934
    //   5271: iconst_0
    //   5272: istore_2
    //   5273: goto -200 -> 5073
    //   5276: iconst_0
    //   5277: istore 6
    //   5279: goto -32 -> 5247
    //   5282: iconst_1
    //   5283: iload_3
    //   5284: if_icmpne -26 -> 5258
    //   5287: invokestatic 305	com/tencent/mm/model/ah:tD	()Lcom/tencent/mm/model/c;
    //   5290: invokevirtual 347	com/tencent/mm/model/c:rn	()Lcom/tencent/mm/storage/h;
    //   5293: astore_1
    //   5294: getstatic 1233	com/tencent/mm/storage/j$a:kcx	Lcom/tencent/mm/storage/j$a;
    //   5297: astore 12
    //   5299: iload_2
    //   5300: iconst_1
    //   5301: if_icmpne +20 -> 5321
    //   5304: iconst_1
    //   5305: istore 6
    //   5307: aload_1
    //   5308: aload 12
    //   5310: iload 6
    //   5312: invokestatic 512	java/lang/Boolean:valueOf	(Z)Ljava/lang/Boolean;
    //   5315: invokevirtual 1120	com/tencent/mm/storage/h:b	(Lcom/tencent/mm/storage/j$a;Ljava/lang/Object;)V
    //   5318: goto -60 -> 5258
    //   5321: iconst_0
    //   5322: istore 6
    //   5324: goto -17 -> 5307
    //   5327: goto -1806 -> 3521
    //   5330: goto -3063 -> 2267
    //   5333: iconst_0
    //   5334: istore 6
    //   5336: goto -4720 -> 616
    // Local variable table:
    //   start	length	slot	name	signature
    //   0	5339	0	this	bd
    //   0	5339	1	parama	c.a
    //   330	4972	2	i	int
    //   1755	3530	3	j	int
    //   3714	193	4	k	int
    //   3722	193	5	m	int
    //   614	4721	6	bool	boolean
    //   865	3207	7	l1	long
    //   872	752	9	l2	long
    //   64	5195	11	localObject1	Object
    //   208	897	12	localObject2	Object
    //   1365	5	12	localException1	Exception
    //   1380	5	12	localException2	Exception
    //   1395	211	12	localException3	Exception
    //   1721	1444	12	localObject3	Object
    //   3297	14	12	localException4	Exception
    //   3318	278	12	localObject4	Object
    //   3630	14	12	localException5	Exception
    //   3662	1647	12	localObject5	Object
    //   144	5043	13	localObject6	Object
    //   171	4987	14	localObject7	Object
    //   110	4261	15	localObject8	Object
    //   4	3443	16	localObject9	Object
    //   426	3002	17	localObject10	Object
    //   441	2998	18	str	String
    //   2711	679	19	localObject11	Object
    //   2716	341	20	localObject12	Object
    //   2747	368	21	localObject13	Object
    // Exception table:
    //   from	to	target	type
    //   456	488	1365	java/lang/Exception
    //   528	541	1380	java/lang/Exception
    //   602	613	1395	java/lang/Exception
    //   616	638	1395	java/lang/Exception
    //   867	874	1637	java/lang/Exception
    //   878	893	1637	java/lang/Exception
    //   897	904	1637	java/lang/Exception
    //   908	915	1637	java/lang/Exception
    //   919	927	1637	java/lang/Exception
    //   931	937	1637	java/lang/Exception
    //   941	957	1637	java/lang/Exception
    //   961	977	1637	java/lang/Exception
    //   986	994	1637	java/lang/Exception
    //   998	1010	1637	java/lang/Exception
    //   1014	1023	1637	java/lang/Exception
    //   1027	1039	1637	java/lang/Exception
    //   1043	1061	1637	java/lang/Exception
    //   1069	1076	1637	java/lang/Exception
    //   1080	1089	1637	java/lang/Exception
    //   1093	1100	1637	java/lang/Exception
    //   1104	1114	1637	java/lang/Exception
    //   1118	1138	1637	java/lang/Exception
    //   1142	1149	1637	java/lang/Exception
    //   1153	1164	1637	java/lang/Exception
    //   1168	1177	1637	java/lang/Exception
    //   1181	1194	1637	java/lang/Exception
    //   1198	1211	1637	java/lang/Exception
    //   1215	1225	1637	java/lang/Exception
    //   1229	1269	1637	java/lang/Exception
    //   1430	1450	1637	java/lang/Exception
    //   1454	1471	1637	java/lang/Exception
    //   1475	1486	1637	java/lang/Exception
    //   1490	1500	1637	java/lang/Exception
    //   1508	1515	1637	java/lang/Exception
    //   1519	1539	1637	java/lang/Exception
    //   1543	1554	1637	java/lang/Exception
    //   1560	1568	1637	java/lang/Exception
    //   1572	1584	1637	java/lang/Exception
    //   1588	1597	1637	java/lang/Exception
    //   1601	1610	1637	java/lang/Exception
    //   1614	1623	1637	java/lang/Exception
    //   1627	1635	1637	java/lang/Exception
    //   1802	1817	1910	java/lang/Exception
    //   1822	1830	1910	java/lang/Exception
    //   1830	1838	1910	java/lang/Exception
    //   1865	1872	1910	java/lang/Exception
    //   1872	1894	1910	java/lang/Exception
    //   1899	1907	1910	java/lang/Exception
    //   1938	1982	1910	java/lang/Exception
    //   1985	2025	1910	java/lang/Exception
    //   2030	2050	1910	java/lang/Exception
    //   2050	2101	1910	java/lang/Exception
    //   2109	2165	1910	java/lang/Exception
    //   2170	2229	1910	java/lang/Exception
    //   3072	3132	3297	java/lang/Exception
    //   3577	3595	3630	java/lang/Exception
  }
  
  public final void b(String paramString, b paramb, boolean paramBoolean)
  {
    if ((ay.kz(paramString)) || (paramb == null)) {
      return;
    }
    if (paramBoolean) {}
    for (Map localMap = bCW;; localMap = bCV)
    {
      paramString = (List)localMap.get(paramString);
      if (paramString == null) {
        break;
      }
      paramString.remove(paramb);
      return;
    }
  }
  
  public final void d(ag paramag) {}
  
  public static abstract interface a
  {
    public abstract void aX(String paramString);
  }
  
  public static abstract interface b
  {
    public abstract void a(c.a parama);
  }
}

/* Location:
 * Qualified Name:     com.tencent.mm.model.bd
 * Java Class Version: 6 (50.0)
 * JD-Core Version:    0.7.1
 */