package com.tencent.mm.model;

final class cc
  implements Runnable
{
  /* Error */
  public final void run()
  {
    // Byte code:
    //   0: invokestatic 20	com/tencent/mm/model/ax:qZ	()Z
    //   3: ifne +4 -> 7
    //   6: return
    //   7: invokestatic 26	java/lang/System:currentTimeMillis	()J
    //   10: lstore_2
    //   11: invokestatic 32	com/tencent/mm/sdk/platformtools/aa:getContext	()Landroid/content/Context;
    //   14: astore 7
    //   16: aload 7
    //   18: invokevirtual 38	android/content/Context:getApplicationInfo	()Landroid/content/pm/ApplicationInfo;
    //   21: getfield 44	android/content/pm/ApplicationInfo:sourceDir	Ljava/lang/String;
    //   24: astore 8
    //   26: aload 8
    //   28: invokestatic 48	com/tencent/mm/model/ax:tl	()Lcom/tencent/mm/model/b;
    //   31: getfield 54	com/tencent/mm/model/b:uin	I
    //   34: invokestatic 60	com/tencent/mm/model/NorMsgSource:checkSoftType	(Ljava/lang/String;I)[B
    //   37: astore 6
    //   39: aload 7
    //   41: aload 8
    //   43: invokestatic 48	com/tencent/mm/model/ax:tl	()Lcom/tencent/mm/model/b;
    //   46: getfield 54	com/tencent/mm/model/b:uin	I
    //   49: invokestatic 64	com/tencent/mm/model/NorMsgSource:checkSoftType2	(Landroid/content/Context;Ljava/lang/String;I)[B
    //   52: astore 8
    //   54: invokestatic 26	java/lang/System:currentTimeMillis	()J
    //   57: lstore 4
    //   59: ldc 66
    //   61: iconst_1
    //   62: anewarray 4	java/lang/Object
    //   65: dup
    //   66: iconst_0
    //   67: aload 6
    //   69: iconst_0
    //   70: aload 6
    //   72: arraylength
    //   73: invokestatic 72	com/tencent/mm/model/ca:d	([BII)Ljava/lang/String;
    //   76: aastore
    //   77: invokestatic 78	java/lang/String:format	(Ljava/lang/String;[Ljava/lang/Object;)Ljava/lang/String;
    //   80: astore 7
    //   82: aload 7
    //   84: astore 6
    //   86: aload 8
    //   88: ifnull +137 -> 225
    //   91: aload 8
    //   93: arraylength
    //   94: bipush 8
    //   96: if_icmpne +249 -> 345
    //   99: aload 8
    //   101: iconst_0
    //   102: baload
    //   103: istore_1
    //   104: aload 8
    //   106: iconst_0
    //   107: aload 8
    //   109: iconst_3
    //   110: baload
    //   111: bastore
    //   112: aload 8
    //   114: iconst_3
    //   115: iload_1
    //   116: bastore
    //   117: aload 8
    //   119: iconst_1
    //   120: baload
    //   121: istore_1
    //   122: aload 8
    //   124: iconst_1
    //   125: aload 8
    //   127: iconst_2
    //   128: baload
    //   129: bastore
    //   130: aload 8
    //   132: iconst_2
    //   133: iload_1
    //   134: bastore
    //   135: aload 8
    //   137: iconst_4
    //   138: baload
    //   139: istore_1
    //   140: aload 8
    //   142: iconst_4
    //   143: aload 8
    //   145: bipush 7
    //   147: baload
    //   148: bastore
    //   149: aload 8
    //   151: bipush 7
    //   153: iload_1
    //   154: bastore
    //   155: aload 8
    //   157: iconst_5
    //   158: baload
    //   159: istore_1
    //   160: aload 8
    //   162: iconst_5
    //   163: aload 8
    //   165: bipush 6
    //   167: baload
    //   168: bastore
    //   169: aload 8
    //   171: bipush 6
    //   173: iload_1
    //   174: bastore
    //   175: new 80	java/lang/StringBuilder
    //   178: dup
    //   179: invokespecial 81	java/lang/StringBuilder:<init>	()V
    //   182: aload 7
    //   184: invokevirtual 85	java/lang/StringBuilder:append	(Ljava/lang/String;)Ljava/lang/StringBuilder;
    //   187: ldc 87
    //   189: iconst_2
    //   190: anewarray 4	java/lang/Object
    //   193: dup
    //   194: iconst_0
    //   195: aload 8
    //   197: iconst_0
    //   198: iconst_4
    //   199: invokestatic 72	com/tencent/mm/model/ca:d	([BII)Ljava/lang/String;
    //   202: aastore
    //   203: dup
    //   204: iconst_1
    //   205: aload 8
    //   207: iconst_4
    //   208: bipush 8
    //   210: invokestatic 72	com/tencent/mm/model/ca:d	([BII)Ljava/lang/String;
    //   213: aastore
    //   214: invokestatic 78	java/lang/String:format	(Ljava/lang/String;[Ljava/lang/Object;)Ljava/lang/String;
    //   217: invokevirtual 85	java/lang/StringBuilder:append	(Ljava/lang/String;)Ljava/lang/StringBuilder;
    //   220: invokevirtual 91	java/lang/StringBuilder:toString	()Ljava/lang/String;
    //   223: astore 6
    //   225: ldc 93
    //   227: invokestatic 99	java/net/Inet4Address:getByName	(Ljava/lang/String;)Ljava/net/InetAddress;
    //   230: invokevirtual 104	java/net/InetAddress:getHostAddress	()Ljava/lang/String;
    //   233: astore 7
    //   235: new 80	java/lang/StringBuilder
    //   238: dup
    //   239: invokespecial 81	java/lang/StringBuilder:<init>	()V
    //   242: aload 6
    //   244: invokevirtual 85	java/lang/StringBuilder:append	(Ljava/lang/String;)Ljava/lang/StringBuilder;
    //   247: ldc 106
    //   249: iconst_1
    //   250: anewarray 4	java/lang/Object
    //   253: dup
    //   254: iconst_0
    //   255: aload 7
    //   257: invokestatic 112	com/tencent/mm/sdk/platformtools/bn:iV	(Ljava/lang/String;)Ljava/lang/String;
    //   260: aastore
    //   261: invokestatic 78	java/lang/String:format	(Ljava/lang/String;[Ljava/lang/Object;)Ljava/lang/String;
    //   264: invokevirtual 85	java/lang/StringBuilder:append	(Ljava/lang/String;)Ljava/lang/StringBuilder;
    //   267: invokevirtual 91	java/lang/StringBuilder:toString	()Ljava/lang/String;
    //   270: astore 7
    //   272: aload 7
    //   274: astore 6
    //   276: ldc 114
    //   278: new 80	java/lang/StringBuilder
    //   281: dup
    //   282: ldc 116
    //   284: invokespecial 119	java/lang/StringBuilder:<init>	(Ljava/lang/String;)V
    //   287: lload 4
    //   289: lload_2
    //   290: lsub
    //   291: invokevirtual 122	java/lang/StringBuilder:append	(J)Ljava/lang/StringBuilder;
    //   294: ldc 124
    //   296: invokevirtual 85	java/lang/StringBuilder:append	(Ljava/lang/String;)Ljava/lang/StringBuilder;
    //   299: aload 6
    //   301: invokevirtual 85	java/lang/StringBuilder:append	(Ljava/lang/String;)Ljava/lang/StringBuilder;
    //   304: ldc 126
    //   306: invokevirtual 85	java/lang/StringBuilder:append	(Ljava/lang/String;)Ljava/lang/StringBuilder;
    //   309: invokevirtual 91	java/lang/StringBuilder:toString	()Ljava/lang/String;
    //   312: invokestatic 132	com/tencent/mm/sdk/platformtools/t:i	(Ljava/lang/String;Ljava/lang/String;)V
    //   315: invokestatic 48	com/tencent/mm/model/ax:tl	()Lcom/tencent/mm/model/b;
    //   318: invokevirtual 136	com/tencent/mm/model/b:rf	()Lcom/tencent/mm/storage/h;
    //   321: bipush 79
    //   323: aload 6
    //   325: invokevirtual 142	com/tencent/mm/storage/h:set	(ILjava/lang/Object;)V
    //   328: return
    //   329: astore 6
    //   331: ldc 114
    //   333: aload 6
    //   335: ldc -112
    //   337: iconst_0
    //   338: anewarray 4	java/lang/Object
    //   341: invokestatic 148	com/tencent/mm/sdk/platformtools/t:printErrStackTrace	(Ljava/lang/String;Ljava/lang/Throwable;Ljava/lang/String;[Ljava/lang/Object;)V
    //   344: return
    //   345: new 80	java/lang/StringBuilder
    //   348: dup
    //   349: invokespecial 81	java/lang/StringBuilder:<init>	()V
    //   352: aload 7
    //   354: invokevirtual 85	java/lang/StringBuilder:append	(Ljava/lang/String;)Ljava/lang/StringBuilder;
    //   357: ldc -106
    //   359: iconst_1
    //   360: anewarray 4	java/lang/Object
    //   363: dup
    //   364: iconst_0
    //   365: aload 8
    //   367: iconst_0
    //   368: aload 8
    //   370: arraylength
    //   371: invokestatic 72	com/tencent/mm/model/ca:d	([BII)Ljava/lang/String;
    //   374: aastore
    //   375: invokestatic 78	java/lang/String:format	(Ljava/lang/String;[Ljava/lang/Object;)Ljava/lang/String;
    //   378: invokevirtual 85	java/lang/StringBuilder:append	(Ljava/lang/String;)Ljava/lang/StringBuilder;
    //   381: invokevirtual 91	java/lang/StringBuilder:toString	()Ljava/lang/String;
    //   384: astore 6
    //   386: goto -161 -> 225
    //   389: astore 7
    //   391: ldc 114
    //   393: ldc -104
    //   395: iconst_1
    //   396: anewarray 4	java/lang/Object
    //   399: dup
    //   400: iconst_0
    //   401: aload 7
    //   403: invokestatic 156	com/tencent/mm/sdk/platformtools/bn:a	(Ljava/lang/Throwable;)Ljava/lang/String;
    //   406: aastore
    //   407: invokestatic 160	com/tencent/mm/sdk/platformtools/t:e	(Ljava/lang/String;Ljava/lang/String;[Ljava/lang/Object;)V
    //   410: goto -134 -> 276
    // Local variable table:
    //   start	length	slot	name	signature
    //   0	413	0	this	cc
    //   103	71	1	i	int
    //   10	280	2	l1	long
    //   57	231	4	l2	long
    //   37	287	6	localObject1	Object
    //   329	5	6	localException1	Exception
    //   384	1	6	str	String
    //   14	339	7	localObject2	Object
    //   389	13	7	localException2	Exception
    //   24	345	8	localObject3	Object
    // Exception table:
    //   from	to	target	type
    //   7	82	329	java/lang/Exception
    //   91	99	329	java/lang/Exception
    //   175	225	329	java/lang/Exception
    //   276	328	329	java/lang/Exception
    //   345	386	329	java/lang/Exception
    //   391	410	329	java/lang/Exception
    //   225	272	389	java/lang/Exception
  }
  
  public final String toString()
  {
    return super.toString() + "|checkSoftTypeExtra";
  }
}

/* Location:
 * Qualified Name:     com.tencent.mm.model.cc
 * Java Class Version: 6 (50.0)
 * JD-Core Version:    0.7.1
 */