package com.tencent.mm.plugin.sns.d;

import com.tencent.mm.plugin.sns.h.k;
import com.tencent.mm.plugin.sns.h.l;
import com.tencent.mm.protocal.b.add;
import com.tencent.mm.protocal.b.ade;
import com.tencent.mm.protocal.b.aqx;
import com.tencent.mm.protocal.b.atp;
import com.tencent.mm.protocal.b.iv;
import com.tencent.mm.sdk.platformtools.ay;
import com.tencent.mm.sdk.platformtools.u;
import java.util.Comparator;
import java.util.LinkedList;
import java.util.List;

public final class aj
{
  /* Error */
  private static String azx()
  {
    // Byte code:
    //   0: invokestatic 16	com/tencent/mm/sdk/platformtools/y:getContext	()Landroid/content/Context;
    //   3: astore 16
    //   5: aload 16
    //   7: ifnonnull +12 -> 19
    //   10: ldc 18
    //   12: ldc 20
    //   14: invokestatic 26	com/tencent/mm/sdk/platformtools/u:e	(Ljava/lang/String;Ljava/lang/String;)V
    //   17: aconst_null
    //   18: areturn
    //   19: iconst_0
    //   20: istore_0
    //   21: aload 16
    //   23: ldc 28
    //   25: invokevirtual 34	android/content/Context:getSystemService	(Ljava/lang/String;)Ljava/lang/Object;
    //   28: checkcast 36	android/net/ConnectivityManager
    //   31: invokevirtual 40	android/net/ConnectivityManager:getActiveNetworkInfo	()Landroid/net/NetworkInfo;
    //   34: astore 4
    //   36: aload 4
    //   38: invokevirtual 46	android/net/NetworkInfo:getSubtype	()I
    //   41: istore_1
    //   42: aload 4
    //   44: invokevirtual 49	android/net/NetworkInfo:getType	()I
    //   47: istore_2
    //   48: iload_2
    //   49: iconst_1
    //   50: if_icmpne +373 -> 423
    //   53: iconst_1
    //   54: istore_0
    //   55: ldc 18
    //   57: ldc 51
    //   59: iconst_1
    //   60: anewarray 4	java/lang/Object
    //   63: dup
    //   64: iconst_0
    //   65: iload_0
    //   66: invokestatic 57	java/lang/Integer:valueOf	(I)Ljava/lang/Integer;
    //   69: aastore
    //   70: invokestatic 61	com/tencent/mm/sdk/platformtools/u:i	(Ljava/lang/String;Ljava/lang/String;[Ljava/lang/Object;)V
    //   73: ldc 63
    //   75: astore 7
    //   77: ldc 63
    //   79: astore 6
    //   81: ldc 63
    //   83: astore 12
    //   85: aload 6
    //   87: astore 4
    //   89: aload 7
    //   91: astore 5
    //   93: aload 16
    //   95: ldc 65
    //   97: invokevirtual 34	android/content/Context:getSystemService	(Ljava/lang/String;)Ljava/lang/Object;
    //   100: checkcast 67	android/net/wifi/WifiManager
    //   103: astore 14
    //   105: aload 6
    //   107: astore 4
    //   109: aload 7
    //   111: astore 5
    //   113: aload 14
    //   115: invokevirtual 71	android/net/wifi/WifiManager:getConnectionInfo	()Landroid/net/wifi/WifiInfo;
    //   118: astore 13
    //   120: aload 6
    //   122: astore 4
    //   124: aload 7
    //   126: astore 5
    //   128: new 73	java/lang/StringBuffer
    //   131: dup
    //   132: invokespecial 77	java/lang/StringBuffer:<init>	()V
    //   135: astore 10
    //   137: aload 6
    //   139: astore 4
    //   141: aload 7
    //   143: astore 5
    //   145: new 73	java/lang/StringBuffer
    //   148: dup
    //   149: invokespecial 77	java/lang/StringBuffer:<init>	()V
    //   152: astore 9
    //   154: aload 6
    //   156: astore 4
    //   158: aload 7
    //   160: astore 5
    //   162: new 73	java/lang/StringBuffer
    //   165: dup
    //   166: invokespecial 77	java/lang/StringBuffer:<init>	()V
    //   169: astore 8
    //   171: iconst_0
    //   172: istore_3
    //   173: iconst_0
    //   174: istore_1
    //   175: aload 6
    //   177: astore 4
    //   179: aload 7
    //   181: astore 5
    //   183: new 79	java/util/ArrayList
    //   186: dup
    //   187: invokespecial 80	java/util/ArrayList:<init>	()V
    //   190: astore 11
    //   192: aload 6
    //   194: astore 4
    //   196: aload 7
    //   198: astore 5
    //   200: aload 10
    //   202: aload 13
    //   204: invokevirtual 85	android/net/wifi/WifiInfo:getSSID	()Ljava/lang/String;
    //   207: invokevirtual 89	java/lang/StringBuffer:append	(Ljava/lang/String;)Ljava/lang/StringBuffer;
    //   210: pop
    //   211: aload 6
    //   213: astore 4
    //   215: aload 7
    //   217: astore 5
    //   219: aload 9
    //   221: aload 13
    //   223: invokevirtual 92	android/net/wifi/WifiInfo:getBSSID	()Ljava/lang/String;
    //   226: invokevirtual 89	java/lang/StringBuffer:append	(Ljava/lang/String;)Ljava/lang/StringBuffer;
    //   229: pop
    //   230: aload 6
    //   232: astore 4
    //   234: aload 7
    //   236: astore 5
    //   238: aload 13
    //   240: invokevirtual 92	android/net/wifi/WifiInfo:getBSSID	()Ljava/lang/String;
    //   243: astore 13
    //   245: aload 6
    //   247: astore 4
    //   249: aload 7
    //   251: astore 5
    //   253: aload 11
    //   255: aload 13
    //   257: invokevirtual 96	java/util/ArrayList:add	(Ljava/lang/Object;)Z
    //   260: pop
    //   261: aload 6
    //   263: astore 4
    //   265: aload 7
    //   267: astore 5
    //   269: aload 14
    //   271: invokevirtual 100	android/net/wifi/WifiManager:getScanResults	()Ljava/util/List;
    //   274: astore 14
    //   276: aload 14
    //   278: ifnull +415 -> 693
    //   281: aload 6
    //   283: astore 4
    //   285: aload 7
    //   287: astore 5
    //   289: aload 14
    //   291: new 6	com/tencent/mm/plugin/sns/d/aj$1
    //   294: dup
    //   295: invokespecial 101	com/tencent/mm/plugin/sns/d/aj$1:<init>	()V
    //   298: invokestatic 107	java/util/Collections:sort	(Ljava/util/List;Ljava/util/Comparator;)V
    //   301: aload 6
    //   303: astore 4
    //   305: aload 7
    //   307: astore 5
    //   309: aload 14
    //   311: invokeinterface 113 1 0
    //   316: astore 14
    //   318: bipush 20
    //   320: istore_2
    //   321: iload_1
    //   322: istore_3
    //   323: aload 6
    //   325: astore 4
    //   327: aload 7
    //   329: astore 5
    //   331: aload 14
    //   333: invokeinterface 119 1 0
    //   338: ifeq +355 -> 693
    //   341: aload 6
    //   343: astore 4
    //   345: aload 7
    //   347: astore 5
    //   349: aload 14
    //   351: invokeinterface 123 1 0
    //   356: checkcast 125	android/net/wifi/ScanResult
    //   359: astore 15
    //   361: aload 15
    //   363: ifnull -42 -> 321
    //   366: aload 6
    //   368: astore 4
    //   370: aload 7
    //   372: astore 5
    //   374: aload 15
    //   376: getfield 129	android/net/wifi/ScanResult:BSSID	Ljava/lang/String;
    //   379: invokestatic 135	com/tencent/mm/sdk/platformtools/ay:kz	(Ljava/lang/String;)Z
    //   382: ifne -61 -> 321
    //   385: aload 6
    //   387: astore 4
    //   389: aload 7
    //   391: astore 5
    //   393: aload 15
    //   395: getfield 129	android/net/wifi/ScanResult:BSSID	Ljava/lang/String;
    //   398: aload 13
    //   400: invokevirtual 140	java/lang/String:equals	(Ljava/lang/Object;)Z
    //   403: ifeq +119 -> 522
    //   406: aload 6
    //   408: astore 4
    //   410: aload 7
    //   412: astore 5
    //   414: aload 15
    //   416: getfield 144	android/net/wifi/ScanResult:level	I
    //   419: istore_1
    //   420: goto -99 -> 321
    //   423: iload_1
    //   424: bipush 13
    //   426: if_icmpeq +15 -> 441
    //   429: iload_1
    //   430: bipush 15
    //   432: if_icmpeq +9 -> 441
    //   435: iload_1
    //   436: bipush 14
    //   438: if_icmpne +8 -> 446
    //   441: iconst_4
    //   442: istore_0
    //   443: goto -388 -> 55
    //   446: iload_1
    //   447: iconst_3
    //   448: if_icmpeq +25 -> 473
    //   451: iload_1
    //   452: iconst_4
    //   453: if_icmpeq +20 -> 473
    //   456: iload_1
    //   457: iconst_5
    //   458: if_icmpeq +15 -> 473
    //   461: iload_1
    //   462: bipush 6
    //   464: if_icmpeq +9 -> 473
    //   467: iload_1
    //   468: bipush 12
    //   470: if_icmpne +8 -> 478
    //   473: iconst_3
    //   474: istore_0
    //   475: goto -420 -> 55
    //   478: iload_1
    //   479: iconst_1
    //   480: if_icmpeq +8 -> 488
    //   483: iload_1
    //   484: iconst_2
    //   485: if_icmpne +8 -> 493
    //   488: iconst_2
    //   489: istore_0
    //   490: goto -435 -> 55
    //   493: iconst_0
    //   494: istore_0
    //   495: goto -440 -> 55
    //   498: astore 4
    //   500: ldc 18
    //   502: ldc -110
    //   504: iconst_1
    //   505: anewarray 4	java/lang/Object
    //   508: dup
    //   509: iconst_0
    //   510: aload 4
    //   512: invokestatic 150	com/tencent/mm/sdk/platformtools/ay:b	(Ljava/lang/Throwable;)Ljava/lang/String;
    //   515: aastore
    //   516: invokestatic 152	com/tencent/mm/sdk/platformtools/u:e	(Ljava/lang/String;Ljava/lang/String;[Ljava/lang/Object;)V
    //   519: goto -464 -> 55
    //   522: iload_1
    //   523: istore_3
    //   524: iload_2
    //   525: ifle +168 -> 693
    //   528: aload 6
    //   530: astore 4
    //   532: aload 7
    //   534: astore 5
    //   536: aload 10
    //   538: ldc -102
    //   540: invokevirtual 89	java/lang/StringBuffer:append	(Ljava/lang/String;)Ljava/lang/StringBuffer;
    //   543: pop
    //   544: aload 6
    //   546: astore 4
    //   548: aload 7
    //   550: astore 5
    //   552: aload 10
    //   554: aload 15
    //   556: getfield 157	android/net/wifi/ScanResult:SSID	Ljava/lang/String;
    //   559: invokestatic 161	com/tencent/mm/sdk/platformtools/ay:ky	(Ljava/lang/String;)Ljava/lang/String;
    //   562: ldc -102
    //   564: ldc 63
    //   566: invokevirtual 165	java/lang/String:replace	(Ljava/lang/CharSequence;Ljava/lang/CharSequence;)Ljava/lang/String;
    //   569: ldc -89
    //   571: ldc 63
    //   573: invokevirtual 165	java/lang/String:replace	(Ljava/lang/CharSequence;Ljava/lang/CharSequence;)Ljava/lang/String;
    //   576: invokevirtual 89	java/lang/StringBuffer:append	(Ljava/lang/String;)Ljava/lang/StringBuffer;
    //   579: pop
    //   580: aload 6
    //   582: astore 4
    //   584: aload 7
    //   586: astore 5
    //   588: aload 9
    //   590: ldc -102
    //   592: invokevirtual 89	java/lang/StringBuffer:append	(Ljava/lang/String;)Ljava/lang/StringBuffer;
    //   595: pop
    //   596: aload 6
    //   598: astore 4
    //   600: aload 7
    //   602: astore 5
    //   604: aload 9
    //   606: aload 15
    //   608: getfield 129	android/net/wifi/ScanResult:BSSID	Ljava/lang/String;
    //   611: invokestatic 161	com/tencent/mm/sdk/platformtools/ay:ky	(Ljava/lang/String;)Ljava/lang/String;
    //   614: ldc -102
    //   616: ldc 63
    //   618: invokevirtual 165	java/lang/String:replace	(Ljava/lang/CharSequence;Ljava/lang/CharSequence;)Ljava/lang/String;
    //   621: ldc -89
    //   623: ldc 63
    //   625: invokevirtual 165	java/lang/String:replace	(Ljava/lang/CharSequence;Ljava/lang/CharSequence;)Ljava/lang/String;
    //   628: invokevirtual 89	java/lang/StringBuffer:append	(Ljava/lang/String;)Ljava/lang/StringBuffer;
    //   631: pop
    //   632: aload 6
    //   634: astore 4
    //   636: aload 7
    //   638: astore 5
    //   640: aload 11
    //   642: aload 15
    //   644: getfield 129	android/net/wifi/ScanResult:BSSID	Ljava/lang/String;
    //   647: invokevirtual 96	java/util/ArrayList:add	(Ljava/lang/Object;)Z
    //   650: pop
    //   651: aload 6
    //   653: astore 4
    //   655: aload 7
    //   657: astore 5
    //   659: aload 8
    //   661: ldc -102
    //   663: invokevirtual 89	java/lang/StringBuffer:append	(Ljava/lang/String;)Ljava/lang/StringBuffer;
    //   666: pop
    //   667: aload 6
    //   669: astore 4
    //   671: aload 7
    //   673: astore 5
    //   675: aload 8
    //   677: aload 15
    //   679: getfield 144	android/net/wifi/ScanResult:level	I
    //   682: invokevirtual 170	java/lang/StringBuffer:append	(I)Ljava/lang/StringBuffer;
    //   685: pop
    //   686: iload_2
    //   687: iconst_1
    //   688: isub
    //   689: istore_2
    //   690: goto -369 -> 321
    //   693: aload 6
    //   695: astore 4
    //   697: aload 7
    //   699: astore 5
    //   701: aload 10
    //   703: invokevirtual 173	java/lang/StringBuffer:toString	()Ljava/lang/String;
    //   706: astore 14
    //   708: aload 6
    //   710: astore 4
    //   712: aload 14
    //   714: astore 5
    //   716: aload 9
    //   718: invokevirtual 173	java/lang/StringBuffer:toString	()Ljava/lang/String;
    //   721: astore 13
    //   723: aload 13
    //   725: astore 4
    //   727: aload 14
    //   729: astore 5
    //   731: new 175	java/lang/StringBuilder
    //   734: dup
    //   735: invokespecial 176	java/lang/StringBuilder:<init>	()V
    //   738: iload_3
    //   739: invokevirtual 179	java/lang/StringBuilder:append	(I)Ljava/lang/StringBuilder;
    //   742: aload 8
    //   744: invokevirtual 173	java/lang/StringBuffer:toString	()Ljava/lang/String;
    //   747: invokevirtual 182	java/lang/StringBuilder:append	(Ljava/lang/String;)Ljava/lang/StringBuilder;
    //   750: invokevirtual 183	java/lang/StringBuilder:toString	()Ljava/lang/String;
    //   753: astore 6
    //   755: aload 6
    //   757: astore 12
    //   759: ldc 18
    //   761: ldc -71
    //   763: iconst_3
    //   764: anewarray 4	java/lang/Object
    //   767: dup
    //   768: iconst_0
    //   769: aload 13
    //   771: aastore
    //   772: dup
    //   773: iconst_1
    //   774: aload 14
    //   776: aastore
    //   777: dup
    //   778: iconst_2
    //   779: aload 12
    //   781: aastore
    //   782: invokestatic 188	com/tencent/mm/sdk/platformtools/u:d	(Ljava/lang/String;Ljava/lang/String;[Ljava/lang/Object;)V
    //   785: ldc 63
    //   787: astore 15
    //   789: aload 16
    //   791: ldc -66
    //   793: invokevirtual 34	android/content/Context:getSystemService	(Ljava/lang/String;)Ljava/lang/Object;
    //   796: checkcast 192	android/telephony/TelephonyManager
    //   799: astore 4
    //   801: aload 4
    //   803: ifnull +856 -> 1659
    //   806: aload 4
    //   808: invokevirtual 195	android/telephony/TelephonyManager:getNetworkOperatorName	()Ljava/lang/String;
    //   811: astore 4
    //   813: aload 4
    //   815: astore 15
    //   817: ldc 18
    //   819: ldc -59
    //   821: iconst_1
    //   822: anewarray 4	java/lang/Object
    //   825: dup
    //   826: iconst_0
    //   827: aload 15
    //   829: aastore
    //   830: invokestatic 61	com/tencent/mm/sdk/platformtools/u:i	(Ljava/lang/String;Ljava/lang/String;[Ljava/lang/Object;)V
    //   833: ldc 63
    //   835: astore 10
    //   837: ldc 63
    //   839: astore 11
    //   841: ldc 63
    //   843: astore 6
    //   845: ldc 63
    //   847: astore 5
    //   849: aload 5
    //   851: astore 9
    //   853: aload 6
    //   855: astore 4
    //   857: aload 11
    //   859: astore 8
    //   861: aload 10
    //   863: astore 7
    //   865: aload 16
    //   867: invokestatic 203	com/tencent/mm/sdk/platformtools/ah:dI	(Landroid/content/Context;)Ljava/util/List;
    //   870: astore 17
    //   872: iconst_0
    //   873: istore_1
    //   874: aload 5
    //   876: astore 9
    //   878: aload 6
    //   880: astore 4
    //   882: aload 11
    //   884: astore 8
    //   886: aload 10
    //   888: astore 7
    //   890: iload_1
    //   891: aload 17
    //   893: invokeinterface 206 1 0
    //   898: if_icmpge +497 -> 1395
    //   901: aload 5
    //   903: astore 9
    //   905: aload 6
    //   907: astore 4
    //   909: aload 11
    //   911: astore 8
    //   913: aload 10
    //   915: astore 7
    //   917: aload 17
    //   919: iload_1
    //   920: invokeinterface 210 2 0
    //   925: checkcast 212	com/tencent/mm/sdk/platformtools/ah$a
    //   928: astore 18
    //   930: aload 5
    //   932: astore 9
    //   934: aload 6
    //   936: astore 4
    //   938: aload 11
    //   940: astore 8
    //   942: aload 10
    //   944: astore 7
    //   946: aload 18
    //   948: getfield 215	com/tencent/mm/sdk/platformtools/ah$a:jWD	Ljava/lang/String;
    //   951: ldc 63
    //   953: invokestatic 219	com/tencent/mm/sdk/platformtools/ay:ad	(Ljava/lang/String;Ljava/lang/String;)Ljava/lang/String;
    //   956: astore 16
    //   958: aload 5
    //   960: astore 9
    //   962: aload 6
    //   964: astore 4
    //   966: aload 11
    //   968: astore 8
    //   970: aload 16
    //   972: astore 7
    //   974: aload 18
    //   976: getfield 222	com/tencent/mm/sdk/platformtools/ah$a:jWE	Ljava/lang/String;
    //   979: ldc 63
    //   981: invokestatic 219	com/tencent/mm/sdk/platformtools/ay:ad	(Ljava/lang/String;Ljava/lang/String;)Ljava/lang/String;
    //   984: astore 11
    //   986: aload 6
    //   988: astore 10
    //   990: aload 5
    //   992: astore 9
    //   994: aload 6
    //   996: astore 4
    //   998: aload 11
    //   1000: astore 8
    //   1002: aload 16
    //   1004: astore 7
    //   1006: aload 6
    //   1008: invokevirtual 225	java/lang/String:length	()I
    //   1011: ifle +72 -> 1083
    //   1014: aload 6
    //   1016: astore 10
    //   1018: aload 5
    //   1020: astore 9
    //   1022: aload 6
    //   1024: astore 4
    //   1026: aload 11
    //   1028: astore 8
    //   1030: aload 16
    //   1032: astore 7
    //   1034: aload 18
    //   1036: getfield 228	com/tencent/mm/sdk/platformtools/ah$a:jWG	Ljava/lang/String;
    //   1039: invokestatic 135	com/tencent/mm/sdk/platformtools/ay:kz	(Ljava/lang/String;)Z
    //   1042: ifne +41 -> 1083
    //   1045: aload 5
    //   1047: astore 9
    //   1049: aload 6
    //   1051: astore 4
    //   1053: aload 11
    //   1055: astore 8
    //   1057: aload 16
    //   1059: astore 7
    //   1061: new 175	java/lang/StringBuilder
    //   1064: dup
    //   1065: invokespecial 176	java/lang/StringBuilder:<init>	()V
    //   1068: aload 6
    //   1070: invokevirtual 182	java/lang/StringBuilder:append	(Ljava/lang/String;)Ljava/lang/StringBuilder;
    //   1073: ldc -102
    //   1075: invokevirtual 182	java/lang/StringBuilder:append	(Ljava/lang/String;)Ljava/lang/StringBuilder;
    //   1078: invokevirtual 183	java/lang/StringBuilder:toString	()Ljava/lang/String;
    //   1081: astore 10
    //   1083: aload 10
    //   1085: astore 6
    //   1087: aload 5
    //   1089: astore 9
    //   1091: aload 10
    //   1093: astore 4
    //   1095: aload 11
    //   1097: astore 8
    //   1099: aload 16
    //   1101: astore 7
    //   1103: aload 18
    //   1105: getfield 228	com/tencent/mm/sdk/platformtools/ah$a:jWG	Ljava/lang/String;
    //   1108: invokestatic 135	com/tencent/mm/sdk/platformtools/ay:kz	(Ljava/lang/String;)Z
    //   1111: ifne +44 -> 1155
    //   1114: aload 5
    //   1116: astore 9
    //   1118: aload 10
    //   1120: astore 4
    //   1122: aload 11
    //   1124: astore 8
    //   1126: aload 16
    //   1128: astore 7
    //   1130: new 175	java/lang/StringBuilder
    //   1133: dup
    //   1134: invokespecial 176	java/lang/StringBuilder:<init>	()V
    //   1137: aload 10
    //   1139: invokevirtual 182	java/lang/StringBuilder:append	(Ljava/lang/String;)Ljava/lang/StringBuilder;
    //   1142: aload 18
    //   1144: getfield 228	com/tencent/mm/sdk/platformtools/ah$a:jWG	Ljava/lang/String;
    //   1147: invokevirtual 182	java/lang/StringBuilder:append	(Ljava/lang/String;)Ljava/lang/StringBuilder;
    //   1150: invokevirtual 183	java/lang/StringBuilder:toString	()Ljava/lang/String;
    //   1153: astore 6
    //   1155: aload 5
    //   1157: astore 10
    //   1159: aload 5
    //   1161: astore 9
    //   1163: aload 6
    //   1165: astore 4
    //   1167: aload 11
    //   1169: astore 8
    //   1171: aload 16
    //   1173: astore 7
    //   1175: aload 5
    //   1177: invokevirtual 225	java/lang/String:length	()I
    //   1180: ifle +72 -> 1252
    //   1183: aload 5
    //   1185: astore 10
    //   1187: aload 5
    //   1189: astore 9
    //   1191: aload 6
    //   1193: astore 4
    //   1195: aload 11
    //   1197: astore 8
    //   1199: aload 16
    //   1201: astore 7
    //   1203: aload 18
    //   1205: getfield 231	com/tencent/mm/sdk/platformtools/ah$a:jWF	Ljava/lang/String;
    //   1208: invokestatic 135	com/tencent/mm/sdk/platformtools/ay:kz	(Ljava/lang/String;)Z
    //   1211: ifne +41 -> 1252
    //   1214: aload 5
    //   1216: astore 9
    //   1218: aload 6
    //   1220: astore 4
    //   1222: aload 11
    //   1224: astore 8
    //   1226: aload 16
    //   1228: astore 7
    //   1230: new 175	java/lang/StringBuilder
    //   1233: dup
    //   1234: invokespecial 176	java/lang/StringBuilder:<init>	()V
    //   1237: aload 5
    //   1239: invokevirtual 182	java/lang/StringBuilder:append	(Ljava/lang/String;)Ljava/lang/StringBuilder;
    //   1242: ldc -102
    //   1244: invokevirtual 182	java/lang/StringBuilder:append	(Ljava/lang/String;)Ljava/lang/StringBuilder;
    //   1247: invokevirtual 183	java/lang/StringBuilder:toString	()Ljava/lang/String;
    //   1250: astore 10
    //   1252: aload 10
    //   1254: astore 9
    //   1256: aload 6
    //   1258: astore 4
    //   1260: aload 11
    //   1262: astore 8
    //   1264: aload 16
    //   1266: astore 7
    //   1268: aload 18
    //   1270: getfield 231	com/tencent/mm/sdk/platformtools/ah$a:jWF	Ljava/lang/String;
    //   1273: invokestatic 135	com/tencent/mm/sdk/platformtools/ay:kz	(Ljava/lang/String;)Z
    //   1276: ifne +376 -> 1652
    //   1279: aload 10
    //   1281: astore 9
    //   1283: aload 6
    //   1285: astore 4
    //   1287: aload 11
    //   1289: astore 8
    //   1291: aload 16
    //   1293: astore 7
    //   1295: new 175	java/lang/StringBuilder
    //   1298: dup
    //   1299: invokespecial 176	java/lang/StringBuilder:<init>	()V
    //   1302: aload 10
    //   1304: invokevirtual 182	java/lang/StringBuilder:append	(Ljava/lang/String;)Ljava/lang/StringBuilder;
    //   1307: aload 18
    //   1309: getfield 231	com/tencent/mm/sdk/platformtools/ah$a:jWF	Ljava/lang/String;
    //   1312: invokevirtual 182	java/lang/StringBuilder:append	(Ljava/lang/String;)Ljava/lang/StringBuilder;
    //   1315: invokevirtual 183	java/lang/StringBuilder:toString	()Ljava/lang/String;
    //   1318: astore 5
    //   1320: aload 5
    //   1322: astore 4
    //   1324: iload_1
    //   1325: iconst_1
    //   1326: iadd
    //   1327: istore_1
    //   1328: aload 4
    //   1330: astore 5
    //   1332: aload 16
    //   1334: astore 10
    //   1336: goto -462 -> 874
    //   1339: astore 6
    //   1341: ldc 18
    //   1343: ldc -23
    //   1345: iconst_1
    //   1346: anewarray 4	java/lang/Object
    //   1349: dup
    //   1350: iconst_0
    //   1351: aload 6
    //   1353: invokestatic 150	com/tencent/mm/sdk/platformtools/ay:b	(Ljava/lang/Throwable;)Ljava/lang/String;
    //   1356: aastore
    //   1357: invokestatic 152	com/tencent/mm/sdk/platformtools/u:e	(Ljava/lang/String;Ljava/lang/String;[Ljava/lang/Object;)V
    //   1360: aload 4
    //   1362: astore 13
    //   1364: aload 5
    //   1366: astore 14
    //   1368: goto -609 -> 759
    //   1371: astore 4
    //   1373: ldc 18
    //   1375: ldc -110
    //   1377: iconst_1
    //   1378: anewarray 4	java/lang/Object
    //   1381: dup
    //   1382: iconst_0
    //   1383: aload 4
    //   1385: invokestatic 150	com/tencent/mm/sdk/platformtools/ay:b	(Ljava/lang/Throwable;)Ljava/lang/String;
    //   1388: aastore
    //   1389: invokestatic 152	com/tencent/mm/sdk/platformtools/u:e	(Ljava/lang/String;Ljava/lang/String;[Ljava/lang/Object;)V
    //   1392: goto -575 -> 817
    //   1395: aload 11
    //   1397: astore 4
    //   1399: aload 10
    //   1401: astore 7
    //   1403: ldc 18
    //   1405: ldc -21
    //   1407: iconst_4
    //   1408: anewarray 4	java/lang/Object
    //   1411: dup
    //   1412: iconst_0
    //   1413: aload 7
    //   1415: aastore
    //   1416: dup
    //   1417: iconst_1
    //   1418: aload 4
    //   1420: aastore
    //   1421: dup
    //   1422: iconst_2
    //   1423: aload 6
    //   1425: aastore
    //   1426: dup
    //   1427: iconst_3
    //   1428: aload 5
    //   1430: aastore
    //   1431: invokestatic 188	com/tencent/mm/sdk/platformtools/u:d	(Ljava/lang/String;Ljava/lang/String;[Ljava/lang/Object;)V
    //   1434: new 175	java/lang/StringBuilder
    //   1437: dup
    //   1438: invokespecial 176	java/lang/StringBuilder:<init>	()V
    //   1441: astore 8
    //   1443: aload 8
    //   1445: iload_0
    //   1446: invokevirtual 179	java/lang/StringBuilder:append	(I)Ljava/lang/StringBuilder;
    //   1449: ldc -19
    //   1451: invokevirtual 182	java/lang/StringBuilder:append	(Ljava/lang/String;)Ljava/lang/StringBuilder;
    //   1454: pop
    //   1455: aload 8
    //   1457: aload 14
    //   1459: ldc -19
    //   1461: ldc -89
    //   1463: invokevirtual 165	java/lang/String:replace	(Ljava/lang/CharSequence;Ljava/lang/CharSequence;)Ljava/lang/String;
    //   1466: invokevirtual 182	java/lang/StringBuilder:append	(Ljava/lang/String;)Ljava/lang/StringBuilder;
    //   1469: ldc -19
    //   1471: invokevirtual 182	java/lang/StringBuilder:append	(Ljava/lang/String;)Ljava/lang/StringBuilder;
    //   1474: pop
    //   1475: aload 8
    //   1477: aload 13
    //   1479: ldc -19
    //   1481: ldc -89
    //   1483: invokevirtual 165	java/lang/String:replace	(Ljava/lang/CharSequence;Ljava/lang/CharSequence;)Ljava/lang/String;
    //   1486: invokevirtual 182	java/lang/StringBuilder:append	(Ljava/lang/String;)Ljava/lang/StringBuilder;
    //   1489: ldc -19
    //   1491: invokevirtual 182	java/lang/StringBuilder:append	(Ljava/lang/String;)Ljava/lang/StringBuilder;
    //   1494: pop
    //   1495: aload 8
    //   1497: aload 12
    //   1499: ldc -19
    //   1501: ldc -89
    //   1503: invokevirtual 165	java/lang/String:replace	(Ljava/lang/CharSequence;Ljava/lang/CharSequence;)Ljava/lang/String;
    //   1506: invokevirtual 182	java/lang/StringBuilder:append	(Ljava/lang/String;)Ljava/lang/StringBuilder;
    //   1509: ldc -19
    //   1511: invokevirtual 182	java/lang/StringBuilder:append	(Ljava/lang/String;)Ljava/lang/StringBuilder;
    //   1514: pop
    //   1515: aload 8
    //   1517: aload 15
    //   1519: ldc -19
    //   1521: ldc -89
    //   1523: invokevirtual 165	java/lang/String:replace	(Ljava/lang/CharSequence;Ljava/lang/CharSequence;)Ljava/lang/String;
    //   1526: invokevirtual 182	java/lang/StringBuilder:append	(Ljava/lang/String;)Ljava/lang/StringBuilder;
    //   1529: ldc -19
    //   1531: invokevirtual 182	java/lang/StringBuilder:append	(Ljava/lang/String;)Ljava/lang/StringBuilder;
    //   1534: pop
    //   1535: aload 8
    //   1537: aload 7
    //   1539: ldc -19
    //   1541: ldc -89
    //   1543: invokevirtual 165	java/lang/String:replace	(Ljava/lang/CharSequence;Ljava/lang/CharSequence;)Ljava/lang/String;
    //   1546: invokevirtual 182	java/lang/StringBuilder:append	(Ljava/lang/String;)Ljava/lang/StringBuilder;
    //   1549: ldc -19
    //   1551: invokevirtual 182	java/lang/StringBuilder:append	(Ljava/lang/String;)Ljava/lang/StringBuilder;
    //   1554: pop
    //   1555: aload 8
    //   1557: aload 4
    //   1559: ldc -19
    //   1561: ldc -89
    //   1563: invokevirtual 165	java/lang/String:replace	(Ljava/lang/CharSequence;Ljava/lang/CharSequence;)Ljava/lang/String;
    //   1566: invokevirtual 182	java/lang/StringBuilder:append	(Ljava/lang/String;)Ljava/lang/StringBuilder;
    //   1569: ldc -19
    //   1571: invokevirtual 182	java/lang/StringBuilder:append	(Ljava/lang/String;)Ljava/lang/StringBuilder;
    //   1574: pop
    //   1575: aload 8
    //   1577: aload 6
    //   1579: ldc -19
    //   1581: ldc -89
    //   1583: invokevirtual 165	java/lang/String:replace	(Ljava/lang/CharSequence;Ljava/lang/CharSequence;)Ljava/lang/String;
    //   1586: invokevirtual 182	java/lang/StringBuilder:append	(Ljava/lang/String;)Ljava/lang/StringBuilder;
    //   1589: ldc -19
    //   1591: invokevirtual 182	java/lang/StringBuilder:append	(Ljava/lang/String;)Ljava/lang/StringBuilder;
    //   1594: pop
    //   1595: aload 8
    //   1597: aload 5
    //   1599: ldc -19
    //   1601: ldc -89
    //   1603: invokevirtual 165	java/lang/String:replace	(Ljava/lang/CharSequence;Ljava/lang/CharSequence;)Ljava/lang/String;
    //   1606: invokevirtual 182	java/lang/StringBuilder:append	(Ljava/lang/String;)Ljava/lang/StringBuilder;
    //   1609: pop
    //   1610: aload 8
    //   1612: invokevirtual 183	java/lang/StringBuilder:toString	()Ljava/lang/String;
    //   1615: areturn
    //   1616: astore 6
    //   1618: aload 9
    //   1620: astore 5
    //   1622: ldc 18
    //   1624: ldc -110
    //   1626: iconst_1
    //   1627: anewarray 4	java/lang/Object
    //   1630: dup
    //   1631: iconst_0
    //   1632: aload 6
    //   1634: invokestatic 150	com/tencent/mm/sdk/platformtools/ay:b	(Ljava/lang/Throwable;)Ljava/lang/String;
    //   1637: aastore
    //   1638: invokestatic 152	com/tencent/mm/sdk/platformtools/u:e	(Ljava/lang/String;Ljava/lang/String;[Ljava/lang/Object;)V
    //   1641: aload 4
    //   1643: astore 6
    //   1645: aload 8
    //   1647: astore 4
    //   1649: goto -246 -> 1403
    //   1652: aload 10
    //   1654: astore 4
    //   1656: goto -332 -> 1324
    //   1659: ldc 63
    //   1661: astore 4
    //   1663: goto -850 -> 813
    // Local variable table:
    //   start	length	slot	name	signature
    //   20	1426	0	i	int
    //   41	1287	1	j	int
    //   47	643	2	k	int
    //   172	567	3	m	int
    //   34	375	4	localObject1	Object
    //   498	13	4	localException1	Exception
    //   530	831	4	localObject2	Object
    //   1371	13	4	localException2	Exception
    //   1397	265	4	localObject3	Object
    //   91	1530	5	localObject4	Object
    //   79	1205	6	localObject5	Object
    //   1339	239	6	localException3	Exception
    //   1616	17	6	localException4	Exception
    //   1643	1	6	localObject6	Object
    //   75	1463	7	localObject7	Object
    //   169	1477	8	localObject8	Object
    //   152	1467	9	localObject9	Object
    //   135	1518	10	localObject10	Object
    //   190	1206	11	localObject11	Object
    //   83	1415	12	localObject12	Object
    //   118	1360	13	localObject13	Object
    //   103	1355	14	localObject14	Object
    //   359	1159	15	localObject15	Object
    //   3	1330	16	localObject16	Object
    //   870	48	17	localList	List
    //   928	380	18	locala	com.tencent.mm.sdk.platformtools.ah.a
    // Exception table:
    //   from	to	target	type
    //   21	48	498	java/lang/Exception
    //   93	105	1339	java/lang/Exception
    //   113	120	1339	java/lang/Exception
    //   128	137	1339	java/lang/Exception
    //   145	154	1339	java/lang/Exception
    //   162	171	1339	java/lang/Exception
    //   183	192	1339	java/lang/Exception
    //   200	211	1339	java/lang/Exception
    //   219	230	1339	java/lang/Exception
    //   238	245	1339	java/lang/Exception
    //   253	261	1339	java/lang/Exception
    //   269	276	1339	java/lang/Exception
    //   289	301	1339	java/lang/Exception
    //   309	318	1339	java/lang/Exception
    //   331	341	1339	java/lang/Exception
    //   349	361	1339	java/lang/Exception
    //   374	385	1339	java/lang/Exception
    //   393	406	1339	java/lang/Exception
    //   414	420	1339	java/lang/Exception
    //   536	544	1339	java/lang/Exception
    //   552	580	1339	java/lang/Exception
    //   588	596	1339	java/lang/Exception
    //   604	632	1339	java/lang/Exception
    //   640	651	1339	java/lang/Exception
    //   659	667	1339	java/lang/Exception
    //   675	686	1339	java/lang/Exception
    //   701	708	1339	java/lang/Exception
    //   716	723	1339	java/lang/Exception
    //   731	755	1339	java/lang/Exception
    //   789	801	1371	java/lang/Exception
    //   806	813	1371	java/lang/Exception
    //   865	872	1616	java/lang/Exception
    //   890	901	1616	java/lang/Exception
    //   917	930	1616	java/lang/Exception
    //   946	958	1616	java/lang/Exception
    //   974	986	1616	java/lang/Exception
    //   1006	1014	1616	java/lang/Exception
    //   1034	1045	1616	java/lang/Exception
    //   1061	1083	1616	java/lang/Exception
    //   1103	1114	1616	java/lang/Exception
    //   1130	1155	1616	java/lang/Exception
    //   1175	1183	1616	java/lang/Exception
    //   1203	1214	1616	java/lang/Exception
    //   1230	1252	1616	java/lang/Exception
    //   1268	1279	1616	java/lang/Exception
    //   1295	1320	1616	java/lang/Exception
  }
  
  public static void cn(long paramLong)
  {
    if (paramLong == 0L) {}
    for (;;)
    {
      return;
      Object localObject1 = ad.azi().cx(paramLong);
      if ((localObject1 != null) && (field_type == 1))
      {
        Object localObject2 = ((k)localObject1).aAe();
        if (localObject2 != null)
        {
          LinkedList localLinkedList1 = jzV;
          LinkedList localLinkedList2 = azRjMx.jhw;
          int j = Math.min(localLinkedList1.size(), localLinkedList2.size());
          localObject1 = "";
          if (j > 0)
          {
            localObject1 = azx();
            if (ay.kz((String)localObject1)) {}
          }
          else
          {
            int i = 0;
            while (i < j)
            {
              aqx localaqx = (aqx)localLinkedList1.get(i);
              localObject2 = new StringBuffer();
              Object localObject3 = (add)localLinkedList2.get(i);
              ((StringBuffer)localObject2).append("||index: " + i);
              ((StringBuffer)localObject2).append("||item poi lat " + jKC + " " + jKD);
              ((StringBuffer)localObject2).append("||item poi accuracy loctype " + meQ + " " + meR);
              ((StringBuffer)localObject2).append("||item pic lat " + jKA + " " + jKB);
              ((StringBuffer)localObject2).append("||item exitime:" + jKF + " filetime: " + jKG);
              ((StringBuffer)localObject2).append("||item source: " + jKE);
              ((StringBuffer)localObject2).append("||url" + eiq);
              localObject3 = eiq;
              localObject2 = localObject3;
              if (((String)localObject3).startsWith("http://mmsns.qpic.cn/mmsns/"))
              {
                int k = ((String)localObject3).lastIndexOf("/");
                localObject2 = localObject3;
                if (k > 27)
                {
                  localObject2 = localObject3;
                  if (k < ((String)localObject3).length()) {
                    localObject2 = ((String)localObject3).substring(27, k);
                  }
                }
              }
              localObject2 = (String)localObject2 + "," + com.tencent.mm.plugin.sns.data.h.bX(paramLong) + "," + i + "," + ay.FR() + "," + jKE + "," + jKG + "," + jKF + "," + jKB + "," + jKA + "," + jKD + "," + jKC + "," + (String)localObject1 + "," + meQ + "," + meR;
              u.d("!44@/B4Tb64lLpJBhSxdTZULe8GNbIGM6ZetSXJFQ1plAnw=", "report:%s", new Object[] { localObject2 });
              com.tencent.mm.plugin.report.service.h.fUJ.O(11985, (String)localObject2);
              i += 1;
            }
          }
        }
      }
    }
  }
}

/* Location:
 * Qualified Name:     com.tencent.mm.plugin.sns.d.aj
 * Java Class Version: 6 (50.0)
 * JD-Core Version:    0.7.1
 */