package com.tencent.mm.plugin.hp.a;

import java.util.List;

final class a$a
  implements Runnable
{
  private boolean eyd = false;
  private String eye;
  private List eyf = null;
  
  public a$a(String paramString)
  {
    eye = paramString;
  }
  
  /* Error */
  public final void run()
  {
    // Byte code:
    //   0: invokestatic 40	com/tencent/mm/sdk/platformtools/y:getContext	()Landroid/content/Context;
    //   3: astore 9
    //   5: aload 9
    //   7: ldc 42
    //   9: iconst_0
    //   10: invokevirtual 48	android/content/Context:getDir	(Ljava/lang/String;I)Ljava/io/File;
    //   13: astore 4
    //   15: aload 4
    //   17: invokevirtual 54	java/io/File:listFiles	()[Ljava/io/File;
    //   20: astore 5
    //   22: aload 5
    //   24: arraylength
    //   25: istore_2
    //   26: iconst_0
    //   27: istore_1
    //   28: iload_1
    //   29: iload_2
    //   30: if_icmpge +89 -> 119
    //   33: aload 5
    //   35: iload_1
    //   36: aaload
    //   37: astore 6
    //   39: aload 6
    //   41: invokevirtual 58	java/io/File:isFile	()Z
    //   44: ifeq +49 -> 93
    //   47: aload 6
    //   49: invokevirtual 62	java/io/File:getAbsolutePath	()Ljava/lang/String;
    //   52: astore 7
    //   54: aload 7
    //   56: ldc 64
    //   58: invokevirtual 70	java/lang/String:endsWith	(Ljava/lang/String;)Z
    //   61: ifeq +32 -> 93
    //   64: aload 6
    //   66: invokevirtual 73	java/io/File:delete	()Z
    //   69: ifne +31 -> 100
    //   72: ldc 75
    //   74: ldc 77
    //   76: iconst_1
    //   77: anewarray 4	java/lang/Object
    //   80: dup
    //   81: iconst_0
    //   82: aload 7
    //   84: aastore
    //   85: invokestatic 83	com/tencent/mm/sdk/platformtools/u:w	(Ljava/lang/String;Ljava/lang/String;[Ljava/lang/Object;)V
    //   88: aload 6
    //   90: invokevirtual 86	java/io/File:deleteOnExit	()V
    //   93: iload_1
    //   94: iconst_1
    //   95: iadd
    //   96: istore_1
    //   97: goto -69 -> 28
    //   100: ldc 75
    //   102: ldc 88
    //   104: iconst_1
    //   105: anewarray 4	java/lang/Object
    //   108: dup
    //   109: iconst_0
    //   110: aload 7
    //   112: aastore
    //   113: invokestatic 91	com/tencent/mm/sdk/platformtools/u:i	(Ljava/lang/String;Ljava/lang/String;[Ljava/lang/Object;)V
    //   116: goto -23 -> 93
    //   119: aload 9
    //   121: ldc 93
    //   123: iconst_0
    //   124: invokevirtual 48	android/content/Context:getDir	(Ljava/lang/String;I)Ljava/io/File;
    //   127: astore 5
    //   129: aload 5
    //   131: invokevirtual 54	java/io/File:listFiles	()[Ljava/io/File;
    //   134: astore 6
    //   136: aload 6
    //   138: arraylength
    //   139: istore_2
    //   140: iconst_0
    //   141: istore_1
    //   142: iload_1
    //   143: iload_2
    //   144: if_icmpge +89 -> 233
    //   147: aload 6
    //   149: iload_1
    //   150: aaload
    //   151: astore 7
    //   153: aload 7
    //   155: invokevirtual 58	java/io/File:isFile	()Z
    //   158: ifeq +49 -> 207
    //   161: aload 7
    //   163: invokevirtual 62	java/io/File:getAbsolutePath	()Ljava/lang/String;
    //   166: astore 8
    //   168: aload 8
    //   170: ldc 95
    //   172: invokevirtual 70	java/lang/String:endsWith	(Ljava/lang/String;)Z
    //   175: ifeq +32 -> 207
    //   178: aload 7
    //   180: invokevirtual 73	java/io/File:delete	()Z
    //   183: ifne +31 -> 214
    //   186: ldc 75
    //   188: ldc 77
    //   190: iconst_1
    //   191: anewarray 4	java/lang/Object
    //   194: dup
    //   195: iconst_0
    //   196: aload 8
    //   198: aastore
    //   199: invokestatic 83	com/tencent/mm/sdk/platformtools/u:w	(Ljava/lang/String;Ljava/lang/String;[Ljava/lang/Object;)V
    //   202: aload 7
    //   204: invokevirtual 86	java/io/File:deleteOnExit	()V
    //   207: iload_1
    //   208: iconst_1
    //   209: iadd
    //   210: istore_1
    //   211: goto -69 -> 142
    //   214: ldc 75
    //   216: ldc 97
    //   218: iconst_1
    //   219: anewarray 4	java/lang/Object
    //   222: dup
    //   223: iconst_0
    //   224: aload 8
    //   226: aastore
    //   227: invokestatic 91	com/tencent/mm/sdk/platformtools/u:i	(Ljava/lang/String;Ljava/lang/String;[Ljava/lang/Object;)V
    //   230: goto -23 -> 207
    //   233: aload_0
    //   234: getfield 28	com/tencent/mm/plugin/hp/a/a$a:eye	Ljava/lang/String;
    //   237: invokestatic 103	com/tencent/mm/a/g:aC	(Ljava/lang/String;)Ljava/lang/String;
    //   240: astore 7
    //   242: aload 7
    //   244: invokevirtual 107	java/lang/String:getBytes	()[B
    //   247: astore 8
    //   249: new 109	java/lang/StringBuilder
    //   252: dup
    //   253: invokespecial 110	java/lang/StringBuilder:<init>	()V
    //   256: aload 7
    //   258: iconst_0
    //   259: bipush 8
    //   261: invokevirtual 114	java/lang/String:substring	(II)Ljava/lang/String;
    //   264: invokevirtual 118	java/lang/StringBuilder:append	(Ljava/lang/String;)Ljava/lang/StringBuilder;
    //   267: ldc 64
    //   269: invokevirtual 118	java/lang/StringBuilder:append	(Ljava/lang/String;)Ljava/lang/StringBuilder;
    //   272: invokevirtual 121	java/lang/StringBuilder:toString	()Ljava/lang/String;
    //   275: astore 6
    //   277: new 109	java/lang/StringBuilder
    //   280: dup
    //   281: invokespecial 110	java/lang/StringBuilder:<init>	()V
    //   284: aload 7
    //   286: iconst_0
    //   287: bipush 8
    //   289: invokevirtual 114	java/lang/String:substring	(II)Ljava/lang/String;
    //   292: invokevirtual 118	java/lang/StringBuilder:append	(Ljava/lang/String;)Ljava/lang/StringBuilder;
    //   295: ldc 95
    //   297: invokevirtual 118	java/lang/StringBuilder:append	(Ljava/lang/String;)Ljava/lang/StringBuilder;
    //   300: invokevirtual 121	java/lang/StringBuilder:toString	()Ljava/lang/String;
    //   303: astore 7
    //   305: new 109	java/lang/StringBuilder
    //   308: dup
    //   309: invokespecial 110	java/lang/StringBuilder:<init>	()V
    //   312: aload 9
    //   314: ldc 42
    //   316: iconst_0
    //   317: invokevirtual 48	android/content/Context:getDir	(Ljava/lang/String;I)Ljava/io/File;
    //   320: invokevirtual 62	java/io/File:getAbsolutePath	()Ljava/lang/String;
    //   323: invokevirtual 118	java/lang/StringBuilder:append	(Ljava/lang/String;)Ljava/lang/StringBuilder;
    //   326: ldc 123
    //   328: invokevirtual 118	java/lang/StringBuilder:append	(Ljava/lang/String;)Ljava/lang/StringBuilder;
    //   331: aload 6
    //   333: invokevirtual 118	java/lang/StringBuilder:append	(Ljava/lang/String;)Ljava/lang/StringBuilder;
    //   336: invokevirtual 121	java/lang/StringBuilder:toString	()Ljava/lang/String;
    //   339: astore 6
    //   341: new 109	java/lang/StringBuilder
    //   344: dup
    //   345: invokespecial 110	java/lang/StringBuilder:<init>	()V
    //   348: aload 9
    //   350: ldc 93
    //   352: iconst_0
    //   353: invokevirtual 48	android/content/Context:getDir	(Ljava/lang/String;I)Ljava/io/File;
    //   356: invokevirtual 62	java/io/File:getAbsolutePath	()Ljava/lang/String;
    //   359: invokevirtual 118	java/lang/StringBuilder:append	(Ljava/lang/String;)Ljava/lang/StringBuilder;
    //   362: ldc 123
    //   364: invokevirtual 118	java/lang/StringBuilder:append	(Ljava/lang/String;)Ljava/lang/StringBuilder;
    //   367: aload 7
    //   369: invokevirtual 118	java/lang/StringBuilder:append	(Ljava/lang/String;)Ljava/lang/StringBuilder;
    //   372: invokevirtual 121	java/lang/StringBuilder:toString	()Ljava/lang/String;
    //   375: astore 7
    //   377: aload_0
    //   378: getfield 28	com/tencent/mm/plugin/hp/a/a$a:eye	Ljava/lang/String;
    //   381: aload 6
    //   383: invokestatic 129	com/tencent/mm/a/e:o	(Ljava/lang/String;Ljava/lang/String;)J
    //   386: pop2
    //   387: ldc 75
    //   389: ldc -125
    //   391: iconst_1
    //   392: anewarray 4	java/lang/Object
    //   395: dup
    //   396: iconst_0
    //   397: aload_0
    //   398: getfield 28	com/tencent/mm/plugin/hp/a/a$a:eye	Ljava/lang/String;
    //   401: aastore
    //   402: invokestatic 134	com/tencent/mm/sdk/platformtools/u:d	(Ljava/lang/String;Ljava/lang/String;[Ljava/lang/Object;)V
    //   405: aload 6
    //   407: aload 7
    //   409: iconst_0
    //   410: invokestatic 140	dalvik/system/DexFile:loadDex	(Ljava/lang/String;Ljava/lang/String;I)Ldalvik/system/DexFile;
    //   413: pop
    //   414: aload_0
    //   415: iconst_1
    //   416: putfield 24	com/tencent/mm/plugin/hp/a/a$a:eyd	Z
    //   419: aload 5
    //   421: invokevirtual 144	java/io/File:list	()[Ljava/lang/String;
    //   424: astore 5
    //   426: aload 5
    //   428: arraylength
    //   429: istore_2
    //   430: iconst_0
    //   431: istore_1
    //   432: iload_1
    //   433: iload_2
    //   434: if_icmpge +28 -> 462
    //   437: ldc 75
    //   439: ldc -110
    //   441: iconst_1
    //   442: anewarray 4	java/lang/Object
    //   445: dup
    //   446: iconst_0
    //   447: aload 5
    //   449: iload_1
    //   450: aaload
    //   451: aastore
    //   452: invokestatic 134	com/tencent/mm/sdk/platformtools/u:d	(Ljava/lang/String;Ljava/lang/String;[Ljava/lang/Object;)V
    //   455: iload_1
    //   456: iconst_1
    //   457: iadd
    //   458: istore_1
    //   459: goto -27 -> 432
    //   462: aload 4
    //   464: invokevirtual 144	java/io/File:list	()[Ljava/lang/String;
    //   467: astore 4
    //   469: aload 4
    //   471: arraylength
    //   472: istore_2
    //   473: iconst_0
    //   474: istore_1
    //   475: iload_1
    //   476: iload_2
    //   477: if_icmpge +49 -> 526
    //   480: ldc 75
    //   482: ldc -108
    //   484: iconst_1
    //   485: anewarray 4	java/lang/Object
    //   488: dup
    //   489: iconst_0
    //   490: aload 4
    //   492: iload_1
    //   493: aaload
    //   494: aastore
    //   495: invokestatic 134	com/tencent/mm/sdk/platformtools/u:d	(Ljava/lang/String;Ljava/lang/String;[Ljava/lang/Object;)V
    //   498: iload_1
    //   499: iconst_1
    //   500: iadd
    //   501: istore_1
    //   502: goto -27 -> 475
    //   505: astore 4
    //   507: ldc 75
    //   509: aload 4
    //   511: ldc -106
    //   513: iconst_0
    //   514: anewarray 4	java/lang/Object
    //   517: invokestatic 154	com/tencent/mm/sdk/platformtools/u:printErrStackTrace	(Ljava/lang/String;Ljava/lang/Throwable;Ljava/lang/String;[Ljava/lang/Object;)V
    //   520: aload 6
    //   522: invokestatic 159	com/tencent/mm/loader/stub/b:deleteFile	(Ljava/lang/String;)Z
    //   525: pop
    //   526: aload_0
    //   527: getfield 26	com/tencent/mm/plugin/hp/a/a$a:eyf	Ljava/util/List;
    //   530: ifnull +15 -> 545
    //   533: aload_0
    //   534: getfield 26	com/tencent/mm/plugin/hp/a/a$a:eyf	Ljava/util/List;
    //   537: invokeinterface 164 1 0
    //   542: ifeq +10 -> 552
    //   545: ldc 75
    //   547: ldc -90
    //   549: invokestatic 169	com/tencent/mm/sdk/platformtools/u:i	(Ljava/lang/String;Ljava/lang/String;)V
    //   552: aload_0
    //   553: getfield 26	com/tencent/mm/plugin/hp/a/a$a:eyf	Ljava/util/List;
    //   556: ifnull +394 -> 950
    //   559: aload_0
    //   560: getfield 26	com/tencent/mm/plugin/hp/a/a$a:eyf	Ljava/util/List;
    //   563: invokeinterface 164 1 0
    //   568: ifne +382 -> 950
    //   571: aload 9
    //   573: ldc -85
    //   575: iconst_0
    //   576: invokevirtual 48	android/content/Context:getDir	(Ljava/lang/String;I)Ljava/io/File;
    //   579: astore 10
    //   581: aload 9
    //   583: ldc -83
    //   585: iconst_0
    //   586: invokevirtual 48	android/content/Context:getDir	(Ljava/lang/String;I)Ljava/io/File;
    //   589: astore 11
    //   591: new 175	java/util/zip/ZipFile
    //   594: dup
    //   595: aload_0
    //   596: getfield 28	com/tencent/mm/plugin/hp/a/a$a:eye	Ljava/lang/String;
    //   599: invokespecial 177	java/util/zip/ZipFile:<init>	(Ljava/lang/String;)V
    //   602: astore 6
    //   604: aload 6
    //   606: astore 4
    //   608: aload_0
    //   609: getfield 26	com/tencent/mm/plugin/hp/a/a$a:eyf	Ljava/util/List;
    //   612: invokeinterface 181 1 0
    //   617: astore 12
    //   619: iconst_1
    //   620: istore_1
    //   621: iload_1
    //   622: istore_2
    //   623: aload 6
    //   625: astore 4
    //   627: aload 12
    //   629: invokeinterface 186 1 0
    //   634: ifeq +1482 -> 2116
    //   637: iload_1
    //   638: istore_2
    //   639: aload 6
    //   641: astore 4
    //   643: aload 12
    //   645: invokeinterface 190 1 0
    //   650: checkcast 192	com/tencent/mm/plugin/hp/a/a$c
    //   653: astore 7
    //   655: iload_1
    //   656: istore_2
    //   657: aload 6
    //   659: astore 4
    //   661: aload 7
    //   663: getfield 195	com/tencent/mm/plugin/hp/a/a$c:eyh	Ljava/lang/String;
    //   666: astore 5
    //   668: iload_1
    //   669: istore_2
    //   670: aload 6
    //   672: astore 4
    //   674: aload 7
    //   676: getfield 198	com/tencent/mm/plugin/hp/a/a$c:eyi	Ljava/lang/String;
    //   679: astore 13
    //   681: iload_1
    //   682: istore_2
    //   683: aload 6
    //   685: astore 4
    //   687: aload 7
    //   689: getfield 201	com/tencent/mm/plugin/hp/a/a$c:eyj	Ljava/lang/String;
    //   692: astore 14
    //   694: iload_1
    //   695: istore_2
    //   696: aload 6
    //   698: astore 4
    //   700: aload 7
    //   702: getfield 204	com/tencent/mm/plugin/hp/a/a$c:eyk	Ljava/lang/String;
    //   705: astore 15
    //   707: iload_1
    //   708: istore_2
    //   709: aload 6
    //   711: astore 4
    //   713: aload 5
    //   715: aload 5
    //   717: ldc 123
    //   719: invokevirtual 208	java/lang/String:lastIndexOf	(Ljava/lang/String;)I
    //   722: iconst_1
    //   723: iadd
    //   724: invokevirtual 211	java/lang/String:substring	(I)Ljava/lang/String;
    //   727: astore 16
    //   729: iload_1
    //   730: istore_2
    //   731: aload 6
    //   733: astore 4
    //   735: aload 6
    //   737: aload 6
    //   739: new 109	java/lang/StringBuilder
    //   742: dup
    //   743: ldc -43
    //   745: invokespecial 214	java/lang/StringBuilder:<init>	(Ljava/lang/String;)V
    //   748: aload 5
    //   750: invokevirtual 118	java/lang/StringBuilder:append	(Ljava/lang/String;)Ljava/lang/StringBuilder;
    //   753: invokevirtual 121	java/lang/StringBuilder:toString	()Ljava/lang/String;
    //   756: invokevirtual 218	java/util/zip/ZipFile:getEntry	(Ljava/lang/String;)Ljava/util/zip/ZipEntry;
    //   759: invokevirtual 222	java/util/zip/ZipFile:getInputStream	(Ljava/util/zip/ZipEntry;)Ljava/io/InputStream;
    //   762: astore 5
    //   764: iload_1
    //   765: istore_2
    //   766: aload 6
    //   768: astore 4
    //   770: new 50	java/io/File
    //   773: dup
    //   774: aload 11
    //   776: aload 16
    //   778: invokespecial 225	java/io/File:<init>	(Ljava/io/File;Ljava/lang/String;)V
    //   781: astore 18
    //   783: new 227	java/io/FileOutputStream
    //   786: dup
    //   787: aload 18
    //   789: invokespecial 230	java/io/FileOutputStream:<init>	(Ljava/io/File;)V
    //   792: astore 4
    //   794: new 232	java/io/BufferedOutputStream
    //   797: dup
    //   798: aload 4
    //   800: invokespecial 235	java/io/BufferedOutputStream:<init>	(Ljava/io/OutputStream;)V
    //   803: astore 7
    //   805: sipush 1024
    //   808: newarray <illegal type>
    //   810: astore 17
    //   812: aload 5
    //   814: aload 17
    //   816: invokevirtual 241	java/io/InputStream:read	([B)I
    //   819: istore_2
    //   820: iload_2
    //   821: iconst_m1
    //   822: if_icmpeq +144 -> 966
    //   825: aload 7
    //   827: aload 17
    //   829: iconst_0
    //   830: iload_2
    //   831: invokevirtual 245	java/io/BufferedOutputStream:write	([BII)V
    //   834: aload 7
    //   836: invokevirtual 248	java/io/BufferedOutputStream:flush	()V
    //   839: goto -27 -> 812
    //   842: astore 9
    //   844: aload 7
    //   846: invokevirtual 251	java/io/BufferedOutputStream:close	()V
    //   849: aload 9
    //   851: athrow
    //   852: astore 7
    //   854: aload 5
    //   856: ifnull +8 -> 864
    //   859: aload 5
    //   861: invokevirtual 252	java/io/InputStream:close	()V
    //   864: aload 4
    //   866: invokevirtual 253	java/io/FileOutputStream:close	()V
    //   869: aload 7
    //   871: athrow
    //   872: astore 7
    //   874: aload 5
    //   876: ifnull +14 -> 890
    //   879: iload_1
    //   880: istore_2
    //   881: aload 6
    //   883: astore 4
    //   885: aload 5
    //   887: invokevirtual 252	java/io/InputStream:close	()V
    //   890: iload_1
    //   891: istore_2
    //   892: aload 6
    //   894: astore 4
    //   896: aload 7
    //   898: athrow
    //   899: astore 5
    //   901: iload_2
    //   902: istore_1
    //   903: aload 6
    //   905: astore 4
    //   907: ldc 75
    //   909: aload 5
    //   911: ldc -1
    //   913: iconst_0
    //   914: anewarray 4	java/lang/Object
    //   917: invokestatic 154	com/tencent/mm/sdk/platformtools/u:printErrStackTrace	(Ljava/lang/String;Ljava/lang/Throwable;Ljava/lang/String;[Ljava/lang/Object;)V
    //   920: iload_1
    //   921: istore_2
    //   922: aload 6
    //   924: ifnull +10 -> 934
    //   927: aload 6
    //   929: invokevirtual 256	java/util/zip/ZipFile:close	()V
    //   932: iload_1
    //   933: istore_2
    //   934: aload 11
    //   936: invokestatic 260	com/tencent/mm/a/e:e	(Ljava/io/File;)Z
    //   939: pop
    //   940: iload_2
    //   941: ifne +9 -> 950
    //   944: aload 10
    //   946: invokestatic 260	com/tencent/mm/a/e:e	(Ljava/io/File;)Z
    //   949: pop
    //   950: aload_0
    //   951: getfield 24	com/tencent/mm/plugin/hp/a/a$a:eyd	Z
    //   954: ifne +1233 -> 2187
    //   957: ldc 75
    //   959: ldc_w 262
    //   962: invokestatic 264	com/tencent/mm/sdk/platformtools/u:e	(Ljava/lang/String;Ljava/lang/String;)V
    //   965: return
    //   966: aload 7
    //   968: invokevirtual 251	java/io/BufferedOutputStream:close	()V
    //   971: aload 5
    //   973: ifnull +8 -> 981
    //   976: aload 5
    //   978: invokevirtual 252	java/io/InputStream:close	()V
    //   981: aload 4
    //   983: invokevirtual 253	java/io/FileOutputStream:close	()V
    //   986: aload 18
    //   988: invokestatic 268	com/tencent/mm/a/g:g	(Ljava/io/File;)Ljava/lang/String;
    //   991: astore 17
    //   993: aload 5
    //   995: ifnull +1280 -> 2275
    //   998: iload_1
    //   999: istore_2
    //   1000: aload 6
    //   1002: astore 4
    //   1004: aload 5
    //   1006: invokevirtual 252	java/io/InputStream:close	()V
    //   1009: goto +1266 -> 2275
    //   1012: iload_1
    //   1013: istore_2
    //   1014: aload 6
    //   1016: astore 4
    //   1018: ldc 75
    //   1020: new 109	java/lang/StringBuilder
    //   1023: dup
    //   1024: invokespecial 110	java/lang/StringBuilder:<init>	()V
    //   1027: aload 16
    //   1029: invokevirtual 118	java/lang/StringBuilder:append	(Ljava/lang/String;)Ljava/lang/StringBuilder;
    //   1032: ldc_w 270
    //   1035: invokevirtual 118	java/lang/StringBuilder:append	(Ljava/lang/String;)Ljava/lang/StringBuilder;
    //   1038: aload 17
    //   1040: invokevirtual 118	java/lang/StringBuilder:append	(Ljava/lang/String;)Ljava/lang/StringBuilder;
    //   1043: ldc_w 272
    //   1046: invokevirtual 118	java/lang/StringBuilder:append	(Ljava/lang/String;)Ljava/lang/StringBuilder;
    //   1049: aload 13
    //   1051: invokevirtual 118	java/lang/StringBuilder:append	(Ljava/lang/String;)Ljava/lang/StringBuilder;
    //   1054: invokevirtual 121	java/lang/StringBuilder:toString	()Ljava/lang/String;
    //   1057: invokestatic 169	com/tencent/mm/sdk/platformtools/u:i	(Ljava/lang/String;Ljava/lang/String;)V
    //   1060: iconst_0
    //   1061: istore_1
    //   1062: iload_1
    //   1063: istore_2
    //   1064: aload 6
    //   1066: astore 4
    //   1068: new 50	java/io/File
    //   1071: dup
    //   1072: aload 9
    //   1074: ldc_w 274
    //   1077: iconst_0
    //   1078: invokevirtual 48	android/content/Context:getDir	(Ljava/lang/String;I)Ljava/io/File;
    //   1081: aload 16
    //   1083: invokespecial 225	java/io/File:<init>	(Ljava/io/File;Ljava/lang/String;)V
    //   1086: astore 5
    //   1088: iload_1
    //   1089: istore_2
    //   1090: aload 6
    //   1092: astore 4
    //   1094: aload 5
    //   1096: invokevirtual 277	java/io/File:exists	()Z
    //   1099: ifne +568 -> 1667
    //   1102: iload_1
    //   1103: istore_2
    //   1104: aload 6
    //   1106: astore 4
    //   1108: new 50	java/io/File
    //   1111: dup
    //   1112: new 109	java/lang/StringBuilder
    //   1115: dup
    //   1116: invokespecial 110	java/lang/StringBuilder:<init>	()V
    //   1119: getstatic 282	com/tencent/mm/loader/stub/a:bwZ	Ljava/lang/String;
    //   1122: invokevirtual 118	java/lang/StringBuilder:append	(Ljava/lang/String;)Ljava/lang/StringBuilder;
    //   1125: ldc_w 284
    //   1128: invokevirtual 118	java/lang/StringBuilder:append	(Ljava/lang/String;)Ljava/lang/StringBuilder;
    //   1131: invokevirtual 121	java/lang/StringBuilder:toString	()Ljava/lang/String;
    //   1134: aload 16
    //   1136: invokespecial 286	java/io/File:<init>	(Ljava/lang/String;Ljava/lang/String;)V
    //   1139: astore 7
    //   1141: iload_1
    //   1142: istore_2
    //   1143: aload 6
    //   1145: astore 4
    //   1147: aload 7
    //   1149: invokevirtual 277	java/io/File:exists	()Z
    //   1152: ifeq +480 -> 1632
    //   1155: aload 7
    //   1157: astore 5
    //   1159: iload_1
    //   1160: istore_2
    //   1161: aload 6
    //   1163: astore 4
    //   1165: aload 5
    //   1167: invokestatic 268	com/tencent/mm/a/g:g	(Ljava/io/File;)Ljava/lang/String;
    //   1170: astore 7
    //   1172: aload 7
    //   1174: ifnull +8 -> 1182
    //   1177: aload 14
    //   1179: ifnonnull +523 -> 1702
    //   1182: iload_1
    //   1183: istore_2
    //   1184: aload 6
    //   1186: astore 4
    //   1188: ldc 75
    //   1190: new 109	java/lang/StringBuilder
    //   1193: dup
    //   1194: invokespecial 110	java/lang/StringBuilder:<init>	()V
    //   1197: aload 16
    //   1199: invokevirtual 118	java/lang/StringBuilder:append	(Ljava/lang/String;)Ljava/lang/StringBuilder;
    //   1202: ldc_w 288
    //   1205: invokevirtual 118	java/lang/StringBuilder:append	(Ljava/lang/String;)Ljava/lang/StringBuilder;
    //   1208: aload 7
    //   1210: invokevirtual 118	java/lang/StringBuilder:append	(Ljava/lang/String;)Ljava/lang/StringBuilder;
    //   1213: ldc_w 272
    //   1216: invokevirtual 118	java/lang/StringBuilder:append	(Ljava/lang/String;)Ljava/lang/StringBuilder;
    //   1219: aload 14
    //   1221: invokevirtual 118	java/lang/StringBuilder:append	(Ljava/lang/String;)Ljava/lang/StringBuilder;
    //   1224: invokevirtual 121	java/lang/StringBuilder:toString	()Ljava/lang/String;
    //   1227: invokestatic 169	com/tencent/mm/sdk/platformtools/u:i	(Ljava/lang/String;Ljava/lang/String;)V
    //   1230: iconst_0
    //   1231: istore_1
    //   1232: iload_1
    //   1233: istore_2
    //   1234: aload 6
    //   1236: astore 4
    //   1238: new 50	java/io/File
    //   1241: dup
    //   1242: aload 10
    //   1244: aload 16
    //   1246: invokespecial 225	java/io/File:<init>	(Ljava/io/File;Ljava/lang/String;)V
    //   1249: astore 19
    //   1251: iload_1
    //   1252: istore_2
    //   1253: aload 6
    //   1255: astore 4
    //   1257: aload 5
    //   1259: invokevirtual 292	java/io/File:length	()J
    //   1262: lconst_0
    //   1263: lcmp
    //   1264: ifgt +526 -> 1790
    //   1267: iconst_3
    //   1268: istore_3
    //   1269: iload_1
    //   1270: istore_2
    //   1271: aload 6
    //   1273: astore 4
    //   1275: ldc 75
    //   1277: new 109	java/lang/StringBuilder
    //   1280: dup
    //   1281: invokespecial 110	java/lang/StringBuilder:<init>	()V
    //   1284: aload 16
    //   1286: invokevirtual 118	java/lang/StringBuilder:append	(Ljava/lang/String;)Ljava/lang/StringBuilder;
    //   1289: ldc_w 294
    //   1292: invokevirtual 118	java/lang/StringBuilder:append	(Ljava/lang/String;)Ljava/lang/StringBuilder;
    //   1295: iload_3
    //   1296: invokevirtual 297	java/lang/StringBuilder:append	(I)Ljava/lang/StringBuilder;
    //   1299: ldc_w 299
    //   1302: invokevirtual 118	java/lang/StringBuilder:append	(Ljava/lang/String;)Ljava/lang/StringBuilder;
    //   1305: aload 19
    //   1307: invokevirtual 277	java/io/File:exists	()Z
    //   1310: invokevirtual 302	java/lang/StringBuilder:append	(Z)Ljava/lang/StringBuilder;
    //   1313: invokevirtual 121	java/lang/StringBuilder:toString	()Ljava/lang/String;
    //   1316: invokestatic 169	com/tencent/mm/sdk/platformtools/u:i	(Ljava/lang/String;Ljava/lang/String;)V
    //   1319: aconst_null
    //   1320: astore 5
    //   1322: iload_3
    //   1323: iconst_1
    //   1324: if_icmpne +757 -> 2081
    //   1327: iload_1
    //   1328: istore_2
    //   1329: aload 6
    //   1331: astore 4
    //   1333: aload 19
    //   1335: invokestatic 268	com/tencent/mm/a/g:g	(Ljava/io/File;)Ljava/lang/String;
    //   1338: astore 5
    //   1340: aload 5
    //   1342: ifnull +8 -> 1350
    //   1345: aload 15
    //   1347: ifnonnull +646 -> 1993
    //   1350: iload_1
    //   1351: istore_2
    //   1352: aload 6
    //   1354: astore 4
    //   1356: ldc 75
    //   1358: new 109	java/lang/StringBuilder
    //   1361: dup
    //   1362: invokespecial 110	java/lang/StringBuilder:<init>	()V
    //   1365: aload 16
    //   1367: invokevirtual 118	java/lang/StringBuilder:append	(Ljava/lang/String;)Ljava/lang/StringBuilder;
    //   1370: ldc_w 304
    //   1373: invokevirtual 118	java/lang/StringBuilder:append	(Ljava/lang/String;)Ljava/lang/StringBuilder;
    //   1376: aload 5
    //   1378: invokevirtual 118	java/lang/StringBuilder:append	(Ljava/lang/String;)Ljava/lang/StringBuilder;
    //   1381: ldc_w 272
    //   1384: invokevirtual 118	java/lang/StringBuilder:append	(Ljava/lang/String;)Ljava/lang/StringBuilder;
    //   1387: aload 15
    //   1389: invokevirtual 118	java/lang/StringBuilder:append	(Ljava/lang/String;)Ljava/lang/StringBuilder;
    //   1392: invokevirtual 121	java/lang/StringBuilder:toString	()Ljava/lang/String;
    //   1395: invokestatic 169	com/tencent/mm/sdk/platformtools/u:i	(Ljava/lang/String;Ljava/lang/String;)V
    //   1398: iconst_0
    //   1399: istore_1
    //   1400: iload_1
    //   1401: istore_2
    //   1402: aload 6
    //   1404: astore 4
    //   1406: ldc 75
    //   1408: new 109	java/lang/StringBuilder
    //   1411: dup
    //   1412: invokespecial 110	java/lang/StringBuilder:<init>	()V
    //   1415: aload 16
    //   1417: invokevirtual 118	java/lang/StringBuilder:append	(Ljava/lang/String;)Ljava/lang/StringBuilder;
    //   1420: ldc_w 306
    //   1423: invokevirtual 118	java/lang/StringBuilder:append	(Ljava/lang/String;)Ljava/lang/StringBuilder;
    //   1426: aload 13
    //   1428: invokevirtual 118	java/lang/StringBuilder:append	(Ljava/lang/String;)Ljava/lang/StringBuilder;
    //   1431: ldc_w 308
    //   1434: invokevirtual 118	java/lang/StringBuilder:append	(Ljava/lang/String;)Ljava/lang/StringBuilder;
    //   1437: aload 14
    //   1439: invokevirtual 118	java/lang/StringBuilder:append	(Ljava/lang/String;)Ljava/lang/StringBuilder;
    //   1442: ldc_w 310
    //   1445: invokevirtual 118	java/lang/StringBuilder:append	(Ljava/lang/String;)Ljava/lang/StringBuilder;
    //   1448: aload 15
    //   1450: invokevirtual 118	java/lang/StringBuilder:append	(Ljava/lang/String;)Ljava/lang/StringBuilder;
    //   1453: invokevirtual 121	java/lang/StringBuilder:toString	()Ljava/lang/String;
    //   1456: invokestatic 169	com/tencent/mm/sdk/platformtools/u:i	(Ljava/lang/String;Ljava/lang/String;)V
    //   1459: iload_1
    //   1460: istore_2
    //   1461: aload 6
    //   1463: astore 4
    //   1465: ldc 75
    //   1467: new 109	java/lang/StringBuilder
    //   1470: dup
    //   1471: invokespecial 110	java/lang/StringBuilder:<init>	()V
    //   1474: aload 16
    //   1476: invokevirtual 118	java/lang/StringBuilder:append	(Ljava/lang/String;)Ljava/lang/StringBuilder;
    //   1479: ldc_w 312
    //   1482: invokevirtual 118	java/lang/StringBuilder:append	(Ljava/lang/String;)Ljava/lang/StringBuilder;
    //   1485: aload 17
    //   1487: invokevirtual 118	java/lang/StringBuilder:append	(Ljava/lang/String;)Ljava/lang/StringBuilder;
    //   1490: ldc_w 314
    //   1493: invokevirtual 118	java/lang/StringBuilder:append	(Ljava/lang/String;)Ljava/lang/StringBuilder;
    //   1496: aload 7
    //   1498: invokevirtual 118	java/lang/StringBuilder:append	(Ljava/lang/String;)Ljava/lang/StringBuilder;
    //   1501: ldc_w 316
    //   1504: invokevirtual 118	java/lang/StringBuilder:append	(Ljava/lang/String;)Ljava/lang/StringBuilder;
    //   1507: aload 5
    //   1509: invokevirtual 118	java/lang/StringBuilder:append	(Ljava/lang/String;)Ljava/lang/StringBuilder;
    //   1512: invokevirtual 121	java/lang/StringBuilder:toString	()Ljava/lang/String;
    //   1515: invokestatic 169	com/tencent/mm/sdk/platformtools/u:i	(Ljava/lang/String;Ljava/lang/String;)V
    //   1518: goto -897 -> 621
    //   1521: astore 6
    //   1523: aload 4
    //   1525: astore 5
    //   1527: aload 6
    //   1529: astore 4
    //   1531: aload 5
    //   1533: ifnull +8 -> 1541
    //   1536: aload 5
    //   1538: invokevirtual 256	java/util/zip/ZipFile:close	()V
    //   1541: aload 4
    //   1543: athrow
    //   1544: iload_1
    //   1545: istore_2
    //   1546: aload 6
    //   1548: astore 4
    //   1550: aload 13
    //   1552: aload 17
    //   1554: invokevirtual 320	java/lang/String:equals	(Ljava/lang/Object;)Z
    //   1557: ifne +40 -> 1597
    //   1560: iload_1
    //   1561: istore_2
    //   1562: aload 6
    //   1564: astore 4
    //   1566: ldc 75
    //   1568: new 109	java/lang/StringBuilder
    //   1571: dup
    //   1572: invokespecial 110	java/lang/StringBuilder:<init>	()V
    //   1575: aload 16
    //   1577: invokevirtual 118	java/lang/StringBuilder:append	(Ljava/lang/String;)Ljava/lang/StringBuilder;
    //   1580: ldc_w 322
    //   1583: invokevirtual 118	java/lang/StringBuilder:append	(Ljava/lang/String;)Ljava/lang/StringBuilder;
    //   1586: invokevirtual 121	java/lang/StringBuilder:toString	()Ljava/lang/String;
    //   1589: invokestatic 264	com/tencent/mm/sdk/platformtools/u:e	(Ljava/lang/String;Ljava/lang/String;)V
    //   1592: iconst_0
    //   1593: istore_1
    //   1594: goto -532 -> 1062
    //   1597: iload_1
    //   1598: istore_2
    //   1599: aload 6
    //   1601: astore 4
    //   1603: ldc 75
    //   1605: new 109	java/lang/StringBuilder
    //   1608: dup
    //   1609: invokespecial 110	java/lang/StringBuilder:<init>	()V
    //   1612: aload 16
    //   1614: invokevirtual 118	java/lang/StringBuilder:append	(Ljava/lang/String;)Ljava/lang/StringBuilder;
    //   1617: ldc_w 324
    //   1620: invokevirtual 118	java/lang/StringBuilder:append	(Ljava/lang/String;)Ljava/lang/StringBuilder;
    //   1623: invokevirtual 121	java/lang/StringBuilder:toString	()Ljava/lang/String;
    //   1626: invokestatic 169	com/tencent/mm/sdk/platformtools/u:i	(Ljava/lang/String;Ljava/lang/String;)V
    //   1629: goto -567 -> 1062
    //   1632: iload_1
    //   1633: istore_2
    //   1634: aload 6
    //   1636: astore 4
    //   1638: ldc 75
    //   1640: new 109	java/lang/StringBuilder
    //   1643: dup
    //   1644: invokespecial 110	java/lang/StringBuilder:<init>	()V
    //   1647: aload 16
    //   1649: invokevirtual 118	java/lang/StringBuilder:append	(Ljava/lang/String;)Ljava/lang/StringBuilder;
    //   1652: ldc_w 326
    //   1655: invokevirtual 118	java/lang/StringBuilder:append	(Ljava/lang/String;)Ljava/lang/StringBuilder;
    //   1658: invokevirtual 121	java/lang/StringBuilder:toString	()Ljava/lang/String;
    //   1661: invokestatic 169	com/tencent/mm/sdk/platformtools/u:i	(Ljava/lang/String;Ljava/lang/String;)V
    //   1664: goto -505 -> 1159
    //   1667: iload_1
    //   1668: istore_2
    //   1669: aload 6
    //   1671: astore 4
    //   1673: ldc 75
    //   1675: new 109	java/lang/StringBuilder
    //   1678: dup
    //   1679: invokespecial 110	java/lang/StringBuilder:<init>	()V
    //   1682: aload 16
    //   1684: invokevirtual 118	java/lang/StringBuilder:append	(Ljava/lang/String;)Ljava/lang/StringBuilder;
    //   1687: ldc_w 328
    //   1690: invokevirtual 118	java/lang/StringBuilder:append	(Ljava/lang/String;)Ljava/lang/StringBuilder;
    //   1693: invokevirtual 121	java/lang/StringBuilder:toString	()Ljava/lang/String;
    //   1696: invokestatic 169	com/tencent/mm/sdk/platformtools/u:i	(Ljava/lang/String;Ljava/lang/String;)V
    //   1699: goto -540 -> 1159
    //   1702: iload_1
    //   1703: istore_2
    //   1704: aload 6
    //   1706: astore 4
    //   1708: aload 14
    //   1710: aload 7
    //   1712: invokevirtual 320	java/lang/String:equals	(Ljava/lang/Object;)Z
    //   1715: ifne +40 -> 1755
    //   1718: iload_1
    //   1719: istore_2
    //   1720: aload 6
    //   1722: astore 4
    //   1724: ldc 75
    //   1726: new 109	java/lang/StringBuilder
    //   1729: dup
    //   1730: invokespecial 110	java/lang/StringBuilder:<init>	()V
    //   1733: aload 16
    //   1735: invokevirtual 118	java/lang/StringBuilder:append	(Ljava/lang/String;)Ljava/lang/StringBuilder;
    //   1738: ldc_w 330
    //   1741: invokevirtual 118	java/lang/StringBuilder:append	(Ljava/lang/String;)Ljava/lang/StringBuilder;
    //   1744: invokevirtual 121	java/lang/StringBuilder:toString	()Ljava/lang/String;
    //   1747: invokestatic 264	com/tencent/mm/sdk/platformtools/u:e	(Ljava/lang/String;Ljava/lang/String;)V
    //   1750: iconst_0
    //   1751: istore_1
    //   1752: goto -520 -> 1232
    //   1755: iload_1
    //   1756: istore_2
    //   1757: aload 6
    //   1759: astore 4
    //   1761: ldc 75
    //   1763: new 109	java/lang/StringBuilder
    //   1766: dup
    //   1767: invokespecial 110	java/lang/StringBuilder:<init>	()V
    //   1770: aload 16
    //   1772: invokevirtual 118	java/lang/StringBuilder:append	(Ljava/lang/String;)Ljava/lang/StringBuilder;
    //   1775: ldc_w 332
    //   1778: invokevirtual 118	java/lang/StringBuilder:append	(Ljava/lang/String;)Ljava/lang/StringBuilder;
    //   1781: invokevirtual 121	java/lang/StringBuilder:toString	()Ljava/lang/String;
    //   1784: invokestatic 169	com/tencent/mm/sdk/platformtools/u:i	(Ljava/lang/String;Ljava/lang/String;)V
    //   1787: goto -555 -> 1232
    //   1790: iload_1
    //   1791: istore_2
    //   1792: aload 6
    //   1794: astore 4
    //   1796: aload 18
    //   1798: invokevirtual 292	java/io/File:length	()J
    //   1801: lconst_0
    //   1802: lcmp
    //   1803: ifgt +8 -> 1811
    //   1806: iconst_2
    //   1807: istore_3
    //   1808: goto -539 -> 1269
    //   1811: iload_1
    //   1812: istore_2
    //   1813: aload 6
    //   1815: astore 4
    //   1817: new 334	java/io/BufferedInputStream
    //   1820: dup
    //   1821: new 336	java/io/FileInputStream
    //   1824: dup
    //   1825: aload 5
    //   1827: invokespecial 337	java/io/FileInputStream:<init>	(Ljava/io/File;)V
    //   1830: invokespecial 340	java/io/BufferedInputStream:<init>	(Ljava/io/InputStream;)V
    //   1833: astore 20
    //   1835: iload_1
    //   1836: istore_2
    //   1837: aload 6
    //   1839: astore 4
    //   1841: aload 18
    //   1843: invokevirtual 292	java/io/File:length	()J
    //   1846: l2i
    //   1847: newarray <illegal type>
    //   1849: astore 21
    //   1851: iload_1
    //   1852: istore_2
    //   1853: aload 6
    //   1855: astore 4
    //   1857: new 336	java/io/FileInputStream
    //   1860: dup
    //   1861: aload 18
    //   1863: invokespecial 337	java/io/FileInputStream:<init>	(Ljava/io/File;)V
    //   1866: aload 21
    //   1868: iconst_0
    //   1869: aload 21
    //   1871: arraylength
    //   1872: invokestatic 345	com/tencent/mm/b/d:a	(Ljava/io/InputStream;[BII)Z
    //   1875: pop
    //   1876: iload_1
    //   1877: istore_2
    //   1878: aload 6
    //   1880: astore 4
    //   1882: aload 5
    //   1884: invokevirtual 292	java/io/File:length	()J
    //   1887: l2i
    //   1888: istore_3
    //   1889: iload_1
    //   1890: istore_2
    //   1891: aload 6
    //   1893: astore 4
    //   1895: iload_3
    //   1896: newarray <illegal type>
    //   1898: astore 5
    //   1900: iload_1
    //   1901: istore_2
    //   1902: aload 6
    //   1904: astore 4
    //   1906: aload 20
    //   1908: aload 5
    //   1910: iconst_0
    //   1911: iload_3
    //   1912: invokestatic 345	com/tencent/mm/b/d:a	(Ljava/io/InputStream;[BII)Z
    //   1915: pop
    //   1916: iload_1
    //   1917: istore_2
    //   1918: aload 6
    //   1920: astore 4
    //   1922: aload 20
    //   1924: invokevirtual 252	java/io/InputStream:close	()V
    //   1927: iload_1
    //   1928: istore_2
    //   1929: aload 6
    //   1931: astore 4
    //   1933: aload 5
    //   1935: iload_3
    //   1936: aload 21
    //   1938: aload 21
    //   1940: arraylength
    //   1941: iconst_0
    //   1942: invokestatic 350	com/tencent/mm/b/c:a	([BI[BII)[B
    //   1945: astore 5
    //   1947: iload_1
    //   1948: istore_2
    //   1949: aload 6
    //   1951: astore 4
    //   1953: new 227	java/io/FileOutputStream
    //   1956: dup
    //   1957: aload 19
    //   1959: invokespecial 230	java/io/FileOutputStream:<init>	(Ljava/io/File;)V
    //   1962: astore 18
    //   1964: iload_1
    //   1965: istore_2
    //   1966: aload 6
    //   1968: astore 4
    //   1970: aload 18
    //   1972: aload 5
    //   1974: invokevirtual 355	java/io/OutputStream:write	([B)V
    //   1977: iload_1
    //   1978: istore_2
    //   1979: aload 6
    //   1981: astore 4
    //   1983: aload 18
    //   1985: invokevirtual 356	java/io/OutputStream:close	()V
    //   1988: iconst_1
    //   1989: istore_3
    //   1990: goto -721 -> 1269
    //   1993: iload_1
    //   1994: istore_2
    //   1995: aload 6
    //   1997: astore 4
    //   1999: aload 15
    //   2001: aload 5
    //   2003: invokevirtual 320	java/lang/String:equals	(Ljava/lang/Object;)Z
    //   2006: ifne +40 -> 2046
    //   2009: iload_1
    //   2010: istore_2
    //   2011: aload 6
    //   2013: astore 4
    //   2015: ldc 75
    //   2017: new 109	java/lang/StringBuilder
    //   2020: dup
    //   2021: invokespecial 110	java/lang/StringBuilder:<init>	()V
    //   2024: aload 16
    //   2026: invokevirtual 118	java/lang/StringBuilder:append	(Ljava/lang/String;)Ljava/lang/StringBuilder;
    //   2029: ldc_w 358
    //   2032: invokevirtual 118	java/lang/StringBuilder:append	(Ljava/lang/String;)Ljava/lang/StringBuilder;
    //   2035: invokevirtual 121	java/lang/StringBuilder:toString	()Ljava/lang/String;
    //   2038: invokestatic 264	com/tencent/mm/sdk/platformtools/u:e	(Ljava/lang/String;Ljava/lang/String;)V
    //   2041: iconst_0
    //   2042: istore_1
    //   2043: goto -643 -> 1400
    //   2046: iload_1
    //   2047: istore_2
    //   2048: aload 6
    //   2050: astore 4
    //   2052: ldc 75
    //   2054: new 109	java/lang/StringBuilder
    //   2057: dup
    //   2058: invokespecial 110	java/lang/StringBuilder:<init>	()V
    //   2061: aload 16
    //   2063: invokevirtual 118	java/lang/StringBuilder:append	(Ljava/lang/String;)Ljava/lang/StringBuilder;
    //   2066: ldc_w 360
    //   2069: invokevirtual 118	java/lang/StringBuilder:append	(Ljava/lang/String;)Ljava/lang/StringBuilder;
    //   2072: invokevirtual 121	java/lang/StringBuilder:toString	()Ljava/lang/String;
    //   2075: invokestatic 169	com/tencent/mm/sdk/platformtools/u:i	(Ljava/lang/String;Ljava/lang/String;)V
    //   2078: goto -678 -> 1400
    //   2081: iload_1
    //   2082: istore_2
    //   2083: aload 6
    //   2085: astore 4
    //   2087: ldc 75
    //   2089: new 109	java/lang/StringBuilder
    //   2092: dup
    //   2093: invokespecial 110	java/lang/StringBuilder:<init>	()V
    //   2096: aload 16
    //   2098: invokevirtual 118	java/lang/StringBuilder:append	(Ljava/lang/String;)Ljava/lang/StringBuilder;
    //   2101: ldc_w 362
    //   2104: invokevirtual 118	java/lang/StringBuilder:append	(Ljava/lang/String;)Ljava/lang/StringBuilder;
    //   2107: invokevirtual 121	java/lang/StringBuilder:toString	()Ljava/lang/String;
    //   2110: invokestatic 264	com/tencent/mm/sdk/platformtools/u:e	(Ljava/lang/String;Ljava/lang/String;)V
    //   2113: goto -713 -> 1400
    //   2116: aload 6
    //   2118: invokevirtual 256	java/util/zip/ZipFile:close	()V
    //   2121: iload_1
    //   2122: istore_2
    //   2123: goto -1189 -> 934
    //   2126: astore 4
    //   2128: ldc 75
    //   2130: aload 4
    //   2132: ldc_w 364
    //   2135: iconst_0
    //   2136: anewarray 4	java/lang/Object
    //   2139: invokestatic 154	com/tencent/mm/sdk/platformtools/u:printErrStackTrace	(Ljava/lang/String;Ljava/lang/Throwable;Ljava/lang/String;[Ljava/lang/Object;)V
    //   2142: iload_1
    //   2143: istore_2
    //   2144: goto -1210 -> 934
    //   2147: astore 4
    //   2149: ldc 75
    //   2151: aload 4
    //   2153: ldc_w 364
    //   2156: iconst_0
    //   2157: anewarray 4	java/lang/Object
    //   2160: invokestatic 154	com/tencent/mm/sdk/platformtools/u:printErrStackTrace	(Ljava/lang/String;Ljava/lang/Throwable;Ljava/lang/String;[Ljava/lang/Object;)V
    //   2163: iload_1
    //   2164: istore_2
    //   2165: goto -1231 -> 934
    //   2168: astore 5
    //   2170: ldc 75
    //   2172: aload 5
    //   2174: ldc_w 364
    //   2177: iconst_0
    //   2178: anewarray 4	java/lang/Object
    //   2181: invokestatic 154	com/tencent/mm/sdk/platformtools/u:printErrStackTrace	(Ljava/lang/String;Ljava/lang/Throwable;Ljava/lang/String;[Ljava/lang/Object;)V
    //   2184: goto -643 -> 1541
    //   2187: ldc 75
    //   2189: ldc_w 366
    //   2192: iconst_1
    //   2193: anewarray 4	java/lang/Object
    //   2196: dup
    //   2197: iconst_0
    //   2198: new 109	java/lang/StringBuilder
    //   2201: dup
    //   2202: invokespecial 110	java/lang/StringBuilder:<init>	()V
    //   2205: getstatic 371	com/tencent/mm/compatible/util/d:bxa	Ljava/lang/String;
    //   2208: invokevirtual 118	java/lang/StringBuilder:append	(Ljava/lang/String;)Ljava/lang/StringBuilder;
    //   2211: ldc_w 373
    //   2214: invokevirtual 118	java/lang/StringBuilder:append	(Ljava/lang/String;)Ljava/lang/StringBuilder;
    //   2217: invokevirtual 121	java/lang/StringBuilder:toString	()Ljava/lang/String;
    //   2220: aload 8
    //   2222: aload 8
    //   2224: arraylength
    //   2225: invokestatic 377	com/tencent/mm/a/e:b	(Ljava/lang/String;[BI)I
    //   2228: invokestatic 383	java/lang/Integer:valueOf	(I)Ljava/lang/Integer;
    //   2231: aastore
    //   2232: invokestatic 83	com/tencent/mm/sdk/platformtools/u:w	(Ljava/lang/String;Ljava/lang/String;[Ljava/lang/Object;)V
    //   2235: invokestatic 388	com/tencent/mm/plugin/hp/a/b:acC	()V
    //   2238: new 11	com/tencent/mm/plugin/hp/a/a$a$1
    //   2241: dup
    //   2242: aload_0
    //   2243: invokespecial 391	com/tencent/mm/plugin/hp/a/a$a$1:<init>	(Lcom/tencent/mm/plugin/hp/a/a$a;)V
    //   2246: invokestatic 395	com/tencent/mm/plugin/hp/a/a:l	(Ljava/lang/Runnable;)V
    //   2249: return
    //   2250: astore 4
    //   2252: aconst_null
    //   2253: astore 5
    //   2255: goto -724 -> 1531
    //   2258: astore 5
    //   2260: aconst_null
    //   2261: astore 6
    //   2263: iconst_1
    //   2264: istore_1
    //   2265: goto -1362 -> 903
    //   2268: astore 5
    //   2270: iconst_1
    //   2271: istore_1
    //   2272: goto -1369 -> 903
    //   2275: aload 17
    //   2277: ifnull -1265 -> 1012
    //   2280: aload 13
    //   2282: ifnonnull -738 -> 1544
    //   2285: goto -1273 -> 1012
    // Local variable table:
    //   start	length	slot	name	signature
    //   0	2288	0	this	a
    //   27	2245	1	i	int
    //   25	2140	2	j	int
    //   1268	722	3	k	int
    //   13	478	4	localObject1	Object
    //   505	5	4	localException1	Exception
    //   606	1480	4	localObject2	Object
    //   2126	5	4	localException2	Exception
    //   2147	5	4	localException3	Exception
    //   2250	1	4	localObject3	Object
    //   20	866	5	localObject4	Object
    //   899	106	5	localException4	Exception
    //   1086	916	5	localObject5	Object
    //   2168	5	5	localException5	Exception
    //   2253	1	5	localObject6	Object
    //   2258	1	5	localException6	Exception
    //   2268	1	5	localException7	Exception
    //   37	1425	6	localObject7	Object
    //   1521	596	6	localObject8	Object
    //   2261	1	6	localObject9	Object
    //   52	793	7	localObject10	Object
    //   852	18	7	localObject11	Object
    //   872	95	7	localObject12	Object
    //   1139	572	7	localObject13	Object
    //   166	2057	8	localObject14	Object
    //   3	579	9	localContext	android.content.Context
    //   842	231	9	localObject15	Object
    //   579	664	10	localFile1	java.io.File
    //   589	346	11	localFile2	java.io.File
    //   617	27	12	localIterator	java.util.Iterator
    //   679	1602	13	str1	String
    //   692	1017	14	str2	String
    //   705	1295	15	str3	String
    //   727	1370	16	str4	String
    //   810	1466	17	localObject16	Object
    //   781	1203	18	localObject17	Object
    //   1249	709	19	localFile3	java.io.File
    //   1833	90	20	localBufferedInputStream	java.io.BufferedInputStream
    //   1849	90	21	arrayOfByte	byte[]
    // Exception table:
    //   from	to	target	type
    //   405	430	505	java/lang/Exception
    //   437	455	505	java/lang/Exception
    //   462	473	505	java/lang/Exception
    //   480	498	505	java/lang/Exception
    //   805	812	842	finally
    //   812	820	842	finally
    //   825	839	842	finally
    //   794	805	852	finally
    //   844	852	852	finally
    //   966	971	852	finally
    //   783	794	872	finally
    //   859	864	872	finally
    //   864	872	872	finally
    //   976	981	872	finally
    //   981	993	872	finally
    //   627	637	899	java/lang/Exception
    //   643	655	899	java/lang/Exception
    //   661	668	899	java/lang/Exception
    //   674	681	899	java/lang/Exception
    //   687	694	899	java/lang/Exception
    //   700	707	899	java/lang/Exception
    //   713	729	899	java/lang/Exception
    //   735	764	899	java/lang/Exception
    //   770	783	899	java/lang/Exception
    //   885	890	899	java/lang/Exception
    //   896	899	899	java/lang/Exception
    //   1004	1009	899	java/lang/Exception
    //   1018	1060	899	java/lang/Exception
    //   1068	1088	899	java/lang/Exception
    //   1094	1102	899	java/lang/Exception
    //   1108	1141	899	java/lang/Exception
    //   1147	1155	899	java/lang/Exception
    //   1165	1172	899	java/lang/Exception
    //   1188	1230	899	java/lang/Exception
    //   1238	1251	899	java/lang/Exception
    //   1257	1267	899	java/lang/Exception
    //   1275	1319	899	java/lang/Exception
    //   1333	1340	899	java/lang/Exception
    //   1356	1398	899	java/lang/Exception
    //   1406	1459	899	java/lang/Exception
    //   1465	1518	899	java/lang/Exception
    //   1550	1560	899	java/lang/Exception
    //   1566	1592	899	java/lang/Exception
    //   1603	1629	899	java/lang/Exception
    //   1638	1664	899	java/lang/Exception
    //   1673	1699	899	java/lang/Exception
    //   1708	1718	899	java/lang/Exception
    //   1724	1750	899	java/lang/Exception
    //   1761	1787	899	java/lang/Exception
    //   1796	1806	899	java/lang/Exception
    //   1817	1835	899	java/lang/Exception
    //   1841	1851	899	java/lang/Exception
    //   1857	1876	899	java/lang/Exception
    //   1882	1889	899	java/lang/Exception
    //   1895	1900	899	java/lang/Exception
    //   1906	1916	899	java/lang/Exception
    //   1922	1927	899	java/lang/Exception
    //   1933	1947	899	java/lang/Exception
    //   1953	1964	899	java/lang/Exception
    //   1970	1977	899	java/lang/Exception
    //   1983	1988	899	java/lang/Exception
    //   1999	2009	899	java/lang/Exception
    //   2015	2041	899	java/lang/Exception
    //   2052	2078	899	java/lang/Exception
    //   2087	2113	899	java/lang/Exception
    //   608	619	1521	finally
    //   627	637	1521	finally
    //   643	655	1521	finally
    //   661	668	1521	finally
    //   674	681	1521	finally
    //   687	694	1521	finally
    //   700	707	1521	finally
    //   713	729	1521	finally
    //   735	764	1521	finally
    //   770	783	1521	finally
    //   885	890	1521	finally
    //   896	899	1521	finally
    //   907	920	1521	finally
    //   1004	1009	1521	finally
    //   1018	1060	1521	finally
    //   1068	1088	1521	finally
    //   1094	1102	1521	finally
    //   1108	1141	1521	finally
    //   1147	1155	1521	finally
    //   1165	1172	1521	finally
    //   1188	1230	1521	finally
    //   1238	1251	1521	finally
    //   1257	1267	1521	finally
    //   1275	1319	1521	finally
    //   1333	1340	1521	finally
    //   1356	1398	1521	finally
    //   1406	1459	1521	finally
    //   1465	1518	1521	finally
    //   1550	1560	1521	finally
    //   1566	1592	1521	finally
    //   1603	1629	1521	finally
    //   1638	1664	1521	finally
    //   1673	1699	1521	finally
    //   1708	1718	1521	finally
    //   1724	1750	1521	finally
    //   1761	1787	1521	finally
    //   1796	1806	1521	finally
    //   1817	1835	1521	finally
    //   1841	1851	1521	finally
    //   1857	1876	1521	finally
    //   1882	1889	1521	finally
    //   1895	1900	1521	finally
    //   1906	1916	1521	finally
    //   1922	1927	1521	finally
    //   1933	1947	1521	finally
    //   1953	1964	1521	finally
    //   1970	1977	1521	finally
    //   1983	1988	1521	finally
    //   1999	2009	1521	finally
    //   2015	2041	1521	finally
    //   2052	2078	1521	finally
    //   2087	2113	1521	finally
    //   2116	2121	2126	java/lang/Exception
    //   927	932	2147	java/lang/Exception
    //   1536	1541	2168	java/lang/Exception
    //   591	604	2250	finally
    //   591	604	2258	java/lang/Exception
    //   608	619	2268	java/lang/Exception
  }
}

/* Location:
 * Qualified Name:     com.tencent.mm.plugin.hp.a.a.a
 * Java Class Version: 6 (50.0)
 * JD-Core Version:    0.7.1
 */