package com.tencent.mm.plugin.hp.a;

final class a$b
  implements Runnable
{
  private String aut;
  private boolean bEj = true;
  private String eye;
  private String url;
  
  public a$b(String paramString1, String paramString2, String paramString3)
  {
    url = paramString1;
    eye = paramString2;
    aut = paramString3;
  }
  
  /* Error */
  public final void run()
  {
    // Byte code:
    //   0: aconst_null
    //   1: astore 4
    //   3: aconst_null
    //   4: astore 5
    //   6: aload_0
    //   7: getfield 24	com/tencent/mm/plugin/hp/a/a$b:url	Ljava/lang/String;
    //   10: aconst_null
    //   11: invokestatic 41	com/tencent/mm/network/b:a	(Ljava/lang/String;Lcom/tencent/mm/network/b$b;)Lcom/tencent/mm/network/s;
    //   14: astore_2
    //   15: aload_2
    //   16: ldc 43
    //   18: invokevirtual 49	com/tencent/mm/network/s:setRequestMethod	(Ljava/lang/String;)V
    //   21: aload_2
    //   22: sipush 5000
    //   25: invokevirtual 53	com/tencent/mm/network/s:setConnectTimeout	(I)V
    //   28: aload_2
    //   29: sipush 5000
    //   32: invokevirtual 56	com/tencent/mm/network/s:setReadTimeout	(I)V
    //   35: aload_2
    //   36: invokestatic 59	com/tencent/mm/network/b:a	(Lcom/tencent/mm/network/s;)I
    //   39: ifeq +22 -> 61
    //   42: ldc 61
    //   44: ldc 63
    //   46: iconst_1
    //   47: anewarray 4	java/lang/Object
    //   50: dup
    //   51: iconst_0
    //   52: aload_0
    //   53: getfield 24	com/tencent/mm/plugin/hp/a/a$b:url	Ljava/lang/String;
    //   56: aastore
    //   57: invokestatic 69	com/tencent/mm/sdk/platformtools/u:e	(Ljava/lang/String;Ljava/lang/String;[Ljava/lang/Object;)V
    //   60: return
    //   61: aload_2
    //   62: invokevirtual 73	com/tencent/mm/network/s:getInputStream	()Ljava/io/InputStream;
    //   65: astore_3
    //   66: aload_3
    //   67: ifnonnull +127 -> 194
    //   70: ldc 61
    //   72: ldc 75
    //   74: iconst_1
    //   75: anewarray 4	java/lang/Object
    //   78: dup
    //   79: iconst_0
    //   80: aload_0
    //   81: getfield 24	com/tencent/mm/plugin/hp/a/a$b:url	Ljava/lang/String;
    //   84: aastore
    //   85: invokestatic 78	com/tencent/mm/sdk/platformtools/u:d	(Ljava/lang/String;Ljava/lang/String;[Ljava/lang/Object;)V
    //   88: return
    //   89: astore 4
    //   91: aload_3
    //   92: astore 5
    //   94: aconst_null
    //   95: astore 6
    //   97: aload_2
    //   98: astore_3
    //   99: aload 6
    //   101: astore_2
    //   102: ldc 61
    //   104: ldc 80
    //   106: iconst_1
    //   107: anewarray 4	java/lang/Object
    //   110: dup
    //   111: iconst_0
    //   112: aload 4
    //   114: invokestatic 85	com/tencent/mm/sdk/platformtools/ay:b	(Ljava/lang/Throwable;)Ljava/lang/String;
    //   117: aastore
    //   118: invokestatic 69	com/tencent/mm/sdk/platformtools/u:e	(Ljava/lang/String;Ljava/lang/String;[Ljava/lang/Object;)V
    //   121: aload_0
    //   122: iconst_1
    //   123: putfield 22	com/tencent/mm/plugin/hp/a/a$b:bEj	Z
    //   126: aload_3
    //   127: ifnull +10 -> 137
    //   130: aload_3
    //   131: getfield 89	com/tencent/mm/network/s:cjv	Ljava/net/HttpURLConnection;
    //   134: invokevirtual 94	java/net/HttpURLConnection:disconnect	()V
    //   137: aload 5
    //   139: ifnull +8 -> 147
    //   142: aload 5
    //   144: invokevirtual 99	java/io/InputStream:close	()V
    //   147: aload_2
    //   148: ifnull +185 -> 333
    //   151: aload_2
    //   152: invokevirtual 102	java/io/OutputStream:close	()V
    //   155: return
    //   156: astore_2
    //   157: ldc 61
    //   159: ldc 80
    //   161: iconst_1
    //   162: anewarray 4	java/lang/Object
    //   165: dup
    //   166: iconst_0
    //   167: aload_2
    //   168: invokestatic 85	com/tencent/mm/sdk/platformtools/ay:b	(Ljava/lang/Throwable;)Ljava/lang/String;
    //   171: aastore
    //   172: invokestatic 69	com/tencent/mm/sdk/platformtools/u:e	(Ljava/lang/String;Ljava/lang/String;[Ljava/lang/Object;)V
    //   175: ldc 61
    //   177: ldc 104
    //   179: iconst_1
    //   180: anewarray 4	java/lang/Object
    //   183: dup
    //   184: iconst_0
    //   185: aload_2
    //   186: invokevirtual 108	java/lang/Exception:getMessage	()Ljava/lang/String;
    //   189: aastore
    //   190: invokestatic 69	com/tencent/mm/sdk/platformtools/u:e	(Ljava/lang/String;Ljava/lang/String;[Ljava/lang/Object;)V
    //   193: return
    //   194: sipush 1024
    //   197: newarray <illegal type>
    //   199: astore 7
    //   201: aload_0
    //   202: getfield 26	com/tencent/mm/plugin/hp/a/a$b:eye	Ljava/lang/String;
    //   205: invokestatic 114	com/tencent/mm/modelsfs/FileOp:iI	(Ljava/lang/String;)Ljava/io/OutputStream;
    //   208: astore 6
    //   210: aload_3
    //   211: aload 7
    //   213: invokevirtual 118	java/io/InputStream:read	([B)I
    //   216: istore_1
    //   217: iload_1
    //   218: iconst_m1
    //   219: if_icmpeq +15 -> 234
    //   222: aload 6
    //   224: aload 7
    //   226: iconst_0
    //   227: iload_1
    //   228: invokevirtual 122	java/io/OutputStream:write	([BII)V
    //   231: goto -21 -> 210
    //   234: aload_0
    //   235: iconst_0
    //   236: putfield 22	com/tencent/mm/plugin/hp/a/a$b:bEj	Z
    //   239: aload 6
    //   241: invokevirtual 102	java/io/OutputStream:close	()V
    //   244: aload_2
    //   245: getfield 89	com/tencent/mm/network/s:cjv	Ljava/net/HttpURLConnection;
    //   248: invokevirtual 94	java/net/HttpURLConnection:disconnect	()V
    //   251: aload_3
    //   252: invokevirtual 99	java/io/InputStream:close	()V
    //   255: aload_0
    //   256: getfield 26	com/tencent/mm/plugin/hp/a/a$b:eye	Ljava/lang/String;
    //   259: invokestatic 128	com/tencent/mm/a/g:aC	(Ljava/lang/String;)Ljava/lang/String;
    //   262: aload_0
    //   263: getfield 28	com/tencent/mm/plugin/hp/a/a$b:aut	Ljava/lang/String;
    //   266: invokevirtual 134	java/lang/String:equalsIgnoreCase	(Ljava/lang/String;)Z
    //   269: ifne +15 -> 284
    //   272: ldc 61
    //   274: ldc -120
    //   276: invokestatic 139	com/tencent/mm/sdk/platformtools/u:d	(Ljava/lang/String;Ljava/lang/String;)V
    //   279: aload_0
    //   280: iconst_1
    //   281: putfield 22	com/tencent/mm/plugin/hp/a/a$b:bEj	Z
    //   284: aconst_null
    //   285: astore_2
    //   286: aconst_null
    //   287: astore_3
    //   288: aload 4
    //   290: astore 5
    //   292: goto -166 -> 126
    //   295: astore 4
    //   297: aconst_null
    //   298: astore_2
    //   299: aconst_null
    //   300: astore_3
    //   301: goto -199 -> 102
    //   304: astore 4
    //   306: aconst_null
    //   307: astore 6
    //   309: aload_2
    //   310: astore_3
    //   311: aload 6
    //   313: astore_2
    //   314: goto -212 -> 102
    //   317: astore 4
    //   319: aconst_null
    //   320: astore 6
    //   322: aconst_null
    //   323: astore_2
    //   324: aload_3
    //   325: astore 5
    //   327: aload 6
    //   329: astore_3
    //   330: goto -228 -> 102
    //   333: return
    //   334: astore 4
    //   336: aload_2
    //   337: astore 7
    //   339: aload_3
    //   340: astore 5
    //   342: aload 6
    //   344: astore_2
    //   345: aload 7
    //   347: astore_3
    //   348: goto -246 -> 102
    // Local variable table:
    //   start	length	slot	name	signature
    //   0	351	0	this	b
    //   216	12	1	i	int
    //   14	138	2	localObject1	Object
    //   156	89	2	localException1	Exception
    //   285	60	2	localObject2	Object
    //   65	283	3	localObject3	Object
    //   1	1	4	localObject4	Object
    //   89	200	4	localException2	Exception
    //   295	1	4	localException3	Exception
    //   304	1	4	localException4	Exception
    //   317	1	4	localException5	Exception
    //   334	1	4	localException6	Exception
    //   4	337	5	localObject5	Object
    //   95	248	6	localOutputStream	java.io.OutputStream
    //   199	147	7	localObject6	Object
    // Exception table:
    //   from	to	target	type
    //   70	88	89	java/lang/Exception
    //   194	210	89	java/lang/Exception
    //   244	251	89	java/lang/Exception
    //   130	137	156	java/lang/Exception
    //   142	147	156	java/lang/Exception
    //   151	155	156	java/lang/Exception
    //   6	15	295	java/lang/Exception
    //   255	284	295	java/lang/Exception
    //   15	60	304	java/lang/Exception
    //   61	66	304	java/lang/Exception
    //   251	255	317	java/lang/Exception
    //   210	217	334	java/lang/Exception
    //   222	231	334	java/lang/Exception
    //   234	244	334	java/lang/Exception
  }
}

/* Location:
 * Qualified Name:     com.tencent.mm.plugin.hp.a.a.b
 * Java Class Version: 6 (50.0)
 * JD-Core Version:    0.7.1
 */