package com.tencent.mm.plugin.hp.a;

import com.tencent.mm.sdk.platformtools.u;
import java.util.List;
import java.util.Map;

final class a$d
  implements Runnable
{
  private boolean eyd = false;
  private String eye;
  private List eyf = null;
  private int eyl = 25;
  private Map values;
  
  public a$d(String paramString)
  {
    eye = paramString;
  }
  
  private static boolean w(String paramString1, String paramString2, String paramString3)
  {
    if (!paramString1.equalsIgnoreCase(paramString2))
    {
      u.e("!44@/B4Tb64lLpJqCbAKGOgG7nvk0ZBVocytok34hobwMJ4=", paramString3, new Object[] { paramString1, paramString2 });
      return false;
    }
    return true;
  }
  
  /* Error */
  public final void run()
  {
    // Byte code:
    //   0: aconst_null
    //   1: astore 5
    //   3: aconst_null
    //   4: astore_2
    //   5: aconst_null
    //   6: astore 6
    //   8: aconst_null
    //   9: astore_3
    //   10: aload_0
    //   11: getfield 32	com/tencent/mm/plugin/hp/a/a$d:eye	Ljava/lang/String;
    //   14: invokestatic 67	com/tencent/mm/compatible/loader/b:db	(Ljava/lang/String;)Z
    //   17: ifne +17 -> 34
    //   20: ldc 54
    //   22: ldc 69
    //   24: invokestatic 72	com/tencent/mm/sdk/platformtools/u:e	(Ljava/lang/String;Ljava/lang/String;)V
    //   27: aload_0
    //   28: bipush 26
    //   30: putfield 28	com/tencent/mm/plugin/hp/a/a$d:eyl	I
    //   33: return
    //   34: new 74	java/util/zip/ZipFile
    //   37: dup
    //   38: aload_0
    //   39: getfield 32	com/tencent/mm/plugin/hp/a/a$d:eye	Ljava/lang/String;
    //   42: invokespecial 76	java/util/zip/ZipFile:<init>	(Ljava/lang/String;)V
    //   45: astore 4
    //   47: aload_2
    //   48: astore 5
    //   50: aload 6
    //   52: astore_3
    //   53: aload 4
    //   55: ldc 78
    //   57: invokevirtual 82	java/util/zip/ZipFile:getEntry	(Ljava/lang/String;)Ljava/util/zip/ZipEntry;
    //   60: astore 7
    //   62: aload 7
    //   64: ifnonnull +24 -> 88
    //   67: aload_2
    //   68: astore 5
    //   70: aload 6
    //   72: astore_3
    //   73: ldc 54
    //   75: ldc 84
    //   77: invokestatic 72	com/tencent/mm/sdk/platformtools/u:e	(Ljava/lang/String;Ljava/lang/String;)V
    //   80: aload 4
    //   82: invokevirtual 87	java/util/zip/ZipFile:close	()V
    //   85: return
    //   86: astore_2
    //   87: return
    //   88: aload_2
    //   89: astore 5
    //   91: aload 6
    //   93: astore_3
    //   94: aload 4
    //   96: aload 7
    //   98: invokevirtual 91	java/util/zip/ZipFile:getInputStream	(Ljava/util/zip/ZipEntry;)Ljava/io/InputStream;
    //   101: astore_2
    //   102: aload_2
    //   103: astore 5
    //   105: aload_2
    //   106: astore_3
    //   107: aload_0
    //   108: aload_2
    //   109: invokestatic 96	com/tencent/mm/sdk/platformtools/ay:d	(Ljava/io/InputStream;)Ljava/lang/String;
    //   112: invokestatic 102	com/tencent/mm/sdk/platformtools/q:CK	(Ljava/lang/String;)Ljava/util/Map;
    //   115: putfield 39	com/tencent/mm/plugin/hp/a/a$d:values	Ljava/util/Map;
    //   118: aload_2
    //   119: astore 5
    //   121: aload_2
    //   122: astore_3
    //   123: aload_0
    //   124: getfield 39	com/tencent/mm/plugin/hp/a/a$d:values	Ljava/util/Map;
    //   127: ifnonnull +42 -> 169
    //   130: aload_2
    //   131: astore 5
    //   133: aload_2
    //   134: astore_3
    //   135: ldc 54
    //   137: ldc 104
    //   139: invokestatic 72	com/tencent/mm/sdk/platformtools/u:e	(Ljava/lang/String;Ljava/lang/String;)V
    //   142: aload_2
    //   143: astore 5
    //   145: aload_2
    //   146: astore_3
    //   147: aload_0
    //   148: bipush 25
    //   150: putfield 28	com/tencent/mm/plugin/hp/a/a$d:eyl	I
    //   153: aload_2
    //   154: ifnull +7 -> 161
    //   157: aload_2
    //   158: invokevirtual 107	java/io/InputStream:close	()V
    //   161: aload 4
    //   163: invokevirtual 87	java/util/zip/ZipFile:close	()V
    //   166: return
    //   167: astore_2
    //   168: return
    //   169: aload_2
    //   170: astore 5
    //   172: aload_2
    //   173: astore_3
    //   174: getstatic 112	com/tencent/mm/loader/stub/BaseBuildInfo:btx	Ljava/lang/String;
    //   177: aload_0
    //   178: getfield 39	com/tencent/mm/plugin/hp/a/a$d:values	Ljava/util/Map;
    //   181: ldc 114
    //   183: invokeinterface 120 2 0
    //   188: checkcast 48	java/lang/String
    //   191: ldc 122
    //   193: invokestatic 124	com/tencent/mm/plugin/hp/a/a$d:w	(Ljava/lang/String;Ljava/lang/String;Ljava/lang/String;)Z
    //   196: ifne +30 -> 226
    //   199: aload_2
    //   200: astore 5
    //   202: aload_2
    //   203: astore_3
    //   204: aload_0
    //   205: bipush 19
    //   207: putfield 28	com/tencent/mm/plugin/hp/a/a$d:eyl	I
    //   210: aload_2
    //   211: ifnull +7 -> 218
    //   214: aload_2
    //   215: invokevirtual 107	java/io/InputStream:close	()V
    //   218: aload 4
    //   220: invokevirtual 87	java/util/zip/ZipFile:close	()V
    //   223: return
    //   224: astore_2
    //   225: return
    //   226: aload_2
    //   227: astore 5
    //   229: aload_2
    //   230: astore_3
    //   231: getstatic 127	com/tencent/mm/loader/stub/BaseBuildInfo:bwQ	Ljava/lang/String;
    //   234: aload_0
    //   235: getfield 39	com/tencent/mm/plugin/hp/a/a$d:values	Ljava/util/Map;
    //   238: ldc -127
    //   240: invokeinterface 120 2 0
    //   245: checkcast 48	java/lang/String
    //   248: ldc -125
    //   250: invokestatic 124	com/tencent/mm/plugin/hp/a/a$d:w	(Ljava/lang/String;Ljava/lang/String;Ljava/lang/String;)Z
    //   253: ifne +30 -> 283
    //   256: aload_2
    //   257: astore 5
    //   259: aload_2
    //   260: astore_3
    //   261: aload_0
    //   262: bipush 20
    //   264: putfield 28	com/tencent/mm/plugin/hp/a/a$d:eyl	I
    //   267: aload_2
    //   268: ifnull +7 -> 275
    //   271: aload_2
    //   272: invokevirtual 107	java/io/InputStream:close	()V
    //   275: aload 4
    //   277: invokevirtual 87	java/util/zip/ZipFile:close	()V
    //   280: return
    //   281: astore_2
    //   282: return
    //   283: aload_2
    //   284: astore 5
    //   286: aload_2
    //   287: astore_3
    //   288: getstatic 134	com/tencent/mm/loader/stub/BaseBuildInfo:bwY	Ljava/lang/String;
    //   291: ifnull +80 -> 371
    //   294: aload_2
    //   295: astore 5
    //   297: aload_2
    //   298: astore_3
    //   299: getstatic 134	com/tencent/mm/loader/stub/BaseBuildInfo:bwY	Ljava/lang/String;
    //   302: aload_0
    //   303: getfield 39	com/tencent/mm/plugin/hp/a/a$d:values	Ljava/util/Map;
    //   306: ldc -120
    //   308: invokeinterface 120 2 0
    //   313: checkcast 48	java/lang/String
    //   316: invokevirtual 52	java/lang/String:equalsIgnoreCase	(Ljava/lang/String;)Z
    //   319: ifeq +52 -> 371
    //   322: aload_2
    //   323: astore 5
    //   325: aload_2
    //   326: astore_3
    //   327: ldc 54
    //   329: ldc -118
    //   331: iconst_1
    //   332: anewarray 4	java/lang/Object
    //   335: dup
    //   336: iconst_0
    //   337: getstatic 134	com/tencent/mm/loader/stub/BaseBuildInfo:bwY	Ljava/lang/String;
    //   340: aastore
    //   341: invokestatic 140	com/tencent/mm/sdk/platformtools/u:w	(Ljava/lang/String;Ljava/lang/String;[Ljava/lang/Object;)V
    //   344: aload_2
    //   345: astore 5
    //   347: aload_2
    //   348: astore_3
    //   349: aload_0
    //   350: bipush 21
    //   352: putfield 28	com/tencent/mm/plugin/hp/a/a$d:eyl	I
    //   355: aload_2
    //   356: ifnull +7 -> 363
    //   359: aload_2
    //   360: invokevirtual 107	java/io/InputStream:close	()V
    //   363: aload 4
    //   365: invokevirtual 87	java/util/zip/ZipFile:close	()V
    //   368: return
    //   369: astore_2
    //   370: return
    //   371: aload_2
    //   372: astore 5
    //   374: aload_2
    //   375: astore_3
    //   376: invokestatic 144	com/tencent/mm/loader/stub/BaseBuildInfo:rb	()Z
    //   379: ifne +42 -> 421
    //   382: aload_2
    //   383: astore 5
    //   385: aload_2
    //   386: astore_3
    //   387: ldc 54
    //   389: ldc -110
    //   391: invokestatic 148	com/tencent/mm/sdk/platformtools/u:w	(Ljava/lang/String;Ljava/lang/String;)V
    //   394: aload_2
    //   395: astore 5
    //   397: aload_2
    //   398: astore_3
    //   399: aload_0
    //   400: bipush 22
    //   402: putfield 28	com/tencent/mm/plugin/hp/a/a$d:eyl	I
    //   405: aload_2
    //   406: ifnull +7 -> 413
    //   409: aload_2
    //   410: invokevirtual 107	java/io/InputStream:close	()V
    //   413: aload 4
    //   415: invokevirtual 87	java/util/zip/ZipFile:close	()V
    //   418: return
    //   419: astore_2
    //   420: return
    //   421: aload_2
    //   422: astore 5
    //   424: aload_2
    //   425: astore_3
    //   426: aload 4
    //   428: ldc -106
    //   430: invokevirtual 82	java/util/zip/ZipFile:getEntry	(Ljava/lang/String;)Ljava/util/zip/ZipEntry;
    //   433: astore 6
    //   435: aload 6
    //   437: ifnonnull +43 -> 480
    //   440: aload_2
    //   441: astore 5
    //   443: aload_2
    //   444: astore_3
    //   445: ldc 54
    //   447: ldc -104
    //   449: invokestatic 72	com/tencent/mm/sdk/platformtools/u:e	(Ljava/lang/String;Ljava/lang/String;)V
    //   452: aload_2
    //   453: astore 5
    //   455: aload_2
    //   456: astore_3
    //   457: aload_0
    //   458: iconst_1
    //   459: putfield 26	com/tencent/mm/plugin/hp/a/a$d:eyd	Z
    //   462: aload_2
    //   463: astore_3
    //   464: aload_3
    //   465: ifnull +7 -> 472
    //   468: aload_3
    //   469: invokevirtual 107	java/io/InputStream:close	()V
    //   472: aload 4
    //   474: invokevirtual 87	java/util/zip/ZipFile:close	()V
    //   477: return
    //   478: astore_2
    //   479: return
    //   480: aload_2
    //   481: astore 5
    //   483: aload_2
    //   484: astore_3
    //   485: ldc 54
    //   487: ldc -102
    //   489: invokestatic 157	com/tencent/mm/sdk/platformtools/u:i	(Ljava/lang/String;Ljava/lang/String;)V
    //   492: aload_2
    //   493: astore 5
    //   495: aload_2
    //   496: astore_3
    //   497: aload 4
    //   499: aload 6
    //   501: invokevirtual 91	java/util/zip/ZipFile:getInputStream	(Ljava/util/zip/ZipEntry;)Ljava/io/InputStream;
    //   504: astore_2
    //   505: aload_2
    //   506: invokestatic 96	com/tencent/mm/sdk/platformtools/ay:d	(Ljava/io/InputStream;)Ljava/lang/String;
    //   509: invokestatic 160	com/tencent/mm/plugin/hp/a/a:px	(Ljava/lang/String;)Ljava/util/Map;
    //   512: astore_3
    //   513: ldc 54
    //   515: new 162	java/lang/StringBuilder
    //   518: dup
    //   519: ldc -92
    //   521: invokespecial 165	java/lang/StringBuilder:<init>	(Ljava/lang/String;)V
    //   524: aload_3
    //   525: invokeinterface 169 1 0
    //   530: invokevirtual 173	java/lang/StringBuilder:append	(I)Ljava/lang/StringBuilder;
    //   533: invokevirtual 177	java/lang/StringBuilder:toString	()Ljava/lang/String;
    //   536: invokestatic 157	com/tencent/mm/sdk/platformtools/u:i	(Ljava/lang/String;Ljava/lang/String;)V
    //   539: aload_3
    //   540: invokeinterface 181 1 0
    //   545: invokeinterface 187 1 0
    //   550: astore_3
    //   551: aload_0
    //   552: new 189	java/util/ArrayList
    //   555: dup
    //   556: invokespecial 190	java/util/ArrayList:<init>	()V
    //   559: putfield 30	com/tencent/mm/plugin/hp/a/a$d:eyf	Ljava/util/List;
    //   562: aload_3
    //   563: invokeinterface 195 1 0
    //   568: ifeq +336 -> 904
    //   571: aload_3
    //   572: invokeinterface 199 1 0
    //   577: checkcast 201	java/util/Map$Entry
    //   580: astore 6
    //   582: aload 6
    //   584: invokeinterface 204 1 0
    //   589: checkcast 48	java/lang/String
    //   592: astore 5
    //   594: aload 6
    //   596: invokeinterface 207 1 0
    //   601: checkcast 48	java/lang/String
    //   604: astore 6
    //   606: ldc 54
    //   608: ldc -47
    //   610: iconst_2
    //   611: anewarray 4	java/lang/Object
    //   614: dup
    //   615: iconst_0
    //   616: aload 5
    //   618: aastore
    //   619: dup
    //   620: iconst_1
    //   621: aload 6
    //   623: aastore
    //   624: invokestatic 211	com/tencent/mm/sdk/platformtools/u:i	(Ljava/lang/String;Ljava/lang/String;[Ljava/lang/Object;)V
    //   627: aload 6
    //   629: invokestatic 214	com/tencent/mm/sdk/platformtools/ay:kz	(Ljava/lang/String;)Z
    //   632: ifne -70 -> 562
    //   635: aload 6
    //   637: ldc -40
    //   639: invokevirtual 220	java/lang/String:split	(Ljava/lang/String;)[Ljava/lang/String;
    //   642: astore 8
    //   644: aload 8
    //   646: ifnull +149 -> 795
    //   649: aload 8
    //   651: arraylength
    //   652: iconst_3
    //   653: if_icmpne +142 -> 795
    //   656: aload 8
    //   658: iconst_0
    //   659: aaload
    //   660: astore 6
    //   662: aload 8
    //   664: iconst_1
    //   665: aaload
    //   666: astore 7
    //   668: aload 8
    //   670: iconst_2
    //   671: aaload
    //   672: astore 8
    //   674: aload_0
    //   675: getfield 30	com/tencent/mm/plugin/hp/a/a$d:eyf	Ljava/util/List;
    //   678: new 222	com/tencent/mm/plugin/hp/a/a$c
    //   681: dup
    //   682: aload 5
    //   684: aload 6
    //   686: aload 7
    //   688: aload 8
    //   690: invokespecial 225	com/tencent/mm/plugin/hp/a/a$c:<init>	(Ljava/lang/String;Ljava/lang/String;Ljava/lang/String;Ljava/lang/String;)V
    //   693: invokeinterface 231 2 0
    //   698: pop
    //   699: ldc 54
    //   701: new 162	java/lang/StringBuilder
    //   704: dup
    //   705: invokespecial 232	java/lang/StringBuilder:<init>	()V
    //   708: aload 5
    //   710: invokevirtual 235	java/lang/StringBuilder:append	(Ljava/lang/String;)Ljava/lang/StringBuilder;
    //   713: ldc -19
    //   715: invokevirtual 235	java/lang/StringBuilder:append	(Ljava/lang/String;)Ljava/lang/StringBuilder;
    //   718: aload 6
    //   720: invokevirtual 235	java/lang/StringBuilder:append	(Ljava/lang/String;)Ljava/lang/StringBuilder;
    //   723: ldc -17
    //   725: invokevirtual 235	java/lang/StringBuilder:append	(Ljava/lang/String;)Ljava/lang/StringBuilder;
    //   728: aload 7
    //   730: invokevirtual 235	java/lang/StringBuilder:append	(Ljava/lang/String;)Ljava/lang/StringBuilder;
    //   733: ldc -15
    //   735: invokevirtual 235	java/lang/StringBuilder:append	(Ljava/lang/String;)Ljava/lang/StringBuilder;
    //   738: aload 8
    //   740: invokevirtual 235	java/lang/StringBuilder:append	(Ljava/lang/String;)Ljava/lang/StringBuilder;
    //   743: invokevirtual 177	java/lang/StringBuilder:toString	()Ljava/lang/String;
    //   746: invokestatic 157	com/tencent/mm/sdk/platformtools/u:i	(Ljava/lang/String;Ljava/lang/String;)V
    //   749: goto -187 -> 562
    //   752: astore 5
    //   754: aload_2
    //   755: astore_3
    //   756: aload 4
    //   758: astore_2
    //   759: aload 5
    //   761: astore 4
    //   763: ldc 54
    //   765: aload 4
    //   767: ldc -13
    //   769: iconst_0
    //   770: anewarray 4	java/lang/Object
    //   773: invokestatic 247	com/tencent/mm/sdk/platformtools/u:printErrStackTrace	(Ljava/lang/String;Ljava/lang/Throwable;Ljava/lang/String;[Ljava/lang/Object;)V
    //   776: aload_3
    //   777: ifnull +7 -> 784
    //   780: aload_3
    //   781: invokevirtual 107	java/io/InputStream:close	()V
    //   784: aload_2
    //   785: ifnull -752 -> 33
    //   788: aload_2
    //   789: invokevirtual 87	java/util/zip/ZipFile:close	()V
    //   792: return
    //   793: astore_2
    //   794: return
    //   795: ldc 54
    //   797: ldc -7
    //   799: invokestatic 72	com/tencent/mm/sdk/platformtools/u:e	(Ljava/lang/String;Ljava/lang/String;)V
    //   802: aload_0
    //   803: bipush 27
    //   805: putfield 28	com/tencent/mm/plugin/hp/a/a$d:eyl	I
    //   808: iconst_0
    //   809: istore_1
    //   810: aload_2
    //   811: astore_3
    //   812: iload_1
    //   813: ifeq -349 -> 464
    //   816: aload_0
    //   817: iconst_1
    //   818: putfield 26	com/tencent/mm/plugin/hp/a/a$d:eyd	Z
    //   821: aload_2
    //   822: astore_3
    //   823: goto -359 -> 464
    //   826: astore 5
    //   828: aload_2
    //   829: astore_3
    //   830: aload 5
    //   832: astore_2
    //   833: aload_3
    //   834: ifnull +7 -> 841
    //   837: aload_3
    //   838: invokevirtual 107	java/io/InputStream:close	()V
    //   841: aload 4
    //   843: ifnull +8 -> 851
    //   846: aload 4
    //   848: invokevirtual 87	java/util/zip/ZipFile:close	()V
    //   851: aload_2
    //   852: athrow
    //   853: astore_3
    //   854: goto -3 -> 851
    //   857: astore_2
    //   858: aconst_null
    //   859: astore 4
    //   861: aload 5
    //   863: astore_3
    //   864: goto -31 -> 833
    //   867: astore_2
    //   868: aload 5
    //   870: astore_3
    //   871: goto -38 -> 833
    //   874: astore 5
    //   876: aload_2
    //   877: astore 4
    //   879: aload 5
    //   881: astore_2
    //   882: goto -49 -> 833
    //   885: astore 4
    //   887: aconst_null
    //   888: astore_2
    //   889: goto -126 -> 763
    //   892: astore 5
    //   894: aload 4
    //   896: astore_2
    //   897: aload 5
    //   899: astore 4
    //   901: goto -138 -> 763
    //   904: iconst_1
    //   905: istore_1
    //   906: goto -96 -> 810
    // Local variable table:
    //   start	length	slot	name	signature
    //   0	909	0	this	d
    //   809	97	1	i	int
    //   4	64	2	localObject1	Object
    //   86	3	2	localException1	Exception
    //   101	57	2	localInputStream	java.io.InputStream
    //   167	48	2	localException2	Exception
    //   224	48	2	localException3	Exception
    //   281	79	2	localException4	Exception
    //   369	41	2	localException5	Exception
    //   419	44	2	localException6	Exception
    //   478	18	2	localException7	Exception
    //   504	285	2	localObject2	Object
    //   793	36	2	localException8	Exception
    //   832	20	2	localObject3	Object
    //   857	1	2	localObject4	Object
    //   867	10	2	localObject5	Object
    //   881	16	2	localObject6	Object
    //   9	829	3	localObject7	Object
    //   853	1	3	localException9	Exception
    //   863	8	3	localObject8	Object
    //   45	833	4	localObject9	Object
    //   885	10	4	localException10	Exception
    //   899	1	4	localException11	Exception
    //   1	708	5	localObject10	Object
    //   752	8	5	localException12	Exception
    //   826	43	5	localObject11	Object
    //   874	6	5	localObject12	Object
    //   892	6	5	localException13	Exception
    //   6	713	6	localObject13	Object
    //   60	669	7	localZipEntry	java.util.zip.ZipEntry
    //   642	97	8	localObject14	Object
    // Exception table:
    //   from	to	target	type
    //   80	85	86	java/lang/Exception
    //   157	161	167	java/lang/Exception
    //   161	166	167	java/lang/Exception
    //   214	218	224	java/lang/Exception
    //   218	223	224	java/lang/Exception
    //   271	275	281	java/lang/Exception
    //   275	280	281	java/lang/Exception
    //   359	363	369	java/lang/Exception
    //   363	368	369	java/lang/Exception
    //   409	413	419	java/lang/Exception
    //   413	418	419	java/lang/Exception
    //   468	472	478	java/lang/Exception
    //   472	477	478	java/lang/Exception
    //   505	562	752	java/lang/Exception
    //   562	644	752	java/lang/Exception
    //   649	656	752	java/lang/Exception
    //   674	749	752	java/lang/Exception
    //   795	808	752	java/lang/Exception
    //   816	821	752	java/lang/Exception
    //   780	784	793	java/lang/Exception
    //   788	792	793	java/lang/Exception
    //   505	562	826	finally
    //   562	644	826	finally
    //   649	656	826	finally
    //   674	749	826	finally
    //   795	808	826	finally
    //   816	821	826	finally
    //   837	841	853	java/lang/Exception
    //   846	851	853	java/lang/Exception
    //   34	47	857	finally
    //   53	62	867	finally
    //   73	80	867	finally
    //   94	102	867	finally
    //   107	118	867	finally
    //   123	130	867	finally
    //   135	142	867	finally
    //   147	153	867	finally
    //   174	199	867	finally
    //   204	210	867	finally
    //   231	256	867	finally
    //   261	267	867	finally
    //   288	294	867	finally
    //   299	322	867	finally
    //   327	344	867	finally
    //   349	355	867	finally
    //   376	382	867	finally
    //   387	394	867	finally
    //   399	405	867	finally
    //   426	435	867	finally
    //   445	452	867	finally
    //   457	462	867	finally
    //   485	492	867	finally
    //   497	505	867	finally
    //   763	776	874	finally
    //   34	47	885	java/lang/Exception
    //   53	62	892	java/lang/Exception
    //   73	80	892	java/lang/Exception
    //   94	102	892	java/lang/Exception
    //   107	118	892	java/lang/Exception
    //   123	130	892	java/lang/Exception
    //   135	142	892	java/lang/Exception
    //   147	153	892	java/lang/Exception
    //   174	199	892	java/lang/Exception
    //   204	210	892	java/lang/Exception
    //   231	256	892	java/lang/Exception
    //   261	267	892	java/lang/Exception
    //   288	294	892	java/lang/Exception
    //   299	322	892	java/lang/Exception
    //   327	344	892	java/lang/Exception
    //   349	355	892	java/lang/Exception
    //   376	382	892	java/lang/Exception
    //   387	394	892	java/lang/Exception
    //   399	405	892	java/lang/Exception
    //   426	435	892	java/lang/Exception
    //   445	452	892	java/lang/Exception
    //   457	462	892	java/lang/Exception
    //   485	492	892	java/lang/Exception
    //   497	505	892	java/lang/Exception
  }
}

/* Location:
 * Qualified Name:     com.tencent.mm.plugin.hp.a.a.d
 * Java Class Version: 6 (50.0)
 * JD-Core Version:    0.7.1
 */