package com.tencent.mm.pluginsdk.j.a.a;

import com.tencent.mm.pluginsdk.j.a.c.e.d;

final class k$a
  extends e.d<a>
{
  protected k$a(a parama)
  {
    super(parama);
  }
  
  /* Error */
  public final void run()
  {
    // Byte code:
    //   0: ldc 18
    //   2: ldc 20
    //   4: iconst_1
    //   5: anewarray 22	java/lang/Object
    //   8: dup
    //   9: iconst_0
    //   10: aload_0
    //   11: getfield 26	com/tencent/mm/pluginsdk/j/a/c/e$d:jba	Lcom/tencent/mm/pluginsdk/j/a/c/e$b;
    //   14: checkcast 28	com/tencent/mm/pluginsdk/j/a/a/a
    //   17: getfield 32	com/tencent/mm/pluginsdk/j/a/a/a:iZH	Ljava/lang/String;
    //   20: aastore
    //   21: invokestatic 38	com/tencent/mm/sdk/platformtools/v:i	(Ljava/lang/String;Ljava/lang/String;[Ljava/lang/Object;)V
    //   24: aload_0
    //   25: getfield 26	com/tencent/mm/pluginsdk/j/a/c/e$d:jba	Lcom/tencent/mm/pluginsdk/j/a/c/e$b;
    //   28: checkcast 28	com/tencent/mm/pluginsdk/j/a/a/a
    //   31: astore 4
    //   33: aload 4
    //   35: getfield 42	com/tencent/mm/pluginsdk/j/a/a/a:afi	I
    //   38: istore_1
    //   39: aload 4
    //   41: getfield 45	com/tencent/mm/pluginsdk/j/a/a/a:afj	I
    //   44: istore_2
    //   45: aload 4
    //   47: getfield 48	com/tencent/mm/pluginsdk/j/a/a/a:afk	I
    //   50: istore_3
    //   51: aload_0
    //   52: getfield 26	com/tencent/mm/pluginsdk/j/a/c/e$d:jba	Lcom/tencent/mm/pluginsdk/j/a/c/e$b;
    //   55: checkcast 28	com/tencent/mm/pluginsdk/j/a/a/a
    //   58: astore 4
    //   60: new 50	com/tencent/mm/pluginsdk/j/a/a/l
    //   63: dup
    //   64: aload 4
    //   66: getfield 42	com/tencent/mm/pluginsdk/j/a/a/a:afi	I
    //   69: aload 4
    //   71: getfield 45	com/tencent/mm/pluginsdk/j/a/a/a:afj	I
    //   74: aload 4
    //   76: getfield 53	com/tencent/mm/pluginsdk/j/a/a/a:filePath	Ljava/lang/String;
    //   79: aload 4
    //   81: getfield 57	com/tencent/mm/pluginsdk/j/a/a/a:iZI	Z
    //   84: aload 4
    //   86: getfield 60	com/tencent/mm/pluginsdk/j/a/a/a:iZJ	Z
    //   89: aload 4
    //   91: getfield 63	com/tencent/mm/pluginsdk/j/a/a/a:iZK	Ljava/lang/String;
    //   94: aload 4
    //   96: getfield 66	com/tencent/mm/pluginsdk/j/a/a/a:iZL	I
    //   99: aload 4
    //   101: getfield 69	com/tencent/mm/pluginsdk/j/a/a/a:iZO	Z
    //   104: aload 4
    //   106: getfield 72	com/tencent/mm/pluginsdk/j/a/a/a:afl	Z
    //   109: aload 4
    //   111: getfield 76	com/tencent/mm/pluginsdk/j/a/a/a:iZM	[B
    //   114: aload 4
    //   116: getfield 79	com/tencent/mm/pluginsdk/j/a/a/a:iZN	Ljava/lang/String;
    //   119: aload 4
    //   121: getfield 82	com/tencent/mm/pluginsdk/j/a/a/a:iZQ	Ljava/lang/String;
    //   124: aload 4
    //   126: getfield 86	com/tencent/mm/pluginsdk/j/a/a/a:iZP	J
    //   129: aload 4
    //   131: getfield 89	com/tencent/mm/pluginsdk/j/a/a/a:url	Ljava/lang/String;
    //   134: aload 4
    //   136: getfield 92	com/tencent/mm/pluginsdk/j/a/a/a:iZR	I
    //   139: aload 4
    //   141: getfield 95	com/tencent/mm/pluginsdk/j/a/a/a:iZS	I
    //   144: aload 4
    //   146: getfield 48	com/tencent/mm/pluginsdk/j/a/a/a:afk	I
    //   149: invokespecial 98	com/tencent/mm/pluginsdk/j/a/a/l:<init>	(IILjava/lang/String;ZZLjava/lang/String;IZZ[BLjava/lang/String;Ljava/lang/String;JLjava/lang/String;III)V
    //   152: astore 4
    //   154: aload 4
    //   156: getfield 101	com/tencent/mm/pluginsdk/j/a/a/l:jao	Z
    //   159: ifeq +282 -> 441
    //   162: ldc 103
    //   164: ldc 105
    //   166: iconst_1
    //   167: anewarray 22	java/lang/Object
    //   170: dup
    //   171: iconst_0
    //   172: aload 4
    //   174: getfield 106	com/tencent/mm/pluginsdk/j/a/a/l:iZH	Ljava/lang/String;
    //   177: aastore
    //   178: invokestatic 38	com/tencent/mm/sdk/platformtools/v:i	(Ljava/lang/String;Ljava/lang/String;[Ljava/lang/Object;)V
    //   181: aload 4
    //   183: new 108	java/lang/StringBuilder
    //   186: dup
    //   187: invokespecial 110	java/lang/StringBuilder:<init>	()V
    //   190: aload 4
    //   192: getfield 111	com/tencent/mm/pluginsdk/j/a/a/l:filePath	Ljava/lang/String;
    //   195: invokevirtual 115	java/lang/StringBuilder:append	(Ljava/lang/String;)Ljava/lang/StringBuilder;
    //   198: ldc 117
    //   200: invokevirtual 115	java/lang/StringBuilder:append	(Ljava/lang/String;)Ljava/lang/StringBuilder;
    //   203: invokevirtual 121	java/lang/StringBuilder:toString	()Ljava/lang/String;
    //   206: putfield 124	com/tencent/mm/pluginsdk/j/a/a/l:jaN	Ljava/lang/String;
    //   209: aload 4
    //   211: bipush 32
    //   213: putfield 127	com/tencent/mm/pluginsdk/j/a/a/l:state	I
    //   216: aload 4
    //   218: invokevirtual 130	com/tencent/mm/pluginsdk/j/a/a/l:aUZ	()Ljava/lang/String;
    //   221: ifnull +701 -> 922
    //   224: aload 4
    //   226: bipush 16
    //   228: putfield 127	com/tencent/mm/pluginsdk/j/a/a/l:state	I
    //   231: ldc 103
    //   233: ldc -124
    //   235: iconst_1
    //   236: anewarray 22	java/lang/Object
    //   239: dup
    //   240: iconst_0
    //   241: aload 4
    //   243: getfield 106	com/tencent/mm/pluginsdk/j/a/a/l:iZH	Ljava/lang/String;
    //   246: aastore
    //   247: invokestatic 38	com/tencent/mm/sdk/platformtools/v:i	(Ljava/lang/String;Ljava/lang/String;[Ljava/lang/Object;)V
    //   250: goto +672 -> 922
    //   253: ldc 103
    //   255: new 108	java/lang/StringBuilder
    //   258: dup
    //   259: ldc -122
    //   261: invokespecial 137	java/lang/StringBuilder:<init>	(Ljava/lang/String;)V
    //   264: aload 4
    //   266: invokevirtual 140	com/tencent/mm/pluginsdk/j/a/a/l:aVa	()Ljava/lang/String;
    //   269: invokevirtual 115	java/lang/StringBuilder:append	(Ljava/lang/String;)Ljava/lang/StringBuilder;
    //   272: invokevirtual 121	java/lang/StringBuilder:toString	()Ljava/lang/String;
    //   275: iconst_1
    //   276: anewarray 22	java/lang/Object
    //   279: dup
    //   280: iconst_0
    //   281: aload 4
    //   283: getfield 106	com/tencent/mm/pluginsdk/j/a/a/l:iZH	Ljava/lang/String;
    //   286: aastore
    //   287: invokestatic 38	com/tencent/mm/sdk/platformtools/v:i	(Ljava/lang/String;Ljava/lang/String;[Ljava/lang/Object;)V
    //   290: bipush 16
    //   292: aload 4
    //   294: getfield 127	com/tencent/mm/pluginsdk/j/a/a/l:state	I
    //   297: if_icmpne +316 -> 613
    //   300: aload 4
    //   302: invokevirtual 144	com/tencent/mm/pluginsdk/j/a/a/l:aUX	()Lcom/tencent/mm/pluginsdk/j/a/a/l;
    //   305: invokevirtual 147	com/tencent/mm/pluginsdk/j/a/a/l:aUY	()Lcom/tencent/mm/pluginsdk/j/a/a/l;
    //   308: invokevirtual 130	com/tencent/mm/pluginsdk/j/a/a/l:aUZ	()Ljava/lang/String;
    //   311: astore 4
    //   313: aload 4
    //   315: invokestatic 153	com/tencent/mm/sdk/platformtools/be:kf	(Ljava/lang/String;)Z
    //   318: ifne +537 -> 855
    //   321: invokestatic 159	com/tencent/mm/pluginsdk/j/a/a/b$b:aUR	()Lcom/tencent/mm/pluginsdk/j/a/a/b;
    //   324: iload_1
    //   325: iload_2
    //   326: aload 4
    //   328: iload_3
    //   329: invokevirtual 164	com/tencent/mm/pluginsdk/j/a/a/b:a	(IILjava/lang/String;I)V
    //   332: invokestatic 170	java/lang/Thread:interrupted	()Z
    //   335: ifeq +105 -> 440
    //   338: ldc 18
    //   340: ldc -84
    //   342: iconst_1
    //   343: anewarray 22	java/lang/Object
    //   346: dup
    //   347: iconst_0
    //   348: aload_0
    //   349: getfield 26	com/tencent/mm/pluginsdk/j/a/c/e$d:jba	Lcom/tencent/mm/pluginsdk/j/a/c/e$b;
    //   352: checkcast 28	com/tencent/mm/pluginsdk/j/a/a/a
    //   355: getfield 32	com/tencent/mm/pluginsdk/j/a/a/a:iZH	Ljava/lang/String;
    //   358: aastore
    //   359: invokestatic 38	com/tencent/mm/sdk/platformtools/v:i	(Ljava/lang/String;Ljava/lang/String;[Ljava/lang/Object;)V
    //   362: aload_0
    //   363: getfield 26	com/tencent/mm/pluginsdk/j/a/c/e$d:jba	Lcom/tencent/mm/pluginsdk/j/a/c/e$b;
    //   366: checkcast 28	com/tencent/mm/pluginsdk/j/a/a/a
    //   369: getfield 53	com/tencent/mm/pluginsdk/j/a/a/a:filePath	Ljava/lang/String;
    //   372: invokestatic 177	com/tencent/mm/pluginsdk/j/a/d/a:Cw	(Ljava/lang/String;)Z
    //   375: pop
    //   376: new 108	java/lang/StringBuilder
    //   379: dup
    //   380: invokespecial 110	java/lang/StringBuilder:<init>	()V
    //   383: aload_0
    //   384: getfield 26	com/tencent/mm/pluginsdk/j/a/c/e$d:jba	Lcom/tencent/mm/pluginsdk/j/a/c/e$b;
    //   387: checkcast 28	com/tencent/mm/pluginsdk/j/a/a/a
    //   390: getfield 53	com/tencent/mm/pluginsdk/j/a/a/a:filePath	Ljava/lang/String;
    //   393: invokevirtual 115	java/lang/StringBuilder:append	(Ljava/lang/String;)Ljava/lang/StringBuilder;
    //   396: ldc -77
    //   398: invokevirtual 115	java/lang/StringBuilder:append	(Ljava/lang/String;)Ljava/lang/StringBuilder;
    //   401: invokevirtual 121	java/lang/StringBuilder:toString	()Ljava/lang/String;
    //   404: invokestatic 177	com/tencent/mm/pluginsdk/j/a/d/a:Cw	(Ljava/lang/String;)Z
    //   407: pop
    //   408: new 108	java/lang/StringBuilder
    //   411: dup
    //   412: invokespecial 110	java/lang/StringBuilder:<init>	()V
    //   415: aload_0
    //   416: getfield 26	com/tencent/mm/pluginsdk/j/a/c/e$d:jba	Lcom/tencent/mm/pluginsdk/j/a/c/e$b;
    //   419: checkcast 28	com/tencent/mm/pluginsdk/j/a/a/a
    //   422: getfield 53	com/tencent/mm/pluginsdk/j/a/a/a:filePath	Ljava/lang/String;
    //   425: invokevirtual 115	java/lang/StringBuilder:append	(Ljava/lang/String;)Ljava/lang/StringBuilder;
    //   428: ldc 117
    //   430: invokevirtual 115	java/lang/StringBuilder:append	(Ljava/lang/String;)Ljava/lang/StringBuilder;
    //   433: invokevirtual 121	java/lang/StringBuilder:toString	()Ljava/lang/String;
    //   436: invokestatic 177	com/tencent/mm/pluginsdk/j/a/d/a:Cw	(Ljava/lang/String;)Z
    //   439: pop
    //   440: return
    //   441: aload 4
    //   443: getfield 182	com/tencent/mm/pluginsdk/j/a/a/l:jap	Z
    //   446: ifeq +94 -> 540
    //   449: ldc 103
    //   451: ldc -72
    //   453: iconst_1
    //   454: anewarray 22	java/lang/Object
    //   457: dup
    //   458: iconst_0
    //   459: aload 4
    //   461: getfield 106	com/tencent/mm/pluginsdk/j/a/a/l:iZH	Ljava/lang/String;
    //   464: aastore
    //   465: invokestatic 38	com/tencent/mm/sdk/platformtools/v:i	(Ljava/lang/String;Ljava/lang/String;[Ljava/lang/Object;)V
    //   468: aload 4
    //   470: new 108	java/lang/StringBuilder
    //   473: dup
    //   474: invokespecial 110	java/lang/StringBuilder:<init>	()V
    //   477: aload 4
    //   479: getfield 111	com/tencent/mm/pluginsdk/j/a/a/l:filePath	Ljava/lang/String;
    //   482: invokevirtual 115	java/lang/StringBuilder:append	(Ljava/lang/String;)Ljava/lang/StringBuilder;
    //   485: ldc -77
    //   487: invokevirtual 115	java/lang/StringBuilder:append	(Ljava/lang/String;)Ljava/lang/StringBuilder;
    //   490: invokevirtual 121	java/lang/StringBuilder:toString	()Ljava/lang/String;
    //   493: putfield 124	com/tencent/mm/pluginsdk/j/a/a/l:jaN	Ljava/lang/String;
    //   496: aload 4
    //   498: bipush 32
    //   500: putfield 127	com/tencent/mm/pluginsdk/j/a/a/l:state	I
    //   503: aload 4
    //   505: invokevirtual 130	com/tencent/mm/pluginsdk/j/a/a/l:aUZ	()Ljava/lang/String;
    //   508: ifnull +417 -> 925
    //   511: aload 4
    //   513: bipush 16
    //   515: putfield 127	com/tencent/mm/pluginsdk/j/a/a/l:state	I
    //   518: ldc 103
    //   520: ldc -124
    //   522: iconst_1
    //   523: anewarray 22	java/lang/Object
    //   526: dup
    //   527: iconst_0
    //   528: aload 4
    //   530: getfield 106	com/tencent/mm/pluginsdk/j/a/a/l:iZH	Ljava/lang/String;
    //   533: aastore
    //   534: invokestatic 38	com/tencent/mm/sdk/platformtools/v:i	(Ljava/lang/String;Ljava/lang/String;[Ljava/lang/Object;)V
    //   537: goto +388 -> 925
    //   540: ldc 103
    //   542: ldc -70
    //   544: iconst_1
    //   545: anewarray 22	java/lang/Object
    //   548: dup
    //   549: iconst_0
    //   550: aload 4
    //   552: getfield 106	com/tencent/mm/pluginsdk/j/a/a/l:iZH	Ljava/lang/String;
    //   555: aastore
    //   556: invokestatic 38	com/tencent/mm/sdk/platformtools/v:i	(Ljava/lang/String;Ljava/lang/String;[Ljava/lang/Object;)V
    //   559: aload 4
    //   561: aload 4
    //   563: getfield 111	com/tencent/mm/pluginsdk/j/a/a/l:filePath	Ljava/lang/String;
    //   566: putfield 124	com/tencent/mm/pluginsdk/j/a/a/l:jaN	Ljava/lang/String;
    //   569: aload 4
    //   571: bipush 32
    //   573: putfield 127	com/tencent/mm/pluginsdk/j/a/a/l:state	I
    //   576: aload 4
    //   578: invokevirtual 130	com/tencent/mm/pluginsdk/j/a/a/l:aUZ	()Ljava/lang/String;
    //   581: ifnull +347 -> 928
    //   584: aload 4
    //   586: bipush 16
    //   588: putfield 127	com/tencent/mm/pluginsdk/j/a/a/l:state	I
    //   591: ldc 103
    //   593: ldc -124
    //   595: iconst_1
    //   596: anewarray 22	java/lang/Object
    //   599: dup
    //   600: iconst_0
    //   601: aload 4
    //   603: getfield 106	com/tencent/mm/pluginsdk/j/a/a/l:iZH	Ljava/lang/String;
    //   606: aastore
    //   607: invokestatic 38	com/tencent/mm/sdk/platformtools/v:i	(Ljava/lang/String;Ljava/lang/String;[Ljava/lang/Object;)V
    //   610: goto +318 -> 928
    //   613: aload 4
    //   615: getfield 182	com/tencent/mm/pluginsdk/j/a/a/l:jap	Z
    //   618: ifeq +163 -> 781
    //   621: aload 4
    //   623: aload 4
    //   625: getfield 111	com/tencent/mm/pluginsdk/j/a/a/l:filePath	Ljava/lang/String;
    //   628: putfield 124	com/tencent/mm/pluginsdk/j/a/a/l:jaN	Ljava/lang/String;
    //   631: aload 4
    //   633: new 108	java/lang/StringBuilder
    //   636: dup
    //   637: invokespecial 110	java/lang/StringBuilder:<init>	()V
    //   640: aload 4
    //   642: getfield 111	com/tencent/mm/pluginsdk/j/a/a/l:filePath	Ljava/lang/String;
    //   645: invokevirtual 115	java/lang/StringBuilder:append	(Ljava/lang/String;)Ljava/lang/StringBuilder;
    //   648: ldc -77
    //   650: invokevirtual 115	java/lang/StringBuilder:append	(Ljava/lang/String;)Ljava/lang/StringBuilder;
    //   653: invokevirtual 121	java/lang/StringBuilder:toString	()Ljava/lang/String;
    //   656: putfield 189	com/tencent/mm/pluginsdk/j/a/a/l:jaO	Ljava/lang/String;
    //   659: aload 4
    //   661: iconst_1
    //   662: putfield 127	com/tencent/mm/pluginsdk/j/a/a/l:state	I
    //   665: goto -365 -> 300
    //   668: astore 4
    //   670: invokestatic 170	java/lang/Thread:interrupted	()Z
    //   673: ifeq +105 -> 778
    //   676: ldc 18
    //   678: ldc -84
    //   680: iconst_1
    //   681: anewarray 22	java/lang/Object
    //   684: dup
    //   685: iconst_0
    //   686: aload_0
    //   687: getfield 26	com/tencent/mm/pluginsdk/j/a/c/e$d:jba	Lcom/tencent/mm/pluginsdk/j/a/c/e$b;
    //   690: checkcast 28	com/tencent/mm/pluginsdk/j/a/a/a
    //   693: getfield 32	com/tencent/mm/pluginsdk/j/a/a/a:iZH	Ljava/lang/String;
    //   696: aastore
    //   697: invokestatic 38	com/tencent/mm/sdk/platformtools/v:i	(Ljava/lang/String;Ljava/lang/String;[Ljava/lang/Object;)V
    //   700: aload_0
    //   701: getfield 26	com/tencent/mm/pluginsdk/j/a/c/e$d:jba	Lcom/tencent/mm/pluginsdk/j/a/c/e$b;
    //   704: checkcast 28	com/tencent/mm/pluginsdk/j/a/a/a
    //   707: getfield 53	com/tencent/mm/pluginsdk/j/a/a/a:filePath	Ljava/lang/String;
    //   710: invokestatic 177	com/tencent/mm/pluginsdk/j/a/d/a:Cw	(Ljava/lang/String;)Z
    //   713: pop
    //   714: new 108	java/lang/StringBuilder
    //   717: dup
    //   718: invokespecial 110	java/lang/StringBuilder:<init>	()V
    //   721: aload_0
    //   722: getfield 26	com/tencent/mm/pluginsdk/j/a/c/e$d:jba	Lcom/tencent/mm/pluginsdk/j/a/c/e$b;
    //   725: checkcast 28	com/tencent/mm/pluginsdk/j/a/a/a
    //   728: getfield 53	com/tencent/mm/pluginsdk/j/a/a/a:filePath	Ljava/lang/String;
    //   731: invokevirtual 115	java/lang/StringBuilder:append	(Ljava/lang/String;)Ljava/lang/StringBuilder;
    //   734: ldc -77
    //   736: invokevirtual 115	java/lang/StringBuilder:append	(Ljava/lang/String;)Ljava/lang/StringBuilder;
    //   739: invokevirtual 121	java/lang/StringBuilder:toString	()Ljava/lang/String;
    //   742: invokestatic 177	com/tencent/mm/pluginsdk/j/a/d/a:Cw	(Ljava/lang/String;)Z
    //   745: pop
    //   746: new 108	java/lang/StringBuilder
    //   749: dup
    //   750: invokespecial 110	java/lang/StringBuilder:<init>	()V
    //   753: aload_0
    //   754: getfield 26	com/tencent/mm/pluginsdk/j/a/c/e$d:jba	Lcom/tencent/mm/pluginsdk/j/a/c/e$b;
    //   757: checkcast 28	com/tencent/mm/pluginsdk/j/a/a/a
    //   760: getfield 53	com/tencent/mm/pluginsdk/j/a/a/a:filePath	Ljava/lang/String;
    //   763: invokevirtual 115	java/lang/StringBuilder:append	(Ljava/lang/String;)Ljava/lang/StringBuilder;
    //   766: ldc 117
    //   768: invokevirtual 115	java/lang/StringBuilder:append	(Ljava/lang/String;)Ljava/lang/StringBuilder;
    //   771: invokevirtual 121	java/lang/StringBuilder:toString	()Ljava/lang/String;
    //   774: invokestatic 177	com/tencent/mm/pluginsdk/j/a/d/a:Cw	(Ljava/lang/String;)Z
    //   777: pop
    //   778: aload 4
    //   780: athrow
    //   781: aload 4
    //   783: getfield 101	com/tencent/mm/pluginsdk/j/a/a/l:jao	Z
    //   786: ifeq +50 -> 836
    //   789: aload 4
    //   791: aload 4
    //   793: getfield 111	com/tencent/mm/pluginsdk/j/a/a/l:filePath	Ljava/lang/String;
    //   796: putfield 124	com/tencent/mm/pluginsdk/j/a/a/l:jaN	Ljava/lang/String;
    //   799: aload 4
    //   801: new 108	java/lang/StringBuilder
    //   804: dup
    //   805: invokespecial 110	java/lang/StringBuilder:<init>	()V
    //   808: aload 4
    //   810: getfield 111	com/tencent/mm/pluginsdk/j/a/a/l:filePath	Ljava/lang/String;
    //   813: invokevirtual 115	java/lang/StringBuilder:append	(Ljava/lang/String;)Ljava/lang/StringBuilder;
    //   816: ldc 117
    //   818: invokevirtual 115	java/lang/StringBuilder:append	(Ljava/lang/String;)Ljava/lang/StringBuilder;
    //   821: invokevirtual 121	java/lang/StringBuilder:toString	()Ljava/lang/String;
    //   824: putfield 189	com/tencent/mm/pluginsdk/j/a/a/l:jaO	Ljava/lang/String;
    //   827: aload 4
    //   829: iconst_2
    //   830: putfield 127	com/tencent/mm/pluginsdk/j/a/a/l:state	I
    //   833: goto -533 -> 300
    //   836: aload 4
    //   838: aload 4
    //   840: getfield 111	com/tencent/mm/pluginsdk/j/a/a/l:filePath	Ljava/lang/String;
    //   843: putfield 124	com/tencent/mm/pluginsdk/j/a/a/l:jaN	Ljava/lang/String;
    //   846: aload 4
    //   848: iconst_4
    //   849: putfield 127	com/tencent/mm/pluginsdk/j/a/a/l:state	I
    //   852: goto -552 -> 300
    //   855: new 108	java/lang/StringBuilder
    //   858: dup
    //   859: invokespecial 110	java/lang/StringBuilder:<init>	()V
    //   862: aload_0
    //   863: getfield 26	com/tencent/mm/pluginsdk/j/a/c/e$d:jba	Lcom/tencent/mm/pluginsdk/j/a/c/e$b;
    //   866: checkcast 28	com/tencent/mm/pluginsdk/j/a/a/a
    //   869: getfield 53	com/tencent/mm/pluginsdk/j/a/a/a:filePath	Ljava/lang/String;
    //   872: invokevirtual 115	java/lang/StringBuilder:append	(Ljava/lang/String;)Ljava/lang/StringBuilder;
    //   875: ldc -77
    //   877: invokevirtual 115	java/lang/StringBuilder:append	(Ljava/lang/String;)Ljava/lang/StringBuilder;
    //   880: invokevirtual 121	java/lang/StringBuilder:toString	()Ljava/lang/String;
    //   883: invokestatic 177	com/tencent/mm/pluginsdk/j/a/d/a:Cw	(Ljava/lang/String;)Z
    //   886: pop
    //   887: new 108	java/lang/StringBuilder
    //   890: dup
    //   891: invokespecial 110	java/lang/StringBuilder:<init>	()V
    //   894: aload_0
    //   895: getfield 26	com/tencent/mm/pluginsdk/j/a/c/e$d:jba	Lcom/tencent/mm/pluginsdk/j/a/c/e$b;
    //   898: checkcast 28	com/tencent/mm/pluginsdk/j/a/a/a
    //   901: getfield 53	com/tencent/mm/pluginsdk/j/a/a/a:filePath	Ljava/lang/String;
    //   904: invokevirtual 115	java/lang/StringBuilder:append	(Ljava/lang/String;)Ljava/lang/StringBuilder;
    //   907: ldc 117
    //   909: invokevirtual 115	java/lang/StringBuilder:append	(Ljava/lang/String;)Ljava/lang/StringBuilder;
    //   912: invokevirtual 121	java/lang/StringBuilder:toString	()Ljava/lang/String;
    //   915: invokestatic 177	com/tencent/mm/pluginsdk/j/a/d/a:Cw	(Ljava/lang/String;)Z
    //   918: pop
    //   919: goto -587 -> 332
    //   922: goto -669 -> 253
    //   925: goto -672 -> 253
    //   928: goto -675 -> 253
    // Local variable table:
    //   start	length	slot	name	signature
    //   0	931	0	this	a
    //   38	287	1	i	int
    //   44	282	2	j	int
    //   50	279	3	k	int
    //   31	629	4	localObject1	Object
    //   668	179	4	localObject2	Object
    // Exception table:
    //   from	to	target	type
    //   51	250	668	finally
    //   253	300	668	finally
    //   300	332	668	finally
    //   441	537	668	finally
    //   540	610	668	finally
    //   613	665	668	finally
    //   781	833	668	finally
    //   836	852	668	finally
    //   855	919	668	finally
  }
}

/* Location:
 * Qualified Name:     com.tencent.mm.pluginsdk.j.a.a.k.a
 * Java Class Version: 6 (50.0)
 * JD-Core Version:    0.7.1
 */