package com.tencent.mm.pluginsdk.i.a.a;

import com.tencent.mm.pluginsdk.i.a.c.e.d;

final class k$a
  extends e.d
{
  protected k$a(a parama)
  {
    super(parama);
  }
  
  /* Error */
  public final void run()
  {
    // Byte code:
    //   0: ldc 17
    //   2: ldc 19
    //   4: iconst_1
    //   5: anewarray 21	java/lang/Object
    //   8: dup
    //   9: iconst_0
    //   10: aload_0
    //   11: getfield 25	com/tencent/mm/pluginsdk/i/a/c/e$d:iEd	Lcom/tencent/mm/pluginsdk/i/a/c/e$b;
    //   14: checkcast 27	com/tencent/mm/pluginsdk/i/a/a/a
    //   17: getfield 31	com/tencent/mm/pluginsdk/i/a/a/a:iCT	Ljava/lang/String;
    //   20: aastore
    //   21: invokestatic 37	com/tencent/mm/sdk/platformtools/u:i	(Ljava/lang/String;Ljava/lang/String;[Ljava/lang/Object;)V
    //   24: aload_0
    //   25: getfield 25	com/tencent/mm/pluginsdk/i/a/c/e$d:iEd	Lcom/tencent/mm/pluginsdk/i/a/c/e$b;
    //   28: checkcast 27	com/tencent/mm/pluginsdk/i/a/a/a
    //   31: astore 4
    //   33: aload 4
    //   35: getfield 41	com/tencent/mm/pluginsdk/i/a/a/a:atA	I
    //   38: istore_1
    //   39: aload 4
    //   41: getfield 44	com/tencent/mm/pluginsdk/i/a/a/a:atB	I
    //   44: istore_2
    //   45: aload 4
    //   47: getfield 47	com/tencent/mm/pluginsdk/i/a/a/a:atC	I
    //   50: istore_3
    //   51: aload_0
    //   52: getfield 25	com/tencent/mm/pluginsdk/i/a/c/e$d:iEd	Lcom/tencent/mm/pluginsdk/i/a/c/e$b;
    //   55: checkcast 27	com/tencent/mm/pluginsdk/i/a/a/a
    //   58: astore 4
    //   60: new 49	com/tencent/mm/pluginsdk/i/a/a/l
    //   63: dup
    //   64: aload 4
    //   66: getfield 41	com/tencent/mm/pluginsdk/i/a/a/a:atA	I
    //   69: aload 4
    //   71: getfield 44	com/tencent/mm/pluginsdk/i/a/a/a:atB	I
    //   74: aload 4
    //   76: getfield 52	com/tencent/mm/pluginsdk/i/a/a/a:filePath	Ljava/lang/String;
    //   79: aload 4
    //   81: getfield 56	com/tencent/mm/pluginsdk/i/a/a/a:iCU	Z
    //   84: aload 4
    //   86: getfield 59	com/tencent/mm/pluginsdk/i/a/a/a:iCV	Z
    //   89: aload 4
    //   91: getfield 62	com/tencent/mm/pluginsdk/i/a/a/a:iCW	Ljava/lang/String;
    //   94: aload 4
    //   96: getfield 65	com/tencent/mm/pluginsdk/i/a/a/a:iCX	I
    //   99: aload 4
    //   101: getfield 68	com/tencent/mm/pluginsdk/i/a/a/a:iDa	Z
    //   104: aload 4
    //   106: getfield 71	com/tencent/mm/pluginsdk/i/a/a/a:atD	Z
    //   109: aload 4
    //   111: getfield 75	com/tencent/mm/pluginsdk/i/a/a/a:iCY	[B
    //   114: aload 4
    //   116: getfield 78	com/tencent/mm/pluginsdk/i/a/a/a:iCZ	Ljava/lang/String;
    //   119: aload 4
    //   121: getfield 81	com/tencent/mm/pluginsdk/i/a/a/a:iDc	Ljava/lang/String;
    //   124: aload 4
    //   126: getfield 85	com/tencent/mm/pluginsdk/i/a/a/a:iDb	J
    //   129: aload 4
    //   131: getfield 88	com/tencent/mm/pluginsdk/i/a/a/a:url	Ljava/lang/String;
    //   134: aload 4
    //   136: getfield 91	com/tencent/mm/pluginsdk/i/a/a/a:iDd	I
    //   139: aload 4
    //   141: getfield 94	com/tencent/mm/pluginsdk/i/a/a/a:iDe	I
    //   144: aload 4
    //   146: getfield 47	com/tencent/mm/pluginsdk/i/a/a/a:atC	I
    //   149: invokespecial 97	com/tencent/mm/pluginsdk/i/a/a/l:<init>	(IILjava/lang/String;ZZLjava/lang/String;IZZ[BLjava/lang/String;Ljava/lang/String;JLjava/lang/String;III)V
    //   152: astore 4
    //   154: aload 4
    //   156: getfield 100	com/tencent/mm/pluginsdk/i/a/a/l:iDt	Z
    //   159: ifeq +279 -> 438
    //   162: ldc 102
    //   164: ldc 104
    //   166: iconst_1
    //   167: anewarray 21	java/lang/Object
    //   170: dup
    //   171: iconst_0
    //   172: aload 4
    //   174: getfield 105	com/tencent/mm/pluginsdk/i/a/a/l:iCT	Ljava/lang/String;
    //   177: aastore
    //   178: invokestatic 37	com/tencent/mm/sdk/platformtools/u:i	(Ljava/lang/String;Ljava/lang/String;[Ljava/lang/Object;)V
    //   181: aload 4
    //   183: new 107	java/lang/StringBuilder
    //   186: dup
    //   187: invokespecial 109	java/lang/StringBuilder:<init>	()V
    //   190: aload 4
    //   192: getfield 110	com/tencent/mm/pluginsdk/i/a/a/l:filePath	Ljava/lang/String;
    //   195: invokevirtual 114	java/lang/StringBuilder:append	(Ljava/lang/String;)Ljava/lang/StringBuilder;
    //   198: ldc 116
    //   200: invokevirtual 114	java/lang/StringBuilder:append	(Ljava/lang/String;)Ljava/lang/StringBuilder;
    //   203: invokevirtual 120	java/lang/StringBuilder:toString	()Ljava/lang/String;
    //   206: putfield 123	com/tencent/mm/pluginsdk/i/a/a/l:iDS	Ljava/lang/String;
    //   209: aload 4
    //   211: bipush 32
    //   213: putfield 126	com/tencent/mm/pluginsdk/i/a/a/l:state	I
    //   216: aload 4
    //   218: invokevirtual 129	com/tencent/mm/pluginsdk/i/a/a/l:aQq	()Ljava/lang/String;
    //   221: ifnull +29 -> 250
    //   224: aload 4
    //   226: bipush 16
    //   228: putfield 126	com/tencent/mm/pluginsdk/i/a/a/l:state	I
    //   231: ldc 102
    //   233: ldc -125
    //   235: iconst_1
    //   236: anewarray 21	java/lang/Object
    //   239: dup
    //   240: iconst_0
    //   241: aload 4
    //   243: getfield 105	com/tencent/mm/pluginsdk/i/a/a/l:iCT	Ljava/lang/String;
    //   246: aastore
    //   247: invokestatic 37	com/tencent/mm/sdk/platformtools/u:i	(Ljava/lang/String;Ljava/lang/String;[Ljava/lang/Object;)V
    //   250: ldc 102
    //   252: new 107	java/lang/StringBuilder
    //   255: dup
    //   256: ldc -123
    //   258: invokespecial 136	java/lang/StringBuilder:<init>	(Ljava/lang/String;)V
    //   261: aload 4
    //   263: invokevirtual 139	com/tencent/mm/pluginsdk/i/a/a/l:aQr	()Ljava/lang/String;
    //   266: invokevirtual 114	java/lang/StringBuilder:append	(Ljava/lang/String;)Ljava/lang/StringBuilder;
    //   269: invokevirtual 120	java/lang/StringBuilder:toString	()Ljava/lang/String;
    //   272: iconst_1
    //   273: anewarray 21	java/lang/Object
    //   276: dup
    //   277: iconst_0
    //   278: aload 4
    //   280: getfield 105	com/tencent/mm/pluginsdk/i/a/a/l:iCT	Ljava/lang/String;
    //   283: aastore
    //   284: invokestatic 37	com/tencent/mm/sdk/platformtools/u:i	(Ljava/lang/String;Ljava/lang/String;[Ljava/lang/Object;)V
    //   287: bipush 16
    //   289: aload 4
    //   291: getfield 126	com/tencent/mm/pluginsdk/i/a/a/l:state	I
    //   294: if_icmpne +429 -> 723
    //   297: aload 4
    //   299: invokevirtual 143	com/tencent/mm/pluginsdk/i/a/a/l:aQo	()Lcom/tencent/mm/pluginsdk/i/a/a/l;
    //   302: invokevirtual 146	com/tencent/mm/pluginsdk/i/a/a/l:aQp	()Lcom/tencent/mm/pluginsdk/i/a/a/l;
    //   305: invokevirtual 129	com/tencent/mm/pluginsdk/i/a/a/l:aQq	()Ljava/lang/String;
    //   308: astore 4
    //   310: aload 4
    //   312: invokestatic 152	com/tencent/mm/sdk/platformtools/ay:kz	(Ljava/lang/String;)Z
    //   315: ifne +537 -> 852
    //   318: invokestatic 158	com/tencent/mm/pluginsdk/i/a/a/b$b:aQi	()Lcom/tencent/mm/pluginsdk/i/a/a/b;
    //   321: iload_1
    //   322: iload_2
    //   323: aload 4
    //   325: iload_3
    //   326: invokevirtual 164	com/tencent/mm/pluginsdk/i/a/a/b:b	(IILjava/lang/String;I)V
    //   329: invokestatic 170	java/lang/Thread:interrupted	()Z
    //   332: ifeq +105 -> 437
    //   335: ldc 17
    //   337: ldc -84
    //   339: iconst_1
    //   340: anewarray 21	java/lang/Object
    //   343: dup
    //   344: iconst_0
    //   345: aload_0
    //   346: getfield 25	com/tencent/mm/pluginsdk/i/a/c/e$d:iEd	Lcom/tencent/mm/pluginsdk/i/a/c/e$b;
    //   349: checkcast 27	com/tencent/mm/pluginsdk/i/a/a/a
    //   352: getfield 31	com/tencent/mm/pluginsdk/i/a/a/a:iCT	Ljava/lang/String;
    //   355: aastore
    //   356: invokestatic 37	com/tencent/mm/sdk/platformtools/u:i	(Ljava/lang/String;Ljava/lang/String;[Ljava/lang/Object;)V
    //   359: aload_0
    //   360: getfield 25	com/tencent/mm/pluginsdk/i/a/c/e$d:iEd	Lcom/tencent/mm/pluginsdk/i/a/c/e$b;
    //   363: checkcast 27	com/tencent/mm/pluginsdk/i/a/a/a
    //   366: getfield 52	com/tencent/mm/pluginsdk/i/a/a/a:filePath	Ljava/lang/String;
    //   369: invokestatic 177	com/tencent/mm/pluginsdk/i/a/d/a:Av	(Ljava/lang/String;)Z
    //   372: pop
    //   373: new 107	java/lang/StringBuilder
    //   376: dup
    //   377: invokespecial 109	java/lang/StringBuilder:<init>	()V
    //   380: aload_0
    //   381: getfield 25	com/tencent/mm/pluginsdk/i/a/c/e$d:iEd	Lcom/tencent/mm/pluginsdk/i/a/c/e$b;
    //   384: checkcast 27	com/tencent/mm/pluginsdk/i/a/a/a
    //   387: getfield 52	com/tencent/mm/pluginsdk/i/a/a/a:filePath	Ljava/lang/String;
    //   390: invokevirtual 114	java/lang/StringBuilder:append	(Ljava/lang/String;)Ljava/lang/StringBuilder;
    //   393: ldc -77
    //   395: invokevirtual 114	java/lang/StringBuilder:append	(Ljava/lang/String;)Ljava/lang/StringBuilder;
    //   398: invokevirtual 120	java/lang/StringBuilder:toString	()Ljava/lang/String;
    //   401: invokestatic 177	com/tencent/mm/pluginsdk/i/a/d/a:Av	(Ljava/lang/String;)Z
    //   404: pop
    //   405: new 107	java/lang/StringBuilder
    //   408: dup
    //   409: invokespecial 109	java/lang/StringBuilder:<init>	()V
    //   412: aload_0
    //   413: getfield 25	com/tencent/mm/pluginsdk/i/a/c/e$d:iEd	Lcom/tencent/mm/pluginsdk/i/a/c/e$b;
    //   416: checkcast 27	com/tencent/mm/pluginsdk/i/a/a/a
    //   419: getfield 52	com/tencent/mm/pluginsdk/i/a/a/a:filePath	Ljava/lang/String;
    //   422: invokevirtual 114	java/lang/StringBuilder:append	(Ljava/lang/String;)Ljava/lang/StringBuilder;
    //   425: ldc 116
    //   427: invokevirtual 114	java/lang/StringBuilder:append	(Ljava/lang/String;)Ljava/lang/StringBuilder;
    //   430: invokevirtual 120	java/lang/StringBuilder:toString	()Ljava/lang/String;
    //   433: invokestatic 177	com/tencent/mm/pluginsdk/i/a/d/a:Av	(Ljava/lang/String;)Z
    //   436: pop
    //   437: return
    //   438: aload 4
    //   440: getfield 182	com/tencent/mm/pluginsdk/i/a/a/l:iDu	Z
    //   443: ifeq +207 -> 650
    //   446: ldc 102
    //   448: ldc -72
    //   450: iconst_1
    //   451: anewarray 21	java/lang/Object
    //   454: dup
    //   455: iconst_0
    //   456: aload 4
    //   458: getfield 105	com/tencent/mm/pluginsdk/i/a/a/l:iCT	Ljava/lang/String;
    //   461: aastore
    //   462: invokestatic 37	com/tencent/mm/sdk/platformtools/u:i	(Ljava/lang/String;Ljava/lang/String;[Ljava/lang/Object;)V
    //   465: aload 4
    //   467: new 107	java/lang/StringBuilder
    //   470: dup
    //   471: invokespecial 109	java/lang/StringBuilder:<init>	()V
    //   474: aload 4
    //   476: getfield 110	com/tencent/mm/pluginsdk/i/a/a/l:filePath	Ljava/lang/String;
    //   479: invokevirtual 114	java/lang/StringBuilder:append	(Ljava/lang/String;)Ljava/lang/StringBuilder;
    //   482: ldc -77
    //   484: invokevirtual 114	java/lang/StringBuilder:append	(Ljava/lang/String;)Ljava/lang/StringBuilder;
    //   487: invokevirtual 120	java/lang/StringBuilder:toString	()Ljava/lang/String;
    //   490: putfield 123	com/tencent/mm/pluginsdk/i/a/a/l:iDS	Ljava/lang/String;
    //   493: aload 4
    //   495: bipush 32
    //   497: putfield 126	com/tencent/mm/pluginsdk/i/a/a/l:state	I
    //   500: aload 4
    //   502: invokevirtual 129	com/tencent/mm/pluginsdk/i/a/a/l:aQq	()Ljava/lang/String;
    //   505: ifnull -255 -> 250
    //   508: aload 4
    //   510: bipush 16
    //   512: putfield 126	com/tencent/mm/pluginsdk/i/a/a/l:state	I
    //   515: ldc 102
    //   517: ldc -125
    //   519: iconst_1
    //   520: anewarray 21	java/lang/Object
    //   523: dup
    //   524: iconst_0
    //   525: aload 4
    //   527: getfield 105	com/tencent/mm/pluginsdk/i/a/a/l:iCT	Ljava/lang/String;
    //   530: aastore
    //   531: invokestatic 37	com/tencent/mm/sdk/platformtools/u:i	(Ljava/lang/String;Ljava/lang/String;[Ljava/lang/Object;)V
    //   534: goto -284 -> 250
    //   537: astore 4
    //   539: invokestatic 170	java/lang/Thread:interrupted	()Z
    //   542: ifeq +105 -> 647
    //   545: ldc 17
    //   547: ldc -84
    //   549: iconst_1
    //   550: anewarray 21	java/lang/Object
    //   553: dup
    //   554: iconst_0
    //   555: aload_0
    //   556: getfield 25	com/tencent/mm/pluginsdk/i/a/c/e$d:iEd	Lcom/tencent/mm/pluginsdk/i/a/c/e$b;
    //   559: checkcast 27	com/tencent/mm/pluginsdk/i/a/a/a
    //   562: getfield 31	com/tencent/mm/pluginsdk/i/a/a/a:iCT	Ljava/lang/String;
    //   565: aastore
    //   566: invokestatic 37	com/tencent/mm/sdk/platformtools/u:i	(Ljava/lang/String;Ljava/lang/String;[Ljava/lang/Object;)V
    //   569: aload_0
    //   570: getfield 25	com/tencent/mm/pluginsdk/i/a/c/e$d:iEd	Lcom/tencent/mm/pluginsdk/i/a/c/e$b;
    //   573: checkcast 27	com/tencent/mm/pluginsdk/i/a/a/a
    //   576: getfield 52	com/tencent/mm/pluginsdk/i/a/a/a:filePath	Ljava/lang/String;
    //   579: invokestatic 177	com/tencent/mm/pluginsdk/i/a/d/a:Av	(Ljava/lang/String;)Z
    //   582: pop
    //   583: new 107	java/lang/StringBuilder
    //   586: dup
    //   587: invokespecial 109	java/lang/StringBuilder:<init>	()V
    //   590: aload_0
    //   591: getfield 25	com/tencent/mm/pluginsdk/i/a/c/e$d:iEd	Lcom/tencent/mm/pluginsdk/i/a/c/e$b;
    //   594: checkcast 27	com/tencent/mm/pluginsdk/i/a/a/a
    //   597: getfield 52	com/tencent/mm/pluginsdk/i/a/a/a:filePath	Ljava/lang/String;
    //   600: invokevirtual 114	java/lang/StringBuilder:append	(Ljava/lang/String;)Ljava/lang/StringBuilder;
    //   603: ldc -77
    //   605: invokevirtual 114	java/lang/StringBuilder:append	(Ljava/lang/String;)Ljava/lang/StringBuilder;
    //   608: invokevirtual 120	java/lang/StringBuilder:toString	()Ljava/lang/String;
    //   611: invokestatic 177	com/tencent/mm/pluginsdk/i/a/d/a:Av	(Ljava/lang/String;)Z
    //   614: pop
    //   615: new 107	java/lang/StringBuilder
    //   618: dup
    //   619: invokespecial 109	java/lang/StringBuilder:<init>	()V
    //   622: aload_0
    //   623: getfield 25	com/tencent/mm/pluginsdk/i/a/c/e$d:iEd	Lcom/tencent/mm/pluginsdk/i/a/c/e$b;
    //   626: checkcast 27	com/tencent/mm/pluginsdk/i/a/a/a
    //   629: getfield 52	com/tencent/mm/pluginsdk/i/a/a/a:filePath	Ljava/lang/String;
    //   632: invokevirtual 114	java/lang/StringBuilder:append	(Ljava/lang/String;)Ljava/lang/StringBuilder;
    //   635: ldc 116
    //   637: invokevirtual 114	java/lang/StringBuilder:append	(Ljava/lang/String;)Ljava/lang/StringBuilder;
    //   640: invokevirtual 120	java/lang/StringBuilder:toString	()Ljava/lang/String;
    //   643: invokestatic 177	com/tencent/mm/pluginsdk/i/a/d/a:Av	(Ljava/lang/String;)Z
    //   646: pop
    //   647: aload 4
    //   649: athrow
    //   650: ldc 102
    //   652: ldc -70
    //   654: iconst_1
    //   655: anewarray 21	java/lang/Object
    //   658: dup
    //   659: iconst_0
    //   660: aload 4
    //   662: getfield 105	com/tencent/mm/pluginsdk/i/a/a/l:iCT	Ljava/lang/String;
    //   665: aastore
    //   666: invokestatic 37	com/tencent/mm/sdk/platformtools/u:i	(Ljava/lang/String;Ljava/lang/String;[Ljava/lang/Object;)V
    //   669: aload 4
    //   671: aload 4
    //   673: getfield 110	com/tencent/mm/pluginsdk/i/a/a/l:filePath	Ljava/lang/String;
    //   676: putfield 123	com/tencent/mm/pluginsdk/i/a/a/l:iDS	Ljava/lang/String;
    //   679: aload 4
    //   681: bipush 32
    //   683: putfield 126	com/tencent/mm/pluginsdk/i/a/a/l:state	I
    //   686: aload 4
    //   688: invokevirtual 129	com/tencent/mm/pluginsdk/i/a/a/l:aQq	()Ljava/lang/String;
    //   691: ifnull -441 -> 250
    //   694: aload 4
    //   696: bipush 16
    //   698: putfield 126	com/tencent/mm/pluginsdk/i/a/a/l:state	I
    //   701: ldc 102
    //   703: ldc -125
    //   705: iconst_1
    //   706: anewarray 21	java/lang/Object
    //   709: dup
    //   710: iconst_0
    //   711: aload 4
    //   713: getfield 105	com/tencent/mm/pluginsdk/i/a/a/l:iCT	Ljava/lang/String;
    //   716: aastore
    //   717: invokestatic 37	com/tencent/mm/sdk/platformtools/u:i	(Ljava/lang/String;Ljava/lang/String;[Ljava/lang/Object;)V
    //   720: goto -470 -> 250
    //   723: aload 4
    //   725: getfield 182	com/tencent/mm/pluginsdk/i/a/a/l:iDu	Z
    //   728: ifeq +50 -> 778
    //   731: aload 4
    //   733: aload 4
    //   735: getfield 110	com/tencent/mm/pluginsdk/i/a/a/l:filePath	Ljava/lang/String;
    //   738: putfield 123	com/tencent/mm/pluginsdk/i/a/a/l:iDS	Ljava/lang/String;
    //   741: aload 4
    //   743: new 107	java/lang/StringBuilder
    //   746: dup
    //   747: invokespecial 109	java/lang/StringBuilder:<init>	()V
    //   750: aload 4
    //   752: getfield 110	com/tencent/mm/pluginsdk/i/a/a/l:filePath	Ljava/lang/String;
    //   755: invokevirtual 114	java/lang/StringBuilder:append	(Ljava/lang/String;)Ljava/lang/StringBuilder;
    //   758: ldc -77
    //   760: invokevirtual 114	java/lang/StringBuilder:append	(Ljava/lang/String;)Ljava/lang/StringBuilder;
    //   763: invokevirtual 120	java/lang/StringBuilder:toString	()Ljava/lang/String;
    //   766: putfield 189	com/tencent/mm/pluginsdk/i/a/a/l:iDT	Ljava/lang/String;
    //   769: aload 4
    //   771: iconst_1
    //   772: putfield 126	com/tencent/mm/pluginsdk/i/a/a/l:state	I
    //   775: goto -478 -> 297
    //   778: aload 4
    //   780: getfield 100	com/tencent/mm/pluginsdk/i/a/a/l:iDt	Z
    //   783: ifeq +50 -> 833
    //   786: aload 4
    //   788: aload 4
    //   790: getfield 110	com/tencent/mm/pluginsdk/i/a/a/l:filePath	Ljava/lang/String;
    //   793: putfield 123	com/tencent/mm/pluginsdk/i/a/a/l:iDS	Ljava/lang/String;
    //   796: aload 4
    //   798: new 107	java/lang/StringBuilder
    //   801: dup
    //   802: invokespecial 109	java/lang/StringBuilder:<init>	()V
    //   805: aload 4
    //   807: getfield 110	com/tencent/mm/pluginsdk/i/a/a/l:filePath	Ljava/lang/String;
    //   810: invokevirtual 114	java/lang/StringBuilder:append	(Ljava/lang/String;)Ljava/lang/StringBuilder;
    //   813: ldc 116
    //   815: invokevirtual 114	java/lang/StringBuilder:append	(Ljava/lang/String;)Ljava/lang/StringBuilder;
    //   818: invokevirtual 120	java/lang/StringBuilder:toString	()Ljava/lang/String;
    //   821: putfield 189	com/tencent/mm/pluginsdk/i/a/a/l:iDT	Ljava/lang/String;
    //   824: aload 4
    //   826: iconst_2
    //   827: putfield 126	com/tencent/mm/pluginsdk/i/a/a/l:state	I
    //   830: goto -533 -> 297
    //   833: aload 4
    //   835: aload 4
    //   837: getfield 110	com/tencent/mm/pluginsdk/i/a/a/l:filePath	Ljava/lang/String;
    //   840: putfield 123	com/tencent/mm/pluginsdk/i/a/a/l:iDS	Ljava/lang/String;
    //   843: aload 4
    //   845: iconst_4
    //   846: putfield 126	com/tencent/mm/pluginsdk/i/a/a/l:state	I
    //   849: goto -552 -> 297
    //   852: new 107	java/lang/StringBuilder
    //   855: dup
    //   856: invokespecial 109	java/lang/StringBuilder:<init>	()V
    //   859: aload_0
    //   860: getfield 25	com/tencent/mm/pluginsdk/i/a/c/e$d:iEd	Lcom/tencent/mm/pluginsdk/i/a/c/e$b;
    //   863: checkcast 27	com/tencent/mm/pluginsdk/i/a/a/a
    //   866: getfield 52	com/tencent/mm/pluginsdk/i/a/a/a:filePath	Ljava/lang/String;
    //   869: invokevirtual 114	java/lang/StringBuilder:append	(Ljava/lang/String;)Ljava/lang/StringBuilder;
    //   872: ldc -77
    //   874: invokevirtual 114	java/lang/StringBuilder:append	(Ljava/lang/String;)Ljava/lang/StringBuilder;
    //   877: invokevirtual 120	java/lang/StringBuilder:toString	()Ljava/lang/String;
    //   880: invokestatic 177	com/tencent/mm/pluginsdk/i/a/d/a:Av	(Ljava/lang/String;)Z
    //   883: pop
    //   884: new 107	java/lang/StringBuilder
    //   887: dup
    //   888: invokespecial 109	java/lang/StringBuilder:<init>	()V
    //   891: aload_0
    //   892: getfield 25	com/tencent/mm/pluginsdk/i/a/c/e$d:iEd	Lcom/tencent/mm/pluginsdk/i/a/c/e$b;
    //   895: checkcast 27	com/tencent/mm/pluginsdk/i/a/a/a
    //   898: getfield 52	com/tencent/mm/pluginsdk/i/a/a/a:filePath	Ljava/lang/String;
    //   901: invokevirtual 114	java/lang/StringBuilder:append	(Ljava/lang/String;)Ljava/lang/StringBuilder;
    //   904: ldc 116
    //   906: invokevirtual 114	java/lang/StringBuilder:append	(Ljava/lang/String;)Ljava/lang/StringBuilder;
    //   909: invokevirtual 120	java/lang/StringBuilder:toString	()Ljava/lang/String;
    //   912: invokestatic 177	com/tencent/mm/pluginsdk/i/a/d/a:Av	(Ljava/lang/String;)Z
    //   915: pop
    //   916: goto -587 -> 329
    // Local variable table:
    //   start	length	slot	name	signature
    //   0	919	0	this	a
    //   38	284	1	i	int
    //   44	279	2	j	int
    //   50	276	3	k	int
    //   31	495	4	localObject1	Object
    //   537	307	4	localObject2	Object
    // Exception table:
    //   from	to	target	type
    //   51	250	537	finally
    //   250	297	537	finally
    //   297	329	537	finally
    //   438	534	537	finally
    //   650	720	537	finally
    //   723	775	537	finally
    //   778	830	537	finally
    //   833	849	537	finally
    //   852	916	537	finally
  }
}

/* Location:
 * Qualified Name:     com.tencent.mm.pluginsdk.i.a.a.k.a
 * Java Class Version: 6 (50.0)
 * JD-Core Version:    0.7.1
 */