package com.tencent.mm.plugin.webview.ui.tools;

final class WebViewUI$v
  implements WebViewUI.w
{
  private WebViewUI$v(WebViewUI paramWebViewUI) {}
  
  public final String aNF()
  {
    return "weixin://private/setresult/";
  }
  
  public final void detach() {}
  
  /* Error */
  public final boolean yD(String paramString)
  {
    // Byte code:
    //   0: aconst_null
    //   1: astore 4
    //   3: aload_0
    //   4: getfield 15	com/tencent/mm/plugin/webview/ui/tools/WebViewUI$v:ioV	Lcom/tencent/mm/plugin/webview/ui/tools/WebViewUI;
    //   7: getfield 35	com/tencent/mm/plugin/webview/ui/tools/WebViewUI:fHK	Lcom/tencent/mm/ui/widget/MMWebView;
    //   10: ldc 37
    //   12: aconst_null
    //   13: invokevirtual 43	com/tencent/mm/ui/widget/MMWebView:evaluateJavascript	(Ljava/lang/String;Lcom/tencent/smtt/sdk/u;)V
    //   16: aload_1
    //   17: bipush 27
    //   19: invokevirtual 49	java/lang/String:substring	(I)Ljava/lang/String;
    //   22: astore_1
    //   23: aload_1
    //   24: invokestatic 54	com/tencent/mm/sdk/platformtools/ay:kz	(Ljava/lang/String;)Z
    //   27: ifeq +12 -> 39
    //   30: ldc 56
    //   32: ldc 58
    //   34: invokestatic 64	com/tencent/mm/sdk/platformtools/u:e	(Ljava/lang/String;Ljava/lang/String;)V
    //   37: iconst_0
    //   38: ireturn
    //   39: aload_1
    //   40: ldc 66
    //   42: invokevirtual 70	java/lang/String:indexOf	(Ljava/lang/String;)I
    //   45: istore_2
    //   46: iload_2
    //   47: ifgt +23 -> 70
    //   50: ldc 56
    //   52: ldc 72
    //   54: iconst_1
    //   55: anewarray 4	java/lang/Object
    //   58: dup
    //   59: iconst_0
    //   60: iload_2
    //   61: invokestatic 78	java/lang/Integer:valueOf	(I)Ljava/lang/Integer;
    //   64: aastore
    //   65: invokestatic 81	com/tencent/mm/sdk/platformtools/u:e	(Ljava/lang/String;Ljava/lang/String;[Ljava/lang/Object;)V
    //   68: iconst_0
    //   69: ireturn
    //   70: aload_1
    //   71: iconst_0
    //   72: iload_2
    //   73: invokevirtual 84	java/lang/String:substring	(II)Ljava/lang/String;
    //   76: astore 5
    //   78: aload_1
    //   79: iload_2
    //   80: iconst_1
    //   81: iadd
    //   82: invokevirtual 49	java/lang/String:substring	(I)Ljava/lang/String;
    //   85: iconst_0
    //   86: invokestatic 90	android/util/Base64:decode	(Ljava/lang/String;I)[B
    //   89: astore_1
    //   90: aload_1
    //   91: ifnonnull +234 -> 325
    //   94: aconst_null
    //   95: astore_3
    //   96: ldc 56
    //   98: ldc 92
    //   100: iconst_2
    //   101: anewarray 4	java/lang/Object
    //   104: dup
    //   105: iconst_0
    //   106: aload 5
    //   108: aastore
    //   109: dup
    //   110: iconst_1
    //   111: aload_3
    //   112: aastore
    //   113: invokestatic 95	com/tencent/mm/sdk/platformtools/u:i	(Ljava/lang/String;Ljava/lang/String;[Ljava/lang/Object;)V
    //   116: ldc 97
    //   118: aload 5
    //   120: invokevirtual 101	java/lang/String:equals	(Ljava/lang/Object;)Z
    //   123: ifeq +187 -> 310
    //   126: aload_3
    //   127: ifnull +183 -> 310
    //   130: aload_3
    //   131: ldc 103
    //   133: invokevirtual 106	java/lang/String:startsWith	(Ljava/lang/String;)Z
    //   136: ifeq +201 -> 337
    //   139: aload_3
    //   140: bipush 14
    //   142: invokevirtual 49	java/lang/String:substring	(I)Ljava/lang/String;
    //   145: astore_1
    //   146: aload_1
    //   147: ifnull +78 -> 225
    //   150: aload_1
    //   151: ldc 108
    //   153: invokevirtual 112	java/lang/String:split	(Ljava/lang/String;)[Ljava/lang/String;
    //   156: invokestatic 116	com/tencent/mm/plugin/webview/ui/tools/WebViewUI:z	([Ljava/lang/String;)Ljava/util/Map;
    //   159: astore_1
    //   160: aload_0
    //   161: getfield 15	com/tencent/mm/plugin/webview/ui/tools/WebViewUI$v:ioV	Lcom/tencent/mm/plugin/webview/ui/tools/WebViewUI;
    //   164: ldc 118
    //   166: invokestatic 122	com/tencent/mm/plugin/webview/ui/tools/WebViewUI:q	(Lcom/tencent/mm/plugin/webview/ui/tools/WebViewUI;Ljava/lang/String;)Ljava/lang/String;
    //   169: astore 6
    //   171: aload 6
    //   173: aload_1
    //   174: invokestatic 126	com/tencent/mm/plugin/webview/ui/tools/WebViewUI:h	(Ljava/lang/String;Ljava/util/Map;)Z
    //   177: ifeq +207 -> 384
    //   180: aload_0
    //   181: getfield 15	com/tencent/mm/plugin/webview/ui/tools/WebViewUI$v:ioV	Lcom/tencent/mm/plugin/webview/ui/tools/WebViewUI;
    //   184: getfield 130	com/tencent/mm/plugin/webview/ui/tools/WebViewUI:ims	Lcom/tencent/mm/plugin/webview/stub/d;
    //   187: ifnull +38 -> 225
    //   190: aload_0
    //   191: getfield 15	com/tencent/mm/plugin/webview/ui/tools/WebViewUI$v:ioV	Lcom/tencent/mm/plugin/webview/ui/tools/WebViewUI;
    //   194: getfield 35	com/tencent/mm/plugin/webview/ui/tools/WebViewUI:fHK	Lcom/tencent/mm/ui/widget/MMWebView;
    //   197: ifnull +28 -> 225
    //   200: aload_0
    //   201: getfield 15	com/tencent/mm/plugin/webview/ui/tools/WebViewUI$v:ioV	Lcom/tencent/mm/plugin/webview/ui/tools/WebViewUI;
    //   204: getfield 130	com/tencent/mm/plugin/webview/ui/tools/WebViewUI:ims	Lcom/tencent/mm/plugin/webview/stub/d;
    //   207: iconst_0
    //   208: aload_0
    //   209: getfield 15	com/tencent/mm/plugin/webview/ui/tools/WebViewUI$v:ioV	Lcom/tencent/mm/plugin/webview/ui/tools/WebViewUI;
    //   212: getfield 35	com/tencent/mm/plugin/webview/ui/tools/WebViewUI:fHK	Lcom/tencent/mm/ui/widget/MMWebView;
    //   215: invokevirtual 133	com/tencent/mm/ui/widget/MMWebView:getUrl	()Ljava/lang/String;
    //   218: aload 6
    //   220: invokeinterface 138 4 0
    //   225: aload_3
    //   226: ldc -116
    //   228: invokevirtual 106	java/lang/String:startsWith	(Ljava/lang/String;)Z
    //   231: ifeq +163 -> 394
    //   234: aload_3
    //   235: bipush 17
    //   237: invokevirtual 49	java/lang/String:substring	(I)Ljava/lang/String;
    //   240: astore_1
    //   241: aload_1
    //   242: ifnull +68 -> 310
    //   245: aload_0
    //   246: getfield 15	com/tencent/mm/plugin/webview/ui/tools/WebViewUI$v:ioV	Lcom/tencent/mm/plugin/webview/ui/tools/WebViewUI;
    //   249: ldc -114
    //   251: invokestatic 122	com/tencent/mm/plugin/webview/ui/tools/WebViewUI:q	(Lcom/tencent/mm/plugin/webview/ui/tools/WebViewUI;Ljava/lang/String;)Ljava/lang/String;
    //   254: astore 4
    //   256: aload 4
    //   258: aload_1
    //   259: invokestatic 146	com/tencent/mm/plugin/webview/ui/tools/WebViewUI:bN	(Ljava/lang/String;Ljava/lang/String;)Z
    //   262: ifeq +182 -> 444
    //   265: aload_0
    //   266: getfield 15	com/tencent/mm/plugin/webview/ui/tools/WebViewUI$v:ioV	Lcom/tencent/mm/plugin/webview/ui/tools/WebViewUI;
    //   269: getfield 130	com/tencent/mm/plugin/webview/ui/tools/WebViewUI:ims	Lcom/tencent/mm/plugin/webview/stub/d;
    //   272: ifnull +38 -> 310
    //   275: aload_0
    //   276: getfield 15	com/tencent/mm/plugin/webview/ui/tools/WebViewUI$v:ioV	Lcom/tencent/mm/plugin/webview/ui/tools/WebViewUI;
    //   279: getfield 35	com/tencent/mm/plugin/webview/ui/tools/WebViewUI:fHK	Lcom/tencent/mm/ui/widget/MMWebView;
    //   282: ifnull +28 -> 310
    //   285: aload_0
    //   286: getfield 15	com/tencent/mm/plugin/webview/ui/tools/WebViewUI$v:ioV	Lcom/tencent/mm/plugin/webview/ui/tools/WebViewUI;
    //   289: getfield 130	com/tencent/mm/plugin/webview/ui/tools/WebViewUI:ims	Lcom/tencent/mm/plugin/webview/stub/d;
    //   292: iconst_1
    //   293: aload_0
    //   294: getfield 15	com/tencent/mm/plugin/webview/ui/tools/WebViewUI$v:ioV	Lcom/tencent/mm/plugin/webview/ui/tools/WebViewUI;
    //   297: getfield 35	com/tencent/mm/plugin/webview/ui/tools/WebViewUI:fHK	Lcom/tencent/mm/ui/widget/MMWebView;
    //   300: invokevirtual 133	com/tencent/mm/ui/widget/MMWebView:getUrl	()Ljava/lang/String;
    //   303: aload 4
    //   305: invokeinterface 138 4 0
    //   310: aload_0
    //   311: getfield 15	com/tencent/mm/plugin/webview/ui/tools/WebViewUI$v:ioV	Lcom/tencent/mm/plugin/webview/ui/tools/WebViewUI;
    //   314: getfield 150	com/tencent/mm/plugin/webview/ui/tools/WebViewUI:inA	Lcom/tencent/mm/plugin/webview/ui/tools/jsapi/f;
    //   317: aload 5
    //   319: aload_3
    //   320: invokevirtual 155	com/tencent/mm/plugin/webview/ui/tools/jsapi/f:keep_setReturnValue	(Ljava/lang/String;Ljava/lang/String;)V
    //   323: iconst_1
    //   324: ireturn
    //   325: new 45	java/lang/String
    //   328: dup
    //   329: aload_1
    //   330: invokespecial 158	java/lang/String:<init>	([B)V
    //   333: astore_3
    //   334: goto -238 -> 96
    //   337: aload_3
    //   338: ldc -96
    //   340: invokevirtual 106	java/lang/String:startsWith	(Ljava/lang/String;)Z
    //   343: ifeq +111 -> 454
    //   346: aload_3
    //   347: bipush 15
    //   349: aload_3
    //   350: invokevirtual 164	java/lang/String:length	()I
    //   353: iconst_1
    //   354: isub
    //   355: invokevirtual 84	java/lang/String:substring	(II)Ljava/lang/String;
    //   358: astore_1
    //   359: goto -213 -> 146
    //   362: astore_1
    //   363: ldc 56
    //   365: ldc -90
    //   367: iconst_1
    //   368: anewarray 4	java/lang/Object
    //   371: dup
    //   372: iconst_0
    //   373: aload_1
    //   374: invokevirtual 169	android/os/RemoteException:getMessage	()Ljava/lang/String;
    //   377: aastore
    //   378: invokestatic 81	com/tencent/mm/sdk/platformtools/u:e	(Ljava/lang/String;Ljava/lang/String;[Ljava/lang/Object;)V
    //   381: goto -156 -> 225
    //   384: ldc 56
    //   386: ldc -85
    //   388: invokestatic 64	com/tencent/mm/sdk/platformtools/u:e	(Ljava/lang/String;Ljava/lang/String;)V
    //   391: goto -166 -> 225
    //   394: aload 4
    //   396: astore_1
    //   397: aload_3
    //   398: ldc -83
    //   400: invokevirtual 106	java/lang/String:startsWith	(Ljava/lang/String;)Z
    //   403: ifeq -162 -> 241
    //   406: aload_3
    //   407: bipush 18
    //   409: aload_3
    //   410: invokevirtual 164	java/lang/String:length	()I
    //   413: iconst_1
    //   414: isub
    //   415: invokevirtual 84	java/lang/String:substring	(II)Ljava/lang/String;
    //   418: astore_1
    //   419: goto -178 -> 241
    //   422: astore_1
    //   423: ldc 56
    //   425: ldc -90
    //   427: iconst_1
    //   428: anewarray 4	java/lang/Object
    //   431: dup
    //   432: iconst_0
    //   433: aload_1
    //   434: invokevirtual 169	android/os/RemoteException:getMessage	()Ljava/lang/String;
    //   437: aastore
    //   438: invokestatic 81	com/tencent/mm/sdk/platformtools/u:e	(Ljava/lang/String;Ljava/lang/String;[Ljava/lang/Object;)V
    //   441: goto -131 -> 310
    //   444: ldc 56
    //   446: ldc -81
    //   448: invokestatic 64	com/tencent/mm/sdk/platformtools/u:e	(Ljava/lang/String;Ljava/lang/String;)V
    //   451: goto -141 -> 310
    //   454: aconst_null
    //   455: astore_1
    //   456: goto -310 -> 146
    // Local variable table:
    //   start	length	slot	name	signature
    //   0	459	0	this	v
    //   0	459	1	paramString	String
    //   45	37	2	i	int
    //   95	315	3	str1	String
    //   1	394	4	str2	String
    //   76	242	5	str3	String
    //   169	50	6	str4	String
    // Exception table:
    //   from	to	target	type
    //   200	225	362	android/os/RemoteException
    //   285	310	422	android/os/RemoteException
  }
}

/* Location:
 * Qualified Name:     com.tencent.mm.plugin.webview.ui.tools.WebViewUI.v
 * Java Class Version: 6 (50.0)
 * JD-Core Version:    0.7.1
 */