package com.tencent.mm.plugin.webview.ui.tools;

import com.tencent.mm.ui.base.n.c;

final class WebViewUI$26
  implements n.c
{
  WebViewUI$26(WebViewUI paramWebViewUI) {}
  
  /* Error */
  public final void a(com.tencent.mm.ui.base.l paraml)
  {
    // Byte code:
    //   0: aload_0
    //   1: getfield 14	com/tencent/mm/plugin/webview/ui/tools/WebViewUI$26:ioV	Lcom/tencent/mm/plugin/webview/ui/tools/WebViewUI;
    //   4: astore 9
    //   6: aload 9
    //   8: getfield 26	com/tencent/mm/plugin/webview/ui/tools/WebViewUI:fHK	Lcom/tencent/mm/ui/widget/MMWebView;
    //   11: invokevirtual 32	com/tencent/mm/ui/widget/MMWebView:getUrl	()Ljava/lang/String;
    //   14: astore 10
    //   16: aload 9
    //   18: getfield 36	com/tencent/mm/plugin/webview/ui/tools/WebViewUI:iob	Ljava/util/HashMap;
    //   21: aload 10
    //   23: invokevirtual 42	java/util/HashMap:containsKey	(Ljava/lang/Object;)Z
    //   26: ifeq +102 -> 128
    //   29: aload 9
    //   31: getfield 36	com/tencent/mm/plugin/webview/ui/tools/WebViewUI:iob	Ljava/util/HashMap;
    //   34: aload 10
    //   36: invokevirtual 46	java/util/HashMap:get	(Ljava/lang/Object;)Ljava/lang/Object;
    //   39: checkcast 48	java/util/ArrayList
    //   42: astore 9
    //   44: aload 9
    //   46: ifnull +88 -> 134
    //   49: aload 9
    //   51: invokevirtual 52	java/util/ArrayList:size	()I
    //   54: ifle +80 -> 134
    //   57: aload 9
    //   59: invokevirtual 52	java/util/ArrayList:size	()I
    //   62: istore_3
    //   63: iconst_0
    //   64: istore_2
    //   65: iload_2
    //   66: iload_3
    //   67: if_icmpge +1339 -> 1406
    //   70: aload 9
    //   72: iload_2
    //   73: invokevirtual 55	java/util/ArrayList:get	(I)Ljava/lang/Object;
    //   76: checkcast 57	com/tencent/mm/g/d$b
    //   79: astore 10
    //   81: aload_1
    //   82: aload 10
    //   84: getfield 61	com/tencent/mm/g/d$b:id	I
    //   87: aload 10
    //   89: getfield 65	com/tencent/mm/g/d$b:title	Ljava/lang/String;
    //   92: invokevirtual 71	com/tencent/mm/ui/base/l:b	(ILjava/lang/CharSequence;)Landroid/view/MenuItem;
    //   95: checkcast 73	com/tencent/mm/ui/base/m
    //   98: astore 11
    //   100: aload 11
    //   102: aload 10
    //   104: putfield 77	com/tencent/mm/ui/base/m:kFw	Landroid/view/ContextMenu$ContextMenuInfo;
    //   107: aload 11
    //   109: aconst_null
    //   110: invokevirtual 81	com/tencent/mm/ui/base/m:setIcon	(Landroid/graphics/drawable/Drawable;)Landroid/view/MenuItem;
    //   113: pop
    //   114: aload 11
    //   116: iconst_0
    //   117: invokevirtual 84	com/tencent/mm/ui/base/m:setIcon	(I)Landroid/view/MenuItem;
    //   120: pop
    //   121: iload_2
    //   122: iconst_1
    //   123: iadd
    //   124: istore_2
    //   125: goto -60 -> 65
    //   128: aconst_null
    //   129: astore 9
    //   131: goto -87 -> 44
    //   134: aload_0
    //   135: getfield 14	com/tencent/mm/plugin/webview/ui/tools/WebViewUI$26:ioV	Lcom/tencent/mm/plugin/webview/ui/tools/WebViewUI;
    //   138: invokestatic 88	com/tencent/mm/plugin/webview/ui/tools/WebViewUI:aa	(Lcom/tencent/mm/plugin/webview/ui/tools/WebViewUI;)Ljava/util/LinkedList;
    //   141: astore 10
    //   143: aload 10
    //   145: ifnull +278 -> 423
    //   148: iconst_0
    //   149: istore_2
    //   150: iload_2
    //   151: aload 10
    //   153: invokevirtual 91	java/util/LinkedList:size	()I
    //   156: if_icmpge +267 -> 423
    //   159: iload_2
    //   160: bipush 8
    //   162: if_icmpge +261 -> 423
    //   165: aload 10
    //   167: iload_2
    //   168: invokevirtual 92	java/util/LinkedList:get	(I)Ljava/lang/Object;
    //   171: checkcast 94	com/tencent/mm/g/d$a
    //   174: astore 11
    //   176: ldc 96
    //   178: aload 11
    //   180: getfield 98	com/tencent/mm/g/d$a:id	Ljava/lang/String;
    //   183: invokestatic 104	com/tencent/mm/sdk/platformtools/ay:ky	(Ljava/lang/String;)Ljava/lang/String;
    //   186: invokevirtual 109	java/lang/String:equals	(Ljava/lang/Object;)Z
    //   189: ifeq +43 -> 232
    //   192: aload_1
    //   193: bipush 15
    //   195: aload_0
    //   196: getfield 14	com/tencent/mm/plugin/webview/ui/tools/WebViewUI$26:ioV	Lcom/tencent/mm/plugin/webview/ui/tools/WebViewUI;
    //   199: ldc 110
    //   201: invokevirtual 114	com/tencent/mm/plugin/webview/ui/tools/WebViewUI:getString	(I)Ljava/lang/String;
    //   204: ldc 115
    //   206: invokevirtual 118	com/tencent/mm/ui/base/l:a	(ILjava/lang/CharSequence;I)Landroid/view/MenuItem;
    //   209: checkcast 73	com/tencent/mm/ui/base/m
    //   212: astore 9
    //   214: aload 9
    //   216: ifnull +1453 -> 1669
    //   219: aload 9
    //   221: aload 11
    //   223: getfield 121	com/tencent/mm/g/d$a:url	Ljava/lang/String;
    //   226: putfield 124	com/tencent/mm/ui/base/m:eqd	Ljava/lang/String;
    //   229: goto +1440 -> 1669
    //   232: ldc 126
    //   234: aload 11
    //   236: getfield 98	com/tencent/mm/g/d$a:id	Ljava/lang/String;
    //   239: invokestatic 104	com/tencent/mm/sdk/platformtools/ay:ky	(Ljava/lang/String;)Ljava/lang/String;
    //   242: invokevirtual 109	java/lang/String:equals	(Ljava/lang/Object;)Z
    //   245: ifeq +28 -> 273
    //   248: aload_1
    //   249: bipush 16
    //   251: aload_0
    //   252: getfield 14	com/tencent/mm/plugin/webview/ui/tools/WebViewUI$26:ioV	Lcom/tencent/mm/plugin/webview/ui/tools/WebViewUI;
    //   255: ldc 127
    //   257: invokevirtual 114	com/tencent/mm/plugin/webview/ui/tools/WebViewUI:getString	(I)Ljava/lang/String;
    //   260: ldc -128
    //   262: invokevirtual 118	com/tencent/mm/ui/base/l:a	(ILjava/lang/CharSequence;I)Landroid/view/MenuItem;
    //   265: checkcast 73	com/tencent/mm/ui/base/m
    //   268: astore 9
    //   270: goto -56 -> 214
    //   273: ldc -126
    //   275: aload 11
    //   277: getfield 98	com/tencent/mm/g/d$a:id	Ljava/lang/String;
    //   280: invokestatic 104	com/tencent/mm/sdk/platformtools/ay:ky	(Ljava/lang/String;)Ljava/lang/String;
    //   283: invokevirtual 109	java/lang/String:equals	(Ljava/lang/Object;)Z
    //   286: ifeq +28 -> 314
    //   289: aload_1
    //   290: bipush 17
    //   292: aload_0
    //   293: getfield 14	com/tencent/mm/plugin/webview/ui/tools/WebViewUI$26:ioV	Lcom/tencent/mm/plugin/webview/ui/tools/WebViewUI;
    //   296: ldc -125
    //   298: invokevirtual 114	com/tencent/mm/plugin/webview/ui/tools/WebViewUI:getString	(I)Ljava/lang/String;
    //   301: ldc -124
    //   303: invokevirtual 118	com/tencent/mm/ui/base/l:a	(ILjava/lang/CharSequence;I)Landroid/view/MenuItem;
    //   306: checkcast 73	com/tencent/mm/ui/base/m
    //   309: astore 9
    //   311: goto -97 -> 214
    //   314: ldc -122
    //   316: aload 11
    //   318: getfield 98	com/tencent/mm/g/d$a:id	Ljava/lang/String;
    //   321: invokestatic 104	com/tencent/mm/sdk/platformtools/ay:ky	(Ljava/lang/String;)Ljava/lang/String;
    //   324: invokevirtual 109	java/lang/String:equals	(Ljava/lang/Object;)Z
    //   327: ifeq +28 -> 355
    //   330: aload_1
    //   331: bipush 18
    //   333: aload_0
    //   334: getfield 14	com/tencent/mm/plugin/webview/ui/tools/WebViewUI$26:ioV	Lcom/tencent/mm/plugin/webview/ui/tools/WebViewUI;
    //   337: ldc -121
    //   339: invokevirtual 114	com/tencent/mm/plugin/webview/ui/tools/WebViewUI:getString	(I)Ljava/lang/String;
    //   342: ldc -120
    //   344: invokevirtual 118	com/tencent/mm/ui/base/l:a	(ILjava/lang/CharSequence;I)Landroid/view/MenuItem;
    //   347: checkcast 73	com/tencent/mm/ui/base/m
    //   350: astore 9
    //   352: goto -138 -> 214
    //   355: ldc -118
    //   357: aload 11
    //   359: getfield 98	com/tencent/mm/g/d$a:id	Ljava/lang/String;
    //   362: invokestatic 104	com/tencent/mm/sdk/platformtools/ay:ky	(Ljava/lang/String;)Ljava/lang/String;
    //   365: invokevirtual 109	java/lang/String:equals	(Ljava/lang/Object;)Z
    //   368: ifeq +1295 -> 1663
    //   371: aload_1
    //   372: bipush 19
    //   374: aload_0
    //   375: getfield 14	com/tencent/mm/plugin/webview/ui/tools/WebViewUI$26:ioV	Lcom/tencent/mm/plugin/webview/ui/tools/WebViewUI;
    //   378: ldc -117
    //   380: invokevirtual 114	com/tencent/mm/plugin/webview/ui/tools/WebViewUI:getString	(I)Ljava/lang/String;
    //   383: ldc -116
    //   385: invokevirtual 118	com/tencent/mm/ui/base/l:a	(ILjava/lang/CharSequence;I)Landroid/view/MenuItem;
    //   388: checkcast 73	com/tencent/mm/ui/base/m
    //   391: astore 9
    //   393: goto -179 -> 214
    //   396: astore 9
    //   398: ldc -114
    //   400: new 144	java/lang/StringBuilder
    //   403: dup
    //   404: ldc -110
    //   406: invokespecial 149	java/lang/StringBuilder:<init>	(Ljava/lang/String;)V
    //   409: aload 9
    //   411: invokevirtual 152	java/lang/Exception:getMessage	()Ljava/lang/String;
    //   414: invokevirtual 156	java/lang/StringBuilder:append	(Ljava/lang/String;)Ljava/lang/StringBuilder;
    //   417: invokevirtual 159	java/lang/StringBuilder:toString	()Ljava/lang/String;
    //   420: invokestatic 165	com/tencent/mm/sdk/platformtools/u:e	(Ljava/lang/String;Ljava/lang/String;)V
    //   423: aload_0
    //   424: getfield 14	com/tencent/mm/plugin/webview/ui/tools/WebViewUI$26:ioV	Lcom/tencent/mm/plugin/webview/ui/tools/WebViewUI;
    //   427: invokestatic 168	com/tencent/mm/plugin/webview/ui/tools/WebViewUI:b	(Lcom/tencent/mm/plugin/webview/ui/tools/WebViewUI;)Lcom/tencent/mm/plugin/webview/ui/tools/e;
    //   430: invokevirtual 174	com/tencent/mm/plugin/webview/ui/tools/e:aMX	()Lcom/tencent/mm/protocal/JsapiPermissionWrapper;
    //   433: astore 10
    //   435: aload 10
    //   437: bipush 21
    //   439: invokevirtual 180	com/tencent/mm/protocal/JsapiPermissionWrapper:oT	(I)Z
    //   442: ifeq +31 -> 473
    //   445: aload_0
    //   446: getfield 14	com/tencent/mm/plugin/webview/ui/tools/WebViewUI$26:ioV	Lcom/tencent/mm/plugin/webview/ui/tools/WebViewUI;
    //   449: iconst_1
    //   450: invokestatic 184	com/tencent/mm/plugin/webview/ui/tools/WebViewUI:c	(Lcom/tencent/mm/plugin/webview/ui/tools/WebViewUI;I)Z
    //   453: ifeq +20 -> 473
    //   456: aload_1
    //   457: iconst_1
    //   458: aload_0
    //   459: getfield 14	com/tencent/mm/plugin/webview/ui/tools/WebViewUI$26:ioV	Lcom/tencent/mm/plugin/webview/ui/tools/WebViewUI;
    //   462: ldc -71
    //   464: invokevirtual 114	com/tencent/mm/plugin/webview/ui/tools/WebViewUI:getString	(I)Ljava/lang/String;
    //   467: ldc -70
    //   469: invokevirtual 118	com/tencent/mm/ui/base/l:a	(ILjava/lang/CharSequence;I)Landroid/view/MenuItem;
    //   472: pop
    //   473: aload 10
    //   475: bipush 23
    //   477: invokevirtual 180	com/tencent/mm/protocal/JsapiPermissionWrapper:oT	(I)Z
    //   480: ifeq +31 -> 511
    //   483: aload_0
    //   484: getfield 14	com/tencent/mm/plugin/webview/ui/tools/WebViewUI$26:ioV	Lcom/tencent/mm/plugin/webview/ui/tools/WebViewUI;
    //   487: iconst_2
    //   488: invokestatic 184	com/tencent/mm/plugin/webview/ui/tools/WebViewUI:c	(Lcom/tencent/mm/plugin/webview/ui/tools/WebViewUI;I)Z
    //   491: ifeq +20 -> 511
    //   494: aload_1
    //   495: iconst_2
    //   496: aload_0
    //   497: getfield 14	com/tencent/mm/plugin/webview/ui/tools/WebViewUI$26:ioV	Lcom/tencent/mm/plugin/webview/ui/tools/WebViewUI;
    //   500: ldc -69
    //   502: invokevirtual 114	com/tencent/mm/plugin/webview/ui/tools/WebViewUI:getString	(I)Ljava/lang/String;
    //   505: ldc -68
    //   507: invokevirtual 118	com/tencent/mm/ui/base/l:a	(ILjava/lang/CharSequence;I)Landroid/view/MenuItem;
    //   510: pop
    //   511: aload_0
    //   512: getfield 14	com/tencent/mm/plugin/webview/ui/tools/WebViewUI$26:ioV	Lcom/tencent/mm/plugin/webview/ui/tools/WebViewUI;
    //   515: invokestatic 192	com/tencent/mm/plugin/webview/ui/tools/WebViewUI:ab	(Lcom/tencent/mm/plugin/webview/ui/tools/WebViewUI;)Z
    //   518: ifne +41 -> 559
    //   521: aload_0
    //   522: getfield 14	com/tencent/mm/plugin/webview/ui/tools/WebViewUI$26:ioV	Lcom/tencent/mm/plugin/webview/ui/tools/WebViewUI;
    //   525: invokestatic 195	com/tencent/mm/plugin/webview/ui/tools/WebViewUI:ac	(Lcom/tencent/mm/plugin/webview/ui/tools/WebViewUI;)Z
    //   528: ifeq +31 -> 559
    //   531: aload_0
    //   532: getfield 14	com/tencent/mm/plugin/webview/ui/tools/WebViewUI$26:ioV	Lcom/tencent/mm/plugin/webview/ui/tools/WebViewUI;
    //   535: iconst_3
    //   536: invokestatic 184	com/tencent/mm/plugin/webview/ui/tools/WebViewUI:c	(Lcom/tencent/mm/plugin/webview/ui/tools/WebViewUI;I)Z
    //   539: ifeq +20 -> 559
    //   542: aload_1
    //   543: iconst_3
    //   544: aload_0
    //   545: getfield 14	com/tencent/mm/plugin/webview/ui/tools/WebViewUI$26:ioV	Lcom/tencent/mm/plugin/webview/ui/tools/WebViewUI;
    //   548: ldc -60
    //   550: invokevirtual 114	com/tencent/mm/plugin/webview/ui/tools/WebViewUI:getString	(I)Ljava/lang/String;
    //   553: ldc -59
    //   555: invokevirtual 118	com/tencent/mm/ui/base/l:a	(ILjava/lang/CharSequence;I)Landroid/view/MenuItem;
    //   558: pop
    //   559: aload_0
    //   560: getfield 14	com/tencent/mm/plugin/webview/ui/tools/WebViewUI$26:ioV	Lcom/tencent/mm/plugin/webview/ui/tools/WebViewUI;
    //   563: invokevirtual 201	com/tencent/mm/plugin/webview/ui/tools/WebViewUI:getIntent	()Landroid/content/Intent;
    //   566: ldc -53
    //   568: ldc2_w 204
    //   571: invokevirtual 211	android/content/Intent:getLongExtra	(Ljava/lang/String;J)J
    //   574: lstore 4
    //   576: aload_0
    //   577: getfield 14	com/tencent/mm/plugin/webview/ui/tools/WebViewUI$26:ioV	Lcom/tencent/mm/plugin/webview/ui/tools/WebViewUI;
    //   580: getfield 215	com/tencent/mm/plugin/webview/ui/tools/WebViewUI:ims	Lcom/tencent/mm/plugin/webview/stub/d;
    //   583: lload 4
    //   585: invokeinterface 221 3 0
    //   590: ifeq +21 -> 611
    //   593: aload_1
    //   594: bipush 23
    //   596: aload_0
    //   597: getfield 14	com/tencent/mm/plugin/webview/ui/tools/WebViewUI$26:ioV	Lcom/tencent/mm/plugin/webview/ui/tools/WebViewUI;
    //   600: ldc -34
    //   602: invokevirtual 114	com/tencent/mm/plugin/webview/ui/tools/WebViewUI:getString	(I)Ljava/lang/String;
    //   605: ldc -33
    //   607: invokevirtual 118	com/tencent/mm/ui/base/l:a	(ILjava/lang/CharSequence;I)Landroid/view/MenuItem;
    //   610: pop
    //   611: aload 10
    //   613: bipush 44
    //   615: invokevirtual 180	com/tencent/mm/protocal/JsapiPermissionWrapper:oT	(I)Z
    //   618: ifeq +33 -> 651
    //   621: aload_0
    //   622: getfield 14	com/tencent/mm/plugin/webview/ui/tools/WebViewUI$26:ioV	Lcom/tencent/mm/plugin/webview/ui/tools/WebViewUI;
    //   625: bipush 6
    //   627: invokestatic 184	com/tencent/mm/plugin/webview/ui/tools/WebViewUI:c	(Lcom/tencent/mm/plugin/webview/ui/tools/WebViewUI;I)Z
    //   630: ifeq +21 -> 651
    //   633: aload_1
    //   634: bipush 6
    //   636: aload_0
    //   637: getfield 14	com/tencent/mm/plugin/webview/ui/tools/WebViewUI$26:ioV	Lcom/tencent/mm/plugin/webview/ui/tools/WebViewUI;
    //   640: ldc -32
    //   642: invokevirtual 114	com/tencent/mm/plugin/webview/ui/tools/WebViewUI:getString	(I)Ljava/lang/String;
    //   645: ldc -31
    //   647: invokevirtual 118	com/tencent/mm/ui/base/l:a	(ILjava/lang/CharSequence;I)Landroid/view/MenuItem;
    //   650: pop
    //   651: aload 10
    //   653: getfield 229	com/tencent/mm/protocal/JsapiPermissionWrapper:iUt	[B
    //   656: ifnull +99 -> 755
    //   659: aload_0
    //   660: getfield 14	com/tencent/mm/plugin/webview/ui/tools/WebViewUI$26:ioV	Lcom/tencent/mm/plugin/webview/ui/tools/WebViewUI;
    //   663: invokestatic 192	com/tencent/mm/plugin/webview/ui/tools/WebViewUI:ab	(Lcom/tencent/mm/plugin/webview/ui/tools/WebViewUI;)Z
    //   666: ifeq +89 -> 755
    //   669: aload_0
    //   670: getfield 14	com/tencent/mm/plugin/webview/ui/tools/WebViewUI$26:ioV	Lcom/tencent/mm/plugin/webview/ui/tools/WebViewUI;
    //   673: invokevirtual 201	com/tencent/mm/plugin/webview/ui/tools/WebViewUI:getIntent	()Landroid/content/Intent;
    //   676: ldc -25
    //   678: iconst_1
    //   679: invokevirtual 235	android/content/Intent:getBooleanExtra	(Ljava/lang/String;Z)Z
    //   682: ifeq +73 -> 755
    //   685: aload_0
    //   686: getfield 14	com/tencent/mm/plugin/webview/ui/tools/WebViewUI$26:ioV	Lcom/tencent/mm/plugin/webview/ui/tools/WebViewUI;
    //   689: invokestatic 195	com/tencent/mm/plugin/webview/ui/tools/WebViewUI:ac	(Lcom/tencent/mm/plugin/webview/ui/tools/WebViewUI;)Z
    //   692: ifeq +63 -> 755
    //   695: aload_0
    //   696: getfield 14	com/tencent/mm/plugin/webview/ui/tools/WebViewUI$26:ioV	Lcom/tencent/mm/plugin/webview/ui/tools/WebViewUI;
    //   699: bipush 12
    //   701: invokestatic 184	com/tencent/mm/plugin/webview/ui/tools/WebViewUI:c	(Lcom/tencent/mm/plugin/webview/ui/tools/WebViewUI;I)Z
    //   704: ifeq +21 -> 725
    //   707: aload_1
    //   708: bipush 12
    //   710: aload_0
    //   711: getfield 14	com/tencent/mm/plugin/webview/ui/tools/WebViewUI$26:ioV	Lcom/tencent/mm/plugin/webview/ui/tools/WebViewUI;
    //   714: ldc -20
    //   716: invokevirtual 114	com/tencent/mm/plugin/webview/ui/tools/WebViewUI:getString	(I)Ljava/lang/String;
    //   719: ldc -19
    //   721: invokevirtual 118	com/tencent/mm/ui/base/l:a	(ILjava/lang/CharSequence;I)Landroid/view/MenuItem;
    //   724: pop
    //   725: aload_0
    //   726: getfield 14	com/tencent/mm/plugin/webview/ui/tools/WebViewUI$26:ioV	Lcom/tencent/mm/plugin/webview/ui/tools/WebViewUI;
    //   729: bipush 9
    //   731: invokestatic 184	com/tencent/mm/plugin/webview/ui/tools/WebViewUI:c	(Lcom/tencent/mm/plugin/webview/ui/tools/WebViewUI;I)Z
    //   734: ifeq +21 -> 755
    //   737: aload_1
    //   738: bipush 9
    //   740: aload_0
    //   741: getfield 14	com/tencent/mm/plugin/webview/ui/tools/WebViewUI$26:ioV	Lcom/tencent/mm/plugin/webview/ui/tools/WebViewUI;
    //   744: ldc -18
    //   746: invokevirtual 114	com/tencent/mm/plugin/webview/ui/tools/WebViewUI:getString	(I)Ljava/lang/String;
    //   749: ldc -17
    //   751: invokevirtual 118	com/tencent/mm/ui/base/l:a	(ILjava/lang/CharSequence;I)Landroid/view/MenuItem;
    //   754: pop
    //   755: aload_0
    //   756: getfield 14	com/tencent/mm/plugin/webview/ui/tools/WebViewUI$26:ioV	Lcom/tencent/mm/plugin/webview/ui/tools/WebViewUI;
    //   759: invokevirtual 201	com/tencent/mm/plugin/webview/ui/tools/WebViewUI:getIntent	()Landroid/content/Intent;
    //   762: ldc -15
    //   764: invokevirtual 244	android/content/Intent:getStringExtra	(Ljava/lang/String;)Ljava/lang/String;
    //   767: astore 9
    //   769: aload 9
    //   771: invokestatic 248	com/tencent/mm/sdk/platformtools/ay:kz	(Ljava/lang/String;)Z
    //   774: ifne +38 -> 812
    //   777: aload_0
    //   778: getfield 14	com/tencent/mm/plugin/webview/ui/tools/WebViewUI$26:ioV	Lcom/tencent/mm/plugin/webview/ui/tools/WebViewUI;
    //   781: getfield 215	com/tencent/mm/plugin/webview/ui/tools/WebViewUI:ims	Lcom/tencent/mm/plugin/webview/stub/d;
    //   784: aload 9
    //   786: invokeinterface 251 2 0
    //   791: istore 6
    //   793: iload 6
    //   795: ifne +677 -> 1472
    //   798: aload_0
    //   799: getfield 14	com/tencent/mm/plugin/webview/ui/tools/WebViewUI$26:ioV	Lcom/tencent/mm/plugin/webview/ui/tools/WebViewUI;
    //   802: getfield 215	com/tencent/mm/plugin/webview/ui/tools/WebViewUI:ims	Lcom/tencent/mm/plugin/webview/stub/d;
    //   805: aload 9
    //   807: invokeinterface 254 2 0
    //   812: aload 10
    //   814: bipush 45
    //   816: invokevirtual 180	com/tencent/mm/protocal/JsapiPermissionWrapper:oT	(I)Z
    //   819: ifeq +34 -> 853
    //   822: aload_0
    //   823: getfield 14	com/tencent/mm/plugin/webview/ui/tools/WebViewUI$26:ioV	Lcom/tencent/mm/plugin/webview/ui/tools/WebViewUI;
    //   826: bipush 7
    //   828: invokestatic 184	com/tencent/mm/plugin/webview/ui/tools/WebViewUI:c	(Lcom/tencent/mm/plugin/webview/ui/tools/WebViewUI;I)Z
    //   831: ifeq +22 -> 853
    //   834: aload_1
    //   835: bipush 7
    //   837: aload_0
    //   838: getfield 14	com/tencent/mm/plugin/webview/ui/tools/WebViewUI$26:ioV	Lcom/tencent/mm/plugin/webview/ui/tools/WebViewUI;
    //   841: ldc -1
    //   843: invokevirtual 114	com/tencent/mm/plugin/webview/ui/tools/WebViewUI:getString	(I)Ljava/lang/String;
    //   846: ldc_w 256
    //   849: invokevirtual 118	com/tencent/mm/ui/base/l:a	(ILjava/lang/CharSequence;I)Landroid/view/MenuItem;
    //   852: pop
    //   853: aload 10
    //   855: bipush 91
    //   857: invokevirtual 180	com/tencent/mm/protocal/JsapiPermissionWrapper:oT	(I)Z
    //   860: ifeq +45 -> 905
    //   863: aload_0
    //   864: getfield 14	com/tencent/mm/plugin/webview/ui/tools/WebViewUI$26:ioV	Lcom/tencent/mm/plugin/webview/ui/tools/WebViewUI;
    //   867: invokestatic 262	com/tencent/mm/plugin/webview/stub/a:cw	(Landroid/content/Context;)Z
    //   870: ifeq +35 -> 905
    //   873: aload_0
    //   874: getfield 14	com/tencent/mm/plugin/webview/ui/tools/WebViewUI$26:ioV	Lcom/tencent/mm/plugin/webview/ui/tools/WebViewUI;
    //   877: bipush 20
    //   879: invokestatic 184	com/tencent/mm/plugin/webview/ui/tools/WebViewUI:c	(Lcom/tencent/mm/plugin/webview/ui/tools/WebViewUI;I)Z
    //   882: ifeq +23 -> 905
    //   885: aload_1
    //   886: bipush 20
    //   888: aload_0
    //   889: getfield 14	com/tencent/mm/plugin/webview/ui/tools/WebViewUI$26:ioV	Lcom/tencent/mm/plugin/webview/ui/tools/WebViewUI;
    //   892: ldc_w 263
    //   895: invokevirtual 114	com/tencent/mm/plugin/webview/ui/tools/WebViewUI:getString	(I)Ljava/lang/String;
    //   898: ldc_w 264
    //   901: invokevirtual 118	com/tencent/mm/ui/base/l:a	(ILjava/lang/CharSequence;I)Landroid/view/MenuItem;
    //   904: pop
    //   905: aload 10
    //   907: bipush 108
    //   909: invokevirtual 180	com/tencent/mm/protocal/JsapiPermissionWrapper:oT	(I)Z
    //   912: ifeq +45 -> 957
    //   915: aload_0
    //   916: getfield 14	com/tencent/mm/plugin/webview/ui/tools/WebViewUI$26:ioV	Lcom/tencent/mm/plugin/webview/ui/tools/WebViewUI;
    //   919: invokestatic 267	com/tencent/mm/plugin/webview/stub/a:cx	(Landroid/content/Context;)Z
    //   922: ifeq +35 -> 957
    //   925: aload_0
    //   926: getfield 14	com/tencent/mm/plugin/webview/ui/tools/WebViewUI$26:ioV	Lcom/tencent/mm/plugin/webview/ui/tools/WebViewUI;
    //   929: bipush 21
    //   931: invokestatic 184	com/tencent/mm/plugin/webview/ui/tools/WebViewUI:c	(Lcom/tencent/mm/plugin/webview/ui/tools/WebViewUI;I)Z
    //   934: ifeq +23 -> 957
    //   937: aload_1
    //   938: bipush 21
    //   940: aload_0
    //   941: getfield 14	com/tencent/mm/plugin/webview/ui/tools/WebViewUI$26:ioV	Lcom/tencent/mm/plugin/webview/ui/tools/WebViewUI;
    //   944: ldc_w 268
    //   947: invokevirtual 114	com/tencent/mm/plugin/webview/ui/tools/WebViewUI:getString	(I)Ljava/lang/String;
    //   950: ldc_w 269
    //   953: invokevirtual 118	com/tencent/mm/ui/base/l:a	(ILjava/lang/CharSequence;I)Landroid/view/MenuItem;
    //   956: pop
    //   957: aload 10
    //   959: sipush 133
    //   962: invokevirtual 180	com/tencent/mm/protocal/JsapiPermissionWrapper:oT	(I)Z
    //   965: ifeq +45 -> 1010
    //   968: aload_0
    //   969: getfield 14	com/tencent/mm/plugin/webview/ui/tools/WebViewUI$26:ioV	Lcom/tencent/mm/plugin/webview/ui/tools/WebViewUI;
    //   972: invokestatic 272	com/tencent/mm/plugin/webview/stub/a:cy	(Landroid/content/Context;)Z
    //   975: ifeq +35 -> 1010
    //   978: aload_0
    //   979: getfield 14	com/tencent/mm/plugin/webview/ui/tools/WebViewUI$26:ioV	Lcom/tencent/mm/plugin/webview/ui/tools/WebViewUI;
    //   982: bipush 22
    //   984: invokestatic 184	com/tencent/mm/plugin/webview/ui/tools/WebViewUI:c	(Lcom/tencent/mm/plugin/webview/ui/tools/WebViewUI;I)Z
    //   987: ifeq +23 -> 1010
    //   990: aload_1
    //   991: bipush 22
    //   993: aload_0
    //   994: getfield 14	com/tencent/mm/plugin/webview/ui/tools/WebViewUI$26:ioV	Lcom/tencent/mm/plugin/webview/ui/tools/WebViewUI;
    //   997: ldc_w 273
    //   1000: invokevirtual 114	com/tencent/mm/plugin/webview/ui/tools/WebViewUI:getString	(I)Ljava/lang/String;
    //   1003: ldc_w 274
    //   1006: invokevirtual 118	com/tencent/mm/ui/base/l:a	(ILjava/lang/CharSequence;I)Landroid/view/MenuItem;
    //   1009: pop
    //   1010: aload 10
    //   1012: bipush 18
    //   1014: invokevirtual 180	com/tencent/mm/protocal/JsapiPermissionWrapper:oT	(I)Z
    //   1017: ifeq +35 -> 1052
    //   1020: aload_0
    //   1021: getfield 14	com/tencent/mm/plugin/webview/ui/tools/WebViewUI$26:ioV	Lcom/tencent/mm/plugin/webview/ui/tools/WebViewUI;
    //   1024: bipush 11
    //   1026: invokestatic 184	com/tencent/mm/plugin/webview/ui/tools/WebViewUI:c	(Lcom/tencent/mm/plugin/webview/ui/tools/WebViewUI;I)Z
    //   1029: ifeq +23 -> 1052
    //   1032: aload_1
    //   1033: bipush 11
    //   1035: aload_0
    //   1036: getfield 14	com/tencent/mm/plugin/webview/ui/tools/WebViewUI$26:ioV	Lcom/tencent/mm/plugin/webview/ui/tools/WebViewUI;
    //   1039: ldc_w 275
    //   1042: invokevirtual 114	com/tencent/mm/plugin/webview/ui/tools/WebViewUI:getString	(I)Ljava/lang/String;
    //   1045: ldc_w 276
    //   1048: invokevirtual 118	com/tencent/mm/ui/base/l:a	(ILjava/lang/CharSequence;I)Landroid/view/MenuItem;
    //   1051: pop
    //   1052: aload 10
    //   1054: bipush 73
    //   1056: invokevirtual 180	com/tencent/mm/protocal/JsapiPermissionWrapper:oT	(I)Z
    //   1059: ifeq +45 -> 1104
    //   1062: aload_0
    //   1063: getfield 14	com/tencent/mm/plugin/webview/ui/tools/WebViewUI$26:ioV	Lcom/tencent/mm/plugin/webview/ui/tools/WebViewUI;
    //   1066: bipush 14
    //   1068: invokestatic 184	com/tencent/mm/plugin/webview/ui/tools/WebViewUI:c	(Lcom/tencent/mm/plugin/webview/ui/tools/WebViewUI;I)Z
    //   1071: ifeq +33 -> 1104
    //   1074: aload_0
    //   1075: getfield 14	com/tencent/mm/plugin/webview/ui/tools/WebViewUI$26:ioV	Lcom/tencent/mm/plugin/webview/ui/tools/WebViewUI;
    //   1078: invokestatic 279	com/tencent/mm/plugin/webview/ui/tools/WebViewUI:T	(Lcom/tencent/mm/plugin/webview/ui/tools/WebViewUI;)Z
    //   1081: ifne +23 -> 1104
    //   1084: aload_1
    //   1085: bipush 14
    //   1087: aload_0
    //   1088: getfield 14	com/tencent/mm/plugin/webview/ui/tools/WebViewUI$26:ioV	Lcom/tencent/mm/plugin/webview/ui/tools/WebViewUI;
    //   1091: ldc_w 280
    //   1094: invokevirtual 114	com/tencent/mm/plugin/webview/ui/tools/WebViewUI:getString	(I)Ljava/lang/String;
    //   1097: ldc_w 281
    //   1100: invokevirtual 118	com/tencent/mm/ui/base/l:a	(ILjava/lang/CharSequence;I)Landroid/view/MenuItem;
    //   1103: pop
    //   1104: aload_0
    //   1105: getfield 14	com/tencent/mm/plugin/webview/ui/tools/WebViewUI$26:ioV	Lcom/tencent/mm/plugin/webview/ui/tools/WebViewUI;
    //   1108: invokestatic 279	com/tencent/mm/plugin/webview/ui/tools/WebViewUI:T	(Lcom/tencent/mm/plugin/webview/ui/tools/WebViewUI;)Z
    //   1111: ifeq +35 -> 1146
    //   1114: aload_0
    //   1115: getfield 14	com/tencent/mm/plugin/webview/ui/tools/WebViewUI$26:ioV	Lcom/tencent/mm/plugin/webview/ui/tools/WebViewUI;
    //   1118: bipush 14
    //   1120: invokestatic 184	com/tencent/mm/plugin/webview/ui/tools/WebViewUI:c	(Lcom/tencent/mm/plugin/webview/ui/tools/WebViewUI;I)Z
    //   1123: ifeq +23 -> 1146
    //   1126: aload_1
    //   1127: bipush 14
    //   1129: aload_0
    //   1130: getfield 14	com/tencent/mm/plugin/webview/ui/tools/WebViewUI$26:ioV	Lcom/tencent/mm/plugin/webview/ui/tools/WebViewUI;
    //   1133: ldc_w 282
    //   1136: invokevirtual 114	com/tencent/mm/plugin/webview/ui/tools/WebViewUI:getString	(I)Ljava/lang/String;
    //   1139: ldc_w 283
    //   1142: invokevirtual 118	com/tencent/mm/ui/base/l:a	(ILjava/lang/CharSequence;I)Landroid/view/MenuItem;
    //   1145: pop
    //   1146: aload_0
    //   1147: getfield 14	com/tencent/mm/plugin/webview/ui/tools/WebViewUI$26:ioV	Lcom/tencent/mm/plugin/webview/ui/tools/WebViewUI;
    //   1150: invokestatic 168	com/tencent/mm/plugin/webview/ui/tools/WebViewUI:b	(Lcom/tencent/mm/plugin/webview/ui/tools/WebViewUI;)Lcom/tencent/mm/plugin/webview/ui/tools/e;
    //   1153: invokevirtual 287	com/tencent/mm/plugin/webview/ui/tools/e:aMY	()Lcom/tencent/mm/protocal/GeneralControlWrapper;
    //   1156: getfield 292	com/tencent/mm/protocal/GeneralControlWrapper:iUo	I
    //   1159: bipush 16
    //   1161: iand
    //   1162: ifle +461 -> 1623
    //   1165: iconst_1
    //   1166: istore 6
    //   1168: ldc_w 294
    //   1171: new 144	java/lang/StringBuilder
    //   1174: dup
    //   1175: ldc_w 296
    //   1178: invokespecial 149	java/lang/StringBuilder:<init>	(Ljava/lang/String;)V
    //   1181: iload 6
    //   1183: invokevirtual 299	java/lang/StringBuilder:append	(Z)Ljava/lang/StringBuilder;
    //   1186: invokevirtual 159	java/lang/StringBuilder:toString	()Ljava/lang/String;
    //   1189: invokestatic 302	com/tencent/mm/sdk/platformtools/u:d	(Ljava/lang/String;Ljava/lang/String;)V
    //   1192: iload 6
    //   1194: ifeq +35 -> 1229
    //   1197: aload_0
    //   1198: getfield 14	com/tencent/mm/plugin/webview/ui/tools/WebViewUI$26:ioV	Lcom/tencent/mm/plugin/webview/ui/tools/WebViewUI;
    //   1201: bipush 10
    //   1203: invokestatic 184	com/tencent/mm/plugin/webview/ui/tools/WebViewUI:c	(Lcom/tencent/mm/plugin/webview/ui/tools/WebViewUI;I)Z
    //   1206: ifeq +23 -> 1229
    //   1209: aload_1
    //   1210: bipush 10
    //   1212: aload_0
    //   1213: getfield 14	com/tencent/mm/plugin/webview/ui/tools/WebViewUI$26:ioV	Lcom/tencent/mm/plugin/webview/ui/tools/WebViewUI;
    //   1216: ldc_w 303
    //   1219: invokevirtual 114	com/tencent/mm/plugin/webview/ui/tools/WebViewUI:getString	(I)Ljava/lang/String;
    //   1222: ldc_w 304
    //   1225: invokevirtual 118	com/tencent/mm/ui/base/l:a	(ILjava/lang/CharSequence;I)Landroid/view/MenuItem;
    //   1228: pop
    //   1229: aload 10
    //   1231: bipush 36
    //   1233: invokevirtual 180	com/tencent/mm/protocal/JsapiPermissionWrapper:oT	(I)Z
    //   1236: ifeq +57 -> 1293
    //   1239: aload_0
    //   1240: getfield 14	com/tencent/mm/plugin/webview/ui/tools/WebViewUI$26:ioV	Lcom/tencent/mm/plugin/webview/ui/tools/WebViewUI;
    //   1243: bipush 8
    //   1245: invokestatic 184	com/tencent/mm/plugin/webview/ui/tools/WebViewUI:c	(Lcom/tencent/mm/plugin/webview/ui/tools/WebViewUI;I)Z
    //   1248: ifeq +45 -> 1293
    //   1251: aload_0
    //   1252: getfield 14	com/tencent/mm/plugin/webview/ui/tools/WebViewUI$26:ioV	Lcom/tencent/mm/plugin/webview/ui/tools/WebViewUI;
    //   1255: getfield 215	com/tencent/mm/plugin/webview/ui/tools/WebViewUI:ims	Lcom/tencent/mm/plugin/webview/stub/d;
    //   1258: invokeinterface 307 1 0
    //   1263: astore 9
    //   1265: aload 9
    //   1267: invokestatic 248	com/tencent/mm/sdk/platformtools/ay:kz	(Ljava/lang/String;)Z
    //   1270: ifne +367 -> 1637
    //   1273: aload_1
    //   1274: bipush 8
    //   1276: aload_0
    //   1277: getfield 14	com/tencent/mm/plugin/webview/ui/tools/WebViewUI$26:ioV	Lcom/tencent/mm/plugin/webview/ui/tools/WebViewUI;
    //   1280: ldc_w 308
    //   1283: invokevirtual 114	com/tencent/mm/plugin/webview/ui/tools/WebViewUI:getString	(I)Ljava/lang/String;
    //   1286: ldc_w 309
    //   1289: invokevirtual 118	com/tencent/mm/ui/base/l:a	(ILjava/lang/CharSequence;I)Landroid/view/MenuItem;
    //   1292: pop
    //   1293: aload 10
    //   1295: bipush 43
    //   1297: invokevirtual 180	com/tencent/mm/protocal/JsapiPermissionWrapper:oT	(I)Z
    //   1300: ifeq +106 -> 1406
    //   1303: aload_0
    //   1304: getfield 14	com/tencent/mm/plugin/webview/ui/tools/WebViewUI$26:ioV	Lcom/tencent/mm/plugin/webview/ui/tools/WebViewUI;
    //   1307: iconst_0
    //   1308: invokestatic 184	com/tencent/mm/plugin/webview/ui/tools/WebViewUI:c	(Lcom/tencent/mm/plugin/webview/ui/tools/WebViewUI;I)Z
    //   1311: ifeq +95 -> 1406
    //   1314: aload_0
    //   1315: getfield 14	com/tencent/mm/plugin/webview/ui/tools/WebViewUI$26:ioV	Lcom/tencent/mm/plugin/webview/ui/tools/WebViewUI;
    //   1318: getfield 215	com/tencent/mm/plugin/webview/ui/tools/WebViewUI:ims	Lcom/tencent/mm/plugin/webview/stub/d;
    //   1321: invokeinterface 313 1 0
    //   1326: ifeq +80 -> 1406
    //   1329: aload_0
    //   1330: getfield 14	com/tencent/mm/plugin/webview/ui/tools/WebViewUI$26:ioV	Lcom/tencent/mm/plugin/webview/ui/tools/WebViewUI;
    //   1333: getfield 215	com/tencent/mm/plugin/webview/ui/tools/WebViewUI:ims	Lcom/tencent/mm/plugin/webview/stub/d;
    //   1336: invokeinterface 317 1 0
    //   1341: astore 9
    //   1343: aload 9
    //   1345: invokeinterface 323 1 0
    //   1350: astore 10
    //   1352: aload 10
    //   1354: invokeinterface 328 1 0
    //   1359: ifeq +289 -> 1648
    //   1362: aload_1
    //   1363: aload 10
    //   1365: invokeinterface 332 1 0
    //   1370: checkcast 106	java/lang/String
    //   1373: invokevirtual 336	com/tencent/mm/ui/base/l:add	(Ljava/lang/CharSequence;)Landroid/view/MenuItem;
    //   1376: pop
    //   1377: goto -25 -> 1352
    //   1380: astore_1
    //   1381: ldc -114
    //   1383: new 144	java/lang/StringBuilder
    //   1386: dup
    //   1387: ldc_w 338
    //   1390: invokespecial 149	java/lang/StringBuilder:<init>	(Ljava/lang/String;)V
    //   1393: aload_1
    //   1394: invokevirtual 152	java/lang/Exception:getMessage	()Ljava/lang/String;
    //   1397: invokevirtual 156	java/lang/StringBuilder:append	(Ljava/lang/String;)Ljava/lang/StringBuilder;
    //   1400: invokevirtual 159	java/lang/StringBuilder:toString	()Ljava/lang/String;
    //   1403: invokestatic 341	com/tencent/mm/sdk/platformtools/u:w	(Ljava/lang/String;Ljava/lang/String;)V
    //   1406: return
    //   1407: astore 11
    //   1409: ldc -114
    //   1411: new 144	java/lang/StringBuilder
    //   1414: dup
    //   1415: ldc_w 343
    //   1418: invokespecial 149	java/lang/StringBuilder:<init>	(Ljava/lang/String;)V
    //   1421: aload 11
    //   1423: invokevirtual 152	java/lang/Exception:getMessage	()Ljava/lang/String;
    //   1426: invokevirtual 156	java/lang/StringBuilder:append	(Ljava/lang/String;)Ljava/lang/StringBuilder;
    //   1429: invokevirtual 159	java/lang/StringBuilder:toString	()Ljava/lang/String;
    //   1432: invokestatic 165	com/tencent/mm/sdk/platformtools/u:e	(Ljava/lang/String;Ljava/lang/String;)V
    //   1435: iconst_0
    //   1436: istore 6
    //   1438: goto -645 -> 793
    //   1441: astore 9
    //   1443: ldc -114
    //   1445: new 144	java/lang/StringBuilder
    //   1448: dup
    //   1449: ldc_w 345
    //   1452: invokespecial 149	java/lang/StringBuilder:<init>	(Ljava/lang/String;)V
    //   1455: aload 9
    //   1457: invokevirtual 152	java/lang/Exception:getMessage	()Ljava/lang/String;
    //   1460: invokevirtual 156	java/lang/StringBuilder:append	(Ljava/lang/String;)Ljava/lang/StringBuilder;
    //   1463: invokevirtual 159	java/lang/StringBuilder:toString	()Ljava/lang/String;
    //   1466: invokestatic 165	com/tencent/mm/sdk/platformtools/u:e	(Ljava/lang/String;Ljava/lang/String;)V
    //   1469: goto -657 -> 812
    //   1472: aload_0
    //   1473: getfield 14	com/tencent/mm/plugin/webview/ui/tools/WebViewUI$26:ioV	Lcom/tencent/mm/plugin/webview/ui/tools/WebViewUI;
    //   1476: getfield 215	com/tencent/mm/plugin/webview/ui/tools/WebViewUI:ims	Lcom/tencent/mm/plugin/webview/stub/d;
    //   1479: aload 9
    //   1481: invokeinterface 348 2 0
    //   1486: istore 6
    //   1488: iload 6
    //   1490: ifeq +114 -> 1604
    //   1493: aload 10
    //   1495: bipush 19
    //   1497: invokevirtual 180	com/tencent/mm/protocal/JsapiPermissionWrapper:oT	(I)Z
    //   1500: istore 7
    //   1502: aload_0
    //   1503: getfield 14	com/tencent/mm/plugin/webview/ui/tools/WebViewUI$26:ioV	Lcom/tencent/mm/plugin/webview/ui/tools/WebViewUI;
    //   1506: invokestatic 351	com/tencent/mm/plugin/webview/ui/tools/WebViewUI:ad	(Lcom/tencent/mm/plugin/webview/ui/tools/WebViewUI;)Z
    //   1509: istore 8
    //   1511: iload 7
    //   1513: ifeq +14 -> 1527
    //   1516: aload_0
    //   1517: getfield 14	com/tencent/mm/plugin/webview/ui/tools/WebViewUI$26:ioV	Lcom/tencent/mm/plugin/webview/ui/tools/WebViewUI;
    //   1520: iconst_5
    //   1521: invokestatic 184	com/tencent/mm/plugin/webview/ui/tools/WebViewUI:c	(Lcom/tencent/mm/plugin/webview/ui/tools/WebViewUI;I)Z
    //   1524: ifne +8 -> 1532
    //   1527: iload 8
    //   1529: ifeq -717 -> 812
    //   1532: iload 6
    //   1534: ifeq +82 -> 1616
    //   1537: ldc_w 352
    //   1540: istore_2
    //   1541: iload 8
    //   1543: ifeq +7 -> 1550
    //   1546: ldc_w 353
    //   1549: istore_2
    //   1550: aload_1
    //   1551: iconst_5
    //   1552: aload_0
    //   1553: getfield 14	com/tencent/mm/plugin/webview/ui/tools/WebViewUI$26:ioV	Lcom/tencent/mm/plugin/webview/ui/tools/WebViewUI;
    //   1556: iload_2
    //   1557: invokevirtual 114	com/tencent/mm/plugin/webview/ui/tools/WebViewUI:getString	(I)Ljava/lang/String;
    //   1560: ldc_w 354
    //   1563: invokevirtual 118	com/tencent/mm/ui/base/l:a	(ILjava/lang/CharSequence;I)Landroid/view/MenuItem;
    //   1566: pop
    //   1567: goto -755 -> 812
    //   1570: astore 9
    //   1572: ldc -114
    //   1574: new 144	java/lang/StringBuilder
    //   1577: dup
    //   1578: ldc_w 356
    //   1581: invokespecial 149	java/lang/StringBuilder:<init>	(Ljava/lang/String;)V
    //   1584: aload 9
    //   1586: invokevirtual 152	java/lang/Exception:getMessage	()Ljava/lang/String;
    //   1589: invokevirtual 156	java/lang/StringBuilder:append	(Ljava/lang/String;)Ljava/lang/StringBuilder;
    //   1592: invokevirtual 159	java/lang/StringBuilder:toString	()Ljava/lang/String;
    //   1595: invokestatic 165	com/tencent/mm/sdk/platformtools/u:e	(Ljava/lang/String;Ljava/lang/String;)V
    //   1598: iconst_0
    //   1599: istore 6
    //   1601: goto -113 -> 1488
    //   1604: aload 10
    //   1606: bipush 20
    //   1608: invokevirtual 180	com/tencent/mm/protocal/JsapiPermissionWrapper:oT	(I)Z
    //   1611: istore 7
    //   1613: goto -111 -> 1502
    //   1616: ldc_w 357
    //   1619: istore_2
    //   1620: goto -79 -> 1541
    //   1623: iconst_0
    //   1624: istore 6
    //   1626: goto -458 -> 1168
    //   1629: astore 9
    //   1631: aconst_null
    //   1632: astore 9
    //   1634: goto -369 -> 1265
    //   1637: ldc -114
    //   1639: ldc_w 359
    //   1642: invokestatic 362	com/tencent/mm/sdk/platformtools/u:i	(Ljava/lang/String;Ljava/lang/String;)V
    //   1645: goto -352 -> 1293
    //   1648: aload_0
    //   1649: getfield 14	com/tencent/mm/plugin/webview/ui/tools/WebViewUI$26:ioV	Lcom/tencent/mm/plugin/webview/ui/tools/WebViewUI;
    //   1652: aload 9
    //   1654: invokestatic 365	com/tencent/mm/plugin/webview/ui/tools/WebViewUI:a	(Lcom/tencent/mm/plugin/webview/ui/tools/WebViewUI;Ljava/util/List;)V
    //   1657: return
    //   1658: astore 9
    //   1660: goto -1049 -> 611
    //   1663: aconst_null
    //   1664: astore 9
    //   1666: goto -1452 -> 214
    //   1669: iload_2
    //   1670: iconst_1
    //   1671: iadd
    //   1672: istore_2
    //   1673: goto -1523 -> 150
    // Local variable table:
    //   start	length	slot	name	signature
    //   0	1676	0	this	26
    //   0	1676	1	paraml	com.tencent.mm.ui.base.l
    //   64	1609	2	i	int
    //   62	6	3	j	int
    //   574	10	4	l	long
    //   791	834	6	bool1	boolean
    //   1500	112	7	bool2	boolean
    //   1509	33	8	bool3	boolean
    //   4	388	9	localObject1	Object
    //   396	14	9	localException1	Exception
    //   767	577	9	localObject2	Object
    //   1441	39	9	localException2	Exception
    //   1570	15	9	localException3	Exception
    //   1629	1	9	localException4	Exception
    //   1632	21	9	localList	java.util.List
    //   1658	1	9	localException5	Exception
    //   1664	1	9	localObject3	Object
    //   14	1591	10	localObject4	Object
    //   98	260	11	localObject5	Object
    //   1407	15	11	localException6	Exception
    // Exception table:
    //   from	to	target	type
    //   134	143	396	java/lang/Exception
    //   150	159	396	java/lang/Exception
    //   165	214	396	java/lang/Exception
    //   219	229	396	java/lang/Exception
    //   232	270	396	java/lang/Exception
    //   273	311	396	java/lang/Exception
    //   314	352	396	java/lang/Exception
    //   355	393	396	java/lang/Exception
    //   1293	1352	1380	java/lang/Exception
    //   1352	1377	1380	java/lang/Exception
    //   1648	1657	1380	java/lang/Exception
    //   777	793	1407	java/lang/Exception
    //   798	812	1441	java/lang/Exception
    //   1472	1488	1570	java/lang/Exception
    //   1251	1265	1629	java/lang/Exception
    //   576	611	1658	java/lang/Exception
  }
}

/* Location:
 * Qualified Name:     com.tencent.mm.plugin.webview.ui.tools.WebViewUI.26
 * Java Class Version: 6 (50.0)
 * JD-Core Version:    0.7.1
 */