package com.tencent.wxop.stat;

import java.util.List;

final class ak
  implements Runnable
{
  ak(ai paramai, List paramList, ah paramah) {}
  
  /* Error */
  public final void run()
  {
    // Byte code:
    //   0: aload_0
    //   1: getfield 16	com/tencent/wxop/stat/ak:maS	Lcom/tencent/wxop/stat/ai;
    //   4: astore 7
    //   6: aload_0
    //   7: getfield 18	com/tencent/wxop/stat/ak:a	Ljava/util/List;
    //   10: astore 5
    //   12: aload_0
    //   13: getfield 20	com/tencent/wxop/stat/ak:maf	Lcom/tencent/wxop/stat/ah;
    //   16: astore 8
    //   18: aload 5
    //   20: ifnull +13 -> 33
    //   23: aload 5
    //   25: invokeinterface 33 1 0
    //   30: ifeq +4 -> 34
    //   33: return
    //   34: aload 5
    //   36: invokeinterface 37 1 0
    //   41: istore_2
    //   42: aload 5
    //   44: iconst_0
    //   45: invokeinterface 41 2 0
    //   50: pop
    //   51: aload 7
    //   53: getfield 47	com/tencent/wxop/stat/ai:maO	Ljava/lang/StringBuilder;
    //   56: iconst_0
    //   57: aload 7
    //   59: getfield 47	com/tencent/wxop/stat/ai:maO	Ljava/lang/StringBuilder;
    //   62: invokevirtual 52	java/lang/StringBuilder:length	()I
    //   65: invokevirtual 56	java/lang/StringBuilder:delete	(II)Ljava/lang/StringBuilder;
    //   68: pop
    //   69: aload 7
    //   71: getfield 47	com/tencent/wxop/stat/ai:maO	Ljava/lang/StringBuilder;
    //   74: ldc 58
    //   76: invokevirtual 62	java/lang/StringBuilder:append	(Ljava/lang/String;)Ljava/lang/StringBuilder;
    //   79: pop
    //   80: iconst_0
    //   81: istore_1
    //   82: iload_1
    //   83: iload_2
    //   84: if_icmpge +44 -> 128
    //   87: aload 7
    //   89: getfield 47	com/tencent/wxop/stat/ai:maO	Ljava/lang/StringBuilder;
    //   92: aload 5
    //   94: iload_1
    //   95: invokeinterface 41 2 0
    //   100: invokevirtual 66	java/lang/Object:toString	()Ljava/lang/String;
    //   103: invokevirtual 62	java/lang/StringBuilder:append	(Ljava/lang/String;)Ljava/lang/StringBuilder;
    //   106: pop
    //   107: iload_1
    //   108: iload_2
    //   109: iconst_1
    //   110: isub
    //   111: if_icmpeq +1308 -> 1419
    //   114: aload 7
    //   116: getfield 47	com/tencent/wxop/stat/ai:maO	Ljava/lang/StringBuilder;
    //   119: ldc 68
    //   121: invokevirtual 62	java/lang/StringBuilder:append	(Ljava/lang/String;)Ljava/lang/StringBuilder;
    //   124: pop
    //   125: goto +1294 -> 1419
    //   128: aload 7
    //   130: getfield 47	com/tencent/wxop/stat/ai:maO	Ljava/lang/StringBuilder;
    //   133: ldc 70
    //   135: invokevirtual 62	java/lang/StringBuilder:append	(Ljava/lang/String;)Ljava/lang/StringBuilder;
    //   138: pop
    //   139: aload 7
    //   141: getfield 47	com/tencent/wxop/stat/ai:maO	Ljava/lang/StringBuilder;
    //   144: invokevirtual 71	java/lang/StringBuilder:toString	()Ljava/lang/String;
    //   147: astore 5
    //   149: aload 5
    //   151: invokevirtual 74	java/lang/String:length	()I
    //   154: istore_1
    //   155: new 49	java/lang/StringBuilder
    //   158: dup
    //   159: invokespecial 75	java/lang/StringBuilder:<init>	()V
    //   162: invokestatic 80	com/tencent/wxop/stat/b:bnD	()Ljava/lang/String;
    //   165: invokevirtual 62	java/lang/StringBuilder:append	(Ljava/lang/String;)Ljava/lang/StringBuilder;
    //   168: ldc 82
    //   170: invokevirtual 62	java/lang/StringBuilder:append	(Ljava/lang/String;)Ljava/lang/StringBuilder;
    //   173: aload 7
    //   175: getfield 86	com/tencent/wxop/stat/ai:g	J
    //   178: invokevirtual 89	java/lang/StringBuilder:append	(J)Ljava/lang/StringBuilder;
    //   181: invokevirtual 71	java/lang/StringBuilder:toString	()Ljava/lang/String;
    //   184: astore 6
    //   186: aload 7
    //   188: aload 7
    //   190: getfield 86	com/tencent/wxop/stat/ai:g	J
    //   193: lconst_1
    //   194: ladd
    //   195: putfield 86	com/tencent/wxop/stat/ai:g	J
    //   198: invokestatic 92	com/tencent/wxop/stat/b:bns	()Z
    //   201: ifeq +45 -> 246
    //   204: getstatic 96	com/tencent/wxop/stat/ai:man	Lcom/tencent/wxop/stat/b/b;
    //   207: new 49	java/lang/StringBuilder
    //   210: dup
    //   211: ldc 58
    //   213: invokespecial 99	java/lang/StringBuilder:<init>	(Ljava/lang/String;)V
    //   216: aload 6
    //   218: invokevirtual 62	java/lang/StringBuilder:append	(Ljava/lang/String;)Ljava/lang/StringBuilder;
    //   221: ldc 101
    //   223: invokevirtual 62	java/lang/StringBuilder:append	(Ljava/lang/String;)Ljava/lang/StringBuilder;
    //   226: iload_1
    //   227: invokevirtual 104	java/lang/StringBuilder:append	(I)Ljava/lang/StringBuilder;
    //   230: ldc 106
    //   232: invokevirtual 62	java/lang/StringBuilder:append	(Ljava/lang/String;)Ljava/lang/StringBuilder;
    //   235: aload 5
    //   237: invokevirtual 62	java/lang/StringBuilder:append	(Ljava/lang/String;)Ljava/lang/StringBuilder;
    //   240: invokevirtual 71	java/lang/StringBuilder:toString	()Ljava/lang/String;
    //   243: invokevirtual 112	com/tencent/wxop/stat/b/b:aC	(Ljava/lang/Object;)V
    //   246: new 114	org/apache/http/client/methods/HttpPost
    //   249: dup
    //   250: aload 6
    //   252: invokespecial 115	org/apache/http/client/methods/HttpPost:<init>	(Ljava/lang/String;)V
    //   255: astore 10
    //   257: aload 10
    //   259: ldc 117
    //   261: ldc 119
    //   263: invokevirtual 123	org/apache/http/client/methods/HttpPost:addHeader	(Ljava/lang/String;Ljava/lang/String;)V
    //   266: aload 10
    //   268: ldc 125
    //   270: ldc 127
    //   272: invokevirtual 130	org/apache/http/client/methods/HttpPost:setHeader	(Ljava/lang/String;Ljava/lang/String;)V
    //   275: aload 10
    //   277: ldc -124
    //   279: invokevirtual 135	org/apache/http/client/methods/HttpPost:removeHeaders	(Ljava/lang/String;)V
    //   282: getstatic 139	com/tencent/wxop/stat/ai:maQ	Landroid/content/Context;
    //   285: invokestatic 145	com/tencent/wxop/stat/f:gj	(Landroid/content/Context;)Lcom/tencent/wxop/stat/f;
    //   288: getfield 149	com/tencent/wxop/stat/f:lZs	Lorg/apache/http/HttpHost;
    //   291: astore 11
    //   293: aload 10
    //   295: ldc -105
    //   297: ldc -103
    //   299: invokevirtual 123	org/apache/http/client/methods/HttpPost:addHeader	(Ljava/lang/String;Ljava/lang/String;)V
    //   302: aload 11
    //   304: ifnonnull +441 -> 745
    //   307: aload 7
    //   309: getfield 157	com/tencent/wxop/stat/ai:maM	Lorg/apache/http/impl/client/DefaultHttpClient;
    //   312: invokevirtual 163	org/apache/http/impl/client/DefaultHttpClient:getParams	()Lorg/apache/http/params/HttpParams;
    //   315: ldc -91
    //   317: invokeinterface 171 2 0
    //   322: pop
    //   323: new 173	java/io/ByteArrayOutputStream
    //   326: dup
    //   327: iload_1
    //   328: invokespecial 176	java/io/ByteArrayOutputStream:<init>	(I)V
    //   331: astore 9
    //   333: aload 5
    //   335: ldc -78
    //   337: invokevirtual 182	java/lang/String:getBytes	(Ljava/lang/String;)[B
    //   340: astore 6
    //   342: aload 6
    //   344: arraylength
    //   345: istore_2
    //   346: iload_1
    //   347: getstatic 186	com/tencent/wxop/stat/b:o	I
    //   350: if_icmple +496 -> 846
    //   353: iconst_1
    //   354: istore_1
    //   355: aload 6
    //   357: astore 5
    //   359: iload_1
    //   360: ifeq +164 -> 524
    //   363: aload 10
    //   365: ldc -105
    //   367: invokevirtual 135	org/apache/http/client/methods/HttpPost:removeHeaders	(Ljava/lang/String;)V
    //   370: new 49	java/lang/StringBuilder
    //   373: dup
    //   374: invokespecial 75	java/lang/StringBuilder:<init>	()V
    //   377: ldc -103
    //   379: invokevirtual 62	java/lang/StringBuilder:append	(Ljava/lang/String;)Ljava/lang/StringBuilder;
    //   382: ldc -68
    //   384: invokevirtual 62	java/lang/StringBuilder:append	(Ljava/lang/String;)Ljava/lang/StringBuilder;
    //   387: invokevirtual 71	java/lang/StringBuilder:toString	()Ljava/lang/String;
    //   390: astore 5
    //   392: aload 10
    //   394: ldc -105
    //   396: aload 5
    //   398: invokevirtual 123	org/apache/http/client/methods/HttpPost:addHeader	(Ljava/lang/String;Ljava/lang/String;)V
    //   401: aload 11
    //   403: ifnull +19 -> 422
    //   406: aload 10
    //   408: ldc -66
    //   410: invokevirtual 135	org/apache/http/client/methods/HttpPost:removeHeaders	(Ljava/lang/String;)V
    //   413: aload 10
    //   415: ldc -66
    //   417: aload 5
    //   419: invokevirtual 123	org/apache/http/client/methods/HttpPost:addHeader	(Ljava/lang/String;Ljava/lang/String;)V
    //   422: aload 9
    //   424: iconst_4
    //   425: newarray <illegal type>
    //   427: invokevirtual 194	java/io/ByteArrayOutputStream:write	([B)V
    //   430: new 196	java/util/zip/GZIPOutputStream
    //   433: dup
    //   434: aload 9
    //   436: invokespecial 199	java/util/zip/GZIPOutputStream:<init>	(Ljava/io/OutputStream;)V
    //   439: astore 5
    //   441: aload 5
    //   443: aload 6
    //   445: invokevirtual 200	java/util/zip/GZIPOutputStream:write	([B)V
    //   448: aload 5
    //   450: invokevirtual 203	java/util/zip/GZIPOutputStream:close	()V
    //   453: aload 9
    //   455: invokevirtual 207	java/io/ByteArrayOutputStream:toByteArray	()[B
    //   458: astore 6
    //   460: aload 6
    //   462: iconst_0
    //   463: iconst_4
    //   464: invokestatic 213	java/nio/ByteBuffer:wrap	([BII)Ljava/nio/ByteBuffer;
    //   467: iload_2
    //   468: invokevirtual 217	java/nio/ByteBuffer:putInt	(I)Ljava/nio/ByteBuffer;
    //   471: pop
    //   472: aload 6
    //   474: astore 5
    //   476: invokestatic 92	com/tencent/wxop/stat/b:bns	()Z
    //   479: ifeq +45 -> 524
    //   482: getstatic 96	com/tencent/wxop/stat/ai:man	Lcom/tencent/wxop/stat/b/b;
    //   485: new 49	java/lang/StringBuilder
    //   488: dup
    //   489: ldc -37
    //   491: invokespecial 99	java/lang/StringBuilder:<init>	(Ljava/lang/String;)V
    //   494: iload_2
    //   495: invokevirtual 104	java/lang/StringBuilder:append	(I)Ljava/lang/StringBuilder;
    //   498: ldc -35
    //   500: invokevirtual 62	java/lang/StringBuilder:append	(Ljava/lang/String;)Ljava/lang/StringBuilder;
    //   503: aload 6
    //   505: arraylength
    //   506: invokevirtual 104	java/lang/StringBuilder:append	(I)Ljava/lang/StringBuilder;
    //   509: ldc -33
    //   511: invokevirtual 62	java/lang/StringBuilder:append	(Ljava/lang/String;)Ljava/lang/StringBuilder;
    //   514: invokevirtual 71	java/lang/StringBuilder:toString	()Ljava/lang/String;
    //   517: invokevirtual 226	com/tencent/wxop/stat/b/b:L	(Ljava/lang/Object;)V
    //   520: aload 6
    //   522: astore 5
    //   524: aload 10
    //   526: new 228	org/apache/http/entity/ByteArrayEntity
    //   529: dup
    //   530: aload 5
    //   532: invokestatic 233	com/tencent/wxop/stat/b/g:a	([B)[B
    //   535: invokespecial 235	org/apache/http/entity/ByteArrayEntity:<init>	([B)V
    //   538: invokevirtual 239	org/apache/http/client/methods/HttpPost:setEntity	(Lorg/apache/http/HttpEntity;)V
    //   541: aload 7
    //   543: getfield 157	com/tencent/wxop/stat/ai:maM	Lorg/apache/http/impl/client/DefaultHttpClient;
    //   546: aload 10
    //   548: invokevirtual 243	org/apache/http/impl/client/DefaultHttpClient:execute	(Lorg/apache/http/client/methods/HttpUriRequest;)Lorg/apache/http/HttpResponse;
    //   551: astore 5
    //   553: aload 5
    //   555: invokeinterface 249 1 0
    //   560: astore 6
    //   562: aload 5
    //   564: invokeinterface 253 1 0
    //   569: invokeinterface 258 1 0
    //   574: istore_1
    //   575: aload 6
    //   577: invokeinterface 264 1 0
    //   582: lstore_3
    //   583: invokestatic 92	com/tencent/wxop/stat/b:bns	()Z
    //   586: ifeq +36 -> 622
    //   589: getstatic 96	com/tencent/wxop/stat/ai:man	Lcom/tencent/wxop/stat/b/b;
    //   592: new 49	java/lang/StringBuilder
    //   595: dup
    //   596: ldc_w 266
    //   599: invokespecial 99	java/lang/StringBuilder:<init>	(Ljava/lang/String;)V
    //   602: iload_1
    //   603: invokevirtual 104	java/lang/StringBuilder:append	(I)Ljava/lang/StringBuilder;
    //   606: ldc_w 268
    //   609: invokevirtual 62	java/lang/StringBuilder:append	(Ljava/lang/String;)Ljava/lang/StringBuilder;
    //   612: lload_3
    //   613: invokevirtual 89	java/lang/StringBuilder:append	(J)Ljava/lang/StringBuilder;
    //   616: invokevirtual 71	java/lang/StringBuilder:toString	()Ljava/lang/String;
    //   619: invokevirtual 112	com/tencent/wxop/stat/b/b:aC	(Ljava/lang/Object;)V
    //   622: lload_3
    //   623: lconst_0
    //   624: lcmp
    //   625: ifgt +226 -> 851
    //   628: getstatic 96	com/tencent/wxop/stat/ai:man	Lcom/tencent/wxop/stat/b/b;
    //   631: ldc_w 270
    //   634: invokevirtual 273	com/tencent/wxop/stat/b/b:aE	(Ljava/lang/Object;)V
    //   637: aload 8
    //   639: ifnull +10 -> 649
    //   642: aload 8
    //   644: invokeinterface 278 1 0
    //   649: aload 6
    //   651: invokestatic 283	org/apache/http/util/EntityUtils:toString	(Lorg/apache/http/HttpEntity;)Ljava/lang/String;
    //   654: pop
    //   655: return
    //   656: astore 5
    //   658: aload 5
    //   660: ifnull -627 -> 33
    //   663: getstatic 96	com/tencent/wxop/stat/ai:man	Lcom/tencent/wxop/stat/b/b;
    //   666: invokevirtual 286	com/tencent/wxop/stat/b/b:bnT	()V
    //   669: aload 8
    //   671: ifnull +10 -> 681
    //   674: aload 8
    //   676: invokeinterface 278 1 0
    //   681: aload 5
    //   683: instanceof 288
    //   686: ifeq +27 -> 713
    //   689: invokestatic 293	java/lang/System:gc	()V
    //   692: aload 7
    //   694: aconst_null
    //   695: putfield 47	com/tencent/wxop/stat/ai:maO	Ljava/lang/StringBuilder;
    //   698: aload 7
    //   700: new 49	java/lang/StringBuilder
    //   703: dup
    //   704: sipush 2048
    //   707: invokespecial 294	java/lang/StringBuilder:<init>	(I)V
    //   710: putfield 47	com/tencent/wxop/stat/ai:maO	Ljava/lang/StringBuilder;
    //   713: getstatic 139	com/tencent/wxop/stat/ai:maQ	Landroid/content/Context;
    //   716: invokestatic 145	com/tencent/wxop/stat/f:gj	(Landroid/content/Context;)Lcom/tencent/wxop/stat/f;
    //   719: astore 5
    //   721: aload 5
    //   723: aload 5
    //   725: getfield 297	com/tencent/wxop/stat/f:f	I
    //   728: iconst_1
    //   729: iadd
    //   730: aload 5
    //   732: getfield 298	com/tencent/wxop/stat/f:a	Ljava/util/List;
    //   735: invokeinterface 37 1 0
    //   740: irem
    //   741: putfield 297	com/tencent/wxop/stat/f:f	I
    //   744: return
    //   745: invokestatic 92	com/tencent/wxop/stat/b:bns	()Z
    //   748: ifeq +30 -> 778
    //   751: getstatic 96	com/tencent/wxop/stat/ai:man	Lcom/tencent/wxop/stat/b/b;
    //   754: new 49	java/lang/StringBuilder
    //   757: dup
    //   758: ldc_w 300
    //   761: invokespecial 99	java/lang/StringBuilder:<init>	(Ljava/lang/String;)V
    //   764: aload 11
    //   766: invokevirtual 305	org/apache/http/HttpHost:toHostString	()Ljava/lang/String;
    //   769: invokevirtual 62	java/lang/StringBuilder:append	(Ljava/lang/String;)Ljava/lang/StringBuilder;
    //   772: invokevirtual 71	java/lang/StringBuilder:toString	()Ljava/lang/String;
    //   775: invokevirtual 226	com/tencent/wxop/stat/b/b:L	(Ljava/lang/Object;)V
    //   778: aload 10
    //   780: ldc -66
    //   782: ldc -103
    //   784: invokevirtual 123	org/apache/http/client/methods/HttpPost:addHeader	(Ljava/lang/String;Ljava/lang/String;)V
    //   787: aload 7
    //   789: getfield 157	com/tencent/wxop/stat/ai:maM	Lorg/apache/http/impl/client/DefaultHttpClient;
    //   792: invokevirtual 163	org/apache/http/impl/client/DefaultHttpClient:getParams	()Lorg/apache/http/params/HttpParams;
    //   795: ldc -91
    //   797: aload 11
    //   799: invokeinterface 309 3 0
    //   804: pop
    //   805: aload 10
    //   807: ldc_w 311
    //   810: getstatic 315	com/tencent/wxop/stat/b:k	Ljava/lang/String;
    //   813: invokevirtual 123	org/apache/http/client/methods/HttpPost:addHeader	(Ljava/lang/String;Ljava/lang/String;)V
    //   816: aload 10
    //   818: ldc_w 317
    //   821: ldc_w 319
    //   824: invokevirtual 123	org/apache/http/client/methods/HttpPost:addHeader	(Ljava/lang/String;Ljava/lang/String;)V
    //   827: aload 10
    //   829: ldc_w 321
    //   832: ldc_w 323
    //   835: invokevirtual 123	org/apache/http/client/methods/HttpPost:addHeader	(Ljava/lang/String;Ljava/lang/String;)V
    //   838: goto -515 -> 323
    //   841: astore 5
    //   843: aload 5
    //   845: athrow
    //   846: iconst_0
    //   847: istore_1
    //   848: goto -493 -> 355
    //   851: lload_3
    //   852: lconst_0
    //   853: lcmp
    //   854: ifle +543 -> 1397
    //   857: aload 6
    //   859: invokeinterface 327 1 0
    //   864: astore 10
    //   866: new 329	java/io/DataInputStream
    //   869: dup
    //   870: aload 10
    //   872: invokespecial 332	java/io/DataInputStream:<init>	(Ljava/io/InputStream;)V
    //   875: astore 11
    //   877: aload 6
    //   879: invokeinterface 264 1 0
    //   884: l2i
    //   885: newarray <illegal type>
    //   887: astore 6
    //   889: aload 11
    //   891: aload 6
    //   893: invokevirtual 335	java/io/DataInputStream:readFully	([B)V
    //   896: aload 10
    //   898: invokevirtual 338	java/io/InputStream:close	()V
    //   901: aload 11
    //   903: invokevirtual 339	java/io/DataInputStream:close	()V
    //   906: aload 5
    //   908: ldc -105
    //   910: invokeinterface 343 2 0
    //   915: astore 11
    //   917: aload 6
    //   919: astore 5
    //   921: aload 11
    //   923: ifnull +29 -> 952
    //   926: aload 11
    //   928: invokeinterface 348 1 0
    //   933: ldc_w 350
    //   936: invokevirtual 353	java/lang/String:equalsIgnoreCase	(Ljava/lang/String;)Z
    //   939: ifeq +285 -> 1224
    //   942: aload 6
    //   944: invokestatic 356	com/tencent/wxop/stat/b/l:a	([B)[B
    //   947: invokestatic 358	com/tencent/wxop/stat/b/g:b	([B)[B
    //   950: astore 5
    //   952: new 73	java/lang/String
    //   955: dup
    //   956: aload 5
    //   958: ldc -78
    //   960: invokespecial 361	java/lang/String:<init>	([BLjava/lang/String;)V
    //   963: astore 6
    //   965: invokestatic 92	com/tencent/wxop/stat/b:bns	()Z
    //   968: ifeq +27 -> 995
    //   971: getstatic 96	com/tencent/wxop/stat/ai:man	Lcom/tencent/wxop/stat/b/b;
    //   974: new 49	java/lang/StringBuilder
    //   977: dup
    //   978: ldc_w 363
    //   981: invokespecial 99	java/lang/StringBuilder:<init>	(Ljava/lang/String;)V
    //   984: aload 6
    //   986: invokevirtual 62	java/lang/StringBuilder:append	(Ljava/lang/String;)Ljava/lang/StringBuilder;
    //   989: invokevirtual 71	java/lang/StringBuilder:toString	()Ljava/lang/String;
    //   992: invokevirtual 112	com/tencent/wxop/stat/b/b:aC	(Ljava/lang/Object;)V
    //   995: new 365	org/json/JSONObject
    //   998: dup
    //   999: aload 6
    //   1001: invokespecial 366	org/json/JSONObject:<init>	(Ljava/lang/String;)V
    //   1004: astore 6
    //   1006: iload_1
    //   1007: sipush 200
    //   1010: if_icmpne +329 -> 1339
    //   1013: aload 6
    //   1015: ldc_w 368
    //   1018: invokevirtual 372	org/json/JSONObject:optString	(Ljava/lang/String;)Ljava/lang/String;
    //   1021: astore 5
    //   1023: aload 5
    //   1025: invokestatic 377	com/tencent/a/a/a/a/h:c	(Ljava/lang/String;)Z
    //   1028: ifeq +44 -> 1072
    //   1031: invokestatic 92	com/tencent/wxop/stat/b:bns	()Z
    //   1034: ifeq +27 -> 1061
    //   1037: getstatic 96	com/tencent/wxop/stat/ai:man	Lcom/tencent/wxop/stat/b/b;
    //   1040: new 49	java/lang/StringBuilder
    //   1043: dup
    //   1044: ldc_w 379
    //   1047: invokespecial 99	java/lang/StringBuilder:<init>	(Ljava/lang/String;)V
    //   1050: aload 5
    //   1052: invokevirtual 62	java/lang/StringBuilder:append	(Ljava/lang/String;)Ljava/lang/StringBuilder;
    //   1055: invokevirtual 71	java/lang/StringBuilder:toString	()Ljava/lang/String;
    //   1058: invokevirtual 112	com/tencent/wxop/stat/b/b:aC	(Ljava/lang/Object;)V
    //   1061: getstatic 139	com/tencent/wxop/stat/ai:maQ	Landroid/content/Context;
    //   1064: invokestatic 385	com/tencent/a/a/a/a/g:O	(Landroid/content/Context;)Lcom/tencent/a/a/a/a/g;
    //   1067: aload 5
    //   1069: invokevirtual 387	com/tencent/a/a/a/a/g:a	(Ljava/lang/String;)V
    //   1072: aload 6
    //   1074: ldc_w 389
    //   1077: invokevirtual 392	org/json/JSONObject:isNull	(Ljava/lang/String;)Z
    //   1080: ifne +21 -> 1101
    //   1083: aload 6
    //   1085: ldc_w 389
    //   1088: invokevirtual 396	org/json/JSONObject:getJSONObject	(Ljava/lang/String;)Lorg/json/JSONObject;
    //   1091: astore 5
    //   1093: getstatic 139	com/tencent/wxop/stat/ai:maQ	Landroid/content/Context;
    //   1096: aload 5
    //   1098: invokestatic 399	com/tencent/wxop/stat/b:a	(Landroid/content/Context;Lorg/json/JSONObject;)V
    //   1101: aload 6
    //   1103: ldc_w 401
    //   1106: invokevirtual 392	org/json/JSONObject:isNull	(Ljava/lang/String;)Z
    //   1109: ifne +76 -> 1185
    //   1112: aload 6
    //   1114: ldc_w 401
    //   1117: invokevirtual 405	org/json/JSONObject:getInt	(Ljava/lang/String;)I
    //   1120: istore_1
    //   1121: iload_1
    //   1122: i2l
    //   1123: invokestatic 408	java/lang/System:currentTimeMillis	()J
    //   1126: ldc2_w 409
    //   1129: ldiv
    //   1130: lsub
    //   1131: l2i
    //   1132: istore_2
    //   1133: invokestatic 92	com/tencent/wxop/stat/b:bns	()Z
    //   1136: ifeq +36 -> 1172
    //   1139: getstatic 96	com/tencent/wxop/stat/ai:man	Lcom/tencent/wxop/stat/b/b;
    //   1142: new 49	java/lang/StringBuilder
    //   1145: dup
    //   1146: ldc_w 412
    //   1149: invokespecial 99	java/lang/StringBuilder:<init>	(Ljava/lang/String;)V
    //   1152: iload_1
    //   1153: invokevirtual 104	java/lang/StringBuilder:append	(I)Ljava/lang/StringBuilder;
    //   1156: ldc_w 414
    //   1159: invokevirtual 62	java/lang/StringBuilder:append	(Ljava/lang/String;)Ljava/lang/StringBuilder;
    //   1162: iload_2
    //   1163: invokevirtual 104	java/lang/StringBuilder:append	(I)Ljava/lang/StringBuilder;
    //   1166: invokevirtual 71	java/lang/StringBuilder:toString	()Ljava/lang/String;
    //   1169: invokevirtual 112	com/tencent/wxop/stat/b/b:aC	(Ljava/lang/Object;)V
    //   1172: getstatic 139	com/tencent/wxop/stat/ai:maQ	Landroid/content/Context;
    //   1175: invokestatic 418	com/tencent/wxop/stat/b/l:s	(Landroid/content/Context;)V
    //   1178: getstatic 139	com/tencent/wxop/stat/ai:maQ	Landroid/content/Context;
    //   1181: iload_2
    //   1182: invokestatic 422	com/tencent/wxop/stat/b/l:T	(Landroid/content/Context;I)V
    //   1185: aload 8
    //   1187: ifnull +21 -> 1208
    //   1190: aload 6
    //   1192: ldc_w 424
    //   1195: invokevirtual 427	org/json/JSONObject:optInt	(Ljava/lang/String;)I
    //   1198: ifne +122 -> 1320
    //   1201: aload 8
    //   1203: invokeinterface 429 1 0
    //   1208: aload 10
    //   1210: invokevirtual 338	java/io/InputStream:close	()V
    //   1213: aload 9
    //   1215: invokevirtual 430	java/io/ByteArrayOutputStream:close	()V
    //   1218: aconst_null
    //   1219: astore 5
    //   1221: goto -563 -> 658
    //   1224: aload 11
    //   1226: invokeinterface 348 1 0
    //   1231: ldc_w 432
    //   1234: invokevirtual 353	java/lang/String:equalsIgnoreCase	(Ljava/lang/String;)Z
    //   1237: ifeq +16 -> 1253
    //   1240: aload 6
    //   1242: invokestatic 358	com/tencent/wxop/stat/b/g:b	([B)[B
    //   1245: invokestatic 356	com/tencent/wxop/stat/b/l:a	([B)[B
    //   1248: astore 5
    //   1250: goto -298 -> 952
    //   1253: aload 11
    //   1255: invokeinterface 348 1 0
    //   1260: ldc 119
    //   1262: invokevirtual 353	java/lang/String:equalsIgnoreCase	(Ljava/lang/String;)Z
    //   1265: ifeq +13 -> 1278
    //   1268: aload 6
    //   1270: invokestatic 356	com/tencent/wxop/stat/b/l:a	([B)[B
    //   1273: astore 5
    //   1275: goto -323 -> 952
    //   1278: aload 6
    //   1280: astore 5
    //   1282: aload 11
    //   1284: invokeinterface 348 1 0
    //   1289: ldc -103
    //   1291: invokevirtual 353	java/lang/String:equalsIgnoreCase	(Ljava/lang/String;)Z
    //   1294: ifeq -342 -> 952
    //   1297: aload 6
    //   1299: invokestatic 358	com/tencent/wxop/stat/b/g:b	([B)[B
    //   1302: astore 5
    //   1304: goto -352 -> 952
    //   1307: astore 5
    //   1309: getstatic 96	com/tencent/wxop/stat/ai:man	Lcom/tencent/wxop/stat/b/b;
    //   1312: aload 5
    //   1314: invokevirtual 435	com/tencent/wxop/stat/b/b:aD	(Ljava/lang/Object;)V
    //   1317: goto -132 -> 1185
    //   1320: getstatic 96	com/tencent/wxop/stat/ai:man	Lcom/tencent/wxop/stat/b/b;
    //   1323: ldc_w 437
    //   1326: invokevirtual 440	com/tencent/wxop/stat/b/b:error	(Ljava/lang/Object;)V
    //   1329: aload 8
    //   1331: invokeinterface 278 1 0
    //   1336: goto -128 -> 1208
    //   1339: getstatic 96	com/tencent/wxop/stat/ai:man	Lcom/tencent/wxop/stat/b/b;
    //   1342: new 49	java/lang/StringBuilder
    //   1345: dup
    //   1346: ldc_w 442
    //   1349: invokespecial 99	java/lang/StringBuilder:<init>	(Ljava/lang/String;)V
    //   1352: iload_1
    //   1353: invokevirtual 104	java/lang/StringBuilder:append	(I)Ljava/lang/StringBuilder;
    //   1356: ldc_w 444
    //   1359: invokevirtual 62	java/lang/StringBuilder:append	(Ljava/lang/String;)Ljava/lang/StringBuilder;
    //   1362: new 73	java/lang/String
    //   1365: dup
    //   1366: aload 5
    //   1368: ldc -78
    //   1370: invokespecial 361	java/lang/String:<init>	([BLjava/lang/String;)V
    //   1373: invokevirtual 62	java/lang/StringBuilder:append	(Ljava/lang/String;)Ljava/lang/StringBuilder;
    //   1376: invokevirtual 71	java/lang/StringBuilder:toString	()Ljava/lang/String;
    //   1379: invokevirtual 440	com/tencent/wxop/stat/b/b:error	(Ljava/lang/Object;)V
    //   1382: aload 8
    //   1384: ifnull -176 -> 1208
    //   1387: aload 8
    //   1389: invokeinterface 278 1 0
    //   1394: goto -186 -> 1208
    //   1397: aload 6
    //   1399: invokestatic 283	org/apache/http/util/EntityUtils:toString	(Lorg/apache/http/HttpEntity;)Ljava/lang/String;
    //   1402: pop
    //   1403: goto -190 -> 1213
    //   1406: astore 6
    //   1408: getstatic 96	com/tencent/wxop/stat/ai:man	Lcom/tencent/wxop/stat/b/b;
    //   1411: aload 6
    //   1413: invokevirtual 448	com/tencent/wxop/stat/b/b:d	(Ljava/lang/Throwable;)V
    //   1416: goto -735 -> 681
    //   1419: iload_1
    //   1420: iconst_1
    //   1421: iadd
    //   1422: istore_1
    //   1423: goto -1341 -> 82
    // Local variable table:
    //   start	length	slot	name	signature
    //   0	1426	0	this	ak
    //   81	1342	1	i	int
    //   41	1141	2	j	int
    //   582	270	3	l	long
    //   10	553	5	localObject1	Object
    //   656	26	5	localThrowable1	Throwable
    //   719	12	5	localf	f
    //   841	66	5	localObject2	Object
    //   919	384	5	localObject3	Object
    //   1307	60	5	localThrowable2	Throwable
    //   184	1214	6	localObject4	Object
    //   1406	6	6	localThrowable3	Throwable
    //   4	784	7	localai	ai
    //   16	1372	8	localah	ah
    //   331	883	9	localByteArrayOutputStream	java.io.ByteArrayOutputStream
    //   255	954	10	localObject5	Object
    //   291	992	11	localObject6	Object
    // Exception table:
    //   from	to	target	type
    //   51	80	656	java/lang/Throwable
    //   87	107	656	java/lang/Throwable
    //   114	125	656	java/lang/Throwable
    //   128	246	656	java/lang/Throwable
    //   246	302	656	java/lang/Throwable
    //   307	323	656	java/lang/Throwable
    //   323	353	656	java/lang/Throwable
    //   363	401	656	java/lang/Throwable
    //   406	422	656	java/lang/Throwable
    //   422	472	656	java/lang/Throwable
    //   476	520	656	java/lang/Throwable
    //   524	622	656	java/lang/Throwable
    //   628	637	656	java/lang/Throwable
    //   642	649	656	java/lang/Throwable
    //   649	655	656	java/lang/Throwable
    //   745	778	656	java/lang/Throwable
    //   778	838	656	java/lang/Throwable
    //   857	917	656	java/lang/Throwable
    //   926	952	656	java/lang/Throwable
    //   952	995	656	java/lang/Throwable
    //   995	1006	656	java/lang/Throwable
    //   1190	1208	656	java/lang/Throwable
    //   1208	1213	656	java/lang/Throwable
    //   1213	1218	656	java/lang/Throwable
    //   1224	1250	656	java/lang/Throwable
    //   1253	1275	656	java/lang/Throwable
    //   1282	1304	656	java/lang/Throwable
    //   1309	1317	656	java/lang/Throwable
    //   1320	1336	656	java/lang/Throwable
    //   1339	1382	656	java/lang/Throwable
    //   1387	1394	656	java/lang/Throwable
    //   1397	1403	656	java/lang/Throwable
    //   51	80	841	finally
    //   87	107	841	finally
    //   114	125	841	finally
    //   128	246	841	finally
    //   246	302	841	finally
    //   307	323	841	finally
    //   323	353	841	finally
    //   363	401	841	finally
    //   406	422	841	finally
    //   422	472	841	finally
    //   476	520	841	finally
    //   524	622	841	finally
    //   628	637	841	finally
    //   642	649	841	finally
    //   649	655	841	finally
    //   745	778	841	finally
    //   778	838	841	finally
    //   857	917	841	finally
    //   926	952	841	finally
    //   952	995	841	finally
    //   995	1006	841	finally
    //   1013	1061	841	finally
    //   1061	1072	841	finally
    //   1072	1101	841	finally
    //   1101	1172	841	finally
    //   1172	1185	841	finally
    //   1190	1208	841	finally
    //   1208	1213	841	finally
    //   1213	1218	841	finally
    //   1224	1250	841	finally
    //   1253	1275	841	finally
    //   1282	1304	841	finally
    //   1309	1317	841	finally
    //   1320	1336	841	finally
    //   1339	1382	841	finally
    //   1387	1394	841	finally
    //   1397	1403	841	finally
    //   1013	1061	1307	java/lang/Throwable
    //   1061	1072	1307	java/lang/Throwable
    //   1072	1101	1307	java/lang/Throwable
    //   1101	1172	1307	java/lang/Throwable
    //   1172	1185	1307	java/lang/Throwable
    //   674	681	1406	java/lang/Throwable
  }
}

/* Location:
 * Qualified Name:     com.tencent.wxop.stat.ak
 * Java Class Version: 6 (50.0)
 * JD-Core Version:    0.7.1
 */