package com.tencent.mm.y.a.f;

import android.graphics.Bitmap;
import com.tencent.mm.sdk.platformtools.ac;
import com.tencent.mm.sdk.platformtools.bn;
import com.tencent.mm.sdk.platformtools.t;
import com.tencent.mm.y.a.c.d;
import com.tencent.mm.y.a.c.f;
import com.tencent.mm.y.a.c.g;
import com.tencent.mm.y.a.c.h;
import com.tencent.mm.y.a.c.i;

public final class a
  implements Runnable
{
  private final com.tencent.mm.y.a.a.b bEJ;
  public final com.tencent.mm.y.a.a.c bEZ;
  private final com.tencent.mm.y.a.c bFL;
  private final ac bFM;
  private final com.tencent.mm.y.a.b bFN;
  private final f bFO;
  private final d bFP;
  private final h bFQ;
  private final i bFa;
  private final com.tencent.mm.y.a.c.a bFb;
  private final com.tencent.mm.y.a.c.b bFc;
  private final com.tencent.mm.y.a.c.c bFd;
  private final g bFe;
  private final String url;
  
  public a(String paramString, com.tencent.mm.y.a.c paramc, ac paramac, com.tencent.mm.y.a.a.c paramc1, f paramf, g paramg, com.tencent.mm.y.a.b paramb, d paramd)
  {
    url = paramString;
    bFL = paramc;
    bFM = paramac;
    bFN = paramb;
    bFP = paramd;
    bEJ = bFN.bEJ;
    if (paramc1 == null)
    {
      bEZ = bEJ.bEZ;
      bFO = paramf;
      if (paramg != null) {
        break label155;
      }
      bFe = bEJ.bFe;
      label80:
      if (bEZ.bFc == null) {
        break label164;
      }
    }
    label155:
    label164:
    for (bFc = bEZ.bFc;; bFc = bEJ.bFc)
    {
      bFa = bEJ.bFa;
      bFb = bEJ.bFb;
      bFd = bEJ.bFd;
      bFQ = bEJ.bFf;
      return;
      bEZ = paramc1;
      break;
      bFe = paramg;
      break label80;
    }
  }
  
  private void h(String paramString, Bitmap paramBitmap)
  {
    if (bEZ.bFj)
    {
      t.d("!56@/B4Tb64lLpJ3W0chKRkeCOp5DLdC+H/lc8CsH5NwjcaElRJ+MR/qDA==", "[cpan] run. put key %s to memory cache.", new Object[] { url });
      bFa.g(paramString, paramBitmap);
    }
  }
  
  public final void P(long paramLong)
  {
    if (bFe != null) {
      bFe.P(paramLong);
    }
  }
  
  public final String gZ(String paramString)
  {
    if ((bn.iW(paramString)) || (bEZ == null)) {
      return null;
    }
    String str = paramString;
    if (bEZ.bFC) {
      str = paramString + "round" + bEZ.bFD;
    }
    return str + "size" + bEZ.bFr + bEZ.bFs;
  }
  
  /* Error */
  public final void run()
  {
    // Byte code:
    //   0: aconst_null
    //   1: astore 11
    //   3: new 162	com/tencent/mm/y/a/d/b
    //   6: dup
    //   7: invokespecial 163	com/tencent/mm/y/a/d/b:<init>	()V
    //   10: astore 10
    //   12: aload_0
    //   13: aload_0
    //   14: getfield 41	com/tencent/mm/y/a/f/a:url	Ljava/lang/String;
    //   17: invokevirtual 165	com/tencent/mm/y/a/f/a:gZ	(Ljava/lang/String;)Ljava/lang/String;
    //   20: astore 14
    //   22: ldc 93
    //   24: ldc -89
    //   26: iconst_1
    //   27: anewarray 4	java/lang/Object
    //   30: dup
    //   31: iconst_0
    //   32: aload_0
    //   33: getfield 41	com/tencent/mm/y/a/f/a:url	Ljava/lang/String;
    //   36: aastore
    //   37: invokestatic 101	com/tencent/mm/sdk/platformtools/t:d	(Ljava/lang/String;Ljava/lang/String;[Ljava/lang/Object;)V
    //   40: invokestatic 173	java/lang/System:currentTimeMillis	()J
    //   43: lstore 4
    //   45: aload_0
    //   46: getfield 59	com/tencent/mm/y/a/f/a:bEZ	Lcom/tencent/mm/y/a/a/c;
    //   49: getfield 176	com/tencent/mm/y/a/a/c:bFq	I
    //   52: istore_2
    //   53: aload_0
    //   54: getfield 59	com/tencent/mm/y/a/f/a:bEZ	Lcom/tencent/mm/y/a/a/c;
    //   57: getfield 179	com/tencent/mm/y/a/a/c:bFt	Z
    //   60: istore 8
    //   62: aload_0
    //   63: getfield 59	com/tencent/mm/y/a/f/a:bEZ	Lcom/tencent/mm/y/a/a/c;
    //   66: getfield 182	com/tencent/mm/y/a/a/c:avf	Ljava/lang/String;
    //   69: astore 15
    //   71: ldc 93
    //   73: new 125	java/lang/StringBuilder
    //   76: dup
    //   77: ldc -72
    //   79: invokespecial 187	java/lang/StringBuilder:<init>	(Ljava/lang/String;)V
    //   82: iload 8
    //   84: invokevirtual 190	java/lang/StringBuilder:append	(Z)Ljava/lang/StringBuilder;
    //   87: invokevirtual 143	java/lang/StringBuilder:toString	()Ljava/lang/String;
    //   90: invokestatic 193	com/tencent/mm/sdk/platformtools/t:d	(Ljava/lang/String;Ljava/lang/String;)V
    //   93: ldc 93
    //   95: ldc -61
    //   97: iconst_1
    //   98: anewarray 4	java/lang/Object
    //   101: dup
    //   102: iconst_0
    //   103: iload_2
    //   104: invokestatic 201	java/lang/Integer:valueOf	(I)Ljava/lang/Integer;
    //   107: aastore
    //   108: invokestatic 101	com/tencent/mm/sdk/platformtools/t:d	(Ljava/lang/String;Ljava/lang/String;[Ljava/lang/Object;)V
    //   111: ldc 93
    //   113: ldc -53
    //   115: iconst_2
    //   116: anewarray 4	java/lang/Object
    //   119: dup
    //   120: iconst_0
    //   121: aload_0
    //   122: getfield 43	com/tencent/mm/y/a/f/a:bFL	Lcom/tencent/mm/y/a/c;
    //   125: getfield 208	com/tencent/mm/y/a/c:width	I
    //   128: invokestatic 201	java/lang/Integer:valueOf	(I)Ljava/lang/Integer;
    //   131: aastore
    //   132: dup
    //   133: iconst_1
    //   134: aload_0
    //   135: getfield 43	com/tencent/mm/y/a/f/a:bFL	Lcom/tencent/mm/y/a/c;
    //   138: getfield 211	com/tencent/mm/y/a/c:height	I
    //   141: invokestatic 201	java/lang/Integer:valueOf	(I)Ljava/lang/Integer;
    //   144: aastore
    //   145: invokestatic 101	com/tencent/mm/sdk/platformtools/t:d	(Ljava/lang/String;Ljava/lang/String;[Ljava/lang/Object;)V
    //   148: aload 11
    //   150: astore 9
    //   152: iload_2
    //   153: tableswitch	default:+1790->1943, 1:+243->396, 2:+762->915, 3:+792->945, 4:+844->997, 5:+405->558
    //   188: ldc 93
    //   190: ldc -43
    //   192: iconst_1
    //   193: anewarray 4	java/lang/Object
    //   196: dup
    //   197: iconst_0
    //   198: iload_2
    //   199: invokestatic 201	java/lang/Integer:valueOf	(I)Ljava/lang/Integer;
    //   202: aastore
    //   203: invokestatic 216	com/tencent/mm/sdk/platformtools/t:e	(Ljava/lang/String;Ljava/lang/String;[Ljava/lang/Object;)V
    //   206: aconst_null
    //   207: astore 9
    //   209: invokestatic 173	java/lang/System:currentTimeMillis	()J
    //   212: lstore 6
    //   214: aload 9
    //   216: ifnull +1730 -> 1946
    //   219: aload 9
    //   221: invokevirtual 222	android/graphics/Bitmap:isRecycled	()Z
    //   224: ifeq +1473 -> 1697
    //   227: goto +1719 -> 1946
    //   230: ldc 93
    //   232: ldc -32
    //   234: invokestatic 227	com/tencent/mm/sdk/platformtools/t:w	(Ljava/lang/String;Ljava/lang/String;)V
    //   237: aload 9
    //   239: ifnull +1645 -> 1884
    //   242: aload 9
    //   244: invokevirtual 222	android/graphics/Bitmap:isRecycled	()Z
    //   247: ifne +1637 -> 1884
    //   250: ldc 93
    //   252: ldc -27
    //   254: invokestatic 193	com/tencent/mm/sdk/platformtools/t:d	(Ljava/lang/String;Ljava/lang/String;)V
    //   257: new 231	com/tencent/mm/y/a/f/b
    //   260: dup
    //   261: aload_0
    //   262: getfield 41	com/tencent/mm/y/a/f/a:url	Ljava/lang/String;
    //   265: aload_0
    //   266: getfield 43	com/tencent/mm/y/a/f/a:bFL	Lcom/tencent/mm/y/a/c;
    //   269: aload 9
    //   271: aload_0
    //   272: getfield 47	com/tencent/mm/y/a/f/a:bFN	Lcom/tencent/mm/y/a/b;
    //   275: aload_0
    //   276: aload_0
    //   277: getfield 41	com/tencent/mm/y/a/f/a:url	Ljava/lang/String;
    //   280: invokevirtual 165	com/tencent/mm/y/a/f/a:gZ	(Ljava/lang/String;)Ljava/lang/String;
    //   283: invokespecial 234	com/tencent/mm/y/a/f/b:<init>	(Ljava/lang/String;Lcom/tencent/mm/y/a/c;Landroid/graphics/Bitmap;Lcom/tencent/mm/y/a/b;Ljava/lang/String;)V
    //   286: astore 11
    //   288: aload_0
    //   289: getfield 45	com/tencent/mm/y/a/f/a:bFM	Lcom/tencent/mm/sdk/platformtools/ac;
    //   292: ifnull +13 -> 305
    //   295: aload_0
    //   296: getfield 45	com/tencent/mm/y/a/f/a:bFM	Lcom/tencent/mm/sdk/platformtools/ac;
    //   299: aload 11
    //   301: invokevirtual 240	com/tencent/mm/sdk/platformtools/ac:post	(Ljava/lang/Runnable;)Z
    //   304: pop
    //   305: aload_0
    //   306: getfield 49	com/tencent/mm/y/a/f/a:bFP	Lcom/tencent/mm/y/a/c/d;
    //   309: ifnull +48 -> 357
    //   312: aload 10
    //   314: ifnull +43 -> 357
    //   317: aload 10
    //   319: getfield 243	com/tencent/mm/y/a/d/b:status	I
    //   322: iconst_m1
    //   323: if_icmpeq +34 -> 357
    //   326: aload_0
    //   327: getfield 49	com/tencent/mm/y/a/f/a:bFP	Lcom/tencent/mm/y/a/c/d;
    //   330: astore 11
    //   332: aload_0
    //   333: getfield 41	com/tencent/mm/y/a/f/a:url	Ljava/lang/String;
    //   336: astore 12
    //   338: aload_0
    //   339: getfield 43	com/tencent/mm/y/a/f/a:bFL	Lcom/tencent/mm/y/a/c;
    //   342: invokevirtual 247	com/tencent/mm/y/a/c:getImageView	()Landroid/widget/ImageView;
    //   345: pop
    //   346: aload 11
    //   348: aload 12
    //   350: aload 10
    //   352: invokeinterface 253 3 0
    //   357: aload_0
    //   358: getfield 61	com/tencent/mm/y/a/f/a:bFO	Lcom/tencent/mm/y/a/c/f;
    //   361: astore 10
    //   363: aload_0
    //   364: getfield 41	com/tencent/mm/y/a/f/a:url	Ljava/lang/String;
    //   367: astore 11
    //   369: aload_0
    //   370: getfield 43	com/tencent/mm/y/a/f/a:bFL	Lcom/tencent/mm/y/a/c;
    //   373: invokevirtual 247	com/tencent/mm/y/a/c:getImageView	()Landroid/widget/ImageView;
    //   376: pop
    //   377: aload 10
    //   379: aload 11
    //   381: aload 9
    //   383: aload_0
    //   384: getfield 59	com/tencent/mm/y/a/f/a:bEZ	Lcom/tencent/mm/y/a/a/c;
    //   387: getfield 257	com/tencent/mm/y/a/a/c:bFE	[Ljava/lang/Object;
    //   390: invokeinterface 262 4 0
    //   395: return
    //   396: aload_0
    //   397: getfield 41	com/tencent/mm/y/a/f/a:url	Ljava/lang/String;
    //   400: invokestatic 120	com/tencent/mm/sdk/platformtools/bn:iW	(Ljava/lang/String;)Z
    //   403: ifne +390 -> 793
    //   406: aload 11
    //   408: astore 9
    //   410: aload_0
    //   411: getfield 41	com/tencent/mm/y/a/f/a:url	Ljava/lang/String;
    //   414: invokestatic 267	com/tencent/mm/a/c:az	(Ljava/lang/String;)Z
    //   417: ifeq +141 -> 558
    //   420: iload 8
    //   422: ifeq +21 -> 443
    //   425: aload_0
    //   426: getfield 83	com/tencent/mm/y/a/f/a:bFQ	Lcom/tencent/mm/y/a/c/h;
    //   429: aload 15
    //   431: aload_0
    //   432: getfield 41	com/tencent/mm/y/a/f/a:url	Ljava/lang/String;
    //   435: invokeinterface 273 3 0
    //   440: ifeq +339 -> 779
    //   443: aload_0
    //   444: getfield 43	com/tencent/mm/y/a/f/a:bFL	Lcom/tencent/mm/y/a/c;
    //   447: astore 9
    //   449: aload_0
    //   450: getfield 41	com/tencent/mm/y/a/f/a:url	Ljava/lang/String;
    //   453: astore 11
    //   455: aload_0
    //   456: getfield 59	com/tencent/mm/y/a/f/a:bEZ	Lcom/tencent/mm/y/a/a/c;
    //   459: getfield 149	com/tencent/mm/y/a/a/c:bFr	I
    //   462: istore_1
    //   463: aload_0
    //   464: getfield 59	com/tencent/mm/y/a/f/a:bEZ	Lcom/tencent/mm/y/a/a/c;
    //   467: getfield 155	com/tencent/mm/y/a/a/c:bFs	I
    //   470: istore_3
    //   471: iload_1
    //   472: ifle +7 -> 479
    //   475: iload_3
    //   476: ifgt +291 -> 767
    //   479: aload 9
    //   481: ifnull +276 -> 757
    //   484: aload 9
    //   486: getfield 208	com/tencent/mm/y/a/c:width	I
    //   489: ifle +268 -> 757
    //   492: aload 9
    //   494: getfield 208	com/tencent/mm/y/a/c:width	I
    //   497: ifle +260 -> 757
    //   500: aload 11
    //   502: aload 9
    //   504: getfield 208	com/tencent/mm/y/a/c:width	I
    //   507: aload 9
    //   509: getfield 211	com/tencent/mm/y/a/c:height	I
    //   512: invokestatic 279	com/tencent/mm/sdk/platformtools/e:q	(Ljava/lang/String;II)Landroid/graphics/Bitmap;
    //   515: astore 9
    //   517: aload 9
    //   519: astore 11
    //   521: ldc 93
    //   523: ldc_w 281
    //   526: invokestatic 193	com/tencent/mm/sdk/platformtools/t:d	(Ljava/lang/String;Ljava/lang/String;)V
    //   529: aload 9
    //   531: astore 11
    //   533: aload 11
    //   535: astore 9
    //   537: aload 11
    //   539: ifnonnull +19 -> 558
    //   542: aload 11
    //   544: astore 12
    //   546: aload_0
    //   547: getfield 41	com/tencent/mm/y/a/f/a:url	Ljava/lang/String;
    //   550: invokestatic 284	com/tencent/mm/a/c:deleteFile	(Ljava/lang/String;)Z
    //   553: pop
    //   554: aload 11
    //   556: astore 9
    //   558: aconst_null
    //   559: astore 11
    //   561: aload_0
    //   562: getfield 75	com/tencent/mm/y/a/f/a:bFb	Lcom/tencent/mm/y/a/c/a;
    //   565: aload_0
    //   566: getfield 41	com/tencent/mm/y/a/f/a:url	Ljava/lang/String;
    //   569: aload_0
    //   570: getfield 59	com/tencent/mm/y/a/f/a:bEZ	Lcom/tencent/mm/y/a/a/c;
    //   573: invokeinterface 289 3 0
    //   578: astore 12
    //   580: aload 12
    //   582: ifnull +1356 -> 1938
    //   585: iload 8
    //   587: ifeq +23 -> 610
    //   590: aload 12
    //   592: astore 11
    //   594: aload_0
    //   595: getfield 83	com/tencent/mm/y/a/f/a:bFQ	Lcom/tencent/mm/y/a/c/h;
    //   598: aload 15
    //   600: aload 12
    //   602: invokeinterface 292 3 0
    //   607: ifeq +268 -> 875
    //   610: aload 12
    //   612: astore 11
    //   614: aload_0
    //   615: getfield 43	com/tencent/mm/y/a/f/a:bFL	Lcom/tencent/mm/y/a/c;
    //   618: astore 13
    //   620: aload 12
    //   622: astore 11
    //   624: aload_0
    //   625: getfield 59	com/tencent/mm/y/a/f/a:bEZ	Lcom/tencent/mm/y/a/a/c;
    //   628: getfield 149	com/tencent/mm/y/a/a/c:bFr	I
    //   631: istore_1
    //   632: aload 12
    //   634: astore 11
    //   636: aload_0
    //   637: getfield 59	com/tencent/mm/y/a/f/a:bEZ	Lcom/tencent/mm/y/a/a/c;
    //   640: getfield 155	com/tencent/mm/y/a/a/c:bFs	I
    //   643: istore_3
    //   644: iload_1
    //   645: ifle +7 -> 652
    //   648: iload_3
    //   649: ifgt +205 -> 854
    //   652: aload 13
    //   654: ifnull +182 -> 836
    //   657: aload 12
    //   659: astore 11
    //   661: aload 13
    //   663: getfield 208	com/tencent/mm/y/a/c:width	I
    //   666: ifle +170 -> 836
    //   669: aload 12
    //   671: astore 11
    //   673: aload 13
    //   675: getfield 208	com/tencent/mm/y/a/c:width	I
    //   678: ifle +158 -> 836
    //   681: aload 12
    //   683: astore 11
    //   685: aload 12
    //   687: fconst_0
    //   688: aload 13
    //   690: getfield 208	com/tencent/mm/y/a/c:width	I
    //   693: aload 13
    //   695: getfield 211	com/tencent/mm/y/a/c:height	I
    //   698: invokestatic 295	com/tencent/mm/sdk/platformtools/e:a	(Ljava/io/InputStream;FII)Landroid/graphics/Bitmap;
    //   701: astore 13
    //   703: aload 13
    //   705: astore 9
    //   707: iconst_1
    //   708: istore_1
    //   709: aload 12
    //   711: ifnull +12 -> 723
    //   714: aload 9
    //   716: astore 11
    //   718: aload 12
    //   720: invokevirtual 300	java/io/InputStream:close	()V
    //   723: iload_1
    //   724: ifeq +1211 -> 1935
    //   727: aload 9
    //   729: ifnonnull +1206 -> 1935
    //   732: aload 9
    //   734: astore 11
    //   736: aload_0
    //   737: getfield 75	com/tencent/mm/y/a/f/a:bFb	Lcom/tencent/mm/y/a/c/a;
    //   740: aload_0
    //   741: getfield 41	com/tencent/mm/y/a/f/a:url	Ljava/lang/String;
    //   744: aload_0
    //   745: getfield 59	com/tencent/mm/y/a/f/a:bEZ	Lcom/tencent/mm/y/a/a/c;
    //   748: invokeinterface 304 3 0
    //   753: pop
    //   754: goto -545 -> 209
    //   757: aload 11
    //   759: invokestatic 308	com/tencent/mm/sdk/platformtools/e:xf	(Ljava/lang/String;)Landroid/graphics/Bitmap;
    //   762: astore 9
    //   764: goto -247 -> 517
    //   767: aload 11
    //   769: iload_1
    //   770: iload_3
    //   771: invokestatic 279	com/tencent/mm/sdk/platformtools/e:q	(Ljava/lang/String;II)Landroid/graphics/Bitmap;
    //   774: astore 9
    //   776: goto -259 -> 517
    //   779: ldc 93
    //   781: ldc_w 310
    //   784: invokestatic 227	com/tencent/mm/sdk/platformtools/t:w	(Ljava/lang/String;Ljava/lang/String;)V
    //   787: aconst_null
    //   788: astore 11
    //   790: goto -257 -> 533
    //   793: ldc 93
    //   795: ldc_w 312
    //   798: invokestatic 227	com/tencent/mm/sdk/platformtools/t:w	(Ljava/lang/String;Ljava/lang/String;)V
    //   801: aload 11
    //   803: astore 9
    //   805: goto -247 -> 558
    //   808: astore 11
    //   810: aconst_null
    //   811: astore 9
    //   813: ldc 93
    //   815: ldc_w 314
    //   818: iconst_1
    //   819: anewarray 4	java/lang/Object
    //   822: dup
    //   823: iconst_0
    //   824: aload 11
    //   826: invokevirtual 315	java/lang/Exception:toString	()Ljava/lang/String;
    //   829: aastore
    //   830: invokestatic 216	com/tencent/mm/sdk/platformtools/t:e	(Ljava/lang/String;Ljava/lang/String;[Ljava/lang/Object;)V
    //   833: goto -596 -> 237
    //   836: aload 12
    //   838: astore 11
    //   840: aload 12
    //   842: invokestatic 319	com/tencent/mm/sdk/platformtools/e:decodeStream	(Ljava/io/InputStream;)Landroid/graphics/Bitmap;
    //   845: astore 13
    //   847: aload 13
    //   849: astore 9
    //   851: goto -144 -> 707
    //   854: aload 12
    //   856: astore 11
    //   858: aload 12
    //   860: fconst_0
    //   861: iload_1
    //   862: iload_3
    //   863: invokestatic 295	com/tencent/mm/sdk/platformtools/e:a	(Ljava/io/InputStream;FII)Landroid/graphics/Bitmap;
    //   866: astore 13
    //   868: aload 13
    //   870: astore 9
    //   872: goto -165 -> 707
    //   875: iconst_1
    //   876: istore_1
    //   877: aconst_null
    //   878: astore 9
    //   880: goto -171 -> 709
    //   883: astore 13
    //   885: aload 11
    //   887: ifnull +12 -> 899
    //   890: aload 9
    //   892: astore 12
    //   894: aload 11
    //   896: invokevirtual 300	java/io/InputStream:close	()V
    //   899: aload 9
    //   901: astore 12
    //   903: aload 13
    //   905: athrow
    //   906: astore 11
    //   908: aload 12
    //   910: astore 9
    //   912: goto -99 -> 813
    //   915: aload_0
    //   916: getfield 43	com/tencent/mm/y/a/f/a:bFL	Lcom/tencent/mm/y/a/c;
    //   919: aload_0
    //   920: getfield 41	com/tencent/mm/y/a/f/a:url	Ljava/lang/String;
    //   923: aload_0
    //   924: getfield 59	com/tencent/mm/y/a/f/a:bEZ	Lcom/tencent/mm/y/a/a/c;
    //   927: getfield 149	com/tencent/mm/y/a/a/c:bFr	I
    //   930: aload_0
    //   931: getfield 59	com/tencent/mm/y/a/f/a:bEZ	Lcom/tencent/mm/y/a/a/c;
    //   934: getfield 155	com/tencent/mm/y/a/a/c:bFs	I
    //   937: invokestatic 324	com/tencent/mm/y/a/g/a:a	(Lcom/tencent/mm/y/a/c;Ljava/lang/String;II)Landroid/graphics/Bitmap;
    //   940: astore 9
    //   942: goto -733 -> 209
    //   945: aload_0
    //   946: getfield 54	com/tencent/mm/y/a/f/a:bEJ	Lcom/tencent/mm/y/a/a/b;
    //   949: getfield 328	com/tencent/mm/y/a/a/b:bEW	Landroid/content/res/Resources;
    //   952: aload_0
    //   953: getfield 41	com/tencent/mm/y/a/f/a:url	Ljava/lang/String;
    //   956: ldc_w 330
    //   959: aload_0
    //   960: getfield 54	com/tencent/mm/y/a/f/a:bEJ	Lcom/tencent/mm/y/a/a/b;
    //   963: getfield 333	com/tencent/mm/y/a/a/b:packageName	Ljava/lang/String;
    //   966: invokevirtual 339	android/content/res/Resources:getIdentifier	(Ljava/lang/String;Ljava/lang/String;Ljava/lang/String;)I
    //   969: istore_1
    //   970: aload_0
    //   971: getfield 43	com/tencent/mm/y/a/f/a:bFL	Lcom/tencent/mm/y/a/c;
    //   974: iload_1
    //   975: aload_0
    //   976: getfield 59	com/tencent/mm/y/a/f/a:bEZ	Lcom/tencent/mm/y/a/a/c;
    //   979: getfield 149	com/tencent/mm/y/a/a/c:bFr	I
    //   982: aload_0
    //   983: getfield 59	com/tencent/mm/y/a/f/a:bEZ	Lcom/tencent/mm/y/a/a/c;
    //   986: getfield 155	com/tencent/mm/y/a/a/c:bFs	I
    //   989: invokestatic 342	com/tencent/mm/y/a/g/a:a	(Lcom/tencent/mm/y/a/c;III)Landroid/graphics/Bitmap;
    //   992: astore 9
    //   994: goto -785 -> 209
    //   997: aload_0
    //   998: getfield 41	com/tencent/mm/y/a/f/a:url	Ljava/lang/String;
    //   1001: invokestatic 345	java/lang/Integer:valueOf	(Ljava/lang/String;)Ljava/lang/Integer;
    //   1004: invokevirtual 349	java/lang/Integer:intValue	()I
    //   1007: istore_1
    //   1008: aload_0
    //   1009: getfield 43	com/tencent/mm/y/a/f/a:bFL	Lcom/tencent/mm/y/a/c;
    //   1012: iload_1
    //   1013: aload_0
    //   1014: getfield 59	com/tencent/mm/y/a/f/a:bEZ	Lcom/tencent/mm/y/a/a/c;
    //   1017: getfield 149	com/tencent/mm/y/a/a/c:bFr	I
    //   1020: aload_0
    //   1021: getfield 59	com/tencent/mm/y/a/f/a:bEZ	Lcom/tencent/mm/y/a/a/c;
    //   1024: getfield 155	com/tencent/mm/y/a/a/c:bFs	I
    //   1027: invokestatic 342	com/tencent/mm/y/a/g/a:a	(Lcom/tencent/mm/y/a/c;III)Landroid/graphics/Bitmap;
    //   1030: astore 9
    //   1032: goto -823 -> 209
    //   1035: invokestatic 173	java/lang/System:currentTimeMillis	()J
    //   1038: lstore 4
    //   1040: ldc 93
    //   1042: ldc_w 351
    //   1045: invokestatic 193	com/tencent/mm/sdk/platformtools/t:d	(Ljava/lang/String;Ljava/lang/String;)V
    //   1048: aload_0
    //   1049: getfield 49	com/tencent/mm/y/a/f/a:bFP	Lcom/tencent/mm/y/a/c/d;
    //   1052: ifnull +32 -> 1084
    //   1055: aload_0
    //   1056: getfield 49	com/tencent/mm/y/a/f/a:bFP	Lcom/tencent/mm/y/a/c/d;
    //   1059: astore 11
    //   1061: aload_0
    //   1062: getfield 41	com/tencent/mm/y/a/f/a:url	Ljava/lang/String;
    //   1065: astore 12
    //   1067: aload_0
    //   1068: getfield 43	com/tencent/mm/y/a/f/a:bFL	Lcom/tencent/mm/y/a/c;
    //   1071: invokevirtual 247	com/tencent/mm/y/a/c:getImageView	()Landroid/widget/ImageView;
    //   1074: pop
    //   1075: aload 11
    //   1077: aload 12
    //   1079: invokeinterface 354 2 0
    //   1084: aload_0
    //   1085: getfield 69	com/tencent/mm/y/a/f/a:bFc	Lcom/tencent/mm/y/a/c/b;
    //   1088: aload_0
    //   1089: getfield 41	com/tencent/mm/y/a/f/a:url	Ljava/lang/String;
    //   1092: invokeinterface 360 2 0
    //   1097: astore 11
    //   1099: aload 11
    //   1101: astore 10
    //   1103: aload 9
    //   1105: astore 12
    //   1107: aload 10
    //   1109: getfield 364	com/tencent/mm/y/a/d/b:data	[B
    //   1112: ifnonnull +16 -> 1128
    //   1115: aload 9
    //   1117: astore 12
    //   1119: aload 10
    //   1121: iconst_1
    //   1122: putfield 243	com/tencent/mm/y/a/d/b:status	I
    //   1125: goto -888 -> 237
    //   1128: iload 8
    //   1130: ifeq +26 -> 1156
    //   1133: aload 9
    //   1135: astore 12
    //   1137: aload_0
    //   1138: getfield 83	com/tencent/mm/y/a/f/a:bFQ	Lcom/tencent/mm/y/a/c/h;
    //   1141: aload 15
    //   1143: aload 10
    //   1145: getfield 364	com/tencent/mm/y/a/d/b:data	[B
    //   1148: invokeinterface 367 3 0
    //   1153: ifeq +505 -> 1658
    //   1156: aload 9
    //   1158: astore 12
    //   1160: ldc 93
    //   1162: ldc_w 369
    //   1165: invokestatic 193	com/tencent/mm/sdk/platformtools/t:d	(Ljava/lang/String;Ljava/lang/String;)V
    //   1168: aload 9
    //   1170: astore 12
    //   1172: invokestatic 173	java/lang/System:currentTimeMillis	()J
    //   1175: lstore 6
    //   1177: aload 9
    //   1179: astore 12
    //   1181: aload_0
    //   1182: getfield 43	com/tencent/mm/y/a/f/a:bFL	Lcom/tencent/mm/y/a/c;
    //   1185: astore 11
    //   1187: aload 9
    //   1189: astore 12
    //   1191: aload 10
    //   1193: getfield 364	com/tencent/mm/y/a/d/b:data	[B
    //   1196: astore 13
    //   1198: aload 9
    //   1200: astore 12
    //   1202: aload_0
    //   1203: getfield 59	com/tencent/mm/y/a/f/a:bEZ	Lcom/tencent/mm/y/a/a/c;
    //   1206: getfield 149	com/tencent/mm/y/a/a/c:bFr	I
    //   1209: istore_1
    //   1210: aload 9
    //   1212: astore 12
    //   1214: aload_0
    //   1215: getfield 59	com/tencent/mm/y/a/f/a:bEZ	Lcom/tencent/mm/y/a/a/c;
    //   1218: getfield 155	com/tencent/mm/y/a/a/c:bFs	I
    //   1221: istore_2
    //   1222: iload_1
    //   1223: ifle +7 -> 1230
    //   1226: iload_2
    //   1227: ifgt +85 -> 1312
    //   1230: aload 11
    //   1232: ifnull +66 -> 1298
    //   1235: aload 9
    //   1237: astore 12
    //   1239: aload 11
    //   1241: getfield 208	com/tencent/mm/y/a/c:width	I
    //   1244: ifle +54 -> 1298
    //   1247: aload 9
    //   1249: astore 12
    //   1251: aload 11
    //   1253: getfield 208	com/tencent/mm/y/a/c:width	I
    //   1256: ifle +42 -> 1298
    //   1259: aload 9
    //   1261: astore 12
    //   1263: aload 13
    //   1265: aload 11
    //   1267: getfield 208	com/tencent/mm/y/a/c:width	I
    //   1270: aload 11
    //   1272: getfield 211	com/tencent/mm/y/a/c:height	I
    //   1275: invokestatic 373	com/tencent/mm/sdk/platformtools/e:decodeByteArray	([BII)Landroid/graphics/Bitmap;
    //   1278: astore 9
    //   1280: aload 9
    //   1282: ifnonnull +46 -> 1328
    //   1285: aload 9
    //   1287: astore 12
    //   1289: aload 10
    //   1291: iconst_3
    //   1292: putfield 243	com/tencent/mm/y/a/d/b:status	I
    //   1295: goto -1058 -> 237
    //   1298: aload 9
    //   1300: astore 12
    //   1302: aload 13
    //   1304: invokestatic 377	com/tencent/mm/sdk/platformtools/e:aC	([B)Landroid/graphics/Bitmap;
    //   1307: astore 9
    //   1309: goto -29 -> 1280
    //   1312: aload 9
    //   1314: astore 12
    //   1316: aload 13
    //   1318: iload_1
    //   1319: iload_2
    //   1320: invokestatic 373	com/tencent/mm/sdk/platformtools/e:decodeByteArray	([BII)Landroid/graphics/Bitmap;
    //   1323: astore 9
    //   1325: goto -45 -> 1280
    //   1328: aload 9
    //   1330: astore 12
    //   1332: aload 10
    //   1334: getfield 364	com/tencent/mm/y/a/d/b:data	[B
    //   1337: astore 11
    //   1339: aload 9
    //   1341: astore 12
    //   1343: aload_0
    //   1344: getfield 59	com/tencent/mm/y/a/f/a:bEZ	Lcom/tencent/mm/y/a/a/c;
    //   1347: getfield 380	com/tencent/mm/y/a/a/c:bFl	Z
    //   1350: ifeq +27 -> 1377
    //   1353: aload 9
    //   1355: astore 12
    //   1357: aload_0
    //   1358: getfield 75	com/tencent/mm/y/a/f/a:bFb	Lcom/tencent/mm/y/a/c/a;
    //   1361: aload_0
    //   1362: getfield 41	com/tencent/mm/y/a/f/a:url	Ljava/lang/String;
    //   1365: aload 11
    //   1367: aload_0
    //   1368: getfield 59	com/tencent/mm/y/a/f/a:bEZ	Lcom/tencent/mm/y/a/a/c;
    //   1371: invokeinterface 383 4 0
    //   1376: pop
    //   1377: aload 9
    //   1379: astore 12
    //   1381: aload_0
    //   1382: getfield 59	com/tencent/mm/y/a/f/a:bEZ	Lcom/tencent/mm/y/a/a/c;
    //   1385: getfield 386	com/tencent/mm/y/a/a/c:bFk	Z
    //   1388: ifeq +67 -> 1455
    //   1391: aload 9
    //   1393: astore 12
    //   1395: new 125	java/lang/StringBuilder
    //   1398: dup
    //   1399: invokespecial 126	java/lang/StringBuilder:<init>	()V
    //   1402: invokestatic 391	com/tencent/mm/y/a/g/b:zz	()Ljava/lang/String;
    //   1405: invokevirtual 130	java/lang/StringBuilder:append	(Ljava/lang/String;)Ljava/lang/StringBuilder;
    //   1408: getstatic 396	java/io/File:separator	Ljava/lang/String;
    //   1411: invokevirtual 130	java/lang/StringBuilder:append	(Ljava/lang/String;)Ljava/lang/StringBuilder;
    //   1414: aload_0
    //   1415: getfield 78	com/tencent/mm/y/a/f/a:bFd	Lcom/tencent/mm/y/a/c/c;
    //   1418: aload_0
    //   1419: getfield 41	com/tencent/mm/y/a/f/a:url	Ljava/lang/String;
    //   1422: invokeinterface 401 2 0
    //   1427: invokevirtual 130	java/lang/StringBuilder:append	(Ljava/lang/String;)Ljava/lang/StringBuilder;
    //   1430: pop
    //   1431: aload 9
    //   1433: astore 12
    //   1435: aload_0
    //   1436: getfield 75	com/tencent/mm/y/a/f/a:bFb	Lcom/tencent/mm/y/a/c/a;
    //   1439: aload_0
    //   1440: getfield 41	com/tencent/mm/y/a/f/a:url	Ljava/lang/String;
    //   1443: aload 11
    //   1445: aload_0
    //   1446: getfield 59	com/tencent/mm/y/a/f/a:bEZ	Lcom/tencent/mm/y/a/a/c;
    //   1449: invokeinterface 383 4 0
    //   1454: pop
    //   1455: aload 9
    //   1457: astore 11
    //   1459: aload 9
    //   1461: astore 12
    //   1463: aload_0
    //   1464: getfield 59	com/tencent/mm/y/a/f/a:bEZ	Lcom/tencent/mm/y/a/a/c;
    //   1467: getfield 123	com/tencent/mm/y/a/a/c:bFC	Z
    //   1470: ifeq +56 -> 1526
    //   1473: aload 9
    //   1475: astore 12
    //   1477: aload_0
    //   1478: getfield 59	com/tencent/mm/y/a/f/a:bEZ	Lcom/tencent/mm/y/a/a/c;
    //   1481: getfield 136	com/tencent/mm/y/a/a/c:bFD	F
    //   1484: fconst_0
    //   1485: fcmpl
    //   1486: ifne +150 -> 1636
    //   1489: aload 9
    //   1491: astore 12
    //   1493: aload 9
    //   1495: invokevirtual 404	android/graphics/Bitmap:getWidth	()I
    //   1498: aload 9
    //   1500: invokevirtual 407	android/graphics/Bitmap:getHeight	()I
    //   1503: if_icmpne +55 -> 1558
    //   1506: aload 9
    //   1508: astore 12
    //   1510: aload 9
    //   1512: iconst_0
    //   1513: aload 9
    //   1515: invokevirtual 404	android/graphics/Bitmap:getWidth	()I
    //   1518: iconst_2
    //   1519: idiv
    //   1520: i2f
    //   1521: invokestatic 410	com/tencent/mm/sdk/platformtools/e:a	(Landroid/graphics/Bitmap;ZF)Landroid/graphics/Bitmap;
    //   1524: astore 11
    //   1526: aload 11
    //   1528: astore 12
    //   1530: aload_0
    //   1531: aload 14
    //   1533: aload 11
    //   1535: invokespecial 412	com/tencent/mm/y/a/f/a:h	(Ljava/lang/String;Landroid/graphics/Bitmap;)V
    //   1538: aload 11
    //   1540: astore 12
    //   1542: aload_0
    //   1543: lload 6
    //   1545: lload 4
    //   1547: lsub
    //   1548: invokevirtual 413	com/tencent/mm/y/a/f/a:P	(J)V
    //   1551: aload 11
    //   1553: astore 9
    //   1555: goto -1318 -> 237
    //   1558: aload 9
    //   1560: astore 12
    //   1562: aload 9
    //   1564: invokevirtual 404	android/graphics/Bitmap:getWidth	()I
    //   1567: aload 9
    //   1569: invokevirtual 407	android/graphics/Bitmap:getHeight	()I
    //   1572: invokestatic 419	java/lang/Math:min	(II)I
    //   1575: istore_2
    //   1576: iload_2
    //   1577: istore_1
    //   1578: iload_2
    //   1579: ifgt +21 -> 1600
    //   1582: aload 9
    //   1584: astore 12
    //   1586: aload 9
    //   1588: invokevirtual 404	android/graphics/Bitmap:getWidth	()I
    //   1591: aload 9
    //   1593: invokevirtual 407	android/graphics/Bitmap:getHeight	()I
    //   1596: invokestatic 422	java/lang/Math:max	(II)I
    //   1599: istore_1
    //   1600: aload 9
    //   1602: astore 12
    //   1604: aload 9
    //   1606: iload_1
    //   1607: iload_1
    //   1608: invokestatic 426	com/tencent/mm/sdk/platformtools/e:b	(Landroid/graphics/Bitmap;II)Landroid/graphics/Bitmap;
    //   1611: astore 9
    //   1613: aload 9
    //   1615: astore 12
    //   1617: aload 9
    //   1619: iconst_0
    //   1620: aload 9
    //   1622: invokevirtual 404	android/graphics/Bitmap:getWidth	()I
    //   1625: iconst_2
    //   1626: idiv
    //   1627: i2f
    //   1628: invokestatic 410	com/tencent/mm/sdk/platformtools/e:a	(Landroid/graphics/Bitmap;ZF)Landroid/graphics/Bitmap;
    //   1631: astore 11
    //   1633: goto -107 -> 1526
    //   1636: aload 9
    //   1638: astore 12
    //   1640: aload 9
    //   1642: iconst_0
    //   1643: aload_0
    //   1644: getfield 59	com/tencent/mm/y/a/f/a:bEZ	Lcom/tencent/mm/y/a/a/c;
    //   1647: getfield 136	com/tencent/mm/y/a/a/c:bFD	F
    //   1650: invokestatic 410	com/tencent/mm/sdk/platformtools/e:a	(Landroid/graphics/Bitmap;ZF)Landroid/graphics/Bitmap;
    //   1653: astore 11
    //   1655: goto -129 -> 1526
    //   1658: aload 9
    //   1660: astore 12
    //   1662: aload 10
    //   1664: iconst_2
    //   1665: putfield 243	com/tencent/mm/y/a/d/b:status	I
    //   1668: aload 9
    //   1670: astore 12
    //   1672: ldc 93
    //   1674: ldc_w 428
    //   1677: invokestatic 227	com/tencent/mm/sdk/platformtools/t:w	(Ljava/lang/String;Ljava/lang/String;)V
    //   1680: aconst_null
    //   1681: astore 9
    //   1683: goto -1446 -> 237
    //   1686: ldc 93
    //   1688: ldc_w 430
    //   1691: invokestatic 227	com/tencent/mm/sdk/platformtools/t:w	(Ljava/lang/String;Ljava/lang/String;)V
    //   1694: goto -1457 -> 237
    //   1697: aload_0
    //   1698: getfield 59	com/tencent/mm/y/a/f/a:bEZ	Lcom/tencent/mm/y/a/a/c;
    //   1701: getfield 123	com/tencent/mm/y/a/a/c:bFC	Z
    //   1704: ifeq +228 -> 1932
    //   1707: aload_0
    //   1708: getfield 59	com/tencent/mm/y/a/f/a:bEZ	Lcom/tencent/mm/y/a/a/c;
    //   1711: getfield 136	com/tencent/mm/y/a/a/c:bFD	F
    //   1714: fconst_0
    //   1715: fcmpl
    //   1716: ifne +146 -> 1862
    //   1719: aload 9
    //   1721: invokevirtual 404	android/graphics/Bitmap:getWidth	()I
    //   1724: aload 9
    //   1726: invokevirtual 407	android/graphics/Bitmap:getHeight	()I
    //   1729: if_icmpne +63 -> 1792
    //   1732: aload 9
    //   1734: iconst_0
    //   1735: aload 9
    //   1737: invokevirtual 404	android/graphics/Bitmap:getWidth	()I
    //   1740: iconst_2
    //   1741: idiv
    //   1742: i2f
    //   1743: invokestatic 410	com/tencent/mm/sdk/platformtools/e:a	(Landroid/graphics/Bitmap;ZF)Landroid/graphics/Bitmap;
    //   1746: astore 11
    //   1748: aload 11
    //   1750: astore 9
    //   1752: aload 9
    //   1754: astore 11
    //   1756: aload_0
    //   1757: aload 14
    //   1759: aload 9
    //   1761: invokespecial 412	com/tencent/mm/y/a/f/a:h	(Ljava/lang/String;Landroid/graphics/Bitmap;)V
    //   1764: aload 9
    //   1766: astore 11
    //   1768: aload_0
    //   1769: lload 6
    //   1771: lload 4
    //   1773: lsub
    //   1774: invokevirtual 413	com/tencent/mm/y/a/f/a:P	(J)V
    //   1777: aload 9
    //   1779: astore 11
    //   1781: ldc 93
    //   1783: ldc_w 432
    //   1786: invokestatic 193	com/tencent/mm/sdk/platformtools/t:d	(Ljava/lang/String;Ljava/lang/String;)V
    //   1789: goto -1552 -> 237
    //   1792: aload 9
    //   1794: invokevirtual 404	android/graphics/Bitmap:getWidth	()I
    //   1797: aload 9
    //   1799: invokevirtual 407	android/graphics/Bitmap:getHeight	()I
    //   1802: invokestatic 419	java/lang/Math:min	(II)I
    //   1805: istore_2
    //   1806: iload_2
    //   1807: istore_1
    //   1808: iload_2
    //   1809: ifgt +17 -> 1826
    //   1812: aload 9
    //   1814: invokevirtual 404	android/graphics/Bitmap:getWidth	()I
    //   1817: aload 9
    //   1819: invokevirtual 407	android/graphics/Bitmap:getHeight	()I
    //   1822: invokestatic 422	java/lang/Math:max	(II)I
    //   1825: istore_1
    //   1826: aload 9
    //   1828: iload_1
    //   1829: iload_1
    //   1830: invokestatic 426	com/tencent/mm/sdk/platformtools/e:b	(Landroid/graphics/Bitmap;II)Landroid/graphics/Bitmap;
    //   1833: astore 11
    //   1835: aload 11
    //   1837: astore 9
    //   1839: aload 9
    //   1841: astore 11
    //   1843: aload 9
    //   1845: iconst_0
    //   1846: aload 9
    //   1848: invokevirtual 404	android/graphics/Bitmap:getWidth	()I
    //   1851: iconst_2
    //   1852: idiv
    //   1853: i2f
    //   1854: invokestatic 410	com/tencent/mm/sdk/platformtools/e:a	(Landroid/graphics/Bitmap;ZF)Landroid/graphics/Bitmap;
    //   1857: astore 9
    //   1859: goto -107 -> 1752
    //   1862: aload 9
    //   1864: iconst_0
    //   1865: aload_0
    //   1866: getfield 59	com/tencent/mm/y/a/f/a:bEZ	Lcom/tencent/mm/y/a/a/c;
    //   1869: getfield 136	com/tencent/mm/y/a/a/c:bFD	F
    //   1872: invokestatic 410	com/tencent/mm/sdk/platformtools/e:a	(Landroid/graphics/Bitmap;ZF)Landroid/graphics/Bitmap;
    //   1875: astore 11
    //   1877: aload 11
    //   1879: astore 9
    //   1881: goto -129 -> 1752
    //   1884: ldc 93
    //   1886: ldc_w 434
    //   1889: invokestatic 227	com/tencent/mm/sdk/platformtools/t:w	(Ljava/lang/String;Ljava/lang/String;)V
    //   1892: goto -1587 -> 305
    //   1895: astore 11
    //   1897: goto -1174 -> 723
    //   1900: astore 11
    //   1902: goto -1003 -> 899
    //   1905: astore 12
    //   1907: aload 11
    //   1909: astore 9
    //   1911: aload 12
    //   1913: astore 11
    //   1915: goto -1102 -> 813
    //   1918: astore 11
    //   1920: goto -1107 -> 813
    //   1923: astore 11
    //   1925: aload 12
    //   1927: astore 9
    //   1929: goto -1116 -> 813
    //   1932: goto -180 -> 1752
    //   1935: goto -1726 -> 209
    //   1938: iconst_0
    //   1939: istore_1
    //   1940: goto -1231 -> 709
    //   1943: goto -1755 -> 188
    //   1946: iload_2
    //   1947: tableswitch	default:+33->1980, 1:+-261->1686, 2:+-261->1686, 3:+-261->1686, 4:+-261->1686, 5:+-912->1035
    //   1980: goto -1750 -> 230
    // Local variable table:
    //   start	length	slot	name	signature
    //   0	1983	0	this	a
    //   462	1478	1	i	int
    //   52	1895	2	j	int
    //   470	393	3	k	int
    //   43	1729	4	l1	long
    //   212	1558	6	l2	long
    //   60	1069	8	bool	boolean
    //   150	1778	9	localObject1	Object
    //   10	1653	10	localObject2	Object
    //   1	801	11	localObject3	Object
    //   808	17	11	localException1	Exception
    //   838	57	11	localObject4	Object
    //   906	1	11	localException2	Exception
    //   1059	819	11	localObject5	Object
    //   1895	1	11	localIOException1	java.io.IOException
    //   1900	8	11	localIOException2	java.io.IOException
    //   1913	1	11	localObject6	Object
    //   1918	1	11	localException3	Exception
    //   1923	1	11	localException4	Exception
    //   336	1335	12	localObject7	Object
    //   1905	21	12	localException5	Exception
    //   618	251	13	localObject8	Object
    //   883	21	13	localObject9	Object
    //   1196	121	13	arrayOfByte	byte[]
    //   20	1738	14	str1	String
    //   69	1073	15	str2	String
    // Exception table:
    //   from	to	target	type
    //   12	148	808	java/lang/Exception
    //   188	206	808	java/lang/Exception
    //   396	406	808	java/lang/Exception
    //   410	420	808	java/lang/Exception
    //   425	443	808	java/lang/Exception
    //   443	471	808	java/lang/Exception
    //   484	517	808	java/lang/Exception
    //   757	764	808	java/lang/Exception
    //   767	776	808	java/lang/Exception
    //   779	787	808	java/lang/Exception
    //   793	801	808	java/lang/Exception
    //   915	942	808	java/lang/Exception
    //   945	994	808	java/lang/Exception
    //   997	1032	808	java/lang/Exception
    //   561	580	883	finally
    //   594	610	883	finally
    //   614	620	883	finally
    //   624	632	883	finally
    //   636	644	883	finally
    //   661	669	883	finally
    //   673	681	883	finally
    //   685	703	883	finally
    //   840	847	883	finally
    //   858	868	883	finally
    //   546	554	906	java/lang/Exception
    //   894	899	906	java/lang/Exception
    //   903	906	906	java/lang/Exception
    //   718	723	1895	java/io/IOException
    //   894	899	1900	java/io/IOException
    //   521	529	1905	java/lang/Exception
    //   718	723	1905	java/lang/Exception
    //   736	754	1905	java/lang/Exception
    //   1756	1764	1905	java/lang/Exception
    //   1768	1777	1905	java/lang/Exception
    //   1781	1789	1905	java/lang/Exception
    //   1843	1859	1905	java/lang/Exception
    //   209	214	1918	java/lang/Exception
    //   219	227	1918	java/lang/Exception
    //   230	237	1918	java/lang/Exception
    //   1035	1084	1918	java/lang/Exception
    //   1084	1099	1918	java/lang/Exception
    //   1686	1694	1918	java/lang/Exception
    //   1697	1748	1918	java/lang/Exception
    //   1792	1806	1918	java/lang/Exception
    //   1812	1826	1918	java/lang/Exception
    //   1826	1835	1918	java/lang/Exception
    //   1862	1877	1918	java/lang/Exception
    //   1107	1115	1923	java/lang/Exception
    //   1119	1125	1923	java/lang/Exception
    //   1137	1156	1923	java/lang/Exception
    //   1160	1168	1923	java/lang/Exception
    //   1172	1177	1923	java/lang/Exception
    //   1181	1187	1923	java/lang/Exception
    //   1191	1198	1923	java/lang/Exception
    //   1202	1210	1923	java/lang/Exception
    //   1214	1222	1923	java/lang/Exception
    //   1239	1247	1923	java/lang/Exception
    //   1251	1259	1923	java/lang/Exception
    //   1263	1280	1923	java/lang/Exception
    //   1289	1295	1923	java/lang/Exception
    //   1302	1309	1923	java/lang/Exception
    //   1316	1325	1923	java/lang/Exception
    //   1332	1339	1923	java/lang/Exception
    //   1343	1353	1923	java/lang/Exception
    //   1357	1377	1923	java/lang/Exception
    //   1381	1391	1923	java/lang/Exception
    //   1395	1431	1923	java/lang/Exception
    //   1435	1455	1923	java/lang/Exception
    //   1463	1473	1923	java/lang/Exception
    //   1477	1489	1923	java/lang/Exception
    //   1493	1506	1923	java/lang/Exception
    //   1510	1526	1923	java/lang/Exception
    //   1530	1538	1923	java/lang/Exception
    //   1542	1551	1923	java/lang/Exception
    //   1562	1576	1923	java/lang/Exception
    //   1586	1600	1923	java/lang/Exception
    //   1604	1613	1923	java/lang/Exception
    //   1617	1633	1923	java/lang/Exception
    //   1640	1655	1923	java/lang/Exception
    //   1662	1668	1923	java/lang/Exception
    //   1672	1680	1923	java/lang/Exception
  }
}

/* Location:
 * Qualified Name:     com.tencent.mm.y.a.f.a
 * Java Class Version: 6 (50.0)
 * JD-Core Version:    0.7.1
 */