package com.tencent.mm.plugin.backup.f;

import com.tencent.mm.plugin.report.service.g;
import com.tencent.mm.sdk.platformtools.v;

final class p$1
  implements Runnable
{
  p$1(p paramp) {}
  
  /* Error */
  public final void run()
  {
    // Byte code:
    //   0: invokestatic 28	com/tencent/mm/plugin/backup/d/h:reset	()V
    //   3: invokestatic 31	com/tencent/mm/plugin/backup/d/h:Hz	()V
    //   6: new 33	com/tencent/mm/plugin/backup/e/z
    //   9: dup
    //   10: invokespecial 34	com/tencent/mm/plugin/backup/e/z:<init>	()V
    //   13: astore 6
    //   15: aload 6
    //   17: invokevirtual 37	com/tencent/mm/plugin/backup/e/z:begin	()V
    //   20: new 39	java/util/HashMap
    //   23: dup
    //   24: invokespecial 40	java/util/HashMap:<init>	()V
    //   27: astore 7
    //   29: new 42	java/util/HashSet
    //   32: dup
    //   33: invokespecial 43	java/util/HashSet:<init>	()V
    //   36: astore 8
    //   38: aload_0
    //   39: getfield 16	com/tencent/mm/plugin/backup/f/p$1:ctX	Lcom/tencent/mm/plugin/backup/f/p;
    //   42: getfield 47	com/tencent/mm/plugin/backup/f/p:coG	Ljava/util/List;
    //   45: invokeinterface 53 1 0
    //   50: astore 9
    //   52: iconst_0
    //   53: istore_1
    //   54: aload 9
    //   56: invokeinterface 59 1 0
    //   61: ifeq +233 -> 294
    //   64: aload 9
    //   66: invokeinterface 63 1 0
    //   71: checkcast 65	java/lang/String
    //   74: astore 5
    //   76: new 67	java/lang/StringBuilder
    //   79: dup
    //   80: invokespecial 68	java/lang/StringBuilder:<init>	()V
    //   83: invokestatic 74	com/tencent/mm/plugin/backup/e/b:HY	()Ljava/lang/String;
    //   86: invokevirtual 78	java/lang/StringBuilder:append	(Ljava/lang/String;)Ljava/lang/StringBuilder;
    //   89: ldc 80
    //   91: invokevirtual 78	java/lang/StringBuilder:append	(Ljava/lang/String;)Ljava/lang/StringBuilder;
    //   94: aload 5
    //   96: invokestatic 86	com/tencent/mm/plugin/backup/e/g:lD	(Ljava/lang/String;)Ljava/lang/String;
    //   99: invokevirtual 78	java/lang/StringBuilder:append	(Ljava/lang/String;)Ljava/lang/StringBuilder;
    //   102: aload 5
    //   104: invokevirtual 78	java/lang/StringBuilder:append	(Ljava/lang/String;)Ljava/lang/StringBuilder;
    //   107: invokevirtual 89	java/lang/StringBuilder:toString	()Ljava/lang/String;
    //   110: astore 5
    //   112: invokestatic 95	java/lang/System:currentTimeMillis	()J
    //   115: lstore_3
    //   116: aload_0
    //   117: getfield 16	com/tencent/mm/plugin/backup/f/p$1:ctX	Lcom/tencent/mm/plugin/backup/f/p;
    //   120: aload 5
    //   122: aload 7
    //   124: aload 6
    //   126: aload 8
    //   128: invokevirtual 99	com/tencent/mm/plugin/backup/f/p:a	(Ljava/lang/String;Ljava/util/HashMap;Lcom/tencent/mm/plugin/backup/e/z;Ljava/util/HashSet;)I
    //   131: istore_2
    //   132: aload_0
    //   133: getfield 16	com/tencent/mm/plugin/backup/f/p$1:ctX	Lcom/tencent/mm/plugin/backup/f/p;
    //   136: astore 5
    //   138: aload 5
    //   140: invokestatic 95	java/lang/System:currentTimeMillis	()J
    //   143: lload_3
    //   144: lsub
    //   145: aload 5
    //   147: getfield 103	com/tencent/mm/plugin/backup/f/p:ctU	I
    //   150: i2l
    //   151: ladd
    //   152: l2i
    //   153: putfield 103	com/tencent/mm/plugin/backup/f/p:ctU	I
    //   156: iload_2
    //   157: ifge +16 -> 173
    //   160: aload 6
    //   162: invokevirtual 106	com/tencent/mm/plugin/backup/e/z:end	()V
    //   165: ldc 108
    //   167: ldc 110
    //   169: invokestatic 116	com/tencent/mm/sdk/platformtools/v:w	(Ljava/lang/String;Ljava/lang/String;)V
    //   172: return
    //   173: iload_2
    //   174: iload_1
    //   175: iadd
    //   176: istore_1
    //   177: aload_0
    //   178: getfield 16	com/tencent/mm/plugin/backup/f/p$1:ctX	Lcom/tencent/mm/plugin/backup/f/p;
    //   181: iload_1
    //   182: aload_0
    //   183: getfield 16	com/tencent/mm/plugin/backup/f/p$1:ctX	Lcom/tencent/mm/plugin/backup/f/p;
    //   186: getfield 119	com/tencent/mm/plugin/backup/f/p:ctS	I
    //   189: invokevirtual 123	com/tencent/mm/plugin/backup/f/p:al	(II)V
    //   192: ldc 108
    //   194: ldc 125
    //   196: iconst_3
    //   197: anewarray 4	java/lang/Object
    //   200: dup
    //   201: iconst_0
    //   202: iload_1
    //   203: invokestatic 131	java/lang/Integer:valueOf	(I)Ljava/lang/Integer;
    //   206: aastore
    //   207: dup
    //   208: iconst_1
    //   209: aload_0
    //   210: getfield 16	com/tencent/mm/plugin/backup/f/p$1:ctX	Lcom/tencent/mm/plugin/backup/f/p;
    //   213: getfield 134	com/tencent/mm/plugin/backup/f/p:ctV	I
    //   216: invokestatic 131	java/lang/Integer:valueOf	(I)Ljava/lang/Integer;
    //   219: aastore
    //   220: dup
    //   221: iconst_2
    //   222: aload_0
    //   223: getfield 16	com/tencent/mm/plugin/backup/f/p$1:ctX	Lcom/tencent/mm/plugin/backup/f/p;
    //   226: getfield 119	com/tencent/mm/plugin/backup/f/p:ctS	I
    //   229: invokestatic 131	java/lang/Integer:valueOf	(I)Ljava/lang/Integer;
    //   232: aastore
    //   233: invokestatic 138	com/tencent/mm/sdk/platformtools/v:i	(Ljava/lang/String;Ljava/lang/String;[Ljava/lang/Object;)V
    //   236: goto -182 -> 54
    //   239: astore 5
    //   241: ldc 108
    //   243: new 67	java/lang/StringBuilder
    //   246: dup
    //   247: ldc -116
    //   249: invokespecial 143	java/lang/StringBuilder:<init>	(Ljava/lang/String;)V
    //   252: aload 5
    //   254: invokevirtual 144	java/lang/Exception:toString	()Ljava/lang/String;
    //   257: invokevirtual 78	java/lang/StringBuilder:append	(Ljava/lang/String;)Ljava/lang/StringBuilder;
    //   260: invokevirtual 89	java/lang/StringBuilder:toString	()Ljava/lang/String;
    //   263: invokestatic 147	com/tencent/mm/sdk/platformtools/v:e	(Ljava/lang/String;Ljava/lang/String;)V
    //   266: ldc 108
    //   268: new 67	java/lang/StringBuilder
    //   271: dup
    //   272: ldc -107
    //   274: invokespecial 143	java/lang/StringBuilder:<init>	(Ljava/lang/String;)V
    //   277: aload 5
    //   279: invokevirtual 144	java/lang/Exception:toString	()Ljava/lang/String;
    //   282: invokevirtual 78	java/lang/StringBuilder:append	(Ljava/lang/String;)Ljava/lang/StringBuilder;
    //   285: invokevirtual 89	java/lang/StringBuilder:toString	()Ljava/lang/String;
    //   288: invokestatic 152	com/tencent/mm/sdk/platformtools/v:f	(Ljava/lang/String;Ljava/lang/String;)V
    //   291: goto -237 -> 54
    //   294: aload_0
    //   295: getfield 16	com/tencent/mm/plugin/backup/f/p$1:ctX	Lcom/tencent/mm/plugin/backup/f/p;
    //   298: aload 8
    //   300: invokevirtual 156	java/util/HashSet:size	()I
    //   303: putfield 159	com/tencent/mm/plugin/backup/f/p:ctT	I
    //   306: aload 7
    //   308: invokestatic 165	com/tencent/mm/plugin/backup/h/a:b	(Ljava/util/HashMap;)V
    //   311: aload 6
    //   313: invokevirtual 106	com/tencent/mm/plugin/backup/e/z:end	()V
    //   316: aload_0
    //   317: getfield 16	com/tencent/mm/plugin/backup/f/p$1:ctX	Lcom/tencent/mm/plugin/backup/f/p;
    //   320: bipush 100
    //   322: bipush 100
    //   324: invokevirtual 123	com/tencent/mm/plugin/backup/f/p:al	(II)V
    //   327: ldc 108
    //   329: ldc -89
    //   331: invokestatic 169	com/tencent/mm/sdk/platformtools/v:i	(Ljava/lang/String;Ljava/lang/String;)V
    //   334: invokestatic 172	com/tencent/mm/sdk/platformtools/v:appenderFlush	()V
    //   337: new 10	com/tencent/mm/plugin/backup/f/p$1$1
    //   340: dup
    //   341: aload_0
    //   342: invokespecial 175	com/tencent/mm/plugin/backup/f/p$1$1:<init>	(Lcom/tencent/mm/plugin/backup/f/p$1;)V
    //   345: invokestatic 178	com/tencent/mm/plugin/backup/e/b:e	(Ljava/lang/Runnable;)V
    //   348: return
    //   349: astore 5
    //   351: goto -110 -> 241
    // Local variable table:
    //   start	length	slot	name	signature
    //   0	354	0	this	1
    //   53	150	1	i	int
    //   131	45	2	j	int
    //   115	29	3	l	long
    //   74	72	5	localObject	Object
    //   239	39	5	localException1	Exception
    //   349	1	5	localException2	Exception
    //   13	299	6	localz	com.tencent.mm.plugin.backup.e.z
    //   27	280	7	localHashMap	java.util.HashMap
    //   36	263	8	localHashSet	java.util.HashSet
    //   50	15	9	localIterator	java.util.Iterator
    // Exception table:
    //   from	to	target	type
    //   112	156	239	java/lang/Exception
    //   160	172	239	java/lang/Exception
    //   177	236	349	java/lang/Exception
  }
}

/* Location:
 * Qualified Name:     com.tencent.mm.plugin.backup.f.p.1
 * Java Class Version: 6 (50.0)
 * JD-Core Version:    0.7.1
 */