package com.tencent.mm.ab.a.f;

import android.graphics.Bitmap;
import com.tencent.mm.ab.a.c.a;
import com.tencent.mm.ab.a.c.d;
import com.tencent.mm.ab.a.c.e;
import com.tencent.mm.ab.a.c.f;
import com.tencent.mm.ab.a.c.g;
import com.tencent.mm.ab.a.c.i;
import com.tencent.mm.ab.a.c.j;
import com.tencent.mm.ab.a.c.k;
import com.tencent.mm.ab.a.c.l;
import com.tencent.mm.sdk.platformtools.aa;
import com.tencent.mm.sdk.platformtools.ay;
import com.tencent.mm.sdk.platformtools.u;

public final class b
  implements Runnable
{
  private final com.tencent.mm.ab.a.a.b bSX;
  public final com.tencent.mm.ab.a.a.c bTq;
  private final l bTr;
  private final a bTs;
  private final com.tencent.mm.ab.a.c.b bTt;
  private final f bTu;
  private final j bTv;
  private final e bTx;
  private final com.tencent.mm.ab.a.b bUg;
  public final com.tencent.mm.ab.a.c bUi;
  private final aa bUj;
  private final i bUk;
  private final g bUl;
  private final k bUm;
  private final d bUn;
  public final String url;
  
  public b(String paramString, com.tencent.mm.ab.a.c paramc, aa paramaa, com.tencent.mm.ab.a.a.c paramc1, i parami, j paramj, com.tencent.mm.ab.a.b paramb, g paramg, e parame, d paramd)
  {
    url = paramString;
    bUi = paramc;
    bUj = paramaa;
    bUg = paramb;
    bUl = paramg;
    bSX = bUg.bSX;
    if (paramc1 == null)
    {
      bTq = bSX.bTq;
      bUk = parami;
      if (paramj != null) {
        break label177;
      }
      bTv = bSX.bTv;
      label80:
      if (bTq.bTt == null) {
        break label186;
      }
      bTt = bTq.bTt;
      label101:
      bTr = bSX.bTr;
      bTs = bSX.bTs;
      bTu = bSX.bTu;
      bUm = bSX.bTw;
      if (parame != null) {
        break label200;
      }
    }
    label177:
    label186:
    label200:
    for (bTx = bSX.bTx;; bTx = parame)
    {
      bUn = paramd;
      return;
      bTq = paramc1;
      break;
      bTv = paramj;
      break label80;
      bTt = bSX.bTt;
      break label101;
    }
  }
  
  private void h(String paramString, Bitmap paramBitmap)
  {
    if (bTq.bTB)
    {
      u.d("!56@/B4Tb64lLpJ3W0chKRkeCOp5DLdC+H/lc8CsH5NwjcaElRJ+MR/qDA==", "[cpan] run. put key %s to memory cache.", new Object[] { url });
      bTr.g(paramString, paramBitmap);
    }
  }
  
  public final void ad(long paramLong)
  {
    if (bTv != null) {
      bTv.ad(paramLong);
    }
  }
  
  public final String jdMethod_if(String paramString)
  {
    if ((ay.kz(paramString)) || (bTq == null)) {
      return null;
    }
    String str = paramString;
    if (bTq.bTW) {
      str = paramString + "round" + bTq.bTX;
    }
    return str + "size" + bTq.bTJ + bTq.bTK;
  }
  
  /* Error */
  public final void run()
  {
    // Byte code:
    //   0: aconst_null
    //   1: astore 11
    //   3: aconst_null
    //   4: astore 9
    //   6: new 171	com/tencent/mm/ab/a/d/b
    //   9: dup
    //   10: invokespecial 172	com/tencent/mm/ab/a/d/b:<init>	()V
    //   13: astore 10
    //   15: aload_0
    //   16: aload_0
    //   17: getfield 45	com/tencent/mm/ab/a/f/b:url	Ljava/lang/String;
    //   20: invokevirtual 174	com/tencent/mm/ab/a/f/b:if	(Ljava/lang/String;)Ljava/lang/String;
    //   23: astore 14
    //   25: ldc 102
    //   27: ldc -80
    //   29: iconst_1
    //   30: anewarray 4	java/lang/Object
    //   33: dup
    //   34: iconst_0
    //   35: aload_0
    //   36: getfield 45	com/tencent/mm/ab/a/f/b:url	Ljava/lang/String;
    //   39: aastore
    //   40: invokestatic 110	com/tencent/mm/sdk/platformtools/u:d	(Ljava/lang/String;Ljava/lang/String;[Ljava/lang/Object;)V
    //   43: invokestatic 182	java/lang/System:currentTimeMillis	()J
    //   46: lstore 4
    //   48: aload_0
    //   49: getfield 63	com/tencent/mm/ab/a/f/b:bTq	Lcom/tencent/mm/ab/a/a/c;
    //   52: getfield 185	com/tencent/mm/ab/a/a/c:bTI	I
    //   55: istore_2
    //   56: aload_0
    //   57: getfield 63	com/tencent/mm/ab/a/f/b:bTq	Lcom/tencent/mm/ab/a/a/c;
    //   60: getfield 188	com/tencent/mm/ab/a/a/c:bTL	Z
    //   63: istore 8
    //   65: aload_0
    //   66: getfield 63	com/tencent/mm/ab/a/f/b:bTq	Lcom/tencent/mm/ab/a/a/c;
    //   69: getfield 191	com/tencent/mm/ab/a/a/c:aut	Ljava/lang/String;
    //   72: astore 15
    //   74: ldc 102
    //   76: new 134	java/lang/StringBuilder
    //   79: dup
    //   80: ldc -63
    //   82: invokespecial 196	java/lang/StringBuilder:<init>	(Ljava/lang/String;)V
    //   85: iload 8
    //   87: invokevirtual 199	java/lang/StringBuilder:append	(Z)Ljava/lang/StringBuilder;
    //   90: invokevirtual 152	java/lang/StringBuilder:toString	()Ljava/lang/String;
    //   93: invokestatic 202	com/tencent/mm/sdk/platformtools/u:d	(Ljava/lang/String;Ljava/lang/String;)V
    //   96: ldc 102
    //   98: ldc -52
    //   100: iconst_1
    //   101: anewarray 4	java/lang/Object
    //   104: dup
    //   105: iconst_0
    //   106: iload_2
    //   107: invokestatic 210	java/lang/Integer:valueOf	(I)Ljava/lang/Integer;
    //   110: aastore
    //   111: invokestatic 110	com/tencent/mm/sdk/platformtools/u:d	(Ljava/lang/String;Ljava/lang/String;[Ljava/lang/Object;)V
    //   114: ldc 102
    //   116: ldc -44
    //   118: iconst_2
    //   119: anewarray 4	java/lang/Object
    //   122: dup
    //   123: iconst_0
    //   124: aload_0
    //   125: getfield 47	com/tencent/mm/ab/a/f/b:bUi	Lcom/tencent/mm/ab/a/c;
    //   128: getfield 217	com/tencent/mm/ab/a/c:width	I
    //   131: invokestatic 210	java/lang/Integer:valueOf	(I)Ljava/lang/Integer;
    //   134: aastore
    //   135: dup
    //   136: iconst_1
    //   137: aload_0
    //   138: getfield 47	com/tencent/mm/ab/a/f/b:bUi	Lcom/tencent/mm/ab/a/c;
    //   141: getfield 220	com/tencent/mm/ab/a/c:height	I
    //   144: invokestatic 210	java/lang/Integer:valueOf	(I)Ljava/lang/Integer;
    //   147: aastore
    //   148: invokestatic 110	com/tencent/mm/sdk/platformtools/u:d	(Ljava/lang/String;Ljava/lang/String;[Ljava/lang/Object;)V
    //   151: iload_2
    //   152: tableswitch	default:+2008->2160, 1:+293->445, 2:+1006->1158, 3:+1036->1188, 4:+1088->1240, 5:+718->870
    //   188: ldc 102
    //   190: ldc -34
    //   192: iconst_1
    //   193: anewarray 4	java/lang/Object
    //   196: dup
    //   197: iconst_0
    //   198: iload_2
    //   199: invokestatic 210	java/lang/Integer:valueOf	(I)Ljava/lang/Integer;
    //   202: aastore
    //   203: invokestatic 225	com/tencent/mm/sdk/platformtools/u:e	(Ljava/lang/String;Ljava/lang/String;[Ljava/lang/Object;)V
    //   206: aload 9
    //   208: astore 12
    //   210: invokestatic 182	java/lang/System:currentTimeMillis	()J
    //   213: lstore 6
    //   215: aload 9
    //   217: ifnull +1946 -> 2163
    //   220: aload 9
    //   222: astore 12
    //   224: aload 9
    //   226: invokevirtual 231	android/graphics/Bitmap:isRecycled	()Z
    //   229: ifeq +1666 -> 1895
    //   232: goto +1931 -> 2163
    //   235: aload 9
    //   237: astore 12
    //   239: ldc 102
    //   241: ldc -23
    //   243: invokestatic 236	com/tencent/mm/sdk/platformtools/u:w	(Ljava/lang/String;Ljava/lang/String;)V
    //   246: aload 9
    //   248: ifnull +1854 -> 2102
    //   251: aload 9
    //   253: invokevirtual 231	android/graphics/Bitmap:isRecycled	()Z
    //   256: ifne +1846 -> 2102
    //   259: ldc 102
    //   261: ldc -18
    //   263: invokestatic 202	com/tencent/mm/sdk/platformtools/u:d	(Ljava/lang/String;Ljava/lang/String;)V
    //   266: new 240	com/tencent/mm/ab/a/f/c
    //   269: dup
    //   270: aload_0
    //   271: getfield 45	com/tencent/mm/ab/a/f/b:url	Ljava/lang/String;
    //   274: aload_0
    //   275: getfield 47	com/tencent/mm/ab/a/f/b:bUi	Lcom/tencent/mm/ab/a/c;
    //   278: aload 9
    //   280: aload_0
    //   281: getfield 51	com/tencent/mm/ab/a/f/b:bUg	Lcom/tencent/mm/ab/a/b;
    //   284: aload_0
    //   285: aload_0
    //   286: getfield 45	com/tencent/mm/ab/a/f/b:url	Ljava/lang/String;
    //   289: invokevirtual 174	com/tencent/mm/ab/a/f/b:if	(Ljava/lang/String;)Ljava/lang/String;
    //   292: invokespecial 243	com/tencent/mm/ab/a/f/c:<init>	(Ljava/lang/String;Lcom/tencent/mm/ab/a/c;Landroid/graphics/Bitmap;Lcom/tencent/mm/ab/a/b;Ljava/lang/String;)V
    //   295: astore 11
    //   297: aload_0
    //   298: getfield 49	com/tencent/mm/ab/a/f/b:bUj	Lcom/tencent/mm/sdk/platformtools/aa;
    //   301: ifnull +13 -> 314
    //   304: aload_0
    //   305: getfield 49	com/tencent/mm/ab/a/f/b:bUj	Lcom/tencent/mm/sdk/platformtools/aa;
    //   308: aload 11
    //   310: invokevirtual 249	com/tencent/mm/sdk/platformtools/aa:post	(Ljava/lang/Runnable;)Z
    //   313: pop
    //   314: aload 10
    //   316: aload 9
    //   318: putfield 253	com/tencent/mm/ab/a/d/b:bitmap	Landroid/graphics/Bitmap;
    //   321: aload_0
    //   322: getfield 53	com/tencent/mm/ab/a/f/b:bUl	Lcom/tencent/mm/ab/a/c/g;
    //   325: ifnull +37 -> 362
    //   328: aload 10
    //   330: ifnull +32 -> 362
    //   333: aload 10
    //   335: aload 9
    //   337: putfield 253	com/tencent/mm/ab/a/d/b:bitmap	Landroid/graphics/Bitmap;
    //   340: aload_0
    //   341: getfield 53	com/tencent/mm/ab/a/f/b:bUl	Lcom/tencent/mm/ab/a/c/g;
    //   344: aload_0
    //   345: getfield 45	com/tencent/mm/ab/a/f/b:url	Ljava/lang/String;
    //   348: aload_0
    //   349: getfield 47	com/tencent/mm/ab/a/f/b:bUi	Lcom/tencent/mm/ab/a/c;
    //   352: invokevirtual 257	com/tencent/mm/ab/a/c:getImageView	()Landroid/widget/ImageView;
    //   355: aload 10
    //   357: invokeinterface 263 4 0
    //   362: aload_0
    //   363: getfield 65	com/tencent/mm/ab/a/f/b:bUk	Lcom/tencent/mm/ab/a/c/i;
    //   366: astore 10
    //   368: aload_0
    //   369: getfield 45	com/tencent/mm/ab/a/f/b:url	Ljava/lang/String;
    //   372: astore 11
    //   374: aload_0
    //   375: getfield 47	com/tencent/mm/ab/a/f/b:bUi	Lcom/tencent/mm/ab/a/c;
    //   378: invokevirtual 257	com/tencent/mm/ab/a/c:getImageView	()Landroid/widget/ImageView;
    //   381: pop
    //   382: aload 10
    //   384: aload 11
    //   386: aload 9
    //   388: aload_0
    //   389: getfield 63	com/tencent/mm/ab/a/f/b:bTq	Lcom/tencent/mm/ab/a/a/c;
    //   392: getfield 267	com/tencent/mm/ab/a/a/c:bUa	[Ljava/lang/Object;
    //   395: invokeinterface 272 4 0
    //   400: aload_0
    //   401: getfield 51	com/tencent/mm/ab/a/f/b:bUg	Lcom/tencent/mm/ab/a/b;
    //   404: astore 9
    //   406: aload 9
    //   408: getfield 276	com/tencent/mm/ab/a/b:bTb	Ljava/util/HashMap;
    //   411: ifnull +33 -> 444
    //   414: aload_0
    //   415: ifnull +29 -> 444
    //   418: aload_0
    //   419: getfield 47	com/tencent/mm/ab/a/f/b:bUi	Lcom/tencent/mm/ab/a/c;
    //   422: ifnull +22 -> 444
    //   425: aload 9
    //   427: getfield 276	com/tencent/mm/ab/a/b:bTb	Ljava/util/HashMap;
    //   430: aload_0
    //   431: getfield 47	com/tencent/mm/ab/a/f/b:bUi	Lcom/tencent/mm/ab/a/c;
    //   434: invokevirtual 280	com/tencent/mm/ab/a/c:Az	()I
    //   437: invokestatic 210	java/lang/Integer:valueOf	(I)Ljava/lang/Integer;
    //   440: invokevirtual 286	java/util/HashMap:remove	(Ljava/lang/Object;)Ljava/lang/Object;
    //   443: pop
    //   444: return
    //   445: aload_0
    //   446: getfield 63	com/tencent/mm/ab/a/f/b:bTq	Lcom/tencent/mm/ab/a/a/c;
    //   449: getfield 289	com/tencent/mm/ab/a/a/c:ayz	Ljava/lang/String;
    //   452: astore 11
    //   454: aload_0
    //   455: getfield 63	com/tencent/mm/ab/a/f/b:bTq	Lcom/tencent/mm/ab/a/a/c;
    //   458: getfield 292	com/tencent/mm/ab/a/a/c:bTM	Z
    //   461: ifeq +115 -> 576
    //   464: aload 11
    //   466: invokestatic 129	com/tencent/mm/sdk/platformtools/ay:kz	(Ljava/lang/String;)Z
    //   469: ifne +107 -> 576
    //   472: aload 11
    //   474: invokestatic 297	com/tencent/mm/a/e:ax	(Ljava/lang/String;)Z
    //   477: ifeq +99 -> 576
    //   480: aload_0
    //   481: getfield 63	com/tencent/mm/ab/a/f/b:bTq	Lcom/tencent/mm/ab/a/a/c;
    //   484: getfield 300	com/tencent/mm/ab/a/a/c:bTY	Z
    //   487: ifeq +61 -> 548
    //   490: aload_0
    //   491: getfield 47	com/tencent/mm/ab/a/f/b:bUi	Lcom/tencent/mm/ab/a/c;
    //   494: aload 11
    //   496: aload_0
    //   497: getfield 63	com/tencent/mm/ab/a/f/b:bTq	Lcom/tencent/mm/ab/a/a/c;
    //   500: getfield 158	com/tencent/mm/ab/a/a/c:bTJ	I
    //   503: aload_0
    //   504: getfield 63	com/tencent/mm/ab/a/f/b:bTq	Lcom/tencent/mm/ab/a/a/c;
    //   507: getfield 164	com/tencent/mm/ab/a/a/c:bTK	I
    //   510: invokestatic 306	com/tencent/mm/ab/a/g/a:b	(Lcom/tencent/mm/ab/a/c;Ljava/lang/String;II)Landroid/graphics/Bitmap;
    //   513: astore 9
    //   515: aload 9
    //   517: astore 11
    //   519: aload_0
    //   520: getfield 63	com/tencent/mm/ab/a/f/b:bTq	Lcom/tencent/mm/ab/a/a/c;
    //   523: getfield 309	com/tencent/mm/ab/a/a/c:density	I
    //   526: ifle +1631 -> 2157
    //   529: aload 9
    //   531: astore 11
    //   533: aload 9
    //   535: aload_0
    //   536: getfield 63	com/tencent/mm/ab/a/f/b:bTq	Lcom/tencent/mm/ab/a/a/c;
    //   539: getfield 309	com/tencent/mm/ab/a/a/c:density	I
    //   542: invokevirtual 313	android/graphics/Bitmap:setDensity	(I)V
    //   545: goto -339 -> 206
    //   548: aload_0
    //   549: getfield 47	com/tencent/mm/ab/a/f/b:bUi	Lcom/tencent/mm/ab/a/c;
    //   552: aload 11
    //   554: aload_0
    //   555: getfield 63	com/tencent/mm/ab/a/f/b:bTq	Lcom/tencent/mm/ab/a/a/c;
    //   558: getfield 158	com/tencent/mm/ab/a/a/c:bTJ	I
    //   561: aload_0
    //   562: getfield 63	com/tencent/mm/ab/a/f/b:bTq	Lcom/tencent/mm/ab/a/a/c;
    //   565: getfield 164	com/tencent/mm/ab/a/a/c:bTK	I
    //   568: invokestatic 315	com/tencent/mm/ab/a/g/a:a	(Lcom/tencent/mm/ab/a/c;Ljava/lang/String;II)Landroid/graphics/Bitmap;
    //   571: astore 9
    //   573: goto -58 -> 515
    //   576: aload_0
    //   577: getfield 45	com/tencent/mm/ab/a/f/b:url	Ljava/lang/String;
    //   580: invokestatic 129	com/tencent/mm/sdk/platformtools/ay:kz	(Ljava/lang/String;)Z
    //   583: ifne +276 -> 859
    //   586: aload_0
    //   587: getfield 45	com/tencent/mm/ab/a/f/b:url	Ljava/lang/String;
    //   590: invokestatic 297	com/tencent/mm/a/e:ax	(Ljava/lang/String;)Z
    //   593: ifeq +201 -> 794
    //   596: iload 8
    //   598: ifeq +21 -> 619
    //   601: aload_0
    //   602: getfield 87	com/tencent/mm/ab/a/f/b:bUm	Lcom/tencent/mm/ab/a/c/k;
    //   605: aload 15
    //   607: aload_0
    //   608: getfield 45	com/tencent/mm/ab/a/f/b:url	Ljava/lang/String;
    //   611: invokeinterface 321 3 0
    //   616: ifeq +164 -> 780
    //   619: aload_0
    //   620: getfield 63	com/tencent/mm/ab/a/f/b:bTq	Lcom/tencent/mm/ab/a/a/c;
    //   623: getfield 300	com/tencent/mm/ab/a/a/c:bTY	Z
    //   626: ifeq +75 -> 701
    //   629: aload_0
    //   630: getfield 47	com/tencent/mm/ab/a/f/b:bUi	Lcom/tencent/mm/ab/a/c;
    //   633: aload_0
    //   634: getfield 45	com/tencent/mm/ab/a/f/b:url	Ljava/lang/String;
    //   637: aload_0
    //   638: getfield 63	com/tencent/mm/ab/a/f/b:bTq	Lcom/tencent/mm/ab/a/a/c;
    //   641: getfield 158	com/tencent/mm/ab/a/a/c:bTJ	I
    //   644: aload_0
    //   645: getfield 63	com/tencent/mm/ab/a/f/b:bTq	Lcom/tencent/mm/ab/a/a/c;
    //   648: getfield 164	com/tencent/mm/ab/a/a/c:bTK	I
    //   651: invokestatic 306	com/tencent/mm/ab/a/g/a:b	(Lcom/tencent/mm/ab/a/c;Ljava/lang/String;II)Landroid/graphics/Bitmap;
    //   654: astore 9
    //   656: aload 9
    //   658: astore 11
    //   660: aload_0
    //   661: getfield 63	com/tencent/mm/ab/a/f/b:bTq	Lcom/tencent/mm/ab/a/a/c;
    //   664: getfield 309	com/tencent/mm/ab/a/a/c:density	I
    //   667: ifle +19 -> 686
    //   670: aload 9
    //   672: astore 11
    //   674: aload 9
    //   676: aload_0
    //   677: getfield 63	com/tencent/mm/ab/a/f/b:bTq	Lcom/tencent/mm/ab/a/a/c;
    //   680: getfield 309	com/tencent/mm/ab/a/a/c:density	I
    //   683: invokevirtual 313	android/graphics/Bitmap:setDensity	(I)V
    //   686: aload 9
    //   688: astore 11
    //   690: ldc 102
    //   692: ldc_w 323
    //   695: invokestatic 202	com/tencent/mm/sdk/platformtools/u:d	(Ljava/lang/String;Ljava/lang/String;)V
    //   698: goto -492 -> 206
    //   701: aload_0
    //   702: getfield 92	com/tencent/mm/ab/a/f/b:bUn	Lcom/tencent/mm/ab/a/c/d;
    //   705: ifnull +45 -> 750
    //   708: aload_0
    //   709: getfield 47	com/tencent/mm/ab/a/f/b:bUi	Lcom/tencent/mm/ab/a/c;
    //   712: aload_0
    //   713: getfield 92	com/tencent/mm/ab/a/f/b:bUn	Lcom/tencent/mm/ab/a/c/d;
    //   716: aload_0
    //   717: getfield 63	com/tencent/mm/ab/a/f/b:bTq	Lcom/tencent/mm/ab/a/a/c;
    //   720: getfield 267	com/tencent/mm/ab/a/a/c:bUa	[Ljava/lang/Object;
    //   723: invokeinterface 328 2 0
    //   728: aload_0
    //   729: getfield 63	com/tencent/mm/ab/a/f/b:bTq	Lcom/tencent/mm/ab/a/a/c;
    //   732: getfield 158	com/tencent/mm/ab/a/a/c:bTJ	I
    //   735: aload_0
    //   736: getfield 63	com/tencent/mm/ab/a/f/b:bTq	Lcom/tencent/mm/ab/a/a/c;
    //   739: getfield 164	com/tencent/mm/ab/a/a/c:bTK	I
    //   742: invokestatic 331	com/tencent/mm/ab/a/g/a:a	(Lcom/tencent/mm/ab/a/c;[BII)Landroid/graphics/Bitmap;
    //   745: astore 9
    //   747: goto -91 -> 656
    //   750: aload_0
    //   751: getfield 47	com/tencent/mm/ab/a/f/b:bUi	Lcom/tencent/mm/ab/a/c;
    //   754: aload_0
    //   755: getfield 45	com/tencent/mm/ab/a/f/b:url	Ljava/lang/String;
    //   758: aload_0
    //   759: getfield 63	com/tencent/mm/ab/a/f/b:bTq	Lcom/tencent/mm/ab/a/a/c;
    //   762: getfield 158	com/tencent/mm/ab/a/a/c:bTJ	I
    //   765: aload_0
    //   766: getfield 63	com/tencent/mm/ab/a/f/b:bTq	Lcom/tencent/mm/ab/a/a/c;
    //   769: getfield 164	com/tencent/mm/ab/a/a/c:bTK	I
    //   772: invokestatic 315	com/tencent/mm/ab/a/g/a:a	(Lcom/tencent/mm/ab/a/c;Ljava/lang/String;II)Landroid/graphics/Bitmap;
    //   775: astore 9
    //   777: goto -121 -> 656
    //   780: ldc 102
    //   782: ldc_w 333
    //   785: invokestatic 236	com/tencent/mm/sdk/platformtools/u:w	(Ljava/lang/String;Ljava/lang/String;)V
    //   788: aconst_null
    //   789: astore 9
    //   791: goto -585 -> 206
    //   794: aload_0
    //   795: getfield 63	com/tencent/mm/ab/a/f/b:bTq	Lcom/tencent/mm/ab/a/a/c;
    //   798: getfield 336	com/tencent/mm/ab/a/a/c:bTN	Z
    //   801: ifeq +19 -> 820
    //   804: aload_0
    //   805: getfield 90	com/tencent/mm/ab/a/f/b:bTx	Lcom/tencent/mm/ab/a/c/e;
    //   808: aload_0
    //   809: getfield 63	com/tencent/mm/ab/a/f/b:bTq	Lcom/tencent/mm/ab/a/a/c;
    //   812: getfield 267	com/tencent/mm/ab/a/a/c:bUa	[Ljava/lang/Object;
    //   815: invokeinterface 341 2 0
    //   820: ldc 102
    //   822: ldc_w 343
    //   825: invokestatic 236	com/tencent/mm/sdk/platformtools/u:w	(Ljava/lang/String;Ljava/lang/String;)V
    //   828: goto -622 -> 206
    //   831: astore 11
    //   833: aconst_null
    //   834: astore 9
    //   836: ldc 102
    //   838: ldc_w 345
    //   841: iconst_1
    //   842: anewarray 4	java/lang/Object
    //   845: dup
    //   846: iconst_0
    //   847: aload 11
    //   849: invokevirtual 346	java/lang/Exception:toString	()Ljava/lang/String;
    //   852: aastore
    //   853: invokestatic 225	com/tencent/mm/sdk/platformtools/u:e	(Ljava/lang/String;Ljava/lang/String;[Ljava/lang/Object;)V
    //   856: goto -610 -> 246
    //   859: ldc 102
    //   861: ldc_w 348
    //   864: invokestatic 236	com/tencent/mm/sdk/platformtools/u:w	(Ljava/lang/String;Ljava/lang/String;)V
    //   867: goto -661 -> 206
    //   870: aconst_null
    //   871: astore 9
    //   873: iconst_0
    //   874: istore_1
    //   875: aload_0
    //   876: getfield 79	com/tencent/mm/ab/a/f/b:bTs	Lcom/tencent/mm/ab/a/c/a;
    //   879: aload_0
    //   880: getfield 45	com/tencent/mm/ab/a/f/b:url	Ljava/lang/String;
    //   883: aload_0
    //   884: getfield 63	com/tencent/mm/ab/a/f/b:bTq	Lcom/tencent/mm/ab/a/a/c;
    //   887: invokeinterface 353 3 0
    //   892: astore 13
    //   894: aload 13
    //   896: ifnull +131 -> 1027
    //   899: iload 8
    //   901: ifeq +23 -> 924
    //   904: aload 13
    //   906: astore 9
    //   908: aload_0
    //   909: getfield 87	com/tencent/mm/ab/a/f/b:bUm	Lcom/tencent/mm/ab/a/c/k;
    //   912: aload 15
    //   914: aload 13
    //   916: invokeinterface 356 3 0
    //   921: ifeq +214 -> 1135
    //   924: aload 13
    //   926: astore 9
    //   928: aload_0
    //   929: getfield 47	com/tencent/mm/ab/a/f/b:bUi	Lcom/tencent/mm/ab/a/c;
    //   932: astore 11
    //   934: aload 13
    //   936: astore 9
    //   938: aload_0
    //   939: getfield 63	com/tencent/mm/ab/a/f/b:bTq	Lcom/tencent/mm/ab/a/a/c;
    //   942: getfield 158	com/tencent/mm/ab/a/a/c:bTJ	I
    //   945: istore_1
    //   946: aload 13
    //   948: astore 9
    //   950: aload_0
    //   951: getfield 63	com/tencent/mm/ab/a/f/b:bTq	Lcom/tencent/mm/ab/a/a/c;
    //   954: getfield 164	com/tencent/mm/ab/a/a/c:bTK	I
    //   957: istore_3
    //   958: iload_1
    //   959: ifle +7 -> 966
    //   962: iload_3
    //   963: ifgt +151 -> 1114
    //   966: aload 11
    //   968: ifnull +128 -> 1096
    //   971: aload 13
    //   973: astore 9
    //   975: aload 11
    //   977: getfield 217	com/tencent/mm/ab/a/c:width	I
    //   980: ifle +116 -> 1096
    //   983: aload 13
    //   985: astore 9
    //   987: aload 11
    //   989: getfield 217	com/tencent/mm/ab/a/c:width	I
    //   992: ifle +104 -> 1096
    //   995: aload 13
    //   997: astore 9
    //   999: aload 13
    //   1001: fconst_0
    //   1002: aload 11
    //   1004: getfield 217	com/tencent/mm/ab/a/c:width	I
    //   1007: aload 11
    //   1009: getfield 220	com/tencent/mm/ab/a/c:height	I
    //   1012: invokestatic 361	com/tencent/mm/sdk/platformtools/d:a	(Ljava/io/InputStream;FII)Landroid/graphics/Bitmap;
    //   1015: astore 11
    //   1017: aload 11
    //   1019: astore 9
    //   1021: iconst_1
    //   1022: istore_1
    //   1023: aload 9
    //   1025: astore 11
    //   1027: aload 13
    //   1029: ifnull +12 -> 1041
    //   1032: aload 11
    //   1034: astore 12
    //   1036: aload 13
    //   1038: invokevirtual 366	java/io/InputStream:close	()V
    //   1041: aload 11
    //   1043: astore 9
    //   1045: iload_1
    //   1046: ifeq -840 -> 206
    //   1049: aload 11
    //   1051: astore 9
    //   1053: aload 11
    //   1055: ifnonnull -849 -> 206
    //   1058: aload 11
    //   1060: astore 12
    //   1062: aload_0
    //   1063: getfield 79	com/tencent/mm/ab/a/f/b:bTs	Lcom/tencent/mm/ab/a/c/a;
    //   1066: aload_0
    //   1067: getfield 45	com/tencent/mm/ab/a/f/b:url	Ljava/lang/String;
    //   1070: aload_0
    //   1071: getfield 63	com/tencent/mm/ab/a/f/b:bTq	Lcom/tencent/mm/ab/a/a/c;
    //   1074: invokeinterface 370 3 0
    //   1079: pop
    //   1080: aload 11
    //   1082: astore 9
    //   1084: goto -878 -> 206
    //   1087: astore 11
    //   1089: aload 12
    //   1091: astore 9
    //   1093: goto -257 -> 836
    //   1096: aload 13
    //   1098: astore 9
    //   1100: aload 13
    //   1102: invokestatic 374	com/tencent/mm/sdk/platformtools/d:decodeStream	(Ljava/io/InputStream;)Landroid/graphics/Bitmap;
    //   1105: astore 11
    //   1107: aload 11
    //   1109: astore 9
    //   1111: goto -90 -> 1021
    //   1114: aload 13
    //   1116: astore 9
    //   1118: aload 13
    //   1120: fconst_0
    //   1121: iload_1
    //   1122: iload_3
    //   1123: invokestatic 361	com/tencent/mm/sdk/platformtools/d:a	(Ljava/io/InputStream;FII)Landroid/graphics/Bitmap;
    //   1126: astore 11
    //   1128: aload 11
    //   1130: astore 9
    //   1132: goto -111 -> 1021
    //   1135: iconst_1
    //   1136: istore_1
    //   1137: aconst_null
    //   1138: astore 11
    //   1140: goto -113 -> 1027
    //   1143: astore 11
    //   1145: aload 9
    //   1147: ifnull +8 -> 1155
    //   1150: aload 9
    //   1152: invokevirtual 366	java/io/InputStream:close	()V
    //   1155: aload 11
    //   1157: athrow
    //   1158: aload_0
    //   1159: getfield 47	com/tencent/mm/ab/a/f/b:bUi	Lcom/tencent/mm/ab/a/c;
    //   1162: aload_0
    //   1163: getfield 45	com/tencent/mm/ab/a/f/b:url	Ljava/lang/String;
    //   1166: aload_0
    //   1167: getfield 63	com/tencent/mm/ab/a/f/b:bTq	Lcom/tencent/mm/ab/a/a/c;
    //   1170: getfield 158	com/tencent/mm/ab/a/a/c:bTJ	I
    //   1173: aload_0
    //   1174: getfield 63	com/tencent/mm/ab/a/f/b:bTq	Lcom/tencent/mm/ab/a/a/c;
    //   1177: getfield 164	com/tencent/mm/ab/a/a/c:bTK	I
    //   1180: invokestatic 376	com/tencent/mm/ab/a/g/a:c	(Lcom/tencent/mm/ab/a/c;Ljava/lang/String;II)Landroid/graphics/Bitmap;
    //   1183: astore 9
    //   1185: goto -979 -> 206
    //   1188: aload_0
    //   1189: getfield 58	com/tencent/mm/ab/a/f/b:bSX	Lcom/tencent/mm/ab/a/a/b;
    //   1192: getfield 380	com/tencent/mm/ab/a/a/b:bTn	Landroid/content/res/Resources;
    //   1195: aload_0
    //   1196: getfield 45	com/tencent/mm/ab/a/f/b:url	Ljava/lang/String;
    //   1199: ldc_w 382
    //   1202: aload_0
    //   1203: getfield 58	com/tencent/mm/ab/a/f/b:bSX	Lcom/tencent/mm/ab/a/a/b;
    //   1206: getfield 385	com/tencent/mm/ab/a/a/b:packageName	Ljava/lang/String;
    //   1209: invokevirtual 391	android/content/res/Resources:getIdentifier	(Ljava/lang/String;Ljava/lang/String;Ljava/lang/String;)I
    //   1212: istore_1
    //   1213: aload_0
    //   1214: getfield 47	com/tencent/mm/ab/a/f/b:bUi	Lcom/tencent/mm/ab/a/c;
    //   1217: iload_1
    //   1218: aload_0
    //   1219: getfield 63	com/tencent/mm/ab/a/f/b:bTq	Lcom/tencent/mm/ab/a/a/c;
    //   1222: getfield 158	com/tencent/mm/ab/a/a/c:bTJ	I
    //   1225: aload_0
    //   1226: getfield 63	com/tencent/mm/ab/a/f/b:bTq	Lcom/tencent/mm/ab/a/a/c;
    //   1229: getfield 164	com/tencent/mm/ab/a/a/c:bTK	I
    //   1232: invokestatic 394	com/tencent/mm/ab/a/g/a:a	(Lcom/tencent/mm/ab/a/c;III)Landroid/graphics/Bitmap;
    //   1235: astore 9
    //   1237: goto -1031 -> 206
    //   1240: aload_0
    //   1241: getfield 45	com/tencent/mm/ab/a/f/b:url	Ljava/lang/String;
    //   1244: invokestatic 397	java/lang/Integer:valueOf	(Ljava/lang/String;)Ljava/lang/Integer;
    //   1247: invokevirtual 400	java/lang/Integer:intValue	()I
    //   1250: istore_1
    //   1251: aload_0
    //   1252: getfield 47	com/tencent/mm/ab/a/f/b:bUi	Lcom/tencent/mm/ab/a/c;
    //   1255: iload_1
    //   1256: aload_0
    //   1257: getfield 63	com/tencent/mm/ab/a/f/b:bTq	Lcom/tencent/mm/ab/a/a/c;
    //   1260: getfield 158	com/tencent/mm/ab/a/a/c:bTJ	I
    //   1263: aload_0
    //   1264: getfield 63	com/tencent/mm/ab/a/f/b:bTq	Lcom/tencent/mm/ab/a/a/c;
    //   1267: getfield 164	com/tencent/mm/ab/a/a/c:bTK	I
    //   1270: invokestatic 394	com/tencent/mm/ab/a/g/a:a	(Lcom/tencent/mm/ab/a/c;III)Landroid/graphics/Bitmap;
    //   1273: astore 9
    //   1275: goto -1069 -> 206
    //   1278: aload 9
    //   1280: astore 12
    //   1282: invokestatic 182	java/lang/System:currentTimeMillis	()J
    //   1285: lstore 4
    //   1287: aload 9
    //   1289: astore 12
    //   1291: ldc 102
    //   1293: ldc_w 402
    //   1296: invokestatic 202	com/tencent/mm/sdk/platformtools/u:d	(Ljava/lang/String;Ljava/lang/String;)V
    //   1299: aload 9
    //   1301: astore 12
    //   1303: aload_0
    //   1304: getfield 53	com/tencent/mm/ab/a/f/b:bUl	Lcom/tencent/mm/ab/a/c/g;
    //   1307: ifnull +48 -> 1355
    //   1310: aload 9
    //   1312: astore 12
    //   1314: aload_0
    //   1315: getfield 53	com/tencent/mm/ab/a/f/b:bUl	Lcom/tencent/mm/ab/a/c/g;
    //   1318: astore 11
    //   1320: aload 9
    //   1322: astore 12
    //   1324: aload_0
    //   1325: getfield 45	com/tencent/mm/ab/a/f/b:url	Ljava/lang/String;
    //   1328: astore 13
    //   1330: aload 9
    //   1332: astore 12
    //   1334: aload_0
    //   1335: getfield 47	com/tencent/mm/ab/a/f/b:bUi	Lcom/tencent/mm/ab/a/c;
    //   1338: invokevirtual 257	com/tencent/mm/ab/a/c:getImageView	()Landroid/widget/ImageView;
    //   1341: pop
    //   1342: aload 9
    //   1344: astore 12
    //   1346: aload 11
    //   1348: aload 13
    //   1350: invokeinterface 405 2 0
    //   1355: aload 9
    //   1357: astore 12
    //   1359: aload_0
    //   1360: getfield 73	com/tencent/mm/ab/a/f/b:bTt	Lcom/tencent/mm/ab/a/c/b;
    //   1363: aload_0
    //   1364: getfield 45	com/tencent/mm/ab/a/f/b:url	Ljava/lang/String;
    //   1367: invokeinterface 411 2 0
    //   1372: astore 11
    //   1374: aload 11
    //   1376: astore 12
    //   1378: aload 12
    //   1380: astore 10
    //   1382: aload 12
    //   1384: ifnonnull +14 -> 1398
    //   1387: new 171	com/tencent/mm/ab/a/d/b
    //   1390: dup
    //   1391: aconst_null
    //   1392: aconst_null
    //   1393: invokespecial 414	com/tencent/mm/ab/a/d/b:<init>	([BLjava/lang/String;)V
    //   1396: astore 10
    //   1398: aload 10
    //   1400: astore 12
    //   1402: aload 10
    //   1404: getfield 418	com/tencent/mm/ab/a/d/b:data	[B
    //   1407: ifnonnull +16 -> 1423
    //   1410: aload 10
    //   1412: astore 12
    //   1414: aload 10
    //   1416: iconst_1
    //   1417: putfield 421	com/tencent/mm/ab/a/d/b:status	I
    //   1420: goto -1174 -> 246
    //   1423: iload 8
    //   1425: ifeq +26 -> 1451
    //   1428: aload 10
    //   1430: astore 12
    //   1432: aload_0
    //   1433: getfield 87	com/tencent/mm/ab/a/f/b:bUm	Lcom/tencent/mm/ab/a/c/k;
    //   1436: aload 15
    //   1438: aload 10
    //   1440: getfield 418	com/tencent/mm/ab/a/d/b:data	[B
    //   1443: invokeinterface 425 3 0
    //   1448: ifeq +404 -> 1852
    //   1451: aload 10
    //   1453: astore 12
    //   1455: ldc 102
    //   1457: ldc_w 427
    //   1460: invokestatic 202	com/tencent/mm/sdk/platformtools/u:d	(Ljava/lang/String;Ljava/lang/String;)V
    //   1463: aload 10
    //   1465: astore 12
    //   1467: invokestatic 182	java/lang/System:currentTimeMillis	()J
    //   1470: lstore 6
    //   1472: aload 10
    //   1474: astore 12
    //   1476: aload_0
    //   1477: getfield 47	com/tencent/mm/ab/a/f/b:bUi	Lcom/tencent/mm/ab/a/c;
    //   1480: aload 10
    //   1482: getfield 418	com/tencent/mm/ab/a/d/b:data	[B
    //   1485: aload_0
    //   1486: getfield 63	com/tencent/mm/ab/a/f/b:bTq	Lcom/tencent/mm/ab/a/a/c;
    //   1489: getfield 158	com/tencent/mm/ab/a/a/c:bTJ	I
    //   1492: aload_0
    //   1493: getfield 63	com/tencent/mm/ab/a/f/b:bTq	Lcom/tencent/mm/ab/a/a/c;
    //   1496: getfield 164	com/tencent/mm/ab/a/a/c:bTK	I
    //   1499: invokestatic 331	com/tencent/mm/ab/a/g/a:a	(Lcom/tencent/mm/ab/a/c;[BII)Landroid/graphics/Bitmap;
    //   1502: astore 11
    //   1504: aload 11
    //   1506: ifnonnull +20 -> 1526
    //   1509: aload 11
    //   1511: astore 12
    //   1513: aload 10
    //   1515: iconst_3
    //   1516: putfield 421	com/tencent/mm/ab/a/d/b:status	I
    //   1519: aload 11
    //   1521: astore 9
    //   1523: goto -1277 -> 246
    //   1526: aload 11
    //   1528: astore 12
    //   1530: aload 10
    //   1532: getfield 418	com/tencent/mm/ab/a/d/b:data	[B
    //   1535: astore 9
    //   1537: aload 11
    //   1539: astore 12
    //   1541: aload_0
    //   1542: getfield 63	com/tencent/mm/ab/a/f/b:bTq	Lcom/tencent/mm/ab/a/a/c;
    //   1545: getfield 430	com/tencent/mm/ab/a/a/c:bTD	Z
    //   1548: ifeq +27 -> 1575
    //   1551: aload 11
    //   1553: astore 12
    //   1555: aload_0
    //   1556: getfield 79	com/tencent/mm/ab/a/f/b:bTs	Lcom/tencent/mm/ab/a/c/a;
    //   1559: aload_0
    //   1560: getfield 45	com/tencent/mm/ab/a/f/b:url	Ljava/lang/String;
    //   1563: aload 9
    //   1565: aload_0
    //   1566: getfield 63	com/tencent/mm/ab/a/f/b:bTq	Lcom/tencent/mm/ab/a/a/c;
    //   1569: invokeinterface 433 4 0
    //   1574: pop
    //   1575: aload 11
    //   1577: astore 12
    //   1579: aload_0
    //   1580: getfield 63	com/tencent/mm/ab/a/f/b:bTq	Lcom/tencent/mm/ab/a/a/c;
    //   1583: getfield 436	com/tencent/mm/ab/a/a/c:bTC	Z
    //   1586: ifeq +67 -> 1653
    //   1589: aload 11
    //   1591: astore 12
    //   1593: new 134	java/lang/StringBuilder
    //   1596: dup
    //   1597: invokespecial 135	java/lang/StringBuilder:<init>	()V
    //   1600: invokestatic 441	com/tencent/mm/ab/a/g/b:AC	()Ljava/lang/String;
    //   1603: invokevirtual 139	java/lang/StringBuilder:append	(Ljava/lang/String;)Ljava/lang/StringBuilder;
    //   1606: getstatic 446	java/io/File:separator	Ljava/lang/String;
    //   1609: invokevirtual 139	java/lang/StringBuilder:append	(Ljava/lang/String;)Ljava/lang/StringBuilder;
    //   1612: aload_0
    //   1613: getfield 82	com/tencent/mm/ab/a/f/b:bTu	Lcom/tencent/mm/ab/a/c/f;
    //   1616: aload_0
    //   1617: getfield 45	com/tencent/mm/ab/a/f/b:url	Ljava/lang/String;
    //   1620: invokeinterface 451 2 0
    //   1625: invokevirtual 139	java/lang/StringBuilder:append	(Ljava/lang/String;)Ljava/lang/StringBuilder;
    //   1628: pop
    //   1629: aload 11
    //   1631: astore 12
    //   1633: aload_0
    //   1634: getfield 79	com/tencent/mm/ab/a/f/b:bTs	Lcom/tencent/mm/ab/a/c/a;
    //   1637: aload_0
    //   1638: getfield 45	com/tencent/mm/ab/a/f/b:url	Ljava/lang/String;
    //   1641: aload 9
    //   1643: aload_0
    //   1644: getfield 63	com/tencent/mm/ab/a/f/b:bTq	Lcom/tencent/mm/ab/a/a/c;
    //   1647: invokeinterface 433 4 0
    //   1652: pop
    //   1653: aload 11
    //   1655: astore 9
    //   1657: aload 11
    //   1659: astore 12
    //   1661: aload_0
    //   1662: getfield 63	com/tencent/mm/ab/a/f/b:bTq	Lcom/tencent/mm/ab/a/a/c;
    //   1665: getfield 132	com/tencent/mm/ab/a/a/c:bTW	Z
    //   1668: ifeq +56 -> 1724
    //   1671: aload 11
    //   1673: astore 12
    //   1675: aload_0
    //   1676: getfield 63	com/tencent/mm/ab/a/f/b:bTq	Lcom/tencent/mm/ab/a/a/c;
    //   1679: getfield 145	com/tencent/mm/ab/a/a/c:bTX	F
    //   1682: fconst_0
    //   1683: fcmpl
    //   1684: ifne +146 -> 1830
    //   1687: aload 11
    //   1689: astore 12
    //   1691: aload 11
    //   1693: invokevirtual 454	android/graphics/Bitmap:getWidth	()I
    //   1696: aload 11
    //   1698: invokevirtual 457	android/graphics/Bitmap:getHeight	()I
    //   1701: if_icmpne +51 -> 1752
    //   1704: aload 11
    //   1706: astore 12
    //   1708: aload 11
    //   1710: iconst_0
    //   1711: aload 11
    //   1713: invokevirtual 454	android/graphics/Bitmap:getWidth	()I
    //   1716: iconst_2
    //   1717: idiv
    //   1718: i2f
    //   1719: invokestatic 460	com/tencent/mm/sdk/platformtools/d:a	(Landroid/graphics/Bitmap;ZF)Landroid/graphics/Bitmap;
    //   1722: astore 9
    //   1724: aload 9
    //   1726: astore 12
    //   1728: aload_0
    //   1729: aload 14
    //   1731: aload 9
    //   1733: invokespecial 462	com/tencent/mm/ab/a/f/b:h	(Ljava/lang/String;Landroid/graphics/Bitmap;)V
    //   1736: aload 9
    //   1738: astore 12
    //   1740: aload_0
    //   1741: lload 6
    //   1743: lload 4
    //   1745: lsub
    //   1746: invokevirtual 463	com/tencent/mm/ab/a/f/b:ad	(J)V
    //   1749: goto -1503 -> 246
    //   1752: aload 11
    //   1754: astore 12
    //   1756: aload 11
    //   1758: invokevirtual 454	android/graphics/Bitmap:getWidth	()I
    //   1761: aload 11
    //   1763: invokevirtual 457	android/graphics/Bitmap:getHeight	()I
    //   1766: invokestatic 469	java/lang/Math:min	(II)I
    //   1769: istore_2
    //   1770: iload_2
    //   1771: istore_1
    //   1772: iload_2
    //   1773: ifgt +21 -> 1794
    //   1776: aload 11
    //   1778: astore 12
    //   1780: aload 11
    //   1782: invokevirtual 454	android/graphics/Bitmap:getWidth	()I
    //   1785: aload 11
    //   1787: invokevirtual 457	android/graphics/Bitmap:getHeight	()I
    //   1790: invokestatic 472	java/lang/Math:max	(II)I
    //   1793: istore_1
    //   1794: aload 11
    //   1796: astore 12
    //   1798: aload 11
    //   1800: iload_1
    //   1801: iload_1
    //   1802: invokestatic 475	com/tencent/mm/sdk/platformtools/d:c	(Landroid/graphics/Bitmap;II)Landroid/graphics/Bitmap;
    //   1805: astore 9
    //   1807: aload 9
    //   1809: astore 12
    //   1811: aload 9
    //   1813: iconst_0
    //   1814: aload 9
    //   1816: invokevirtual 454	android/graphics/Bitmap:getWidth	()I
    //   1819: iconst_2
    //   1820: idiv
    //   1821: i2f
    //   1822: invokestatic 460	com/tencent/mm/sdk/platformtools/d:a	(Landroid/graphics/Bitmap;ZF)Landroid/graphics/Bitmap;
    //   1825: astore 9
    //   1827: goto -103 -> 1724
    //   1830: aload 11
    //   1832: astore 12
    //   1834: aload 11
    //   1836: iconst_0
    //   1837: aload_0
    //   1838: getfield 63	com/tencent/mm/ab/a/f/b:bTq	Lcom/tencent/mm/ab/a/a/c;
    //   1841: getfield 145	com/tencent/mm/ab/a/a/c:bTX	F
    //   1844: invokestatic 460	com/tencent/mm/sdk/platformtools/d:a	(Landroid/graphics/Bitmap;ZF)Landroid/graphics/Bitmap;
    //   1847: astore 9
    //   1849: goto -125 -> 1724
    //   1852: aload 10
    //   1854: astore 12
    //   1856: aload 10
    //   1858: iconst_2
    //   1859: putfield 421	com/tencent/mm/ab/a/d/b:status	I
    //   1862: aload 10
    //   1864: astore 12
    //   1866: ldc 102
    //   1868: ldc_w 477
    //   1871: invokestatic 236	com/tencent/mm/sdk/platformtools/u:w	(Ljava/lang/String;Ljava/lang/String;)V
    //   1874: aconst_null
    //   1875: astore 9
    //   1877: goto -1631 -> 246
    //   1880: aload 9
    //   1882: astore 12
    //   1884: ldc 102
    //   1886: ldc_w 479
    //   1889: invokestatic 236	com/tencent/mm/sdk/platformtools/u:w	(Ljava/lang/String;Ljava/lang/String;)V
    //   1892: goto -1646 -> 246
    //   1895: aload 9
    //   1897: astore 12
    //   1899: aload_0
    //   1900: getfield 63	com/tencent/mm/ab/a/f/b:bTq	Lcom/tencent/mm/ab/a/a/c;
    //   1903: getfield 132	com/tencent/mm/ab/a/a/c:bTW	Z
    //   1906: ifeq +248 -> 2154
    //   1909: aload 9
    //   1911: astore 12
    //   1913: aload_0
    //   1914: getfield 63	com/tencent/mm/ab/a/f/b:bTq	Lcom/tencent/mm/ab/a/a/c;
    //   1917: getfield 145	com/tencent/mm/ab/a/a/c:bTX	F
    //   1920: fconst_0
    //   1921: fcmpl
    //   1922: ifne +158 -> 2080
    //   1925: aload 9
    //   1927: astore 12
    //   1929: aload 9
    //   1931: invokevirtual 454	android/graphics/Bitmap:getWidth	()I
    //   1934: aload 9
    //   1936: invokevirtual 457	android/graphics/Bitmap:getHeight	()I
    //   1939: if_icmpne +63 -> 2002
    //   1942: aload 9
    //   1944: astore 12
    //   1946: aload 9
    //   1948: iconst_0
    //   1949: aload 9
    //   1951: invokevirtual 454	android/graphics/Bitmap:getWidth	()I
    //   1954: iconst_2
    //   1955: idiv
    //   1956: i2f
    //   1957: invokestatic 460	com/tencent/mm/sdk/platformtools/d:a	(Landroid/graphics/Bitmap;ZF)Landroid/graphics/Bitmap;
    //   1960: astore 9
    //   1962: aload 9
    //   1964: astore 11
    //   1966: aload_0
    //   1967: aload 14
    //   1969: aload 9
    //   1971: invokespecial 462	com/tencent/mm/ab/a/f/b:h	(Ljava/lang/String;Landroid/graphics/Bitmap;)V
    //   1974: aload 9
    //   1976: astore 11
    //   1978: aload_0
    //   1979: lload 6
    //   1981: lload 4
    //   1983: lsub
    //   1984: invokevirtual 463	com/tencent/mm/ab/a/f/b:ad	(J)V
    //   1987: aload 9
    //   1989: astore 11
    //   1991: ldc 102
    //   1993: ldc_w 481
    //   1996: invokestatic 202	com/tencent/mm/sdk/platformtools/u:d	(Ljava/lang/String;Ljava/lang/String;)V
    //   1999: goto -1753 -> 246
    //   2002: aload 9
    //   2004: astore 12
    //   2006: aload 9
    //   2008: invokevirtual 454	android/graphics/Bitmap:getWidth	()I
    //   2011: aload 9
    //   2013: invokevirtual 457	android/graphics/Bitmap:getHeight	()I
    //   2016: invokestatic 469	java/lang/Math:min	(II)I
    //   2019: istore_2
    //   2020: iload_2
    //   2021: istore_1
    //   2022: iload_2
    //   2023: ifgt +21 -> 2044
    //   2026: aload 9
    //   2028: astore 12
    //   2030: aload 9
    //   2032: invokevirtual 454	android/graphics/Bitmap:getWidth	()I
    //   2035: aload 9
    //   2037: invokevirtual 457	android/graphics/Bitmap:getHeight	()I
    //   2040: invokestatic 472	java/lang/Math:max	(II)I
    //   2043: istore_1
    //   2044: aload 9
    //   2046: astore 12
    //   2048: aload 9
    //   2050: iload_1
    //   2051: iload_1
    //   2052: invokestatic 475	com/tencent/mm/sdk/platformtools/d:c	(Landroid/graphics/Bitmap;II)Landroid/graphics/Bitmap;
    //   2055: astore 9
    //   2057: aload 9
    //   2059: astore 11
    //   2061: aload 9
    //   2063: iconst_0
    //   2064: aload 9
    //   2066: invokevirtual 454	android/graphics/Bitmap:getWidth	()I
    //   2069: iconst_2
    //   2070: idiv
    //   2071: i2f
    //   2072: invokestatic 460	com/tencent/mm/sdk/platformtools/d:a	(Landroid/graphics/Bitmap;ZF)Landroid/graphics/Bitmap;
    //   2075: astore 9
    //   2077: goto -115 -> 1962
    //   2080: aload 9
    //   2082: astore 12
    //   2084: aload 9
    //   2086: iconst_0
    //   2087: aload_0
    //   2088: getfield 63	com/tencent/mm/ab/a/f/b:bTq	Lcom/tencent/mm/ab/a/a/c;
    //   2091: getfield 145	com/tencent/mm/ab/a/a/c:bTX	F
    //   2094: invokestatic 460	com/tencent/mm/sdk/platformtools/d:a	(Landroid/graphics/Bitmap;ZF)Landroid/graphics/Bitmap;
    //   2097: astore 9
    //   2099: goto -137 -> 1962
    //   2102: ldc 102
    //   2104: ldc_w 483
    //   2107: invokestatic 236	com/tencent/mm/sdk/platformtools/u:w	(Ljava/lang/String;Ljava/lang/String;)V
    //   2110: goto -1789 -> 321
    //   2113: astore 9
    //   2115: goto -1074 -> 1041
    //   2118: astore 9
    //   2120: goto -965 -> 1155
    //   2123: astore 12
    //   2125: aload 11
    //   2127: astore 9
    //   2129: aload 12
    //   2131: astore 11
    //   2133: goto -1297 -> 836
    //   2136: astore 11
    //   2138: aload 12
    //   2140: astore 10
    //   2142: goto -1306 -> 836
    //   2145: astore 11
    //   2147: aload 12
    //   2149: astore 9
    //   2151: goto -1315 -> 836
    //   2154: goto -192 -> 1962
    //   2157: goto -1951 -> 206
    //   2160: goto -1972 -> 188
    //   2163: iload_2
    //   2164: tableswitch	default:+36->2200, 1:+-284->1880, 2:+-284->1880, 3:+-284->1880, 4:+-284->1880, 5:+-886->1278
    //   2200: goto -1965 -> 235
    // Local variable table:
    //   start	length	slot	name	signature
    //   0	2203	0	this	b
    //   874	1178	1	i	int
    //   55	2109	2	j	int
    //   957	166	3	k	int
    //   46	1936	4	l1	long
    //   213	1767	6	l2	long
    //   63	1361	8	bool	boolean
    //   4	2094	9	localObject1	Object
    //   2113	1	9	localIOException1	java.io.IOException
    //   2118	1	9	localIOException2	java.io.IOException
    //   2127	23	9	localObject2	Object
    //   13	2128	10	localObject3	Object
    //   1	688	11	localObject4	Object
    //   831	17	11	localException1	Exception
    //   932	149	11	localObject5	Object
    //   1087	1	11	localException2	Exception
    //   1105	34	11	localBitmap	Bitmap
    //   1143	13	11	localObject6	Object
    //   1318	814	11	localObject7	Object
    //   2136	1	11	localException3	Exception
    //   2145	1	11	localException4	Exception
    //   208	1875	12	localObject8	Object
    //   2123	25	12	localException5	Exception
    //   892	457	13	localObject9	Object
    //   23	1945	14	str1	String
    //   72	1365	15	str2	String
    // Exception table:
    //   from	to	target	type
    //   15	151	831	java/lang/Exception
    //   188	206	831	java/lang/Exception
    //   445	515	831	java/lang/Exception
    //   548	573	831	java/lang/Exception
    //   576	596	831	java/lang/Exception
    //   601	619	831	java/lang/Exception
    //   619	656	831	java/lang/Exception
    //   701	747	831	java/lang/Exception
    //   750	777	831	java/lang/Exception
    //   780	788	831	java/lang/Exception
    //   794	820	831	java/lang/Exception
    //   820	828	831	java/lang/Exception
    //   859	867	831	java/lang/Exception
    //   1150	1155	831	java/lang/Exception
    //   1155	1158	831	java/lang/Exception
    //   1158	1185	831	java/lang/Exception
    //   1188	1237	831	java/lang/Exception
    //   1240	1275	831	java/lang/Exception
    //   210	215	1087	java/lang/Exception
    //   224	232	1087	java/lang/Exception
    //   239	246	1087	java/lang/Exception
    //   1036	1041	1087	java/lang/Exception
    //   1062	1080	1087	java/lang/Exception
    //   1282	1287	1087	java/lang/Exception
    //   1291	1299	1087	java/lang/Exception
    //   1303	1310	1087	java/lang/Exception
    //   1314	1320	1087	java/lang/Exception
    //   1324	1330	1087	java/lang/Exception
    //   1334	1342	1087	java/lang/Exception
    //   1346	1355	1087	java/lang/Exception
    //   1359	1374	1087	java/lang/Exception
    //   1884	1892	1087	java/lang/Exception
    //   1899	1909	1087	java/lang/Exception
    //   1913	1925	1087	java/lang/Exception
    //   1929	1942	1087	java/lang/Exception
    //   1946	1962	1087	java/lang/Exception
    //   2006	2020	1087	java/lang/Exception
    //   2030	2044	1087	java/lang/Exception
    //   2048	2057	1087	java/lang/Exception
    //   2084	2099	1087	java/lang/Exception
    //   875	894	1143	finally
    //   908	924	1143	finally
    //   928	934	1143	finally
    //   938	946	1143	finally
    //   950	958	1143	finally
    //   975	983	1143	finally
    //   987	995	1143	finally
    //   999	1017	1143	finally
    //   1100	1107	1143	finally
    //   1118	1128	1143	finally
    //   1036	1041	2113	java/io/IOException
    //   1150	1155	2118	java/io/IOException
    //   519	529	2123	java/lang/Exception
    //   533	545	2123	java/lang/Exception
    //   660	670	2123	java/lang/Exception
    //   674	686	2123	java/lang/Exception
    //   690	698	2123	java/lang/Exception
    //   1966	1974	2123	java/lang/Exception
    //   1978	1987	2123	java/lang/Exception
    //   1991	1999	2123	java/lang/Exception
    //   2061	2077	2123	java/lang/Exception
    //   1387	1398	2136	java/lang/Exception
    //   1402	1410	2136	java/lang/Exception
    //   1414	1420	2136	java/lang/Exception
    //   1432	1451	2136	java/lang/Exception
    //   1455	1463	2136	java/lang/Exception
    //   1467	1472	2136	java/lang/Exception
    //   1476	1504	2136	java/lang/Exception
    //   1856	1862	2136	java/lang/Exception
    //   1866	1874	2136	java/lang/Exception
    //   1513	1519	2145	java/lang/Exception
    //   1530	1537	2145	java/lang/Exception
    //   1541	1551	2145	java/lang/Exception
    //   1555	1575	2145	java/lang/Exception
    //   1579	1589	2145	java/lang/Exception
    //   1593	1629	2145	java/lang/Exception
    //   1633	1653	2145	java/lang/Exception
    //   1661	1671	2145	java/lang/Exception
    //   1675	1687	2145	java/lang/Exception
    //   1691	1704	2145	java/lang/Exception
    //   1708	1724	2145	java/lang/Exception
    //   1728	1736	2145	java/lang/Exception
    //   1740	1749	2145	java/lang/Exception
    //   1756	1770	2145	java/lang/Exception
    //   1780	1794	2145	java/lang/Exception
    //   1798	1807	2145	java/lang/Exception
    //   1811	1827	2145	java/lang/Exception
    //   1834	1849	2145	java/lang/Exception
  }
}

/* Location:
 * Qualified Name:     com.tencent.mm.ab.a.f.b
 * Java Class Version: 6 (50.0)
 * JD-Core Version:    0.7.1
 */