package com.google.android.gms.wearable.internal;

import android.os.Binder;
import android.os.IBinder;
import android.os.IInterface;
import android.os.Parcel;
import android.os.Parcelable.Creator;
import com.google.android.gms.common.data.DataHolder;
import com.google.android.gms.common.data.g;
import java.util.List;

public abstract interface w
  extends IInterface
{
  public abstract void a(DataHolder paramDataHolder);
  
  public abstract void a(AmsEntityUpdateParcelable paramAmsEntityUpdateParcelable);
  
  public abstract void a(AncsNotificationParcelable paramAncsNotificationParcelable);
  
  public abstract void a(CapabilityInfoParcelable paramCapabilityInfoParcelable);
  
  public abstract void a(ChannelEventParcelable paramChannelEventParcelable);
  
  public abstract void a(MessageEventParcelable paramMessageEventParcelable);
  
  public abstract void a(NodeParcelable paramNodeParcelable);
  
  public abstract void b(NodeParcelable paramNodeParcelable);
  
  public abstract void i(List<NodeParcelable> paramList);
  
  public static abstract class a
    extends Binder
    implements w
  {
    public a()
    {
      attachInterface(this, "com.google.android.gms.wearable.internal.IWearableListener");
    }
    
    public static w r(IBinder paramIBinder)
    {
      if (paramIBinder == null) {
        return null;
      }
      IInterface localIInterface = paramIBinder.queryLocalInterface("com.google.android.gms.wearable.internal.IWearableListener");
      if ((localIInterface != null) && ((localIInterface instanceof w))) {
        return (w)localIInterface;
      }
      return new a(paramIBinder);
    }
    
    public IBinder asBinder()
    {
      return this;
    }
    
    public boolean onTransact(int paramInt1, Parcel paramParcel1, Parcel paramParcel2, int paramInt2)
    {
      Object localObject2 = null;
      Object localObject3 = null;
      Object localObject4 = null;
      Object localObject5 = null;
      Object localObject6 = null;
      Object localObject7 = null;
      Object localObject8 = null;
      Object localObject1 = null;
      switch (paramInt1)
      {
      default: 
        return super.onTransact(paramInt1, paramParcel1, paramParcel2, paramInt2);
      case 1598968902: 
        paramParcel2.writeString("com.google.android.gms.wearable.internal.IWearableListener");
        return true;
      case 1: 
        paramParcel1.enforceInterface("com.google.android.gms.wearable.internal.IWearableListener");
        paramParcel2 = (Parcel)localObject1;
        if (paramParcel1.readInt() != 0)
        {
          paramParcel2 = DataHolder.CREATOR;
          paramParcel2 = g.a(paramParcel1);
        }
        a(paramParcel2);
        return true;
      case 2: 
        paramParcel1.enforceInterface("com.google.android.gms.wearable.internal.IWearableListener");
        paramParcel2 = (Parcel)localObject2;
        if (paramParcel1.readInt() != 0) {
          paramParcel2 = (MessageEventParcelable)MessageEventParcelable.CREATOR.createFromParcel(paramParcel1);
        }
        a(paramParcel2);
        return true;
      case 3: 
        paramParcel1.enforceInterface("com.google.android.gms.wearable.internal.IWearableListener");
        paramParcel2 = (Parcel)localObject3;
        if (paramParcel1.readInt() != 0) {
          paramParcel2 = (NodeParcelable)NodeParcelable.CREATOR.createFromParcel(paramParcel1);
        }
        a(paramParcel2);
        return true;
      case 4: 
        paramParcel1.enforceInterface("com.google.android.gms.wearable.internal.IWearableListener");
        paramParcel2 = (Parcel)localObject4;
        if (paramParcel1.readInt() != 0) {
          paramParcel2 = (NodeParcelable)NodeParcelable.CREATOR.createFromParcel(paramParcel1);
        }
        b(paramParcel2);
        return true;
      case 5: 
        paramParcel1.enforceInterface("com.google.android.gms.wearable.internal.IWearableListener");
        i(paramParcel1.createTypedArrayList(NodeParcelable.CREATOR));
        return true;
      case 6: 
        paramParcel1.enforceInterface("com.google.android.gms.wearable.internal.IWearableListener");
        paramParcel2 = (Parcel)localObject5;
        if (paramParcel1.readInt() != 0) {
          paramParcel2 = (AncsNotificationParcelable)AncsNotificationParcelable.CREATOR.createFromParcel(paramParcel1);
        }
        a(paramParcel2);
        return true;
      case 7: 
        paramParcel1.enforceInterface("com.google.android.gms.wearable.internal.IWearableListener");
        paramParcel2 = (Parcel)localObject6;
        if (paramParcel1.readInt() != 0) {
          paramParcel2 = (ChannelEventParcelable)ChannelEventParcelable.CREATOR.createFromParcel(paramParcel1);
        }
        a(paramParcel2);
        return true;
      case 8: 
        paramParcel1.enforceInterface("com.google.android.gms.wearable.internal.IWearableListener");
        paramParcel2 = (Parcel)localObject7;
        if (paramParcel1.readInt() != 0) {
          paramParcel2 = (CapabilityInfoParcelable)CapabilityInfoParcelable.CREATOR.createFromParcel(paramParcel1);
        }
        a(paramParcel2);
        return true;
      }
      paramParcel1.enforceInterface("com.google.android.gms.wearable.internal.IWearableListener");
      paramParcel2 = (Parcel)localObject8;
      if (paramParcel1.readInt() != 0) {
        paramParcel2 = (AmsEntityUpdateParcelable)AmsEntityUpdateParcelable.CREATOR.createFromParcel(paramParcel1);
      }
      a(paramParcel2);
      return true;
    }
    
    private static final class a
      implements w
    {
      private IBinder tD;
      
      a(IBinder paramIBinder)
      {
        tD = paramIBinder;
      }
      
      /* Error */
      public final void a(DataHolder paramDataHolder)
      {
        // Byte code:
        //   0: invokestatic 26	android/os/Parcel:obtain	()Landroid/os/Parcel;
        //   3: astore_2
        //   4: aload_2
        //   5: ldc 28
        //   7: invokevirtual 32	android/os/Parcel:writeInterfaceToken	(Ljava/lang/String;)V
        //   10: aload_1
        //   11: ifnull +33 -> 44
        //   14: aload_2
        //   15: iconst_1
        //   16: invokevirtual 36	android/os/Parcel:writeInt	(I)V
        //   19: aload_1
        //   20: aload_2
        //   21: iconst_0
        //   22: invokevirtual 42	com/google/android/gms/common/data/DataHolder:writeToParcel	(Landroid/os/Parcel;I)V
        //   25: aload_0
        //   26: getfield 18	com/google/android/gms/wearable/internal/w$a$a:tD	Landroid/os/IBinder;
        //   29: iconst_1
        //   30: aload_2
        //   31: aconst_null
        //   32: iconst_1
        //   33: invokeinterface 48 5 0
        //   38: pop
        //   39: aload_2
        //   40: invokevirtual 51	android/os/Parcel:recycle	()V
        //   43: return
        //   44: aload_2
        //   45: iconst_0
        //   46: invokevirtual 36	android/os/Parcel:writeInt	(I)V
        //   49: goto -24 -> 25
        //   52: astore_1
        //   53: aload_2
        //   54: invokevirtual 51	android/os/Parcel:recycle	()V
        //   57: aload_1
        //   58: athrow
        // Local variable table:
        //   start	length	slot	name	signature
        //   0	59	0	this	a
        //   0	59	1	paramDataHolder	DataHolder
        //   3	51	2	localParcel	Parcel
        // Exception table:
        //   from	to	target	type
        //   4	10	52	finally
        //   14	25	52	finally
        //   25	39	52	finally
        //   44	49	52	finally
      }
      
      /* Error */
      public final void a(AmsEntityUpdateParcelable paramAmsEntityUpdateParcelable)
      {
        // Byte code:
        //   0: invokestatic 26	android/os/Parcel:obtain	()Landroid/os/Parcel;
        //   3: astore_2
        //   4: aload_2
        //   5: ldc 28
        //   7: invokevirtual 32	android/os/Parcel:writeInterfaceToken	(Ljava/lang/String;)V
        //   10: aload_1
        //   11: ifnull +34 -> 45
        //   14: aload_2
        //   15: iconst_1
        //   16: invokevirtual 36	android/os/Parcel:writeInt	(I)V
        //   19: aload_1
        //   20: aload_2
        //   21: iconst_0
        //   22: invokevirtual 55	com/google/android/gms/wearable/internal/AmsEntityUpdateParcelable:writeToParcel	(Landroid/os/Parcel;I)V
        //   25: aload_0
        //   26: getfield 18	com/google/android/gms/wearable/internal/w$a$a:tD	Landroid/os/IBinder;
        //   29: bipush 9
        //   31: aload_2
        //   32: aconst_null
        //   33: iconst_1
        //   34: invokeinterface 48 5 0
        //   39: pop
        //   40: aload_2
        //   41: invokevirtual 51	android/os/Parcel:recycle	()V
        //   44: return
        //   45: aload_2
        //   46: iconst_0
        //   47: invokevirtual 36	android/os/Parcel:writeInt	(I)V
        //   50: goto -25 -> 25
        //   53: astore_1
        //   54: aload_2
        //   55: invokevirtual 51	android/os/Parcel:recycle	()V
        //   58: aload_1
        //   59: athrow
        // Local variable table:
        //   start	length	slot	name	signature
        //   0	60	0	this	a
        //   0	60	1	paramAmsEntityUpdateParcelable	AmsEntityUpdateParcelable
        //   3	52	2	localParcel	Parcel
        // Exception table:
        //   from	to	target	type
        //   4	10	53	finally
        //   14	25	53	finally
        //   25	40	53	finally
        //   45	50	53	finally
      }
      
      /* Error */
      public final void a(AncsNotificationParcelable paramAncsNotificationParcelable)
      {
        // Byte code:
        //   0: invokestatic 26	android/os/Parcel:obtain	()Landroid/os/Parcel;
        //   3: astore_2
        //   4: aload_2
        //   5: ldc 28
        //   7: invokevirtual 32	android/os/Parcel:writeInterfaceToken	(Ljava/lang/String;)V
        //   10: aload_1
        //   11: ifnull +34 -> 45
        //   14: aload_2
        //   15: iconst_1
        //   16: invokevirtual 36	android/os/Parcel:writeInt	(I)V
        //   19: aload_1
        //   20: aload_2
        //   21: iconst_0
        //   22: invokevirtual 59	com/google/android/gms/wearable/internal/AncsNotificationParcelable:writeToParcel	(Landroid/os/Parcel;I)V
        //   25: aload_0
        //   26: getfield 18	com/google/android/gms/wearable/internal/w$a$a:tD	Landroid/os/IBinder;
        //   29: bipush 6
        //   31: aload_2
        //   32: aconst_null
        //   33: iconst_1
        //   34: invokeinterface 48 5 0
        //   39: pop
        //   40: aload_2
        //   41: invokevirtual 51	android/os/Parcel:recycle	()V
        //   44: return
        //   45: aload_2
        //   46: iconst_0
        //   47: invokevirtual 36	android/os/Parcel:writeInt	(I)V
        //   50: goto -25 -> 25
        //   53: astore_1
        //   54: aload_2
        //   55: invokevirtual 51	android/os/Parcel:recycle	()V
        //   58: aload_1
        //   59: athrow
        // Local variable table:
        //   start	length	slot	name	signature
        //   0	60	0	this	a
        //   0	60	1	paramAncsNotificationParcelable	AncsNotificationParcelable
        //   3	52	2	localParcel	Parcel
        // Exception table:
        //   from	to	target	type
        //   4	10	53	finally
        //   14	25	53	finally
        //   25	40	53	finally
        //   45	50	53	finally
      }
      
      /* Error */
      public final void a(CapabilityInfoParcelable paramCapabilityInfoParcelable)
      {
        // Byte code:
        //   0: invokestatic 26	android/os/Parcel:obtain	()Landroid/os/Parcel;
        //   3: astore_2
        //   4: aload_2
        //   5: ldc 28
        //   7: invokevirtual 32	android/os/Parcel:writeInterfaceToken	(Ljava/lang/String;)V
        //   10: aload_1
        //   11: ifnull +34 -> 45
        //   14: aload_2
        //   15: iconst_1
        //   16: invokevirtual 36	android/os/Parcel:writeInt	(I)V
        //   19: aload_1
        //   20: aload_2
        //   21: iconst_0
        //   22: invokevirtual 63	com/google/android/gms/wearable/internal/CapabilityInfoParcelable:writeToParcel	(Landroid/os/Parcel;I)V
        //   25: aload_0
        //   26: getfield 18	com/google/android/gms/wearable/internal/w$a$a:tD	Landroid/os/IBinder;
        //   29: bipush 8
        //   31: aload_2
        //   32: aconst_null
        //   33: iconst_1
        //   34: invokeinterface 48 5 0
        //   39: pop
        //   40: aload_2
        //   41: invokevirtual 51	android/os/Parcel:recycle	()V
        //   44: return
        //   45: aload_2
        //   46: iconst_0
        //   47: invokevirtual 36	android/os/Parcel:writeInt	(I)V
        //   50: goto -25 -> 25
        //   53: astore_1
        //   54: aload_2
        //   55: invokevirtual 51	android/os/Parcel:recycle	()V
        //   58: aload_1
        //   59: athrow
        // Local variable table:
        //   start	length	slot	name	signature
        //   0	60	0	this	a
        //   0	60	1	paramCapabilityInfoParcelable	CapabilityInfoParcelable
        //   3	52	2	localParcel	Parcel
        // Exception table:
        //   from	to	target	type
        //   4	10	53	finally
        //   14	25	53	finally
        //   25	40	53	finally
        //   45	50	53	finally
      }
      
      /* Error */
      public final void a(ChannelEventParcelable paramChannelEventParcelable)
      {
        // Byte code:
        //   0: invokestatic 26	android/os/Parcel:obtain	()Landroid/os/Parcel;
        //   3: astore_2
        //   4: aload_2
        //   5: ldc 28
        //   7: invokevirtual 32	android/os/Parcel:writeInterfaceToken	(Ljava/lang/String;)V
        //   10: aload_1
        //   11: ifnull +34 -> 45
        //   14: aload_2
        //   15: iconst_1
        //   16: invokevirtual 36	android/os/Parcel:writeInt	(I)V
        //   19: aload_1
        //   20: aload_2
        //   21: iconst_0
        //   22: invokevirtual 67	com/google/android/gms/wearable/internal/ChannelEventParcelable:writeToParcel	(Landroid/os/Parcel;I)V
        //   25: aload_0
        //   26: getfield 18	com/google/android/gms/wearable/internal/w$a$a:tD	Landroid/os/IBinder;
        //   29: bipush 7
        //   31: aload_2
        //   32: aconst_null
        //   33: iconst_1
        //   34: invokeinterface 48 5 0
        //   39: pop
        //   40: aload_2
        //   41: invokevirtual 51	android/os/Parcel:recycle	()V
        //   44: return
        //   45: aload_2
        //   46: iconst_0
        //   47: invokevirtual 36	android/os/Parcel:writeInt	(I)V
        //   50: goto -25 -> 25
        //   53: astore_1
        //   54: aload_2
        //   55: invokevirtual 51	android/os/Parcel:recycle	()V
        //   58: aload_1
        //   59: athrow
        // Local variable table:
        //   start	length	slot	name	signature
        //   0	60	0	this	a
        //   0	60	1	paramChannelEventParcelable	ChannelEventParcelable
        //   3	52	2	localParcel	Parcel
        // Exception table:
        //   from	to	target	type
        //   4	10	53	finally
        //   14	25	53	finally
        //   25	40	53	finally
        //   45	50	53	finally
      }
      
      /* Error */
      public final void a(MessageEventParcelable paramMessageEventParcelable)
      {
        // Byte code:
        //   0: invokestatic 26	android/os/Parcel:obtain	()Landroid/os/Parcel;
        //   3: astore_2
        //   4: aload_2
        //   5: ldc 28
        //   7: invokevirtual 32	android/os/Parcel:writeInterfaceToken	(Ljava/lang/String;)V
        //   10: aload_1
        //   11: ifnull +33 -> 44
        //   14: aload_2
        //   15: iconst_1
        //   16: invokevirtual 36	android/os/Parcel:writeInt	(I)V
        //   19: aload_1
        //   20: aload_2
        //   21: iconst_0
        //   22: invokevirtual 71	com/google/android/gms/wearable/internal/MessageEventParcelable:writeToParcel	(Landroid/os/Parcel;I)V
        //   25: aload_0
        //   26: getfield 18	com/google/android/gms/wearable/internal/w$a$a:tD	Landroid/os/IBinder;
        //   29: iconst_2
        //   30: aload_2
        //   31: aconst_null
        //   32: iconst_1
        //   33: invokeinterface 48 5 0
        //   38: pop
        //   39: aload_2
        //   40: invokevirtual 51	android/os/Parcel:recycle	()V
        //   43: return
        //   44: aload_2
        //   45: iconst_0
        //   46: invokevirtual 36	android/os/Parcel:writeInt	(I)V
        //   49: goto -24 -> 25
        //   52: astore_1
        //   53: aload_2
        //   54: invokevirtual 51	android/os/Parcel:recycle	()V
        //   57: aload_1
        //   58: athrow
        // Local variable table:
        //   start	length	slot	name	signature
        //   0	59	0	this	a
        //   0	59	1	paramMessageEventParcelable	MessageEventParcelable
        //   3	51	2	localParcel	Parcel
        // Exception table:
        //   from	to	target	type
        //   4	10	52	finally
        //   14	25	52	finally
        //   25	39	52	finally
        //   44	49	52	finally
      }
      
      /* Error */
      public final void a(NodeParcelable paramNodeParcelable)
      {
        // Byte code:
        //   0: invokestatic 26	android/os/Parcel:obtain	()Landroid/os/Parcel;
        //   3: astore_2
        //   4: aload_2
        //   5: ldc 28
        //   7: invokevirtual 32	android/os/Parcel:writeInterfaceToken	(Ljava/lang/String;)V
        //   10: aload_1
        //   11: ifnull +33 -> 44
        //   14: aload_2
        //   15: iconst_1
        //   16: invokevirtual 36	android/os/Parcel:writeInt	(I)V
        //   19: aload_1
        //   20: aload_2
        //   21: iconst_0
        //   22: invokevirtual 75	com/google/android/gms/wearable/internal/NodeParcelable:writeToParcel	(Landroid/os/Parcel;I)V
        //   25: aload_0
        //   26: getfield 18	com/google/android/gms/wearable/internal/w$a$a:tD	Landroid/os/IBinder;
        //   29: iconst_3
        //   30: aload_2
        //   31: aconst_null
        //   32: iconst_1
        //   33: invokeinterface 48 5 0
        //   38: pop
        //   39: aload_2
        //   40: invokevirtual 51	android/os/Parcel:recycle	()V
        //   43: return
        //   44: aload_2
        //   45: iconst_0
        //   46: invokevirtual 36	android/os/Parcel:writeInt	(I)V
        //   49: goto -24 -> 25
        //   52: astore_1
        //   53: aload_2
        //   54: invokevirtual 51	android/os/Parcel:recycle	()V
        //   57: aload_1
        //   58: athrow
        // Local variable table:
        //   start	length	slot	name	signature
        //   0	59	0	this	a
        //   0	59	1	paramNodeParcelable	NodeParcelable
        //   3	51	2	localParcel	Parcel
        // Exception table:
        //   from	to	target	type
        //   4	10	52	finally
        //   14	25	52	finally
        //   25	39	52	finally
        //   44	49	52	finally
      }
      
      public final IBinder asBinder()
      {
        return tD;
      }
      
      /* Error */
      public final void b(NodeParcelable paramNodeParcelable)
      {
        // Byte code:
        //   0: invokestatic 26	android/os/Parcel:obtain	()Landroid/os/Parcel;
        //   3: astore_2
        //   4: aload_2
        //   5: ldc 28
        //   7: invokevirtual 32	android/os/Parcel:writeInterfaceToken	(Ljava/lang/String;)V
        //   10: aload_1
        //   11: ifnull +33 -> 44
        //   14: aload_2
        //   15: iconst_1
        //   16: invokevirtual 36	android/os/Parcel:writeInt	(I)V
        //   19: aload_1
        //   20: aload_2
        //   21: iconst_0
        //   22: invokevirtual 75	com/google/android/gms/wearable/internal/NodeParcelable:writeToParcel	(Landroid/os/Parcel;I)V
        //   25: aload_0
        //   26: getfield 18	com/google/android/gms/wearable/internal/w$a$a:tD	Landroid/os/IBinder;
        //   29: iconst_4
        //   30: aload_2
        //   31: aconst_null
        //   32: iconst_1
        //   33: invokeinterface 48 5 0
        //   38: pop
        //   39: aload_2
        //   40: invokevirtual 51	android/os/Parcel:recycle	()V
        //   43: return
        //   44: aload_2
        //   45: iconst_0
        //   46: invokevirtual 36	android/os/Parcel:writeInt	(I)V
        //   49: goto -24 -> 25
        //   52: astore_1
        //   53: aload_2
        //   54: invokevirtual 51	android/os/Parcel:recycle	()V
        //   57: aload_1
        //   58: athrow
        // Local variable table:
        //   start	length	slot	name	signature
        //   0	59	0	this	a
        //   0	59	1	paramNodeParcelable	NodeParcelable
        //   3	51	2	localParcel	Parcel
        // Exception table:
        //   from	to	target	type
        //   4	10	52	finally
        //   14	25	52	finally
        //   25	39	52	finally
        //   44	49	52	finally
      }
      
      public final void i(List<NodeParcelable> paramList)
      {
        Parcel localParcel = Parcel.obtain();
        try
        {
          localParcel.writeInterfaceToken("com.google.android.gms.wearable.internal.IWearableListener");
          localParcel.writeTypedList(paramList);
          tD.transact(5, localParcel, null, 1);
          return;
        }
        finally
        {
          localParcel.recycle();
        }
      }
    }
  }
}

/* Location:
 * Qualified Name:     com.google.android.gms.wearable.internal.w
 * Java Class Version: 6 (50.0)
 * JD-Core Version:    0.7.1
 */