package com.google.android.gms.wearable.internal;

import android.os.IBinder;

final class x$a$a
  implements x
{
  private IBinder tD;
  
  x$a$a(IBinder paramIBinder)
  {
    tD = paramIBinder;
  }
  
  /* Error */
  public final void a(v paramv)
  {
    // Byte code:
    //   0: invokestatic 26	android/os/Parcel:obtain	()Landroid/os/Parcel;
    //   3: astore_2
    //   4: invokestatic 26	android/os/Parcel:obtain	()Landroid/os/Parcel;
    //   7: astore_3
    //   8: aload_2
    //   9: ldc 28
    //   11: invokevirtual 32	android/os/Parcel:writeInterfaceToken	(Ljava/lang/String;)V
    //   14: aload_1
    //   15: ifnull +43 -> 58
    //   18: aload_1
    //   19: invokeinterface 38 1 0
    //   24: astore_1
    //   25: aload_2
    //   26: aload_1
    //   27: invokevirtual 41	android/os/Parcel:writeStrongBinder	(Landroid/os/IBinder;)V
    //   30: aload_0
    //   31: getfield 18	com/google/android/gms/wearable/internal/x$a$a:tD	Landroid/os/IBinder;
    //   34: bipush 22
    //   36: aload_2
    //   37: aload_3
    //   38: iconst_0
    //   39: invokeinterface 47 5 0
    //   44: pop
    //   45: aload_3
    //   46: invokevirtual 50	android/os/Parcel:readException	()V
    //   49: aload_3
    //   50: invokevirtual 53	android/os/Parcel:recycle	()V
    //   53: aload_2
    //   54: invokevirtual 53	android/os/Parcel:recycle	()V
    //   57: return
    //   58: aconst_null
    //   59: astore_1
    //   60: goto -35 -> 25
    //   63: astore_1
    //   64: aload_3
    //   65: invokevirtual 53	android/os/Parcel:recycle	()V
    //   68: aload_2
    //   69: invokevirtual 53	android/os/Parcel:recycle	()V
    //   72: aload_1
    //   73: athrow
    // Local variable table:
    //   start	length	slot	name	signature
    //   0	74	0	this	a
    //   0	74	1	paramv	v
    //   3	66	2	localParcel1	android.os.Parcel
    //   7	58	3	localParcel2	android.os.Parcel
    // Exception table:
    //   from	to	target	type
    //   8	14	63	finally
    //   18	25	63	finally
    //   25	49	63	finally
  }
  
  /* Error */
  public final void a(v paramv, byte paramByte)
  {
    // Byte code:
    //   0: invokestatic 26	android/os/Parcel:obtain	()Landroid/os/Parcel;
    //   3: astore_3
    //   4: invokestatic 26	android/os/Parcel:obtain	()Landroid/os/Parcel;
    //   7: astore 4
    //   9: aload_3
    //   10: ldc 28
    //   12: invokevirtual 32	android/os/Parcel:writeInterfaceToken	(Ljava/lang/String;)V
    //   15: aload_1
    //   16: ifnull +51 -> 67
    //   19: aload_1
    //   20: invokeinterface 38 1 0
    //   25: astore_1
    //   26: aload_3
    //   27: aload_1
    //   28: invokevirtual 41	android/os/Parcel:writeStrongBinder	(Landroid/os/IBinder;)V
    //   31: aload_3
    //   32: iload_2
    //   33: invokevirtual 58	android/os/Parcel:writeByte	(B)V
    //   36: aload_0
    //   37: getfield 18	com/google/android/gms/wearable/internal/x$a$a:tD	Landroid/os/IBinder;
    //   40: bipush 53
    //   42: aload_3
    //   43: aload 4
    //   45: iconst_0
    //   46: invokeinterface 47 5 0
    //   51: pop
    //   52: aload 4
    //   54: invokevirtual 50	android/os/Parcel:readException	()V
    //   57: aload 4
    //   59: invokevirtual 53	android/os/Parcel:recycle	()V
    //   62: aload_3
    //   63: invokevirtual 53	android/os/Parcel:recycle	()V
    //   66: return
    //   67: aconst_null
    //   68: astore_1
    //   69: goto -43 -> 26
    //   72: astore_1
    //   73: aload 4
    //   75: invokevirtual 53	android/os/Parcel:recycle	()V
    //   78: aload_3
    //   79: invokevirtual 53	android/os/Parcel:recycle	()V
    //   82: aload_1
    //   83: athrow
    // Local variable table:
    //   start	length	slot	name	signature
    //   0	84	0	this	a
    //   0	84	1	paramv	v
    //   0	84	2	paramByte	byte
    //   3	76	3	localParcel1	android.os.Parcel
    //   7	67	4	localParcel2	android.os.Parcel
    // Exception table:
    //   from	to	target	type
    //   9	15	72	finally
    //   19	26	72	finally
    //   26	57	72	finally
  }
  
  /* Error */
  public final void a(v paramv, int paramInt)
  {
    // Byte code:
    //   0: invokestatic 26	android/os/Parcel:obtain	()Landroid/os/Parcel;
    //   3: astore_3
    //   4: invokestatic 26	android/os/Parcel:obtain	()Landroid/os/Parcel;
    //   7: astore 4
    //   9: aload_3
    //   10: ldc 28
    //   12: invokevirtual 32	android/os/Parcel:writeInterfaceToken	(Ljava/lang/String;)V
    //   15: aload_1
    //   16: ifnull +51 -> 67
    //   19: aload_1
    //   20: invokeinterface 38 1 0
    //   25: astore_1
    //   26: aload_3
    //   27: aload_1
    //   28: invokevirtual 41	android/os/Parcel:writeStrongBinder	(Landroid/os/IBinder;)V
    //   31: aload_3
    //   32: iload_2
    //   33: invokevirtual 63	android/os/Parcel:writeInt	(I)V
    //   36: aload_0
    //   37: getfield 18	com/google/android/gms/wearable/internal/x$a$a:tD	Landroid/os/IBinder;
    //   40: bipush 43
    //   42: aload_3
    //   43: aload 4
    //   45: iconst_0
    //   46: invokeinterface 47 5 0
    //   51: pop
    //   52: aload 4
    //   54: invokevirtual 50	android/os/Parcel:readException	()V
    //   57: aload 4
    //   59: invokevirtual 53	android/os/Parcel:recycle	()V
    //   62: aload_3
    //   63: invokevirtual 53	android/os/Parcel:recycle	()V
    //   66: return
    //   67: aconst_null
    //   68: astore_1
    //   69: goto -43 -> 26
    //   72: astore_1
    //   73: aload 4
    //   75: invokevirtual 53	android/os/Parcel:recycle	()V
    //   78: aload_3
    //   79: invokevirtual 53	android/os/Parcel:recycle	()V
    //   82: aload_1
    //   83: athrow
    // Local variable table:
    //   start	length	slot	name	signature
    //   0	84	0	this	a
    //   0	84	1	paramv	v
    //   0	84	2	paramInt	int
    //   3	76	3	localParcel1	android.os.Parcel
    //   7	67	4	localParcel2	android.os.Parcel
    // Exception table:
    //   from	to	target	type
    //   9	15	72	finally
    //   19	26	72	finally
    //   26	57	72	finally
  }
  
  /* Error */
  public final void a(v paramv, android.net.Uri paramUri)
  {
    // Byte code:
    //   0: invokestatic 26	android/os/Parcel:obtain	()Landroid/os/Parcel;
    //   3: astore_3
    //   4: invokestatic 26	android/os/Parcel:obtain	()Landroid/os/Parcel;
    //   7: astore 4
    //   9: aload_3
    //   10: ldc 28
    //   12: invokevirtual 32	android/os/Parcel:writeInterfaceToken	(Ljava/lang/String;)V
    //   15: aload_1
    //   16: ifnull +61 -> 77
    //   19: aload_1
    //   20: invokeinterface 38 1 0
    //   25: astore_1
    //   26: aload_3
    //   27: aload_1
    //   28: invokevirtual 41	android/os/Parcel:writeStrongBinder	(Landroid/os/IBinder;)V
    //   31: aload_2
    //   32: ifnull +50 -> 82
    //   35: aload_3
    //   36: iconst_1
    //   37: invokevirtual 63	android/os/Parcel:writeInt	(I)V
    //   40: aload_2
    //   41: aload_3
    //   42: iconst_0
    //   43: invokevirtual 70	android/net/Uri:writeToParcel	(Landroid/os/Parcel;I)V
    //   46: aload_0
    //   47: getfield 18	com/google/android/gms/wearable/internal/x$a$a:tD	Landroid/os/IBinder;
    //   50: bipush 7
    //   52: aload_3
    //   53: aload 4
    //   55: iconst_0
    //   56: invokeinterface 47 5 0
    //   61: pop
    //   62: aload 4
    //   64: invokevirtual 50	android/os/Parcel:readException	()V
    //   67: aload 4
    //   69: invokevirtual 53	android/os/Parcel:recycle	()V
    //   72: aload_3
    //   73: invokevirtual 53	android/os/Parcel:recycle	()V
    //   76: return
    //   77: aconst_null
    //   78: astore_1
    //   79: goto -53 -> 26
    //   82: aload_3
    //   83: iconst_0
    //   84: invokevirtual 63	android/os/Parcel:writeInt	(I)V
    //   87: goto -41 -> 46
    //   90: astore_1
    //   91: aload 4
    //   93: invokevirtual 53	android/os/Parcel:recycle	()V
    //   96: aload_3
    //   97: invokevirtual 53	android/os/Parcel:recycle	()V
    //   100: aload_1
    //   101: athrow
    // Local variable table:
    //   start	length	slot	name	signature
    //   0	102	0	this	a
    //   0	102	1	paramv	v
    //   0	102	2	paramUri	android.net.Uri
    //   3	94	3	localParcel1	android.os.Parcel
    //   7	85	4	localParcel2	android.os.Parcel
    // Exception table:
    //   from	to	target	type
    //   9	15	90	finally
    //   19	26	90	finally
    //   26	31	90	finally
    //   35	46	90	finally
    //   46	67	90	finally
    //   82	87	90	finally
  }
  
  /* Error */
  public final void a(v paramv, android.net.Uri paramUri, int paramInt)
  {
    // Byte code:
    //   0: invokestatic 26	android/os/Parcel:obtain	()Landroid/os/Parcel;
    //   3: astore 4
    //   5: invokestatic 26	android/os/Parcel:obtain	()Landroid/os/Parcel;
    //   8: astore 5
    //   10: aload 4
    //   12: ldc 28
    //   14: invokevirtual 32	android/os/Parcel:writeInterfaceToken	(Ljava/lang/String;)V
    //   17: aload_1
    //   18: ifnull +72 -> 90
    //   21: aload_1
    //   22: invokeinterface 38 1 0
    //   27: astore_1
    //   28: aload 4
    //   30: aload_1
    //   31: invokevirtual 41	android/os/Parcel:writeStrongBinder	(Landroid/os/IBinder;)V
    //   34: aload_2
    //   35: ifnull +60 -> 95
    //   38: aload 4
    //   40: iconst_1
    //   41: invokevirtual 63	android/os/Parcel:writeInt	(I)V
    //   44: aload_2
    //   45: aload 4
    //   47: iconst_0
    //   48: invokevirtual 70	android/net/Uri:writeToParcel	(Landroid/os/Parcel;I)V
    //   51: aload 4
    //   53: iload_3
    //   54: invokevirtual 63	android/os/Parcel:writeInt	(I)V
    //   57: aload_0
    //   58: getfield 18	com/google/android/gms/wearable/internal/x$a$a:tD	Landroid/os/IBinder;
    //   61: bipush 40
    //   63: aload 4
    //   65: aload 5
    //   67: iconst_0
    //   68: invokeinterface 47 5 0
    //   73: pop
    //   74: aload 5
    //   76: invokevirtual 50	android/os/Parcel:readException	()V
    //   79: aload 5
    //   81: invokevirtual 53	android/os/Parcel:recycle	()V
    //   84: aload 4
    //   86: invokevirtual 53	android/os/Parcel:recycle	()V
    //   89: return
    //   90: aconst_null
    //   91: astore_1
    //   92: goto -64 -> 28
    //   95: aload 4
    //   97: iconst_0
    //   98: invokevirtual 63	android/os/Parcel:writeInt	(I)V
    //   101: goto -50 -> 51
    //   104: astore_1
    //   105: aload 5
    //   107: invokevirtual 53	android/os/Parcel:recycle	()V
    //   110: aload 4
    //   112: invokevirtual 53	android/os/Parcel:recycle	()V
    //   115: aload_1
    //   116: athrow
    // Local variable table:
    //   start	length	slot	name	signature
    //   0	117	0	this	a
    //   0	117	1	paramv	v
    //   0	117	2	paramUri	android.net.Uri
    //   0	117	3	paramInt	int
    //   3	108	4	localParcel1	android.os.Parcel
    //   8	98	5	localParcel2	android.os.Parcel
    // Exception table:
    //   from	to	target	type
    //   10	17	104	finally
    //   21	28	104	finally
    //   28	34	104	finally
    //   38	51	104	finally
    //   51	79	104	finally
    //   95	101	104	finally
  }
  
  /* Error */
  public final void a(v paramv, com.google.android.gms.wearable.Asset paramAsset)
  {
    // Byte code:
    //   0: invokestatic 26	android/os/Parcel:obtain	()Landroid/os/Parcel;
    //   3: astore_3
    //   4: invokestatic 26	android/os/Parcel:obtain	()Landroid/os/Parcel;
    //   7: astore 4
    //   9: aload_3
    //   10: ldc 28
    //   12: invokevirtual 32	android/os/Parcel:writeInterfaceToken	(Ljava/lang/String;)V
    //   15: aload_1
    //   16: ifnull +61 -> 77
    //   19: aload_1
    //   20: invokeinterface 38 1 0
    //   25: astore_1
    //   26: aload_3
    //   27: aload_1
    //   28: invokevirtual 41	android/os/Parcel:writeStrongBinder	(Landroid/os/IBinder;)V
    //   31: aload_2
    //   32: ifnull +50 -> 82
    //   35: aload_3
    //   36: iconst_1
    //   37: invokevirtual 63	android/os/Parcel:writeInt	(I)V
    //   40: aload_2
    //   41: aload_3
    //   42: iconst_0
    //   43: invokevirtual 75	com/google/android/gms/wearable/Asset:writeToParcel	(Landroid/os/Parcel;I)V
    //   46: aload_0
    //   47: getfield 18	com/google/android/gms/wearable/internal/x$a$a:tD	Landroid/os/IBinder;
    //   50: bipush 13
    //   52: aload_3
    //   53: aload 4
    //   55: iconst_0
    //   56: invokeinterface 47 5 0
    //   61: pop
    //   62: aload 4
    //   64: invokevirtual 50	android/os/Parcel:readException	()V
    //   67: aload 4
    //   69: invokevirtual 53	android/os/Parcel:recycle	()V
    //   72: aload_3
    //   73: invokevirtual 53	android/os/Parcel:recycle	()V
    //   76: return
    //   77: aconst_null
    //   78: astore_1
    //   79: goto -53 -> 26
    //   82: aload_3
    //   83: iconst_0
    //   84: invokevirtual 63	android/os/Parcel:writeInt	(I)V
    //   87: goto -41 -> 46
    //   90: astore_1
    //   91: aload 4
    //   93: invokevirtual 53	android/os/Parcel:recycle	()V
    //   96: aload_3
    //   97: invokevirtual 53	android/os/Parcel:recycle	()V
    //   100: aload_1
    //   101: athrow
    // Local variable table:
    //   start	length	slot	name	signature
    //   0	102	0	this	a
    //   0	102	1	paramv	v
    //   0	102	2	paramAsset	com.google.android.gms.wearable.Asset
    //   3	94	3	localParcel1	android.os.Parcel
    //   7	85	4	localParcel2	android.os.Parcel
    // Exception table:
    //   from	to	target	type
    //   9	15	90	finally
    //   19	26	90	finally
    //   26	31	90	finally
    //   35	46	90	finally
    //   46	67	90	finally
    //   82	87	90	finally
  }
  
  /* Error */
  public final void a(v paramv, com.google.android.gms.wearable.ConnectionConfiguration paramConnectionConfiguration)
  {
    // Byte code:
    //   0: invokestatic 26	android/os/Parcel:obtain	()Landroid/os/Parcel;
    //   3: astore_3
    //   4: invokestatic 26	android/os/Parcel:obtain	()Landroid/os/Parcel;
    //   7: astore 4
    //   9: aload_3
    //   10: ldc 28
    //   12: invokevirtual 32	android/os/Parcel:writeInterfaceToken	(Ljava/lang/String;)V
    //   15: aload_1
    //   16: ifnull +61 -> 77
    //   19: aload_1
    //   20: invokeinterface 38 1 0
    //   25: astore_1
    //   26: aload_3
    //   27: aload_1
    //   28: invokevirtual 41	android/os/Parcel:writeStrongBinder	(Landroid/os/IBinder;)V
    //   31: aload_2
    //   32: ifnull +50 -> 82
    //   35: aload_3
    //   36: iconst_1
    //   37: invokevirtual 63	android/os/Parcel:writeInt	(I)V
    //   40: aload_2
    //   41: aload_3
    //   42: iconst_0
    //   43: invokevirtual 79	com/google/android/gms/wearable/ConnectionConfiguration:writeToParcel	(Landroid/os/Parcel;I)V
    //   46: aload_0
    //   47: getfield 18	com/google/android/gms/wearable/internal/x$a$a:tD	Landroid/os/IBinder;
    //   50: bipush 20
    //   52: aload_3
    //   53: aload 4
    //   55: iconst_0
    //   56: invokeinterface 47 5 0
    //   61: pop
    //   62: aload 4
    //   64: invokevirtual 50	android/os/Parcel:readException	()V
    //   67: aload 4
    //   69: invokevirtual 53	android/os/Parcel:recycle	()V
    //   72: aload_3
    //   73: invokevirtual 53	android/os/Parcel:recycle	()V
    //   76: return
    //   77: aconst_null
    //   78: astore_1
    //   79: goto -53 -> 26
    //   82: aload_3
    //   83: iconst_0
    //   84: invokevirtual 63	android/os/Parcel:writeInt	(I)V
    //   87: goto -41 -> 46
    //   90: astore_1
    //   91: aload 4
    //   93: invokevirtual 53	android/os/Parcel:recycle	()V
    //   96: aload_3
    //   97: invokevirtual 53	android/os/Parcel:recycle	()V
    //   100: aload_1
    //   101: athrow
    // Local variable table:
    //   start	length	slot	name	signature
    //   0	102	0	this	a
    //   0	102	1	paramv	v
    //   0	102	2	paramConnectionConfiguration	com.google.android.gms.wearable.ConnectionConfiguration
    //   3	94	3	localParcel1	android.os.Parcel
    //   7	85	4	localParcel2	android.os.Parcel
    // Exception table:
    //   from	to	target	type
    //   9	15	90	finally
    //   19	26	90	finally
    //   26	31	90	finally
    //   35	46	90	finally
    //   46	67	90	finally
    //   82	87	90	finally
  }
  
  /* Error */
  public final void a(v paramv, com.google.android.gms.wearable.PutDataRequest paramPutDataRequest)
  {
    // Byte code:
    //   0: invokestatic 26	android/os/Parcel:obtain	()Landroid/os/Parcel;
    //   3: astore_3
    //   4: invokestatic 26	android/os/Parcel:obtain	()Landroid/os/Parcel;
    //   7: astore 4
    //   9: aload_3
    //   10: ldc 28
    //   12: invokevirtual 32	android/os/Parcel:writeInterfaceToken	(Ljava/lang/String;)V
    //   15: aload_1
    //   16: ifnull +61 -> 77
    //   19: aload_1
    //   20: invokeinterface 38 1 0
    //   25: astore_1
    //   26: aload_3
    //   27: aload_1
    //   28: invokevirtual 41	android/os/Parcel:writeStrongBinder	(Landroid/os/IBinder;)V
    //   31: aload_2
    //   32: ifnull +50 -> 82
    //   35: aload_3
    //   36: iconst_1
    //   37: invokevirtual 63	android/os/Parcel:writeInt	(I)V
    //   40: aload_2
    //   41: aload_3
    //   42: iconst_0
    //   43: invokevirtual 83	com/google/android/gms/wearable/PutDataRequest:writeToParcel	(Landroid/os/Parcel;I)V
    //   46: aload_0
    //   47: getfield 18	com/google/android/gms/wearable/internal/x$a$a:tD	Landroid/os/IBinder;
    //   50: bipush 6
    //   52: aload_3
    //   53: aload 4
    //   55: iconst_0
    //   56: invokeinterface 47 5 0
    //   61: pop
    //   62: aload 4
    //   64: invokevirtual 50	android/os/Parcel:readException	()V
    //   67: aload 4
    //   69: invokevirtual 53	android/os/Parcel:recycle	()V
    //   72: aload_3
    //   73: invokevirtual 53	android/os/Parcel:recycle	()V
    //   76: return
    //   77: aconst_null
    //   78: astore_1
    //   79: goto -53 -> 26
    //   82: aload_3
    //   83: iconst_0
    //   84: invokevirtual 63	android/os/Parcel:writeInt	(I)V
    //   87: goto -41 -> 46
    //   90: astore_1
    //   91: aload 4
    //   93: invokevirtual 53	android/os/Parcel:recycle	()V
    //   96: aload_3
    //   97: invokevirtual 53	android/os/Parcel:recycle	()V
    //   100: aload_1
    //   101: athrow
    // Local variable table:
    //   start	length	slot	name	signature
    //   0	102	0	this	a
    //   0	102	1	paramv	v
    //   0	102	2	paramPutDataRequest	com.google.android.gms.wearable.PutDataRequest
    //   3	94	3	localParcel1	android.os.Parcel
    //   7	85	4	localParcel2	android.os.Parcel
    // Exception table:
    //   from	to	target	type
    //   9	15	90	finally
    //   19	26	90	finally
    //   26	31	90	finally
    //   35	46	90	finally
    //   46	67	90	finally
    //   82	87	90	finally
  }
  
  /* Error */
  public final void a(v paramv, AddListenerRequest paramAddListenerRequest)
  {
    // Byte code:
    //   0: invokestatic 26	android/os/Parcel:obtain	()Landroid/os/Parcel;
    //   3: astore_3
    //   4: invokestatic 26	android/os/Parcel:obtain	()Landroid/os/Parcel;
    //   7: astore 4
    //   9: aload_3
    //   10: ldc 28
    //   12: invokevirtual 32	android/os/Parcel:writeInterfaceToken	(Ljava/lang/String;)V
    //   15: aload_1
    //   16: ifnull +61 -> 77
    //   19: aload_1
    //   20: invokeinterface 38 1 0
    //   25: astore_1
    //   26: aload_3
    //   27: aload_1
    //   28: invokevirtual 41	android/os/Parcel:writeStrongBinder	(Landroid/os/IBinder;)V
    //   31: aload_2
    //   32: ifnull +50 -> 82
    //   35: aload_3
    //   36: iconst_1
    //   37: invokevirtual 63	android/os/Parcel:writeInt	(I)V
    //   40: aload_2
    //   41: aload_3
    //   42: iconst_0
    //   43: invokevirtual 87	com/google/android/gms/wearable/internal/AddListenerRequest:writeToParcel	(Landroid/os/Parcel;I)V
    //   46: aload_0
    //   47: getfield 18	com/google/android/gms/wearable/internal/x$a$a:tD	Landroid/os/IBinder;
    //   50: bipush 16
    //   52: aload_3
    //   53: aload 4
    //   55: iconst_0
    //   56: invokeinterface 47 5 0
    //   61: pop
    //   62: aload 4
    //   64: invokevirtual 50	android/os/Parcel:readException	()V
    //   67: aload 4
    //   69: invokevirtual 53	android/os/Parcel:recycle	()V
    //   72: aload_3
    //   73: invokevirtual 53	android/os/Parcel:recycle	()V
    //   76: return
    //   77: aconst_null
    //   78: astore_1
    //   79: goto -53 -> 26
    //   82: aload_3
    //   83: iconst_0
    //   84: invokevirtual 63	android/os/Parcel:writeInt	(I)V
    //   87: goto -41 -> 46
    //   90: astore_1
    //   91: aload 4
    //   93: invokevirtual 53	android/os/Parcel:recycle	()V
    //   96: aload_3
    //   97: invokevirtual 53	android/os/Parcel:recycle	()V
    //   100: aload_1
    //   101: athrow
    // Local variable table:
    //   start	length	slot	name	signature
    //   0	102	0	this	a
    //   0	102	1	paramv	v
    //   0	102	2	paramAddListenerRequest	AddListenerRequest
    //   3	94	3	localParcel1	android.os.Parcel
    //   7	85	4	localParcel2	android.os.Parcel
    // Exception table:
    //   from	to	target	type
    //   9	15	90	finally
    //   19	26	90	finally
    //   26	31	90	finally
    //   35	46	90	finally
    //   46	67	90	finally
    //   82	87	90	finally
  }
  
  /* Error */
  public final void a(v paramv, AncsNotificationParcelable paramAncsNotificationParcelable)
  {
    // Byte code:
    //   0: invokestatic 26	android/os/Parcel:obtain	()Landroid/os/Parcel;
    //   3: astore_3
    //   4: invokestatic 26	android/os/Parcel:obtain	()Landroid/os/Parcel;
    //   7: astore 4
    //   9: aload_3
    //   10: ldc 28
    //   12: invokevirtual 32	android/os/Parcel:writeInterfaceToken	(Ljava/lang/String;)V
    //   15: aload_1
    //   16: ifnull +61 -> 77
    //   19: aload_1
    //   20: invokeinterface 38 1 0
    //   25: astore_1
    //   26: aload_3
    //   27: aload_1
    //   28: invokevirtual 41	android/os/Parcel:writeStrongBinder	(Landroid/os/IBinder;)V
    //   31: aload_2
    //   32: ifnull +50 -> 82
    //   35: aload_3
    //   36: iconst_1
    //   37: invokevirtual 63	android/os/Parcel:writeInt	(I)V
    //   40: aload_2
    //   41: aload_3
    //   42: iconst_0
    //   43: invokevirtual 91	com/google/android/gms/wearable/internal/AncsNotificationParcelable:writeToParcel	(Landroid/os/Parcel;I)V
    //   46: aload_0
    //   47: getfield 18	com/google/android/gms/wearable/internal/x$a$a:tD	Landroid/os/IBinder;
    //   50: bipush 27
    //   52: aload_3
    //   53: aload 4
    //   55: iconst_0
    //   56: invokeinterface 47 5 0
    //   61: pop
    //   62: aload 4
    //   64: invokevirtual 50	android/os/Parcel:readException	()V
    //   67: aload 4
    //   69: invokevirtual 53	android/os/Parcel:recycle	()V
    //   72: aload_3
    //   73: invokevirtual 53	android/os/Parcel:recycle	()V
    //   76: return
    //   77: aconst_null
    //   78: astore_1
    //   79: goto -53 -> 26
    //   82: aload_3
    //   83: iconst_0
    //   84: invokevirtual 63	android/os/Parcel:writeInt	(I)V
    //   87: goto -41 -> 46
    //   90: astore_1
    //   91: aload 4
    //   93: invokevirtual 53	android/os/Parcel:recycle	()V
    //   96: aload_3
    //   97: invokevirtual 53	android/os/Parcel:recycle	()V
    //   100: aload_1
    //   101: athrow
    // Local variable table:
    //   start	length	slot	name	signature
    //   0	102	0	this	a
    //   0	102	1	paramv	v
    //   0	102	2	paramAncsNotificationParcelable	AncsNotificationParcelable
    //   3	94	3	localParcel1	android.os.Parcel
    //   7	85	4	localParcel2	android.os.Parcel
    // Exception table:
    //   from	to	target	type
    //   9	15	90	finally
    //   19	26	90	finally
    //   26	31	90	finally
    //   35	46	90	finally
    //   46	67	90	finally
    //   82	87	90	finally
  }
  
  /* Error */
  public final void a(v paramv, RemoveListenerRequest paramRemoveListenerRequest)
  {
    // Byte code:
    //   0: invokestatic 26	android/os/Parcel:obtain	()Landroid/os/Parcel;
    //   3: astore_3
    //   4: invokestatic 26	android/os/Parcel:obtain	()Landroid/os/Parcel;
    //   7: astore 4
    //   9: aload_3
    //   10: ldc 28
    //   12: invokevirtual 32	android/os/Parcel:writeInterfaceToken	(Ljava/lang/String;)V
    //   15: aload_1
    //   16: ifnull +61 -> 77
    //   19: aload_1
    //   20: invokeinterface 38 1 0
    //   25: astore_1
    //   26: aload_3
    //   27: aload_1
    //   28: invokevirtual 41	android/os/Parcel:writeStrongBinder	(Landroid/os/IBinder;)V
    //   31: aload_2
    //   32: ifnull +50 -> 82
    //   35: aload_3
    //   36: iconst_1
    //   37: invokevirtual 63	android/os/Parcel:writeInt	(I)V
    //   40: aload_2
    //   41: aload_3
    //   42: iconst_0
    //   43: invokevirtual 95	com/google/android/gms/wearable/internal/RemoveListenerRequest:writeToParcel	(Landroid/os/Parcel;I)V
    //   46: aload_0
    //   47: getfield 18	com/google/android/gms/wearable/internal/x$a$a:tD	Landroid/os/IBinder;
    //   50: bipush 17
    //   52: aload_3
    //   53: aload 4
    //   55: iconst_0
    //   56: invokeinterface 47 5 0
    //   61: pop
    //   62: aload 4
    //   64: invokevirtual 50	android/os/Parcel:readException	()V
    //   67: aload 4
    //   69: invokevirtual 53	android/os/Parcel:recycle	()V
    //   72: aload_3
    //   73: invokevirtual 53	android/os/Parcel:recycle	()V
    //   76: return
    //   77: aconst_null
    //   78: astore_1
    //   79: goto -53 -> 26
    //   82: aload_3
    //   83: iconst_0
    //   84: invokevirtual 63	android/os/Parcel:writeInt	(I)V
    //   87: goto -41 -> 46
    //   90: astore_1
    //   91: aload 4
    //   93: invokevirtual 53	android/os/Parcel:recycle	()V
    //   96: aload_3
    //   97: invokevirtual 53	android/os/Parcel:recycle	()V
    //   100: aload_1
    //   101: athrow
    // Local variable table:
    //   start	length	slot	name	signature
    //   0	102	0	this	a
    //   0	102	1	paramv	v
    //   0	102	2	paramRemoveListenerRequest	RemoveListenerRequest
    //   3	94	3	localParcel1	android.os.Parcel
    //   7	85	4	localParcel2	android.os.Parcel
    // Exception table:
    //   from	to	target	type
    //   9	15	90	finally
    //   19	26	90	finally
    //   26	31	90	finally
    //   35	46	90	finally
    //   46	67	90	finally
    //   82	87	90	finally
  }
  
  /* Error */
  public final void a(v paramv, u paramu, String paramString)
  {
    // Byte code:
    //   0: aconst_null
    //   1: astore 4
    //   3: invokestatic 26	android/os/Parcel:obtain	()Landroid/os/Parcel;
    //   6: astore 5
    //   8: invokestatic 26	android/os/Parcel:obtain	()Landroid/os/Parcel;
    //   11: astore 6
    //   13: aload 5
    //   15: ldc 28
    //   17: invokevirtual 32	android/os/Parcel:writeInterfaceToken	(Ljava/lang/String;)V
    //   20: aload_1
    //   21: ifnull +75 -> 96
    //   24: aload_1
    //   25: invokeinterface 38 1 0
    //   30: astore_1
    //   31: aload 5
    //   33: aload_1
    //   34: invokevirtual 41	android/os/Parcel:writeStrongBinder	(Landroid/os/IBinder;)V
    //   37: aload 4
    //   39: astore_1
    //   40: aload_2
    //   41: ifnull +10 -> 51
    //   44: aload_2
    //   45: invokeinterface 99 1 0
    //   50: astore_1
    //   51: aload 5
    //   53: aload_1
    //   54: invokevirtual 41	android/os/Parcel:writeStrongBinder	(Landroid/os/IBinder;)V
    //   57: aload 5
    //   59: aload_3
    //   60: invokevirtual 102	android/os/Parcel:writeString	(Ljava/lang/String;)V
    //   63: aload_0
    //   64: getfield 18	com/google/android/gms/wearable/internal/x$a$a:tD	Landroid/os/IBinder;
    //   67: bipush 34
    //   69: aload 5
    //   71: aload 6
    //   73: iconst_0
    //   74: invokeinterface 47 5 0
    //   79: pop
    //   80: aload 6
    //   82: invokevirtual 50	android/os/Parcel:readException	()V
    //   85: aload 6
    //   87: invokevirtual 53	android/os/Parcel:recycle	()V
    //   90: aload 5
    //   92: invokevirtual 53	android/os/Parcel:recycle	()V
    //   95: return
    //   96: aconst_null
    //   97: astore_1
    //   98: goto -67 -> 31
    //   101: astore_1
    //   102: aload 6
    //   104: invokevirtual 53	android/os/Parcel:recycle	()V
    //   107: aload 5
    //   109: invokevirtual 53	android/os/Parcel:recycle	()V
    //   112: aload_1
    //   113: athrow
    // Local variable table:
    //   start	length	slot	name	signature
    //   0	114	0	this	a
    //   0	114	1	paramv	v
    //   0	114	2	paramu	u
    //   0	114	3	paramString	String
    //   1	37	4	localObject	Object
    //   6	102	5	localParcel1	android.os.Parcel
    //   11	92	6	localParcel2	android.os.Parcel
    // Exception table:
    //   from	to	target	type
    //   13	20	101	finally
    //   24	31	101	finally
    //   31	37	101	finally
    //   44	51	101	finally
    //   51	85	101	finally
  }
  
  /* Error */
  public final void a(v paramv, String paramString)
  {
    // Byte code:
    //   0: invokestatic 26	android/os/Parcel:obtain	()Landroid/os/Parcel;
    //   3: astore_3
    //   4: invokestatic 26	android/os/Parcel:obtain	()Landroid/os/Parcel;
    //   7: astore 4
    //   9: aload_3
    //   10: ldc 28
    //   12: invokevirtual 32	android/os/Parcel:writeInterfaceToken	(Ljava/lang/String;)V
    //   15: aload_1
    //   16: ifnull +51 -> 67
    //   19: aload_1
    //   20: invokeinterface 38 1 0
    //   25: astore_1
    //   26: aload_3
    //   27: aload_1
    //   28: invokevirtual 41	android/os/Parcel:writeStrongBinder	(Landroid/os/IBinder;)V
    //   31: aload_3
    //   32: aload_2
    //   33: invokevirtual 102	android/os/Parcel:writeString	(Ljava/lang/String;)V
    //   36: aload_0
    //   37: getfield 18	com/google/android/gms/wearable/internal/x$a$a:tD	Landroid/os/IBinder;
    //   40: bipush 21
    //   42: aload_3
    //   43: aload 4
    //   45: iconst_0
    //   46: invokeinterface 47 5 0
    //   51: pop
    //   52: aload 4
    //   54: invokevirtual 50	android/os/Parcel:readException	()V
    //   57: aload 4
    //   59: invokevirtual 53	android/os/Parcel:recycle	()V
    //   62: aload_3
    //   63: invokevirtual 53	android/os/Parcel:recycle	()V
    //   66: return
    //   67: aconst_null
    //   68: astore_1
    //   69: goto -43 -> 26
    //   72: astore_1
    //   73: aload 4
    //   75: invokevirtual 53	android/os/Parcel:recycle	()V
    //   78: aload_3
    //   79: invokevirtual 53	android/os/Parcel:recycle	()V
    //   82: aload_1
    //   83: athrow
    // Local variable table:
    //   start	length	slot	name	signature
    //   0	84	0	this	a
    //   0	84	1	paramv	v
    //   0	84	2	paramString	String
    //   3	76	3	localParcel1	android.os.Parcel
    //   7	67	4	localParcel2	android.os.Parcel
    // Exception table:
    //   from	to	target	type
    //   9	15	72	finally
    //   19	26	72	finally
    //   26	57	72	finally
  }
  
  /* Error */
  public final void a(v paramv, String paramString, int paramInt)
  {
    // Byte code:
    //   0: invokestatic 26	android/os/Parcel:obtain	()Landroid/os/Parcel;
    //   3: astore 4
    //   5: invokestatic 26	android/os/Parcel:obtain	()Landroid/os/Parcel;
    //   8: astore 5
    //   10: aload 4
    //   12: ldc 28
    //   14: invokevirtual 32	android/os/Parcel:writeInterfaceToken	(Ljava/lang/String;)V
    //   17: aload_1
    //   18: ifnull +61 -> 79
    //   21: aload_1
    //   22: invokeinterface 38 1 0
    //   27: astore_1
    //   28: aload 4
    //   30: aload_1
    //   31: invokevirtual 41	android/os/Parcel:writeStrongBinder	(Landroid/os/IBinder;)V
    //   34: aload 4
    //   36: aload_2
    //   37: invokevirtual 102	android/os/Parcel:writeString	(Ljava/lang/String;)V
    //   40: aload 4
    //   42: iload_3
    //   43: invokevirtual 63	android/os/Parcel:writeInt	(I)V
    //   46: aload_0
    //   47: getfield 18	com/google/android/gms/wearable/internal/x$a$a:tD	Landroid/os/IBinder;
    //   50: bipush 42
    //   52: aload 4
    //   54: aload 5
    //   56: iconst_0
    //   57: invokeinterface 47 5 0
    //   62: pop
    //   63: aload 5
    //   65: invokevirtual 50	android/os/Parcel:readException	()V
    //   68: aload 5
    //   70: invokevirtual 53	android/os/Parcel:recycle	()V
    //   73: aload 4
    //   75: invokevirtual 53	android/os/Parcel:recycle	()V
    //   78: return
    //   79: aconst_null
    //   80: astore_1
    //   81: goto -53 -> 28
    //   84: astore_1
    //   85: aload 5
    //   87: invokevirtual 53	android/os/Parcel:recycle	()V
    //   90: aload 4
    //   92: invokevirtual 53	android/os/Parcel:recycle	()V
    //   95: aload_1
    //   96: athrow
    // Local variable table:
    //   start	length	slot	name	signature
    //   0	97	0	this	a
    //   0	97	1	paramv	v
    //   0	97	2	paramString	String
    //   0	97	3	paramInt	int
    //   3	88	4	localParcel1	android.os.Parcel
    //   8	78	5	localParcel2	android.os.Parcel
    // Exception table:
    //   from	to	target	type
    //   10	17	84	finally
    //   21	28	84	finally
    //   28	68	84	finally
  }
  
  /* Error */
  public final void a(v paramv, String paramString, android.os.ParcelFileDescriptor paramParcelFileDescriptor)
  {
    // Byte code:
    //   0: invokestatic 26	android/os/Parcel:obtain	()Landroid/os/Parcel;
    //   3: astore 4
    //   5: invokestatic 26	android/os/Parcel:obtain	()Landroid/os/Parcel;
    //   8: astore 5
    //   10: aload 4
    //   12: ldc 28
    //   14: invokevirtual 32	android/os/Parcel:writeInterfaceToken	(Ljava/lang/String;)V
    //   17: aload_1
    //   18: ifnull +72 -> 90
    //   21: aload_1
    //   22: invokeinterface 38 1 0
    //   27: astore_1
    //   28: aload 4
    //   30: aload_1
    //   31: invokevirtual 41	android/os/Parcel:writeStrongBinder	(Landroid/os/IBinder;)V
    //   34: aload 4
    //   36: aload_2
    //   37: invokevirtual 102	android/os/Parcel:writeString	(Ljava/lang/String;)V
    //   40: aload_3
    //   41: ifnull +54 -> 95
    //   44: aload 4
    //   46: iconst_1
    //   47: invokevirtual 63	android/os/Parcel:writeInt	(I)V
    //   50: aload_3
    //   51: aload 4
    //   53: iconst_0
    //   54: invokevirtual 108	android/os/ParcelFileDescriptor:writeToParcel	(Landroid/os/Parcel;I)V
    //   57: aload_0
    //   58: getfield 18	com/google/android/gms/wearable/internal/x$a$a:tD	Landroid/os/IBinder;
    //   61: bipush 38
    //   63: aload 4
    //   65: aload 5
    //   67: iconst_0
    //   68: invokeinterface 47 5 0
    //   73: pop
    //   74: aload 5
    //   76: invokevirtual 50	android/os/Parcel:readException	()V
    //   79: aload 5
    //   81: invokevirtual 53	android/os/Parcel:recycle	()V
    //   84: aload 4
    //   86: invokevirtual 53	android/os/Parcel:recycle	()V
    //   89: return
    //   90: aconst_null
    //   91: astore_1
    //   92: goto -64 -> 28
    //   95: aload 4
    //   97: iconst_0
    //   98: invokevirtual 63	android/os/Parcel:writeInt	(I)V
    //   101: goto -44 -> 57
    //   104: astore_1
    //   105: aload 5
    //   107: invokevirtual 53	android/os/Parcel:recycle	()V
    //   110: aload 4
    //   112: invokevirtual 53	android/os/Parcel:recycle	()V
    //   115: aload_1
    //   116: athrow
    // Local variable table:
    //   start	length	slot	name	signature
    //   0	117	0	this	a
    //   0	117	1	paramv	v
    //   0	117	2	paramString	String
    //   0	117	3	paramParcelFileDescriptor	android.os.ParcelFileDescriptor
    //   3	108	4	localParcel1	android.os.Parcel
    //   8	98	5	localParcel2	android.os.Parcel
    // Exception table:
    //   from	to	target	type
    //   10	17	104	finally
    //   21	28	104	finally
    //   28	40	104	finally
    //   44	57	104	finally
    //   57	79	104	finally
    //   95	101	104	finally
  }
  
  /* Error */
  public final void a(v paramv, String paramString, android.os.ParcelFileDescriptor paramParcelFileDescriptor, long paramLong1, long paramLong2)
  {
    // Byte code:
    //   0: invokestatic 26	android/os/Parcel:obtain	()Landroid/os/Parcel;
    //   3: astore 8
    //   5: invokestatic 26	android/os/Parcel:obtain	()Landroid/os/Parcel;
    //   8: astore 9
    //   10: aload 8
    //   12: ldc 28
    //   14: invokevirtual 32	android/os/Parcel:writeInterfaceToken	(Ljava/lang/String;)V
    //   17: aload_1
    //   18: ifnull +86 -> 104
    //   21: aload_1
    //   22: invokeinterface 38 1 0
    //   27: astore_1
    //   28: aload 8
    //   30: aload_1
    //   31: invokevirtual 41	android/os/Parcel:writeStrongBinder	(Landroid/os/IBinder;)V
    //   34: aload 8
    //   36: aload_2
    //   37: invokevirtual 102	android/os/Parcel:writeString	(Ljava/lang/String;)V
    //   40: aload_3
    //   41: ifnull +68 -> 109
    //   44: aload 8
    //   46: iconst_1
    //   47: invokevirtual 63	android/os/Parcel:writeInt	(I)V
    //   50: aload_3
    //   51: aload 8
    //   53: iconst_0
    //   54: invokevirtual 108	android/os/ParcelFileDescriptor:writeToParcel	(Landroid/os/Parcel;I)V
    //   57: aload 8
    //   59: lload 4
    //   61: invokevirtual 113	android/os/Parcel:writeLong	(J)V
    //   64: aload 8
    //   66: lload 6
    //   68: invokevirtual 113	android/os/Parcel:writeLong	(J)V
    //   71: aload_0
    //   72: getfield 18	com/google/android/gms/wearable/internal/x$a$a:tD	Landroid/os/IBinder;
    //   75: bipush 39
    //   77: aload 8
    //   79: aload 9
    //   81: iconst_0
    //   82: invokeinterface 47 5 0
    //   87: pop
    //   88: aload 9
    //   90: invokevirtual 50	android/os/Parcel:readException	()V
    //   93: aload 9
    //   95: invokevirtual 53	android/os/Parcel:recycle	()V
    //   98: aload 8
    //   100: invokevirtual 53	android/os/Parcel:recycle	()V
    //   103: return
    //   104: aconst_null
    //   105: astore_1
    //   106: goto -78 -> 28
    //   109: aload 8
    //   111: iconst_0
    //   112: invokevirtual 63	android/os/Parcel:writeInt	(I)V
    //   115: goto -58 -> 57
    //   118: astore_1
    //   119: aload 9
    //   121: invokevirtual 53	android/os/Parcel:recycle	()V
    //   124: aload 8
    //   126: invokevirtual 53	android/os/Parcel:recycle	()V
    //   129: aload_1
    //   130: athrow
    // Local variable table:
    //   start	length	slot	name	signature
    //   0	131	0	this	a
    //   0	131	1	paramv	v
    //   0	131	2	paramString	String
    //   0	131	3	paramParcelFileDescriptor	android.os.ParcelFileDescriptor
    //   0	131	4	paramLong1	long
    //   0	131	6	paramLong2	long
    //   3	122	8	localParcel1	android.os.Parcel
    //   8	112	9	localParcel2	android.os.Parcel
    // Exception table:
    //   from	to	target	type
    //   10	17	118	finally
    //   21	28	118	finally
    //   28	40	118	finally
    //   44	57	118	finally
    //   57	93	118	finally
    //   109	115	118	finally
  }
  
  /* Error */
  public final void a(v paramv, String paramString1, String paramString2)
  {
    // Byte code:
    //   0: invokestatic 26	android/os/Parcel:obtain	()Landroid/os/Parcel;
    //   3: astore 4
    //   5: invokestatic 26	android/os/Parcel:obtain	()Landroid/os/Parcel;
    //   8: astore 5
    //   10: aload 4
    //   12: ldc 28
    //   14: invokevirtual 32	android/os/Parcel:writeInterfaceToken	(Ljava/lang/String;)V
    //   17: aload_1
    //   18: ifnull +61 -> 79
    //   21: aload_1
    //   22: invokeinterface 38 1 0
    //   27: astore_1
    //   28: aload 4
    //   30: aload_1
    //   31: invokevirtual 41	android/os/Parcel:writeStrongBinder	(Landroid/os/IBinder;)V
    //   34: aload 4
    //   36: aload_2
    //   37: invokevirtual 102	android/os/Parcel:writeString	(Ljava/lang/String;)V
    //   40: aload 4
    //   42: aload_3
    //   43: invokevirtual 102	android/os/Parcel:writeString	(Ljava/lang/String;)V
    //   46: aload_0
    //   47: getfield 18	com/google/android/gms/wearable/internal/x$a$a:tD	Landroid/os/IBinder;
    //   50: bipush 31
    //   52: aload 4
    //   54: aload 5
    //   56: iconst_0
    //   57: invokeinterface 47 5 0
    //   62: pop
    //   63: aload 5
    //   65: invokevirtual 50	android/os/Parcel:readException	()V
    //   68: aload 5
    //   70: invokevirtual 53	android/os/Parcel:recycle	()V
    //   73: aload 4
    //   75: invokevirtual 53	android/os/Parcel:recycle	()V
    //   78: return
    //   79: aconst_null
    //   80: astore_1
    //   81: goto -53 -> 28
    //   84: astore_1
    //   85: aload 5
    //   87: invokevirtual 53	android/os/Parcel:recycle	()V
    //   90: aload 4
    //   92: invokevirtual 53	android/os/Parcel:recycle	()V
    //   95: aload_1
    //   96: athrow
    // Local variable table:
    //   start	length	slot	name	signature
    //   0	97	0	this	a
    //   0	97	1	paramv	v
    //   0	97	2	paramString1	String
    //   0	97	3	paramString2	String
    //   3	88	4	localParcel1	android.os.Parcel
    //   8	78	5	localParcel2	android.os.Parcel
    // Exception table:
    //   from	to	target	type
    //   10	17	84	finally
    //   21	28	84	finally
    //   28	68	84	finally
  }
  
  /* Error */
  public final void a(v paramv, String paramString1, String paramString2, byte[] paramArrayOfByte)
  {
    // Byte code:
    //   0: invokestatic 26	android/os/Parcel:obtain	()Landroid/os/Parcel;
    //   3: astore 5
    //   5: invokestatic 26	android/os/Parcel:obtain	()Landroid/os/Parcel;
    //   8: astore 6
    //   10: aload 5
    //   12: ldc 28
    //   14: invokevirtual 32	android/os/Parcel:writeInterfaceToken	(Ljava/lang/String;)V
    //   17: aload_1
    //   18: ifnull +68 -> 86
    //   21: aload_1
    //   22: invokeinterface 38 1 0
    //   27: astore_1
    //   28: aload 5
    //   30: aload_1
    //   31: invokevirtual 41	android/os/Parcel:writeStrongBinder	(Landroid/os/IBinder;)V
    //   34: aload 5
    //   36: aload_2
    //   37: invokevirtual 102	android/os/Parcel:writeString	(Ljava/lang/String;)V
    //   40: aload 5
    //   42: aload_3
    //   43: invokevirtual 102	android/os/Parcel:writeString	(Ljava/lang/String;)V
    //   46: aload 5
    //   48: aload 4
    //   50: invokevirtual 119	android/os/Parcel:writeByteArray	([B)V
    //   53: aload_0
    //   54: getfield 18	com/google/android/gms/wearable/internal/x$a$a:tD	Landroid/os/IBinder;
    //   57: bipush 12
    //   59: aload 5
    //   61: aload 6
    //   63: iconst_0
    //   64: invokeinterface 47 5 0
    //   69: pop
    //   70: aload 6
    //   72: invokevirtual 50	android/os/Parcel:readException	()V
    //   75: aload 6
    //   77: invokevirtual 53	android/os/Parcel:recycle	()V
    //   80: aload 5
    //   82: invokevirtual 53	android/os/Parcel:recycle	()V
    //   85: return
    //   86: aconst_null
    //   87: astore_1
    //   88: goto -60 -> 28
    //   91: astore_1
    //   92: aload 6
    //   94: invokevirtual 53	android/os/Parcel:recycle	()V
    //   97: aload 5
    //   99: invokevirtual 53	android/os/Parcel:recycle	()V
    //   102: aload_1
    //   103: athrow
    // Local variable table:
    //   start	length	slot	name	signature
    //   0	104	0	this	a
    //   0	104	1	paramv	v
    //   0	104	2	paramString1	String
    //   0	104	3	paramString2	String
    //   0	104	4	paramArrayOfByte	byte[]
    //   3	95	5	localParcel1	android.os.Parcel
    //   8	85	6	localParcel2	android.os.Parcel
    // Exception table:
    //   from	to	target	type
    //   10	17	91	finally
    //   21	28	91	finally
    //   28	75	91	finally
  }
  
  /* Error */
  public final void a(v paramv, boolean paramBoolean)
  {
    // Byte code:
    //   0: iconst_0
    //   1: istore_3
    //   2: invokestatic 26	android/os/Parcel:obtain	()Landroid/os/Parcel;
    //   5: astore 4
    //   7: invokestatic 26	android/os/Parcel:obtain	()Landroid/os/Parcel;
    //   10: astore 5
    //   12: aload 4
    //   14: ldc 28
    //   16: invokevirtual 32	android/os/Parcel:writeInterfaceToken	(Ljava/lang/String;)V
    //   19: aload_1
    //   20: ifnull +61 -> 81
    //   23: aload_1
    //   24: invokeinterface 38 1 0
    //   29: astore_1
    //   30: aload 4
    //   32: aload_1
    //   33: invokevirtual 41	android/os/Parcel:writeStrongBinder	(Landroid/os/IBinder;)V
    //   36: iload_2
    //   37: ifeq +5 -> 42
    //   40: iconst_1
    //   41: istore_3
    //   42: aload 4
    //   44: iload_3
    //   45: invokevirtual 63	android/os/Parcel:writeInt	(I)V
    //   48: aload_0
    //   49: getfield 18	com/google/android/gms/wearable/internal/x$a$a:tD	Landroid/os/IBinder;
    //   52: bipush 48
    //   54: aload 4
    //   56: aload 5
    //   58: iconst_0
    //   59: invokeinterface 47 5 0
    //   64: pop
    //   65: aload 5
    //   67: invokevirtual 50	android/os/Parcel:readException	()V
    //   70: aload 5
    //   72: invokevirtual 53	android/os/Parcel:recycle	()V
    //   75: aload 4
    //   77: invokevirtual 53	android/os/Parcel:recycle	()V
    //   80: return
    //   81: aconst_null
    //   82: astore_1
    //   83: goto -53 -> 30
    //   86: astore_1
    //   87: aload 5
    //   89: invokevirtual 53	android/os/Parcel:recycle	()V
    //   92: aload 4
    //   94: invokevirtual 53	android/os/Parcel:recycle	()V
    //   97: aload_1
    //   98: athrow
    // Local variable table:
    //   start	length	slot	name	signature
    //   0	99	0	this	a
    //   0	99	1	paramv	v
    //   0	99	2	paramBoolean	boolean
    //   1	44	3	i	int
    //   5	88	4	localParcel1	android.os.Parcel
    //   10	78	5	localParcel2	android.os.Parcel
    // Exception table:
    //   from	to	target	type
    //   12	19	86	finally
    //   23	30	86	finally
    //   30	36	86	finally
    //   42	70	86	finally
  }
  
  public final IBinder asBinder()
  {
    return tD;
  }
  
  /* Error */
  public final void b(v paramv)
  {
    // Byte code:
    //   0: invokestatic 26	android/os/Parcel:obtain	()Landroid/os/Parcel;
    //   3: astore_2
    //   4: invokestatic 26	android/os/Parcel:obtain	()Landroid/os/Parcel;
    //   7: astore_3
    //   8: aload_2
    //   9: ldc 28
    //   11: invokevirtual 32	android/os/Parcel:writeInterfaceToken	(Ljava/lang/String;)V
    //   14: aload_1
    //   15: ifnull +43 -> 58
    //   18: aload_1
    //   19: invokeinterface 38 1 0
    //   24: astore_1
    //   25: aload_2
    //   26: aload_1
    //   27: invokevirtual 41	android/os/Parcel:writeStrongBinder	(Landroid/os/IBinder;)V
    //   30: aload_0
    //   31: getfield 18	com/google/android/gms/wearable/internal/x$a$a:tD	Landroid/os/IBinder;
    //   34: bipush 8
    //   36: aload_2
    //   37: aload_3
    //   38: iconst_0
    //   39: invokeinterface 47 5 0
    //   44: pop
    //   45: aload_3
    //   46: invokevirtual 50	android/os/Parcel:readException	()V
    //   49: aload_3
    //   50: invokevirtual 53	android/os/Parcel:recycle	()V
    //   53: aload_2
    //   54: invokevirtual 53	android/os/Parcel:recycle	()V
    //   57: return
    //   58: aconst_null
    //   59: astore_1
    //   60: goto -35 -> 25
    //   63: astore_1
    //   64: aload_3
    //   65: invokevirtual 53	android/os/Parcel:recycle	()V
    //   68: aload_2
    //   69: invokevirtual 53	android/os/Parcel:recycle	()V
    //   72: aload_1
    //   73: athrow
    // Local variable table:
    //   start	length	slot	name	signature
    //   0	74	0	this	a
    //   0	74	1	paramv	v
    //   3	66	2	localParcel1	android.os.Parcel
    //   7	58	3	localParcel2	android.os.Parcel
    // Exception table:
    //   from	to	target	type
    //   8	14	63	finally
    //   18	25	63	finally
    //   25	49	63	finally
  }
  
  /* Error */
  public final void b(v paramv, int paramInt)
  {
    // Byte code:
    //   0: invokestatic 26	android/os/Parcel:obtain	()Landroid/os/Parcel;
    //   3: astore_3
    //   4: invokestatic 26	android/os/Parcel:obtain	()Landroid/os/Parcel;
    //   7: astore 4
    //   9: aload_3
    //   10: ldc 28
    //   12: invokevirtual 32	android/os/Parcel:writeInterfaceToken	(Ljava/lang/String;)V
    //   15: aload_1
    //   16: ifnull +51 -> 67
    //   19: aload_1
    //   20: invokeinterface 38 1 0
    //   25: astore_1
    //   26: aload_3
    //   27: aload_1
    //   28: invokevirtual 41	android/os/Parcel:writeStrongBinder	(Landroid/os/IBinder;)V
    //   31: aload_3
    //   32: iload_2
    //   33: invokevirtual 63	android/os/Parcel:writeInt	(I)V
    //   36: aload_0
    //   37: getfield 18	com/google/android/gms/wearable/internal/x$a$a:tD	Landroid/os/IBinder;
    //   40: bipush 28
    //   42: aload_3
    //   43: aload 4
    //   45: iconst_0
    //   46: invokeinterface 47 5 0
    //   51: pop
    //   52: aload 4
    //   54: invokevirtual 50	android/os/Parcel:readException	()V
    //   57: aload 4
    //   59: invokevirtual 53	android/os/Parcel:recycle	()V
    //   62: aload_3
    //   63: invokevirtual 53	android/os/Parcel:recycle	()V
    //   66: return
    //   67: aconst_null
    //   68: astore_1
    //   69: goto -43 -> 26
    //   72: astore_1
    //   73: aload 4
    //   75: invokevirtual 53	android/os/Parcel:recycle	()V
    //   78: aload_3
    //   79: invokevirtual 53	android/os/Parcel:recycle	()V
    //   82: aload_1
    //   83: athrow
    // Local variable table:
    //   start	length	slot	name	signature
    //   0	84	0	this	a
    //   0	84	1	paramv	v
    //   0	84	2	paramInt	int
    //   3	76	3	localParcel1	android.os.Parcel
    //   7	67	4	localParcel2	android.os.Parcel
    // Exception table:
    //   from	to	target	type
    //   9	15	72	finally
    //   19	26	72	finally
    //   26	57	72	finally
  }
  
  /* Error */
  public final void b(v paramv, android.net.Uri paramUri)
  {
    // Byte code:
    //   0: invokestatic 26	android/os/Parcel:obtain	()Landroid/os/Parcel;
    //   3: astore_3
    //   4: invokestatic 26	android/os/Parcel:obtain	()Landroid/os/Parcel;
    //   7: astore 4
    //   9: aload_3
    //   10: ldc 28
    //   12: invokevirtual 32	android/os/Parcel:writeInterfaceToken	(Ljava/lang/String;)V
    //   15: aload_1
    //   16: ifnull +61 -> 77
    //   19: aload_1
    //   20: invokeinterface 38 1 0
    //   25: astore_1
    //   26: aload_3
    //   27: aload_1
    //   28: invokevirtual 41	android/os/Parcel:writeStrongBinder	(Landroid/os/IBinder;)V
    //   31: aload_2
    //   32: ifnull +50 -> 82
    //   35: aload_3
    //   36: iconst_1
    //   37: invokevirtual 63	android/os/Parcel:writeInt	(I)V
    //   40: aload_2
    //   41: aload_3
    //   42: iconst_0
    //   43: invokevirtual 70	android/net/Uri:writeToParcel	(Landroid/os/Parcel;I)V
    //   46: aload_0
    //   47: getfield 18	com/google/android/gms/wearable/internal/x$a$a:tD	Landroid/os/IBinder;
    //   50: bipush 9
    //   52: aload_3
    //   53: aload 4
    //   55: iconst_0
    //   56: invokeinterface 47 5 0
    //   61: pop
    //   62: aload 4
    //   64: invokevirtual 50	android/os/Parcel:readException	()V
    //   67: aload 4
    //   69: invokevirtual 53	android/os/Parcel:recycle	()V
    //   72: aload_3
    //   73: invokevirtual 53	android/os/Parcel:recycle	()V
    //   76: return
    //   77: aconst_null
    //   78: astore_1
    //   79: goto -53 -> 26
    //   82: aload_3
    //   83: iconst_0
    //   84: invokevirtual 63	android/os/Parcel:writeInt	(I)V
    //   87: goto -41 -> 46
    //   90: astore_1
    //   91: aload 4
    //   93: invokevirtual 53	android/os/Parcel:recycle	()V
    //   96: aload_3
    //   97: invokevirtual 53	android/os/Parcel:recycle	()V
    //   100: aload_1
    //   101: athrow
    // Local variable table:
    //   start	length	slot	name	signature
    //   0	102	0	this	a
    //   0	102	1	paramv	v
    //   0	102	2	paramUri	android.net.Uri
    //   3	94	3	localParcel1	android.os.Parcel
    //   7	85	4	localParcel2	android.os.Parcel
    // Exception table:
    //   from	to	target	type
    //   9	15	90	finally
    //   19	26	90	finally
    //   26	31	90	finally
    //   35	46	90	finally
    //   46	67	90	finally
    //   82	87	90	finally
  }
  
  /* Error */
  public final void b(v paramv, android.net.Uri paramUri, int paramInt)
  {
    // Byte code:
    //   0: invokestatic 26	android/os/Parcel:obtain	()Landroid/os/Parcel;
    //   3: astore 4
    //   5: invokestatic 26	android/os/Parcel:obtain	()Landroid/os/Parcel;
    //   8: astore 5
    //   10: aload 4
    //   12: ldc 28
    //   14: invokevirtual 32	android/os/Parcel:writeInterfaceToken	(Ljava/lang/String;)V
    //   17: aload_1
    //   18: ifnull +72 -> 90
    //   21: aload_1
    //   22: invokeinterface 38 1 0
    //   27: astore_1
    //   28: aload 4
    //   30: aload_1
    //   31: invokevirtual 41	android/os/Parcel:writeStrongBinder	(Landroid/os/IBinder;)V
    //   34: aload_2
    //   35: ifnull +60 -> 95
    //   38: aload 4
    //   40: iconst_1
    //   41: invokevirtual 63	android/os/Parcel:writeInt	(I)V
    //   44: aload_2
    //   45: aload 4
    //   47: iconst_0
    //   48: invokevirtual 70	android/net/Uri:writeToParcel	(Landroid/os/Parcel;I)V
    //   51: aload 4
    //   53: iload_3
    //   54: invokevirtual 63	android/os/Parcel:writeInt	(I)V
    //   57: aload_0
    //   58: getfield 18	com/google/android/gms/wearable/internal/x$a$a:tD	Landroid/os/IBinder;
    //   61: bipush 41
    //   63: aload 4
    //   65: aload 5
    //   67: iconst_0
    //   68: invokeinterface 47 5 0
    //   73: pop
    //   74: aload 5
    //   76: invokevirtual 50	android/os/Parcel:readException	()V
    //   79: aload 5
    //   81: invokevirtual 53	android/os/Parcel:recycle	()V
    //   84: aload 4
    //   86: invokevirtual 53	android/os/Parcel:recycle	()V
    //   89: return
    //   90: aconst_null
    //   91: astore_1
    //   92: goto -64 -> 28
    //   95: aload 4
    //   97: iconst_0
    //   98: invokevirtual 63	android/os/Parcel:writeInt	(I)V
    //   101: goto -50 -> 51
    //   104: astore_1
    //   105: aload 5
    //   107: invokevirtual 53	android/os/Parcel:recycle	()V
    //   110: aload 4
    //   112: invokevirtual 53	android/os/Parcel:recycle	()V
    //   115: aload_1
    //   116: athrow
    // Local variable table:
    //   start	length	slot	name	signature
    //   0	117	0	this	a
    //   0	117	1	paramv	v
    //   0	117	2	paramUri	android.net.Uri
    //   0	117	3	paramInt	int
    //   3	108	4	localParcel1	android.os.Parcel
    //   8	98	5	localParcel2	android.os.Parcel
    // Exception table:
    //   from	to	target	type
    //   10	17	104	finally
    //   21	28	104	finally
    //   28	34	104	finally
    //   38	51	104	finally
    //   51	79	104	finally
    //   95	101	104	finally
  }
  
  /* Error */
  public final void b(v paramv, com.google.android.gms.wearable.ConnectionConfiguration paramConnectionConfiguration)
  {
    // Byte code:
    //   0: invokestatic 26	android/os/Parcel:obtain	()Landroid/os/Parcel;
    //   3: astore_3
    //   4: invokestatic 26	android/os/Parcel:obtain	()Landroid/os/Parcel;
    //   7: astore 4
    //   9: aload_3
    //   10: ldc 28
    //   12: invokevirtual 32	android/os/Parcel:writeInterfaceToken	(Ljava/lang/String;)V
    //   15: aload_1
    //   16: ifnull +60 -> 76
    //   19: aload_1
    //   20: invokeinterface 38 1 0
    //   25: astore_1
    //   26: aload_3
    //   27: aload_1
    //   28: invokevirtual 41	android/os/Parcel:writeStrongBinder	(Landroid/os/IBinder;)V
    //   31: aload_2
    //   32: ifnull +49 -> 81
    //   35: aload_3
    //   36: iconst_1
    //   37: invokevirtual 63	android/os/Parcel:writeInt	(I)V
    //   40: aload_2
    //   41: aload_3
    //   42: iconst_0
    //   43: invokevirtual 79	com/google/android/gms/wearable/ConnectionConfiguration:writeToParcel	(Landroid/os/Parcel;I)V
    //   46: aload_0
    //   47: getfield 18	com/google/android/gms/wearable/internal/x$a$a:tD	Landroid/os/IBinder;
    //   50: iconst_2
    //   51: aload_3
    //   52: aload 4
    //   54: iconst_0
    //   55: invokeinterface 47 5 0
    //   60: pop
    //   61: aload 4
    //   63: invokevirtual 50	android/os/Parcel:readException	()V
    //   66: aload 4
    //   68: invokevirtual 53	android/os/Parcel:recycle	()V
    //   71: aload_3
    //   72: invokevirtual 53	android/os/Parcel:recycle	()V
    //   75: return
    //   76: aconst_null
    //   77: astore_1
    //   78: goto -52 -> 26
    //   81: aload_3
    //   82: iconst_0
    //   83: invokevirtual 63	android/os/Parcel:writeInt	(I)V
    //   86: goto -40 -> 46
    //   89: astore_1
    //   90: aload 4
    //   92: invokevirtual 53	android/os/Parcel:recycle	()V
    //   95: aload_3
    //   96: invokevirtual 53	android/os/Parcel:recycle	()V
    //   99: aload_1
    //   100: athrow
    // Local variable table:
    //   start	length	slot	name	signature
    //   0	101	0	this	a
    //   0	101	1	paramv	v
    //   0	101	2	paramConnectionConfiguration	com.google.android.gms.wearable.ConnectionConfiguration
    //   3	93	3	localParcel1	android.os.Parcel
    //   7	84	4	localParcel2	android.os.Parcel
    // Exception table:
    //   from	to	target	type
    //   9	15	89	finally
    //   19	26	89	finally
    //   26	31	89	finally
    //   35	46	89	finally
    //   46	66	89	finally
    //   81	86	89	finally
  }
  
  /* Error */
  public final void b(v paramv, u paramu, String paramString)
  {
    // Byte code:
    //   0: aconst_null
    //   1: astore 4
    //   3: invokestatic 26	android/os/Parcel:obtain	()Landroid/os/Parcel;
    //   6: astore 5
    //   8: invokestatic 26	android/os/Parcel:obtain	()Landroid/os/Parcel;
    //   11: astore 6
    //   13: aload 5
    //   15: ldc 28
    //   17: invokevirtual 32	android/os/Parcel:writeInterfaceToken	(Ljava/lang/String;)V
    //   20: aload_1
    //   21: ifnull +75 -> 96
    //   24: aload_1
    //   25: invokeinterface 38 1 0
    //   30: astore_1
    //   31: aload 5
    //   33: aload_1
    //   34: invokevirtual 41	android/os/Parcel:writeStrongBinder	(Landroid/os/IBinder;)V
    //   37: aload 4
    //   39: astore_1
    //   40: aload_2
    //   41: ifnull +10 -> 51
    //   44: aload_2
    //   45: invokeinterface 99 1 0
    //   50: astore_1
    //   51: aload 5
    //   53: aload_1
    //   54: invokevirtual 41	android/os/Parcel:writeStrongBinder	(Landroid/os/IBinder;)V
    //   57: aload 5
    //   59: aload_3
    //   60: invokevirtual 102	android/os/Parcel:writeString	(Ljava/lang/String;)V
    //   63: aload_0
    //   64: getfield 18	com/google/android/gms/wearable/internal/x$a$a:tD	Landroid/os/IBinder;
    //   67: bipush 35
    //   69: aload 5
    //   71: aload 6
    //   73: iconst_0
    //   74: invokeinterface 47 5 0
    //   79: pop
    //   80: aload 6
    //   82: invokevirtual 50	android/os/Parcel:readException	()V
    //   85: aload 6
    //   87: invokevirtual 53	android/os/Parcel:recycle	()V
    //   90: aload 5
    //   92: invokevirtual 53	android/os/Parcel:recycle	()V
    //   95: return
    //   96: aconst_null
    //   97: astore_1
    //   98: goto -67 -> 31
    //   101: astore_1
    //   102: aload 6
    //   104: invokevirtual 53	android/os/Parcel:recycle	()V
    //   107: aload 5
    //   109: invokevirtual 53	android/os/Parcel:recycle	()V
    //   112: aload_1
    //   113: athrow
    // Local variable table:
    //   start	length	slot	name	signature
    //   0	114	0	this	a
    //   0	114	1	paramv	v
    //   0	114	2	paramu	u
    //   0	114	3	paramString	String
    //   1	37	4	localObject	Object
    //   6	102	5	localParcel1	android.os.Parcel
    //   11	92	6	localParcel2	android.os.Parcel
    // Exception table:
    //   from	to	target	type
    //   13	20	101	finally
    //   24	31	101	finally
    //   31	37	101	finally
    //   44	51	101	finally
    //   51	85	101	finally
  }
  
  /* Error */
  public final void b(v paramv, String paramString)
  {
    // Byte code:
    //   0: invokestatic 26	android/os/Parcel:obtain	()Landroid/os/Parcel;
    //   3: astore_3
    //   4: invokestatic 26	android/os/Parcel:obtain	()Landroid/os/Parcel;
    //   7: astore 4
    //   9: aload_3
    //   10: ldc 28
    //   12: invokevirtual 32	android/os/Parcel:writeInterfaceToken	(Ljava/lang/String;)V
    //   15: aload_1
    //   16: ifnull +51 -> 67
    //   19: aload_1
    //   20: invokeinterface 38 1 0
    //   25: astore_1
    //   26: aload_3
    //   27: aload_1
    //   28: invokevirtual 41	android/os/Parcel:writeStrongBinder	(Landroid/os/IBinder;)V
    //   31: aload_3
    //   32: aload_2
    //   33: invokevirtual 102	android/os/Parcel:writeString	(Ljava/lang/String;)V
    //   36: aload_0
    //   37: getfield 18	com/google/android/gms/wearable/internal/x$a$a:tD	Landroid/os/IBinder;
    //   40: bipush 23
    //   42: aload_3
    //   43: aload 4
    //   45: iconst_0
    //   46: invokeinterface 47 5 0
    //   51: pop
    //   52: aload 4
    //   54: invokevirtual 50	android/os/Parcel:readException	()V
    //   57: aload 4
    //   59: invokevirtual 53	android/os/Parcel:recycle	()V
    //   62: aload_3
    //   63: invokevirtual 53	android/os/Parcel:recycle	()V
    //   66: return
    //   67: aconst_null
    //   68: astore_1
    //   69: goto -43 -> 26
    //   72: astore_1
    //   73: aload 4
    //   75: invokevirtual 53	android/os/Parcel:recycle	()V
    //   78: aload_3
    //   79: invokevirtual 53	android/os/Parcel:recycle	()V
    //   82: aload_1
    //   83: athrow
    // Local variable table:
    //   start	length	slot	name	signature
    //   0	84	0	this	a
    //   0	84	1	paramv	v
    //   0	84	2	paramString	String
    //   3	76	3	localParcel1	android.os.Parcel
    //   7	67	4	localParcel2	android.os.Parcel
    // Exception table:
    //   from	to	target	type
    //   9	15	72	finally
    //   19	26	72	finally
    //   26	57	72	finally
  }
  
  /* Error */
  public final void b(v paramv, String paramString, int paramInt)
  {
    // Byte code:
    //   0: invokestatic 26	android/os/Parcel:obtain	()Landroid/os/Parcel;
    //   3: astore 4
    //   5: invokestatic 26	android/os/Parcel:obtain	()Landroid/os/Parcel;
    //   8: astore 5
    //   10: aload 4
    //   12: ldc 28
    //   14: invokevirtual 32	android/os/Parcel:writeInterfaceToken	(Ljava/lang/String;)V
    //   17: aload_1
    //   18: ifnull +61 -> 79
    //   21: aload_1
    //   22: invokeinterface 38 1 0
    //   27: astore_1
    //   28: aload 4
    //   30: aload_1
    //   31: invokevirtual 41	android/os/Parcel:writeStrongBinder	(Landroid/os/IBinder;)V
    //   34: aload 4
    //   36: aload_2
    //   37: invokevirtual 102	android/os/Parcel:writeString	(Ljava/lang/String;)V
    //   40: aload 4
    //   42: iload_3
    //   43: invokevirtual 63	android/os/Parcel:writeInt	(I)V
    //   46: aload_0
    //   47: getfield 18	com/google/android/gms/wearable/internal/x$a$a:tD	Landroid/os/IBinder;
    //   50: bipush 33
    //   52: aload 4
    //   54: aload 5
    //   56: iconst_0
    //   57: invokeinterface 47 5 0
    //   62: pop
    //   63: aload 5
    //   65: invokevirtual 50	android/os/Parcel:readException	()V
    //   68: aload 5
    //   70: invokevirtual 53	android/os/Parcel:recycle	()V
    //   73: aload 4
    //   75: invokevirtual 53	android/os/Parcel:recycle	()V
    //   78: return
    //   79: aconst_null
    //   80: astore_1
    //   81: goto -53 -> 28
    //   84: astore_1
    //   85: aload 5
    //   87: invokevirtual 53	android/os/Parcel:recycle	()V
    //   90: aload 4
    //   92: invokevirtual 53	android/os/Parcel:recycle	()V
    //   95: aload_1
    //   96: athrow
    // Local variable table:
    //   start	length	slot	name	signature
    //   0	97	0	this	a
    //   0	97	1	paramv	v
    //   0	97	2	paramString	String
    //   0	97	3	paramInt	int
    //   3	88	4	localParcel1	android.os.Parcel
    //   8	78	5	localParcel2	android.os.Parcel
    // Exception table:
    //   from	to	target	type
    //   10	17	84	finally
    //   21	28	84	finally
    //   28	68	84	finally
  }
  
  /* Error */
  public final void b(v paramv, boolean paramBoolean)
  {
    // Byte code:
    //   0: iconst_0
    //   1: istore_3
    //   2: invokestatic 26	android/os/Parcel:obtain	()Landroid/os/Parcel;
    //   5: astore 4
    //   7: invokestatic 26	android/os/Parcel:obtain	()Landroid/os/Parcel;
    //   10: astore 5
    //   12: aload 4
    //   14: ldc 28
    //   16: invokevirtual 32	android/os/Parcel:writeInterfaceToken	(Ljava/lang/String;)V
    //   19: aload_1
    //   20: ifnull +61 -> 81
    //   23: aload_1
    //   24: invokeinterface 38 1 0
    //   29: astore_1
    //   30: aload 4
    //   32: aload_1
    //   33: invokevirtual 41	android/os/Parcel:writeStrongBinder	(Landroid/os/IBinder;)V
    //   36: iload_2
    //   37: ifeq +5 -> 42
    //   40: iconst_1
    //   41: istore_3
    //   42: aload 4
    //   44: iload_3
    //   45: invokevirtual 63	android/os/Parcel:writeInt	(I)V
    //   48: aload_0
    //   49: getfield 18	com/google/android/gms/wearable/internal/x$a$a:tD	Landroid/os/IBinder;
    //   52: bipush 50
    //   54: aload 4
    //   56: aload 5
    //   58: iconst_0
    //   59: invokeinterface 47 5 0
    //   64: pop
    //   65: aload 5
    //   67: invokevirtual 50	android/os/Parcel:readException	()V
    //   70: aload 5
    //   72: invokevirtual 53	android/os/Parcel:recycle	()V
    //   75: aload 4
    //   77: invokevirtual 53	android/os/Parcel:recycle	()V
    //   80: return
    //   81: aconst_null
    //   82: astore_1
    //   83: goto -53 -> 30
    //   86: astore_1
    //   87: aload 5
    //   89: invokevirtual 53	android/os/Parcel:recycle	()V
    //   92: aload 4
    //   94: invokevirtual 53	android/os/Parcel:recycle	()V
    //   97: aload_1
    //   98: athrow
    // Local variable table:
    //   start	length	slot	name	signature
    //   0	99	0	this	a
    //   0	99	1	paramv	v
    //   0	99	2	paramBoolean	boolean
    //   1	44	3	i	int
    //   5	88	4	localParcel1	android.os.Parcel
    //   10	78	5	localParcel2	android.os.Parcel
    // Exception table:
    //   from	to	target	type
    //   12	19	86	finally
    //   23	30	86	finally
    //   30	36	86	finally
    //   42	70	86	finally
  }
  
  /* Error */
  public final void c(v paramv)
  {
    // Byte code:
    //   0: invokestatic 26	android/os/Parcel:obtain	()Landroid/os/Parcel;
    //   3: astore_2
    //   4: invokestatic 26	android/os/Parcel:obtain	()Landroid/os/Parcel;
    //   7: astore_3
    //   8: aload_2
    //   9: ldc 28
    //   11: invokevirtual 32	android/os/Parcel:writeInterfaceToken	(Ljava/lang/String;)V
    //   14: aload_1
    //   15: ifnull +43 -> 58
    //   18: aload_1
    //   19: invokeinterface 38 1 0
    //   24: astore_1
    //   25: aload_2
    //   26: aload_1
    //   27: invokevirtual 41	android/os/Parcel:writeStrongBinder	(Landroid/os/IBinder;)V
    //   30: aload_0
    //   31: getfield 18	com/google/android/gms/wearable/internal/x$a$a:tD	Landroid/os/IBinder;
    //   34: bipush 14
    //   36: aload_2
    //   37: aload_3
    //   38: iconst_0
    //   39: invokeinterface 47 5 0
    //   44: pop
    //   45: aload_3
    //   46: invokevirtual 50	android/os/Parcel:readException	()V
    //   49: aload_3
    //   50: invokevirtual 53	android/os/Parcel:recycle	()V
    //   53: aload_2
    //   54: invokevirtual 53	android/os/Parcel:recycle	()V
    //   57: return
    //   58: aconst_null
    //   59: astore_1
    //   60: goto -35 -> 25
    //   63: astore_1
    //   64: aload_3
    //   65: invokevirtual 53	android/os/Parcel:recycle	()V
    //   68: aload_2
    //   69: invokevirtual 53	android/os/Parcel:recycle	()V
    //   72: aload_1
    //   73: athrow
    // Local variable table:
    //   start	length	slot	name	signature
    //   0	74	0	this	a
    //   0	74	1	paramv	v
    //   3	66	2	localParcel1	android.os.Parcel
    //   7	58	3	localParcel2	android.os.Parcel
    // Exception table:
    //   from	to	target	type
    //   8	14	63	finally
    //   18	25	63	finally
    //   25	49	63	finally
  }
  
  /* Error */
  public final void c(v paramv, int paramInt)
  {
    // Byte code:
    //   0: invokestatic 26	android/os/Parcel:obtain	()Landroid/os/Parcel;
    //   3: astore_3
    //   4: invokestatic 26	android/os/Parcel:obtain	()Landroid/os/Parcel;
    //   7: astore 4
    //   9: aload_3
    //   10: ldc 28
    //   12: invokevirtual 32	android/os/Parcel:writeInterfaceToken	(Ljava/lang/String;)V
    //   15: aload_1
    //   16: ifnull +51 -> 67
    //   19: aload_1
    //   20: invokeinterface 38 1 0
    //   25: astore_1
    //   26: aload_3
    //   27: aload_1
    //   28: invokevirtual 41	android/os/Parcel:writeStrongBinder	(Landroid/os/IBinder;)V
    //   31: aload_3
    //   32: iload_2
    //   33: invokevirtual 63	android/os/Parcel:writeInt	(I)V
    //   36: aload_0
    //   37: getfield 18	com/google/android/gms/wearable/internal/x$a$a:tD	Landroid/os/IBinder;
    //   40: bipush 29
    //   42: aload_3
    //   43: aload 4
    //   45: iconst_0
    //   46: invokeinterface 47 5 0
    //   51: pop
    //   52: aload 4
    //   54: invokevirtual 50	android/os/Parcel:readException	()V
    //   57: aload 4
    //   59: invokevirtual 53	android/os/Parcel:recycle	()V
    //   62: aload_3
    //   63: invokevirtual 53	android/os/Parcel:recycle	()V
    //   66: return
    //   67: aconst_null
    //   68: astore_1
    //   69: goto -43 -> 26
    //   72: astore_1
    //   73: aload 4
    //   75: invokevirtual 53	android/os/Parcel:recycle	()V
    //   78: aload_3
    //   79: invokevirtual 53	android/os/Parcel:recycle	()V
    //   82: aload_1
    //   83: athrow
    // Local variable table:
    //   start	length	slot	name	signature
    //   0	84	0	this	a
    //   0	84	1	paramv	v
    //   0	84	2	paramInt	int
    //   3	76	3	localParcel1	android.os.Parcel
    //   7	67	4	localParcel2	android.os.Parcel
    // Exception table:
    //   from	to	target	type
    //   9	15	72	finally
    //   19	26	72	finally
    //   26	57	72	finally
  }
  
  /* Error */
  public final void c(v paramv, android.net.Uri paramUri)
  {
    // Byte code:
    //   0: invokestatic 26	android/os/Parcel:obtain	()Landroid/os/Parcel;
    //   3: astore_3
    //   4: invokestatic 26	android/os/Parcel:obtain	()Landroid/os/Parcel;
    //   7: astore 4
    //   9: aload_3
    //   10: ldc 28
    //   12: invokevirtual 32	android/os/Parcel:writeInterfaceToken	(Ljava/lang/String;)V
    //   15: aload_1
    //   16: ifnull +61 -> 77
    //   19: aload_1
    //   20: invokeinterface 38 1 0
    //   25: astore_1
    //   26: aload_3
    //   27: aload_1
    //   28: invokevirtual 41	android/os/Parcel:writeStrongBinder	(Landroid/os/IBinder;)V
    //   31: aload_2
    //   32: ifnull +50 -> 82
    //   35: aload_3
    //   36: iconst_1
    //   37: invokevirtual 63	android/os/Parcel:writeInt	(I)V
    //   40: aload_2
    //   41: aload_3
    //   42: iconst_0
    //   43: invokevirtual 70	android/net/Uri:writeToParcel	(Landroid/os/Parcel;I)V
    //   46: aload_0
    //   47: getfield 18	com/google/android/gms/wearable/internal/x$a$a:tD	Landroid/os/IBinder;
    //   50: bipush 11
    //   52: aload_3
    //   53: aload 4
    //   55: iconst_0
    //   56: invokeinterface 47 5 0
    //   61: pop
    //   62: aload 4
    //   64: invokevirtual 50	android/os/Parcel:readException	()V
    //   67: aload 4
    //   69: invokevirtual 53	android/os/Parcel:recycle	()V
    //   72: aload_3
    //   73: invokevirtual 53	android/os/Parcel:recycle	()V
    //   76: return
    //   77: aconst_null
    //   78: astore_1
    //   79: goto -53 -> 26
    //   82: aload_3
    //   83: iconst_0
    //   84: invokevirtual 63	android/os/Parcel:writeInt	(I)V
    //   87: goto -41 -> 46
    //   90: astore_1
    //   91: aload 4
    //   93: invokevirtual 53	android/os/Parcel:recycle	()V
    //   96: aload_3
    //   97: invokevirtual 53	android/os/Parcel:recycle	()V
    //   100: aload_1
    //   101: athrow
    // Local variable table:
    //   start	length	slot	name	signature
    //   0	102	0	this	a
    //   0	102	1	paramv	v
    //   0	102	2	paramUri	android.net.Uri
    //   3	94	3	localParcel1	android.os.Parcel
    //   7	85	4	localParcel2	android.os.Parcel
    // Exception table:
    //   from	to	target	type
    //   9	15	90	finally
    //   19	26	90	finally
    //   26	31	90	finally
    //   35	46	90	finally
    //   46	67	90	finally
    //   82	87	90	finally
  }
  
  /* Error */
  public final void c(v paramv, String paramString)
  {
    // Byte code:
    //   0: invokestatic 26	android/os/Parcel:obtain	()Landroid/os/Parcel;
    //   3: astore_3
    //   4: invokestatic 26	android/os/Parcel:obtain	()Landroid/os/Parcel;
    //   7: astore 4
    //   9: aload_3
    //   10: ldc 28
    //   12: invokevirtual 32	android/os/Parcel:writeInterfaceToken	(Ljava/lang/String;)V
    //   15: aload_1
    //   16: ifnull +51 -> 67
    //   19: aload_1
    //   20: invokeinterface 38 1 0
    //   25: astore_1
    //   26: aload_3
    //   27: aload_1
    //   28: invokevirtual 41	android/os/Parcel:writeStrongBinder	(Landroid/os/IBinder;)V
    //   31: aload_3
    //   32: aload_2
    //   33: invokevirtual 102	android/os/Parcel:writeString	(Ljava/lang/String;)V
    //   36: aload_0
    //   37: getfield 18	com/google/android/gms/wearable/internal/x$a$a:tD	Landroid/os/IBinder;
    //   40: bipush 24
    //   42: aload_3
    //   43: aload 4
    //   45: iconst_0
    //   46: invokeinterface 47 5 0
    //   51: pop
    //   52: aload 4
    //   54: invokevirtual 50	android/os/Parcel:readException	()V
    //   57: aload 4
    //   59: invokevirtual 53	android/os/Parcel:recycle	()V
    //   62: aload_3
    //   63: invokevirtual 53	android/os/Parcel:recycle	()V
    //   66: return
    //   67: aconst_null
    //   68: astore_1
    //   69: goto -43 -> 26
    //   72: astore_1
    //   73: aload 4
    //   75: invokevirtual 53	android/os/Parcel:recycle	()V
    //   78: aload_3
    //   79: invokevirtual 53	android/os/Parcel:recycle	()V
    //   82: aload_1
    //   83: athrow
    // Local variable table:
    //   start	length	slot	name	signature
    //   0	84	0	this	a
    //   0	84	1	paramv	v
    //   0	84	2	paramString	String
    //   3	76	3	localParcel1	android.os.Parcel
    //   7	67	4	localParcel2	android.os.Parcel
    // Exception table:
    //   from	to	target	type
    //   9	15	72	finally
    //   19	26	72	finally
    //   26	57	72	finally
  }
  
  /* Error */
  public final void d(v paramv)
  {
    // Byte code:
    //   0: invokestatic 26	android/os/Parcel:obtain	()Landroid/os/Parcel;
    //   3: astore_2
    //   4: invokestatic 26	android/os/Parcel:obtain	()Landroid/os/Parcel;
    //   7: astore_3
    //   8: aload_2
    //   9: ldc 28
    //   11: invokevirtual 32	android/os/Parcel:writeInterfaceToken	(Ljava/lang/String;)V
    //   14: aload_1
    //   15: ifnull +43 -> 58
    //   18: aload_1
    //   19: invokeinterface 38 1 0
    //   24: astore_1
    //   25: aload_2
    //   26: aload_1
    //   27: invokevirtual 41	android/os/Parcel:writeStrongBinder	(Landroid/os/IBinder;)V
    //   30: aload_0
    //   31: getfield 18	com/google/android/gms/wearable/internal/x$a$a:tD	Landroid/os/IBinder;
    //   34: bipush 15
    //   36: aload_2
    //   37: aload_3
    //   38: iconst_0
    //   39: invokeinterface 47 5 0
    //   44: pop
    //   45: aload_3
    //   46: invokevirtual 50	android/os/Parcel:readException	()V
    //   49: aload_3
    //   50: invokevirtual 53	android/os/Parcel:recycle	()V
    //   53: aload_2
    //   54: invokevirtual 53	android/os/Parcel:recycle	()V
    //   57: return
    //   58: aconst_null
    //   59: astore_1
    //   60: goto -35 -> 25
    //   63: astore_1
    //   64: aload_3
    //   65: invokevirtual 53	android/os/Parcel:recycle	()V
    //   68: aload_2
    //   69: invokevirtual 53	android/os/Parcel:recycle	()V
    //   72: aload_1
    //   73: athrow
    // Local variable table:
    //   start	length	slot	name	signature
    //   0	74	0	this	a
    //   0	74	1	paramv	v
    //   3	66	2	localParcel1	android.os.Parcel
    //   7	58	3	localParcel2	android.os.Parcel
    // Exception table:
    //   from	to	target	type
    //   8	14	63	finally
    //   18	25	63	finally
    //   25	49	63	finally
  }
  
  /* Error */
  public final void d(v paramv, String paramString)
  {
    // Byte code:
    //   0: invokestatic 26	android/os/Parcel:obtain	()Landroid/os/Parcel;
    //   3: astore_3
    //   4: invokestatic 26	android/os/Parcel:obtain	()Landroid/os/Parcel;
    //   7: astore 4
    //   9: aload_3
    //   10: ldc 28
    //   12: invokevirtual 32	android/os/Parcel:writeInterfaceToken	(Ljava/lang/String;)V
    //   15: aload_1
    //   16: ifnull +51 -> 67
    //   19: aload_1
    //   20: invokeinterface 38 1 0
    //   25: astore_1
    //   26: aload_3
    //   27: aload_1
    //   28: invokevirtual 41	android/os/Parcel:writeStrongBinder	(Landroid/os/IBinder;)V
    //   31: aload_3
    //   32: aload_2
    //   33: invokevirtual 102	android/os/Parcel:writeString	(Ljava/lang/String;)V
    //   36: aload_0
    //   37: getfield 18	com/google/android/gms/wearable/internal/x$a$a:tD	Landroid/os/IBinder;
    //   40: bipush 46
    //   42: aload_3
    //   43: aload 4
    //   45: iconst_0
    //   46: invokeinterface 47 5 0
    //   51: pop
    //   52: aload 4
    //   54: invokevirtual 50	android/os/Parcel:readException	()V
    //   57: aload 4
    //   59: invokevirtual 53	android/os/Parcel:recycle	()V
    //   62: aload_3
    //   63: invokevirtual 53	android/os/Parcel:recycle	()V
    //   66: return
    //   67: aconst_null
    //   68: astore_1
    //   69: goto -43 -> 26
    //   72: astore_1
    //   73: aload 4
    //   75: invokevirtual 53	android/os/Parcel:recycle	()V
    //   78: aload_3
    //   79: invokevirtual 53	android/os/Parcel:recycle	()V
    //   82: aload_1
    //   83: athrow
    // Local variable table:
    //   start	length	slot	name	signature
    //   0	84	0	this	a
    //   0	84	1	paramv	v
    //   0	84	2	paramString	String
    //   3	76	3	localParcel1	android.os.Parcel
    //   7	67	4	localParcel2	android.os.Parcel
    // Exception table:
    //   from	to	target	type
    //   9	15	72	finally
    //   19	26	72	finally
    //   26	57	72	finally
  }
  
  /* Error */
  public final void e(v paramv)
  {
    // Byte code:
    //   0: invokestatic 26	android/os/Parcel:obtain	()Landroid/os/Parcel;
    //   3: astore_2
    //   4: invokestatic 26	android/os/Parcel:obtain	()Landroid/os/Parcel;
    //   7: astore_3
    //   8: aload_2
    //   9: ldc 28
    //   11: invokevirtual 32	android/os/Parcel:writeInterfaceToken	(Ljava/lang/String;)V
    //   14: aload_1
    //   15: ifnull +43 -> 58
    //   18: aload_1
    //   19: invokeinterface 38 1 0
    //   24: astore_1
    //   25: aload_2
    //   26: aload_1
    //   27: invokevirtual 41	android/os/Parcel:writeStrongBinder	(Landroid/os/IBinder;)V
    //   30: aload_0
    //   31: getfield 18	com/google/android/gms/wearable/internal/x$a$a:tD	Landroid/os/IBinder;
    //   34: bipush 18
    //   36: aload_2
    //   37: aload_3
    //   38: iconst_0
    //   39: invokeinterface 47 5 0
    //   44: pop
    //   45: aload_3
    //   46: invokevirtual 50	android/os/Parcel:readException	()V
    //   49: aload_3
    //   50: invokevirtual 53	android/os/Parcel:recycle	()V
    //   53: aload_2
    //   54: invokevirtual 53	android/os/Parcel:recycle	()V
    //   57: return
    //   58: aconst_null
    //   59: astore_1
    //   60: goto -35 -> 25
    //   63: astore_1
    //   64: aload_3
    //   65: invokevirtual 53	android/os/Parcel:recycle	()V
    //   68: aload_2
    //   69: invokevirtual 53	android/os/Parcel:recycle	()V
    //   72: aload_1
    //   73: athrow
    // Local variable table:
    //   start	length	slot	name	signature
    //   0	74	0	this	a
    //   0	74	1	paramv	v
    //   3	66	2	localParcel1	android.os.Parcel
    //   7	58	3	localParcel2	android.os.Parcel
    // Exception table:
    //   from	to	target	type
    //   8	14	63	finally
    //   18	25	63	finally
    //   25	49	63	finally
  }
  
  /* Error */
  public final void e(v paramv, String paramString)
  {
    // Byte code:
    //   0: invokestatic 26	android/os/Parcel:obtain	()Landroid/os/Parcel;
    //   3: astore_3
    //   4: invokestatic 26	android/os/Parcel:obtain	()Landroid/os/Parcel;
    //   7: astore 4
    //   9: aload_3
    //   10: ldc 28
    //   12: invokevirtual 32	android/os/Parcel:writeInterfaceToken	(Ljava/lang/String;)V
    //   15: aload_1
    //   16: ifnull +51 -> 67
    //   19: aload_1
    //   20: invokeinterface 38 1 0
    //   25: astore_1
    //   26: aload_3
    //   27: aload_1
    //   28: invokevirtual 41	android/os/Parcel:writeStrongBinder	(Landroid/os/IBinder;)V
    //   31: aload_3
    //   32: aload_2
    //   33: invokevirtual 102	android/os/Parcel:writeString	(Ljava/lang/String;)V
    //   36: aload_0
    //   37: getfield 18	com/google/android/gms/wearable/internal/x$a$a:tD	Landroid/os/IBinder;
    //   40: bipush 47
    //   42: aload_3
    //   43: aload 4
    //   45: iconst_0
    //   46: invokeinterface 47 5 0
    //   51: pop
    //   52: aload 4
    //   54: invokevirtual 50	android/os/Parcel:readException	()V
    //   57: aload 4
    //   59: invokevirtual 53	android/os/Parcel:recycle	()V
    //   62: aload_3
    //   63: invokevirtual 53	android/os/Parcel:recycle	()V
    //   66: return
    //   67: aconst_null
    //   68: astore_1
    //   69: goto -43 -> 26
    //   72: astore_1
    //   73: aload 4
    //   75: invokevirtual 53	android/os/Parcel:recycle	()V
    //   78: aload_3
    //   79: invokevirtual 53	android/os/Parcel:recycle	()V
    //   82: aload_1
    //   83: athrow
    // Local variable table:
    //   start	length	slot	name	signature
    //   0	84	0	this	a
    //   0	84	1	paramv	v
    //   0	84	2	paramString	String
    //   3	76	3	localParcel1	android.os.Parcel
    //   7	67	4	localParcel2	android.os.Parcel
    // Exception table:
    //   from	to	target	type
    //   9	15	72	finally
    //   19	26	72	finally
    //   26	57	72	finally
  }
  
  /* Error */
  public final void f(v paramv)
  {
    // Byte code:
    //   0: invokestatic 26	android/os/Parcel:obtain	()Landroid/os/Parcel;
    //   3: astore_2
    //   4: invokestatic 26	android/os/Parcel:obtain	()Landroid/os/Parcel;
    //   7: astore_3
    //   8: aload_2
    //   9: ldc 28
    //   11: invokevirtual 32	android/os/Parcel:writeInterfaceToken	(Ljava/lang/String;)V
    //   14: aload_1
    //   15: ifnull +43 -> 58
    //   18: aload_1
    //   19: invokeinterface 38 1 0
    //   24: astore_1
    //   25: aload_2
    //   26: aload_1
    //   27: invokevirtual 41	android/os/Parcel:writeStrongBinder	(Landroid/os/IBinder;)V
    //   30: aload_0
    //   31: getfield 18	com/google/android/gms/wearable/internal/x$a$a:tD	Landroid/os/IBinder;
    //   34: bipush 19
    //   36: aload_2
    //   37: aload_3
    //   38: iconst_0
    //   39: invokeinterface 47 5 0
    //   44: pop
    //   45: aload_3
    //   46: invokevirtual 50	android/os/Parcel:readException	()V
    //   49: aload_3
    //   50: invokevirtual 53	android/os/Parcel:recycle	()V
    //   53: aload_2
    //   54: invokevirtual 53	android/os/Parcel:recycle	()V
    //   57: return
    //   58: aconst_null
    //   59: astore_1
    //   60: goto -35 -> 25
    //   63: astore_1
    //   64: aload_3
    //   65: invokevirtual 53	android/os/Parcel:recycle	()V
    //   68: aload_2
    //   69: invokevirtual 53	android/os/Parcel:recycle	()V
    //   72: aload_1
    //   73: athrow
    // Local variable table:
    //   start	length	slot	name	signature
    //   0	74	0	this	a
    //   0	74	1	paramv	v
    //   3	66	2	localParcel1	android.os.Parcel
    //   7	58	3	localParcel2	android.os.Parcel
    // Exception table:
    //   from	to	target	type
    //   8	14	63	finally
    //   18	25	63	finally
    //   25	49	63	finally
  }
  
  /* Error */
  public final void f(v paramv, String paramString)
  {
    // Byte code:
    //   0: invokestatic 26	android/os/Parcel:obtain	()Landroid/os/Parcel;
    //   3: astore_3
    //   4: invokestatic 26	android/os/Parcel:obtain	()Landroid/os/Parcel;
    //   7: astore 4
    //   9: aload_3
    //   10: ldc 28
    //   12: invokevirtual 32	android/os/Parcel:writeInterfaceToken	(Ljava/lang/String;)V
    //   15: aload_1
    //   16: ifnull +51 -> 67
    //   19: aload_1
    //   20: invokeinterface 38 1 0
    //   25: astore_1
    //   26: aload_3
    //   27: aload_1
    //   28: invokevirtual 41	android/os/Parcel:writeStrongBinder	(Landroid/os/IBinder;)V
    //   31: aload_3
    //   32: aload_2
    //   33: invokevirtual 102	android/os/Parcel:writeString	(Ljava/lang/String;)V
    //   36: aload_0
    //   37: getfield 18	com/google/android/gms/wearable/internal/x$a$a:tD	Landroid/os/IBinder;
    //   40: bipush 32
    //   42: aload_3
    //   43: aload 4
    //   45: iconst_0
    //   46: invokeinterface 47 5 0
    //   51: pop
    //   52: aload 4
    //   54: invokevirtual 50	android/os/Parcel:readException	()V
    //   57: aload 4
    //   59: invokevirtual 53	android/os/Parcel:recycle	()V
    //   62: aload_3
    //   63: invokevirtual 53	android/os/Parcel:recycle	()V
    //   66: return
    //   67: aconst_null
    //   68: astore_1
    //   69: goto -43 -> 26
    //   72: astore_1
    //   73: aload 4
    //   75: invokevirtual 53	android/os/Parcel:recycle	()V
    //   78: aload_3
    //   79: invokevirtual 53	android/os/Parcel:recycle	()V
    //   82: aload_1
    //   83: athrow
    // Local variable table:
    //   start	length	slot	name	signature
    //   0	84	0	this	a
    //   0	84	1	paramv	v
    //   0	84	2	paramString	String
    //   3	76	3	localParcel1	android.os.Parcel
    //   7	67	4	localParcel2	android.os.Parcel
    // Exception table:
    //   from	to	target	type
    //   9	15	72	finally
    //   19	26	72	finally
    //   26	57	72	finally
  }
  
  /* Error */
  public final void g(v paramv)
  {
    // Byte code:
    //   0: invokestatic 26	android/os/Parcel:obtain	()Landroid/os/Parcel;
    //   3: astore_2
    //   4: invokestatic 26	android/os/Parcel:obtain	()Landroid/os/Parcel;
    //   7: astore_3
    //   8: aload_2
    //   9: ldc 28
    //   11: invokevirtual 32	android/os/Parcel:writeInterfaceToken	(Ljava/lang/String;)V
    //   14: aload_1
    //   15: ifnull +43 -> 58
    //   18: aload_1
    //   19: invokeinterface 38 1 0
    //   24: astore_1
    //   25: aload_2
    //   26: aload_1
    //   27: invokevirtual 41	android/os/Parcel:writeStrongBinder	(Landroid/os/IBinder;)V
    //   30: aload_0
    //   31: getfield 18	com/google/android/gms/wearable/internal/x$a$a:tD	Landroid/os/IBinder;
    //   34: bipush 25
    //   36: aload_2
    //   37: aload_3
    //   38: iconst_0
    //   39: invokeinterface 47 5 0
    //   44: pop
    //   45: aload_3
    //   46: invokevirtual 50	android/os/Parcel:readException	()V
    //   49: aload_3
    //   50: invokevirtual 53	android/os/Parcel:recycle	()V
    //   53: aload_2
    //   54: invokevirtual 53	android/os/Parcel:recycle	()V
    //   57: return
    //   58: aconst_null
    //   59: astore_1
    //   60: goto -35 -> 25
    //   63: astore_1
    //   64: aload_3
    //   65: invokevirtual 53	android/os/Parcel:recycle	()V
    //   68: aload_2
    //   69: invokevirtual 53	android/os/Parcel:recycle	()V
    //   72: aload_1
    //   73: athrow
    // Local variable table:
    //   start	length	slot	name	signature
    //   0	74	0	this	a
    //   0	74	1	paramv	v
    //   3	66	2	localParcel1	android.os.Parcel
    //   7	58	3	localParcel2	android.os.Parcel
    // Exception table:
    //   from	to	target	type
    //   8	14	63	finally
    //   18	25	63	finally
    //   25	49	63	finally
  }
  
  /* Error */
  public final void h(v paramv)
  {
    // Byte code:
    //   0: invokestatic 26	android/os/Parcel:obtain	()Landroid/os/Parcel;
    //   3: astore_2
    //   4: invokestatic 26	android/os/Parcel:obtain	()Landroid/os/Parcel;
    //   7: astore_3
    //   8: aload_2
    //   9: ldc 28
    //   11: invokevirtual 32	android/os/Parcel:writeInterfaceToken	(Ljava/lang/String;)V
    //   14: aload_1
    //   15: ifnull +43 -> 58
    //   18: aload_1
    //   19: invokeinterface 38 1 0
    //   24: astore_1
    //   25: aload_2
    //   26: aload_1
    //   27: invokevirtual 41	android/os/Parcel:writeStrongBinder	(Landroid/os/IBinder;)V
    //   30: aload_0
    //   31: getfield 18	com/google/android/gms/wearable/internal/x$a$a:tD	Landroid/os/IBinder;
    //   34: bipush 26
    //   36: aload_2
    //   37: aload_3
    //   38: iconst_0
    //   39: invokeinterface 47 5 0
    //   44: pop
    //   45: aload_3
    //   46: invokevirtual 50	android/os/Parcel:readException	()V
    //   49: aload_3
    //   50: invokevirtual 53	android/os/Parcel:recycle	()V
    //   53: aload_2
    //   54: invokevirtual 53	android/os/Parcel:recycle	()V
    //   57: return
    //   58: aconst_null
    //   59: astore_1
    //   60: goto -35 -> 25
    //   63: astore_1
    //   64: aload_3
    //   65: invokevirtual 53	android/os/Parcel:recycle	()V
    //   68: aload_2
    //   69: invokevirtual 53	android/os/Parcel:recycle	()V
    //   72: aload_1
    //   73: athrow
    // Local variable table:
    //   start	length	slot	name	signature
    //   0	74	0	this	a
    //   0	74	1	paramv	v
    //   3	66	2	localParcel1	android.os.Parcel
    //   7	58	3	localParcel2	android.os.Parcel
    // Exception table:
    //   from	to	target	type
    //   8	14	63	finally
    //   18	25	63	finally
    //   25	49	63	finally
  }
  
  /* Error */
  public final void i(v paramv)
  {
    // Byte code:
    //   0: invokestatic 26	android/os/Parcel:obtain	()Landroid/os/Parcel;
    //   3: astore_2
    //   4: invokestatic 26	android/os/Parcel:obtain	()Landroid/os/Parcel;
    //   7: astore_3
    //   8: aload_2
    //   9: ldc 28
    //   11: invokevirtual 32	android/os/Parcel:writeInterfaceToken	(Ljava/lang/String;)V
    //   14: aload_1
    //   15: ifnull +43 -> 58
    //   18: aload_1
    //   19: invokeinterface 38 1 0
    //   24: astore_1
    //   25: aload_2
    //   26: aload_1
    //   27: invokevirtual 41	android/os/Parcel:writeStrongBinder	(Landroid/os/IBinder;)V
    //   30: aload_0
    //   31: getfield 18	com/google/android/gms/wearable/internal/x$a$a:tD	Landroid/os/IBinder;
    //   34: bipush 30
    //   36: aload_2
    //   37: aload_3
    //   38: iconst_0
    //   39: invokeinterface 47 5 0
    //   44: pop
    //   45: aload_3
    //   46: invokevirtual 50	android/os/Parcel:readException	()V
    //   49: aload_3
    //   50: invokevirtual 53	android/os/Parcel:recycle	()V
    //   53: aload_2
    //   54: invokevirtual 53	android/os/Parcel:recycle	()V
    //   57: return
    //   58: aconst_null
    //   59: astore_1
    //   60: goto -35 -> 25
    //   63: astore_1
    //   64: aload_3
    //   65: invokevirtual 53	android/os/Parcel:recycle	()V
    //   68: aload_2
    //   69: invokevirtual 53	android/os/Parcel:recycle	()V
    //   72: aload_1
    //   73: athrow
    // Local variable table:
    //   start	length	slot	name	signature
    //   0	74	0	this	a
    //   0	74	1	paramv	v
    //   3	66	2	localParcel1	android.os.Parcel
    //   7	58	3	localParcel2	android.os.Parcel
    // Exception table:
    //   from	to	target	type
    //   8	14	63	finally
    //   18	25	63	finally
    //   25	49	63	finally
  }
  
  /* Error */
  public final void j(v paramv)
  {
    // Byte code:
    //   0: invokestatic 26	android/os/Parcel:obtain	()Landroid/os/Parcel;
    //   3: astore_2
    //   4: invokestatic 26	android/os/Parcel:obtain	()Landroid/os/Parcel;
    //   7: astore_3
    //   8: aload_2
    //   9: ldc 28
    //   11: invokevirtual 32	android/os/Parcel:writeInterfaceToken	(Ljava/lang/String;)V
    //   14: aload_1
    //   15: ifnull +43 -> 58
    //   18: aload_1
    //   19: invokeinterface 38 1 0
    //   24: astore_1
    //   25: aload_2
    //   26: aload_1
    //   27: invokevirtual 41	android/os/Parcel:writeStrongBinder	(Landroid/os/IBinder;)V
    //   30: aload_0
    //   31: getfield 18	com/google/android/gms/wearable/internal/x$a$a:tD	Landroid/os/IBinder;
    //   34: bipush 37
    //   36: aload_2
    //   37: aload_3
    //   38: iconst_0
    //   39: invokeinterface 47 5 0
    //   44: pop
    //   45: aload_3
    //   46: invokevirtual 50	android/os/Parcel:readException	()V
    //   49: aload_3
    //   50: invokevirtual 53	android/os/Parcel:recycle	()V
    //   53: aload_2
    //   54: invokevirtual 53	android/os/Parcel:recycle	()V
    //   57: return
    //   58: aconst_null
    //   59: astore_1
    //   60: goto -35 -> 25
    //   63: astore_1
    //   64: aload_3
    //   65: invokevirtual 53	android/os/Parcel:recycle	()V
    //   68: aload_2
    //   69: invokevirtual 53	android/os/Parcel:recycle	()V
    //   72: aload_1
    //   73: athrow
    // Local variable table:
    //   start	length	slot	name	signature
    //   0	74	0	this	a
    //   0	74	1	paramv	v
    //   3	66	2	localParcel1	android.os.Parcel
    //   7	58	3	localParcel2	android.os.Parcel
    // Exception table:
    //   from	to	target	type
    //   8	14	63	finally
    //   18	25	63	finally
    //   25	49	63	finally
  }
  
  /* Error */
  public final void k(v paramv)
  {
    // Byte code:
    //   0: invokestatic 26	android/os/Parcel:obtain	()Landroid/os/Parcel;
    //   3: astore_2
    //   4: invokestatic 26	android/os/Parcel:obtain	()Landroid/os/Parcel;
    //   7: astore_3
    //   8: aload_2
    //   9: ldc 28
    //   11: invokevirtual 32	android/os/Parcel:writeInterfaceToken	(Ljava/lang/String;)V
    //   14: aload_1
    //   15: ifnull +43 -> 58
    //   18: aload_1
    //   19: invokeinterface 38 1 0
    //   24: astore_1
    //   25: aload_2
    //   26: aload_1
    //   27: invokevirtual 41	android/os/Parcel:writeStrongBinder	(Landroid/os/IBinder;)V
    //   30: aload_0
    //   31: getfield 18	com/google/android/gms/wearable/internal/x$a$a:tD	Landroid/os/IBinder;
    //   34: bipush 49
    //   36: aload_2
    //   37: aload_3
    //   38: iconst_0
    //   39: invokeinterface 47 5 0
    //   44: pop
    //   45: aload_3
    //   46: invokevirtual 50	android/os/Parcel:readException	()V
    //   49: aload_3
    //   50: invokevirtual 53	android/os/Parcel:recycle	()V
    //   53: aload_2
    //   54: invokevirtual 53	android/os/Parcel:recycle	()V
    //   57: return
    //   58: aconst_null
    //   59: astore_1
    //   60: goto -35 -> 25
    //   63: astore_1
    //   64: aload_3
    //   65: invokevirtual 53	android/os/Parcel:recycle	()V
    //   68: aload_2
    //   69: invokevirtual 53	android/os/Parcel:recycle	()V
    //   72: aload_1
    //   73: athrow
    // Local variable table:
    //   start	length	slot	name	signature
    //   0	74	0	this	a
    //   0	74	1	paramv	v
    //   3	66	2	localParcel1	android.os.Parcel
    //   7	58	3	localParcel2	android.os.Parcel
    // Exception table:
    //   from	to	target	type
    //   8	14	63	finally
    //   18	25	63	finally
    //   25	49	63	finally
  }
  
  /* Error */
  public final void l(v paramv)
  {
    // Byte code:
    //   0: invokestatic 26	android/os/Parcel:obtain	()Landroid/os/Parcel;
    //   3: astore_2
    //   4: invokestatic 26	android/os/Parcel:obtain	()Landroid/os/Parcel;
    //   7: astore_3
    //   8: aload_2
    //   9: ldc 28
    //   11: invokevirtual 32	android/os/Parcel:writeInterfaceToken	(Ljava/lang/String;)V
    //   14: aload_1
    //   15: ifnull +43 -> 58
    //   18: aload_1
    //   19: invokeinterface 38 1 0
    //   24: astore_1
    //   25: aload_2
    //   26: aload_1
    //   27: invokevirtual 41	android/os/Parcel:writeStrongBinder	(Landroid/os/IBinder;)V
    //   30: aload_0
    //   31: getfield 18	com/google/android/gms/wearable/internal/x$a$a:tD	Landroid/os/IBinder;
    //   34: bipush 51
    //   36: aload_2
    //   37: aload_3
    //   38: iconst_0
    //   39: invokeinterface 47 5 0
    //   44: pop
    //   45: aload_3
    //   46: invokevirtual 50	android/os/Parcel:readException	()V
    //   49: aload_3
    //   50: invokevirtual 53	android/os/Parcel:recycle	()V
    //   53: aload_2
    //   54: invokevirtual 53	android/os/Parcel:recycle	()V
    //   57: return
    //   58: aconst_null
    //   59: astore_1
    //   60: goto -35 -> 25
    //   63: astore_1
    //   64: aload_3
    //   65: invokevirtual 53	android/os/Parcel:recycle	()V
    //   68: aload_2
    //   69: invokevirtual 53	android/os/Parcel:recycle	()V
    //   72: aload_1
    //   73: athrow
    // Local variable table:
    //   start	length	slot	name	signature
    //   0	74	0	this	a
    //   0	74	1	paramv	v
    //   3	66	2	localParcel1	android.os.Parcel
    //   7	58	3	localParcel2	android.os.Parcel
    // Exception table:
    //   from	to	target	type
    //   8	14	63	finally
    //   18	25	63	finally
    //   25	49	63	finally
  }
  
  /* Error */
  public final void m(v paramv)
  {
    // Byte code:
    //   0: invokestatic 26	android/os/Parcel:obtain	()Landroid/os/Parcel;
    //   3: astore_2
    //   4: invokestatic 26	android/os/Parcel:obtain	()Landroid/os/Parcel;
    //   7: astore_3
    //   8: aload_2
    //   9: ldc 28
    //   11: invokevirtual 32	android/os/Parcel:writeInterfaceToken	(Ljava/lang/String;)V
    //   14: aload_1
    //   15: ifnull +43 -> 58
    //   18: aload_1
    //   19: invokeinterface 38 1 0
    //   24: astore_1
    //   25: aload_2
    //   26: aload_1
    //   27: invokevirtual 41	android/os/Parcel:writeStrongBinder	(Landroid/os/IBinder;)V
    //   30: aload_0
    //   31: getfield 18	com/google/android/gms/wearable/internal/x$a$a:tD	Landroid/os/IBinder;
    //   34: bipush 52
    //   36: aload_2
    //   37: aload_3
    //   38: iconst_0
    //   39: invokeinterface 47 5 0
    //   44: pop
    //   45: aload_3
    //   46: invokevirtual 50	android/os/Parcel:readException	()V
    //   49: aload_3
    //   50: invokevirtual 53	android/os/Parcel:recycle	()V
    //   53: aload_2
    //   54: invokevirtual 53	android/os/Parcel:recycle	()V
    //   57: return
    //   58: aconst_null
    //   59: astore_1
    //   60: goto -35 -> 25
    //   63: astore_1
    //   64: aload_3
    //   65: invokevirtual 53	android/os/Parcel:recycle	()V
    //   68: aload_2
    //   69: invokevirtual 53	android/os/Parcel:recycle	()V
    //   72: aload_1
    //   73: athrow
    // Local variable table:
    //   start	length	slot	name	signature
    //   0	74	0	this	a
    //   0	74	1	paramv	v
    //   3	66	2	localParcel1	android.os.Parcel
    //   7	58	3	localParcel2	android.os.Parcel
    // Exception table:
    //   from	to	target	type
    //   8	14	63	finally
    //   18	25	63	finally
    //   25	49	63	finally
  }
  
  /* Error */
  public final void n(v paramv)
  {
    // Byte code:
    //   0: invokestatic 26	android/os/Parcel:obtain	()Landroid/os/Parcel;
    //   3: astore_2
    //   4: invokestatic 26	android/os/Parcel:obtain	()Landroid/os/Parcel;
    //   7: astore_3
    //   8: aload_2
    //   9: ldc 28
    //   11: invokevirtual 32	android/os/Parcel:writeInterfaceToken	(Ljava/lang/String;)V
    //   14: aload_1
    //   15: ifnull +42 -> 57
    //   18: aload_1
    //   19: invokeinterface 38 1 0
    //   24: astore_1
    //   25: aload_2
    //   26: aload_1
    //   27: invokevirtual 41	android/os/Parcel:writeStrongBinder	(Landroid/os/IBinder;)V
    //   30: aload_0
    //   31: getfield 18	com/google/android/gms/wearable/internal/x$a$a:tD	Landroid/os/IBinder;
    //   34: iconst_3
    //   35: aload_2
    //   36: aload_3
    //   37: iconst_0
    //   38: invokeinterface 47 5 0
    //   43: pop
    //   44: aload_3
    //   45: invokevirtual 50	android/os/Parcel:readException	()V
    //   48: aload_3
    //   49: invokevirtual 53	android/os/Parcel:recycle	()V
    //   52: aload_2
    //   53: invokevirtual 53	android/os/Parcel:recycle	()V
    //   56: return
    //   57: aconst_null
    //   58: astore_1
    //   59: goto -34 -> 25
    //   62: astore_1
    //   63: aload_3
    //   64: invokevirtual 53	android/os/Parcel:recycle	()V
    //   67: aload_2
    //   68: invokevirtual 53	android/os/Parcel:recycle	()V
    //   71: aload_1
    //   72: athrow
    // Local variable table:
    //   start	length	slot	name	signature
    //   0	73	0	this	a
    //   0	73	1	paramv	v
    //   3	65	2	localParcel1	android.os.Parcel
    //   7	57	3	localParcel2	android.os.Parcel
    // Exception table:
    //   from	to	target	type
    //   8	14	62	finally
    //   18	25	62	finally
    //   25	48	62	finally
  }
  
  /* Error */
  public final void o(v paramv)
  {
    // Byte code:
    //   0: invokestatic 26	android/os/Parcel:obtain	()Landroid/os/Parcel;
    //   3: astore_2
    //   4: invokestatic 26	android/os/Parcel:obtain	()Landroid/os/Parcel;
    //   7: astore_3
    //   8: aload_2
    //   9: ldc 28
    //   11: invokevirtual 32	android/os/Parcel:writeInterfaceToken	(Ljava/lang/String;)V
    //   14: aload_1
    //   15: ifnull +42 -> 57
    //   18: aload_1
    //   19: invokeinterface 38 1 0
    //   24: astore_1
    //   25: aload_2
    //   26: aload_1
    //   27: invokevirtual 41	android/os/Parcel:writeStrongBinder	(Landroid/os/IBinder;)V
    //   30: aload_0
    //   31: getfield 18	com/google/android/gms/wearable/internal/x$a$a:tD	Landroid/os/IBinder;
    //   34: iconst_4
    //   35: aload_2
    //   36: aload_3
    //   37: iconst_0
    //   38: invokeinterface 47 5 0
    //   43: pop
    //   44: aload_3
    //   45: invokevirtual 50	android/os/Parcel:readException	()V
    //   48: aload_3
    //   49: invokevirtual 53	android/os/Parcel:recycle	()V
    //   52: aload_2
    //   53: invokevirtual 53	android/os/Parcel:recycle	()V
    //   56: return
    //   57: aconst_null
    //   58: astore_1
    //   59: goto -34 -> 25
    //   62: astore_1
    //   63: aload_3
    //   64: invokevirtual 53	android/os/Parcel:recycle	()V
    //   67: aload_2
    //   68: invokevirtual 53	android/os/Parcel:recycle	()V
    //   71: aload_1
    //   72: athrow
    // Local variable table:
    //   start	length	slot	name	signature
    //   0	73	0	this	a
    //   0	73	1	paramv	v
    //   3	65	2	localParcel1	android.os.Parcel
    //   7	57	3	localParcel2	android.os.Parcel
    // Exception table:
    //   from	to	target	type
    //   8	14	62	finally
    //   18	25	62	finally
    //   25	48	62	finally
  }
  
  /* Error */
  public final void p(v paramv)
  {
    // Byte code:
    //   0: invokestatic 26	android/os/Parcel:obtain	()Landroid/os/Parcel;
    //   3: astore_2
    //   4: invokestatic 26	android/os/Parcel:obtain	()Landroid/os/Parcel;
    //   7: astore_3
    //   8: aload_2
    //   9: ldc 28
    //   11: invokevirtual 32	android/os/Parcel:writeInterfaceToken	(Ljava/lang/String;)V
    //   14: aload_1
    //   15: ifnull +42 -> 57
    //   18: aload_1
    //   19: invokeinterface 38 1 0
    //   24: astore_1
    //   25: aload_2
    //   26: aload_1
    //   27: invokevirtual 41	android/os/Parcel:writeStrongBinder	(Landroid/os/IBinder;)V
    //   30: aload_0
    //   31: getfield 18	com/google/android/gms/wearable/internal/x$a$a:tD	Landroid/os/IBinder;
    //   34: iconst_5
    //   35: aload_2
    //   36: aload_3
    //   37: iconst_0
    //   38: invokeinterface 47 5 0
    //   43: pop
    //   44: aload_3
    //   45: invokevirtual 50	android/os/Parcel:readException	()V
    //   48: aload_3
    //   49: invokevirtual 53	android/os/Parcel:recycle	()V
    //   52: aload_2
    //   53: invokevirtual 53	android/os/Parcel:recycle	()V
    //   56: return
    //   57: aconst_null
    //   58: astore_1
    //   59: goto -34 -> 25
    //   62: astore_1
    //   63: aload_3
    //   64: invokevirtual 53	android/os/Parcel:recycle	()V
    //   67: aload_2
    //   68: invokevirtual 53	android/os/Parcel:recycle	()V
    //   71: aload_1
    //   72: athrow
    // Local variable table:
    //   start	length	slot	name	signature
    //   0	73	0	this	a
    //   0	73	1	paramv	v
    //   3	65	2	localParcel1	android.os.Parcel
    //   7	57	3	localParcel2	android.os.Parcel
    // Exception table:
    //   from	to	target	type
    //   8	14	62	finally
    //   18	25	62	finally
    //   25	48	62	finally
  }
}

/* Location:
 * Qualified Name:     com.google.android.gms.wearable.internal.x.a.a
 * Java Class Version: 6 (50.0)
 * JD-Core Version:    0.7.1
 */